Workbook

Sheet Capacidades CIBER
A1: Plataforma | B1: Capacidad | C1: Rol | D1: % | E1: Razón
A2: 360 Brand Guardian | B2: Ciberfraude, Abuso Digital y Protección de Marca | C2: PRIMARIA | D2: 0.65 | E2: Protege la marca frente a suplantación de dominios y perfiles: abuso digital puro, Salida prevista Noviembre
A3: 360 Brand Guardian | B3: Vulnerabilidades y Superficie de Ataque | C3: SECUNDARIA | D3: 0.35 | E3: Monitorea dominios y superficie externa expuesta, que es medición de exposición de ataque.
A4: Akamai WAF | B4: Redes, Perímetro y Conectividad Segura | C4: TERCIARIA | D4: 0.2 | E4: Es el control perimetral del tráfico entrante hacia las aplicaciones expuestas.
A5: Akamai WAF | B5: Seguridad de Aplicaciones y DevSecOps | C5: PRIMARIA | D5: 0.5 | E5: Protege aplicaciones y APIs en ejecución, que es seguridad de aplicaciones en runtime.
A6: Akamai WAF | B6: Detección, Contención y Respuesta SOC | C6: SECUNDARIA | D6: 0.3 | E6: Ejecuta una deteccion y bloqueos por medio de politicas de seguridad.
A7: Alarmnet | B7: Seguridad Física Integral | C7: PRIMARIA | D7: 0.85 | E7: Recepción de señales de alarma de agencias. Comparte la línea TEC0152 con Softguard y SG-System III.
A8: Alarmnet | B8: Detección, Contención y Respuesta SOC | C8: SECUNDARIA | D8: 0.15 | E8: Aporta alertas validadas y trazabilidad de eventos físicos para su escalamiento, coordinación y respuesta; su contribución es complementaria a la seguridad física.
A9: AntiDDoS Radware | B9: Redes, Perímetro y Conectividad Segura | C9: PRIMARIA | D9: 0.8 | E9: Protege la disponibilidad del canal frente a ataques volumétricos; no aporta a otra capacidad.
A10: AntiDDoS Radware | B10: Detección, Contención y Respuesta SOC | C10: SECUNDARIA | D10: 0.2 | E10: Se tiene casos de uso que valida el SOC, correlaciona eventos de trafico de red y gestiona la remediacion
A11: Atalla | B11: Criptografía y Confianza Digital | C11: PRIMARIA | D11: 0.6 | E11: Custodia el material criptográfico del banco y ejecuta las operaciones de llave.
A12: Atalla | B12: Ciberfraude, Abuso Digital y Protección de Marca | C12: SECUNDARIA | D12: 0.4 | E12: Sostiene el cifrado de PIN de tarjetas,ATMs y cheques, sin el cual no opera la cadena de pagos.
A13: Biocatch | B13: Ciberfraude, Abuso Digital y Protección de Marca | C13: PRIMARIA | D13: 0.85 | E13: Detectar fraude por comportamiento (físico y cognitivo) y apropiación de cuentas (ATO) en canales digitales.
... A103: Trellix | B103: Privacidad y Protección de Datos | C103: SECUNDARIA | D103: 0.2 | E103: Conexion cifrada entre el agente instalado en el ATM y la consola

Sheet Subcategorias NIST
A1: Plataforma | B1: Subcategoría | C1: Descripción. | D1: Categoría | E1: Función | F1: % | G1: Razón
A2: 360 Brand Guardian | B2: ID.RA-03 | C2: =VLOOKUP(B2,'1_Subcategorias'!E:F,2,0) -> Amenazas internas y externas a la organización identificadas y registradas | D2: =VLOOKUP(B2,'1_Subcategorias'!E:H,4,0) -> ID.RA - Evaluación de riesgo | E2: Identificar | F2: 0.35 | G2: Identifica y registra amenazas externas de suplantación de marca y dominio: es el resultado que la plataforma compra.
A3: 360 Brand Guardian | B3: DE.CM-09 | C3: =VLOOKUP(B3,'1_Subcategorias'!E:F,2,0) -> Hardware y software de cómputo, entornos de ejecución y sus datos monitoreados para hallar eventos adversos | D3: =VLOOKUP(B3,'1_Subcategorias'!E:H,4,0) -> DE.CM - Monitoreo continuo | E3: Detectar | F3: 0.25 | G3: Monitorea de forma continua la exposición digital de la marca en Internet.
A4: 360 Brand Guardian | B4: DE.AE-02 | C4: =VLOOKUP(B4,'1_Subcategorias'!E:F,2,0) -> Eventos potencialmente adversos analizados para comprender mejor la actividad asociada | D4: =VLOOKUP(B4,'1_Subcategorias'!E:H,4,0) -> DE.AE - Análisis de eventos adversos | E4: Detectar | F4: 0.25 | G4: Analiza los hallazgos para determinar si constituyen actividad adversa real.
A5: 360 Brand Guardian | B5: RS.MI-01 | C5: =VLOOKUP(B5,'1_Subcategorias'!E:F,2,0) -> Los incidentes son contenidos | D5: =VLOOKUP(B5,'1_Subcategorias'!E:H,4,0) -> RS.MI - Mitigación del incidente | E5: Responder | F5: 0.15 | G5: El takedown de un dominio suplantador es una acción de mitigación posterior a un evento confirmado.
A6: Akamai WAF | B6: PR.IR-01 | C6: =VLOOKUP(B6,'1_Subcategorias'!E:F,2,0) -> Redes y entornos protegidos de acceso y uso lógico no autorizado | D6: =VLOOKUP(B6,'1_Subcategorias'!E:H,4,0) -> PR.IR - Resiliencia de la infraestructura tecnológica | E6: Proteger | F6: 0.5 | G6: Protege las aplicaciones y APIs expuestas frente a acceso y uso no autorizado.
A7: Akamai WAF | B7: DE.CM-01 | C7: =VLOOKUP(B7,'1_Subcategorias'!E:F,2,0) -> Redes y servicios de red monitoreados para hallar eventos potencialmente adversos | D7: =VLOOKUP(B7,'1_Subcategorias'!E:H,4,0) -> DE.CM - Monitoreo continuo | E7: Detectar | F7: 0.3 | G7: Genera telemetría continua de capa 7 sobre el tráfico entrante.
A8: Akamai WAF | B8: DE.AE-02 | C8: =VLOOKUP(B8,'1_Subcategorias'!E:F,2,0) -> Eventos potencialmente adversos analizados para comprender mejor la actividad asociada | D8: =VLOOKUP(B8,'1_Subcategorias'!E:H,4,0) -> DE.AE - Análisis de eventos adversos | E8: Detectar | F8: 0.2 | G8: Analiza patrones de petición para distinguir ataque de tráfico legítimo.
A9: Alarmnet | B9: DE.CM-02 | C9: =VLOOKUP(B9,'1_Subcategorias'!E:F,2,0) -> El entorno físico es monitoreado para hallar eventos potencialmente adversos | D9: =VLOOKUP(B9,'1_Subcategorias'!E:H,4,0) -> DE.CM - Monitoreo continuo | E9: Detectar | F9: 0.7 | G9: Recepción y monitoreo continuo de señales del entorno físico de agencias
A10: Alarmnet | B10: PR.PS-04 | C10: =VLOOKUP(B10,'1_Subcategorias'!E:F,2,0) -> Registros de log generados y disponibles para monitoreo continuo | D10: =VLOOKUP(B10,'1_Subcategorias'!E:H,4,0) -> PR.PS - Seguridad de plataforma | E10: Proteger | F10: 0.1 | G10: Mantiene disponible la trazabilidad de las señales y eventos recibidos para seguimiento y consulta operativa.
A11: Alarmnet | B11: RS.MA-02 | C11: =VLOOKUP(B11,'1_Subcategorias'!E:F,2,0) -> Los reportes de incidente son triados y validados | D11: =VLOOKUP(B11,'1_Subcategorias'!E:H,4,0) -> RS.MA - Gestión de incidentes | E11: Responder | F11: 0.1 | G11: Tría y valida los reportes de alarma recibidos.
A12: Alarmnet | B12: RS.CO-02 | C12: =VLOOKUP(B12,'1_Subcategorias'!E:F,2,0) -> Las partes interesadas internas y externas son notificadas de los incidentes | D12: =VLOOKUP(B12,'1_Subcategorias'!E:H,4,0) -> RS.CO - Reporte y comunicación del incidente | E12: Responder | F12: 0.1 | G12: Notifica al centro de monitoreo y a los responsables de seguridad.
A13: AntiDDoS Radware | B13: PR.IR-03 | C13: =VLOOKUP(B13,'1_Subcategorias'!E:F,2,0) -> Mecanismos implementados para lograr los requisitos de resiliencia en situaciones normales y adversas | D13: =VLOOKUP(B13,'1_Subcategorias'!E:H,4,0) -> PR.IR - Resiliencia de la infraestructura tecnológica | E13: Proteger | F13: 0.45 | G13: La mitigación volumétrica es un mecanismo permanente de resiliencia ante situación adversa, no una respuesta a incidente.
... A201: Trellix | B201: PR.DS-02 | C201: =VLOOKUP(B201,'1_Subcategorias'!E:F,2,0) -> Confidencialidad, integridad y disponibilidad del dato en tránsito protegidas | D201: =VLOOKUP(B201,'1_Subcategorias'!E:H,4,0) -> PR.DS - Seguridad de datos | E201: Proteger | F201: 0.15 | G201: Impone el cifrado del canal de comunicación del cajero, protegiendo la transacción y los datos del cliente frente a interceptación en el trayecto.

Sheet TD _ Función
A3: Suma de % | B3: Etiquetas de columna | H3: Suma de % | I3: Etiquetas de columna
A4: Etiquetas de fila | B4: Detectar | C4: Identificar | D4: Proteger | E4: Responder | F4: Total general | H4: Etiquetas de fila | I4: Ciberfraude, Abuso Digital y Protección de Marca | J4: Concientización y Cultura | K4: Correo, Web y Colaboración Segura | L4: Criptografía y Confianza Digital | M4: Detección, Contención y Respuesta SOC | N4: Endpoint, Servidores y Workload | O4: Identidades, Accesos y Privilegios | P4: Privacidad y Protección de Datos | Q4: Redes, Perímetro y Conectividad Segura | R4: Seguridad Cloud | S4: Seguridad de Aplicaciones y DevSecOps | T4: Seguridad Física Integral | U4: Vulnerabilidades y Superficie de Ataque | V4: (en blanco) | W4: Total general
A5: 360 Brand Guardian | B5: 0.5 | C5: 0.35 | E5: 0.15 | F5: 1 | H5: 360 Brand Guardian | I5: 0.65 | U5: 0.35 | W5: 1
A6: Akamai WAF | B6: 0.5 | D6: 0.5 | F6: 1 | H6: Akamai WAF | M6: 0.3 | Q6: 0.2 | S6: 0.5 | W6: 1
A7: Alarmnet | B7: 0.7 | D7: 0.1 | E7: 0.2 | F7: 1 | H7: Alarmnet | M7: 0.15 | T7: 0.85 | W7: 1
A8: AntiDDoS Radware | B8: 0.2 | D8: 0.8 | F8: 1 | H8: AntiDDoS Radware | M8: 0.2 | Q8: 0.8 | W8: 1
A9: Atalla | D9: 1 | F9: 1 | H9: Atalla | I9: 0.4 | L9: 0.6 | W9: 1
A10: Biocatch | B10: 0.85 | D10: 0.15 | F10: 1 | H10: Biocatch | I10: 0.85 | O10: 0.15 | W10: 1
A11: Certificados Digicert | C11: 0.25 | D11: 0.75 | F11: 1 | H11: Certificados Digicert | L11: 0.7 | R11: 0.2 | U11: 0.1 | W11: 1
A12: Cloud Defender for Apps | B12: 0.2 | C12: 0.1 | D12: 0.7 | F12: 1 | H12: Cloud Defender for Apps | K12: 0.4 | P12: 0.4 | R12: 0.2 | W12: 1
A13: Colector de Eventos SOC (NXLog) | B13: 0.4 | D13: 0.6 | F13: 1 | H13: Colector de Eventos SOC (NXLog) | M13: 1 | W13: 1
A14: Compass | B14: 0.45 | D14: 0.55 | F14: 1 | H14: Compass | M14: 0.25 | T14: 0.75 | W14: 1
A15: Coren Web | B15: 0.25 | D15: 0.75 | F15: 1 | H15: Coren Web | O15: 0.4 | T15: 0.6 | W15: 1
A16: Correlacionador de Eventos SOC (SPLUNK) | B16: 0.75 | D16: 0.1 | E16: 0.15 | F16: 1 | H16: Correlacionador de Eventos SOC (SPLUNK) | M16: 1 | W16: 1
A17: Cortex Cloud | B17: 0.2 | C17: 0.35 | D17: 0.45 | F17: 1 | H17: Cortex Cloud | R17: 0.55 | S17: 0.15 | U17: 0.3 | W17: 1
A18: Crowdstrike | B18: 0.5 | D18: 0.2 | E18: 0.3 | F18: 1 | H18: Crowdstrike | M18: 0.3 | N18: 0.55 | O18: 0.05 | U18: 0.1 | W18: 1
A19: Cyberark | B19: 0.15 | D19: 0.75 | E19: 0.1 | F19: 1 | H19: Cyberark | M19: 0.15 | O19: 0.85 | W19: 1
A20: Darktrace | B20: 1 | F20: 1 | H20: Darktrace | M20: 0.75 | Q20: 0.25 | W20: 1
A21: DecisionCLoud | B21: 0.15 | D21: 0.85 | F21: 1 | H21: DecisionCLoud | O21: 0.2 | T21: 0.8 | W21: 1
A22: Deep Security | B22: 0.45 | D22: 0.25 | E22: 0.3 | F22: 1 | H22: Deep Security | N22: 0.5 | Q22: 0.25 | U22: 0.25 | W22: 1
A23: Detect ID | D23: 1 | F23: 1 | H23: Detect ID | O23: 1 | W23: 1
A24: DLS5 | B24: 0.45 | D24: 0.55 | F24: 1 | H24: DLS5 | M24: 0.25 | T24: 0.75 | W24: 1
A25: DynamicsCodes | B25: 0.15 | D25: 0.85 | F25: 1 | H25: DynamicsCodes | M25: 0.1 | O25: 0.3 | T25: 0.6 | W25: 1
A26: Entidad Certificadora INTERNA | C26: 0.15 | D26: 0.85 | F26: 1 | H26: Entidad Certificadora INTERNA | L26: 0.7 | O26: 0.3 | W26: 1
A27: Facephi | D27: 1 | F27: 1 | H27: Facephi | I27: 0.6 | O27: 0.4 | W27: 1
A28: Firemon | C28: 0.4 | D28: 0.6 | F28: 1 | H28: Firemon | Q28: 1 | W28: 1
A29: Forcepoint DLP | B29: 0.2 | D29: 0.65 | E29: 0.15 | F29: 1 | H29: Forcepoint DLP | N29: 0.25 | P29: 0.75 | W29: 1
A30: Gestión Identidades (WSO2) | C30: 0.1 | D30: 0.9 | F30: 1 | H30: Gestión Identidades (WSO2) | O30: 1 | W30: 1
A31: IPS CISCO | B31: 0.45 | D31: 0.45 | E31: 0.1 | F31: 1 | H31: IPS CISCO | M31: 0.4 | Q31: 0.6 | W31: 1
A32: ISE | C32: 0.15 | D32: 0.85 | F32: 1 | H32: ISE | O32: 0.45 | Q32: 0.55 | W32: 1
A33: Keeper Security | D33: 1 | F33: 1 | H33: Keeper Security | O33: 1 | W33: 1
A34: KnowBe4 | C34: 0.2 | D34: 0.8 | F34: 1 | H34: KnowBe4 | J34: 1 | W34: 1
A35: Kriptos | C35: 0.75 | D35: 0.25 | F35: 1 | H35: Kriptos | P35: 1 | W35: 1
A36: MAM Intune | D36: 1 | F36: 1 | H36: MAM Intune | N36: 0.5 | O36: 0.15 | P36: 0.35 | W36: 1
A37: Microsoft 365 Defender / Email & Colaboration Security | B37: 0.55 | D37: 0.3 | E37: 0.15 | F37: 1 | H37: Microsoft 365 Defender / Email & Colaboration Security | K37: 0.65 | M37: 0.15 | P37: 0.2 | W37: 1
A38: Netskope | B38: 0.15 | D38: 0.85 | F38: 1 | H38: Netskope | K38: 0.5 | P38: 0.3 | R38: 0.2 | W38: 1
A39: Octopus | B39: 0.6 | D39: 0.1 | E39: 0.3 | F39: 1 | H39: Octopus | M39: 0.4 | T39: 0.6 | W39: 1
A40: Optimizador de Eventos SOC (ORXLog) | B40: 0.65 | D40: 0.35 | F40: 1 | H40: Optimizador de Eventos SOC (ORXLog) | M40: 1 | W40: 1
A41: Proofpoint | B41: 0.55 | D41: 0.3 | E41: 0.15 | F41: 1 | H41: Proofpoint | K41: 0.6 | P41: 0.4 | W41: 1
A42: ProtegeGX | B42: 0.2 | D42: 0.8 | F42: 1 | H42: ProtegeGX | O42: 0.15 | T42: 0.85 | W42: 1
A43: Security Scorecard | C43: 1 | F43: 1 | H43: Security Scorecard | U43: 1 | W43: 1
A44: Seguridad Perimetral Firewall Nube | B44: 0.25 | D44: 0.65 | E44: 0.1 | F44: 1 | H44: Seguridad Perimetral Firewall Nube | Q44: 0.7 | R44: 0.3 | W44: 1
A45: Seguridad Perimetral Firewall Onpremise | B45: 0.25 | D45: 0.65 | E45: 0.1 | F45: 1 | H45: Seguridad Perimetral Firewall Onpremise | Q45: 1 | W45: 1
A46: Sentinel Prevention | B46: 1 | F46: 1 | H46: Sentinel Prevention | I46: 1 | W46: 1
A47: SG-System III Console | B47: 0.4 | D47: 0.4 | E47: 0.2 | F47: 1 | H47: SG-System III Console | M47: 0.15 | T47: 0.85 | W47: 1
A48: SNOW (SIR & TIP / Certificados) | C48: 0.3 | E48: 0.7 | F48: 1 | H48: SNOW (SIR & TIP / Certificados) | L48: 0.25 | M48: 0.75 | W48: 1
A49: Snyk | C49: 0.7 | D49: 0.3 | F49: 1 | H49: Snyk | M49: 0.3 | S49: 0.55 | U49: 0.15 | W49: 1
A50: Softguard | B50: 0.55 | D50: 0.1 | E50: 0.35 | F50: 1 | H50: Softguard | M50: 0.2 | T50: 0.8 | W50: 1
A51: Spartan | B51: 1 | F51: 1 | H51: Spartan | I51: 1 | W51: 1
A52: Stackhawk | C52: 0.6 | D52: 0.4 | F52: 1 | H52: Stackhawk | M52: 0.15 | S52: 0.5 | U52: 0.35 | W52: 1
A53: Stealthwatch | B53: 0.9 | E53: 0.1 | F53: 1 | H53: Stealthwatch | M53: 0.75 | Q53: 0.25 | W53: 1
A54: Tenable | B54: 0.2 | C54: 0.8 | F54: 1 | H54: Tenable | U54: 1 | W54: 1
A55: Trellix | B55: 0.3 | D55: 0.7 | F55: 1 | H55: Trellix | L55: 0.15 | N55: 0.6 | S55: 0.15 | T55: 0.1 | W55: 1
A56: Total general | B56: 16.05 | C56: 6.2 | D56: 25.15 | E56: 3.6 | F56: 51 | H56: (en blanco)
H57: Total general | I57: 4.5 | J57: 1 | K57: 2.15 | L57: 2.4 | M57: 8.7 | N57: 2.4 | O57: 6.4 | P57: 3.4 | Q57: 5.6 | R57: 1.45 | S57: 1.85 | T57: 7.55 | U57: 3.6 | W57: 51

Sheet 1_Subcategorias
A1: CATÁLOGO COMPLETO NIST CSF 2.0 — 106 SUBCATEGORÍAS
A2: 6 funciones · 22 categorías · 106 subcategorías. Texto oficial en inglés (NIST.CSWP.29, feb-2024) y glosa en español. La columna «En uso» marca las que aplica el portafolio de la Gerencia de Plataformas.
A4: Función | B4: Código función | C4: Categoría | D4: Nombre de la categoría | E4: Subcategoría | F4: Descripción / glosa (es) | G4: Texto oficial NIST CSF 2.0 (en) | H4: Cat - Nomb | I4: En uso en el portafolio
A5: Gobernar | B5: GV | C5: GV.OC | D5: Contexto organizacional | E5: GV.OC-01 | F5: La misión organizacional se comprende e informa la gestión del riesgo de ciberseguridad | G5: The organizational mission is understood and informs cybersecurity risk management | H5: =_xlfn.CONCAT(C5," - ",D5) -> GV.OC - Contexto organizacional
A6: Gobernar | B6: GV | C6: GV.OC | D6: Contexto organizacional | E6: GV.OC-02 | F6: Se comprenden las partes interesadas internas y externas y sus necesidades y expectativas sobre la gestión del riesgo | G6: Internal and external stakeholders are understood, and their needs and expectations regarding cybersecurity risk management are understood and considered | H6: =_xlfn.CONCAT(C6," - ",D6) -> GV.OC - Contexto organizacional
A7: Gobernar | B7: GV | C7: GV.OC | D7: Contexto organizacional | E7: GV.OC-03 | F7: Los requisitos legales, regulatorios y contractuales de ciberseguridad, incluidas las obligaciones de privacidad, se comprenden y gestionan | G7: Legal, regulatory, and contractual requirements regarding cybersecurity — including privacy and civil liberties obligations — are understood and managed | H7: =_xlfn.CONCAT(C7," - ",D7) -> GV.OC - Contexto organizacional
A8: Gobernar | B8: GV | C8: GV.OC | D8: Contexto organizacional | E8: GV.OC-04 | F8: Los objetivos, capacidades y servicios críticos que los terceros esperan de la organización se comprenden y comunican | G8: Critical objectives, capabilities, and services that external stakeholders depend on or expect from the organization are understood and communicated | H8: =_xlfn.CONCAT(C8," - ",D8) -> GV.OC - Contexto organizacional
A9: Gobernar | B9: GV | C9: GV.OC | D9: Contexto organizacional | E9: GV.OC-05 | F9: Los resultados, capacidades y servicios de los que depende la organización se comprenden y comunican | G9: Outcomes, capabilities, and services that the organization depends on are understood and communicated | H9: =_xlfn.CONCAT(C9," - ",D9) -> GV.OC - Contexto organizacional
A10: Gobernar | B10: GV | C10: GV.RM | D10: Estrategia de gestión de riesgo | E10: GV.RM-01 | F10: Los objetivos de gestión del riesgo se establecen y son acordados por las partes interesadas | G10: Risk management objectives are established and agreed to by organizational stakeholders | H10: =_xlfn.CONCAT(C10," - ",D10) -> GV.RM - Estrategia de gestión de riesgo
A11: Gobernar | B11: GV | C11: GV.RM | D11: Estrategia de gestión de riesgo | E11: GV.RM-02 | F11: Las declaraciones de apetito y tolerancia al riesgo se establecen, comunican y mantienen | G11: Risk appetite and risk tolerance statements are established, communicated, and maintained | H11: =_xlfn.CONCAT(C11," - ",D11) -> GV.RM - Estrategia de gestión de riesgo
A12: Gobernar | B12: GV | C12: GV.RM | D12: Estrategia de gestión de riesgo | E12: GV.RM-03 | F12: Las actividades y resultados de gestión del riesgo de ciber se incluyen en la gestión de riesgo empresarial | G12: Cybersecurity risk management activities and outcomes are included in enterprise risk management processes | H12: =_xlfn.CONCAT(C12," - ",D12) -> GV.RM - Estrategia de gestión de riesgo
A13: Gobernar | B13: GV | C13: GV.RM | D13: Estrategia de gestión de riesgo | E13: GV.RM-04 | F13: Se establece y comunica la dirección estratégica con las opciones de respuesta al riesgo | G13: Strategic direction that describes appropriate risk response options is established and communicated | H13: =_xlfn.CONCAT(C13," - ",D13) -> GV.RM - Estrategia de gestión de riesgo
A14: Gobernar | B14: GV | C14: GV.RM | D14: Estrategia de gestión de riesgo | E14: GV.RM-05 | F14: Se establecen líneas de comunicación sobre riesgos de ciber, incluidos los de proveedores y terceros | G14: Lines of communication across the organization are established for cybersecurity risks, including risks from suppliers and other third parties | H14: =_xlfn.CONCAT(C14," - ",D14) -> GV.RM - Estrategia de gestión de riesgo
A15: Gobernar | B15: GV | C15: GV.RM | D15: Estrategia de gestión de riesgo | E15: GV.RM-06 | F15: Se establece y comunica un método estandarizado para calcular, documentar, categorizar y priorizar riesgos | G15: A standardized method for calculating, documenting, categorizing, and prioritizing cybersecurity risks is established and communicated | H15: =_xlfn.CONCAT(C15," - ",D15) -> GV.RM - Estrategia de gestión de riesgo
A16: Gobernar | B16: GV | C16: GV.RM | D16: Estrategia de gestión de riesgo | E16: GV.RM-07 | F16: Las oportunidades estratégicas (riesgos positivos) se caracterizan e incluyen en la discusión de riesgo | G16: Strategic opportunities (i.e., positive risks) are characterized and are included in organizational cybersecurity risk discussions | H16: =_xlfn.CONCAT(C16," - ",D16) -> GV.RM - Estrategia de gestión de riesgo
... A35: Gobernar | B35: GV | C35: GV.SC | D35: Gestión del riesgo de la cadena de suministro | E35: GV.SC-10 | F35: Los planes incluyen previsiones para las actividades posteriores al término de la relación o del acuerdo de servicio | G35: Cybersecurity supply chain risk management plans include provisions for activities that occur after the conclusion of a partnership or service agreement | H35: =_xlfn.CONCAT(C35," - ",D35) -> GV.SC - Gestión del riesgo de la cadena de suministro
A36: Identificar | B36: ID | C36: ID.AM | D36: Gestión de activos | E36: ID.AM-01 | F36: Inventarios de hardware administrado son mantenidos | G36: Inventories of hardware managed by the organization are maintained | H36: =_xlfn.CONCAT(C36," - ",D36) -> ID.AM - Gestión de activos | I36: SÍ
A37: Identificar | B37: ID | C37: ID.AM | D37: Gestión de activos | E37: ID.AM-02 | F37: Inventarios de software, servicios y sistemas son mantenidos | G37: Inventories of software, services, and systems managed by the organization are maintained | H37: =_xlfn.CONCAT(C37," - ",D37) -> ID.AM - Gestión de activos | I37: SÍ
A38: Identificar | B38: ID | C38: ID.AM | D38: Gestión de activos | E38: ID.AM-03 | F38: Representaciones de la comunicación de red autorizada y flujos de datos internos y externos mantenidas | G38: Representations of the organization’s authorized network communication and internal and external network data flows are maintained | H38: =_xlfn.CONCAT(C38," - ",D38) -> ID.AM - Gestión de activos | I38: SÍ
A39: Identificar | B39: ID | C39: ID.AM | D39: Gestión de activos | E39: ID.AM-04 | F39: Inventarios de servicios provistos por proveedores son mantenidos | G39: Inventories of services provided by suppliers are maintained | H39: =_xlfn.CONCAT(C39," - ",D39) -> ID.AM - Gestión de activos
A40: Identificar | B40: ID | C40: ID.AM | D40: Gestión de activos | E40: ID.AM-05 | F40: Activos priorizados por clasificación, criticidad, recursos e impacto en la misión | G40: Assets are prioritized based on classification, criticality, resources, and impact on the mission | H40: =_xlfn.CONCAT(C40," - ",D40) -> ID.AM - Gestión de activos | I40: SÍ
A41: Identificar | B41: ID | C41: ID.AM | D41: Gestión de activos | E41: ID.AM-07 | F41: Inventarios de datos y metadatos de tipos designados mantenidos | G41: Inventories of data and corresponding metadata for designated data types are maintained | H41: =_xlfn.CONCAT(C41," - ",D41) -> ID.AM - Gestión de activos | I41: SÍ
A42: Identificar | B42: ID | C42: ID.AM | D42: Gestión de activos | E42: ID.AM-08 | F42: Sistemas, hardware, software, servicios y datos gestionados en todo su ciclo de vida | G42: Systems, hardware, software, services, and data are managed throughout their life cycles | H42: =_xlfn.CONCAT(C42," - ",D42) -> ID.AM - Gestión de activos | I42: SÍ
A43: Identificar | B43: ID | C43: ID.RA | D43: Evaluación de riesgo | E43: ID.RA-01 | F43: Vulnerabilidades en activos identificadas, validadas y registradas | G43: Vulnerabilities in assets are identified, validated, and recorded | H43: =_xlfn.CONCAT(C43," - ",D43) -> ID.RA - Evaluación de riesgo | I43: SÍ
A44: Identificar | B44: ID | C44: ID.RA | D44: Evaluación de riesgo | E44: ID.RA-02 | F44: Inteligencia de amenazas recibida de foros y fuentes de intercambio | G44: Cyber threat intelligence is received from information sharing forums and sources | H44: =_xlfn.CONCAT(C44," - ",D44) -> ID.RA - Evaluación de riesgo | I44: SÍ
A45: Identificar | B45: ID | C45: ID.RA | D45: Evaluación de riesgo | E45: ID.RA-03 | F45: Amenazas internas y externas a la organización identificadas y registradas | G45: Internal and external threats to the organization are identified and recorded | H45: =_xlfn.CONCAT(C45," - ",D45) -> ID.RA - Evaluación de riesgo | I45: SÍ
A46: Identificar | B46: ID | C46: ID.RA | D46: Evaluación de riesgo | E46: ID.RA-04 | F46: Impactos potenciales y probabilidades de que las amenazas exploten vulnerabilidades identificados y registrados | G46: Potential impacts and likelihoods of threats exploiting vulnerabilities are identified and recorded | H46: =_xlfn.CONCAT(C46," - ",D46) -> ID.RA - Evaluación de riesgo
A47: Identificar | B47: ID | C47: ID.RA | D47: Evaluación de riesgo | E47: ID.RA-05 | F47: Amenazas, vulnerabilidades, probabilidades e impactos usados para entender el riesgo inherente y priorizar la respuesta | G47: Threats, vulnerabilities, likelihoods, and impacts are used to understand inherent risk and inform risk response prioritization | H47: =_xlfn.CONCAT(C47," - ",D47) -> ID.RA - Evaluación de riesgo | I47: SÍ
A48: Identificar | B48: ID | C48: ID.RA | D48: Evaluación de riesgo | E48: ID.RA-06 | F48: Las respuestas al riesgo se eligen, priorizan, planifican, siguen y comunican | G48: Risk responses are chosen, prioritized, planned, tracked, and communicated | H48: =_xlfn.CONCAT(C48," - ",D48) -> ID.RA - Evaluación de riesgo
A49: Identificar | B49: ID | C49: ID.RA | D49: Evaluación de riesgo | E49: ID.RA-07 | F49: Los cambios y excepciones se gestionan, evalúan por impacto de riesgo, registran y siguen | G49: Changes and exceptions are managed, assessed for risk impact, recorded, and tracked | H49: =_xlfn.CONCAT(C49," - ",D49) -> ID.RA - Evaluación de riesgo
A50: Identificar | B50: ID | C50: ID.RA | D50: Evaluación de riesgo | E50: ID.RA-08 | F50: Se establecen procesos para recibir, analizar y responder a divulgaciones de vulnerabilidades | G50: Processes for receiving, analyzing, and responding to vulnerability disclosures are established | H50: =_xlfn.CONCAT(C50," - ",D50) -> ID.RA - Evaluación de riesgo
A51: Identificar | B51: ID | C51: ID.RA | D51: Evaluación de riesgo | E51: ID.RA-09 | F51: La autenticidad e integridad del hardware y software se evalúan antes de su adquisición y uso | G51: The authenticity and integrity of hardware and software are assessed prior to acquisition and use | H51: =_xlfn.CONCAT(C51," - ",D51) -> ID.RA - Evaluación de riesgo
A52: Identificar | B52: ID | C52: ID.RA | D52: Evaluación de riesgo | E52: ID.RA-10 | F52: Los proveedores críticos se evalúan antes de la adquisición | G52: Critical suppliers are assessed prior to acquisition | H52: =_xlfn.CONCAT(C52," - ",D52) -> ID.RA - Evaluación de riesgo
A53: Identificar | B53: ID | C53: ID.IM | D53: Mejora | E53: ID.IM-01 | F53: Mejoras identificadas a partir de evaluaciones | G53: Improvements are identified from evaluations | H53: =_xlfn.CONCAT(C53," - ",D53) -> ID.IM - Mejora | I53: SÍ
A54: Identificar | B54: ID | C54: ID.IM | D54: Mejora | E54: ID.IM-02 | F54: Mejoras identificadas de pruebas y ejercicios de seguridad, incluidos los coordinados con terceros | G54: Improvements are identified from security tests and exercises, including those done in coordination with suppliers and relevant third parties | H54: =_xlfn.CONCAT(C54," - ",D54) -> ID.IM - Mejora | I54: SÍ
A55: Identificar | B55: ID | C55: ID.IM | D55: Mejora | E55: ID.IM-03 | F55: Mejoras identificadas a partir de la ejecución de procesos, procedimientos y actividades operativas | G55: Improvements are identified from execution of operational processes, procedures, and activities | H55: =_xlfn.CONCAT(C55," - ",D55) -> ID.IM - Mejora
A56: Identificar | B56: ID | C56: ID.IM | D56: Mejora | E56: ID.IM-04 | F56: Los planes de respuesta a incidentes y otros planes que afectan la operación se establecen, comunican, mantienen y mejoran | G56: Incident response plans and other cybersecurity plans that affect operations are established, communicated, maintained, and improved | H56: =_xlfn.CONCAT(C56," - ",D56) -> ID.IM - Mejora
A57: Proteger | B57: PR | C57: PR.AA | D57: Identidad, autenticación y control de acceso | E57: PR.AA-01 | F57: Identidades y credenciales de usuarios, servicios y hardware autorizados gestionadas por la organización | G57: Identities and credentials for authorized users, services, and hardware are managed by the organization | H57: =_xlfn.CONCAT(C57," - ",D57) -> PR.AA - Identidad, autenticación y control de acceso | I57: SÍ
A58: Proteger | B58: PR | C58: PR.AA | D58: Identidad, autenticación y control de acceso | E58: PR.AA-02 | F58: Identidades verificadas y vinculadas a credenciales según el contexto de las interacciones | G58: Identities are proofed and bound to credentials based on the context of interactions | H58: =_xlfn.CONCAT(C58," - ",D58) -> PR.AA - Identidad, autenticación y control de acceso | I58: SÍ
A59: Proteger | B59: PR | C59: PR.AA | D59: Identidad, autenticación y control de acceso | E59: PR.AA-03 | F59: Usuarios, servicios y hardware son autenticados | G59: Users, services, and hardware are authenticated | H59: =_xlfn.CONCAT(C59," - ",D59) -> PR.AA - Identidad, autenticación y control de acceso | I59: SÍ
A60: Proteger | B60: PR | C60: PR.AA | D60: Identidad, autenticación y control de acceso | E60: PR.AA-04 | F60: Aserciones de identidad protegidas, transmitidas y verificadas | G60: Identity assertions are protected, conveyed, and verified | H60: =_xlfn.CONCAT(C60," - ",D60) -> PR.AA - Identidad, autenticación y control de acceso | I60: SÍ
A61: Proteger | B61: PR | C61: PR.AA | D61: Identidad, autenticación y control de acceso | E61: PR.AA-05 | F61: Permisos y autorizaciones definidos en política, gestionados, exigidos y revisados, con mínimo privilegio y segregación de funciones | G61: Access permissions, entitlements, and authorizations are defined in a policy, managed, enforced, and reviewed, and incorporate the principles of least privilege and separation of duties | H61: =_xlfn.CONCAT(C61," - ",D61) -> PR.AA - Identidad, autenticación y control de acceso | I61: SÍ
A62: Proteger | B62: PR | C62: PR.AA | D62: Identidad, autenticación y control de acceso | E62: PR.AA-06 | F62: Acceso físico a los activos gestionado, monitoreado y exigido según el riesgo | G62: Physical access to assets is managed, monitored, and enforced commensurate with risk | H62: =_xlfn.CONCAT(C62," - ",D62) -> PR.AA - Identidad, autenticación y control de acceso | I62: SÍ
A63: Proteger | B63: PR | C63: PR.AT | D63: Concientización y formación | E63: PR.AT-01 | F63: El personal recibe concientización y formación general para ejecutar sus tareas considerando los riesgos de ciber | G63: Personnel are provided with awareness and training so that they possess the knowledge and skills to perform general tasks with cybersecurity risks in mind | H63: =_xlfn.CONCAT(C63," - ",D63) -> PR.AT - Concientización y formación | I63: SÍ
A64: Proteger | B64: PR | C64: PR.AT | D64: Concientización y formación | E64: PR.AT-02 | F64: Los roles especializados reciben concientización y formación específica para sus tareas relevantes | G64: Individuals in specialized roles are provided with awareness and training so that they possess the knowledge and skills to perform relevant tasks with cybersecurity risks in mind | H64: =_xlfn.CONCAT(C64," - ",D64) -> PR.AT - Concientización y formación | I64: SÍ
A65: Proteger | B65: PR | C65: PR.DS | D65: Seguridad de datos | E65: PR.DS-01 | F65: Confidencialidad, integridad y disponibilidad del dato en reposo protegidas | G65: The confidentiality, integrity, and availability of data-at-rest are protected | H65: =_xlfn.CONCAT(C65," - ",D65) -> PR.DS - Seguridad de datos | I65: SÍ
A66: Proteger | B66: PR | C66: PR.DS | D66: Seguridad de datos | E66: PR.DS-02 | F66: Confidencialidad, integridad y disponibilidad del dato en tránsito protegidas | G66: The confidentiality, integrity, and availability of data-in-transit are protected | H66: =_xlfn.CONCAT(C66," - ",D66) -> PR.DS - Seguridad de datos | I66: SÍ
A67: Proteger | B67: PR | C67: PR.DS | D67: Seguridad de datos | E67: PR.DS-10 | F67: Confidencialidad, integridad y disponibilidad del dato en uso protegidas | G67: The confidentiality, integrity, and availability of data-in-use are protected | H67: =_xlfn.CONCAT(C67," - ",D67) -> PR.DS - Seguridad de datos | I67: SÍ
A68: Proteger | B68: PR | C68: PR.DS | D68: Seguridad de datos | E68: PR.DS-11 | F68: Los respaldos de datos se crean, protegen, mantienen y prueban | G68: Backups of data are created, protected, maintained, and tested | H68: =_xlfn.CONCAT(C68," - ",D68) -> PR.DS - Seguridad de datos
A69: Proteger | B69: PR | C69: PR.PS | D69: Seguridad de plataforma | E69: PR.PS-01 | F69: Prácticas de gestión de configuración establecidas y aplicadas | G69: Configuration management practices are established and applied | H69: =_xlfn.CONCAT(C69," - ",D69) -> PR.PS - Seguridad de plataforma | I69: SÍ
A70: Proteger | B70: PR | C70: PR.PS | D70: Seguridad de plataforma | E70: PR.PS-02 | F70: Software mantenido, reemplazado y retirado según el riesgo | G70: Software is maintained, replaced, and removed commensurate with risk | H70: =_xlfn.CONCAT(C70," - ",D70) -> PR.PS - Seguridad de plataforma
A71: Proteger | B71: PR | C71: PR.PS | D71: Seguridad de plataforma | E71: PR.PS-03 | F71: Hardware mantenido, reemplazado y retirado según el riesgo | G71: Hardware is maintained, replaced, and removed commensurate with risk | H71: =_xlfn.CONCAT(C71," - ",D71) -> PR.PS - Seguridad de plataforma | I71: SÍ
A72: Proteger | B72: PR | C72: PR.PS | D72: Seguridad de plataforma | E72: PR.PS-04 | F72: Registros de log generados y disponibles para monitoreo continuo | G72: Log records are generated and made available for continuous monitoring | H72: =_xlfn.CONCAT(C72," - ",D72) -> PR.PS - Seguridad de plataforma | I72: SÍ
A73: Proteger | B73: PR | C73: PR.PS | D73: Seguridad de plataforma | E73: PR.PS-05 | F73: Instalación y ejecución de software no autorizado son prevenidas | G73: Installation and execution of unauthorized software are prevented | H73: =_xlfn.CONCAT(C73," - ",D73) -> PR.PS - Seguridad de plataforma | I73: SÍ
A74: Proteger | B74: PR | C74: PR.PS | D74: Seguridad de plataforma | E74: PR.PS-06 | F74: Prácticas de desarrollo seguro integradas y su desempeño monitoreado en todo el ciclo de vida del software | G74: Secure software development practices are integrated, and their performance is monitored throughout the software development life cycle | H74: =_xlfn.CONCAT(C74," - ",D74) -> PR.PS - Seguridad de plataforma | I74: SÍ
A75: Proteger | B75: PR | C75: PR.IR | D75: Resiliencia de la infraestructura tecnológica | E75: PR.IR-01 | F75: Redes y entornos protegidos de acceso y uso lógico no autorizado | G75: Networks and environments are protected from unauthorized logical access and usage | H75: =_xlfn.CONCAT(C75," - ",D75) -> PR.IR - Resiliencia de la infraestructura tecnológica | I75: SÍ
A76: Proteger | B76: PR | C76: PR.IR | D76: Resiliencia de la infraestructura tecnológica | E76: PR.IR-02 | F76: Los activos tecnológicos de la organización están protegidos de amenazas ambientales | G76: The organization’s technology assets are protected from environmental threats | H76: =_xlfn.CONCAT(C76," - ",D76) -> PR.IR - Resiliencia de la infraestructura tecnológica
A77: Proteger | B77: PR | C77: PR.IR | D77: Resiliencia de la infraestructura tecnológica | E77: PR.IR-03 | F77: Mecanismos implementados para lograr los requisitos de resiliencia en situaciones normales y adversas | G77: Mechanisms are implemented to achieve resilience requirements in normal and adverse situations | H77: =_xlfn.CONCAT(C77," - ",D77) -> PR.IR - Resiliencia de la infraestructura tecnológica | I77: SÍ
A78: Proteger | B78: PR | C78: PR.IR | D78: Resiliencia de la infraestructura tecnológica | E78: PR.IR-04 | F78: Se mantiene capacidad de recursos adecuada para asegurar la disponibilidad | G78: Adequate resource capacity to ensure availability is maintained | H78: =_xlfn.CONCAT(C78," - ",D78) -> PR.IR - Resiliencia de la infraestructura tecnológica
A79: Detectar | B79: DE | C79: DE.CM | D79: Monitoreo continuo | E79: DE.CM-01 | F79: Redes y servicios de red monitoreados para hallar eventos potencialmente adversos | G79: Networks and network services are monitored to find potentially adverse events | H79: =_xlfn.CONCAT(C79," - ",D79) -> DE.CM - Monitoreo continuo | I79: SÍ
A80: Detectar | B80: DE | C80: DE.CM | D80: Monitoreo continuo | E80: DE.CM-02 | F80: El entorno físico es monitoreado para hallar eventos potencialmente adversos | G80: The physical environment is monitored to find potentially adverse events | H80: =_xlfn.CONCAT(C80," - ",D80) -> DE.CM - Monitoreo continuo | I80: SÍ
A81: Detectar | B81: DE | C81: DE.CM | D81: Monitoreo continuo | E81: DE.CM-03 | F81: La actividad del personal y el uso de la tecnología son monitoreados para hallar eventos adversos | G81: Personnel activity and technology usage are monitored to find potentially adverse events | H81: =_xlfn.CONCAT(C81," - ",D81) -> DE.CM - Monitoreo continuo | I81: SÍ
A82: Detectar | B82: DE | C82: DE.CM | D82: Monitoreo continuo | E82: DE.CM-06 | F82: Las actividades y servicios de proveedores externos son monitoreados para hallar eventos adversos | G82: External service provider activities and services are monitored to find potentially adverse events | H82: =_xlfn.CONCAT(C82," - ",D82) -> DE.CM - Monitoreo continuo
A83: Detectar | B83: DE | C83: DE.CM | D83: Monitoreo continuo | E83: DE.CM-09 | F83: Hardware y software de cómputo, entornos de ejecución y sus datos monitoreados para hallar eventos adversos | G83: Computing hardware and software, runtime environments, and their data are monitored to find potentially adverse events | H83: =_xlfn.CONCAT(C83," - ",D83) -> DE.CM - Monitoreo continuo | I83: SÍ
A84: Detectar | B84: DE | C84: DE.AE | D84: Análisis de eventos adversos | E84: DE.AE-02 | F84: Eventos potencialmente adversos analizados para comprender mejor la actividad asociada | G84: Potentially adverse events are analyzed to better understand associated activities | H84: =_xlfn.CONCAT(C84," - ",D84) -> DE.AE - Análisis de eventos adversos | I84: SÍ
A85: Detectar | B85: DE | C85: DE.AE | D85: Análisis de eventos adversos | E85: DE.AE-03 | F85: La información es correlacionada desde múltiples fuentes | G85: Information is correlated from multiple sources | H85: =_xlfn.CONCAT(C85," - ",D85) -> DE.AE - Análisis de eventos adversos | I85: SÍ
A86: Detectar | B86: DE | C86: DE.AE | D86: Análisis de eventos adversos | E86: DE.AE-04 | F86: El impacto y alcance estimados de los eventos adversos son comprendidos | G86: The estimated impact and scope of adverse events are understood | H86: =_xlfn.CONCAT(C86," - ",D86) -> DE.AE - Análisis de eventos adversos | I86: SÍ
A87: Detectar | B87: DE | C87: DE.AE | D87: Análisis de eventos adversos | E87: DE.AE-06 | F87: La información sobre eventos adversos se pone a disposición del personal y las herramientas autorizadas | G87: Information on adverse events is provided to authorized staff and tools | H87: =_xlfn.CONCAT(C87," - ",D87) -> DE.AE - Análisis de eventos adversos
A88: Detectar | B88: DE | C88: DE.AE | D88: Análisis de eventos adversos | E88: DE.AE-07 | F88: La inteligencia de amenazas y otra información contextual se integran en el análisis | G88: Cyber threat intelligence and other contextual information are integrated into the analysis | H88: =_xlfn.CONCAT(C88," - ",D88) -> DE.AE - Análisis de eventos adversos
A89: Detectar | B89: DE | C89: DE.AE | D89: Análisis de eventos adversos | E89: DE.AE-08 | F89: Se declaran incidentes cuando los eventos adversos cumplen los criterios definidos | G89: Incidents are declared when adverse events meet the defined incident criteria | H89: =_xlfn.CONCAT(C89," - ",D89) -> DE.AE - Análisis de eventos adversos
A90: Responder | B90: RS | C90: RS.MA | D90: Gestión de incidentes | E90: RS.MA-01 | F90: El plan de respuesta se ejecuta en coordinación con terceros relevantes una vez declarado el incidente | G90: The incident response plan is executed in coordination with relevant third parties once an incident is declared | H90: =_xlfn.CONCAT(C90," - ",D90) -> RS.MA - Gestión de incidentes
A91: Responder | B91: RS | C91: RS.MA | D91: Gestión de incidentes | E91: RS.MA-02 | F91: Los reportes de incidente son triados y validados | G91: Incident reports are triaged and validated | H91: =_xlfn.CONCAT(C91," - ",D91) -> RS.MA - Gestión de incidentes | I91: SÍ
A92: Responder | B92: RS | C92: RS.MA | D92: Gestión de incidentes | E92: RS.MA-03 | F92: Los incidentes son categorizados y priorizados | G92: Incidents are categorized and prioritized | H92: =_xlfn.CONCAT(C92," - ",D92) -> RS.MA - Gestión de incidentes | I92: SÍ
A93: Responder | B93: RS | C93: RS.MA | D93: Gestión de incidentes | E93: RS.MA-04 | F93: Los incidentes se escalan o elevan según sea necesario | G93: Incidents are escalated or elevated as needed | H93: =_xlfn.CONCAT(C93," - ",D93) -> RS.MA - Gestión de incidentes
A94: Responder | B94: RS | C94: RS.MA | D94: Gestión de incidentes | E94: RS.MA-05 | F94: Se aplican los criterios para iniciar la recuperación del incidente | G94: The criteria for initiating incident recovery are applied | H94: =_xlfn.CONCAT(C94," - ",D94) -> RS.MA - Gestión de incidentes
A95: Responder | B95: RS | C95: RS.AN | D95: Análisis de incidentes | E95: RS.AN-03 | F95: Se realiza análisis para establecer qué ocurrió durante el incidente y su causa raíz | G95: Analysis is performed to establish what has taken place during an incident and the root cause of the incident | H95: =_xlfn.CONCAT(C95," - ",D95) -> RS.AN - Análisis de incidentes | I95: SÍ
A96: Responder | B96: RS | C96: RS.AN | D96: Análisis de incidentes | E96: RS.AN-06 | F96: Las acciones de la investigación se registran y se preserva la integridad y procedencia de los registros | G96: Actions performed during an investigation are recorded, and the records’ integrity and provenance are preserved | H96: =_xlfn.CONCAT(C96," - ",D96) -> RS.AN - Análisis de incidentes
A97: Responder | B97: RS | C97: RS.AN | D97: Análisis de incidentes | E97: RS.AN-07 | F97: Los datos y metadatos del incidente se recolectan y se preserva su integridad y procedencia | G97: Incident data and metadata are collected, and their integrity and provenance are preserved | H97: =_xlfn.CONCAT(C97," - ",D97) -> RS.AN - Análisis de incidentes
A98: Responder | B98: RS | C98: RS.AN | D98: Análisis de incidentes | E98: RS.AN-08 | F98: La magnitud del incidente se estima y valida | G98: An incident’s magnitude is estimated and validated | H98: =_xlfn.CONCAT(C98," - ",D98) -> RS.AN - Análisis de incidentes
A99: Responder | B99: RS | C99: RS.CO | D99: Reporte y comunicación del incidente | E99: RS.CO-02 | F99: Las partes interesadas internas y externas son notificadas de los incidentes | G99: Internal and external stakeholders are notified of incidents | H99: =_xlfn.CONCAT(C99," - ",D99) -> RS.CO - Reporte y comunicación del incidente | I99: SÍ
A100: Responder | B100: RS | C100: RS.CO | D100: Reporte y comunicación del incidente | E100: RS.CO-03 | F100: Se comparte información con las partes interesadas internas y externas designadas | G100: Information is shared with designated internal and external stakeholders | H100: =_xlfn.CONCAT(C100," - ",D100) -> RS.CO - Reporte y comunicación del incidente
A101: Responder | B101: RS | C101: RS.MI | D101: Mitigación del incidente | E101: RS.MI-01 | F101: Los incidentes son contenidos | G101: Incidents are contained | H101: =_xlfn.CONCAT(C101," - ",D101) -> RS.MI - Mitigación del incidente | I101: SÍ
A102: Responder | B102: RS | C102: RS.MI | D102: Mitigación del incidente | E102: RS.MI-02 | F102: Los incidentes son erradicados | G102: Incidents are eradicated | H102: =_xlfn.CONCAT(C102," - ",D102) -> RS.MI - Mitigación del incidente
A103: Recuperar | B103: RC | C103: RC.RP | D103: Ejecución del plan de recuperación | E103: RC.RP-01 | F103: La porción de recuperación del plan de respuesta se ejecuta una vez iniciada desde el proceso de respuesta | G103: The recovery portion of the incident response plan is executed once initiated from the incident response process | H103: =_xlfn.CONCAT(C103," - ",D103) -> RC.RP - Ejecución del plan de recuperación
A104: Recuperar | B104: RC | C104: RC.RP | D104: Ejecución del plan de recuperación | E104: RC.RP-02 | F104: Las acciones de recuperación se seleccionan, dimensionan, priorizan y ejecutan | G104: Recovery actions are selected, scoped, prioritized, and performed | H104: =_xlfn.CONCAT(C104," - ",D104) -> RC.RP - Ejecución del plan de recuperación
A105: Recuperar | B105: RC | C105: RC.RP | D105: Ejecución del plan de recuperación | E105: RC.RP-03 | F105: La integridad de los respaldos y activos de restauración se verifica antes de usarlos | G105: The integrity of backups and other restoration assets is verified before using them for restoration | H105: =_xlfn.CONCAT(C105," - ",D105) -> RC.RP - Ejecución del plan de recuperación
A106: Recuperar | B106: RC | C106: RC.RP | D106: Ejecución del plan de recuperación | E106: RC.RP-04 | F106: Las funciones críticas de la misión y la gestión del riesgo se consideran para establecer las normas operativas posincidente | G106: Critical mission functions and cybersecurity risk management are considered to establish post-incident operational norms | H106: =_xlfn.CONCAT(C106," - ",D106) -> RC.RP - Ejecución del plan de recuperación
A107: Recuperar | B107: RC | C107: RC.RP | D107: Ejecución del plan de recuperación | E107: RC.RP-05 | F107: Se verifica la integridad de los activos restaurados, se restauran sistemas y servicios y se confirma el estado normal de operación | G107: The integrity of restored assets is verified, systems and services are restored, and normal operating status is confirmed | H107: =_xlfn.CONCAT(C107," - ",D107) -> RC.RP - Ejecución del plan de recuperación
A108: Recuperar | B108: RC | C108: RC.RP | D108: Ejecución del plan de recuperación | E108: RC.RP-06 | F108: Se declara el fin de la recuperación con base en criterios y se completa la documentación del incidente | G108: The end of incident recovery is declared based on criteria, and incident-related documentation is completed | H108: =_xlfn.CONCAT(C108," - ",D108) -> RC.RP - Ejecución del plan de recuperación
A109: Recuperar | B109: RC | C109: RC.CO | D109: Comunicación de la recuperación | E109: RC.CO-03 | F109: Las actividades y el avance de la recuperación se comunican a las partes interesadas designadas | G109: Recovery activities and progress in restoring operational capabilities are communicated to designated internal and external stakeholders | H109: =_xlfn.CONCAT(C109," - ",D109) -> RC.CO - Comunicación de la recuperación
A110: Recuperar | B110: RC | C110: RC.CO | D110: Comunicación de la recuperación | E110: RC.CO-04 | F110: Las actualizaciones públicas sobre la recuperación se comparten con métodos y mensajes aprobados | G110: Public updates on incident recovery are shared using approved methods and messaging | H110: =_xlfn.CONCAT(C110," - ",D110) -> RC.CO - Comunicación de la recuperación

Sheet 2_Categorias
A1: CATEGORÍAS NIST CSF 2.0 — 22
A2: Cada categoría agrupa las subcategorías de un mismo resultado de gestión.
A4: Función | B4: Código función | C4: Categoría | D4: Nombre | E4: Categoría - Nombre | F4: Descripción / glosa (es) | G4: Texto oficial NIST CSF 2.0 (en) | H4: Subcategorías | I4: En uso en el portafolio
A5: Gobernar | B5: GV | C5: GV.OC | D5: Contexto organizacional | E5: {=con} -> #NAME? | F5: Se comprenden las circunstancias que rodean las decisiones de gestión del riesgo: misión, expectativas de las partes interesadas, dependencias y requisitos legales, regulatorios y contractuales. | G5: The circumstances — mission, stakeholder expectations, dependencies, and legal, regulatory, and contractual requirements — surrounding the organization’s cybersecurity risk management decisions are understood | H5: 5
A6: Gobernar | B6: GV | C6: GV.RM | D6: Estrategia de gestión de riesgo | F6: Se establecen, comunican y usan las prioridades, restricciones, declaraciones de apetito y tolerancia al riesgo y supuestos que sustentan las decisiones operativas. | G6: The organization’s priorities, constraints, risk tolerance and appetite statements, and assumptions are established, communicated, and used to support operational risk decisions | H6: 7
A7: Gobernar | B7: GV | C7: GV.RR | D7: Roles, responsabilidades y autoridades | F7: Se establecen y comunican roles, responsabilidades y autoridades de ciberseguridad para sostener la rendición de cuentas, la evaluación del desempeño y la mejora continua. | G7: Cybersecurity roles, responsibilities, and authorities to foster accountability, performance assessment, and continuous improvement are established and communicated | H7: 4
A8: Gobernar | B8: GV | C8: GV.PO | D8: Política | F8: Se establece, comunica y exige el cumplimiento de la política de ciberseguridad de la organización. | G8: Organizational cybersecurity policy is established, communicated, and enforced | H8: 2
A9: Gobernar | B9: GV | C9: GV.OV | D9: Supervisión | F9: Los resultados y el desempeño de la gestión del riesgo se usan para informar, mejorar y ajustar la estrategia. | G9: Results of organization-wide cybersecurity risk management activities and performance are used to inform, improve, and adjust the risk management strategy | H9: 3
A10: Gobernar | B10: GV | C10: GV.SC | D10: Gestión del riesgo de la cadena de suministro | F10: Se identifican, establecen, gestionan, monitorean y mejoran los procesos de gestión del riesgo de la cadena de suministro cibernética. | G10: Cyber supply chain risk management processes are identified, established, managed, monitored, and improved by organizational stakeholders | H10: 10
A11: Identificar | B11: ID | C11: ID.AM | D11: Gestión de activos | F11: Los activos que permiten a la organización cumplir sus propósitos se identifican y gestionan según su importancia relativa y la estrategia de riesgo. | G11: Assets (e.g., data, hardware, software, systems, facilities, services, people) that enable the organization to achieve business purposes are identified and managed consistent with their relative importance to organizational objectives and the organization’s risk strategy | H11: 7 | I11: 6 de 7
A12: Identificar | B12: ID | C12: ID.RA | D12: Evaluación de riesgo | F12: La organización comprende el riesgo de ciberseguridad para sí misma, sus activos y las personas. | G12: The cybersecurity risk to the organization, assets, and individuals is understood by the organization | H12: 10 | I12: 4 de 10
A13: Identificar | B13: ID | C13: ID.IM | D13: Mejora | F13: Se identifican mejoras a los procesos, procedimientos y actividades de gestión del riesgo en todas las funciones del marco. | G13: Improvements to organizational cybersecurity risk management processes, procedures and activities are identified across all CSF Functions | H13: 4 | I13: 2 de 4
A14: Proteger | B14: PR | C14: PR.AA | D14: Identidad, autenticación y control de acceso | F14: El acceso a activos físicos y lógicos se limita a usuarios, servicios y hardware autorizados y se gestiona según el riesgo de acceso no autorizado. | G14: Access to physical and logical assets is limited to authorized users, services, and hardware and managed commensurate with the assessed risk of unauthorized access | H14: 6 | I14: 6 de 6
A15: Proteger | B15: PR | C15: PR.AT | D15: Concientización y formación | F15: El personal recibe concientización y formación en ciberseguridad para poder ejecutar sus tareas relacionadas. | G15: The organization’s personnel are provided with cybersecurity awareness and training so that they can perform their cybersecurity-related tasks | H15: 2 | I15: 2 de 2
A16: Proteger | B16: PR | C16: PR.DS | D16: Seguridad de datos | F16: Los datos se gestionan conforme a la estrategia de riesgo para proteger su confidencialidad, integridad y disponibilidad. | G16: Data are managed consistent with the organization’s risk strategy to protect the confidentiality, integrity, and availability of information | H16: 4 | I16: 3 de 4
A17: Proteger | B17: PR | C17: PR.PS | D17: Seguridad de plataforma | F17: El hardware, software y servicios de las plataformas físicas y virtuales se gestionan conforme a la estrategia de riesgo. | G17: The hardware, software (e.g., firmware, operating systems, applications), and services of physical and virtual platforms are managed consistent with the organization’s risk strategy to protect their confidentiality, integrity, and availability | H17: 6 | I17: 5 de 6
A18: Proteger | B18: PR | C18: PR.IR | D18: Resiliencia de la infraestructura tecnológica | F18: Las arquitecturas de seguridad se gestionan para proteger los activos y sostener la resiliencia organizacional. | G18: Security architectures are managed with the organization’s risk strategy to protect asset confidentiality, integrity, and availability, and organizational resilience | H18: 4 | I18: 2 de 4
A19: Detectar | B19: DE | C19: DE.CM | D19: Monitoreo continuo | F19: Los activos se monitorean para hallar anomalías, indicadores de compromiso y otros eventos potencialmente adversos. | G19: Assets are monitored to find anomalies, indicators of compromise, and other potentially adverse events | H19: 5 | I19: 4 de 5
A20: Detectar | B20: DE | C20: DE.AE | D20: Análisis de eventos adversos | F20: Las anomalías, indicadores de compromiso y eventos adversos se analizan para caracterizarlos y detectar incidentes. | G20: Anomalies, indicators of compromise, and other potentially adverse events are analyzed to characterize the events and detect cybersecurity incidents | H20: 6 | I20: 3 de 6
A21: Responder | B21: RS | C21: RS.MA | D21: Gestión de incidentes | F21: Se gestionan las respuestas a los incidentes de ciberseguridad detectados. | G21: Responses to detected cybersecurity incidents are managed | H21: 5 | I21: 2 de 5
A22: Responder | B22: RS | C22: RS.AN | D22: Análisis de incidentes | F22: Se realizan investigaciones para asegurar una respuesta efectiva y sostener las actividades forenses y de recuperación. | G22: Investigations are conducted to ensure effective response and support forensics and recovery activities | H22: 4 | I22: 1 de 4
... A24: Responder | B24: RS | C24: RS.MI | D24: Mitigación del incidente | F24: Se ejecutan actividades para impedir la expansión del evento y mitigar sus efectos. | G24: Activities are performed to prevent expansion of an event and mitigate its effects | H24: 2 | I24: 1 de 2
A25: Recuperar | B25: RC | C25: RC.RP | D25: Ejecución del plan de recuperación | F25: Se ejecutan actividades de restauración para asegurar la disponibilidad operativa de los sistemas y servicios afectados. | G25: Restoration activities are performed to ensure operational availability of systems and services affected by cybersecurity incidents | H25: 6
A26: Recuperar | B26: RC | C26: RC.CO | D26: Comunicación de la recuperación | F26: Las actividades de restauración se coordinan con partes internas y externas. | G26: Restoration activities are coordinated with internal and external parties | H26: 2

Sheet 3_Funciones
A1: FUNCIONES NIST CSF 2.0 — 6
A2: Gobernar es transversal: informa cómo la organización implementa las otras cinco.
A4: Código | B4: Función | C4: Descripción / glosa (es) | D4: Texto oficial NIST CSF 2.0 (en) | E4: Categorías | F4: Subcategorías | G4: En uso en el portafolio
A5: GV | B5: Gobernar | C5: Establecer, comunicar y supervisar la estrategia, las expectativas y la política de gestión del riesgo de ciberseguridad de la organización. | D5: The organization’s cybersecurity risk management strategy, expectations, and policy are established, communicated, and monitored | E5: 6 | F5: 31 | G5: sin aporte
A6: ID | B6: Identificar | C6: Comprender los riesgos de ciberseguridad actuales de la organización. | D6: The organization’s current cybersecurity risks are understood | E6: 3 | F6: 21 | G6: 12 de 21
A7: PR | B7: Proteger | C7: Aplicar salvaguardas para gestionar los riesgos de ciberseguridad de la organización. | D7: Safeguards to manage the organization’s cybersecurity risks are used | E7: 5 | F7: 22 | G7: 18 de 22
A8: DE | B8: Detectar | C8: Encontrar y analizar posibles ataques y compromisos de ciberseguridad. | D8: Possible cybersecurity attacks and compromises are found and analyzed | E8: 2 | F8: 11 | G8: 7 de 11
A9: RS | B9: Responder | C9: Ejecutar acciones frente a un incidente de ciberseguridad detectado. | D9: Actions regarding a detected cybersecurity incident are taken | E9: 4 | F9: 13 | G9: 5 de 13
A10: RC | B10: Recuperar | C10: Restaurar los activos y las operaciones afectados por un incidente de ciberseguridad. | D10: Assets and operations affected by a cybersecurity incident are restored | E10: 2 | F10: 8 | G10: sin aporte
