Workbook

Sheet Sheet2
A1: Nombre | B1: Bp Id | C1: Columna1 | D1: Columna2 | E1: Descripcion | F1: Estado | G1: Prioridad | H1: Ubicacion | I1: Equipo Administrado Por | J1: Dueno Aplicacion | K1: Dueno Negocio | L1: Administrado Por | M1: Categoria Identidades | N1: Tipo Usuario | O1: ¿Existe módulo de gestión de accesos? | P1: Metodo Autenticacion | Q1: Metodo Autorizacion | R1: ¿Cumple criterios de recepción? | S1: Entregada Identidades | T1: Observacion | U1: Fecha Recepcion | V1: Administrador Aplicativo Externo | W1: Administrador Aplicativo Identidades Principal | X1: Administrador Aplicativo Identidades Backup | Y1: Metodo Reporteria Usuarios | Z1: Metodo Reporteria Perfiles Opciones | AA1: Metodo Gestion | AB1: Metodo Baja Usuarios | AC1: Url Acceso
A2: IBM WebSphere Portal | B2: CHL0017 | C2: =sheet1[[#This Row],[Nombre]]&sheet1[[#This Row],[Bp Id]] -> IBM WebSphere PortalCHL0017 | D2: =VLOOKUP(sheet1[[#This Row],[Columna1]],sheet13[[Columna1]:[Estado]],4,FALSE) -> Operativo | E2: IBM Websphere Portal, es el portal web empresarial que ofrece experiencias sociales altamente personalizadas a los usuarios. Brinda a los usuarios un único punto de acceso a las aplicaciones, servicios, información y conexiones sociales que necesiten. El usuario puede acceder de manera directa a aplicaciones como: BancsLink, Administrador de Remesas, Asesores, Balcones, Cardholder, CreditosCom, Riesgo Global, Reclamos y Requerimientos, BPM, Informes Legales. | F2: Operativo | G2: A - Apetito de Riesgo Disponibilidad | H2: On Premise | I2: TRIBU_CANALES | J2: DANIEL PATRICIO PAZ ENRIQUEZ | K2: JORGE HUMBERTO BRAVO YUNDA | L2: Luis Remigio Bayas Rea | M2: Aplicación del negocio | N2: Usuario Interno | O2: Si | P2: Active Directory | Q2: Active Directory | R2: Si | S2: No
A3: IBM WSRR | B3: INT0007 | C3: =sheet1[[#This Row],[Nombre]]&sheet1[[#This Row],[Bp Id]] -> IBM WSRRINT0007 | D3: =VLOOKUP(sheet1[[#This Row],[Columna1]],sheet13[[Columna1]:[Estado]],4,FALSE) -> Retirado | E3: Herramienta que proporciona el registro de servicios y funciones de repositorio para aplicaciones empresariales de arquitectura orientada a servicios (SOA). | F3: Retirado | G3: E - No Crítica | H3: On Premise | I3: Tribu_Integraciones_Apis | J3: DAVID RODRIGO REVELO RIVERA | K3: DIEGO VLADIMIR JAYA GUAMANZARA | L3: DIEGO VLADIMIR JAYA GUAMANZARA | M3: Consolas de Administración TI | N3: Usuario Interno | O3: Si | P3: Propio | Q3: Propio | R3: No | S3: No | T3: EVALUADA, NO CUMPLE CRITERIOS
A4: ICEPanel | B4: ITM0068 | C4: =sheet1[[#This Row],[Nombre]]&sheet1[[#This Row],[Bp Id]] -> ICEPanelITM0068 | D4: =VLOOKUP(sheet1[[#This Row],[Columna1]],sheet13[[Columna1]:[Estado]],4,FALSE) -> Operativo | E4: Modelado de Arquitectura de Soluciones | F4: Operativo | G4: D - BIA No Crítica | H4: Nube | I4: COE ARQUITECTURA | J4: MAURICIO BLADIMIR AUQUI MIRANDA | K4: LUIS MIGUEL ULLOA MOREIRA | L4: LUIS MIGUEL ULLOA MOREIRA | M4: Aplicación complementaria | N4: Usuario Interno | O4: Si | P4: Entra ID | Q4: Entra ID | R4: No | S4: No | T4: EVALUADA, NO CUMPLE CRITERIOS
A5: Idera | B5: ITM0035 | C5: =sheet1[[#This Row],[Nombre]]&sheet1[[#This Row],[Bp Id]] -> IderaITM0035 | D5: =VLOOKUP(sheet1[[#This Row],[Columna1]],sheet13[[Columna1]:[Estado]],4,FALSE) -> Operativo | E5: Es una aplicación para administrar motores SQL, donde se visualiza eventos que ocurran en las bases de datos como en el servidor | F5: Operativo | G5: D - BIA No Crítica | H5: On Premise | I5: INFRAESTRUCTURA | J5: BYRON ORLANDO MELENDREZ CABRERA | K5: NELSON ANDRES POZO YEPEZ | L5: FELIX ALEXANDER MANJARRES QUEZADA | M5: Consolas de Administración TI | N5: Usuario Interno | O5: Si | P5: Propio | Q5: Propio | R5: Si | S5: No | AC5: Conectarse a Idera y sacar los scripts de migración es_x000D_ Test: POECWDB064
A6: IGNITION | B6: ITM0069 | C6: =sheet1[[#This Row],[Nombre]]&sheet1[[#This Row],[Bp Id]] -> IGNITIONITM0069 | D6: =VLOOKUP(sheet1[[#This Row],[Columna1]],sheet13[[Columna1]:[Estado]],4,FALSE) -> Operativo | E6: Monitoreo de las facilidades de los centros de datos, Sistemas Electricos, Enfriamiento, Electrogenos | F6: Operativo | G6: C - BIA Crítica | H6: On Premise | I6: INFRAESTRUCTURA | J6: BYRON ORLANDO MELENDREZ CABRERA | K6: DIEGO JAVIER SALAZAR MOLINA | L6: DIEGO PAUL BETANCOURT REYES | M6: Aplicación complementaria | N6: Usuario Interno | O6: Si | P6: Propio | Q6: Propio | R6: No | S6: No | T6: EVALUADA, NO CUMPLE CRITERIOS
A7: ILMT | B7: ITM0036 | C7: =sheet1[[#This Row],[Nombre]]&sheet1[[#This Row],[Bp Id]] -> ILMTITM0036 | D7: =VLOOKUP(sheet1[[#This Row],[Columna1]],sheet13[[Columna1]:[Estado]],4,FALSE) -> Operativo | E7: Monitoreo de Software IBM instalado en servidores licenciamiento | F7: Operativo | G7: E - No Crítica | H7: On Premise | I7: INFRAESTRUCTURA | J7: BYRON ORLANDO MELENDREZ CABRERA | K7: HORACIO LEONEL HOLGUIN ALCIVAR | L7: FREDDY VINICIO ESTRELLA HIDALGO | M7: Consolas de Administración TI | N7: Usuario Interno | O7: Si | P7: Propio | Q7: Propio | R7: No | S7: No | T7: EVALUADA, NO CUMPLE CRITERIOS
A8: Impacto 360 | B8: DAT0015 | C8: =sheet1[[#This Row],[Nombre]]&sheet1[[#This Row],[Bp Id]] -> Impacto 360DAT0015 | D8: =VLOOKUP(sheet1[[#This Row],[Columna1]],sheet13[[Columna1]:[Estado]],4,FALSE) -> Operativo | E8: la iniciativa es una plataforma de inteligencia empresarial y análisis de mercado con un enfoque específico en los clientes que utilizan medios de pago del Banco Pichincha (tarjetas de crédito, tarjetas de débito y transferencias digitales). Esta plataforma brinda a los empresarios la capacidad de acceder y visualizar información histórica y resumida de estos clientes, permitiéndoles obtener una visión más detallada y específica de su base de clientes y sus comportamientos de pago. | F8: Operativo | G8: E - No Crítica | H8: Nube | I8: Negocios y Monetización | J8: ANTONIO ALEJANDRO CANAVERAL GIL | K8: SEBASTIAN MUNOZ ANDERSEN | L8: HEVER GONZALEZ GARCIA | M8: Aplicación del negocio | N8: Clientes | O8: Si | P8: Entra ID | Q8: Entra ID | R8: No | S8: No | T8: EVALUADA, NO CUMPLE CRITERIOS
A9: Impresion Documentos | B9: TIE0018 | C9: =sheet1[[#This Row],[Nombre]]&sheet1[[#This Row],[Bp Id]] -> Impresion DocumentosTIE0018 | D9: =VLOOKUP(sheet1[[#This Row],[Columna1]],sheet13[[Columna1]:[Estado]],4,FALSE) -> Operativo | E9: Aplicación que permite levantar documentos de word ejecutando macros. Genera documentos entregados a los clientes, principalmente de solicitudes de crédito. | F9: Operativo | G9: E - No Crítica | H9: On Premise | I9: ACTIVOS | J9: LAURA ELIZABETH CARRASCO UQUILLAS | K9: ANDREA FERNANDA ORTIZ CISNEROS | L9: ERISLAN MARTINEZ JERA | M9: Aplicación del negocio | N9: Usuario Interno | O9: Si | P9: Active Directory | Q9: Propio | R9: Si | S9: Si | T9: Se ingresa por Login Central | U9: 45199 | W9: LIVE LOZADA EDGAR ROBERTO | X9: PAREDES NACIPUCHA EDISSON FERNANDO | AA9: AUTORIZACION: PERFIL SIGLO21_x000D_ ASIGNAR GRUPO DE AD: GA_LOGINC_IMPRESION DE DOCUMENTOS | AC9: https://logincentral.bp.bpichincha.com/
A10: Informes de RedTeam | B10: SEC0083 | C10: =sheet1[[#This Row],[Nombre]]&sheet1[[#This Row],[Bp Id]] -> Informes de RedTeamSEC0083 | D10: =VLOOKUP(sheet1[[#This Row],[Columna1]],sheet13[[Columna1]:[Estado]],4,FALSE) -> Retirado | E10: Herramienta permite la generación automatizada de informes a través de plantillas, además de ofrecer un control centralizado de los hallazgos obtenidos durante los ejercicios ofensivos. Versión v4.2.5, released 9 August 2024, con soporte Local. Se adjunta la certificación de software por ciberseguridad para poder ser utilizado en entono Banco. | F10: Retirado | G10: E - No Crítica | H10: Nube | I10: Ciberseguridad | J10: SANTIAGO ANDRES MEDRANDA MOREJON | K10: JOHNATAN SILVA ORREGO | L10: Allan Paul Gomez Ehmig | M10: Consolas de Administración Seguridad | N10: Usuario Interno | O10: Si | P10: Active Directory | Q10: Active Directory | R10: Si | S10: No | T10: Se hizo una revisión con Arq. de Cyberseguridad y se va a replantear la solución para construir esta aplicación sobre la plataforma de sharepoint en vez de usar software libre, por lo que algunos de los criterios de respuesta podrán cambiar.
A11: informesCredito | B11: PRD0021 | C11: =sheet1[[#This Row],[Nombre]]&sheet1[[#This Row],[Bp Id]] -> informesCreditoPRD0021 | D11: =VLOOKUP(sheet1[[#This Row],[Columna1]],sheet13[[Columna1]:[Estado]],4,FALSE) -> Operativo | E11: Aplicación utilizada por las empresas que contratan el servicio para ver referencias bancarias de los clientes del Banco del Pichincha, pueden ver la cantidad de cifras, altas o bajas de sus cuentas, clientes como Dinners, Artefacta, Movistar lo utilizan. Cada consulta de los clientes tiene un costo. | F11: Operativo | G11: E - No Crítica | H11: Nube | I11: Frente de Soluciones Empresariales | J11: LUIS MIGUEL ULLOA MOREIRA | K11: FABRICIO ANTONIO PEREIRA GARCIA | L11: WILLIAM PATRICIO PANCHI SHUGULI | M11: Aplicación del negocio | N11: Usuario Interno | O11: No | P11: Propio | Q11: Propio | R11: Si | S11: Si | T11: SIGLO21 | U11: 45199 | W11: LIVE LOZADA EDGAR ROBERTO | X11: PAREDES NACIPUCHA EDISSON FERNANDO
A12: Integration Bus Soporte | B12: INT0009 | C12: =sheet1[[#This Row],[Nombre]]&sheet1[[#This Row],[Bp Id]] -> Integration Bus SoporteINT0009 | D12: =VLOOKUP(sheet1[[#This Row],[Columna1]],sheet13[[Columna1]:[Estado]],4,FALSE) -> Operativo | E12: Integration Bus permite administrar y monitorear los flujos de integración que conectan múltiples canales digitales y sistemas backend. Facilita la gestión de servicios, procesamiento de mensajes y orquestación de transacciones entre aplicaciones. Es un componente clave para asegurar la operación continua y la integración eficiente en arquitecturas omnicanal. | F12: Operativo | G12: B - Ecosistema Apetito de Riesgo | H12: On Premise | I12: Tribu_Integraciones_Apis | J12: DAVID RODRIGO REVELO RIVERA | K12: DIEGO VLADIMIR JAYA GUAMANZARA | L12: DIEGO VLADIMIR JAYA GUAMANZARA | M12: Consolas de Administración TI | N12: Usuario Interno | O12: Si | P12: Propio | Q12: Propio | R12: Si | S12: Si | U12: 46197 | V12: ESTRELLA HIDALGO FREDDY VINICIO | W12: FLORES YAGUANA JHONATAN DAMIAN | X12: RAMOS SALAZAR SEBASTIAN MATEO | Y12: Manual | Z12: Manual | AA12: Ingresar al nodo (servidor Unix) correspondiente mediante Cyberark utilizando el usuario root y ejecutar los comandos detallados en el instructivo para administrar usuarios | AB12: Eliminar | AC12: APLICACIÓN HOSTNAME IP_x000D_ Integration Bus Soporte Nodo1 PRECBPIB01 10.151.152.221_x000D_ Integration Bus Soporte Nodo2 PRECBPIB02 10.151.152.222_x000D_ Integration Bus Soporte Cash 1 PRECBPIB10 10.151.152.227_x000D_ Integration Bus Soporte Cash 2 PRECBPIB11 10.151.152.226
A13: Interaction Studio | B13: CUS0010 | C13: =sheet1[[#This Row],[Nombre]]&sheet1[[#This Row],[Bp Id]] -> Interaction StudioCUS0010 | D13: =VLOOKUP(sheet1[[#This Row],[Columna1]],sheet13[[Columna1]:[Estado]],4,FALSE) -> Retirado | E13: Es una herramienta de Salesforce Marketing Cloud que aprende de los datos de manera automática para lograr identificar las siguientes mejores ofertas y/o acciones para cada cliente | F13: Retirado | G13: E - No Crítica | H13: Nube | I13: Negocios Digitales (Campañas y Marketing Digital) | J13: ANTONIO ALEJANDRO CANAVERAL GIL | K13: IVANNA MARIA ZAUZICH POSADA | L13: FREDDY LEONARDO ABAD LEON | M13: Aplicación complementaria | N13: Usuario Interno | O13: Si | P13: Propio | Q13: Propio | R13: No | S13: No | T13: EVALUADA, NO CUMPLE CRITERIOS
A14: Interdin AS400 Gestor | B14: PAY0008 | C14: =sheet1[[#This Row],[Nombre]]&sheet1[[#This Row],[Bp Id]] -> Interdin AS400 GestorPAY0008 | D14: =VLOOKUP(sheet1[[#This Row],[Columna1]],sheet13[[Columna1]:[Estado]],4,FALSE) -> Retirado | E14: No existe descripción | F14: Retirado | G14: C - BIA Crítica | H14: Terceros | I14: MEDIOS_DE_PAGO | J14: DIEGO MANUEL CARRERA BENAVIDES | K14: KATHERINE FATIMA CJURO VERA | L14: JEAN ANEL PROANO FALCONES | M14: Aplicación del negocio | N14: Usuario Interno | O14: No | P14: Propio | Q14: Propio | R14: No | S14: No | T14: REPORTERIA: CORREO A EXTERNO LUEGO SUBIR A GEMA | U14: 45200 | W14: PAREDES NACIPUCHA EDISSON FERNANDO | X14: ALVARADO RAMOS OLGER OSWALDO | Y14: ETL | Z14: ETL | AA14: CREAR TICKET | AB14: Eliminar
A15: Interdin Autorizador CAO | B15: PAY0009 | C15: =sheet1[[#This Row],[Nombre]]&sheet1[[#This Row],[Bp Id]] -> Interdin Autorizador CAOPAY0009 | D15: =VLOOKUP(sheet1[[#This Row],[Columna1]],sheet13[[Columna1]:[Estado]],4,FALSE) -> Retirado | E15: No existe descripción | F15: Retirado | G15: C - BIA Crítica | H15: Terceros | I15: MEDIOS_DE_PAGO | J15: EDWIN GEOVANNY FLORES CASTRO | K15: KATHERINE FATIMA CJURO VERA | L15: JEAN ANEL PROANO FALCONES | M15: Aplicación del negocio | N15: Usuario Interno | O15: No | P15: Propio | Q15: Propio | R15: No | S15: No | T15: CREAR TICKET A INTERDIN PARA SOLICITAR REPORTES DE USUARIO Y PERFILES | U15: 45200 | W15: PAREDES NACIPUCHA EDISSON FERNANDO | X15: ALVARADO RAMOS OLGER OSWALDO | Y15: ETL | Z15: ETL | AA15: CREAR TICKET | AB15: Eliminar
A16: Interdin AS 400/ CAO | B16: PAY0010 | C16: =sheet1[[#This Row],[Nombre]]&sheet1[[#This Row],[Bp Id]] -> Interdin AS 400/ CAOPAY0010 | D16: =VLOOKUP(sheet1[[#This Row],[Columna1]],sheet13[[Columna1]:[Estado]],4,FALSE) -> Operativo | E16: No existe descripción | F16: Operativo | G16: C - BIA Crítica | H16: Terceros | I16: MEDIOS_DE_PAGO | J16: EDWIN GEOVANNY FLORES CASTRO | K16: KATHERINE FATIMA CJURO VERA | L16: JEAN ANEL PROANO FALCONES | M16: Aplicación del negocio | N16: Usuario Interno | O16: Si | P16: Propio | Q16: Propio | R16: Si | S16: Si | T16: PIVI/CAO | U16: 45199 | W16: PAREDES NACIPUCHA EDISSON FERNANDO | X16: ALVARADO RAMOS OLGER OSWALDO
A17: Interdin Servicios Integración | B17: PAY0011 | C17: =sheet1[[#This Row],[Nombre]]&sheet1[[#This Row],[Bp Id]] -> Interdin Servicios IntegraciónPAY0011 | D17: =VLOOKUP(sheet1[[#This Row],[Columna1]],sheet13[[Columna1]:[Estado]],4,FALSE) -> Operativo | E17: INTERDIN SERVICIOS INTEGRACION comprende dos servidores que fueron creados para _x000D_ relacionar servicios de Interdin (Proveedor). | F17: Operativo | G17: B - Ecosistema Apetito de Riesgo | H17: Terceros | I17: MEDIOS_DE_PAGO | J17: EDWIN GEOVANNY FLORES CASTRO | K17: WILLIAM RICHARD CORREA JIMENEZ | L17: DAVID DE JESUS BELLO NIEVES | M17: Componente | N17: Usuario Interno | O17: No | P17: Propio | Q17: Propio | R17: No | S17: No | T17: EVALUADO: NO APLICA RECEPCION_x000D_ Descripción del aplicativo: _x000D_ o INTERDIN SERVICIOS INTEGRACION comprende dos servidores que fueron creados para _x000D_ relacionar servicios de Interdin (Proveedor)._x000D_ o En base al documento ¿BPECU-SEG-044-STD - Estándar de Recepción de Módulos de _x000D_ Gestión de Accesos y Perfiles V 2.1-¿; donde se definen uno de los criterios para recepción _x000D_ es contar con un módulo de gestión de accesos y perfiles. _x000D_ _x000D_ o En la reunión mantenida el jueves 20 de noviembre 2025 en conjunto con el equipo _x000D_ administrador del aplicativo, se concluyó que: ¿Interdin Servicios Integración no es una _x000D_ aplicación, son dos servidores que están relacionados a la aplicación de manera _x000D_ incorrecta. No cuenta con módulo de gestión de usuarios ni perfiles, por lo cual no aplica _x000D_ realizar un proceso de recepción¿. Adicional, se tuvieron las siguientes observaciones: _x000D_ _x000D_ o Edwin Geovanny Flores Castro - LIDER TECNICO DE TRIBU menciona: ¿Más adelante _x000D_ procederé a decomisarla cuando apague los servidores¿, de acuerdo con el correo con _x000D_ asunto: Re: Solicitud entrega del aplicativo a Gestión de Identidades: INTERDIN SERVICIOS _x000D_ INTEGRACION, con fecha 20 de noviembre de 2025. _x000D_ _x000D_ o Se realiza la consulta sobre la fecha de apagado y si existe alguna aplicación en su _x000D_ reemplazo, a lo que Edwin Geovanny Flores Castro - LIDER TECNICO DE TRIBU menciona: _x000D_ ¿Aún no tengo esa información. De momento esta aplicación no es prioritaria para la _x000D_ tribu¿._x000D_ o En referencia a la gestión de usuarios y perfiles: Edwin Geovanny Flores Castro - LIDER _x000D_ TECNICO DE TRIBU menciona: ¿la aplicación en mención no tiene roles ni usuarios¿. | U17: 45981 | V17: FLORES CASTRO EDWIN GEOVANNY
A18: Inversiones | B18: PRD0060 | C18: =sheet1[[#This Row],[Nombre]]&sheet1[[#This Row],[Bp Id]] -> InversionesPRD0060 | D18: =VLOOKUP(sheet1[[#This Row],[Columna1]],sheet13[[Columna1]:[Estado]],4,FALSE) -> Operativo | E18: Aplicacion para venta y postventa de Inversiones. | F18: Operativo | G18: E - No Crítica | H18: Nube | I18: PASIVOS Y SEGUROS | J18: LAURA ELIZABETH CARRASCO UQUILLAS | K18: JONATHAN HERNAN ARIAS HERNANDEZ | L18: MANUEL ABELARDO HARO MONTERO | M18: Aplicación del negocio | N18: Clientes | O18: No | P18: Entra ID | Q18: Entra ID | R18: No | S18: No | T18: Detalle del criterio de recepción:_x000D_ _x000D_ o En base al documento ¿BPECU-SEG-044-STD - Estándar de Recepción de Módulos de Gestión de Accesos y Perfiles V 2.1-¿; donde se definen uno de los criterios para recepción es contar con un módulo de gestión de accesos y perfiles. _x000D_ _x000D_ o En la reunión mantenida el lunes 24 de marzo de 2026 en conjunto con el equipo administrador del aplicativo, se concluyó que: que la aplicación no cuenta con un módulo para la gestión de accesos._x000D_ _x000D_ o Loaiza Armijos Mayi Dayali - EXPERTO PORTAFOLIO PRODUCTOS Y SERVICIOS Nos informa _x000D_ que el acceso es a través de la banca web y va dirigido a clientes finales. _x000D_ _x000D_ o Cabe mencionar que el acceso al módulo de Inversiones dentro del Portal de la Banca Web _x000D_ es de autogestión; es decir, lo realiza directamente el cliente final sin la intervención de _x000D_ ningún asesor. | U18: 46107 | V18: CARRASCO UQUILLAS LAURA ELIZABETH
A19: IPS Intrusion Prevention System | B19: SEC0025 | C19: =sheet1[[#This Row],[Nombre]]&sheet1[[#This Row],[Bp Id]] -> IPS Intrusion Prevention SystemSEC0025 | D19: =VLOOKUP(sheet1[[#This Row],[Columna1]],sheet13[[Columna1]:[Estado]],4,FALSE) -> Operativo | E19: Cisco Firepower Management Center 4600 | F19: Operativo | G19: C - BIA Crítica | H19: On Premise | I19: Ciberseguridad | J19: ERICK DAMIAN RISUENO BENITEZ | K19: MARCO FABRICIO FALCONI NORIEGA | L19: JORGE XAVIER LUCERO GALLEGOS | M19: Consolas de Administración Seguridad | N19: Usuario Interno | O19: Si | P19: Active Directory | Q19: Propio | R19: Si | S19: Si | U19: 45929 | V19: RISUENO BENITEZ ERICK DAMIAN | W19: ZAMBRANO NUNEZ PAUL SANTIAGO | X19: RAMOS SALAZAR SEBASTIAN MATEO | Y19: Manual | Z19: Manual | AA19: GESTIONAR EN LA APLICACION USUARIOS Y ROLES | AC19: Cybeark: _x000D_ https://10.70.88.105/
A20: ISE | B20: SEC0026 | C20: =sheet1[[#This Row],[Nombre]]&sheet1[[#This Row],[Bp Id]] -> ISESEC0026 | D20: =VLOOKUP(sheet1[[#This Row],[Columna1]],sheet13[[Columna1]:[Estado]],4,FALSE) -> Operativo | E20: CONTROL DE ACCESO A LA RED | F20: Operativo | G20: C - BIA Crítica | H20: On Premise | I20: Ciberseguridad | J20: JORGE XAVIER LUCERO GALLEGOS | K20: MARCO FABRICIO FALCONI NORIEGA | L20: ROBERT STALIN SOTO CORONEL | M20: Consolas de Administración Seguridad | N20: Usuario Interno | O20: Si | P20: Active Directory | Q20: Active Directory | R20: Si | S20: Si | U20: 45772 | V20: LUCERO GALLEGOS JORGE XAVIER | W20: BARAHONA ESPINOSA SANTIAGO ISRAEL | X20: BARAHONA ESPINOSA SANTIAGO ISRAEL | Y20: Manual | Z20: Manual | AA20: Generar un ticket en el flujo: "Gestión de Acceso a la Red"; junto con la autorización de Jorge Lucero | AB20: Eliminar | AC20: Cyberark: 10.70.88.110
A21: Jaguar Liquidez Plus | B21: PRD0022 | C21: =sheet1[[#This Row],[Nombre]]&sheet1[[#This Row],[Bp Id]] -> Jaguar Liquidez PlusPRD0022 | D21: =VLOOKUP(sheet1[[#This Row],[Columna1]],sheet13[[Columna1]:[Estado]],4,FALSE) -> Retirado | E21: En portafolio | F21: Retirado | G21: E - No Crítica | H21: Nube | I21: Frente de Soluciones Empresariales | J21: LUIS MIGUEL ULLOA MOREIRA | K21: FABRICIO ANTONIO PEREIRA GARCIA | L21: WILLIAM PATRICIO PANCHI SHUGULI | M21: Aplicación del negocio | N21: Usuario Interno | O21: No | P21: Entra ID | Q21: Entra ID | R21: Si | S21: No | T21: ADMINISTRACION ELIMINADA | AA21: Crear un ticket
A22: Jenkins | B22: ITM0037 | C22: =sheet1[[#This Row],[Nombre]]&sheet1[[#This Row],[Bp Id]] -> JenkinsITM0037 | D22: =VLOOKUP(sheet1[[#This Row],[Columna1]],sheet13[[Columna1]:[Estado]],4,FALSE) -> Retirado | E22: Herramienta de integración continua, utilizado por el proyecto de Omnicanalidad. | F22: Retirado | G22: E - No Crítica | H22: On Premise | I22: COE de Ingeniería | J22: GERMAN MARTIN GUTIERREZ | K22: GERMAN MARTIN GUTIERREZ | L22: GERMAN MARTIN GUTIERREZ | M22: Consolas de Administración TI | N22: Usuario Interno | O22: Si | P22: Propio | Q22: Propio | R22: No | S22: No | T22: EVALUADA, NO CUMPLE CRITERIOS
A23: Kafka | B23: OMN0004 | C23: =sheet1[[#This Row],[Nombre]]&sheet1[[#This Row],[Bp Id]] -> KafkaOMN0004 | D23: =VLOOKUP(sheet1[[#This Row],[Columna1]],sheet13[[Columna1]:[Estado]],4,FALSE) -> Operativo | E23: Basado en una transmisión de evetos,captura datos en tiempo real desde varias fuentes, enruta los flujos de datos a diferentes tecnologías de destino según sea necesario. | F23: Operativo | G23: B - Ecosistema Apetito de Riesgo | H23: On Premise | I23: Tribu_Integraciones_Apis | J23: DAVID RODRIGO REVELO RIVERA | K23: DIEGO VLADIMIR JAYA GUAMANZARA | L23: DIEGO VLADIMIR JAYA GUAMANZARA | M23: Consolas de Administración TI | N23: Usuario Interno | O23: No | P23: Propio | Q23: Propio | R23: No | S23: No | T23: EVALUADO_x000D_ Descripción del aplicativo: _x000D_ o Es una plataforma basada en una transmisión de eventos, captura datos en tiempo real _x000D_ desde varias fuentes, enruta los flujos de datos a diferentes tecnologías de destino según _x000D_ sea necesario._x000D_ Detalle del criterio de recepción: _x000D_ o En base al documento ¿BPECU-SEG-044-STD - Estándar de Recepción de Módulos de _x000D_ Gestión de Accesos y Perfiles V 2.1-¿; donde se definen uno de los criterios para recepción _x000D_ es contar con un módulo de gestión de accesos y perfiles. _x000D_ o Sin embargo: luego de la reunión del 2025/11/24 vía Teams con el equipo administrador _x000D_ del aplicativo informa que Kafka no cuenta con un módulo para la gestión de usuarios y _x000D_ perfiles. | U23: 45986 | V23: VALLEJO SOLORZANO OSCAR DAVID
A24: Kafka Deuna | B24: INT0014 | C24: =sheet1[[#This Row],[Nombre]]&sheet1[[#This Row],[Bp Id]] -> Kafka DeunaINT0014 | D24: =VLOOKUP(sheet1[[#This Row],[Columna1]],sheet13[[Columna1]:[Estado]],4,FALSE) -> Retirado | E24: Broker de eventos de Deuna desplegado en AWS | F24: Retirado | G24: D - BIA No Crítica | H24: Nube | I24: TRIBU_DE_UNA | J24: LUIS JAVIER MARIDUENA NOVILLO | K24: LUIS JAVIER MARIDUENA NOVILLO | L24: LUIS JAVIER MARIDUENA NOVILLO | M24: Consolas de Administración TI | N24: Usuario Interno | O24: Si | P24: Entra ID | Q24: Entra ID | R24: Si | S24: No
A25: Keeper Security | B25: SEC0053 | C25: =sheet1[[#This Row],[Nombre]]&sheet1[[#This Row],[Bp Id]] -> Keeper SecuritySEC0053 | D25: =VLOOKUP(sheet1[[#This Row],[Columna1]],sheet13[[Columna1]:[Estado]],4,FALSE) -> Operativo | E25: Solución para la gestión de contraseñas de los usuarios | F25: Operativo | G25: E - No Crítica | H25: Nube | I25: Ciberseguridad | J25: lvtandaz@pichincha.com TANDAZO GALLEGOS | K25: MARCO FABRICIO FALCONI NORIEGA | L25: ISRAEL SEBASTIAN DE LA TORRE TRUJILLO | M25: Consolas de Administración Seguridad | N25: Usuario Interno | O25: Si | P25: Entra ID | Q25: Entra ID | R25: Si | S25: No
A26: Kriptos | B26: SEC0055 | C26: =sheet1[[#This Row],[Nombre]]&sheet1[[#This Row],[Bp Id]] -> KriptosSEC0055 | D26: =VLOOKUP(sheet1[[#This Row],[Columna1]],sheet13[[Columna1]:[Estado]],4,FALSE) -> Operativo | E26: Solución basada en clasificación artificial que tiene la capacidad de identificar y clasificar los datos de la empresa. | F26: Operativo | G26: E - No Crítica | H26: Nube | I26: Ciberseguridad | J26: FERNANDO JAVIER PALADINES BUSTAMANTE | K26: MARCO FABRICIO FALCONI NORIEGA | L26: MARIA DEL CARMEN PENAHERRERA PLUA | M26: Consolas de Administración Seguridad | N26: Usuario Interno | O26: No | P26: Entra ID | Q26: Entra ID | R26: No | S26: No | T26: Detalle del criterio de recepción:_x000D_ _x000D_ o En base al documento ¿BPECU-SEG-044-STD - Estándar de Recepción de Módulos de Gestión de Accesos y Perfiles V 2.1-¿; donde se definen uno de los criterios para recepción es contar con un módulo de gestión de accesos y perfiles. _x000D_ _x000D_ o En la reunión mantenida el lunes 23 de marzo de 2026 en conjunto con el equipo administrador del aplicativo, se concluyó que: que la aplicación no cuenta con un módulo para la gestión de accesos. | U26: 46104 | V26: VIDAL BARBA GABRIELA VIRGINIA | AA26: Vidal Barba Gabriela Virginia- EXPERTO PLATAFORMAS CIBERSEGURIDAD: Nos informa que el acceso es a través de la asignación de grupos de Azure AD de nomenclatura: GSC_KRIPTOS_XXX, no existen usuarios locales.
A27: Fielweb | B27: SUP0011 | C27: =sheet1[[#This Row],[Nombre]]&sheet1[[#This Row],[Bp Id]] -> FielwebSUP0011 | D27: =VLOOKUP(sheet1[[#This Row],[Columna1]],sheet13[[Columna1]:[Estado]],4,FALSE) -> #N/A | E27: No existe descripción | F27: Operativo | G27: E - No Crítica | H27: Terceros | I27: AREAS_DE_APOYO | J27: FABIAN GEOVANNI PAZMINO UBIDIA | K27: JOSE LUIS ZAPATA ROSERO | L27: FERNANDO JOSE ROLDAN CORREA | M27: Aplicación complementaria | N27: Usuario Interno | O27: Si | P27: Propio | Q27: Propio | R27: No | S27: No | T27: EVALUADA, NO CUMPLE CRITERIOS
A28: LEXMARK CLOUD PRINT MANAGEMENT (CPM) | B28: ITM0038 | C28: =sheet1[[#This Row],[Nombre]]&sheet1[[#This Row],[Bp Id]] -> LEXMARK CLOUD PRINT MANAGEMENT (CPM)ITM0038 | D28: =VLOOKUP(sheet1[[#This Row],[Columna1]],sheet13[[Columna1]:[Estado]],4,FALSE) -> Operativo | E28: Administración Multifunción Lexmark para Integración multifuncionales con Talla Impresión | F28: Operativo | G28: E - No Crítica | H28: Nube | I28: Gerencia Arquitectura Usuario Final | J28: AMPARO MARIANA CARDENAS HUILCA | K28: ABNER ANDY AREVALO BRACAMONTE | L28: ABNER ANDY AREVALO BRACAMONTE | M28: Aplicación complementaria | N28: Usuario Interno | O28: Si | P28: Propio | Q28: Propio | R28: No | S28: No | T28: EVALUADA, NO CUMPLE CRITERIOS
A29: Lexmark Printer Management | B29: ITM0038 | C29: =sheet1[[#This Row],[Nombre]]&sheet1[[#This Row],[Bp Id]] -> Lexmark Printer ManagementITM0038 | D29: =VLOOKUP(sheet1[[#This Row],[Columna1]],sheet13[[Columna1]:[Estado]],4,FALSE) -> Retirado | E29: Administración Multifunción Lexmark para Integración multifuncionales con Talla Impresión | F29: Retirado | G29: E - No Crítica | H29: On Premise | I29: INFRAESTRUCTURA | J29: JOSE LUIS GOYES LARA | L29: ABNER ANDY AREVALO BRACAMONTE | M29: Aplicación complementaria | N29: Usuario Interno | O29: Si | P29: Propio | Q29: Propio | R29: No | S29: No | T29: EVALUADA, NO CUMPLE CRITERIOS
A30: Librarian | B30: ITM0071 | C30: =sheet1[[#This Row],[Nombre]]&sheet1[[#This Row],[Bp Id]] -> LibrarianITM0071 | D30: =VLOOKUP(sheet1[[#This Row],[Columna1]],sheet13[[Columna1]:[Estado]],4,FALSE) -> Retirado | E30: Aplicación de equipo Librarian | F30: Retirado | G30: E - No Crítica | H30: On Premise | I30: COE de Ingeniería | J30: GUILLERMO GABRIEL DEPRATI | K30: DIEGO PAUL AREVALO COSTALES | L30: FERNANDO VINICIO OCHOA CARRION | M30: Consolas de Administración TI | N30: Usuario Interno | O30: Si | P30: Propio | Q30: Propio | R30: No | S30: No | T30: EVALUADA, NO CUMPLE CRITERIOS
A31: ListaObservados | B31: GOB0013 | C31: =sheet1[[#This Row],[Nombre]]&sheet1[[#This Row],[Bp Id]] -> ListaObservadosGOB0013 | D31: =VLOOKUP(sheet1[[#This Row],[Columna1]],sheet13[[Columna1]:[Estado]],4,FALSE) -> Operativo | E31: Es una aplicación que permite la validación de clientes en listas de validación utilizando componentes de terceros (Bridger). | F31: Operativo | G31: B - Ecosistema Apetito de Riesgo | H31: Nube | I31: AREAS_DE_APOYO | J31: FABIAN GEOVANNI PAZMINO UBIDIA | K31: JOSE LUIS ZAPATA ROSERO | L31: FERNANDO JOSE ROLDAN CORREA | M31: Aplicación del negocio | N31: Usuario Interno | O31: Si | P31: PPRD - SIGLO21 | Q31: Siglo 21 | R31: Si | S31: No
A32: LogiFlow | B32: TIE0019 | C32: =sheet1[[#This Row],[Nombre]]&sheet1[[#This Row],[Bp Id]] -> LogiFlowTIE0019 | D32: =VLOOKUP(sheet1[[#This Row],[Columna1]],sheet13[[Columna1]:[Estado]],4,FALSE) -> Operativo | E32: Portal de aplicaciones para la gestión y administracion de procesos del Banco. | F32: Operativo | G32: C - BIA Crítica | H32: On Premise | I32: ACTIVOS | J32: LAURA ELIZABETH CARRASCO UQUILLAS | K32: ANDREA FERNANDA ORTIZ CISNEROS | L32: ERISLAN MARTINEZ JERA | M32: Aplicación del negocio | N32: Usuario Interno | O32: Si | P32: Active Directory | Q32: Propio | R32: Si | S32: Si | U32: 45200 | V32: CISNEROS MANOSALVAS EDGAR NAPOLEON | W32: MEJIA MANZANO ROMEO OCTAVIO | X32: TERAN PIEDRA DAYANARA ABIGAIL | Y32: ETL | Z32: ETL | AA32: GESTIONAR EN LA APLICACION USUARIOS Y ROLES | AB32: Eliminar | AC32: https://flujoempresaslan.uio.bpichincha.com:8046/Pichincha/WebLogiPortal/
A33: LoginCentral | B33: SEC0028 | C33: =sheet1[[#This Row],[Nombre]]&sheet1[[#This Row],[Bp Id]] -> LoginCentralSEC0028 | D33: =VLOOKUP(sheet1[[#This Row],[Columna1]],sheet13[[Columna1]:[Estado]],4,FALSE) -> Operativo | E33: Aplicación que reemplaza al Portal Empresarial respecto al tema de ingreso a las aplicaciones portalizadas, por esta aplicación permite el logueo a todas las aplicaciones portalizadas que dispone BP, el Login Central consume el serbvicio de WsConexioLdap, pose conexión con una BD de datos BD_TALOS y consume servicios del Process Server. | F33: Operativo | G33: B - Ecosistema Apetito de Riesgo | H33: On Premise | I33: Tribu Ciberseguridad | J33: JUAN FELIPE GALLEGO COSSIO | K33: FRANCISCO DAVID CEVALLOS GRANJA | L33: ROBERTO CARLOS PINO CEDENO | M33: Aplicación del negocio | N33: Usuario Interno | O33: Si | P33: Active Directory | Q33: Active Directory | R33: Si | S33: Si | U33: 45200 | W33: FLORES YAGUANA JHONATAN DAMIAN | X33: AUQUILLA CHINCHIN GLADYS ARACELI | Y33: ETL | Z33: ETL | AA33: GRUPOS AD | AB33: Eliminar | AC33: https://logincentral.bp.bpichincha.com/loginCentralizado/loginCentralizado
A34: Logística de Efectivo | B34: CHL0001 | C34: =sheet1[[#This Row],[Nombre]]&sheet1[[#This Row],[Bp Id]] -> Logística de EfectivoCHL0001 | D34: =VLOOKUP(sheet1[[#This Row],[Columna1]],sheet13[[Columna1]:[Estado]],4,FALSE) -> Operativo | E34: Aplicación que permite controlar el pedido de remesas de efectivo desde las agencias a los centros de acopio. Permite administrar en forma adecuada el proceso de Gestión de Logística de Efectivo y Valorados, desde el registro de la recepción de la solicitud, procesamiento, envío y contabilización de remesas en los centros de acopio, ATM¿s, agencias o sucursales y Banco Central. | F34: Operativo | G34: C - BIA Crítica | H34: On Premise | I34: AREAS_DE_APOYO | J34: FABIAN GEOVANNI PAZMINO UBIDIA | K34: PRISCILA ALEXANDRA PARRA LEON | L34: PRISCILA ALEXANDRA PARRA LEON | M34: Aplicación del negocio | N34: Usuario Interno | O34: Si | P34: Active Directory | Q34: Propio | R34: Si | S34: Si | T34: SIGLO21 | U34: 45199 | W34: LIVE LOZADA EDGAR ROBERTO | X34: PAREDES NACIPUCHA EDISSON FERNANDO
A35: Lumu | B35: SEC0056 | C35: =sheet1[[#This Row],[Nombre]]&sheet1[[#This Row],[Bp Id]] -> LumuSEC0056 | D35: =VLOOKUP(sheet1[[#This Row],[Columna1]],sheet13[[Columna1]:[Estado]],4,FALSE) -> Retirado | E35: Aplicación ciberseguridad que ofrece visibilidad y respuesta a amenazas en tiempo real. | F35: Retirado | G35: E - No Crítica | H35: Nube | I35: Ciberseguridad | J35: GABRIELA VIRGINIA VIDAL BARBA | K35: MARCO FABRICIO FALCONI NORIEGA | L35: lvtandaz@pichincha.com TANDAZO GALLEGOS | M35: Consolas de Administración Seguridad | N35: Usuario Interno | O35: Si | P35: Entra ID | Q35: Entra ID | R35: Si | S35: No
A36: Mail Control System | B36: SUP0012 | C36: =sheet1[[#This Row],[Nombre]]&sheet1[[#This Row],[Bp Id]] -> Mail Control SystemSUP0012 | D36: =VLOOKUP(sheet1[[#This Row],[Columna1]],sheet13[[Columna1]:[Estado]],4,FALSE) -> Operativo | E36: Aplicación utilizada por el área Administrativa para gestionar el proceso de entrega y recepción de correspondencia interna. | F36: Operativo | G36: E - No Crítica | H36: Nube | I36: AREAS_DE_APOYO | J36: FABIAN GEOVANNI PAZMINO UBIDIA | K36: LIZETH AURORA ENCALADA RAMON | L36: ABRAHAM JOSUE MOGOLLON VASQUEZ | M36: Aplicación del negocio | N36: Usuario Interno | O36: No | P36: Entra ID | Q36: Entra ID | R36: Si | S36: No | T36: Realizar la recepción: está planificada_x000D_ Detalle del criterio de recepción:_x000D_ _x000D_ o En base al documento ¿BPECU-SEG-044-STD - Estándar de Recepción de Módulos de Gestión de Accesos y Perfiles V 2.1-¿; donde se definen uno de los criterios para recepción es contar con un módulo de gestión de accesos y perfiles._x000D_ _x000D_ o Luego de una reunión mantenida con el equipo administrador del aplicativo se recibió _x000D_ mediante email el día 11 de marzo de 2026 que la aplicación no cuenta con un módulo _x000D_ para la gestión de accesos. Adicional se tuvieron las siguientes observaciones:_x000D_ _x000D_ o Muzzillo Gustavo - INGENIERO INFRAESTRUCTURA TI menciona que Mail Control System: _x000D_ "no posee un módulo de gestión de Usuarios y Permisos, encontrándose estas funciones delegadas al IDP (EntraID) apoyándose en las herramientas MyAccess y MySessions para la gestión de permisos y claves de usuario respectivamente", de acuerdo con el correo con asunto: RE: Solicitud entrega del aplicativo a Gestión de Identidades: Mail Control System, con fecha 11 de marzo de 2026. | U36: 46092 | V36: MUZZILLO GUSTAVO
A37: Mambu | B37: COR0008 | C37: =sheet1[[#This Row],[Nombre]]&sheet1[[#This Row],[Bp Id]] -> MambuCOR0008 | D37: =VLOOKUP(sheet1[[#This Row],[Columna1]],sheet13[[Columna1]:[Estado]],4,FALSE) -> Retirado | E37: No existe descripción | F37: Retirado | G37: E - No Crítica | H37: Nube | I37: Tribu_Integraciones_Apis | J37: DAVID RODRIGO REVELO RIVERA | K37: GILBERT ADRIAN CISNEROS TELLO | L37: GILBERT ADRIAN CISNEROS TELLO | M37: Aplicación del negocio | N37: Usuario Interno | O37: Si | P37: Entra ID | Q37: Entra ID | R37: Si | S37: No
A38: Mambu Deuna | B38: SEC0057 | C38: =sheet1[[#This Row],[Nombre]]&sheet1[[#This Row],[Bp Id]] -> Mambu DeunaSEC0057 | D38: =VLOOKUP(sheet1[[#This Row],[Columna1]],sheet13[[Columna1]:[Estado]],4,FALSE) -> Retirado | E38: Core bancario de uso exlclusivo para Deuna | F38: Retirado | G38: A - Apetito de Riesgo Disponibilidad | H38: Nube | I38: TRIBU_DE_UNA | J38: LUIS JAVIER MARIDUENA NOVILLO | K38: LUIS JAVIER MARIDUENA NOVILLO | L38: LUIS JAVIER MARIDUENA NOVILLO | M38: Aplicación del negocio | N38: Usuario Interno | O38: Si | P38: Entra ID | Q38: Entra ID | R38: Si | S38: No
A39: MatiBOT | B39: ITM0075 | C39: =sheet1[[#This Row],[Nombre]]&sheet1[[#This Row],[Bp Id]] -> MatiBOTITM0075 | D39: =VLOOKUP(sheet1[[#This Row],[Columna1]],sheet13[[Columna1]:[Estado]],4,FALSE) -> Operativo | E39: Brindar a los usuarios la capacidad de realizar solicitudes a través de una interfaz de chat en diversos canales conversacionales, como Microsoft Teams, Web Chat o WhatsApp. | F39: Operativo | G39: E - No Crítica | H39: Nube | I39: Gerencia Arquitectura Usuario Final | J39: FAYOL SMITH MONTANO MELENDEZ | K39: ABNER ANDY AREVALO BRACAMONTE | L39: CARMEN ROCIO AGUILAR MAYANQUER | M39: Aplicación complementaria | N39: Usuario Interno | O39: Si | P39: Entra ID | Q39: Propio | R39: No | S39: No | T39: EVALUADA, NO CUMPLE CRITERIOS
A40: Maze | B40: EDC0006 | C40: =sheet1[[#This Row],[Nombre]]&sheet1[[#This Row],[Bp Id]] -> MazeEDC0006 | D40: =VLOOKUP(sheet1[[#This Row],[Columna1]],sheet13[[Columna1]:[Estado]],4,FALSE) -> Operativo | E40: Herramienta de pruebas con usuarios de prototipos y encuestas masivas moderadas y no moderadas. | F40: Operativo | G40: E - No Crítica | H40: Nube | I40: COE Experiencia | J40: ANTONIO ALEJANDRO CANAVERAL GIL | K40: GABRIEL ANDRES PACHECO TELLO | L40: GABRIEL ANDRES PACHECO TELLO | M40: Utilitario | N40: Usuario Interno | O40: Si | P40: Propio | Q40: Propio | R40: No | S40: No | T40: EVALUADA, NO CUMPLE CRITERIOS
A41: Mi Campus Pichincha | B41: SUP0033 | C41: =sheet1[[#This Row],[Nombre]]&sheet1[[#This Row],[Bp Id]] -> Mi Campus PichinchaSUP0033 | D41: =VLOOKUP(sheet1[[#This Row],[Columna1]],sheet13[[Columna1]:[Estado]],4,FALSE) -> Operativo | E41: Sistema de gestión de aprendizaje | F41: Operativo | G41: E - No Crítica | H41: Nube | I41: AREAS_DE_APOYO | J41: FABIAN GEOVANNI PAZMINO UBIDIA | K41: ANDREA PAULINA PARDO ULLAGUARI | L41: PRISCILA ALEXANDRA PARRA LEON | M41: Aplicación complementaria | N41: Usuario Interno | O41: Si | P41: Entra ID | Q41: Entra ID | R41: No | S41: No | T41: EVALUADA, NO CUMPLE CRITERIOS
A42: Mi Portal (4u) | B42: SUP0013 | C42: =sheet1[[#This Row],[Nombre]]&sheet1[[#This Row],[Bp Id]] -> Mi Portal (4u)SUP0013 | D42: =VLOOKUP(sheet1[[#This Row],[Columna1]],sheet13[[Columna1]:[Estado]],4,FALSE) -> Operativo | E42: Es una aplicación web desarrollada en Angular y Node JS con base de datos postgres y se encuentra alojada en la nube de Google Cloud. En esta aplicación se disponibiliza para la autogestión del colaborador en temas internos | F42: Operativo | G42: D - BIA No Crítica | H42: Nube | I42: AREAS_DE_APOYO | J42: FABIAN GEOVANNI PAZMINO UBIDIA | K42: ANDREA PAULINA PARDO ULLAGUARI | L42: FRANKLIN STALIN GARZON ANDRADE | M42: Aplicación complementaria | N42: Usuario Interno | O42: No | P42: Propio | Q42: Propio | R42: No | S42: No | T42: Detalle del criterio de recepción: _x000D_ o En base al documento ¿BPECU-SEG-044-STD - Estándar de Recepción de Módulos de Gestión de Accesos y Perfiles V 2.1-¿; donde se definen los criterios para recepción, registra que las aplicaciones administrables deben contar con un módulo de gestión de accesos y perfiles. _x000D_ o Sin embargo: luego de la reunión del 2026/02/10 vía Teams con el equipo administrador del aplicativo se informa y concluye que MI PORTAL no cuenta con un módulo para la gestión de usuarios y perfiles. | U42: 46063
A43: Microcrédito Digital | B43: PRD0053 | C43: =sheet1[[#This Row],[Nombre]]&sheet1[[#This Row],[Bp Id]] -> Microcrédito DigitalPRD0053 | D43: =VLOOKUP(sheet1[[#This Row],[Columna1]],sheet13[[Columna1]:[Estado]],4,FALSE) -> Operativo | E43: Aplicativo para Microcredito en Linea de Microfinanzas | F43: Operativo | G43: E - No Crítica | H43: Nube | I43: MICROFINANZAS | J43: EUDOCIA BEATRIZ VASQUEZ CASTILLO | K43: LAURA ELIZABETH CARRASCO UQUILLAS | L43: ERISLAN MARTINEZ JERA | M43: Aplicación del negocio | N43: Clientes | O43: No | P43: No Aplica | Q43: No Aplica | R43: No | S43: No | T43: EVALUADA, NO CUMPLE CRITERIOS
A44: Microfinance Portal | B44: PRD0063 | C44: =sheet1[[#This Row],[Nombre]]&sheet1[[#This Row],[Bp Id]] -> Microfinance PortalPRD0063 | D44: =VLOOKUP(sheet1[[#This Row],[Columna1]],sheet13[[Columna1]:[Estado]],4,FALSE) -> Operativo | E44: Aplicativo para la aprobación, instrumentación y desembolso de créditos de la metodología Microfinanzas Individual y Grupal | F44: Operativo | G44: E - No Crítica | H44: Nube | I44: MICROFINANZAS | J44: LAURA ELIZABETH CARRASCO UQUILLAS | K44: FREDDY NEY BASTIDAS CALERO | L44: Willam Marcel Ontaneda Yaguana | M44: Aplicación del negocio | N44: Usuario Interno | O44: Si | P44: Entra ID | Q44: Entra ID | R44: Si | S44: No
A45: Mis Riesgos | B45: RIS0008 | C45: =sheet1[[#This Row],[Nombre]]&sheet1[[#This Row],[Bp Id]] -> Mis RiesgosRIS0008 | D45: =VLOOKUP(sheet1[[#This Row],[Columna1]],sheet13[[Columna1]:[Estado]],4,FALSE) -> Operativo | E45: Agrupación lógica de las aplicaciones internas desarrolladas por Banco, que no cuentan con un ambiente controlado, Banco realiza cambios directos y sus actualizaciones no sigue el proceso de control de cambios. | F45: Operativo | G45: E - No Crítica | H45: On Premise | I45: Tribu Administración de Créditos | J45: JORGE MARIO PULGARIN MAZO | K45: JOHANNA NATALIA RODRIGUEZ SANCHEZ | L45: CHRISTIAN PAUL ENRIQUEZ LOPEZ | M45: Aplicación del negocio | N45: Usuario Interno | O45: Si | P45: Propio - MISRIESGOS | Q45: Propio | R45: Si | S45: No
A46: MODELO PREDICTIVO CIIU | B46: DAT0006 | C46: =sheet1[[#This Row],[Nombre]]&sheet1[[#This Row],[Bp Id]] -> MODELO PREDICTIVO CIIUDAT0006 | D46: =VLOOKUP(sheet1[[#This Row],[Columna1]],sheet13[[Columna1]:[Estado]],4,FALSE) -> Operativo | E46: Modelo de Sector y Actividad Económica | F46: Operativo | G46: E - No Crítica | H46: On Premise | I46: COE DATOS&ANALITICA | J46: JAVIER EDUARDO TORRES ALTAMIRANO | K46: ARNALDO UTRIA AZAN | L46: DIEGO EDUARDO GALLARDO CORRALES | M46: Aplicación complementaria | N46: Usuario Interno | O46: Si | P46: Propio | Q46: Propio | R46: No | S46: No | T46: EVALUADA, NO CUMPLE CRITERIOS
A47: Moengage | B47: OMN0001 | C47: =sheet1[[#This Row],[Nombre]]&sheet1[[#This Row],[Bp Id]] -> MoengageOMN0001 | D47: =VLOOKUP(sheet1[[#This Row],[Columna1]],sheet13[[Columna1]:[Estado]],4,FALSE) -> Operativo | E47: Es una plataforma de compromiso del cliente y automatización de marketing que ayuda a las empresas a interactuar con sus usuarios a través de canales como notificaciones push, mensajes dentro de la aplicación, correos electrónicos, mensajes de texto (SMS) y más | F47: Operativo | G47: B - Ecosistema Apetito de Riesgo | H47: Nube | I47: COE de Ingeniería | J47: GUILLERMO GABRIEL DEPRATI | K47: CESAR ALEJANDRO VELASCO TORO | L47: HORACIO LEONEL HOLGUIN ALCIVAR | M47: Aplicación complementaria | N47: Usuario Interno | O47: Si | P47: Propio | Q47: Propio | R47: No | S47: No | T47: EVALUADA, NO CUMPLE CRITERIOS
A48: Monitor BPM | B48: ITM0039 | C48: =sheet1[[#This Row],[Nombre]]&sheet1[[#This Row],[Bp Id]] -> Monitor BPMITM0039 | D48: =VLOOKUP(sheet1[[#This Row],[Columna1]],sheet13[[Columna1]:[Estado]],4,FALSE) -> Retirado | E48: Es software libre, Monitorea los servicios middleware utilizados en BPM | F48: Retirado | G48: E - No Crítica | H48: On Premise | I48: Tribu_Cores_Transacciones | J48: DAVID RODRIGO REVELO RIVERA | K48: ANDREA ESTEFANIA CHAVEZ ORDONEZ | L48: Johanna Elizabeth Carangui Vivar | M48: Aplicación complementaria | N48: Usuario Interno | O48: Si | P48: Propio | Q48: Propio | R48: No | S48: No
A49: Monitor Plus | B49: GOB0005 | C49: =sheet1[[#This Row],[Nombre]]&sheet1[[#This Row],[Bp Id]] -> Monitor PlusGOB0005 | D49: =VLOOKUP(sheet1[[#This Row],[Columna1]],sheet13[[Columna1]:[Estado]],4,FALSE) -> Operativo | E49: Aplicación que permite realizar el monitoreo de las transacciones de clientes para identificación de lavado de dinero y fraude, es de tercero (nombre proveedor plus Holding) implementado en datacenter de Banco. | F49: Operativo | G49: E - No Crítica | H49: Híbrida | I49: AREAS_DE_APOYO | J49: FABIAN GEOVANNI PAZMINO UBIDIA | K49: JOSE LUIS ZAPATA ROSERO | L49: FERNANDO JOSE ROLDAN CORREA | M49: Aplicación complementaria | N49: Usuario Interno | O49: Si | P49: Propio | Q49: Propio | R49: No | S49: No
A50: MonitorATM | B50: CHL0019 | C50: =sheet1[[#This Row],[Nombre]]&sheet1[[#This Row],[Bp Id]] -> MonitorATMCHL0019 | D50: =VLOOKUP(sheet1[[#This Row],[Columna1]],sheet13[[Columna1]:[Estado]],4,FALSE) -> Retirado | E50: Mediante la aplicación de MonitorATM se puede crear ATMS en el sistema y realiza un monitoreo de los ATMs con sus respectivas transacciones. Relación con el Switch de ATM | F50: Retirado | G50: D - BIA No Crítica | H50: On Premise | I50: TRIBU_CANALES | J50: JUAN FELIPE DIAZ RESTREPO | K50: ABNER ANDY AREVALO BRACAMONTE | L50: Nelson Patricio Cardenas Llumiugsi | M50: Aplicación del negocio | N50: Usuario Interno | O50: Si | P50: PPRD - SIGLO21 | Q50: Siglo 21 | R50: Si | S50: No | T50: ADMINISTRACION ELIMINADA
A51: CreditoDistribuidor | B51: PRD0014 | C51: =sheet1[[#This Row],[Nombre]]&sheet1[[#This Row],[Bp Id]] -> CreditoDistribuidorPRD0014 | D51: =VLOOKUP(sheet1[[#This Row],[Columna1]],sheet13[[Columna1]:[Estado]],4,FALSE) -> Operativo | E51: Aplicación web en la Intranet que genera créditos a pequeñas y medianas empresas que se encuentran afiliadas a Banco Pichincha. Se manejan créditos a proveedores y distribuidores basados en una empresa mayorista o ancla, en el caso de créditos a proveedores se deposita en la cuenta de la empresa directamente afiliada a BP y en el caso de créditos a proveedores en la cuenta del proveedor de la empresa afiliada a Banco Pichincha. | F51: Operativo | G51: D - BIA No Crítica | H51: On Premise | I51: Frente de Soluciones Empresariales | J51: LUIS MIGUEL ULLOA MOREIRA | K51: FABRICIO ANTONIO PEREIRA GARCIA | L51: WILLIAM PATRICIO PANCHI SHUGULI | M51: Aplicación del negocio | N51: Usuario Interno | O51: Si | P51: Propio | Q51: Propio | R51: Si | S51: Si | T51: SIGLO21 | U51: 45199 | W51: LIVE LOZADA EDGAR ROBERTO
A52: CreditosCOM | B52: PRD0015 | C52: =sheet1[[#This Row],[Nombre]]&sheet1[[#This Row],[Bp Id]] -> CreditosCOMPRD0015 | D52: =VLOOKUP(sheet1[[#This Row],[Columna1]],sheet13[[Columna1]:[Estado]],4,FALSE) -> Operativo | E52: Aplicación que maneja el flujo de créditos para Crédito Distribuidor. | F52: Operativo | G52: D - BIA No Crítica | H52: On Premise | I52: ACTIVOS | J52: LAURA ELIZABETH CARRASCO UQUILLAS | K52: ANDREA FERNANDA ORTIZ CISNEROS | L52: ERISLAN MARTINEZ JERA | M52: Aplicación del negocio | N52: Usuario Interno | O52: Si | P52: Active Directory | Q52: Propio | R52: Si | S52: Si | T52: Se ingresa por Login Central | U52: 45199 | W52: LIVE LOZADA EDGAR ROBERTO | X52: PAREDES NACIPUCHA EDISSON FERNANDO | AA52: AUTORIZACIÓN: PERFIL SIGLO21_x000D_ ASIGNAR GRUPO AD: GA_LOGINC_CREDITOS_COM | AC52: https://logincentral.bp.bpichincha.com/
A53: CRM (salesforce - Financial services) | B53: CUS0007 | C53: =sheet1[[#This Row],[Nombre]]&sheet1[[#This Row],[Bp Id]] -> CRM (salesforce - Financial services)CUS0007 | D53: =VLOOKUP(sheet1[[#This Row],[Columna1]],sheet13[[Columna1]:[Estado]],4,FALSE) -> Operativo | E53: No existe descripción | F53: Operativo | G53: C - BIA Crítica | H53: Nube | I53: Negocios y Monetización | J53: ANTONIO ALEJANDRO CANAVERAL GIL | K53: JULIEN LOUIS ADRIEN LEREBOULLET | L53: HECTOR EDUARDO JARAMILLO RUALES | M53: Aplicación del negocio | N53: Usuario Interno | O53: Si | P53: Entra ID | Q53: Propio | R53: Si | S53: Si | T53: En temas de reporteria se descarga la información de una carpeta compartida con el responsable de la aplicación | U53: 45200 | W53: ZAMBRANO NUNEZ PAUL SANTIAGO | X53: LIVE LOZADA EDGAR ROBERTO | Y53: ETL | Z53: Externo | AA53: GESTIONAR EN LA APLICACION USUARIOS Y ROLES | AB53: Eliminar | AC53: https://pichincha.my.salesforce.com/_x000D_ Se ingresa con genéricos usrpacrm@pichincha.com - usrpbcrm@pichincha.com ingresar con la contraseña registrada en la Producción y se aprueba el ingreso mediante el authenticator de Windows (app android)
A54: CRM (salesforce - Marketing Cloud) | B54: CUS0008 | C54: =sheet1[[#This Row],[Nombre]]&sheet1[[#This Row],[Bp Id]] -> CRM (salesforce - Marketing Cloud)CUS0008 | D54: =VLOOKUP(sheet1[[#This Row],[Columna1]],sheet13[[Columna1]:[Estado]],4,FALSE) -> Operativo | E54: Es una plataforma de automatización de marketing digital en la nube, parte del ecosistema CRM de Salesforce, diseñada para gestionar campañas multicanal (email, móvil, redes sociales, web). | F54: Operativo | G54: E - No Crítica | H54: Nube | I54: Negocios y Monetización | J54: ANTONIO ALEJANDRO CANAVERAL GIL | K54: SEBASTIAN MUNOZ ANDERSEN | L54: HECTOR EDUARDO JARAMILLO RUALES | M54: Aplicación del negocio | N54: Usuario Interno | O54: Si | P54: Propio | Q54: Propio | R54: Si | S54: Si | U54: 46052 | V54: ANGULO CAMUENDO BRYAN LENIN | W54: LEON NOGUERA YOLANDA AMPARO | X54: ZAMBRANO NUNEZ PAUL SANTIAGO | Y54: Manual | Z54: Manual | AA54: Creación: Sobre un usuario inactivo se procede con la modificación del usuario por temas de licenciamiento del aplictivo. | AB54: Eliminar | AC54: https://mc.s10.exacttarget.com/cloud/#app/Marketing%20Cloud%20Dashboard/?ks=ks
A55: Crowdstrike | B55: SEC0009 | C55: =sheet1[[#This Row],[Nombre]]&sheet1[[#This Row],[Bp Id]] -> CrowdstrikeSEC0009 | D55: =VLOOKUP(sheet1[[#This Row],[Columna1]],sheet13[[Columna1]:[Estado]],4,FALSE) -> Operativo | E55: Ofrece una prevención de amenazas óptima, mediante el uso de inteligencia artificial (AI) y aprendizaje automático (ML) con detección y respuesta avanzada e información sobre amenazas, integrada a través de una consola de gestión altamente intuitiva. | F55: Operativo | G55: C - BIA Crítica | H55: Nube | I55: Ciberseguridad | J55: ERICK DAMIAN RISUENO BENITEZ | K55: MARCO FABRICIO FALCONI NORIEGA | L55: lvtandaz@pichincha.com TANDAZO GALLEGOS | M55: Consolas de Administración Seguridad | N55: Usuario Interno | O55: Si | P55: Entra ID | Q55: Propio | R55: Si | S55: Si | U55: 45715 | W55: ESPINOZA RENGIFO MISCHEL ESTEFANIA | X55: BARAHONA ESPINOSA SANTIAGO ISRAEL | Y55: GRUPO AD | Z55: Manual | AA55: GESTIONAR EN LA APLICACION USUARIOS Y ROLES | AB55: Eliminar | AC55: falcon.crowdstrike.com
A56: Cuadre Atms | B56: SUP0021 | C56: =sheet1[[#This Row],[Nombre]]&sheet1[[#This Row],[Bp Id]] -> Cuadre AtmsSUP0021 | D56: =VLOOKUP(sheet1[[#This Row],[Columna1]],sheet13[[Columna1]:[Estado]],4,FALSE) -> Operativo | E56: Aplicación que dispone de procesos para cuadre de cajeros automáticos (cuadre físico vs reporte del Switch de Servicios ATMs) y conciliación de transacciones en ATMs propios (clientes BP y clientes de otras redes). | F56: Operativo | G56: C - BIA Crítica | H56: On Premise | I56: TRIBU_CANALES | J56: DANIEL PATRICIO PAZ ENRIQUEZ | K56: MILTON PATRICIO MANTILLA CAYO | L56: JUAN FRANCISCO PROCEL MICHILENA | M56: Aplicación del negocio | N56: Usuario Interno | O56: Si | P56: Propio | Q56: Propio | R56: Si | S56: Si | T56: SIGLO21 | U56: 45199 | W56: LIVE LOZADA EDGAR ROBERTO | X56: PAREDES NACIPUCHA EDISSON FERNANDO
A57: Cuenta Digital Personas | B57: CHL0037 | C57: =sheet1[[#This Row],[Nombre]]&sheet1[[#This Row],[Bp Id]] -> Cuenta Digital PersonasCHL0037 | D57: =VLOOKUP(sheet1[[#This Row],[Columna1]],sheet13[[Columna1]:[Estado]],4,FALSE) -> Operativo | E57: APP ONBOARDING, aplicación movil de Banco Pichincha, en la que podrá crear clientes, activar cuentas, crear chequeras. | F57: Operativo | G57: C - BIA Crítica | H57: Nube | I57: PASIVOS Y SEGUROS | J57: LAURA ELIZABETH CARRASCO UQUILLAS | K57: JONATHAN HERNAN ARIAS HERNANDEZ | L57: MANUEL ABELARDO HARO MONTERO | M57: Aplicación complementaria | N57: Clientes / Usuario Interno | O57: No | P57: Entra ID | Q57: Entra ID | R57: No | S57: No | T57: Estimado,_x000D_ _x000D_ En negrita mis respuestas._x000D_ _x000D_ 1. ¿Qué tipo de usuarios acceden a la aplicación? _x000D_ 1. Clientes._x000D_ 2. Colaboradores (Internos)._x000D_ _x000D_ 2. ¿La aplicación cuenta con un módulo de gestión de accesos y perfiles, que permita la administración del ciclo de vida de los usuarios y roles?_x000D_ ¿¿¿¿¿¿No._x000D_ _x000D_ 3. ¿Cuál es el método de Autenticación de la aplicación? _x000D_ Entra ID._x000D_ Propio._x000D_ _x000D_ 4. ¿Cuál es el método de Autorización de la aplicación?_x000D_ 1. Entra ID._x000D_ 1. Propio._x000D_ _x000D_ 5. En base a su expertis en la aplicación ¿Cual considera de las siguientes categorías se ajusta de manera más cercana a la aplicación?_x000D_ a. Aplicación Complementaria: Se refiera a una aplicación que se proporciona como complemento de otra aplicación, permitiendo extender las funciones de otra aplicación o programa sin tener que modificar el código._x000D_ b. Aplicación del Negocio: Son herramientas digitales que facilitan distintas operaciones dentro de los negocios, es decir, aquellas que son esenciales en la ejecución, desarrollando las operaciones del negocio._x000D_ f. Middleware: Software que ofrece servicios y funciones comunes para las aplicaciones.
A58: Cuentas por pagar | B58: SUP0031 | C58: =sheet1[[#This Row],[Nombre]]&sheet1[[#This Row],[Bp Id]] -> Cuentas por pagarSUP0031 | D58: =VLOOKUP(sheet1[[#This Row],[Columna1]],sheet13[[Columna1]:[Estado]],4,FALSE) -> Operativo | E58: Es un por portal donde se visualiza los diferentes documentos de proveedores de banco (facturas, retenciones). Está en un aks de azure | F58: Operativo | G58: E - No Crítica | H58: Nube | I58: AREAS_DE_APOYO | J58: FABIAN GEOVANNI PAZMINO UBIDIA | K58: LIZETH AURORA ENCALADA RAMON | L58: ABRAHAM JOSUE MOGOLLON VASQUEZ | M58: Aplicación complementaria | N58: Usuario Interno | O58: Si | P58: Propio | Q58: Propio | R58: No | S58: No
A59: CXP (Banca Web) | B59: CHL0014 | C59: =sheet1[[#This Row],[Nombre]]&sheet1[[#This Row],[Bp Id]] -> CXP (Banca Web)CHL0014 | D59: =VLOOKUP(sheet1[[#This Row],[Columna1]],sheet13[[Columna1]:[Estado]],4,FALSE) -> Operativo | E59: Nueva banca electrónica con cambios en su tecnología para soportar el crecimiento de Banco Pichincha, así como también para apalancar los objetivos de banco para lograr una aplicación Omnicanal. Permite realizar transacciones y trámites bancarios a través de Internet. Una solucion virtual, digital y electrónica. | F59: Operativo | G59: A - Apetito de Riesgo Disponibilidad | H59: Nube | I59: TRIBU_CANALES | J59: MIGUEL ALEXANDER MEJIA BRONCANO | K59: DIANA PATRICIA CAICEDO RODRIGUEZ | L59: MIGUEL ALEXANDER MEJIA BRONCANO | M59: Aplicación del negocio | N59: Clientes | O59: Si | P59: Propio | Q59: Propio | R59: No | S59: No
A60: CyberArk | B60: SEC0010 | C60: =sheet1[[#This Row],[Nombre]]&sheet1[[#This Row],[Bp Id]] -> CyberArkSEC0010 | D60: =VLOOKUP(sheet1[[#This Row],[Columna1]],sheet13[[Columna1]:[Estado]],4,FALSE) -> Operativo | E60: Aplicación que permite el manejo de cuentas de usuarios privilegiados | F60: Operativo | G60: C - BIA Crítica | H60: On Premise | I60: Ciberseguridad | J60: ROBERT STALIN SOTO CORONEL | K60: MARCO FABRICIO FALCONI NORIEGA | L60: ERICK DAMIAN RISUENO BENITEZ | M60: Consolas de Administración Seguridad | N60: Usuario Interno | O60: Si | P60: Active Directory | Q60: Active Directory | R60: Si | S60: No
A61: DarkTrace | B61: SEC0011 | C61: =sheet1[[#This Row],[Nombre]]&sheet1[[#This Row],[Bp Id]] -> DarkTraceSEC0011 | D61: =VLOOKUP(sheet1[[#This Row],[Columna1]],sheet13[[Columna1]:[Estado]],4,FALSE) -> Operativo | E61: Inspección de tráfico de Red para determinar amenazas de seguridad. Tecnología de inteligencia artificial cibernética de autoaprendizaje que detecta nuevos ataques y amenazas internas en una etapa temprana | F61: Operativo | G61: E - No Crítica | H61: On Premise | I61: Ciberseguridad | J61: MARIA DEL CARMEN PENAHERRERA PLUA | K61: MARCO FABRICIO FALCONI NORIEGA | L61: JORGE XAVIER LUCERO GALLEGOS | M61: Consolas de Administración Seguridad | N61: Usuario Interno | O61: Si | P61: Propio | Q61: Propio | R61: Si | S61: No
A62: DataPower Externo | B62: INT0005 | C62: =sheet1[[#This Row],[Nombre]]&sheet1[[#This Row],[Bp Id]] -> DataPower ExternoINT0005 | D62: =VLOOKUP(sheet1[[#This Row],[Columna1]],sheet13[[Columna1]:[Estado]],4,FALSE) -> Operativo | E62: IBM DataPower es una consola/plataforma de seguridad e integración usada para administrar, proteger y publicar servicios como APIs, SOAP y REST. Permite aplicar políticas de autenticación, autorización, cifrado, firma y validación de mensajes. También se usa como gateway para enrutar, transformar y monitorear tráfico entre aplicaciones y sistemas | F62: Operativo | G62: B - Ecosistema Apetito de Riesgo | H62: On Premise | I62: Tribu_Integraciones_Apis | J62: DAVID RODRIGO REVELO RIVERA | K62: DIEGO VLADIMIR JAYA GUAMANZARA | L62: CHRISTIAN DARIO PASQUEL PARRA | M62: Consolas de Administración TI | N62: Usuario Interno | O62: Si | P62: Propio | Q62: Propio | R62: Si | S62: Si | T62: DataPower Externo se encuentra alojado en servidores DMZ. | U62: 46197 | V62: ESTRELLA HIDALGO FREDDY VINICIO | W62: RAMOS SALAZAR SEBASTIAN MATEO | X62: FLORES YAGUANA JHONATAN DAMIAN | Y62: Manual | Z62: Manual | AA62: Ingresar al nodo y crear al usuario manualmente con una contraseña personalizada. | AB62: Eliminar | AC62: Ingresar por Cyberark, al nodo correspondiente:_x000D_ _x000D_ ECBPDPP3 10.40.4.47 Datapower Nodo 1 Externo DCP_x000D_ ECBPDPP4 10.40.4.48 Datapower Nodo 2 Externo DCP_x000D_ DRECBPDPP3 10.40.4.54 Datapower Nodo 1 Externo DCA_x000D_ DRECBPDPP4 10.40.4.55 Datapower Nodo 2 Externo DCA
A63: Decisión Cloud | B63: ITM0001 | C63: =sheet1[[#This Row],[Nombre]]&sheet1[[#This Row],[Bp Id]] -> Decisión CloudITM0001 | D63: =VLOOKUP(sheet1[[#This Row],[Columna1]],sheet13[[Columna1]:[Estado]],4,FALSE) -> Operativo | E63: No existe descripción | F63: Operativo | G63: E - No Crítica | H63: Nube | I63: Ciberseguridad | J63: ANDY JOSE ANDRADE BRAVO | K63: MARCO FABRICIO FALCONI NORIEGA | L63: CARLOS ANDRES MORALES MALDONADO | M63: Consolas de Administración Seguridad | N63: Usuario Interno | O63: Si | P63: Entra ID | Q63: Entra ID | R63: Si | S63: Si | U63: 46035 | V63: VALLEJO BAQUERO JAIME GIOVANNY | W63: ESPINOZA RENGIFO MISCHEL ESTEFANIA | X63: ZAMBRANO NUNEZ PAUL SANTIAGO | Y63: Manual | Z63: Manual | AA63: GRUPOS CLOUD | AB63: Desactivar | AC63: pichincha.mydecisioncloud.com
A64: Deep Discovery Analyzer | B64: SEC0012 | C64: =sheet1[[#This Row],[Nombre]]&sheet1[[#This Row],[Bp Id]] -> Deep Discovery AnalyzerSEC0012 | D64: =VLOOKUP(sheet1[[#This Row],[Columna1]],sheet13[[Columna1]:[Estado]],4,FALSE) -> Retirado | E64: Proporciona una protección completa, adaptable y extremadamente eficiente, con antimalware, detección y prevención de intrusiones, firewall, protección de aplicaciones Web, supervisión de la integridad e inspección de registros | F64: Retirado | G64: E - No Crítica | H64: On Premise | I64: Ciberseguridad | J64: GABRIELA VIRGINIA VIDAL BARBA | K64: MARCO FABRICIO FALCONI NORIEGA | L64: WILSON FERNANDO RODRIGUEZ TOBAR | M64: Consolas de Administración Seguridad | N64: Usuario Interno | O64: Si | P64: Propio | Q64: Propio | R64: Si | S64: No
A65: Deep Discovery Inspector | B65: SEC0013 | C65: =sheet1[[#This Row],[Nombre]]&sheet1[[#This Row],[Bp Id]] -> Deep Discovery InspectorSEC0013 | D65: =VLOOKUP(sheet1[[#This Row],[Columna1]],sheet13[[Columna1]:[Estado]],4,FALSE) -> Retirado | E65: Proporciona una protección completa, adaptable y extremadamente eficiente, con antimalware, detección y prevención de intrusiones, firewall, protección de aplicaciones Web, supervisión de la integridad e inspección de registros | F65: Retirado | G65: E - No Crítica | H65: On Premise | I65: Ciberseguridad | J65: GABRIELA VIRGINIA VIDAL BARBA | K65: MARCO FABRICIO FALCONI NORIEGA | L65: ERICK DAMIAN RISUENO BENITEZ | M65: Consolas de Administración Seguridad | N65: Usuario Interno | O65: Si | P65: Propio | Q65: Propio | R65: Si | S65: No
A66: Deep Security | B66: SEC0014 | C66: =sheet1[[#This Row],[Nombre]]&sheet1[[#This Row],[Bp Id]] -> Deep SecuritySEC0014 | D66: =VLOOKUP(sheet1[[#This Row],[Columna1]],sheet13[[Columna1]:[Estado]],4,FALSE) -> Operativo | E66: Proporciona una protección completa, adaptable y extremadamente eficiente, con antimalware, detección y prevención de intrusiones, firewall, protección de aplicaciones Web, supervisión de la integridad e inspección de registros | F66: Operativo | G66: E - No Crítica | H66: On Premise | I66: Ciberseguridad | J66: ERICK DAMIAN RISUENO BENITEZ | K66: MARCO FABRICIO FALCONI NORIEGA | L66: ROBERT STALIN SOTO CORONEL | M66: Consolas de Administración Seguridad | N66: Usuario Interno | O66: Si | P66: Active Directory | Q66: Active Directory | R66: Si | S66: Si | T66: SE ELIMINA DENTRO DE LA APLICACION | U66: 45736 | W66: RAMOS SALAZAR SEBASTIAN MATEO | X66: BARAHONA ESPINOSA SANTIAGO ISRAEL | Y66: Manual | Z66: Manual | AA66: GRUPOS AD | AB66: Eliminar | AC66: CYBERARK: ecbpprsi70
A67: Depositarios | B67: CHL0015 | C67: =sheet1[[#This Row],[Nombre]]&sheet1[[#This Row],[Bp Id]] -> DepositariosCHL0015 | D67: =VLOOKUP(sheet1[[#This Row],[Columna1]],sheet13[[Columna1]:[Estado]],4,FALSE) -> Operativo | E67: Conjunto de componentes instalados en los ATM's que permite llevar a cabo los procesos relacionados a cajeros automáticos del Banco del Pichincha./ Sistema de cajeros automáticos de Banco Pichincha | F67: Operativo | G67: E - No Crítica | H67: On Premise | I67: TRIBU_CANALES | J67: DANIEL PATRICIO PAZ ENRIQUEZ | K67: MILTON PATRICIO MANTILLA CAYO | L67: JUAN FRANCISCO PROCEL MICHILENA | M67: Componente | N67: Usuario Interno | O67: Si | P67: Propio | Q67: Propio | R67: No | S67: No
A68: DESIGNSYSTEM | B68: CHL0044 | C68: =sheet1[[#This Row],[Nombre]]&sheet1[[#This Row],[Bp Id]] -> DESIGNSYSTEMCHL0044 | D68: =VLOOKUP(sheet1[[#This Row],[Columna1]],sheet13[[Columna1]:[Estado]],4,FALSE) -> Operativo | E68: Sin descripción | F68: Operativo | G68: E - No Crítica | H68: Nube | I68: TRIBU_CANALES | J68: JUAN FELIPE DIAZ RESTREPO | K68: JORGE ALBERTO VILLAFUERTE GORDILLO | L68: PRICILA VANESSA QUICHIMBO ARMIJOS | M68: Aplicación complementaria | N68: Usuario Interno | O68: Si | P68: Entra ID | Q68: Entra ID | R68: No | S68: No
A69: Detect ID | B69: SEC0015 | C69: =sheet1[[#This Row],[Nombre]]&sheet1[[#This Row],[Bp Id]] -> Detect IDSEC0015 | D69: =VLOOKUP(sheet1[[#This Row],[Columna1]],sheet13[[Columna1]:[Estado]],4,FALSE) -> Operativo | E69: Aplicación para generación de softoken en lugar de OTP enviada por SMS. | F69: Operativo | G69: B - Ecosistema Apetito de Riesgo | H69: On Premise | I69: Tribu Ciberseguridad | J69: ISRAEL SEBASTIAN DE LA TORRE TRUJILLO | K69: Vladimir Stalin Lamina Sanchez | L69: ROBERTO CARLOS PINO CEDENO | M69: Aplicación del negocio | N69: Usuario Interno | O69: Si | P69: Propio | Q69: Propio | R69: Si | S69: Si | T69: REPORTERIA DE USUARIOS SE EXTRAE DEL APLICATIVO | U69: 45200 | V69: ZAMBRANO SOLORZANO FRANKLIN STEVEN | W69: ZAMBRANO NUNEZ PAUL SANTIAGO | X69: BARAHONA ESPINOSA SANTIAGO ISRAEL | Y69: ETL | Z69: Manual | AA69: GESTIONAR EN LA APLICACION USUARIOS Y ROLES | AB69: Eliminar | AC69: Escoger en Username :usrpdck Plataform ID: BP-DetectID2
A70: Deuna Microcomercios | B70: CHL0041 | C70: =sheet1[[#This Row],[Nombre]]&sheet1[[#This Row],[Bp Id]] -> Deuna MicrocomerciosCHL0041 | D70: =VLOOKUP(sheet1[[#This Row],[Columna1]],sheet13[[Columna1]:[Estado]],4,FALSE) -> Operativo | E70: Aplicacion para administracion de microcomercios | F70: Operativo | G70: E - No Crítica | H70: Nube | I70: TRIBU_DE_UNA | J70: LUIS JAVIER MARIDUENA NOVILLO | K70: DIEGO ALBERTO ORDONEZ BARRIOS | L70: LUIS JAVIER MARIDUENA NOVILLO | M70: Consolas de Administración TI | N70: Clientes | O70: Si | P70: Propio | Q70: Propio | R70: No | S70: No
A71: Ansible | B71: TIE0024 | C71: =sheet1[[#This Row],[Nombre]]&sheet1[[#This Row],[Bp Id]] -> AnsibleTIE0024 | D71: =VLOOKUP(sheet1[[#This Row],[Columna1]],sheet13[[Columna1]:[Estado]],4,FALSE) -> Operativo | E71: Ansible Automation platform para automatizar la configuracion de la infrastructura | F71: Operativo | G71: E - No Crítica | H71: On Premise | I71: Gerencia SRE | J71: GONZALO TRANCILLO | K71: GONZALO TRANCILLO | L71: DIANA CRISTINA AVEIGA LOVATO | M71: Consolas de Administración TI | N71: Usuario Interno | O71: Si | P71: Entra ID | Q71: Propio | R71: No | S71: No
A72: AntiDDoS Radware | B72: SEC0052 | C72: =sheet1[[#This Row],[Nombre]]&sheet1[[#This Row],[Bp Id]] -> AntiDDoS RadwareSEC0052 | D72: =VLOOKUP(sheet1[[#This Row],[Columna1]],sheet13[[Columna1]:[Estado]],4,FALSE) -> Operativo | E72: Es un servicio que bloquea ataques volumétricos de las 3 redes públicas / 24 que el banco tiene adquirido | F72: Operativo | G72: B - Ecosistema Apetito de Riesgo | H72: Nube | I72: Ciberseguridad | J72: ROBERT STALIN SOTO CORONEL | K72: MARCO FABRICIO FALCONI NORIEGA | L72: JORGE XAVIER LUCERO GALLEGOS | M72: Consolas de Administración Seguridad | N72: Usuario Interno | O72: Si | P72: Entra ID | Q72: Entra ID | R72: Si | S72: Si | T72: GSC_BP-Radware-Prod_Reader_x000D_ GSC_BP-Radware-Prod_Admins | U72: 46140 | W72: ZAMBRANO NUNEZ PAUL SANTIAGO | X72: LEON NOGUERA YOLANDA AMPARO | AA72: GESTION DE ROLES EN LA APLICACION | AC72: https://radware.eu.auth0.com/authorize?client_id=KnZSRL3CSoahL0ymcqfwsmt55EHxXxgS&response_type=code&connection=IDP-RADWARE&prompt=login&scope=openid%20profile&redirect_uri=https://console.radwarecloud.com?connection=IDP-RADWARE
A73: AntiSpam | B73: SEC0003 | C73: =sheet1[[#This Row],[Nombre]]&sheet1[[#This Row],[Bp Id]] -> AntiSpamSEC0003 | D73: =VLOOKUP(sheet1[[#This Row],[Columna1]],sheet13[[Columna1]:[Estado]],4,FALSE) -> Retirado | E73: AntiSpam | F73: Retirado | G73: E - No Crítica | H73: Nube | I73: Ciberseguridad | J73: GABRIELA VIRGINIA VIDAL BARBA | K73: MARCO FABRICIO FALCONI NORIEGA | L73: GABRIELA VIRGINIA VIDAL BARBA | M73: Consolas de Administración Seguridad | N73: Usuario Interno | O73: Si | P73: Propio | Q73: Propio | R73: Si | S73: No
A74: APEX | B74: SEC0064 | C74: =sheet1[[#This Row],[Nombre]]&sheet1[[#This Row],[Bp Id]] -> APEXSEC0064 | D74: =VLOOKUP(sheet1[[#This Row],[Columna1]],sheet13[[Columna1]:[Estado]],4,FALSE) -> Operativo | E74: Sistema de gestión de eventos de ciberdefensa | F74: Operativo | G74: B - Ecosistema Apetito de Riesgo | H74: Nube | I74: Tribu Ciberseguridad | J74: JUAN FELIPE GALLEGO COSSIO | K74: FRANCISCO DAVID CEVALLOS GRANJA | L74: ROBERTO CARLOS PINO CEDENO | M74: Consolas de Administración Seguridad | N74: Usuario Interno | O74: Si | P74: Propio | Q74: Propio | R74: Si | S74: No
A75: Apigee | B75: INT0004 | C75: =sheet1[[#This Row],[Nombre]]&sheet1[[#This Row],[Bp Id]] -> ApigeeINT0004 | D75: =VLOOKUP(sheet1[[#This Row],[Columna1]],sheet13[[Columna1]:[Estado]],4,FALSE) -> Operativo | E75: No existe dentro del portafolio | F75: Operativo | G75: B - Ecosistema Apetito de Riesgo | H75: Nube | I75: Tribu_Integraciones_Apis | J75: MARICELA NATALY ACUNA GUANOLUISA | K75: PABLO SANTIAGO DELGADO MONCAYO | L75: ANDREA ESTEFANIA CHAVEZ ORDONEZ | M75: Consolas de Administración TI | N75: Usuario Interno | O75: Si | P75: Propio | Q75: Propio | R75: Si | S75: Si | U75: 46007 | V75: ACUNA GUANOLUISA MARICELA NATALY | W75: TERAN PIEDRA DAYANARA ABIGAIL | X75: ESPINOZA RENGIFO MISCHEL ESTEFANIA | Y75: Manual | Z75: Manual | AA75: GESTIONAR EN LA APLICACION USUARIOS Y ROLES | AB75: Eliminar | AC75: https://login.apigee.com/login
A76: APIM | B76: INT0016 | C76: =sheet1[[#This Row],[Nombre]]&sheet1[[#This Row],[Bp Id]] -> APIMINT0016 | D76: =VLOOKUP(sheet1[[#This Row],[Columna1]],sheet13[[Columna1]:[Estado]],4,FALSE) -> Operativo | E76: Servicio de Microsoft Azure API Management. Mantiene la gestión de las APIs, autorización de consumo y analítica de los componentes. | F76: Operativo | G76: B - Ecosistema Apetito de Riesgo | H76: Nube | I76: Tribu_Integraciones_Apis | J76: DAVID RODRIGO REVELO RIVERA | K76: PABLO SANTIAGO DELGADO MONCAYO | L76: JUAN CARLOS CONTRERAS PAREDES | M76: Consolas de Administración TI | N76: Usuario Interno | O76: Si | P76: Entra ID | Q76: Entra ID | R76: Si | S76: Si | T76: Gestión de Accesos Cloud | U76: 46028 | W76: BARAHONA ESPINOSA SANTIAGO ISRAEL | X76: LEON NOGUERA YOLANDA AMPARO | Y76: GRUPO AD | Z76: GRUPO AD | AA76: GRUPOS AD | AB76: Eliminar | AC76: Microsoft Azure
A77: Appsflyer | B77: CUS0001 | C77: =sheet1[[#This Row],[Nombre]]&sheet1[[#This Row],[Bp Id]] -> AppsflyerCUS0001 | D77: =VLOOKUP(sheet1[[#This Row],[Columna1]],sheet13[[Columna1]:[Estado]],4,FALSE) -> Retirado | E77: Ofrece la posibilidad de trackear eventos que acontecen dentro de la aplicación móvil como pueden ser compras y otros objetivos personalizados para el cliente | F77: Retirado | G77: E - No Crítica | H77: Nube | I77: Negocios Digitales (Campañas y Marketing Digital) | J77: ANTONIO ALEJANDRO CANAVERAL GIL | K77: ESTEFANY CAROLINA GONGORA PAREDES | L77: WILLIAM EDUARDO HUERA ORTIZ | M77: Consolas de Administración TI | N77: Usuario Interno | O77: Si | P77: Active Directory | Q77: Active Directory | R77: No | S77: No
A78: Atalla | B78: SEC0004 | C78: =sheet1[[#This Row],[Nombre]]&sheet1[[#This Row],[Bp Id]] -> AtallaSEC0004 | D78: =VLOOKUP(sheet1[[#This Row],[Columna1]],sheet13[[Columna1]:[Estado]],4,FALSE) -> Operativo | E78: Herramienta de generación de llaves de cifrado para la encripción del tráfico usado por varios aplicativos | F78: Operativo | G78: B - Ecosistema Apetito de Riesgo | H78: On Premise | I78: Ciberseguridad | J78: ERICK DAMIAN RISUENO BENITEZ | K78: MARCO FABRICIO FALCONI NORIEGA | L78: ROBERT STALIN SOTO CORONEL | M78: Consolas de Administración Seguridad | N78: Usuario Interno | O78: No | P78: Propio | Q78: Propio | R78: No | S78: No
A79: Athento | B79: TIE0025 | C79: =sheet1[[#This Row],[Nombre]]&sheet1[[#This Row],[Bp Id]] -> AthentoTIE0025 | D79: =VLOOKUP(sheet1[[#This Row],[Columna1]],sheet13[[Columna1]:[Estado]],4,FALSE) -> Operativo | E79: ECM Athento, es una herramienta de gestión de contenido transversal a institución, que cuenta con capacidades de ocr,ia, clasificación entre otras con la finalidad de dar gestión y almacenamiento a documentos | F79: Operativo | G79: E - No Crítica | H79: Terceros | I79: COE_TRANSFORMACION_PROCESOS | J79: JAVIER ENRIQUE RIOS CASTILLO | K79: FREDI ALEXANDER ELIZALDE RODRIGUEZ | L79: SANTIAGO POSADA ZULUAGA | M79: Aplicación del negocio | N79: Usuario Interno | O79: Si | P79: Entra ID | Q79: Propio | R79: Si | S79: Si | U79: 46107 | V79: ELIZALDE RODRIGUEZ FREDI ALEXANDER | W79: RAMOS SALAZAR SEBASTIAN MATEO | Y79: Externo | Z79: Externo | AB79: Desactivar
A80: ATMCampanias | B80: CUS0002 | C80: =sheet1[[#This Row],[Nombre]]&sheet1[[#This Row],[Bp Id]] -> ATMCampaniasCUS0002 | D80: =VLOOKUP(sheet1[[#This Row],[Columna1]],sheet13[[Columna1]:[Estado]],4,FALSE) -> Retirado | E80: Aplicación stand alone la cual permite cargar archivos de información de campañas para ser promocionadas a través de los cajeros automáticos. Es la nueva aplicación | F80: Retirado | G80: E - No Crítica | H80: On Premise | I80: Negocios Digitales (Campañas y Marketing Digital) | J80: ANTONIO ALEJANDRO CANAVERAL GIL | K80: ABNER ANDY AREVALO BRACAMONTE | L80: WILLIAM EDUARDO HUERA ORTIZ | M80: Utilitario | N80: Usuario Interno | O80: Si | P80: Propio | Q80: Propio | R80: No | S80: No
A81: AURO SUITE | B81: COR0003 | C81: =sheet1[[#This Row],[Nombre]]&sheet1[[#This Row],[Bp Id]] -> AURO SUITECOR0003 | D81: =VLOOKUP(sheet1[[#This Row],[Columna1]],sheet13[[Columna1]:[Estado]],4,FALSE) -> Operativo | E81: Sistema que permite gestionar los depósitos a plazo generados en Banco Pichincha por los segmentos de bancas privada, empresarial y preferencial | F81: Operativo | G81: C - BIA Crítica | H81: On Premise | I81: Tribu_Cores_Transacciones | J81: DAVID RODRIGO REVELO RIVERA | K81: EDITH SUSANA ACUNA GARCIA | L81: DAVID RODRIGO REVELO RIVERA | M81: Aplicación del negocio | N81: Usuario Interno | O81: Si | P81: Active Directory | Q81: Active Directory | R81: Si | S81: Si | T81: EXTRAE REPORTE DE USUARIOS DESDE LA APP | U81: 45200 | W81: FLORES YAGUANA JHONATAN DAMIAN | X81: AUQUILLA CHINCHIN GLADYS ARACELI | Y81: ETL | Z81: ETL | AA81: GRUPOS AD | AB81: Eliminar | AC81: https://servicioauro.uio.bpichincha.com:8443/auro
A82: Auth0 | B82: SEC0051 | C82: =sheet1[[#This Row],[Nombre]]&sheet1[[#This Row],[Bp Id]] -> Auth0SEC0051 | D82: =VLOOKUP(sheet1[[#This Row],[Columna1]],sheet13[[Columna1]:[Estado]],4,FALSE) -> Operativo | E82: Auth0, es la nueva aplicación de autenticación para los clientes de canales digitales | F82: Operativo | G82: B - Ecosistema Apetito de Riesgo | H82: Nube | I82: Tribu Ciberseguridad | J82: JUAN FELIPE GALLEGO COSSIO | K82: Vladimir Stalin Lamina Sanchez | L82: ROBERTO CARLOS PINO CEDENO | M82: Consolas de Administración Seguridad | N82: Usuario Interno | O82: Si | P82: Propio | Q82: Propio | R82: No | S82: No | T82: EVALUADO, CUMPLE CRITERIOS, SIN EMBARGO, POR IMPOSIBILIDAD DE SEGREGACIÓN Y SOLICITUD DE SANTIAGO MEDRANDA IDENTIDADES NO ADMINISTRARA. | U82: 46118
A83: Automation Anywhere RPA | B83: TIE0002 | C83: =sheet1[[#This Row],[Nombre]]&sheet1[[#This Row],[Bp Id]] -> Automation Anywhere RPATIE0002 | D83: =VLOOKUP(sheet1[[#This Row],[Columna1]],sheet13[[Columna1]:[Estado]],4,FALSE) -> Retirado | E83: Una automatización robótica de procesos es una forma naciente de automatización de los procesos de negocio que replica las acciones de un ser humano interactuando con la interfaz de usuario de un sistema informático | F83: Retirado | G83: E - No Crítica | H83: On Premise | I83: COE_TRANSFORMACION_PROCESOS | J83: JAVIER ENRIQUE RIOS CASTILLO | K83: DAVID JOEL REVELO BORJA | L83: THALIA ALEJANDRA LOZADA ARELLANO | M83: Componente | N83: Usuario Interno | O83: Si | P83: Entra ID | Q83: Entra ID | R83: No | S83: No
A84: AutorizadorPichincha | B84: SEC0005 | C84: =sheet1[[#This Row],[Nombre]]&sheet1[[#This Row],[Bp Id]] -> AutorizadorPichinchaSEC0005 | D84: =VLOOKUP(sheet1[[#This Row],[Columna1]],sheet13[[Columna1]:[Estado]],4,FALSE) -> Operativo | E84: Aplicación para generar una OTP para que el asesor ejecute la transacción financiera solicitada. | F84: Operativo | G84: E - No Crítica | H84: On Premise | I84: Tribu Ciberseguridad | J84: JUAN FELIPE GALLEGO COSSIO | K84: FRANCISCO DAVID CEVALLOS GRANJA | L84: ROBERTO CARLOS PINO CEDENO | M84: Aplicación complementaria | N84: Usuario Interno | O84: Si | P84: Active Directory | Q84: Active Directory | R84: No | S84: No
A85: AVAYA Aura | B85: ITM0003 | C85: =sheet1[[#This Row],[Nombre]]&sheet1[[#This Row],[Bp Id]] -> AVAYA AuraITM0003 | D85: =VLOOKUP(sheet1[[#This Row],[Columna1]],sheet13[[Columna1]:[Estado]],4,FALSE) -> Retirado | E85: Plataforma de Comuniaciones Unificadas Coorporativa | F85: Retirado | G85: D - BIA No Crítica | H85: On Premise | I85: INFRAESTRUCTURA | J85: BYRON ORLANDO MELENDREZ CABRERA | K85: MAURICIO FERNANDO NAVAS GALLARDO | L85: ROSITA LORENA CHAVEZ CABRERA | M85: Aplicación complementaria | N85: Usuario Interno | O85: Si | P85: Active Directory | Q85: Active Directory | R85: No | S85: No
A86: Azure AD | B86: SEC0048 | C86: =sheet1[[#This Row],[Nombre]]&sheet1[[#This Row],[Bp Id]] -> Azure ADSEC0048 | D86: =VLOOKUP(sheet1[[#This Row],[Columna1]],sheet13[[Columna1]:[Estado]],4,FALSE) -> Operativo | E86: Sincronización Usuarios Office 365 | F86: Operativo | G86: B - Ecosistema Apetito de Riesgo | H86: Nube | I86: INFRAESTRUCTURA | J86: BYRON ORLANDO MELENDREZ CABRERA | K86: MARIO ALBERTO TOSCANO GUANIN | L86: RICHARD FABRICIO BRIONES LAICA | M86: Consolas de Administración Seguridad | N86: Usuario Interno | O86: No | P86: Entra ID | Q86: Entra ID | R86: Si | S86: No
A87: Cheque Image Server (CIS Totem) | B87: CHL0010 | C87: =sheet1[[#This Row],[Nombre]]&sheet1[[#This Row],[Bp Id]] -> Cheque Image Server (CIS Totem)CHL0010 | D87: =VLOOKUP(sheet1[[#This Row],[Columna1]],sheet13[[Columna1]:[Estado]],4,FALSE) -> Operativo | E87: Componente que permite el envío de imágenes de cheques desde cada ATM de Depositario hacia la solución de Canje Digital (CheqScan). | F87: Operativo | G87: B - Ecosistema Apetito de Riesgo | H87: On Premise | I87: TRIBU_CANALES | J87: DANIEL PATRICIO PAZ ENRIQUEZ | K87: MILTON PATRICIO MANTILLA CAYO | L87: JUAN FRANCISCO PROCEL MICHILENA | M87: Aplicación complementaria | N87: Usuario Interno | O87: No | P87: Propio | Q87: Propio | R87: No | S87: No
A88: Cisco Collector | B88: ITM0004 | C88: =sheet1[[#This Row],[Nombre]]&sheet1[[#This Row],[Bp Id]] -> Cisco CollectorITM0004 | D88: =VLOOKUP(sheet1[[#This Row],[Columna1]],sheet13[[Columna1]:[Estado]],4,FALSE) -> Operativo | E88: Herramienta de monitoreo, El Cisco Collector es una herramienta que permite levar el inventario de los equipos Cisco vía SNMP, esta información posteriormente se sincroniza al portal de Cisco NCST donde se puede ver la información de los contratos de soporte por cada equipo, fechas de fin de soporte ETC | F88: Operativo | G88: E - No Crítica | H88: On Premise | I88: INFRAESTRUCTURA | J88: BYRON ORLANDO MELENDREZ CABRERA | K88: MAURICIO FERNANDO NAVAS GALLARDO | L88: HECTOR DAVID CANTOS CEDENO | M88: Consolas de Administración TI | N88: Usuario Interno | O88: Si | P88: Propio | Q88: Propio | R88: No | S88: No
A89: CLIENT PUEX | B89: CHL0012 | C89: =sheet1[[#This Row],[Nombre]]&sheet1[[#This Row],[Bp Id]] -> CLIENT PUEXCHL0012 | D89: =VLOOKUP(sheet1[[#This Row],[Columna1]],sheet13[[Columna1]:[Estado]],4,FALSE) -> Retirado | E89: Aplicación que permite la actualización de pantallas de los ATMs y la extracción de EDCs (logs) de los mismos. | F89: Retirado | G89: E - No Crítica | H89: On Premise | I89: TRIBU_CANALES | J89: JUAN FELIPE DIAZ RESTREPO | K89: MILTON PATRICIO MANTILLA CAYO | L89: Nelson Patricio Cardenas Llumiugsi | M89: Aplicación del negocio | N89: Usuario Interno | O89: Si | P89: GRUPO ACTIVE DIRECTORY | Q89: Active Directory | R89: Si | S89: No
A90: COBIS BANCA COMUNAL | B90: PRD0052 | C90: =sheet1[[#This Row],[Nombre]]&sheet1[[#This Row],[Bp Id]] -> COBIS BANCA COMUNALPRD0052 | D90: =VLOOKUP(sheet1[[#This Row],[Columna1]],sheet13[[Columna1]:[Estado]],4,FALSE) -> Operativo | E90: Gestión de préstamos colectivos. | F90: Operativo | G90: C - BIA Crítica | H90: On Premise | I90: MICROFINANZAS | J90: LAURA ELIZABETH CARRASCO UQUILLAS | K90: MYRIAM ADRIANA YANGUICELA TIPAN | L90: Willam Marcel Ontaneda Yaguana | M90: Aplicación del negocio | N90: Usuario Interno | O90: Si | P90: Propio | Q90: Propio | R90: Si | S90: Si | U90: 45200 | V90: YEPEZ HERRERA SILVIA VIVIANA | W90: BARAHONA ESPINOSA SANTIAGO ISRAEL | X90: ZAMBRANO NUNEZ PAUL SANTIAGO | Y90: ETL | Z90: ETL | AA90: GESTIONAR EN LA APLICACION USUARIOS Y ROLES | AB90: Eliminar | AC90: http://10.21.30.70/microbanx/Default.htm
A91: CollabNet Subversion | B91: ITM0007 | C91: =sheet1[[#This Row],[Nombre]]&sheet1[[#This Row],[Bp Id]] -> CollabNet SubversionITM0007 | D91: =VLOOKUP(sheet1[[#This Row],[Columna1]],sheet13[[Columna1]:[Estado]],4,FALSE) -> Retirado | E91: Herramienta de repositorio de control de versiones | F91: Retirado | G91: E - No Crítica | H91: On Premise | I91: COE de Ingeniería | J91: GERMAN MARTIN GUTIERREZ | K91: GERMAN MARTIN GUTIERREZ | L91: GERMAN MARTIN GUTIERREZ | M91: Consolas de Administración TI | N91: Usuario Interno | O91: Si | P91: Propio | Q91: Propio | R91: No | S91: No
A92: Compass | B92: SEC0076 | C92: =sheet1[[#This Row],[Nombre]]&sheet1[[#This Row],[Bp Id]] -> CompassSEC0076 | D92: =VLOOKUP(sheet1[[#This Row],[Columna1]],sheet13[[Columna1]:[Estado]],4,FALSE) -> Operativo | E92: Sistema de alarmas | F92: Operativo | G92: C - BIA Crítica | H92: On Premise | I92: Ciberseguridad | J92: ANDY JOSE ANDRADE BRAVO | K92: MARCO FABRICIO FALCONI NORIEGA | L92: LUIS ENRIQUE ALVAREZ GARCIA | M92: Consolas de Administración Seguridad | N92: Usuario Interno | O92: Si | P92: Propio | Q92: Propio | R92: Si | S92: Si | T92: Cambiar las contraseñas de los usuarios personalizados periodicamente y enviar por correo ya que no existe el control de caducidad de clave. | U92: 46104 | V92: ANDRADE BRAVO ANDY JOSE | W92: LEON NOGUERA YOLANDA AMPARO | X92: BARAHONA ESPINOSA SANTIAGO ISRAEL | Y92: Manual | Z92: Manual | AA92: GESTIONAR EN LA APLICACION USUARIOS Y ROLES | AB92: Eliminar | AC92: Acceso mediante cybeark_x000D_ Server: 10.70.72.246_x000D_ Hostname: prewsf001
A93: Compensacion | B93: SUP0025 | C93: =sheet1[[#This Row],[Nombre]]&sheet1[[#This Row],[Bp Id]] -> CompensacionSUP0025 | D93: =VLOOKUP(sheet1[[#This Row],[Columna1]],sheet13[[Columna1]:[Estado]],4,FALSE) -> Retirado | E93: Aplicativo encargado de la generación de los archivos para la compensación de empresas de recaudación en CNB's. Frontea la gestión integral y parametrización relacionada con el servicio de compensación general de Banco Pichincha. | F93: Retirado | G93: D - BIA No Crítica | H93: On Premise | I93: EMPRESAS | J93: MIRTHA CATHERINE ARCELA ESPINOZA | K93: GONZALO MARCELO NAZATI GONZALEZ | L93: FRANKLIN HAYBECK SERRANO GOMEZ | M93: Aplicación complementaria | N93: Usuario Interno | O93: Si | P93: Propio | Q93: Propio | R93: Si | S93: Si | T93: SIGLO21 | U93: 45199 | W93: LIVE LOZADA EDGAR ROBERTO | X93: PAREDES NACIPUCHA EDISSON FERNANDO
A94: Compra de Cartera | B94: PRD0013 | C94: =sheet1[[#This Row],[Nombre]]&sheet1[[#This Row],[Bp Id]] -> Compra de CarteraPRD0013 | D94: =VLOOKUP(sheet1[[#This Row],[Columna1]],sheet13[[Columna1]:[Estado]],4,FALSE) -> Operativo | E94: Aplicación que permite realizar la pre-validación de las tramas de información de clientes, operaciones y pagos remitidas por las diversas instituciones que le venden cartera a BP, mismas que una vez se encuentren correctas pasaran a ser procesadas en ambiente de producción; y proporcionar los diferentes reportes definidos y necesarios para el seguimiento y gestión de la Cartera, dentro de BP como desde las Casas Comerciales e Instituciones Financieras y no Financieras. | F94: Operativo | G94: E - No Crítica | H94: On Premise | I94: ACTIVOS | J94: LAURA ELIZABETH CARRASCO UQUILLAS | K94: FABRICIO ANTONIO PEREIRA GARCIA | L94: Carlos Ernesto Bolanos Abad | M94: Aplicación complementaria | N94: Usuario Interno | O94: Si | P94: Propio | Q94: Propio | R94: No | S94: No
A95: Conexión Empresas Online | B95: PAY0005 | C95: =sheet1[[#This Row],[Nombre]]&sheet1[[#This Row],[Bp Id]] -> Conexión Empresas OnlinePAY0005 | D95: =VLOOKUP(sheet1[[#This Row],[Columna1]],sheet13[[Columna1]:[Estado]],4,FALSE) -> Operativo | E95: Front del Sitio Web que permite administrar tarjetas prepago. | F95: Operativo | G95: D - BIA No Crítica | H95: Terceros | I95: MEDIOS_DE_PAGO | J95: EDWIN GEOVANNY FLORES CASTRO | K95: DAVID ALEJANDRO CHAVEZ PENAHERRERA | L95: HENRRY DANIEL MORETA IZA | M95: Aplicación del negocio | N95: Clientes | O95: No | P95: Propio | Q95: Propio | R95: No | S95: No
A96: Conexión Personas Online | B96: PAY0006 | C96: =sheet1[[#This Row],[Nombre]]&sheet1[[#This Row],[Bp Id]] -> Conexión Personas OnlinePAY0006 | D96: =VLOOKUP(sheet1[[#This Row],[Columna1]],sheet13[[Columna1]:[Estado]],4,FALSE) -> Operativo | E96: Front del Sitio Web que permite administrar tarjetas prepago. | F96: Operativo | G96: D - BIA No Crítica | H96: Terceros | I96: MEDIOS_DE_PAGO | J96: EDWIN GEOVANNY FLORES CASTRO | K96: DAVID ALEJANDRO CHAVEZ PENAHERRERA | L96: HENRRY DANIEL MORETA IZA | M96: Aplicación del negocio | N96: Usuario Interno | O96: Si | P96: Propio | Q96: Propio | R96: Si | S96: No
A97: Configuración Centralizada | B97: SEC0008 | C97: =sheet1[[#This Row],[Nombre]]&sheet1[[#This Row],[Bp Id]] -> Configuración CentralizadaSEC0008 | D97: =VLOOKUP(sheet1[[#This Row],[Columna1]],sheet13[[Columna1]:[Estado]],4,FALSE) -> Operativo | E97: Aplicativo que permite la administración de las configuraciones de comunicación de las distintas aplicaciones: servidores, usuarios, cadenas de conexión, bases de datos, servicios. | F97: Operativo | G97: B - Ecosistema Apetito de Riesgo | H97: On Premise | I97: Tribu Ciberseguridad | J97: RODNEY XAVIER JACOME TERAN | K97: FRANCISCO DAVID CEVALLOS GRANJA | L97: ROBERTO CARLOS PINO CEDENO | M97: Consolas de Administración Seguridad | N97: Usuario Interno | O97: No | P97: Active Directory | Q97: Active Directory | R97: Si | S97: Si | U97: 45200 | W97: FLORES YAGUANA JHONATAN DAMIAN | X97: AUQUILLA CHINCHIN GLADYS ARACELI | Y97: ETL | Z97: ETL | AA97: GRUPOS AD | AB97: Eliminar | AC97: http://10.151.12.59/Tcs.ServicioConfiguracion.Web/Paginas/Administracion/Usuarios.aspx
A98: Confluent | B98: OMN0002 | C98: =sheet1[[#This Row],[Nombre]]&sheet1[[#This Row],[Bp Id]] -> ConfluentOMN0002 | D98: =VLOOKUP(sheet1[[#This Row],[Columna1]],sheet13[[Columna1]:[Estado]],4,FALSE) -> Operativo | E98: No existe descripción | F98: Operativo | G98: E - No Crítica | H98: Nube | I98: COE DATOS&ANALITICA | J98: SANTIAGO ALEXANDER CHERREZ RAMIREZ | K98: JOHANNA ELIZABETH CARANGUI VIVAR | L98: DIEGO VLADIMIR JAYA GUAMANZARA | M98: Aplicación complementaria | N98: Usuario Interno | O98: Si | P98: Propio | Q98: Propio | R98: No | S98: No
A99: Control-M | B99: ITM0008 | C99: =sheet1[[#This Row],[Nombre]]&sheet1[[#This Row],[Bp Id]] -> Control-MITM0008 | D99: =VLOOKUP(sheet1[[#This Row],[Columna1]],sheet13[[Columna1]:[Estado]],4,FALSE) -> Operativo | E99: Herramienta Schedule (Calendarización y ejecución de Procesos Batch) | F99: Operativo | G99: C - BIA Crítica | H99: Híbrida | I99: Gerencia Servicios Producción Tecnológica | J99: MARIO SIXTO ZEGARRA OREZZOLI | K99: XAVIER ALEJANDRO JARAMILLO CEVALLOS | L99: HEVER GONZALEZ GARCIA | M99: Consolas de Administración TI | N99: Usuario Interno | O99: Si | P99: Propio | Q99: Propio | R99: Si | S99: No
A100: Copy Services Manager | B100: ITM0009 | C100: =sheet1[[#This Row],[Nombre]]&sheet1[[#This Row],[Bp Id]] -> Copy Services ManagerITM0009 | D100: =VLOOKUP(sheet1[[#This Row],[Columna1]],sheet13[[Columna1]:[Estado]],4,FALSE) -> Operativo | E100: Software Administración de Replicas del Storage | F100: Operativo | G100: C - BIA Crítica | H100: On Premise | I100: INFRAESTRUCTURA | J100: BYRON ORLANDO MELENDREZ CABRERA | K100: NELSON ANDRES POZO YEPEZ | L100: PABLO RAUL CAICEDO ARELLANO | M100: Consolas de Administración TI | N100: Usuario Interno | O100: Si | P100: Propio | Q100: Propio | R100: Si | S100: No
...

Sheet Sheet1
A1: Nombre | B1: Bp Id | C1: Columna1 | D1: Columna2 | E1: Descripcion | F1: Estado | G1: Prioridad | H1: Ubicacion | I1: Equipo Administrado Por | J1: Dueno Aplicacion | K1: Dueno Negocio | L1: Administrado Por | M1: Categoria Identidades | N1: Criterio de inclusion | O1: Tipo Usuario | P1: ¿Existe módulo de gestión de accesos? | Q1: Metodo Autenticacion | R1: Metodo Autorizacion | S1: ¿Cumple criterios de recepción? | T1: Fase | U1: Entregada Identidades | V1: Observacion | W1: Fecha Recepcion | X1: Administrador Aplicativo Externo | Y1: Administrador Aplicativo Identidades Principal | Z1: Administrador Aplicativo Identidades Backup | AA1: Metodo Reporteria Usuarios | AB1: Metodo Reporteria Perfiles Opciones | AC1: Metodo Gestion | AD1: Metodo Baja Usuarios | AE1: Url Acceso
A2: IBM WebSphere Portal | B2: CHL0017 | C2: =sheet13[[#This Row],[Nombre]]&sheet13[[#This Row],[Bp Id]] -> IBM WebSphere PortalCHL0017 | D2: =VLOOKUP(sheet13[[#This Row],[Columna1]],Sheet2!C:S,4,FALSE) -> Operativo | E2: IBM Websphere Portal, es el portal web empresarial que ofrece experiencias sociales altamente personalizadas a los usuarios. Brinda a los usuarios un único punto de acceso a las aplicaciones, servicios, información y conexiones sociales que necesiten. El usuario puede acceder de manera directa a aplicaciones como: BancsLink, Administrador de Remesas, Asesores, Balcones, Cardholder, CreditosCom, Riesgo Global, Reclamos y Requerimientos, BPM, Informes Legales. | F2: Operativo | G2: A - Apetito de Riesgo Disponibilidad | H2: On Premise | I2: TRIBU_CANALES | J2: DANIEL PATRICIO PAZ ENRIQUEZ | K2: JORGE HUMBERTO BRAVO YUNDA | L2: Luis Remigio Bayas Rea | M2: Aplicación del negocio | N2: SI | O2: Usuario Interno | P2: Si | Q2: Active Directory | R2: Active Directory | S2: Si | T2: FASE 0 | U2: No
A3: IBM WSRR | B3: INT0007 | C3: =sheet13[[#This Row],[Nombre]]&sheet13[[#This Row],[Bp Id]] -> IBM WSRRINT0007 | D3: =VLOOKUP(sheet13[[#This Row],[Columna1]],Sheet2!C:S,4,FALSE) -> Retirado | E3: Herramienta que proporciona el registro de servicios y funciones de repositorio para aplicaciones empresariales de arquitectura orientada a servicios (SOA). | F3: Retirado | G3: E - No Crítica | H3: On Premise | I3: Tribu_Integraciones_Apis | J3: DAVID RODRIGO REVELO RIVERA | K3: DIEGO VLADIMIR JAYA GUAMANZARA | L3: DIEGO VLADIMIR JAYA GUAMANZARA | M3: Consolas de Administración TI | N3: NO | O3: Usuario Interno | P3: Si | Q3: Propio | R3: Propio | S3: No | U3: No | V3: EVALUADA, NO CUMPLE CRITERIOS
A4: ICEPanel | B4: ITM0068 | C4: =sheet13[[#This Row],[Nombre]]&sheet13[[#This Row],[Bp Id]] -> ICEPanelITM0068 | D4: =VLOOKUP(sheet13[[#This Row],[Columna1]],Sheet2!C:S,4,FALSE) -> Operativo | E4: Modelado de Arquitectura de Soluciones | F4: Operativo | G4: D - BIA No Crítica | H4: Nube | I4: COE ARQUITECTURA | J4: MAURICIO BLADIMIR AUQUI MIRANDA | K4: LUIS MIGUEL ULLOA MOREIRA | L4: LUIS MIGUEL ULLOA MOREIRA | M4: Aplicación complementaria | N4: SI | O4: Usuario Interno | P4: Si | Q4: Entra ID | R4: Entra ID | S4: No | T4: FASE 0 | U4: No | V4: EVALUADA, NO CUMPLE CRITERIOS
A5: Idera | B5: ITM0035 | C5: =sheet13[[#This Row],[Nombre]]&sheet13[[#This Row],[Bp Id]] -> IderaITM0035 | D5: =VLOOKUP(sheet13[[#This Row],[Columna1]],Sheet2!C:S,4,FALSE) -> Operativo | E5: Es una aplicación para administrar motores SQL, donde se visualiza eventos que ocurran en las bases de datos como en el servidor | F5: Operativo | G5: D - BIA No Crítica | H5: On Premise | I5: INFRAESTRUCTURA | J5: BYRON ORLANDO MELENDREZ CABRERA | K5: NELSON ANDRES POZO YEPEZ | L5: FELIX ALEXANDER MANJARRES QUEZADA | M5: Consolas de Administración TI | N5: SI | O5: Usuario Interno | P5: Si | Q5: Propio | R5: Propio | S5: Si | T5: FASE 0 | U5: No | AE5: Conectarse a Idera y sacar los scripts de migración es_x000D_ Test: POECWDB064
A6: IGNITION | B6: ITM0069 | C6: =sheet13[[#This Row],[Nombre]]&sheet13[[#This Row],[Bp Id]] -> IGNITIONITM0069 | D6: =VLOOKUP(sheet13[[#This Row],[Columna1]],Sheet2!C:S,4,FALSE) -> Operativo | E6: Monitoreo de las facilidades de los centros de datos, Sistemas Electricos, Enfriamiento, Electrogenos | F6: Operativo | G6: C - BIA Crítica | H6: On Premise | I6: INFRAESTRUCTURA | J6: BYRON ORLANDO MELENDREZ CABRERA | K6: DIEGO JAVIER SALAZAR MOLINA | L6: DIEGO PAUL BETANCOURT REYES | M6: Aplicación complementaria | N6: SI | O6: Usuario Interno | P6: Si | Q6: Propio | R6: Propio | S6: No | T6: FASE 0 | U6: No | V6: EVALUADA, NO CUMPLE CRITERIOS
A7: ILMT | B7: ITM0036 | C7: =sheet13[[#This Row],[Nombre]]&sheet13[[#This Row],[Bp Id]] -> ILMTITM0036 | D7: =VLOOKUP(sheet13[[#This Row],[Columna1]],Sheet2!C:S,4,FALSE) -> Operativo | E7: Monitoreo de Software IBM instalado en servidores licenciamiento | F7: Operativo | G7: E - No Crítica | H7: On Premise | I7: INFRAESTRUCTURA | J7: BYRON ORLANDO MELENDREZ CABRERA | K7: HORACIO LEONEL HOLGUIN ALCIVAR | L7: FREDDY VINICIO ESTRELLA HIDALGO | M7: Consolas de Administración TI | N7: SI | O7: Usuario Interno | P7: Si | Q7: Propio | R7: Propio | S7: No | T7: FASE 0 | U7: No | V7: EVALUADA, NO CUMPLE CRITERIOS
A8: Impacto 360 | B8: DAT0015 | C8: =sheet13[[#This Row],[Nombre]]&sheet13[[#This Row],[Bp Id]] -> Impacto 360DAT0015 | D8: =VLOOKUP(sheet13[[#This Row],[Columna1]],Sheet2!C:S,4,FALSE) -> Operativo | E8: la iniciativa es una plataforma de inteligencia empresarial y análisis de mercado con un enfoque específico en los clientes que utilizan medios de pago del Banco Pichincha (tarjetas de crédito, tarjetas de débito y transferencias digitales). Esta plataforma brinda a los empresarios la capacidad de acceder y visualizar información histórica y resumida de estos clientes, permitiéndoles obtener una visión más detallada y específica de su base de clientes y sus comportamientos de pago. | F8: Operativo | G8: E - No Crítica | H8: Nube | I8: Negocios y Monetización | J8: ANTONIO ALEJANDRO CANAVERAL GIL | K8: SEBASTIAN MUNOZ ANDERSEN | L8: HEVER GONZALEZ GARCIA | M8: Aplicación del negocio | N8: NO | O8: Clientes | P8: Si | Q8: Entra ID | R8: Entra ID | S8: No | U8: No | V8: EVALUADA, NO CUMPLE CRITERIOS
A9: Impresion Documentos | B9: TIE0018 | C9: =sheet13[[#This Row],[Nombre]]&sheet13[[#This Row],[Bp Id]] -> Impresion DocumentosTIE0018 | D9: =VLOOKUP(sheet13[[#This Row],[Columna1]],Sheet2!C:S,4,FALSE) -> Operativo | E9: Aplicación que permite levantar documentos de word ejecutando macros. Genera documentos entregados a los clientes, principalmente de solicitudes de crédito. | F9: Operativo | G9: E - No Crítica | H9: On Premise | I9: ACTIVOS | J9: LAURA ELIZABETH CARRASCO UQUILLAS | K9: ANDREA FERNANDA ORTIZ CISNEROS | L9: ERISLAN MARTINEZ JERA | M9: Aplicación del negocio | N9: SI | O9: Usuario Interno | P9: Si | Q9: Active Directory | R9: Propio | S9: Si | U9: Si | V9: Se ingresa por Login Central | W9: 45199 | AC9: AUTORIZACION: PERFIL SIGLO21_x000D_ ASIGNAR GRUPO DE AD: GA_LOGINC_IMPRESION DE DOCUMENTOS | AE9: https://logincentral.bp.bpichincha.com/
A10: Informes de RedTeam | B10: SEC0083 | C10: =sheet13[[#This Row],[Nombre]]&sheet13[[#This Row],[Bp Id]] -> Informes de RedTeamSEC0083 | D10: =VLOOKUP(sheet13[[#This Row],[Columna1]],Sheet2!C:S,4,FALSE) -> Retirado | E10: Herramienta permite la generación automatizada de informes a través de plantillas, además de ofrecer un control centralizado de los hallazgos obtenidos durante los ejercicios ofensivos. Versión v4.2.5, released 9 August 2024, con soporte Local. Se adjunta la certificación de software por ciberseguridad para poder ser utilizado en entono Banco. | F10: Retirado | G10: E - No Crítica | H10: Nube | I10: COE_SEGURIDAD | J10: SANTIAGO ANDRES MEDRANDA MOREJON | K10: JOHNATAN SILVA ORREGO | L10: Allan Paul Gomez Ehmig | M10: Consolas de Administración Seguridad | N10: NO | O10: Usuario Interno | P10: Si | Q10: Active Directory | R10: Active Directory | S10: Si | U10: No | V10: Se hizo una revisión con Arq. de Cyberseguridad y se va a replantear la solución para construir esta aplicación sobre la plataforma de sharepoint en vez de usar software libre, por lo que algunos de los criterios de respuesta podrán cambiar.
A11: informesCredito | B11: PRD0021 | C11: =sheet13[[#This Row],[Nombre]]&sheet13[[#This Row],[Bp Id]] -> informesCreditoPRD0021 | D11: =VLOOKUP(sheet13[[#This Row],[Columna1]],Sheet2!C:S,4,FALSE) -> Operativo | E11: Aplicación utilizada por las empresas que contratan el servicio para ver referencias bancarias de los clientes del Banco del Pichincha, pueden ver la cantidad de cifras, altas o bajas de sus cuentas, clientes como Dinners, Artefacta, Movistar lo utilizan. Cada consulta de los clientes tiene un costo. | F11: Operativo | G11: E - No Crítica | H11: Nube | I11: Frente de Soluciones Empresariales | J11: LUIS MIGUEL ULLOA MOREIRA | K11: FABRICIO ANTONIO PEREIRA GARCIA | L11: WILLIAM PATRICIO PANCHI SHUGULI | M11: Aplicación del negocio | N11: SI | O11: Usuario Interno | P11: No | Q11: Propio | R11: Propio | S11: Si | U11: Si | V11: SIGLO21 | W11: 45199
A12: Integration Bus Soporte | B12: INT0009 | C12: =sheet13[[#This Row],[Nombre]]&sheet13[[#This Row],[Bp Id]] -> Integration Bus SoporteINT0009 | D12: =VLOOKUP(sheet13[[#This Row],[Columna1]],Sheet2!C:S,4,FALSE) -> Operativo | E12: Integration Bus permite administrar y monitorear los flujos de integración que conectan múltiples canales digitales y sistemas backend. Facilita la gestión de servicios, procesamiento de mensajes y orquestación de transacciones entre aplicaciones. Es un componente clave para asegurar la operación continua y la integración eficiente en arquitecturas omnicanal. | F12: Operativo | G12: B - Ecosistema Apetito de Riesgo | H12: On Premise | I12: Tribu_Integraciones_Apis | J12: DAVID RODRIGO REVELO RIVERA | K12: DIEGO VLADIMIR JAYA GUAMANZARA | L12: DIEGO VLADIMIR JAYA GUAMANZARA | M12: Consolas de Administración TI | N12: SI | O12: Usuario Interno | P12: Si | Q12: Propio | R12: Propio | S12: Si | U12: Si | W12: 46197 | X12: ESTRELLA HIDALGO FREDDY VINICIO | Y12: FLORES YAGUANA JHONATAN DAMIAN | Z12: RAMOS SALAZAR SEBASTIAN MATEO | AA12: Manual | AB12: Manual | AC12: Ingresar al nodo (servidor Unix) correspondiente mediante Cyberark utilizando el usuario root y ejecutar los comandos detallados en el instructivo para administrar usuarios | AD12: Eliminar | AE12: APLICACIÓN HOSTNAME IP_x000D_ Integration Bus Soporte Nodo1 PRECBPIB01 10.151.152.221_x000D_ Integration Bus Soporte Nodo2 PRECBPIB02 10.151.152.222_x000D_ Integration Bus Soporte Cash 1 PRECBPIB10 10.151.152.227_x000D_ Integration Bus Soporte Cash 2 PRECBPIB11 10.151.152.226
A13: Interaction Studio | B13: CUS0010 | C13: =sheet13[[#This Row],[Nombre]]&sheet13[[#This Row],[Bp Id]] -> Interaction StudioCUS0010 | D13: =VLOOKUP(sheet13[[#This Row],[Columna1]],Sheet2!C:S,4,FALSE) -> Retirado | E13: Es una herramienta de Salesforce Marketing Cloud que aprende de los datos de manera automática para lograr identificar las siguientes mejores ofertas y/o acciones para cada cliente | F13: Retirado | G13: E - No Crítica | H13: Nube | I13: Negocios Digitales (Campañas y Marketing Digital) | J13: ANTONIO ALEJANDRO CANAVERAL GIL | K13: IVANNA MARIA ZAUZICH POSADA | L13: FREDDY LEONARDO ABAD LEON | M13: Aplicación complementaria | N13: NO | O13: Usuario Interno | P13: Si | Q13: Propio | R13: Propio | S13: No | U13: No | V13: EVALUADA, NO CUMPLE CRITERIOS
A14: Interdin AS400 Gestor | B14: PAY0008 | C14: =sheet13[[#This Row],[Nombre]]&sheet13[[#This Row],[Bp Id]] -> Interdin AS400 GestorPAY0008 | D14: =VLOOKUP(sheet13[[#This Row],[Columna1]],Sheet2!C:S,4,FALSE) -> Retirado | E14: No existe descripción | F14: Retirado | G14: C - BIA Crítica | H14: Terceros | I14: MEDIOS_DE_PAGO | J14: DIEGO MANUEL CARRERA BENAVIDES | K14: KATHERINE FATIMA CJURO VERA | L14: JEAN ANEL PROANO FALCONES | M14: Aplicación del negocio | N14: NO | O14: Usuario Interno | P14: No | Q14: Propio | R14: Propio | S14: No | U14: No | V14: REPORTERIA: CORREO A EXTERNO LUEGO SUBIR A GEMA | W14: 45200 | Y14: PAREDES NACIPUCHA EDISSON FERNANDO | Z14: ALVARADO RAMOS OLGER OSWALDO | AA14: ETL | AB14: ETL | AC14: CREAR TICKET | AD14: Eliminar
A15: Interdin Autorizador CAO | B15: PAY0009 | C15: =sheet13[[#This Row],[Nombre]]&sheet13[[#This Row],[Bp Id]] -> Interdin Autorizador CAOPAY0009 | D15: =VLOOKUP(sheet13[[#This Row],[Columna1]],Sheet2!C:S,4,FALSE) -> Retirado | E15: No existe descripción | F15: Retirado | G15: C - BIA Crítica | H15: Terceros | I15: MEDIOS_DE_PAGO | J15: DIEGO MANUEL CARRERA BENAVIDES | K15: ELIANA ESTEFANIA CARRION ALVARADO | L15: JEAN ANEL PROANO FALCONES | M15: Aplicación del negocio | N15: NO | O15: Usuario Interno | P15: No | Q15: Propio | R15: Propio | S15: No | U15: No | V15: CREAR TICKET A INTERDIN PARA SOLICITAR REPORTES DE USUARIO Y PERFILES | W15: 45200 | Y15: PAREDES NACIPUCHA EDISSON FERNANDO | Z15: ALVARADO RAMOS OLGER OSWALDO | AA15: ETL | AB15: ETL | AC15: CREAR TICKET | AD15: Eliminar
A16: Interdin AS 400/ CAO | B16: PAY0010 | C16: =sheet13[[#This Row],[Nombre]]&sheet13[[#This Row],[Bp Id]] -> Interdin AS 400/ CAOPAY0010 | D16: =VLOOKUP(sheet13[[#This Row],[Columna1]],Sheet2!C:S,4,FALSE) -> Operativo | E16: No existe descripción | F16: Operativo | G16: C - BIA Crítica | H16: Terceros | I16: MEDIOS_DE_PAGO | J16: EDWIN GEOVANNY FLORES CASTRO | K16: KATHERINE FATIMA CJURO VERA | L16: JEAN ANEL PROANO FALCONES | M16: Aplicación del negocio | N16: SI | O16: Usuario Interno | P16: Si | Q16: Propio | R16: Propio | S16: Si | U16: Si | V16: PIVI/CAO | W16: 45199
A17: Interdin Servicios Integración | B17: PAY0011 | C17: =sheet13[[#This Row],[Nombre]]&sheet13[[#This Row],[Bp Id]] -> Interdin Servicios IntegraciónPAY0011 | D17: =VLOOKUP(sheet13[[#This Row],[Columna1]],Sheet2!C:S,4,FALSE) -> Operativo | E17: INTERDIN SERVICIOS INTEGRACION comprende dos servidores que fueron creados para _x000D_ relacionar servicios de Interdin (Proveedor). | F17: Operativo | G17: B - Ecosistema Apetito de Riesgo | H17: Terceros | I17: MEDIOS_DE_PAGO | J17: EDWIN GEOVANNY FLORES CASTRO | K17: WILLIAM RICHARD CORREA JIMENEZ | L17: DAVID DE JESUS BELLO NIEVES | M17: Componente | N17: NO | O17: Usuario Interno | P17: No | Q17: Propio | R17: Propio | S17: No | U17: No | V17: EVALUADO: NO APLICA RECEPCION_x000D_ Descripción del aplicativo: _x000D_ o INTERDIN SERVICIOS INTEGRACION comprende dos servidores que fueron creados para _x000D_ relacionar servicios de Interdin (Proveedor)._x000D_ o En base al documento ¿BPECU-SEG-044-STD - Estándar de Recepción de Módulos de _x000D_ Gestión de Accesos y Perfiles V 2.1-¿; donde se definen uno de los criterios para recepción _x000D_ es contar con un módulo de gestión de accesos y perfiles. _x000D_ _x000D_ o En la reunión mantenida el jueves 20 de noviembre 2025 en conjunto con el equipo _x000D_ administrador del aplicativo, se concluyó que: ¿Interdin Servicios Integración no es una _x000D_ aplicación, son dos servidores que están relacionados a la aplicación de manera _x000D_ incorrecta. No cuenta con módulo de gestión de usuarios ni perfiles, por lo cual no aplica _x000D_ realizar un proceso de recepción¿. Adicional, se tuvieron las siguientes observaciones: _x000D_ _x000D_ o Edwin Geovanny Flores Castro - LIDER TECNICO DE TRIBU menciona: ¿Más adelante _x000D_ procederé a decomisarla cuando apague los servidores¿, de acuerdo con el correo con _x000D_ asunto: Re: Solicitud entrega del aplicativo a Gestión de Identidades: INTERDIN SERVICIOS _x000D_ INTEGRACION, con fecha 20 de noviembre de 2025. _x000D_ _x000D_ o Se realiza la consulta sobre la fecha de apagado y si existe alguna aplicación en su _x000D_ reemplazo, a lo que Edwin Geovanny Flores Castro - LIDER TECNICO DE TRIBU menciona: _x000D_ ¿Aún no tengo esa información. De momento esta aplicación no es prioritaria para la _x000D_ tribu¿._x000D_ o En referencia a la gestión de usuarios y perfiles: Edwin Geovanny Flores Castro - LIDER _x000D_ TECNICO DE TRIBU menciona: ¿la aplicación en mención no tiene roles ni usuarios¿. | W17: 45981 | X17: FLORES CASTRO EDWIN GEOVANNY
A18: Inversiones | B18: PRD0060 | C18: =sheet13[[#This Row],[Nombre]]&sheet13[[#This Row],[Bp Id]] -> InversionesPRD0060 | D18: =VLOOKUP(sheet13[[#This Row],[Columna1]],Sheet2!C:S,4,FALSE) -> Operativo | E18: Aplicacion para venta y postventa de Inversiones. | F18: Operativo | G18: E - No Crítica | H18: Nube | I18: PASIVOS Y SEGUROS | J18: LAURA ELIZABETH CARRASCO UQUILLAS | K18: JONATHAN HERNAN ARIAS HERNANDEZ | L18: MANUEL ABELARDO HARO MONTERO | M18: Aplicación del negocio | N18: NO | O18: Clientes | P18: No | Q18: Entra ID | R18: Entra ID | S18: No | U18: No | V18: Detalle del criterio de recepción:_x000D_ _x000D_ o En base al documento ¿BPECU-SEG-044-STD - Estándar de Recepción de Módulos de Gestión de Accesos y Perfiles V 2.1-¿; donde se definen uno de los criterios para recepción es contar con un módulo de gestión de accesos y perfiles. _x000D_ _x000D_ o En la reunión mantenida el lunes 24 de marzo de 2026 en conjunto con el equipo administrador del aplicativo, se concluyó que: que la aplicación no cuenta con un módulo para la gestión de accesos._x000D_ _x000D_ o Loaiza Armijos Mayi Dayali - EXPERTO PORTAFOLIO PRODUCTOS Y SERVICIOS Nos informa _x000D_ que el acceso es a través de la banca web y va dirigido a clientes finales. _x000D_ _x000D_ o Cabe mencionar que el acceso al módulo de Inversiones dentro del Portal de la Banca Web _x000D_ es de autogestión; es decir, lo realiza directamente el cliente final sin la intervención de _x000D_ ningún asesor. | W18: 46107 | X18: CARRASCO UQUILLAS LAURA ELIZABETH
A19: IPS Intrusion Prevention System | B19: SEC0025 | C19: =sheet13[[#This Row],[Nombre]]&sheet13[[#This Row],[Bp Id]] -> IPS Intrusion Prevention SystemSEC0025 | D19: =VLOOKUP(sheet13[[#This Row],[Columna1]],Sheet2!C:S,4,FALSE) -> Operativo | E19: Cisco Firepower Management Center 4600 | F19: Operativo | G19: C - BIA Crítica | H19: On Premise | I19: Plataformas Ciberseguridad | J19: ERICK DAMIAN RISUENO BENITEZ | K19: MARCO FABRICIO FALCONI NORIEGA | L19: JORGE XAVIER LUCERO GALLEGOS | M19: Consolas de Administración Seguridad | N19: SI | O19: Usuario Interno | P19: Si | Q19: Active Directory | R19: Propio | S19: Si | U19: Si | W19: 45929 | X19: RISUENO BENITEZ ERICK DAMIAN | Y19: ZAMBRANO NUNEZ PAUL SANTIAGO | Z19: RAMOS SALAZAR SEBASTIAN MATEO | AA19: Manual | AB19: Manual | AC19: GESTIONAR EN LA APLICACION USUARIOS Y ROLES | AE19: Cybeark: _x000D_ https://10.70.88.105/
A20: ISE | B20: SEC0026 | C20: =sheet13[[#This Row],[Nombre]]&sheet13[[#This Row],[Bp Id]] -> ISESEC0026 | D20: =VLOOKUP(sheet13[[#This Row],[Columna1]],Sheet2!C:S,4,FALSE) -> Operativo | E20: CONTROL DE ACCESO A LA RED | F20: Operativo | G20: C - BIA Crítica | H20: On Premise | I20: Plataformas Ciberseguridad | J20: JORGE XAVIER LUCERO GALLEGOS | K20: MARCO FABRICIO FALCONI NORIEGA | L20: ROBERT STALIN SOTO CORONEL | M20: Consolas de Administración Seguridad | N20: SI | O20: Usuario Interno | P20: Si | Q20: Active Directory | R20: Active Directory | S20: Si | U20: Si | W20: 45772 | X20: LUCERO GALLEGOS JORGE XAVIER | Y20: ALVARADO BORJA JORGE ESTEBAN | Z20: BARAHONA ESPINOSA SANTIAGO ISRAEL | AA20: Manual | AB20: Manual | AC20: Generar un ticket en el flujo: "Gestión de Acceso a la Red"; junto con la autorización de Jorge Lucero | AD20: Eliminar | AE20: Cyberark: 10.70.88.110
A21: Jaguar Liquidez Plus | B21: PRD0022 | C21: =sheet13[[#This Row],[Nombre]]&sheet13[[#This Row],[Bp Id]] -> Jaguar Liquidez PlusPRD0022 | D21: =VLOOKUP(sheet13[[#This Row],[Columna1]],Sheet2!C:S,4,FALSE) -> Retirado | E21: En portafolio | F21: Retirado | G21: E - No Crítica | H21: Nube | I21: Frente de Soluciones Empresariales | J21: LUIS MIGUEL ULLOA MOREIRA | K21: FABRICIO ANTONIO PEREIRA GARCIA | L21: WILLIAM PATRICIO PANCHI SHUGULI | M21: Aplicación del negocio | N21: NO | O21: Usuario Interno | P21: No | Q21: Entra ID | R21: Entra ID | S21: Si | U21: No | V21: ADMINISTRACION ELIMINADA | AC21: Crear un ticket
A22: Jenkins | B22: ITM0037 | C22: =sheet13[[#This Row],[Nombre]]&sheet13[[#This Row],[Bp Id]] -> JenkinsITM0037 | D22: =VLOOKUP(sheet13[[#This Row],[Columna1]],Sheet2!C:S,4,FALSE) -> Retirado | E22: Herramienta de integración continua, utilizado por el proyecto de Omnicanalidad. | F22: Retirado | G22: E - No Crítica | H22: On Premise | I22: COE de Ingeniería | J22: GERMAN MARTIN GUTIERREZ | K22: GERMAN MARTIN GUTIERREZ | L22: GERMAN MARTIN GUTIERREZ | M22: Consolas de Administración TI | N22: NO | O22: Usuario Interno | P22: Si | Q22: Propio | R22: Propio | S22: No | U22: No | V22: EVALUADA, NO CUMPLE CRITERIOS
A23: Kafka | B23: OMN0004 | C23: =sheet13[[#This Row],[Nombre]]&sheet13[[#This Row],[Bp Id]] -> KafkaOMN0004 | D23: =VLOOKUP(sheet13[[#This Row],[Columna1]],Sheet2!C:S,4,FALSE) -> Operativo | E23: Basado en una transmisión de evetos,captura datos en tiempo real desde varias fuentes, enruta los flujos de datos a diferentes tecnologías de destino según sea necesario. | F23: Operativo | G23: B - Ecosistema Apetito de Riesgo | H23: On Premise | I23: Tribu_Integraciones_Apis | J23: DAVID RODRIGO REVELO RIVERA | K23: DIEGO VLADIMIR JAYA GUAMANZARA | L23: DIEGO VLADIMIR JAYA GUAMANZARA | M23: Consolas de Administración TI | N23: SI | O23: Usuario Interno | P23: No | Q23: Propio | R23: Propio | S23: No | T23: FASE 0 | U23: No | V23: EVALUADO_x000D_ Descripción del aplicativo: _x000D_ o Es una plataforma basada en una transmisión de eventos, captura datos en tiempo real _x000D_ desde varias fuentes, enruta los flujos de datos a diferentes tecnologías de destino según _x000D_ sea necesario._x000D_ Detalle del criterio de recepción: _x000D_ o En base al documento ¿BPECU-SEG-044-STD - Estándar de Recepción de Módulos de _x000D_ Gestión de Accesos y Perfiles V 2.1-¿; donde se definen uno de los criterios para recepción _x000D_ es contar con un módulo de gestión de accesos y perfiles. _x000D_ o Sin embargo: luego de la reunión del 2025/11/24 vía Teams con el equipo administrador _x000D_ del aplicativo informa que Kafka no cuenta con un módulo para la gestión de usuarios y _x000D_ perfiles. | W23: 45986 | X23: VALLEJO SOLORZANO OSCAR DAVID
A24: Kafka Deuna | B24: INT0014 | C24: =sheet13[[#This Row],[Nombre]]&sheet13[[#This Row],[Bp Id]] -> Kafka DeunaINT0014 | D24: =VLOOKUP(sheet13[[#This Row],[Columna1]],Sheet2!C:S,4,FALSE) -> Retirado | E24: Broker de eventos de Deuna desplegado en AWS | F24: Retirado | G24: D - BIA No Crítica | H24: Nube | I24: TRIBU_DE_UNA | J24: LUIS JAVIER MARIDUENA NOVILLO | K24: LUIS JAVIER MARIDUENA NOVILLO | L24: LUIS JAVIER MARIDUENA NOVILLO | M24: Consolas de Administración TI | N24: NO | O24: Usuario Interno | P24: Si | Q24: Entra ID | R24: Entra ID | S24: Si | U24: No
A25: Keeper Security | B25: SEC0053 | C25: =sheet13[[#This Row],[Nombre]]&sheet13[[#This Row],[Bp Id]] -> Keeper SecuritySEC0053 | D25: =VLOOKUP(sheet13[[#This Row],[Columna1]],Sheet2!C:S,4,FALSE) -> Operativo | E25: Solución para la gestión de contraseñas de los usuarios | F25: Operativo | G25: E - No Crítica | H25: Nube | I25: Plataformas Ciberseguridad | J25: LAURA VALERIA TANDAZO GALLEGOS | K25: MARCO FABRICIO FALCONI NORIEGA | L25: ISRAEL SEBASTIAN DE LA TORRE TRUJILLO | M25: Consolas de Administración Seguridad | N25: SI | O25: Usuario Interno | P25: Si | Q25: Entra ID | R25: Entra ID | S25: Si | T25: FASE 0 | U25: No
A26: Kriptos | B26: SEC0055 | C26: =sheet13[[#This Row],[Nombre]]&sheet13[[#This Row],[Bp Id]] -> KriptosSEC0055 | D26: =VLOOKUP(sheet13[[#This Row],[Columna1]],Sheet2!C:S,4,FALSE) -> Operativo | E26: Solución basada en clasificación artificial que tiene la capacidad de identificar y clasificar los datos de la empresa. | F26: Operativo | G26: E - No Crítica | H26: Nube | I26: Plataformas Ciberseguridad | J26: FERNANDO JAVIER PALADINES BUSTAMANTE | K26: MARCO FABRICIO FALCONI NORIEGA | L26: MARIA DEL CARMEN PENAHERRERA PLUA | M26: Consolas de Administración Seguridad | N26: SI | O26: Usuario Interno | P26: No | Q26: Entra ID | R26: Entra ID | S26: No | T26: FASE 0 | U26: No | V26: Detalle del criterio de recepción:_x000D_ _x000D_ o En base al documento ¿BPECU-SEG-044-STD - Estándar de Recepción de Módulos de Gestión de Accesos y Perfiles V 2.1-¿; donde se definen uno de los criterios para recepción es contar con un módulo de gestión de accesos y perfiles. _x000D_ _x000D_ o En la reunión mantenida el lunes 23 de marzo de 2026 en conjunto con el equipo administrador del aplicativo, se concluyó que: que la aplicación no cuenta con un módulo para la gestión de accesos. | W26: 46104 | X26: VIDAL BARBA GABRIELA VIRGINIA | AC26: Vidal Barba Gabriela Virginia- EXPERTO PLATAFORMAS CIBERSEGURIDAD: Nos informa que el acceso es a través de la asignación de grupos de Azure AD de nomenclatura: GSC_KRIPTOS_XXX, no existen usuarios locales.
A27: LEXMARK CLOUD PRINT MANAGEMENT (CPM) | B27: ITM0038 | C27: =sheet13[[#This Row],[Nombre]]&sheet13[[#This Row],[Bp Id]] -> LEXMARK CLOUD PRINT MANAGEMENT (CPM)ITM0038 | D27: =VLOOKUP(sheet13[[#This Row],[Columna1]],Sheet2!C:S,4,FALSE) -> Operativo | E27: Administración Multifunción Lexmark para Integración multifuncionales con Talla Impresión | F27: Operativo | G27: E - No Crítica | H27: Nube | I27: Gerencia Arquitectura Usuario Final | J27: AMPARO MARIANA CARDENAS HUILCA | K27: ABNER ANDY AREVALO BRACAMONTE | L27: ABNER ANDY AREVALO BRACAMONTE | M27: Aplicación complementaria | N27: SI | O27: Usuario Interno | P27: Si | Q27: Propio | R27: Propio | S27: No | T27: FASE 0 | U27: No | V27: EVALUADA, NO CUMPLE CRITERIOS
A28: Lexmark Printer Management | B28: ITM0038 | C28: =sheet13[[#This Row],[Nombre]]&sheet13[[#This Row],[Bp Id]] -> Lexmark Printer ManagementITM0038 | D28: =VLOOKUP(sheet13[[#This Row],[Columna1]],Sheet2!C:S,4,FALSE) -> Retirado | E28: Administración Multifunción Lexmark para Integración multifuncionales con Talla Impresión | F28: Retirado | G28: E - No Crítica | H28: On Premise | I28: INFRAESTRUCTURA | J28: JOSE LUIS GOYES LARA | L28: ABNER ANDY AREVALO BRACAMONTE | M28: Aplicación complementaria | N28: NO | O28: Usuario Interno | P28: Si | Q28: Propio | R28: Propio | S28: No | U28: No | V28: EVALUADA, NO CUMPLE CRITERIOS
A29: Librarian | B29: ITM0071 | C29: =sheet13[[#This Row],[Nombre]]&sheet13[[#This Row],[Bp Id]] -> LibrarianITM0071 | D29: =VLOOKUP(sheet13[[#This Row],[Columna1]],Sheet2!C:S,4,FALSE) -> Retirado | E29: Aplicación de equipo Librarian | F29: Retirado | G29: E - No Crítica | H29: On Premise | I29: COE de Ingeniería | J29: GUILLERMO GABRIEL DEPRATI | K29: DIEGO PAUL AREVALO COSTALES | L29: FERNANDO VINICIO OCHOA CARRION | M29: Consolas de Administración TI | N29: NO | O29: Usuario Interno | P29: Si | Q29: Propio | R29: Propio | S29: No | U29: No | V29: EVALUADA, NO CUMPLE CRITERIOS
A30: ListaObservados | B30: GOB0013 | C30: =sheet13[[#This Row],[Nombre]]&sheet13[[#This Row],[Bp Id]] -> ListaObservadosGOB0013 | D30: =VLOOKUP(sheet13[[#This Row],[Columna1]],Sheet2!C:S,4,FALSE) -> Operativo | E30: Es una aplicación que permite la validación de clientes en listas de validación utilizando componentes de terceros (Bridger). | F30: Operativo | G30: B - Ecosistema Apetito de Riesgo | H30: Nube | I30: AREAS_DE_APOYO | J30: FABIAN GEOVANNI PAZMINO UBIDIA | K30: JOSE LUIS ZAPATA ROSERO | L30: FERNANDO JOSE ROLDAN CORREA | M30: Aplicación del negocio | N30: SI | O30: Usuario Interno | P30: Si | Q30: PPRD - SIGLO21 | R30: Siglo 21 | S30: Si | T30: FASE 0 | U30: No
A31: LogiFlow | B31: TIE0019 | C31: =sheet13[[#This Row],[Nombre]]&sheet13[[#This Row],[Bp Id]] -> LogiFlowTIE0019 | D31: =VLOOKUP(sheet13[[#This Row],[Columna1]],Sheet2!C:S,4,FALSE) -> Operativo | E31: Portal de aplicaciones para la gestión y administracion de procesos del Banco. | F31: Operativo | G31: C - BIA Crítica | H31: On Premise | I31: ACTIVOS | J31: LAURA ELIZABETH CARRASCO UQUILLAS | K31: ANDREA FERNANDA ORTIZ CISNEROS | L31: ERISLAN MARTINEZ JERA | M31: Aplicación del negocio | N31: SI | O31: Usuario Interno | P31: Si | Q31: Active Directory | R31: Propio | S31: Si | U31: Si | W31: 45200 | X31: CISNEROS MANOSALVAS EDGAR NAPOLEON | Y31: MEJIA MANZANO ROMEO OCTAVIO | Z31: TERAN PIEDRA DAYANARA ABIGAIL | AA31: ETL | AB31: ETL | AC31: GESTIONAR EN LA APLICACION USUARIOS Y ROLES | AD31: Eliminar | AE31: https://flujoempresaslan.uio.bpichincha.com:8046/Pichincha/WebLogiPortal/
A32: LoginCentral | B32: SEC0028 | C32: =sheet13[[#This Row],[Nombre]]&sheet13[[#This Row],[Bp Id]] -> LoginCentralSEC0028 | D32: =VLOOKUP(sheet13[[#This Row],[Columna1]],Sheet2!C:S,4,FALSE) -> Operativo | E32: Aplicación que reemplaza al Portal Empresarial respecto al tema de ingreso a las aplicaciones portalizadas, por esta aplicación permite el logueo a todas las aplicaciones portalizadas que dispone BP, el Login Central consume el serbvicio de WsConexioLdap, pose conexión con una BD de datos BD_TALOS y consume servicios del Process Server. | F32: Operativo | G32: B - Ecosistema Apetito de Riesgo | H32: On Premise | I32: Tribu Ciberseguridad | J32: JORGE GREGORIO ZAPATA CALVOPINA | K32: FRANCISCO DAVID CEVALLOS GRANJA | L32: DIEGO PAUL TAMAYO BARRIGA | M32: Aplicación del negocio | N32: SI | O32: Usuario Interno | P32: Si | Q32: Active Directory | R32: Active Directory | S32: Si | U32: Si | W32: 45200 | Y32: FLORES YAGUANA JHONATAN DAMIAN | Z32: AUQUILLA CHINCHIN GLADYS ARACELI | AA32: ETL | AB32: ETL | AC32: GRUPOS AD | AD32: Eliminar | AE32: https://logincentral.bp.bpichincha.com/loginCentralizado/loginCentralizado
A33: Logística de Efectivo | B33: CHL0001 | C33: =sheet13[[#This Row],[Nombre]]&sheet13[[#This Row],[Bp Id]] -> Logística de EfectivoCHL0001 | D33: =VLOOKUP(sheet13[[#This Row],[Columna1]],Sheet2!C:S,4,FALSE) -> Operativo | E33: Aplicación que permite controlar el pedido de remesas de efectivo desde las agencias a los centros de acopio. Permite administrar en forma adecuada el proceso de Gestión de Logística de Efectivo y Valorados, desde el registro de la recepción de la solicitud, procesamiento, envío y contabilización de remesas en los centros de acopio, ATM¿s, agencias o sucursales y Banco Central. | F33: Operativo | G33: C - BIA Crítica | H33: On Premise | I33: AREAS_DE_APOYO | J33: FABIAN GEOVANNI PAZMINO UBIDIA | K33: PRISCILA ALEXANDRA PARRA LEON | L33: PRISCILA ALEXANDRA PARRA LEON | M33: Aplicación del negocio | N33: SI | O33: Usuario Interno | P33: Si | Q33: Active Directory | R33: Propio | S33: Si | U33: Si | V33: SIGLO21 | W33: 45199
A34: Lumu | B34: SEC0056 | C34: =sheet13[[#This Row],[Nombre]]&sheet13[[#This Row],[Bp Id]] -> LumuSEC0056 | D34: =VLOOKUP(sheet13[[#This Row],[Columna1]],Sheet2!C:S,4,FALSE) -> Retirado | E34: Aplicación ciberseguridad que ofrece visibilidad y respuesta a amenazas en tiempo real. | F34: Retirado | G34: E - No Crítica | H34: Nube | I34: COE_SEGURIDAD | J34: GABRIELA VIRGINIA VIDAL BARBA | K34: MARCO FABRICIO FALCONI NORIEGA | L34: LAURA VALERIA TANDAZO GALLEGOS | M34: Consolas de Administración Seguridad | N34: NO | O34: Usuario Interno | P34: Si | Q34: Entra ID | R34: Entra ID | S34: Si | U34: No
A35: Mail Control System | B35: SUP0012 | C35: =sheet13[[#This Row],[Nombre]]&sheet13[[#This Row],[Bp Id]] -> Mail Control SystemSUP0012 | D35: =VLOOKUP(sheet13[[#This Row],[Columna1]],Sheet2!C:S,4,FALSE) -> Operativo | E35: Aplicación utilizada por el área Administrativa para gestionar el proceso de entrega y recepción de correspondencia interna. | F35: Operativo | G35: E - No Crítica | H35: Nube | I35: AREAS_DE_APOYO | J35: FABIAN GEOVANNI PAZMINO UBIDIA | K35: JUAN PABLO DURAN VEGA | L35: ABRAHAM JOSUE MOGOLLON VASQUEZ | M35: Aplicación del negocio | N35: SI | O35: Usuario Interno | P35: No | Q35: Entra ID | R35: Entra ID | S35: Si | T35: FASE 0 | U35: No | V35: Realizar la recepción: está planificada_x000D_ Detalle del criterio de recepción:_x000D_ _x000D_ o En base al documento ¿BPECU-SEG-044-STD - Estándar de Recepción de Módulos de Gestión de Accesos y Perfiles V 2.1-¿; donde se definen uno de los criterios para recepción es contar con un módulo de gestión de accesos y perfiles._x000D_ _x000D_ o Luego de una reunión mantenida con el equipo administrador del aplicativo se recibió _x000D_ mediante email el día 11 de marzo de 2026 que la aplicación no cuenta con un módulo _x000D_ para la gestión de accesos. Adicional se tuvieron las siguientes observaciones:_x000D_ _x000D_ o Muzzillo Gustavo - INGENIERO INFRAESTRUCTURA TI menciona que Mail Control System: _x000D_ "no posee un módulo de gestión de Usuarios y Permisos, encontrándose estas funciones delegadas al IDP (EntraID) apoyándose en las herramientas MyAccess y MySessions para la gestión de permisos y claves de usuario respectivamente", de acuerdo con el correo con asunto: RE: Solicitud entrega del aplicativo a Gestión de Identidades: Mail Control System, con fecha 11 de marzo de 2026. | W35: 46092 | X35: MUZZILLO GUSTAVO
A36: Mambu | B36: COR0008 | C36: =sheet13[[#This Row],[Nombre]]&sheet13[[#This Row],[Bp Id]] -> MambuCOR0008 | D36: =VLOOKUP(sheet13[[#This Row],[Columna1]],Sheet2!C:S,4,FALSE) -> Retirado | E36: No existe descripción | F36: Retirado | G36: E - No Crítica | H36: Nube | I36: Tribu_Integraciones_Apis | J36: DAVID RODRIGO REVELO RIVERA | K36: GILBERT ADRIAN CISNEROS TELLO | L36: GILBERT ADRIAN CISNEROS TELLO | M36: Aplicación del negocio | N36: NO | O36: Usuario Interno | P36: Si | Q36: Entra ID | R36: Entra ID | S36: Si | U36: No
A37: Mambu Deuna | B37: SEC0057 | C37: =sheet13[[#This Row],[Nombre]]&sheet13[[#This Row],[Bp Id]] -> Mambu DeunaSEC0057 | D37: =VLOOKUP(sheet13[[#This Row],[Columna1]],Sheet2!C:S,4,FALSE) -> Retirado | E37: Core bancario de uso exlclusivo para Deuna | F37: Retirado | G37: A - Apetito de Riesgo Disponibilidad | H37: Nube | I37: TRIBU_DE_UNA | J37: LUIS JAVIER MARIDUENA NOVILLO | K37: LUIS JAVIER MARIDUENA NOVILLO | L37: LUIS JAVIER MARIDUENA NOVILLO | M37: Aplicación del negocio | N37: NO | O37: Usuario Interno | P37: Si | Q37: Entra ID | R37: Entra ID | S37: Si | U37: No
A38: MatiBOT | B38: ITM0075 | C38: =sheet13[[#This Row],[Nombre]]&sheet13[[#This Row],[Bp Id]] -> MatiBOTITM0075 | D38: =VLOOKUP(sheet13[[#This Row],[Columna1]],Sheet2!C:S,4,FALSE) -> Operativo | E38: Brindar a los usuarios la capacidad de realizar solicitudes a través de una interfaz de chat en diversos canales conversacionales, como Microsoft Teams, Web Chat o WhatsApp. | F38: Operativo | G38: E - No Crítica | H38: Nube | I38: Gerencia Arquitectura Usuario Final | J38: FAYOL SMITH MONTANO MELENDEZ | K38: ABNER ANDY AREVALO BRACAMONTE | L38: CARMEN ROCIO AGUILAR MAYANQUER | M38: Aplicación complementaria | N38: SI | O38: Usuario Interno | P38: Si | Q38: Entra ID | R38: Propio | S38: No | T38: FASE 0 | U38: No | V38: EVALUADA, NO CUMPLE CRITERIOS
A39: Maze | B39: EDC0006 | C39: =sheet13[[#This Row],[Nombre]]&sheet13[[#This Row],[Bp Id]] -> MazeEDC0006 | D39: =VLOOKUP(sheet13[[#This Row],[Columna1]],Sheet2!C:S,4,FALSE) -> Operativo | E39: Herramienta de pruebas con usuarios de prototipos y encuestas masivas moderadas y no moderadas. | F39: Operativo | G39: E - No Crítica | H39: Nube | I39: COE Experiencia | J39: ANTONIO ALEJANDRO CANAVERAL GIL | K39: GABRIEL ANDRES PACHECO TELLO | L39: GABRIEL ANDRES PACHECO TELLO | M39: Utilitario | N39: SI | O39: Usuario Interno | P39: Si | Q39: Propio | R39: Propio | S39: No | T39: FASE 0 | U39: No | V39: EVALUADA, NO CUMPLE CRITERIOS
A40: Mi Campus Pichincha | B40: SUP0033 | C40: =sheet13[[#This Row],[Nombre]]&sheet13[[#This Row],[Bp Id]] -> Mi Campus PichinchaSUP0033 | D40: =VLOOKUP(sheet13[[#This Row],[Columna1]],Sheet2!C:S,4,FALSE) -> Operativo | E40: Sistema de gestión de aprendizaje | F40: Operativo | G40: E - No Crítica | H40: Nube | I40: AREAS_DE_APOYO | J40: FABIAN GEOVANNI PAZMINO UBIDIA | K40: Sylvia Katherine Vega Paillacho | L40: PRICILA ALEXANDRA PARRA LEON | M40: Aplicación complementaria | N40: SI | O40: Usuario Interno | P40: Si | Q40: Entra ID | R40: Entra ID | S40: No | T40: FASE 0 | U40: No | V40: EVALUADA, NO CUMPLE CRITERIOS
A41: Mi Portal (4u) | B41: SUP0013 | C41: =sheet13[[#This Row],[Nombre]]&sheet13[[#This Row],[Bp Id]] -> Mi Portal (4u)SUP0013 | D41: =VLOOKUP(sheet13[[#This Row],[Columna1]],Sheet2!C:S,4,FALSE) -> Operativo | E41: Es una aplicación web desarrollada en Angular y Node JS con base de datos postgres y se encuentra alojada en la nube de Google Cloud. En esta aplicación se disponibiliza para la autogestión del colaborador en temas internos | F41: Operativo | G41: D - BIA No Crítica | H41: Nube | I41: AREAS_DE_APOYO | J41: FABIAN GEOVANNI PAZMINO UBIDIA | K41: ANDREA PAULINA PARDO ULLAGUARI | L41: PRICILA ALEXANDRA PARRA LEON | M41: Aplicación complementaria | N41: SI | O41: Usuario Interno | P41: No | Q41: Propio | R41: Propio | S41: No | T41: FASE 0 | U41: No | V41: Detalle del criterio de recepción: _x000D_ o En base al documento ¿BPECU-SEG-044-STD - Estándar de Recepción de Módulos de Gestión de Accesos y Perfiles V 2.1-¿; donde se definen los criterios para recepción, registra que las aplicaciones administrables deben contar con un módulo de gestión de accesos y perfiles. _x000D_ o Sin embargo: luego de la reunión del 2026/02/10 vía Teams con el equipo administrador del aplicativo se informa y concluye que MI PORTAL no cuenta con un módulo para la gestión de usuarios y perfiles. | W41: 46063
A42: Microcrédito Digital | B42: PRD0053 | C42: =sheet13[[#This Row],[Nombre]]&sheet13[[#This Row],[Bp Id]] -> Microcrédito DigitalPRD0053 | D42: =VLOOKUP(sheet13[[#This Row],[Columna1]],Sheet2!C:S,4,FALSE) -> Operativo | E42: Aplicativo para Microcredito en Linea de Microfinanzas | F42: Operativo | G42: E - No Crítica | H42: Nube | I42: MICROFINANZAS | J42: EUDOCIA BEATRIZ VASQUEZ CASTILLO | K42: LAURA ELIZABETH CARRASCO UQUILLAS | L42: ERISLAN MARTINEZ JERA | M42: Aplicación del negocio | N42: NO | O42: Clientes | P42: No | Q42: No Aplica | R42: No Aplica | S42: No | U42: No | V42: EVALUADA, NO CUMPLE CRITERIOS
A43: Microfinance Portal | B43: PRD0063 | C43: =sheet13[[#This Row],[Nombre]]&sheet13[[#This Row],[Bp Id]] -> Microfinance PortalPRD0063 | D43: =VLOOKUP(sheet13[[#This Row],[Columna1]],Sheet2!C:S,4,FALSE) -> Operativo | E43: Aplicativo para la aprobación, instrumentación y desembolso de créditos de la metodología Microfinanzas Individual y Grupal | F43: Operativo | G43: E - No Crítica | H43: Nube | I43: MICROFINANZAS | J43: LAURA ELIZABETH CARRASCO UQUILLAS | K43: FREDDY NEY BASTIDAS CALERO | L43: Willam Marcel Ontaneda Yaguana | M43: Aplicación del negocio | N43: SI | O43: Usuario Interno | P43: Si | Q43: Entra ID | R43: Entra ID | S43: Si | T43: FASE 0 | U43: No
A44: Mis Riesgos | B44: RIS0008 | C44: =sheet13[[#This Row],[Nombre]]&sheet13[[#This Row],[Bp Id]] -> Mis RiesgosRIS0008 | D44: =VLOOKUP(sheet13[[#This Row],[Columna1]],Sheet2!C:S,4,FALSE) -> Operativo | E44: Agrupación lógica de las aplicaciones internas desarrolladas por Banco, que no cuentan con un ambiente controlado, Banco realiza cambios directos y sus actualizaciones no sigue el proceso de control de cambios. | F44: Operativo | G44: E - No Crítica | H44: On Premise | I44: Tribu Administración de Créditos | J44: JORGE MARIO PULGARIN MAZO | K44: JOHANNA NATALIA RODRIGUEZ SANCHEZ | L44: CHRISTIAN PAUL ENRIQUEZ LOPEZ | M44: Aplicación del negocio | N44: SI | O44: Usuario Interno | P44: Si | Q44: Propio - MISRIESGOS | R44: Propio | S44: Si | T44: FASE 0 | U44: No
A45: MODELO PREDICTIVO CIIU | B45: DAT0006 | C45: =sheet13[[#This Row],[Nombre]]&sheet13[[#This Row],[Bp Id]] -> MODELO PREDICTIVO CIIUDAT0006 | D45: =VLOOKUP(sheet13[[#This Row],[Columna1]],Sheet2!C:S,4,FALSE) -> Operativo | E45: Modelo de Sector y Actividad Económica | F45: Operativo | G45: E - No Crítica | H45: On Premise | I45: COE DATOS&ANALITICA | J45: JAVIER EDUARDO TORRES ALTAMIRANO | K45: ARNALDO UTRIA AZAN | L45: DIEGO EDUARDO GALLARDO CORRALES | M45: Aplicación complementaria | N45: SI | O45: Usuario Interno | P45: Si | Q45: Propio | R45: Propio | S45: No | T45: FASE 0 | U45: No | V45: EVALUADA, NO CUMPLE CRITERIOS
A46: Moengage | B46: OMN0001 | C46: =sheet13[[#This Row],[Nombre]]&sheet13[[#This Row],[Bp Id]] -> MoengageOMN0001 | D46: =VLOOKUP(sheet13[[#This Row],[Columna1]],Sheet2!C:S,4,FALSE) -> Operativo | E46: Es una plataforma de compromiso del cliente y automatización de marketing que ayuda a las empresas a interactuar con sus usuarios a través de canales como notificaciones push, mensajes dentro de la aplicación, correos electrónicos, mensajes de texto (SMS) y más | F46: Operativo | G46: E - No Crítica | H46: Nube | I46: COE de Ingeniería | J46: GUILLERMO GABRIEL DEPRATI | K46: CESAR ALEJANDRO VELASCO TORO | L46: HORACIO LEONEL HOLGUIN ALCIVAR | M46: Aplicación complementaria | N46: SI | O46: Usuario Interno | P46: Si | Q46: Propio | R46: Propio | S46: No | T46: FASE 0 | U46: No | V46: EVALUADA, NO CUMPLE CRITERIOS
A47: Monitor BPM | B47: ITM0039 | C47: =sheet13[[#This Row],[Nombre]]&sheet13[[#This Row],[Bp Id]] -> Monitor BPMITM0039 | D47: =VLOOKUP(sheet13[[#This Row],[Columna1]],Sheet2!C:S,4,FALSE) -> Retirado | E47: Es software libre, Monitorea los servicios middleware utilizados en BPM | F47: Retirado | G47: E - No Crítica | H47: On Premise | I47: Tribu_Cores_Transacciones | J47: DAVID RODRIGO REVELO RIVERA | K47: ANDREA ESTEFANIA CHAVEZ ORDONEZ | L47: Johanna Elizabeth Carangui Vivar | M47: Aplicación complementaria | N47: NO | O47: Usuario Interno | P47: Si | Q47: Propio | R47: Propio | S47: No | U47: No
A48: Monitor Plus | B48: GOB0005 | C48: =sheet13[[#This Row],[Nombre]]&sheet13[[#This Row],[Bp Id]] -> Monitor PlusGOB0005 | D48: =VLOOKUP(sheet13[[#This Row],[Columna1]],Sheet2!C:S,4,FALSE) -> Operativo | E48: Aplicación que permite realizar el monitoreo de las transacciones de clientes para identificación de lavado de dinero y fraude, es de tercero (nombre proveedor plus Holding) implementado en datacenter de Banco. | F48: Operativo | G48: E - No Crítica | H48: Híbrida | I48: AREAS_DE_APOYO | J48: FABIAN GEOVANNI PAZMINO UBIDIA | K48: JOSE LUIS ZAPATA ROSERO | L48: FERNANDO JOSE ROLDAN CORREA | M48: Aplicación complementaria | N48: SI | O48: Usuario Interno | P48: Si | Q48: Propio | R48: Propio | S48: No | T48: =VLOOKUP(sheet13[[#This Row],[Nombre]],[1]Hoja1!A:B,2,FALSE) -> FASE 2 | U48: No
A49: MonitorATM | B49: CHL0019 | C49: =sheet13[[#This Row],[Nombre]]&sheet13[[#This Row],[Bp Id]] -> MonitorATMCHL0019 | D49: =VLOOKUP(sheet13[[#This Row],[Columna1]],Sheet2!C:S,4,FALSE) -> Retirado | E49: Mediante la aplicación de MonitorATM se puede crear ATMS en el sistema y realiza un monitoreo de los ATMs con sus respectivas transacciones. Relación con el Switch de ATM | F49: Retirado | G49: D - BIA No Crítica | H49: On Premise | I49: TRIBU_CANALES | J49: JUAN FELIPE DIAZ RESTREPO | K49: ABNER ANDY AREVALO BRACAMONTE | L49: Nelson Patricio Cardenas Llumiugsi | M49: Aplicación del negocio | N49: NO | O49: Usuario Interno | P49: Si | Q49: PPRD - SIGLO21 | R49: Siglo 21 | S49: Si | U49: No | V49: ADMINISTRACION ELIMINADA
A50: CreditoDistribuidor | B50: PRD0014 | C50: =sheet13[[#This Row],[Nombre]]&sheet13[[#This Row],[Bp Id]] -> CreditoDistribuidorPRD0014 | D50: =VLOOKUP(sheet13[[#This Row],[Columna1]],Sheet2!C:S,4,FALSE) -> Operativo | E50: Aplicación web en la Intranet que genera créditos a pequeñas y medianas empresas que se encuentran afiliadas a Banco Pichincha. Se manejan créditos a proveedores y distribuidores basados en una empresa mayorista o ancla, en el caso de créditos a proveedores se deposita en la cuenta de la empresa directamente afiliada a BP y en el caso de créditos a proveedores en la cuenta del proveedor de la empresa afiliada a Banco Pichincha. | F50: Operativo | G50: D - BIA No Crítica | H50: On Premise | I50: Frente de Soluciones Empresariales | J50: LUIS MIGUEL ULLOA MOREIRA | K50: FABRICIO ANTONIO PEREIRA GARCIA | L50: WILLIAM PATRICIO PANCHI SHUGULI | M50: Aplicación del negocio | N50: SI | O50: Usuario Interno | P50: Si | Q50: Propio | R50: Propio | S50: Si | U50: Si | V50: SIGLO21 | W50: 45199 | Y50: LIVE LOZADA EDGAR ROBERTO
A51: CreditosCOM | B51: PRD0015 | C51: =sheet13[[#This Row],[Nombre]]&sheet13[[#This Row],[Bp Id]] -> CreditosCOMPRD0015 | D51: =VLOOKUP(sheet13[[#This Row],[Columna1]],Sheet2!C:S,4,FALSE) -> Operativo | E51: Aplicación que maneja el flujo de créditos para Crédito Distribuidor. | F51: Operativo | G51: D - BIA No Crítica | H51: On Premise | I51: ACTIVOS | J51: LAURA ELIZABETH CARRASCO UQUILLAS | K51: ANDREA FERNANDA ORTIZ CISNEROS | L51: ERISLAN MARTINEZ JERA | M51: Aplicación del negocio | N51: SI | O51: Usuario Interno | P51: Si | Q51: Active Directory | R51: Propio | S51: Si | U51: Si | V51: Se ingresa por Login Central | W51: 45199 | AC51: AUTORIZACIÓN: PERFIL SIGLO21_x000D_ ASIGNAR GRUPO AD: GA_LOGINC_CREDITOS_COM | AE51: https://logincentral.bp.bpichincha.com/
A52: CRM (salesforce - Financial services) | B52: CUS0007 | C52: =sheet13[[#This Row],[Nombre]]&sheet13[[#This Row],[Bp Id]] -> CRM (salesforce - Financial services)CUS0007 | D52: =VLOOKUP(sheet13[[#This Row],[Columna1]],Sheet2!C:S,4,FALSE) -> Operativo | E52: No existe descripción | F52: Operativo | G52: C - BIA Crítica | H52: Nube | I52: Negocios y Monetización | J52: ANTONIO ALEJANDRO CANAVERAL GIL | K52: JULIEN LOUIS ADRIEN LEREBOULLET | L52: HECTOR EDUARDO JARAMILLO RUALES | M52: Aplicación del negocio | N52: SI | O52: Usuario Interno | P52: Si | Q52: Entra ID | R52: Propio | S52: Si | U52: Si | W52: 45200 | AA52: ETL | AB52: Manual | AC52: GESTIONAR EN LA APLICACION USUARIOS Y ROLES | AD52: Eliminar | AE52: https://pichincha.my.salesforce.com/_x000D_ Se ingresa con genéricos usrpacrm@pichincha.com - usrpbcrm@pichincha.com ingresar con la contraseña registrada en la Producción y se aprueba el ingreso mediante el authenticator de Windows (app android)
A53: CRM (salesforce - Marketing Cloud) | B53: CUS0008 | C53: =sheet13[[#This Row],[Nombre]]&sheet13[[#This Row],[Bp Id]] -> CRM (salesforce - Marketing Cloud)CUS0008 | D53: =VLOOKUP(sheet13[[#This Row],[Columna1]],Sheet2!C:S,4,FALSE) -> Operativo | E53: Es una plataforma de automatización de marketing digital en la nube, parte del ecosistema CRM de Salesforce, diseñada para gestionar campañas multicanal (email, móvil, redes sociales, web). | F53: Operativo | G53: E - No Crítica | H53: Nube | I53: Negocios y Monetización | J53: ANTONIO ALEJANDRO CANAVERAL GIL | K53: SEBASTIAN MUNOZ ANDERSEN | L53: HECTOR EDUARDO JARAMILLO RUALES | M53: Aplicación del negocio | N53: SI | O53: Usuario Interno | P53: Si | Q53: Propio | R53: Propio | S53: Si | U53: Si | W53: 46052 | X53: ANGULO CAMUENDO BRYAN LENIN | Y53: LEON NOGUERA YOLANDA AMPARO | Z53: ZAMBRANO NUNEZ PAUL SANTIAGO | AA53: Manual | AB53: Manual | AC53: Creación: Sobre un usuario inactivo se procede con la modificación del usuario por temas de licenciamiento del aplictivo. | AD53: Eliminar | AE53: https://mc.s10.exacttarget.com/cloud/#app/Marketing%20Cloud%20Dashboard/?ks=ks
A54: Crowdstrike | B54: SEC0009 | C54: =sheet13[[#This Row],[Nombre]]&sheet13[[#This Row],[Bp Id]] -> CrowdstrikeSEC0009 | D54: =VLOOKUP(sheet13[[#This Row],[Columna1]],Sheet2!C:S,4,FALSE) -> Operativo | E54: Ofrece una prevención de amenazas óptima, mediante el uso de inteligencia artificial (AI) y aprendizaje automático (ML) con detección y respuesta avanzada e información sobre amenazas, integrada a través de una consola de gestión altamente intuitiva. | F54: Operativo | G54: C - BIA Crítica | H54: Nube | I54: Plataformas Ciberseguridad | J54: ERICK DAMIAN RISUENO BENITEZ | K54: MARCO FABRICIO FALCONI NORIEGA | L54: LAURA VALERIA TANDAZO GALLEGOS | M54: Consolas de Administración Seguridad | N54: SI | O54: Usuario Interno | P54: Si | Q54: Entra ID | R54: Propio | S54: Si | U54: Si | W54: 45715 | Y54: ESPINOZA RENGIFO MISCHEL ESTEFANIA | Z54: BARAHONA ESPINOSA SANTIAGO ISRAEL | AA54: GRUPO AD | AB54: Manual | AC54: GESTIONAR EN LA APLICACION USUARIOS Y ROLES | AD54: Eliminar | AE54: falcon.crowdstrike.com
A55: Cuadre Atms | B55: SUP0021 | C55: =sheet13[[#This Row],[Nombre]]&sheet13[[#This Row],[Bp Id]] -> Cuadre AtmsSUP0021 | D55: =VLOOKUP(sheet13[[#This Row],[Columna1]],Sheet2!C:S,4,FALSE) -> Operativo | E55: Aplicación que dispone de procesos para cuadre de cajeros automáticos (cuadre físico vs reporte del Switch de Servicios ATMs) y conciliación de transacciones en ATMs propios (clientes BP y clientes de otras redes). | F55: Operativo | G55: C - BIA Crítica | H55: On Premise | I55: TRIBU_CANALES | J55: DANIEL PATRICIO PAZ ENRIQUEZ | K55: MILTON PATRICIO MANTILLA CAYO | L55: JUAN FRANCISCO PROCEL MICHILENA | M55: Aplicación del negocio | N55: SI | O55: Usuario Interno | P55: Si | Q55: Propio | R55: Propio | S55: Si | U55: Si | V55: SIGLO21 | W55: 45199
A56: Cuenta Digital Personas | B56: CHL0037 | C56: =sheet13[[#This Row],[Nombre]]&sheet13[[#This Row],[Bp Id]] -> Cuenta Digital PersonasCHL0037 | D56: =VLOOKUP(sheet13[[#This Row],[Columna1]],Sheet2!C:S,4,FALSE) -> Operativo | E56: APP ONBOARDING, aplicación movil de Banco Pichincha, en la que podrá crear clientes, activar cuentas, crear chequeras. | F56: Operativo | G56: C - BIA Crítica | H56: Nube | I56: PASIVOS Y SEGUROS | J56: LAURA ELIZABETH CARRASCO UQUILLAS | K56: JONATHAN HERNAN ARIAS HERNANDEZ | L56: MANUEL ABELARDO HARO MONTERO | M56: Aplicación complementaria | N56: SI | O56: Clientes / Usuario Interno | P56: No | Q56: Entra ID | R56: Entra ID | S56: No | T56: FASE 0 | U56: No | V56: Estimado,_x000D_ _x000D_ En negrita mis respuestas._x000D_ _x000D_ 1. ¿Qué tipo de usuarios acceden a la aplicación? _x000D_ 1. Clientes._x000D_ 2. Colaboradores (Internos)._x000D_ _x000D_ 2. ¿La aplicación cuenta con un módulo de gestión de accesos y perfiles, que permita la administración del ciclo de vida de los usuarios y roles?_x000D_ ¿¿¿¿¿¿No._x000D_ _x000D_ 3. ¿Cuál es el método de Autenticación de la aplicación? _x000D_ Entra ID._x000D_ Propio._x000D_ _x000D_ 4. ¿Cuál es el método de Autorización de la aplicación?_x000D_ 1. Entra ID._x000D_ 1. Propio._x000D_ _x000D_ 5. En base a su expertis en la aplicación ¿Cual considera de las siguientes categorías se ajusta de manera más cercana a la aplicación?_x000D_ a. Aplicación Complementaria: Se refiera a una aplicación que se proporciona como complemento de otra aplicación, permitiendo extender las funciones de otra aplicación o programa sin tener que modificar el código._x000D_ b. Aplicación del Negocio: Son herramientas digitales que facilitan distintas operaciones dentro de los negocios, es decir, aquellas que son esenciales en la ejecución, desarrollando las operaciones del negocio._x000D_ f. Middleware: Software que ofrece servicios y funciones comunes para las aplicaciones.
A57: Cuentas por pagar | B57: SUP0031 | C57: =sheet13[[#This Row],[Nombre]]&sheet13[[#This Row],[Bp Id]] -> Cuentas por pagarSUP0031 | D57: =VLOOKUP(sheet13[[#This Row],[Columna1]],Sheet2!C:S,4,FALSE) -> Operativo | E57: Es un por portal donde se visualiza los diferentes documentos de proveedores de banco (facturas, retenciones). Está en un aks de azure | F57: Operativo | G57: E - No Crítica | H57: Nube | I57: AREAS_DE_APOYO | J57: FABIAN GEOVANNI PAZMINO UBIDIA | K57: JUAN PABLO DURAN VEGA | L57: ABRAHAM JOSUE MOGOLLON VASQUEZ | M57: Aplicación complementaria | N57: SI | O57: Usuario Interno | P57: Si | Q57: Propio | R57: Propio | S57: No | T57: FASE 0 | U57: No
A58: CXP (Banca Web) | B58: CHL0014 | C58: =sheet13[[#This Row],[Nombre]]&sheet13[[#This Row],[Bp Id]] -> CXP (Banca Web)CHL0014 | D58: =VLOOKUP(sheet13[[#This Row],[Columna1]],Sheet2!C:S,4,FALSE) -> Operativo | E58: Nueva banca electrónica con cambios en su tecnología para soportar el crecimiento de Banco Pichincha, así como también para apalancar los objetivos de banco para lograr una aplicación Omnicanal. Permite realizar transacciones y trámites bancarios a través de Internet. Una solucion virtual, digital y electrónica. | F58: Operativo | G58: A - Apetito de Riesgo Disponibilidad | H58: Nube | I58: TRIBU_CANALES | J58: MIGUEL ALEXANDER MEJIA BRONCANO | K58: DIANA PATRICIA CAICEDO RODRIGUEZ | L58: MIGUEL ALEXANDER MEJIA BRONCANO | M58: Aplicación del negocio | N58: NO | O58: Clientes | P58: Si | Q58: Propio | R58: Propio | S58: No | U58: No
A59: CyberArk | B59: SEC0010 | C59: =sheet13[[#This Row],[Nombre]]&sheet13[[#This Row],[Bp Id]] -> CyberArkSEC0010 | D59: =VLOOKUP(sheet13[[#This Row],[Columna1]],Sheet2!C:S,4,FALSE) -> Operativo | E59: Aplicación que permite el manejo de cuentas de usuarios privilegiados | F59: Operativo | G59: C - BIA Crítica | H59: On Premise | I59: Plataformas Ciberseguridad | J59: ROBERT STALIN SOTO CORONEL | K59: MARCO FABRICIO FALCONI NORIEGA | L59: ERICK DAMIAN RISUENO BENITEZ | M59: Consolas de Administración Seguridad | N59: SI | O59: Usuario Interno | P59: Si | Q59: Active Directory | R59: Active Directory | S59: Si | T59: =VLOOKUP(sheet13[[#This Row],[Nombre]],[1]Hoja1!A:B,2,FALSE) -> FASE 2 | U59: No
A60: DarkTrace | B60: SEC0011 | C60: =sheet13[[#This Row],[Nombre]]&sheet13[[#This Row],[Bp Id]] -> DarkTraceSEC0011 | D60: =VLOOKUP(sheet13[[#This Row],[Columna1]],Sheet2!C:S,4,FALSE) -> Operativo | E60: Inspección de tráfico de Red para determinar amenazas de seguridad. Tecnología de inteligencia artificial cibernética de autoaprendizaje que detecta nuevos ataques y amenazas internas en una etapa temprana | F60: Operativo | G60: E - No Crítica | H60: On Premise | I60: Plataformas Ciberseguridad | J60: MARIA DEL CARMEN PENAHERRERA PLUA | K60: MARCO FABRICIO FALCONI NORIEGA | L60: JORGE XAVIER LUCERO GALLEGOS | M60: Consolas de Administración Seguridad | N60: SI | O60: Usuario Interno | P60: Si | Q60: Propio | R60: Propio | S60: Si | T60: FASE 0 | U60: No
A61: DataPower Externo | B61: INT0005 | C61: =sheet13[[#This Row],[Nombre]]&sheet13[[#This Row],[Bp Id]] -> DataPower ExternoINT0005 | D61: =VLOOKUP(sheet13[[#This Row],[Columna1]],Sheet2!C:S,4,FALSE) -> Operativo | E61: IBM DataPower es una consola/plataforma de seguridad e integración usada para administrar, proteger y publicar servicios como APIs, SOAP y REST. Permite aplicar políticas de autenticación, autorización, cifrado, firma y validación de mensajes. También se usa como gateway para enrutar, transformar y monitorear tráfico entre aplicaciones y sistemas | F61: Operativo | G61: B - Ecosistema Apetito de Riesgo | H61: On Premise | I61: Tribu_Integraciones_Apis | J61: DAVID RODRIGO REVELO RIVERA | K61: DIEGO VLADIMIR JAYA GUAMANZARA | L61: CHRISTIAN DARIO PASQUEL PARRA | M61: Consolas de Administración TI | N61: SI | O61: Usuario Interno | P61: Si | Q61: Propio | R61: Propio | S61: Si | U61: Si | V61: DataPower Externo se encuentra alojado en servidores DMZ. | W61: 46197 | X61: ESTRELLA HIDALGO FREDDY VINICIO | Y61: RAMOS SALAZAR SEBASTIAN MATEO | Z61: FLORES YAGUANA JHONATAN DAMIAN | AA61: Manual | AB61: Manual | AC61: Ingresar al nodo y crear al usuario manualmente con una contraseña personalizada. | AD61: Eliminar | AE61: Ingresar por Cyberark, al nodo correspondiente:_x000D_ _x000D_ ECBPDPP3 10.40.4.47 Datapower Nodo 1 Externo DCP_x000D_ ECBPDPP4 10.40.4.48 Datapower Nodo 2 Externo DCP_x000D_ DRECBPDPP3 10.40.4.54 Datapower Nodo 1 Externo DCA_x000D_ DRECBPDPP4 10.40.4.55 Datapower Nodo 2 Externo DCA
A62: Decisión Cloud | B62: ITM0001 | C62: =sheet13[[#This Row],[Nombre]]&sheet13[[#This Row],[Bp Id]] -> Decisión CloudITM0001 | D62: =VLOOKUP(sheet13[[#This Row],[Columna1]],Sheet2!C:S,4,FALSE) -> Operativo | E62: No existe descripción | F62: Operativo | G62: E - No Crítica | H62: Nube | I62: Plataformas Ciberseguridad | J62: ANDY JOSE ANDRADE BRAVO | K62: MARCO FABRICIO FALCONI NORIEGA | L62: CARLOS ANDRES MORALES MALDONADO | M62: Consolas de Administración Seguridad | N62: SI | O62: Usuario Interno | P62: Si | Q62: Entra ID | R62: Entra ID | S62: Si | U62: Si | W62: 46035 | X62: VALLEJO BAQUERO JAIME GIOVANNY | Y62: ESPINOZA RENGIFO MISCHEL ESTEFANIA | Z62: ZAMBRANO NUNEZ PAUL SANTIAGO | AA62: Manual | AB62: Manual | AC62: GRUPOS CLOUD | AD62: Desactivar | AE62: pichincha.mydecisioncloud.com
A63: Deep Discovery Analyzer | B63: SEC0012 | C63: =sheet13[[#This Row],[Nombre]]&sheet13[[#This Row],[Bp Id]] -> Deep Discovery AnalyzerSEC0012 | D63: =VLOOKUP(sheet13[[#This Row],[Columna1]],Sheet2!C:S,4,FALSE) -> Retirado | E63: Proporciona una protección completa, adaptable y extremadamente eficiente, con antimalware, detección y prevención de intrusiones, firewall, protección de aplicaciones Web, supervisión de la integridad e inspección de registros | F63: Retirado | G63: E - No Crítica | H63: On Premise | I63: COE_SEGURIDAD | J63: GABRIELA VIRGINIA VIDAL BARBA | K63: MARCO FABRICIO FALCONI NORIEGA | L63: WILSON FERNANDO RODRIGUEZ TOBAR | M63: Consolas de Administración Seguridad | N63: NO | O63: Usuario Interno | P63: Si | Q63: Propio | R63: Propio | S63: Si | U63: No
A64: Deep Discovery Inspector | B64: SEC0013 | C64: =sheet13[[#This Row],[Nombre]]&sheet13[[#This Row],[Bp Id]] -> Deep Discovery InspectorSEC0013 | D64: =VLOOKUP(sheet13[[#This Row],[Columna1]],Sheet2!C:S,4,FALSE) -> Retirado | E64: Proporciona una protección completa, adaptable y extremadamente eficiente, con antimalware, detección y prevención de intrusiones, firewall, protección de aplicaciones Web, supervisión de la integridad e inspección de registros | F64: Retirado | G64: E - No Crítica | H64: On Premise | I64: COE_SEGURIDAD | J64: GABRIELA VIRGINIA VIDAL BARBA | K64: MARCO FABRICIO FALCONI NORIEGA | L64: ERICK DAMIAN RISUENO BENITEZ | M64: Consolas de Administración Seguridad | N64: NO | O64: Usuario Interno | P64: Si | Q64: Propio | R64: Propio | S64: Si | U64: No
A65: Deep Security | B65: SEC0014 | C65: =sheet13[[#This Row],[Nombre]]&sheet13[[#This Row],[Bp Id]] -> Deep SecuritySEC0014 | D65: =VLOOKUP(sheet13[[#This Row],[Columna1]],Sheet2!C:S,4,FALSE) -> Operativo | E65: Proporciona una protección completa, adaptable y extremadamente eficiente, con antimalware, detección y prevención de intrusiones, firewall, protección de aplicaciones Web, supervisión de la integridad e inspección de registros | F65: Operativo | G65: E - No Crítica | H65: On Premise | I65: Plataformas Ciberseguridad | J65: ERICK DAMIAN RISUENO BENITEZ | K65: MARCO FABRICIO FALCONI NORIEGA | L65: ROBERT STALIN SOTO CORONEL | M65: Consolas de Administración Seguridad | N65: SI | O65: Usuario Interno | P65: Si | Q65: Active Directory | R65: Active Directory | S65: Si | U65: Si | V65: SE ELIMINA DENTRO DE LA APLICACION | W65: 45736 | AA65: Manual | AB65: Manual | AC65: GRUPOS AD | AD65: Eliminar | AE65: CYBERARK: ecbpprsi70
A66: Depositarios | B66: CHL0015 | C66: =sheet13[[#This Row],[Nombre]]&sheet13[[#This Row],[Bp Id]] -> DepositariosCHL0015 | D66: =VLOOKUP(sheet13[[#This Row],[Columna1]],Sheet2!C:S,4,FALSE) -> Operativo | E66: Conjunto de componentes instalados en los ATM's que permite llevar a cabo los procesos relacionados a cajeros automáticos del Banco del Pichincha./ Sistema de cajeros automáticos de Banco Pichincha | F66: Operativo | G66: E - No Crítica | H66: On Premise | I66: TRIBU_CANALES | J66: DANIEL PATRICIO PAZ ENRIQUEZ | K66: MILTON PATRICIO MANTILLA CAYO | L66: JUAN FRANCISCO PROCEL MICHILENA | M66: Componente | N66: NO | O66: Usuario Interno | P66: Si | Q66: Propio | R66: Propio | S66: No | U66: No
A67: DESIGNSYSTEM | B67: CHL0044 | C67: =sheet13[[#This Row],[Nombre]]&sheet13[[#This Row],[Bp Id]] -> DESIGNSYSTEMCHL0044 | D67: =VLOOKUP(sheet13[[#This Row],[Columna1]],Sheet2!C:S,4,FALSE) -> Operativo | E67: Sin descripción | F67: Operativo | G67: E - No Crítica | H67: Nube | I67: TRIBU_CANALES | J67: JUAN FELIPE DIAZ RESTREPO | K67: JORGE ALBERTO VILLAFUERTE GORDILLO | L67: PRICILA VANESSA QUICHIMBO ARMIJOS | M67: Aplicación complementaria | N67: SI | O67: Usuario Interno | P67: Si | Q67: Entra ID | R67: Entra ID | S67: No | T67: FASE 0 | U67: No
A68: Detect ID | B68: SEC0015 | C68: =sheet13[[#This Row],[Nombre]]&sheet13[[#This Row],[Bp Id]] -> Detect IDSEC0015 | D68: =VLOOKUP(sheet13[[#This Row],[Columna1]],Sheet2!C:S,4,FALSE) -> Operativo | E68: Aplicación para generación de softoken en lugar de OTP enviada por SMS. | F68: Operativo | G68: B - Ecosistema Apetito de Riesgo | H68: On Premise | I68: Tribu Ciberseguridad | J68: ISRAEL SEBASTIAN DE LA TORRE TRUJILLO | K68: Vladimir Stalin Lamina Sanchez | L68: ROBERTO CARLOS PINO CEDENO | M68: Aplicación del negocio | N68: SI | O68: Usuario Interno | P68: Si | Q68: Propio | R68: Propio | S68: Si | U68: Si | V68: REPORTERIA DE USUARIOS SE EXTRAE DEL APLICATIVO | W68: 45200 | X68: ZAMBRANO SOLORZANO FRANKLIN STEVEN | Y68: ZAMBRANO NUNEZ PAUL SANTIAGO | Z68: BARAHONA ESPINOSA SANTIAGO ISRAEL | AA68: ETL | AB68: Manual | AC68: GESTIONAR EN LA APLICACION USUARIOS Y ROLES | AD68: Eliminar | AE68: Escoger en Username :usrpdck Plataform ID: BP-DetectID2
A69: Deuna Microcomercios | B69: CHL0041 | C69: =sheet13[[#This Row],[Nombre]]&sheet13[[#This Row],[Bp Id]] -> Deuna MicrocomerciosCHL0041 | D69: =VLOOKUP(sheet13[[#This Row],[Columna1]],Sheet2!C:S,4,FALSE) -> Operativo | E69: Aplicacion para administracion de microcomercios | F69: Operativo | G69: E - No Crítica | H69: Nube | I69: TRIBU_DE_UNA | J69: LUIS JAVIER MARIDUENA NOVILLO | K69: LUIS JAVIER MARIDUENA NOVILLO | L69: LUIS JAVIER MARIDUENA NOVILLO | M69: Consolas de Administración TI | N69: NO | O69: Clientes | P69: Si | Q69: Propio | R69: Propio | S69: No | U69: No
A70: Ansible | B70: TIE0024 | C70: =sheet13[[#This Row],[Nombre]]&sheet13[[#This Row],[Bp Id]] -> AnsibleTIE0024 | D70: =VLOOKUP(sheet13[[#This Row],[Columna1]],Sheet2!C:S,4,FALSE) -> Operativo | E70: Ansible Automation platform para automatizar la configuracion de la infrastructura | F70: Operativo | G70: E - No Crítica | H70: On Premise | I70: Gerencia SRE | J70: GONZALO TRANCILLO | K70: GONZALO TRANCILLO | L70: DIANA CRISTINA AVEIGA LOVATO | M70: Consolas de Administración TI | N70: SI | O70: Usuario Interno | P70: Si | Q70: Entra ID | R70: Propio | S70: No | T70: FASE 0 | U70: No
A71: AntiDDoS Radware | B71: SEC0052 | C71: =sheet13[[#This Row],[Nombre]]&sheet13[[#This Row],[Bp Id]] -> AntiDDoS RadwareSEC0052 | D71: =VLOOKUP(sheet13[[#This Row],[Columna1]],Sheet2!C:S,4,FALSE) -> Operativo | E71: Es un servicio que bloquea ataques volumétricos de las 3 redes públicas / 24 que el banco tiene adquirido | F71: Operativo | G71: B - Ecosistema Apetito de Riesgo | H71: Nube | I71: Plataformas Ciberseguridad | J71: ROBERT STALIN SOTO CORONEL | K71: MARCO FABRICIO FALCONI NORIEGA | L71: JORGE XAVIER LUCERO GALLEGOS | M71: Consolas de Administración Seguridad | N71: SI | O71: Usuario Interno | P71: Si | Q71: Entra ID | R71: Entra ID | S71: Si | U71: Si | V71: GSC_BP-Radware-Prod_Reader_x000D_ GSC_BP-Radware-Prod_Admins | W71: 46140 | Y71: ZAMBRANO NUNEZ PAUL SANTIAGO | Z71: LEON NOGUERA YOLANDA AMPARO | AC71: GESTION DE ROLES EN LA APLICACION | AE71: https://radware.eu.auth0.com/authorize?client_id=KnZSRL3CSoahL0ymcqfwsmt55EHxXxgS&response_type=code&connection=IDP-RADWARE&prompt=login&scope=openid%20profile&redirect_uri=https://console.radwarecloud.com?connection=IDP-RADWARE
A72: AntiSpam | B72: SEC0003 | C72: =sheet13[[#This Row],[Nombre]]&sheet13[[#This Row],[Bp Id]] -> AntiSpamSEC0003 | D72: =VLOOKUP(sheet13[[#This Row],[Columna1]],Sheet2!C:S,4,FALSE) -> Retirado | E72: AntiSpam | F72: Retirado | G72: E - No Crítica | H72: Nube | I72: COE_SEGURIDAD | J72: GABRIELA VIRGINIA VIDAL BARBA | K72: MARCO FABRICIO FALCONI NORIEGA | L72: GABRIELA VIRGINIA VIDAL BARBA | M72: Consolas de Administración Seguridad | N72: NO | O72: Usuario Interno | P72: Si | Q72: Propio | R72: Propio | S72: Si | U72: No
A73: APEX | B73: SEC0064 | C73: =sheet13[[#This Row],[Nombre]]&sheet13[[#This Row],[Bp Id]] -> APEXSEC0064 | D73: =VLOOKUP(sheet13[[#This Row],[Columna1]],Sheet2!C:S,4,FALSE) -> Operativo | E73: Sistema de gestión de eventos de ciberdefensa | F73: Operativo | G73: B - Ecosistema Apetito de Riesgo | H73: Nube | I73: Tribu Ciberseguridad | J73: FRANCISCO DAVID CEVALLOS GRANJA | K73: FRANCISCO DAVID CEVALLOS GRANJA | L73: Vladimir Stalin Lamina Sanchez | M73: Consolas de Administración Seguridad | N73: SI | O73: Usuario Interno | P73: Si | Q73: Propio | R73: Propio | S73: Si | T73: FASE 0 | U73: No
A74: Apigee | B74: INT0004 | C74: =sheet13[[#This Row],[Nombre]]&sheet13[[#This Row],[Bp Id]] -> ApigeeINT0004 | D74: =VLOOKUP(sheet13[[#This Row],[Columna1]],Sheet2!C:S,4,FALSE) -> Operativo | E74: No existe dentro del portafolio | F74: Operativo | G74: B - Ecosistema Apetito de Riesgo | H74: Nube | I74: Tribu_Integraciones_Apis | J74: MARICELA NATALY ACUNA GUANOLUISA | K74: ANDREA ESTEFANIA CHAVEZ ORDONEZ | L74: ANDREA ESTEFANIA CHAVEZ ORDONEZ | M74: Consolas de Administración TI | N74: SI | O74: Usuario Interno | P74: Si | Q74: Propio | R74: Propio | S74: Si | U74: Si | W74: 46007 | X74: ACUNA GUANOLUISA MARICELA NATALY | Y74: TERAN PIEDRA DAYANARA ABIGAIL | Z74: ESPINOZA RENGIFO MISCHEL ESTEFANIA | AA74: Manual | AB74: Manual | AC74: GESTIONAR EN LA APLICACION USUARIOS Y ROLES | AD74: Eliminar | AE74: https://login.apigee.com/login
A75: APIM | B75: INT0016 | C75: =sheet13[[#This Row],[Nombre]]&sheet13[[#This Row],[Bp Id]] -> APIMINT0016 | D75: =VLOOKUP(sheet13[[#This Row],[Columna1]],Sheet2!C:S,4,FALSE) -> Operativo | E75: Servicio de Microsoft Azure API Management. Mantiene la gestión de las APIs, autorización de consumo y analítica de los componentes. | F75: Operativo | G75: B - Ecosistema Apetito de Riesgo | H75: Nube | I75: Tribu_Integraciones_Apis | J75: DAVID RODRIGO REVELO RIVERA | K75: MARICELA NATALY ACUNA GUANOLUISA | L75: JUAN CARLOS CONTRERAS PAREDES | M75: Consolas de Administración TI | N75: SI | O75: Usuario Interno | P75: Si | Q75: Entra ID | R75: Entra ID | S75: Si | U75: Si | V75: Gestión de Accesos Cloud | W75: 46028 | Y75: BARAHONA ESPINOSA SANTIAGO ISRAEL | Z75: LEON NOGUERA YOLANDA AMPARO | AA75: GRUPO AD | AB75: GRUPO AD | AC75: GRUPOS AD | AD75: Eliminar | AE75: Microsoft Azure
A76: Appsflyer | B76: CUS0001 | C76: =sheet13[[#This Row],[Nombre]]&sheet13[[#This Row],[Bp Id]] -> AppsflyerCUS0001 | D76: =VLOOKUP(sheet13[[#This Row],[Columna1]],Sheet2!C:S,4,FALSE) -> Retirado | E76: Ofrece la posibilidad de trackear eventos que acontecen dentro de la aplicación móvil como pueden ser compras y otros objetivos personalizados para el cliente | F76: Retirado | G76: E - No Crítica | H76: Nube | I76: Negocios Digitales (Campañas y Marketing Digital) | J76: ANTONIO ALEJANDRO CANAVERAL GIL | K76: ESTEFANY CAROLINA GONGORA PAREDES | L76: WILLIAM EDUARDO HUERA ORTIZ | M76: Consolas de Administración TI | N76: NO | O76: Usuario Interno | P76: Si | Q76: Active Directory | R76: Active Directory | S76: No | U76: No
A77: Atalla | B77: SEC0004 | C77: =sheet13[[#This Row],[Nombre]]&sheet13[[#This Row],[Bp Id]] -> AtallaSEC0004 | D77: =VLOOKUP(sheet13[[#This Row],[Columna1]],Sheet2!C:S,4,FALSE) -> Operativo | E77: Herramienta de generación de llaves de cifrado para la encripción del tráfico usado por varios aplicativos | F77: Operativo | G77: B - Ecosistema Apetito de Riesgo | H77: On Premise | I77: Plataformas Ciberseguridad | J77: ERICK DAMIAN RISUENO BENITEZ | K77: MARCO FABRICIO FALCONI NORIEGA | L77: ROBERT STALIN SOTO CORONEL | M77: Consolas de Administración Seguridad | N77: SI | O77: Usuario Interno | P77: No | Q77: Propio | R77: Propio | S77: No | T77: FASE 0 | U77: No
A78: Athento | B78: TIE0025 | C78: =sheet13[[#This Row],[Nombre]]&sheet13[[#This Row],[Bp Id]] -> AthentoTIE0025 | D78: =VLOOKUP(sheet13[[#This Row],[Columna1]],Sheet2!C:S,4,FALSE) -> Operativo | E78: ECM Athento, es una herramienta de gestión de contenido transversal a institución, que cuenta con capacidades de ocr,ia, clasificación entre otras con la finalidad de dar gestión y almacenamiento a documentos | F78: Operativo | G78: E - No Crítica | H78: Terceros | I78: COE_TRANSFORMACION_PROCESOS | J78: JAVIER ENRIQUE RIOS CASTILLO | K78: FREDI ALEXANDER ELIZALDE RODRIGUEZ | L78: SANTIAGO POSADA ZULUAGA | M78: Aplicación del negocio | N78: SI | O78: Usuario Interno | P78: Si | Q78: Entra ID | R78: Propio | S78: Si | U78: Si | W78: 46107 | X78: ELIZALDE RODRIGUEZ FREDI ALEXANDER | Y78: RAMOS SALAZAR SEBASTIAN MATEO | AA78: Externo | AB78: Externo | AD78: Desactivar
A79: ATMCampanias | B79: CUS0002 | C79: =sheet13[[#This Row],[Nombre]]&sheet13[[#This Row],[Bp Id]] -> ATMCampaniasCUS0002 | D79: =VLOOKUP(sheet13[[#This Row],[Columna1]],Sheet2!C:S,4,FALSE) -> Retirado | E79: Aplicación stand alone la cual permite cargar archivos de información de campañas para ser promocionadas a través de los cajeros automáticos. Es la nueva aplicación | F79: Retirado | G79: E - No Crítica | H79: On Premise | I79: Negocios Digitales (Campañas y Marketing Digital) | J79: ANTONIO ALEJANDRO CANAVERAL GIL | K79: ABNER ANDY AREVALO BRACAMONTE | L79: WILLIAM EDUARDO HUERA ORTIZ | M79: Utilitario | N79: NO | O79: Usuario Interno | P79: Si | Q79: Propio | R79: Propio | S79: No | U79: No
A80: AURO SUITE | B80: COR0003 | C80: =sheet13[[#This Row],[Nombre]]&sheet13[[#This Row],[Bp Id]] -> AURO SUITECOR0003 | D80: =VLOOKUP(sheet13[[#This Row],[Columna1]],Sheet2!C:S,4,FALSE) -> Operativo | E80: Sistema que permite gestionar los depósitos a plazo generados en Banco Pichincha por los segmentos de bancas privada, empresarial y preferencial | F80: Operativo | G80: C - BIA Crítica | H80: On Premise | I80: Tribu_Cores_Transacciones | J80: DAVID RODRIGO REVELO RIVERA | K80: EDITH SUSANA ACUNA GARCIA | L80: EDITH SUSANA ACUNA GARCIA | M80: Aplicación del negocio | N80: SI | O80: Usuario Interno | P80: Si | Q80: Active Directory | R80: Active Directory | S80: Si | U80: Si | V80: EXTRAE REPORTE DE USUARIOS DESDE LA APP | W80: 45200 | Z80: AUQUILLA CHINCHIN GLADYS ARACELI | AA80: ETL | AB80: ETL | AC80: GRUPOS AD | AD80: Eliminar | AE80: https://servicioauro.uio.bpichincha.com:8443/shell/#/login
A81: Auth0 | B81: SEC0051 | C81: =sheet13[[#This Row],[Nombre]]&sheet13[[#This Row],[Bp Id]] -> Auth0SEC0051 | D81: =VLOOKUP(sheet13[[#This Row],[Columna1]],Sheet2!C:S,4,FALSE) -> Operativo | E81: Auth0, es la nueva aplicación de autenticación para los clientes de canales digitales | F81: Operativo | G81: B - Ecosistema Apetito de Riesgo | H81: Nube | I81: Tribu Ciberseguridad | J81: ROBERTO CARLOS PINO CEDENO | K81: Vladimir Stalin Lamina Sanchez | L81: ROBERTO CARLOS PINO CEDENO | M81: Consolas de Administración Seguridad | N81: SI | O81: Usuario Interno | P81: Si | Q81: Propio | R81: Propio | S81: No | T81: FASE 0 | U81: No | V81: EVALUADO, CUMPLE CRITERIOS, SIN EMBARGO, POR IMPOSIBILIDAD DE SEGREGACIÓN Y SOLICITUD DE SANTIAGO MEDRANDA IDENTIDADES NO ADMINISTRARA. | W81: 46118
A82: Automation Anywhere RPA | B82: TIE0002 | C82: =sheet13[[#This Row],[Nombre]]&sheet13[[#This Row],[Bp Id]] -> Automation Anywhere RPATIE0002 | D82: =VLOOKUP(sheet13[[#This Row],[Columna1]],Sheet2!C:S,4,FALSE) -> Retirado | E82: Una automatización robótica de procesos es una forma naciente de automatización de los procesos de negocio que replica las acciones de un ser humano interactuando con la interfaz de usuario de un sistema informático | F82: Retirado | G82: E - No Crítica | H82: On Premise | I82: COE_TRANSFORMACION_PROCESOS | J82: JAVIER ENRIQUE RIOS CASTILLO | K82: DAVID JOEL REVELO BORJA | L82: THALIA ALEJANDRA LOZADA ARELLANO | M82: Componente | N82: NO | O82: Usuario Interno | P82: Si | Q82: Entra ID | R82: Entra ID | S82: No | U82: No
A83: AutorizadorPichincha | B83: SEC0005 | C83: =sheet13[[#This Row],[Nombre]]&sheet13[[#This Row],[Bp Id]] -> AutorizadorPichinchaSEC0005 | D83: =VLOOKUP(sheet13[[#This Row],[Columna1]],Sheet2!C:S,4,FALSE) -> Operativo | E83: Aplicación para generar una OTP para que el asesor ejecute la transacción financiera solicitada. | F83: Operativo | G83: E - No Crítica | H83: On Premise | I83: Tribu Ciberseguridad | J83: RODNEY XAVIER JACOME TERAN | K83: FRANCISCO DAVID CEVALLOS GRANJA | L83: RODNEY XAVIER JACOME TERAN | M83: Aplicación complementaria | N83: SI | O83: Usuario Interno | P83: Si | Q83: Active Directory | R83: Active Directory | S83: No | T83: FASE 0 | U83: No
A84: AVAYA Aura | B84: ITM0003 | C84: =sheet13[[#This Row],[Nombre]]&sheet13[[#This Row],[Bp Id]] -> AVAYA AuraITM0003 | D84: =VLOOKUP(sheet13[[#This Row],[Columna1]],Sheet2!C:S,4,FALSE) -> Retirado | E84: Plataforma de Comuniaciones Unificadas Coorporativa | F84: Retirado | G84: D - BIA No Crítica | H84: On Premise | I84: INFRAESTRUCTURA | J84: BYRON ORLANDO MELENDREZ CABRERA | K84: MAURICIO FERNANDO NAVAS GALLARDO | L84: ROSITA LORENA CHAVEZ CABRERA | M84: Aplicación complementaria | N84: NO | O84: Usuario Interno | P84: Si | Q84: Active Directory | R84: Active Directory | S84: No | U84: No
A85: Azure AD | B85: SEC0048 | C85: =sheet13[[#This Row],[Nombre]]&sheet13[[#This Row],[Bp Id]] -> Azure ADSEC0048 | D85: =VLOOKUP(sheet13[[#This Row],[Columna1]],Sheet2!C:S,4,FALSE) -> Operativo | E85: Sincronización Usuarios Office 365 | F85: Operativo | G85: B - Ecosistema Apetito de Riesgo | H85: Nube | I85: INFRAESTRUCTURA | J85: BYRON ORLANDO MELENDREZ CABRERA | K85: MARIO ALBERTO TOSCANO GUANIN | L85: RICHARD FABRICIO BRIONES LAICA | M85: Consolas de Administración Seguridad | N85: SI | O85: Usuario Interno | P85: No | Q85: Entra ID | R85: Entra ID | S85: Si | T85: FASE 0 | U85: No
A86: Cheque Image Server (CIS Totem) | B86: CHL0010 | C86: =sheet13[[#This Row],[Nombre]]&sheet13[[#This Row],[Bp Id]] -> Cheque Image Server (CIS Totem)CHL0010 | D86: =VLOOKUP(sheet13[[#This Row],[Columna1]],Sheet2!C:S,4,FALSE) -> Operativo | E86: Componente que permite el envío de imágenes de cheques desde cada ATM de Depositario hacia la solución de Canje Digital (CheqScan). | F86: Operativo | G86: B - Ecosistema Apetito de Riesgo | H86: On Premise | I86: TRIBU_CANALES | J86: DANIEL PATRICIO PAZ ENRIQUEZ | K86: MILTON PATRICIO MANTILLA CAYO | L86: JUAN FRANCISCO PROCEL MICHILENA | M86: Aplicación complementaria | N86: SI | O86: Usuario Interno | P86: No | Q86: Propio | R86: Propio | S86: No | T86: FASE 0 | U86: No
A87: Cisco Collector | B87: ITM0004 | C87: =sheet13[[#This Row],[Nombre]]&sheet13[[#This Row],[Bp Id]] -> Cisco CollectorITM0004 | D87: =VLOOKUP(sheet13[[#This Row],[Columna1]],Sheet2!C:S,4,FALSE) -> Operativo | E87: Herramienta de monitoreo, El Cisco Collector es una herramienta que permite levar el inventario de los equipos Cisco vía SNMP, esta información posteriormente se sincroniza al portal de Cisco NCST donde se puede ver la información de los contratos de soporte por cada equipo, fechas de fin de soporte ETC | F87: Operativo | G87: E - No Crítica | H87: On Premise | I87: INFRAESTRUCTURA | J87: BYRON ORLANDO MELENDREZ CABRERA | K87: MAURICIO FERNANDO NAVAS GALLARDO | L87: HECTOR DAVID CANTOS CEDENO | M87: Consolas de Administración TI | N87: SI | O87: Usuario Interno | P87: Si | Q87: Propio | R87: Propio | S87: No | T87: FASE 0 | U87: No
A88: CLIENT PUEX | B88: CHL0012 | C88: =sheet13[[#This Row],[Nombre]]&sheet13[[#This Row],[Bp Id]] -> CLIENT PUEXCHL0012 | D88: =VLOOKUP(sheet13[[#This Row],[Columna1]],Sheet2!C:S,4,FALSE) -> Retirado | E88: Aplicación que permite la actualización de pantallas de los ATMs y la extracción de EDCs (logs) de los mismos. | F88: Retirado | G88: E - No Crítica | H88: On Premise | I88: TRIBU_CANALES | J88: JUAN FELIPE DIAZ RESTREPO | K88: MILTON PATRICIO MANTILLA CAYO | L88: Nelson Patricio Cardenas Llumiugsi | M88: Aplicación del negocio | N88: NO | O88: Usuario Interno | P88: Si | Q88: GRUPO ACTIVE DIRECTORY | R88: Active Directory | S88: Si | U88: No
A89: COBIS BANCA COMUNAL | B89: PRD0052 | C89: =sheet13[[#This Row],[Nombre]]&sheet13[[#This Row],[Bp Id]] -> COBIS BANCA COMUNALPRD0052 | D89: =VLOOKUP(sheet13[[#This Row],[Columna1]],Sheet2!C:S,4,FALSE) -> Operativo | E89: Gestión de préstamos colectivos. | F89: Operativo | G89: C - BIA Crítica | H89: On Premise | I89: MICROFINANZAS | J89: LAURA ELIZABETH CARRASCO UQUILLAS | K89: MYRIAM ADRIANA YANGUICELA TIPAN | L89: Willam Marcel Ontaneda Yaguana | M89: Aplicación del negocio | N89: SI | O89: Usuario Interno | P89: Si | Q89: Propio | R89: Propio | S89: Si | U89: Si | W89: 45200 | X89: YEPEZ HERRERA SILVIA VIVIANA | Y89: BARAHONA ESPINOSA SANTIAGO ISRAEL | Z89: ZAMBRANO NUNEZ PAUL SANTIAGO | AA89: ETL | AB89: ETL | AC89: GESTIONAR EN LA APLICACION USUARIOS Y ROLES | AD89: Eliminar | AE89: http://10.21.30.70/microbanx/Default.htm
A90: CollabNet Subversion | B90: ITM0007 | C90: =sheet13[[#This Row],[Nombre]]&sheet13[[#This Row],[Bp Id]] -> CollabNet SubversionITM0007 | D90: =VLOOKUP(sheet13[[#This Row],[Columna1]],Sheet2!C:S,4,FALSE) -> Retirado | E90: Herramienta de repositorio de control de versiones | F90: Retirado | G90: E - No Crítica | H90: On Premise | I90: COE de Ingeniería | J90: GERMAN MARTIN GUTIERREZ | K90: GERMAN MARTIN GUTIERREZ | L90: GERMAN MARTIN GUTIERREZ | M90: Consolas de Administración TI | N90: NO | O90: Usuario Interno | P90: Si | Q90: Propio | R90: Propio | S90: No | U90: No
A91: Compass | B91: SEC0076 | C91: =sheet13[[#This Row],[Nombre]]&sheet13[[#This Row],[Bp Id]] -> CompassSEC0076 | D91: =VLOOKUP(sheet13[[#This Row],[Columna1]],Sheet2!C:S,4,FALSE) -> Operativo | E91: Sistema de alarmas | F91: Operativo | G91: C - BIA Crítica | H91: On Premise | I91: Plataformas Ciberseguridad | J91: ANDY JOSE ANDRADE BRAVO | K91: MARCO FABRICIO FALCONI NORIEGA | L91: LUIS ENRIQUE ALVAREZ GARCIA | M91: Consolas de Administración Seguridad | N91: SI | O91: Usuario Interno | P91: Si | Q91: Propio | R91: Propio | S91: Si | U91: Si | V91: Cambiar las contraseñas de los usuarios personalizados periodicamente y enviar por correo ya que no existe el control de caducidad de clave. | W91: 46104 | X91: ANDRADE BRAVO ANDY JOSE | Y91: LEON NOGUERA YOLANDA AMPARO | Z91: BARAHONA ESPINOSA SANTIAGO ISRAEL | AA91: Manual | AB91: Manual | AC91: GESTIONAR EN LA APLICACION USUARIOS Y ROLES | AD91: Eliminar | AE91: Acceso mediante cybeark_x000D_ Server: 10.70.72.246_x000D_ Hostname: prewsf001
A92: Compensacion | B92: SUP0025 | C92: =sheet13[[#This Row],[Nombre]]&sheet13[[#This Row],[Bp Id]] -> CompensacionSUP0025 | D92: =VLOOKUP(sheet13[[#This Row],[Columna1]],Sheet2!C:S,4,FALSE) -> Retirado | E92: Aplicativo encargado de la generación de los archivos para la compensación de empresas de recaudación en CNB's. Frontea la gestión integral y parametrización relacionada con el servicio de compensación general de Banco Pichincha. | F92: Retirado | G92: D - BIA No Crítica | H92: On Premise | I92: EMPRESAS | J92: MIRTHA CATHERINE ARCELA ESPINOZA | K92: GONZALO MARCELO NAZATI GONZALEZ | L92: FRANKLIN HAYBECK SERRANO GOMEZ | M92: Aplicación complementaria | N92: NO | O92: Usuario Interno | P92: Si | Q92: Propio | R92: Propio | S92: Si | U92: Si | V92: SIGLO21 | W92: 45199
A93: Compra de Cartera | B93: PRD0013 | C93: =sheet13[[#This Row],[Nombre]]&sheet13[[#This Row],[Bp Id]] -> Compra de CarteraPRD0013 | D93: =VLOOKUP(sheet13[[#This Row],[Columna1]],Sheet2!C:S,4,FALSE) -> Operativo | E93: Aplicación que permite realizar la pre-validación de las tramas de información de clientes, operaciones y pagos remitidas por las diversas instituciones que le venden cartera a BP, mismas que una vez se encuentren correctas pasaran a ser procesadas en ambiente de producción; y proporcionar los diferentes reportes definidos y necesarios para el seguimiento y gestión de la Cartera, dentro de BP como desde las Casas Comerciales e Instituciones Financieras y no Financieras. | F93: Operativo | G93: E - No Crítica | H93: On Premise | I93: ACTIVOS | J93: LAURA ELIZABETH CARRASCO UQUILLAS | K93: FABRICIO ANTONIO PEREIRA GARCIA | L93: Carlos Ernesto Bolanos Abad | M93: Aplicación complementaria | N93: SI | O93: Usuario Interno | P93: Si | Q93: Propio | R93: Propio | S93: No | T93: =VLOOKUP(sheet13[[#This Row],[Nombre]],[1]Hoja1!A:B,2,FALSE) -> FASE 3 | U93: No
A94: Conexión Empresas Online | B94: PAY0005 | C94: =sheet13[[#This Row],[Nombre]]&sheet13[[#This Row],[Bp Id]] -> Conexión Empresas OnlinePAY0005 | D94: =VLOOKUP(sheet13[[#This Row],[Columna1]],Sheet2!C:S,4,FALSE) -> Operativo | E94: Front del Sitio Web que permite administrar tarjetas prepago. | F94: Operativo | G94: D - BIA No Crítica | H94: Terceros | I94: MEDIOS_DE_PAGO | J94: EDWIN GEOVANNY FLORES CASTRO | K94: DAVID ALEJANDRO CHAVEZ PENAHERRERA | L94: HENRRY DANIEL MORETA IZA | M94: Aplicación del negocio | N94: NO | O94: Clientes | P94: No | Q94: Propio | R94: Propio | S94: No | U94: No
A95: Conexión Personas Online | B95: PAY0006 | C95: =sheet13[[#This Row],[Nombre]]&sheet13[[#This Row],[Bp Id]] -> Conexión Personas OnlinePAY0006 | D95: =VLOOKUP(sheet13[[#This Row],[Columna1]],Sheet2!C:S,4,FALSE) -> Operativo | E95: Front del Sitio Web que permite administrar tarjetas prepago. | F95: Operativo | G95: D - BIA No Crítica | H95: Terceros | I95: MEDIOS_DE_PAGO | J95: EDWIN GEOVANNY FLORES CASTRO | K95: DAVID ALEJANDRO CHAVEZ PENAHERRERA | L95: HENRRY DANIEL MORETA IZA | M95: Aplicación del negocio | N95: SI | O95: Usuario Interno | P95: Si | Q95: Propio | R95: Propio | S95: Si | T95: FASE 0 | U95: No
A96: Configuración Centralizada | B96: SEC0008 | C96: =sheet13[[#This Row],[Nombre]]&sheet13[[#This Row],[Bp Id]] -> Configuración CentralizadaSEC0008 | D96: =VLOOKUP(sheet13[[#This Row],[Columna1]],Sheet2!C:S,4,FALSE) -> Operativo | E96: Aplicativo que permite la administración de las configuraciones de comunicación de las distintas aplicaciones: servidores, usuarios, cadenas de conexión, bases de datos, servicios. | F96: Operativo | G96: B - Ecosistema Apetito de Riesgo | H96: On Premise | I96: Tribu Ciberseguridad | J96: RODNEY XAVIER JACOME TERAN | K96: FRANCISCO DAVID CEVALLOS GRANJA | L96: DIEGO PAUL TAMAYO BARRIGA | M96: Consolas de Administración Seguridad | N96: SI | O96: Usuario Interno | P96: No | Q96: Active Directory | R96: Active Directory | S96: Si | U96: Si | W96: 45200 | Y96: FLORES YAGUANA JHONATAN DAMIAN | Z96: AUQUILLA CHINCHIN GLADYS ARACELI | AA96: ETL | AB96: ETL | AC96: GRUPOS AD | AD96: Eliminar | AE96: http://10.151.12.59/Tcs.ServicioConfiguracion.Web/Paginas/Administracion/Usuarios.aspx
A97: Confluent | B97: OMN0002 | C97: =sheet13[[#This Row],[Nombre]]&sheet13[[#This Row],[Bp Id]] -> ConfluentOMN0002 | D97: =VLOOKUP(sheet13[[#This Row],[Columna1]],Sheet2!C:S,4,FALSE) -> Operativo | E97: No existe descripción | F97: Operativo | G97: E - No Crítica | H97: Nube | I97: COE DATOS&ANALITICA | J97: SANTIAGO ALEXANDER CHERREZ RAMIREZ | K97: JOHANNA ELIZABETH CARANGUI VIVAR | L97: DIEGO VLADIMIR JAYA GUAMANZARA | M97: Aplicación complementaria | N97: SI | O97: Usuario Interno | P97: Si | Q97: Propio | R97: Propio | S97: No | T97: =VLOOKUP(sheet13[[#This Row],[Nombre]],[1]Hoja1!A:B,2,FALSE) -> FASE 1 | U97: No
A98: Control-M | B98: ITM0008 | C98: =sheet13[[#This Row],[Nombre]]&sheet13[[#This Row],[Bp Id]] -> Control-MITM0008 | D98: =VLOOKUP(sheet13[[#This Row],[Columna1]],Sheet2!C:S,4,FALSE) -> Operativo | E98: Herramienta Schedule (Calendarización y ejecución de Procesos Batch) | F98: Operativo | G98: C - BIA Crítica | H98: On Premise | I98: INFRAESTRUCTURA | J98: MARIO SIXTO ZEGARRA OREZZOLI | K98: XAVIER ALEJANDRO JARAMILLO CEVALLOS | L98: HEVER GONZALEZ GARCIA | M98: Consolas de Administración TI | N98: SI | O98: Usuario Interno | P98: Si | Q98: Propio | R98: Propio | S98: Si | T98: FASE 0 | U98: No
A99: Copy Services Manager | B99: ITM0009 | C99: =sheet13[[#This Row],[Nombre]]&sheet13[[#This Row],[Bp Id]] -> Copy Services ManagerITM0009 | D99: =VLOOKUP(sheet13[[#This Row],[Columna1]],Sheet2!C:S,4,FALSE) -> Operativo | E99: Software Administración de Replicas del Storage | F99: Operativo | G99: C - BIA Crítica | H99: On Premise | I99: INFRAESTRUCTURA | J99: BYRON ORLANDO MELENDREZ CABRERA | K99: NELSON ANDRES POZO YEPEZ | L99: PABLO RAUL CAICEDO ARELLANO | M99: Consolas de Administración TI | N99: SI | O99: Usuario Interno | P99: Si | Q99: Propio | R99: Propio | S99: Si | T99: FASE 0 | U99: No
A100: Coren WEB | B100: SEC0071 | C100: =sheet13[[#This Row],[Nombre]]&sheet13[[#This Row],[Bp Id]] -> Coren WEBSEC0071 | D100: =VLOOKUP(sheet13[[#This Row],[Columna1]],Sheet2!C:S,4,FALSE) -> Operativo | E100: Cerraduras electrónicas | F100: Operativo | G100: C - BIA Crítica | H100: On Premise | I100: Plataformas Ciberseguridad | J100: CARLOS ANDRES MORALES MALDONADO | K100: MARCO FABRICIO FALCONI NORIEGA | L100: ANDY JOSE ANDRADE BRAVO | M100: Consolas de Administración Seguridad | N100: SI | O100: Usuario Interno | P100: Si | Q100: Propio | R100: Propio | S100: Si | U100: Si | W100: 45911 | AA100: ETL | AB100: ETL | AC100: GESTIONAR EN LA APLICACION USUARIOS Y ROLES | AD100: Eliminar | AE100: 10.70.72.249:5000
...

Sheet Hoja1
A1: D | B1: D | C1: D | D1: D | G1: D | H1: G
A2: 360 Brand Guardian | B2: SEC0061 | C2: =A2&B2 -> 360 Brand GuardianSEC0061 | D2: =VLOOKUP(C2,Sheet1!C:U,19,FALSE) -> Si | G2: Impresion DocumentosTIE0018 | H2: =VLOOKUP(G2,C:D,2,FALSE) -> Si
A3: Abonos Anticipados | B3: GI0009 | C3: =A3&B3 -> Abonos AnticipadosGI0009 | D3: =VLOOKUP(C3,Sheet1!C:U,19,FALSE) -> Si | G3: informesCreditoPRD0021 | H3: =VLOOKUP(G3,C:D,2,FALSE) -> Si
A4: Active Directory | B4: SEC0047 | C4: =A4&B4 -> Active DirectorySEC0047 | D4: =VLOOKUP(C4,Sheet1!C:U,19,FALSE) -> Si | G4: Integration Bus SoporteINT0009 | H4: =VLOOKUP(G4,C:D,2,FALSE) -> Si
A5: Administracion de cupos y lineas de credito | B5: GI0012 | C5: =A5&B5 -> Administracion de cupos y lineas de creditoGI0012 | D5: =VLOOKUP(C5,Sheet1!C:U,19,FALSE) -> Si | G5: Interdin AS 400/ CAOPAY0010 | H5: =VLOOKUP(G5,C:D,2,FALSE) -> Si
A6: Administrador ATMS | B6: GI0014 | C6: =A6&B6 -> Administrador ATMSGI0014 | D6: =VLOOKUP(C6,Sheet1!C:U,19,FALSE) -> Si | G6: IPS Intrusion Prevention SystemSEC0025 | H6: =VLOOKUP(G6,C:D,2,FALSE) -> Si
A7: Administrador de Crédito | B7: RIS0001 | C7: =A7&B7 -> Administrador de CréditoRIS0001 | D7: =VLOOKUP(C7,Sheet1!C:U,19,FALSE) -> Si | G7: ISESEC0026 | H7: =VLOOKUP(G7,C:D,2,FALSE) -> Si
A8: Administrador de Líneas de Crédito | B8: RIS0002 | C8: =A8&B8 -> Administrador de Líneas de CréditoRIS0002 | D8: =VLOOKUP(C8,Sheet1!C:U,19,FALSE) -> Si | G8: LogiFlowTIE0019 | H8: =VLOOKUP(G8,C:D,2,FALSE) -> Si
A9: Administrador Omnicanal | B9: CHL0003 | C9: =A9&B9 -> Administrador OmnicanalCHL0003 | D9: =VLOOKUP(C9,Sheet1!C:U,19,FALSE) -> Si | G9: LoginCentralSEC0028 | H9: =VLOOKUP(G9,C:D,2,FALSE) -> Si
A10: Administrador Referencias | B10: PRD0001 | C10: =A10&B10 -> Administrador ReferenciasPRD0001 | D10: =VLOOKUP(C10,Sheet1!C:U,19,FALSE) -> Si | G10: Logística de EfectivoCHL0001 | H10: =VLOOKUP(G10,C:D,2,FALSE) -> Si
A11: Akamai WAF | B11: SEC0002 | C11: =A11&B11 -> Akamai WAFSEC0002 | D11: =VLOOKUP(C11,Sheet1!C:U,19,FALSE) -> Si | G11: CreditoDistribuidorPRD0014 | H11: =VLOOKUP(G11,C:D,2,FALSE) -> Si
A12: AM-Menu Accionistas | B12: GI0022 | C12: =A12&B12 -> AM-Menu AccionistasGI0022 | D12: =VLOOKUP(C12,Sheet1!C:U,19,FALSE) -> Si | G12: CreditosCOMPRD0015 | H12: =VLOOKUP(G12,C:D,2,FALSE) -> Si
A13: AntiDDoS Radware | B13: SEC0052 | C13: =A13&B13 -> AntiDDoS RadwareSEC0052 | D13: =VLOOKUP(C13,Sheet1!C:U,19,FALSE) -> Si | G13: CRM (salesforce - Financial services)CUS0007 | H13: =VLOOKUP(G13,C:D,2,FALSE) -> Si
... A181: Siglo21 | B181: SEC0034 | C181: =A181&B181 -> Siglo21SEC0034 | D181: =VLOOKUP(C181,Sheet1!C:U,19,FALSE) -> SI | G181: MSAL Seguridad de Aplicaciones LegadasITM0145 | H181: =VLOOKUP(G181,C:D,2,FALSE) -> SI
G182: Feature Flags TransversalITM0111 | H182: =VLOOKUP(G182,C:D,2,FALSE) -> SI
G183: BPM - BizagiSUP0063 | H183: =VLOOKUP(G183,C:D,2,FALSE) -> Si
G184: HARDWARE SECURITY MODULE - HSMGA0020 | H184: =VLOOKUP(G184,C:D,2,FALSE) -> Si
