Workbook

Sheet Leeme
B2: Modelo Power BI · Portafolio 2026 de Gestión de Identidades
B3: Especificación para replicar en Power BI el dashboard PDF (4 páginas). Fuente: ACTIVIDADES_GI.xlsx, hoja «Actividades GI 2026».
B5: Cómo usar este libro
B6: 1. Parámetros | C6: Hoja «Parametros»: fecha de corte y umbrales. Las celdas amarillas con texto azul son las únicas que se editan. Todo lo demás se recalcula.
B7: 2. Tabla de hechos | C7: Hoja «fHitos»: un registro por hito del plan 2026. Columnas A–L son la copia del origen; M (NIST_Categoria) es la propuesta de mapeo a validar; N en adelante son columnas calculadas con fórmula Excel (su equivalente DAX está en «Columnas_DAX»).
B8: 3. Dimensiones | C8: dFrente (Actividad → Frente, editable), dNIST (categorías CSF 2.0), dEstado y dTipo (orden y colores), dCalendario.
B9: 4. Medidas | C9: Hoja «Medidas_DAX»: todas las medidas con carpeta, formato y el visual donde se usan. Se copian a Power BI con «Nueva medida».
B10: 5. Visuales | C10: Hoja «Visuales»: cada visual del dashboard, tipo de visual en Power BI, campos y formato condicional.
B11: 6. Validación | C11: Hoja «Validacion»: KPIs calculados con fórmulas Excel y el valor publicado en el PDF. Si Power BI da otro número, revisar la medida.
B12: 7. Power Query | C12: Hoja «PowerQuery_M»: script para cargar el Excel original y reproducir fHitos dentro de Power BI.
B13: 8. Tema | C13: Hoja «Tema_PowerBI»: JSON con la paleta Banco Pichincha. Guardar como .json e importarlo en Vista > Temas > Examinar temas.
B15: Modelo recomendado
B16: Relaciones | C16: dCalendario[Fecha] 1 → * fHitos[Fecha Fin Planificación] (activa) dCalendario[Fecha] 1 → * fHitos[Fecha Fin] (inactiva, se activa con USERELATIONSHIP en [Cierres Reales]) dFrente[Actividad] 1 → * fHitos[Actividad] dNIST[Codigo] 1 → * fHitos[NIST_Categoria] dEstado[Estado] 1 → * fHitos[Estado] dTipo[Tipo] 1 → * fHitos[Tipo Actividad] Parametros: tabla desconectada de una fila.
B17: Opción A (rápida) | C17: Importar directamente las tablas de este libro (fHitos, dFrente, dNIST, dEstado, dTipo, dCalendario, Parametros). Las columnas calculadas llegan con el valor que Excel calculó: al cambiar la fecha de corte hay que abrir el libro en Excel, guardar y actualizar Power BI.
B18: Opción B (recomendada) | C18: Cargar el Excel original con el script de «PowerQuery_M», importar de este libro solo las dimensiones y la columna NIST_Categoria, y crear las columnas calculadas con el DAX de «Columnas_DAX». La fecha de corte se toma de la tabla Parametros.
B19: Clave de unión | C19: ID = número de fila del hito en la hoja «Actividades GI 2026» (fila Excel − 1). Si se insertan filas en el origen, volver a revisar el mapeo NIST, que va por ID.
B21: Reglas de negocio
B22: Recurrente | C22: Hito con valor en «Frecuencia» (mensual, semestral, diario). Se excluye de avance, SPI y estados.
B23: Avance esperado | C23: (Corte − Fecha Inicio) / (Fecha Fin Planificación − Fecha Inicio), acotado entre 0 y 1.
B24: Estado | C24: Completado: avance = 100%. Vencido: < 100% y fecha plan < corte. Por iniciar: 0% y sin inicio o inicio posterior al corte. En riesgo: avance − esperado ≤ umbral (−25 pts). En plazo: el resto.
B25: SPI | C25: Avance real promedio / avance esperado promedio (hitos no recurrentes). Azul ≥ 0,90; amarillo 0,75–0,89; rojo < 0,75.
B26: Frente | C26: Agrupación de «Actividad» en 10 frentes de trabajo (tabla dFrente, editable).
B27: NIST_Categoria | C27: Propuesta inferida por palabras clave: la columna NIST del Excel original está vacía. Validar con Gobierno CS antes de publicar.
B29: Convención de colores | C29: Texto azul sobre fondo amarillo = dato editable. Texto negro = fórmula. Fondo gris azulado = columna calculada.

Sheet fHitos
A1: ID | B1: Periodo | C1: Actividad | D1: Descripcion_Hitos | E1: Frecuencia | F1: Tipo Actividad | G1: Encargado | H1: Fecha Inicio | I1: Fecha Fin | J1: Fecha Fin Planificación | K1: % avance | L1: Observación | M1: NIST_Categoria | N1: Frente | O1: NIST_Funcion | P1: Lider | Q1: NumEncargados | R1: Recurrente | S1: AvanceEsperado | T1: Brecha | U1: Estado | V1: Abierto | W1: DiasVencido | X1: DiasRestantes | Y1: MesPlan | Z1: MesCierre | AA1: PlanFinDeMes | AB1: FinIgualPlan | AC1: DQ_FinFuturo | AD1: DQ_FinAntesInicio | AE1: EsRegulatorio | AF1: CodigoPMC | AG1: Expuesto
A2: 1 | B2: 2026 | C2: Gestor de Identidades Sailpoint | Fase 1 | D2: Integración con fuente autoritativa de internos Success Factors | Conector nativo | F2: Iniciativa | G2: Ana María Vergara | H2: 45658 | I2: 46087 | J2: 46084 | K2: 1 | M2: PR.AA-01 | N2: =IFERROR(INDEX(dFrente!$B$2:$B$76,MATCH(C2,dFrente!$A$2:$A$76,0)),"Sin frente") -> SailPoint IGA | O2: =IFERROR(INDEX(dNIST!$B$2:$B$13,MATCH(M2,dNIST!$A$2:$A$13,0)),"") -> PR | P2: =TRIM(IFERROR(LEFT(G2,FIND(CHAR(10),G2)-1),G2)) -> Ana María Vergara | Q2: =LEN(TRIM(G2))-LEN(SUBSTITUTE(TRIM(G2),CHAR(10),""))+1 -> 1 | R2: =IF(E2<>"","Sí","No") -> No | S2: =IF(OR(J2="",H2=""),"",IF(J2<=H2,IF(FechaCorte>=J2,1,0),MAX(0,MIN(1,(FechaCorte-H2)/(J2-H2))))) -> 1 | T2: =IF(S2="","",K2-S2) -> 0 | U2: =IF(R2="Sí","Recurrente",IF(K2>=1,"Completado",IF(AND(J2<>"",J2<FechaCorte),"Vencido",IF(AND(K2=0,OR(H2="",H2>FechaCorte)),"Por iniciar",IF(AND(T2<>"",T2<=UmbralRiesgo),"En riesgo","En plazo"))))) -> Completado | V2: =IF(OR(U2="Vencido",U2="En riesgo",U2="En plazo",U2="Por iniciar"),1,0) -> 0 | W2: =IF(U2="Vencido",FechaCorte-J2,"") | X2: =IF(AND(V2=1,U2<>"Vencido"),J2-FechaCorte,"") | Y2: =IF(J2="","",DATE(YEAR(J2),MONTH(J2),1)) -> 46082 | Z2: =IF(AND(U2="Completado",I2<>""),IF(I2<=FechaCorte,DATE(YEAR(I2),MONTH(I2),1),""),"") -> 46082 | AA2: =IF(J2="","",IF(DAY(J2+1)=1,1,0)) -> 0 | AB2: =IF(AND(U2="Completado",I2<>"",I2=J2),1,0) -> 0 | AC2: =IF(AND(K2>=1,I2<>""),IF(I2>FechaCorte,1,0),0) -> 0 | AD2: =IF(AND(I2<>"",H2<>""),IF(I2<H2,1,0),0) -> 0 | AE2: =IF(OR(F2="Riesgos",F2="Obs. Auditoría"),1,0) -> 0 | AF2: =IFERROR(MID(D2,FIND("PMC-",D2),8),"") | AG2: =IF(AND(V2=1,J2<>""),IF(AND(J2>=FechaCorte,J2<=HorizonteExpuestos),1,0),0) -> 0
A3: 2 | B3: 2026 | C3: Gestor de Identidades Sailpoint | Fase 1 | D3: Integración aplicaciones conectadas: AD, EntraID, Bancs, Siglo21, RHDS y Logiflow | F3: Iniciativa | G3: Ana María Vergara | H3: 45658 | I3: 46087 | J3: 46084 | K3: 1 | M3: PR.AA-01 | N3: =IFERROR(INDEX(dFrente!$B$2:$B$76,MATCH(C3,dFrente!$A$2:$A$76,0)),"Sin frente") -> SailPoint IGA | O3: =IFERROR(INDEX(dNIST!$B$2:$B$13,MATCH(M3,dNIST!$A$2:$A$13,0)),"") -> PR | P3: =TRIM(IFERROR(LEFT(G3,FIND(CHAR(10),G3)-1),G3)) -> Ana María Vergara | Q3: =LEN(TRIM(G3))-LEN(SUBSTITUTE(TRIM(G3),CHAR(10),""))+1 -> 1 | R3: =IF(E3<>"","Sí","No") -> No | S3: =IF(OR(J3="",H3=""),"",IF(J3<=H3,IF(FechaCorte>=J3,1,0),MAX(0,MIN(1,(FechaCorte-H3)/(J3-H3))))) -> 1 | T3: =IF(S3="","",K3-S3) -> 0 | U3: =IF(R3="Sí","Recurrente",IF(K3>=1,"Completado",IF(AND(J3<>"",J3<FechaCorte),"Vencido",IF(AND(K3=0,OR(H3="",H3>FechaCorte)),"Por iniciar",IF(AND(T3<>"",T3<=UmbralRiesgo),"En riesgo","En plazo"))))) -> Completado | V3: =IF(OR(U3="Vencido",U3="En riesgo",U3="En plazo",U3="Por iniciar"),1,0) -> 0 | W3: =IF(U3="Vencido",FechaCorte-J3,"") | X3: =IF(AND(V3=1,U3<>"Vencido"),J3-FechaCorte,"") | Y3: =IF(J3="","",DATE(YEAR(J3),MONTH(J3),1)) -> 46082 | Z3: =IF(AND(U3="Completado",I3<>""),IF(I3<=FechaCorte,DATE(YEAR(I3),MONTH(I3),1),""),"") -> 46082 | AA3: =IF(J3="","",IF(DAY(J3+1)=1,1,0)) -> 0 | AB3: =IF(AND(U3="Completado",I3<>"",I3=J3),1,0) -> 0 | AC3: =IF(AND(K3>=1,I3<>""),IF(I3>FechaCorte,1,0),0) -> 0 | AD3: =IF(AND(I3<>"",H3<>""),IF(I3<H3,1,0),0) -> 0 | AE3: =IF(OR(F3="Riesgos",F3="Obs. Auditoría"),1,0) -> 0 | AF3: =IFERROR(MID(D3,FIND("PMC-",D3),8),"") | AG3: =IF(AND(V3=1,J3<>""),IF(AND(J3>=FechaCorte,J3<=HorizonteExpuestos),1,0),0) -> 0
A4: 3 | B4: 2026 | C4: Gestor de Identidades Sailpoint | Fase 1 | D4: Implementación módulo usuarios externos y genéricos NERM | F4: Iniciativa | G4: Ana María Vergara | H4: 45839 | I4: 46087 | J4: 46084 | K4: 1 | M4: PR.AA-01 | N4: =IFERROR(INDEX(dFrente!$B$2:$B$76,MATCH(C4,dFrente!$A$2:$A$76,0)),"Sin frente") -> SailPoint IGA | O4: =IFERROR(INDEX(dNIST!$B$2:$B$13,MATCH(M4,dNIST!$A$2:$A$13,0)),"") -> PR | P4: =TRIM(IFERROR(LEFT(G4,FIND(CHAR(10),G4)-1),G4)) -> Ana María Vergara | Q4: =LEN(TRIM(G4))-LEN(SUBSTITUTE(TRIM(G4),CHAR(10),""))+1 -> 1 | R4: =IF(E4<>"","Sí","No") -> No | S4: =IF(OR(J4="",H4=""),"",IF(J4<=H4,IF(FechaCorte>=J4,1,0),MAX(0,MIN(1,(FechaCorte-H4)/(J4-H4))))) -> 1 | T4: =IF(S4="","",K4-S4) -> 0 | U4: =IF(R4="Sí","Recurrente",IF(K4>=1,"Completado",IF(AND(J4<>"",J4<FechaCorte),"Vencido",IF(AND(K4=0,OR(H4="",H4>FechaCorte)),"Por iniciar",IF(AND(T4<>"",T4<=UmbralRiesgo),"En riesgo","En plazo"))))) -> Completado | V4: =IF(OR(U4="Vencido",U4="En riesgo",U4="En plazo",U4="Por iniciar"),1,0) -> 0 | W4: =IF(U4="Vencido",FechaCorte-J4,"") | X4: =IF(AND(V4=1,U4<>"Vencido"),J4-FechaCorte,"") | Y4: =IF(J4="","",DATE(YEAR(J4),MONTH(J4),1)) -> 46082 | Z4: =IF(AND(U4="Completado",I4<>""),IF(I4<=FechaCorte,DATE(YEAR(I4),MONTH(I4),1),""),"") -> 46082 | AA4: =IF(J4="","",IF(DAY(J4+1)=1,1,0)) -> 0 | AB4: =IF(AND(U4="Completado",I4<>"",I4=J4),1,0) -> 0 | AC4: =IF(AND(K4>=1,I4<>""),IF(I4>FechaCorte,1,0),0) -> 0 | AD4: =IF(AND(I4<>"",H4<>""),IF(I4<H4,1,0),0) -> 0 | AE4: =IF(OR(F4="Riesgos",F4="Obs. Auditoría"),1,0) -> 0 | AF4: =IFERROR(MID(D4,FIND("PMC-",D4),8),"") | AG4: =IF(AND(V4=1,J4<>""),IF(AND(J4>=FechaCorte,J4<=HorizonteExpuestos),1,0),0) -> 0
A5: 4 | B5: 2026 | C5: Gestor de Identidades Sailpoint | Fase 1 | D5: Depuración accesos acorde al cargo Red de Agencias | F5: Iniciativa | G5: Ana María Fierro | H5: 45962 | I5: 46087 | J5: 46087 | K5: 1 | M5: PR.AA-05 | N5: =IFERROR(INDEX(dFrente!$B$2:$B$76,MATCH(C5,dFrente!$A$2:$A$76,0)),"Sin frente") -> SailPoint IGA | O5: =IFERROR(INDEX(dNIST!$B$2:$B$13,MATCH(M5,dNIST!$A$2:$A$13,0)),"") -> PR | P5: =TRIM(IFERROR(LEFT(G5,FIND(CHAR(10),G5)-1),G5)) -> Ana María Fierro | Q5: =LEN(TRIM(G5))-LEN(SUBSTITUTE(TRIM(G5),CHAR(10),""))+1 -> 1 | R5: =IF(E5<>"","Sí","No") -> No | S5: =IF(OR(J5="",H5=""),"",IF(J5<=H5,IF(FechaCorte>=J5,1,0),MAX(0,MIN(1,(FechaCorte-H5)/(J5-H5))))) -> 1 | T5: =IF(S5="","",K5-S5) -> 0 | U5: =IF(R5="Sí","Recurrente",IF(K5>=1,"Completado",IF(AND(J5<>"",J5<FechaCorte),"Vencido",IF(AND(K5=0,OR(H5="",H5>FechaCorte)),"Por iniciar",IF(AND(T5<>"",T5<=UmbralRiesgo),"En riesgo","En plazo"))))) -> Completado | V5: =IF(OR(U5="Vencido",U5="En riesgo",U5="En plazo",U5="Por iniciar"),1,0) -> 0 | W5: =IF(U5="Vencido",FechaCorte-J5,"") | X5: =IF(AND(V5=1,U5<>"Vencido"),J5-FechaCorte,"") | Y5: =IF(J5="","",DATE(YEAR(J5),MONTH(J5),1)) -> 46082 | Z5: =IF(AND(U5="Completado",I5<>""),IF(I5<=FechaCorte,DATE(YEAR(I5),MONTH(I5),1),""),"") -> 46082 | AA5: =IF(J5="","",IF(DAY(J5+1)=1,1,0)) -> 0 | AB5: =IF(AND(U5="Completado",I5<>"",I5=J5),1,0) -> 1 | AC5: =IF(AND(K5>=1,I5<>""),IF(I5>FechaCorte,1,0),0) -> 0 | AD5: =IF(AND(I5<>"",H5<>""),IF(I5<H5,1,0),0) -> 0 | AE5: =IF(OR(F5="Riesgos",F5="Obs. Auditoría"),1,0) -> 0 | AF5: =IFERROR(MID(D5,FIND("PMC-",D5),8),"") | AG5: =IF(AND(V5=1,J5<>""),IF(AND(J5>=FechaCorte,J5<=HorizonteExpuestos),1,0),0) -> 0
A6: 5 | B6: 2026 | C6: Gestor de Identidades Sailpoint | Fase 1 | D6: Depuración accesos acorde al cargo Microfinanzas | Tecnología | Banca Personas | F6: Iniciativa | G6: Ana María Fierro | H6: 45992 | J6: 46387 | K6: 0.5 | M6: PR.AA-05 | N6: =IFERROR(INDEX(dFrente!$B$2:$B$76,MATCH(C6,dFrente!$A$2:$A$76,0)),"Sin frente") -> SailPoint IGA | O6: =IFERROR(INDEX(dNIST!$B$2:$B$13,MATCH(M6,dNIST!$A$2:$A$13,0)),"") -> PR | P6: =TRIM(IFERROR(LEFT(G6,FIND(CHAR(10),G6)-1),G6)) -> Ana María Fierro | Q6: =LEN(TRIM(G6))-LEN(SUBSTITUTE(TRIM(G6),CHAR(10),""))+1 -> 1 | R6: =IF(E6<>"","Sí","No") -> No | S6: =IF(OR(J6="",H6=""),"",IF(J6<=H6,IF(FechaCorte>=J6,1,0),MAX(0,MIN(1,(FechaCorte-H6)/(J6-H6))))) -> 0.75189873 | T6: =IF(S6="","",K6-S6) -> -0.25189873 | U6: =IF(R6="Sí","Recurrente",IF(K6>=1,"Completado",IF(AND(J6<>"",J6<FechaCorte),"Vencido",IF(AND(K6=0,OR(H6="",H6>FechaCorte)),"Por iniciar",IF(AND(T6<>"",T6<=UmbralRiesgo),"En riesgo","En plazo"))))) -> En riesgo | V6: =IF(OR(U6="Vencido",U6="En riesgo",U6="En plazo",U6="Por iniciar"),1,0) -> 1 | W6: =IF(U6="Vencido",FechaCorte-J6,"") | X6: =IF(AND(V6=1,U6<>"Vencido"),J6-FechaCorte,"") -> 98 | Y6: =IF(J6="","",DATE(YEAR(J6),MONTH(J6),1)) -> 46357 | Z6: =IF(AND(U6="Completado",I6<>""),IF(I6<=FechaCorte,DATE(YEAR(I6),MONTH(I6),1),""),"") | AA6: =IF(J6="","",IF(DAY(J6+1)=1,1,0)) -> 1 | AB6: =IF(AND(U6="Completado",I6<>"",I6=J6),1,0) -> 0 | AC6: =IF(AND(K6>=1,I6<>""),IF(I6>FechaCorte,1,0),0) -> 0 | AD6: =IF(AND(I6<>"",H6<>""),IF(I6<H6,1,0),0) -> 0 | AE6: =IF(OR(F6="Riesgos",F6="Obs. Auditoría"),1,0) -> 0 | AF6: =IFERROR(MID(D6,FIND("PMC-",D6),8),"") | AG6: =IF(AND(V6=1,J6<>""),IF(AND(J6>=FechaCorte,J6<=HorizonteExpuestos),1,0),0) -> 0
A7: 6 | B7: 2026 | C7: Gestor de Identidades Sailpoint | Fase 1 | D7: Implementación modelo de accesos basado en roles | F7: Iniciativa | G7: Richard Requelme | H7: 46082 | I7: 46084 | J7: 46084 | K7: 1 | M7: PR.AA-05 | N7: =IFERROR(INDEX(dFrente!$B$2:$B$76,MATCH(C7,dFrente!$A$2:$A$76,0)),"Sin frente") -> SailPoint IGA | O7: =IFERROR(INDEX(dNIST!$B$2:$B$13,MATCH(M7,dNIST!$A$2:$A$13,0)),"") -> PR | P7: =TRIM(IFERROR(LEFT(G7,FIND(CHAR(10),G7)-1),G7)) -> Richard Requelme | Q7: =LEN(TRIM(G7))-LEN(SUBSTITUTE(TRIM(G7),CHAR(10),""))+1 -> 1 | R7: =IF(E7<>"","Sí","No") -> No | S7: =IF(OR(J7="",H7=""),"",IF(J7<=H7,IF(FechaCorte>=J7,1,0),MAX(0,MIN(1,(FechaCorte-H7)/(J7-H7))))) -> 1 | T7: =IF(S7="","",K7-S7) -> 0 | U7: =IF(R7="Sí","Recurrente",IF(K7>=1,"Completado",IF(AND(J7<>"",J7<FechaCorte),"Vencido",IF(AND(K7=0,OR(H7="",H7>FechaCorte)),"Por iniciar",IF(AND(T7<>"",T7<=UmbralRiesgo),"En riesgo","En plazo"))))) -> Completado | V7: =IF(OR(U7="Vencido",U7="En riesgo",U7="En plazo",U7="Por iniciar"),1,0) -> 0 | W7: =IF(U7="Vencido",FechaCorte-J7,"") | X7: =IF(AND(V7=1,U7<>"Vencido"),J7-FechaCorte,"") | Y7: =IF(J7="","",DATE(YEAR(J7),MONTH(J7),1)) -> 46082 | Z7: =IF(AND(U7="Completado",I7<>""),IF(I7<=FechaCorte,DATE(YEAR(I7),MONTH(I7),1),""),"") -> 46082 | AA7: =IF(J7="","",IF(DAY(J7+1)=1,1,0)) -> 0 | AB7: =IF(AND(U7="Completado",I7<>"",I7=J7),1,0) -> 1 | AC7: =IF(AND(K7>=1,I7<>""),IF(I7>FechaCorte,1,0),0) -> 0 | AD7: =IF(AND(I7<>"",H7<>""),IF(I7<H7,1,0),0) -> 0 | AE7: =IF(OR(F7="Riesgos",F7="Obs. Auditoría"),1,0) -> 0 | AF7: =IFERROR(MID(D7,FIND("PMC-",D7),8),"") | AG7: =IF(AND(V7=1,J7<>""),IF(AND(J7>=FechaCorte,J7<=HorizonteExpuestos),1,0),0) -> 0
A8: 7 | B8: 2026 | C8: Gestor de Identidades Sailpoint | Fase 1 | D8: Eliminación de accesos a personal de Negocios (Red de Agencias) para cambiar perfiles globales y centros de costos directamente. | F8: Iniciativa | G8: Ana María Fierro | H8: 46082 | I8: 46080 | J8: 46080 | K8: 1 | L8: Gestionaban 1478 requerimientos al mes, que pasaron a GI. | M8: PR.AA-05 | N8: =IFERROR(INDEX(dFrente!$B$2:$B$76,MATCH(C8,dFrente!$A$2:$A$76,0)),"Sin frente") -> SailPoint IGA | O8: =IFERROR(INDEX(dNIST!$B$2:$B$13,MATCH(M8,dNIST!$A$2:$A$13,0)),"") -> PR | P8: =TRIM(IFERROR(LEFT(G8,FIND(CHAR(10),G8)-1),G8)) -> Ana María Fierro | Q8: =LEN(TRIM(G8))-LEN(SUBSTITUTE(TRIM(G8),CHAR(10),""))+1 -> 1 | R8: =IF(E8<>"","Sí","No") -> No | S8: =IF(OR(J8="",H8=""),"",IF(J8<=H8,IF(FechaCorte>=J8,1,0),MAX(0,MIN(1,(FechaCorte-H8)/(J8-H8))))) -> 1 | T8: =IF(S8="","",K8-S8) -> 0 | U8: =IF(R8="Sí","Recurrente",IF(K8>=1,"Completado",IF(AND(J8<>"",J8<FechaCorte),"Vencido",IF(AND(K8=0,OR(H8="",H8>FechaCorte)),"Por iniciar",IF(AND(T8<>"",T8<=UmbralRiesgo),"En riesgo","En plazo"))))) -> Completado | V8: =IF(OR(U8="Vencido",U8="En riesgo",U8="En plazo",U8="Por iniciar"),1,0) -> 0 | W8: =IF(U8="Vencido",FechaCorte-J8,"") | X8: =IF(AND(V8=1,U8<>"Vencido"),J8-FechaCorte,"") | Y8: =IF(J8="","",DATE(YEAR(J8),MONTH(J8),1)) -> 46054 | Z8: =IF(AND(U8="Completado",I8<>""),IF(I8<=FechaCorte,DATE(YEAR(I8),MONTH(I8),1),""),"") -> 46054 | AA8: =IF(J8="","",IF(DAY(J8+1)=1,1,0)) -> 0 | AB8: =IF(AND(U8="Completado",I8<>"",I8=J8),1,0) -> 1 | AC8: =IF(AND(K8>=1,I8<>""),IF(I8>FechaCorte,1,0),0) -> 0 | AD8: =IF(AND(I8<>"",H8<>""),IF(I8<H8,1,0),0) -> 1 | AE8: =IF(OR(F8="Riesgos",F8="Obs. Auditoría"),1,0) -> 0 | AF8: =IFERROR(MID(D8,FIND("PMC-",D8),8),"") | AG8: =IF(AND(V8=1,J8<>""),IF(AND(J8>=FechaCorte,J8<=HorizonteExpuestos),1,0),0) -> 0
A9: 8 | B9: 2026 | C9: Gestor de Identidades Sailpoint | Fase 2 | D9: Inactivar cuentas de usuarios por vacaciones/licencias/maternidad, etc. (Flujo y revisión RRHH) | F9: Iniciativa | G9: Ana María Vergara | H9: 46327 | J9: 46387 | K9: 0 | L9: Dependencia de revisión con RRHH. Se realizará el acercamiento para validar la factibilidad de implementación | M9: PR.AA-01 | N9: =IFERROR(INDEX(dFrente!$B$2:$B$76,MATCH(C9,dFrente!$A$2:$A$76,0)),"Sin frente") -> SailPoint IGA | O9: =IFERROR(INDEX(dNIST!$B$2:$B$13,MATCH(M9,dNIST!$A$2:$A$13,0)),"") -> PR | P9: =TRIM(IFERROR(LEFT(G9,FIND(CHAR(10),G9)-1),G9)) -> Ana María Vergara | Q9: =LEN(TRIM(G9))-LEN(SUBSTITUTE(TRIM(G9),CHAR(10),""))+1 -> 1 | R9: =IF(E9<>"","Sí","No") -> No | S9: =IF(OR(J9="",H9=""),"",IF(J9<=H9,IF(FechaCorte>=J9,1,0),MAX(0,MIN(1,(FechaCorte-H9)/(J9-H9))))) -> 0 | T9: =IF(S9="","",K9-S9) -> 0 | U9: =IF(R9="Sí","Recurrente",IF(K9>=1,"Completado",IF(AND(J9<>"",J9<FechaCorte),"Vencido",IF(AND(K9=0,OR(H9="",H9>FechaCorte)),"Por iniciar",IF(AND(T9<>"",T9<=UmbralRiesgo),"En riesgo","En plazo"))))) -> Por iniciar | V9: =IF(OR(U9="Vencido",U9="En riesgo",U9="En plazo",U9="Por iniciar"),1,0) -> 1 | W9: =IF(U9="Vencido",FechaCorte-J9,"") | X9: =IF(AND(V9=1,U9<>"Vencido"),J9-FechaCorte,"") -> 98 | Y9: =IF(J9="","",DATE(YEAR(J9),MONTH(J9),1)) -> 46357 | Z9: =IF(AND(U9="Completado",I9<>""),IF(I9<=FechaCorte,DATE(YEAR(I9),MONTH(I9),1),""),"") | AA9: =IF(J9="","",IF(DAY(J9+1)=1,1,0)) -> 1 | AB9: =IF(AND(U9="Completado",I9<>"",I9=J9),1,0) -> 0 | AC9: =IF(AND(K9>=1,I9<>""),IF(I9>FechaCorte,1,0),0) -> 0 | AD9: =IF(AND(I9<>"",H9<>""),IF(I9<H9,1,0),0) -> 0 | AE9: =IF(OR(F9="Riesgos",F9="Obs. Auditoría"),1,0) -> 0 | AF9: =IFERROR(MID(D9,FIND("PMC-",D9),8),"") | AG9: =IF(AND(V9=1,J9<>""),IF(AND(J9>=FechaCorte,J9<=HorizonteExpuestos),1,0),0) -> 0
A10: 9 | B10: 2026 | C10: Gestor de Identidades Sailpoint | Fase 2 | D10: Evaluación automatización y Monitoreo de Accesos VPN Integrado a ISC SailPoint | F10: Iniciativa | G10: Jhonny Barreiro | H10: 46143 | J10: 46235 | K10: 0.05 | L10: en diseño de definiciones | M10: DE.CM | N10: =IFERROR(INDEX(dFrente!$B$2:$B$76,MATCH(C10,dFrente!$A$2:$A$76,0)),"Sin frente") -> SailPoint IGA | O10: =IFERROR(INDEX(dNIST!$B$2:$B$13,MATCH(M10,dNIST!$A$2:$A$13,0)),"") -> DE | P10: =TRIM(IFERROR(LEFT(G10,FIND(CHAR(10),G10)-1),G10)) -> Jhonny Barreiro | Q10: =LEN(TRIM(G10))-LEN(SUBSTITUTE(TRIM(G10),CHAR(10),""))+1 -> 1 | R10: =IF(E10<>"","Sí","No") -> No | S10: =IF(OR(J10="",H10=""),"",IF(J10<=H10,IF(FechaCorte>=J10,1,0),MAX(0,MIN(1,(FechaCorte-H10)/(J10-H10))))) -> 1 | T10: =IF(S10="","",K10-S10) -> -0.95 | U10: =IF(R10="Sí","Recurrente",IF(K10>=1,"Completado",IF(AND(J10<>"",J10<FechaCorte),"Vencido",IF(AND(K10=0,OR(H10="",H10>FechaCorte)),"Por iniciar",IF(AND(T10<>"",T10<=UmbralRiesgo),"En riesgo","En plazo"))))) -> Vencido | V10: =IF(OR(U10="Vencido",U10="En riesgo",U10="En plazo",U10="Por iniciar"),1,0) -> 1 | W10: =IF(U10="Vencido",FechaCorte-J10,"") -> 54 | X10: =IF(AND(V10=1,U10<>"Vencido"),J10-FechaCorte,"") | Y10: =IF(J10="","",DATE(YEAR(J10),MONTH(J10),1)) -> 46235 | Z10: =IF(AND(U10="Completado",I10<>""),IF(I10<=FechaCorte,DATE(YEAR(I10),MONTH(I10),1),""),"") | AA10: =IF(J10="","",IF(DAY(J10+1)=1,1,0)) -> 0 | AB10: =IF(AND(U10="Completado",I10<>"",I10=J10),1,0) -> 0 | AC10: =IF(AND(K10>=1,I10<>""),IF(I10>FechaCorte,1,0),0) -> 0 | AD10: =IF(AND(I10<>"",H10<>""),IF(I10<H10,1,0),0) -> 0 | AE10: =IF(OR(F10="Riesgos",F10="Obs. Auditoría"),1,0) -> 0 | AF10: =IFERROR(MID(D10,FIND("PMC-",D10),8),"") | AG10: =IF(AND(V10=1,J10<>""),IF(AND(J10>=FechaCorte,J10<=HorizonteExpuestos),1,0),0) -> 0
A11: 10 | B11: 2026 | C11: Gestor de Identidades Sailpoint | Fase 2 | D11: Implementar la deshabilitación automática en SailPoint para el offboarding de internos | F11: Iniciativa | G11: Ana María Vergara | H11: 46143 | I11: 46143 | J11: 46143 | K11: 1 | L11: Flujo implementado dependencia con "end date" consumido desde SSFF | M11: PR.AA-01 | N11: =IFERROR(INDEX(dFrente!$B$2:$B$76,MATCH(C11,dFrente!$A$2:$A$76,0)),"Sin frente") -> SailPoint IGA | O11: =IFERROR(INDEX(dNIST!$B$2:$B$13,MATCH(M11,dNIST!$A$2:$A$13,0)),"") -> PR | P11: =TRIM(IFERROR(LEFT(G11,FIND(CHAR(10),G11)-1),G11)) -> Ana María Vergara | Q11: =LEN(TRIM(G11))-LEN(SUBSTITUTE(TRIM(G11),CHAR(10),""))+1 -> 1 | R11: =IF(E11<>"","Sí","No") -> No | S11: =IF(OR(J11="",H11=""),"",IF(J11<=H11,IF(FechaCorte>=J11,1,0),MAX(0,MIN(1,(FechaCorte-H11)/(J11-H11))))) -> 1 | T11: =IF(S11="","",K11-S11) -> 0 | U11: =IF(R11="Sí","Recurrente",IF(K11>=1,"Completado",IF(AND(J11<>"",J11<FechaCorte),"Vencido",IF(AND(K11=0,OR(H11="",H11>FechaCorte)),"Por iniciar",IF(AND(T11<>"",T11<=UmbralRiesgo),"En riesgo","En plazo"))))) -> Completado | V11: =IF(OR(U11="Vencido",U11="En riesgo",U11="En plazo",U11="Por iniciar"),1,0) -> 0 | W11: =IF(U11="Vencido",FechaCorte-J11,"") | X11: =IF(AND(V11=1,U11<>"Vencido"),J11-FechaCorte,"") | Y11: =IF(J11="","",DATE(YEAR(J11),MONTH(J11),1)) -> 46143 | Z11: =IF(AND(U11="Completado",I11<>""),IF(I11<=FechaCorte,DATE(YEAR(I11),MONTH(I11),1),""),"") -> 46143 | AA11: =IF(J11="","",IF(DAY(J11+1)=1,1,0)) -> 0 | AB11: =IF(AND(U11="Completado",I11<>"",I11=J11),1,0) -> 1 | AC11: =IF(AND(K11>=1,I11<>""),IF(I11>FechaCorte,1,0),0) -> 0 | AD11: =IF(AND(I11<>"",H11<>""),IF(I11<H11,1,0),0) -> 0 | AE11: =IF(OR(F11="Riesgos",F11="Obs. Auditoría"),1,0) -> 0 | AF11: =IFERROR(MID(D11,FIND("PMC-",D11),8),"") | AG11: =IF(AND(V11=1,J11<>""),IF(AND(J11>=FechaCorte,J11<=HorizonteExpuestos),1,0),0) -> 0
A12: 11 | B12: 2026 | C12: Gestor de Identidades Sailpoint | Fase 2 | D12: Ajustar las notificaciones generadas por ISC para retirar informaión sensible. Ajustar formatos | F12: Mejora | G12: Ana María Vergara | H12: 46143 | J12: 46387 | K12: 0.25 | L12: - Revisión integral de datos sensibles en comunicados fueron retirados - Flujo notificación onboarding de usuarios externos revisado e implementado - Fecha fin vigencia externos (comunicado). | M12: PR.AA-01 | N12: =IFERROR(INDEX(dFrente!$B$2:$B$76,MATCH(C12,dFrente!$A$2:$A$76,0)),"Sin frente") -> SailPoint IGA | O12: =IFERROR(INDEX(dNIST!$B$2:$B$13,MATCH(M12,dNIST!$A$2:$A$13,0)),"") -> PR | P12: =TRIM(IFERROR(LEFT(G12,FIND(CHAR(10),G12)-1),G12)) -> Ana María Vergara | Q12: =LEN(TRIM(G12))-LEN(SUBSTITUTE(TRIM(G12),CHAR(10),""))+1 -> 1 | R12: =IF(E12<>"","Sí","No") -> No | S12: =IF(OR(J12="",H12=""),"",IF(J12<=H12,IF(FechaCorte>=J12,1,0),MAX(0,MIN(1,(FechaCorte-H12)/(J12-H12))))) -> 0.59836066 | T12: =IF(S12="","",K12-S12) -> -0.34836066 | U12: =IF(R12="Sí","Recurrente",IF(K12>=1,"Completado",IF(AND(J12<>"",J12<FechaCorte),"Vencido",IF(AND(K12=0,OR(H12="",H12>FechaCorte)),"Por iniciar",IF(AND(T12<>"",T12<=UmbralRiesgo),"En riesgo","En plazo"))))) -> En riesgo | V12: =IF(OR(U12="Vencido",U12="En riesgo",U12="En plazo",U12="Por iniciar"),1,0) -> 1 | W12: =IF(U12="Vencido",FechaCorte-J12,"") | X12: =IF(AND(V12=1,U12<>"Vencido"),J12-FechaCorte,"") -> 98 | Y12: =IF(J12="","",DATE(YEAR(J12),MONTH(J12),1)) -> 46357 | Z12: =IF(AND(U12="Completado",I12<>""),IF(I12<=FechaCorte,DATE(YEAR(I12),MONTH(I12),1),""),"") | AA12: =IF(J12="","",IF(DAY(J12+1)=1,1,0)) -> 1 | AB12: =IF(AND(U12="Completado",I12<>"",I12=J12),1,0) -> 0 | AC12: =IF(AND(K12>=1,I12<>""),IF(I12>FechaCorte,1,0),0) -> 0 | AD12: =IF(AND(I12<>"",H12<>""),IF(I12<H12,1,0),0) -> 0 | AE12: =IF(OR(F12="Riesgos",F12="Obs. Auditoría"),1,0) -> 0 | AF12: =IFERROR(MID(D12,FIND("PMC-",D12),8),"") | AG12: =IF(AND(V12=1,J12<>""),IF(AND(J12>=FechaCorte,J12<=HorizonteExpuestos),1,0),0) -> 0
A13: 12 | B13: 2026 | C13: Gestor de Identidades Sailpoint | Fase 2 | D13: Revisión duplicidad tickets generados desde ISC | F13: Mejora | G13: Ana María Vergara | H13: 46143 | J13: 46326 | K13: 0.75 | L13: - En proceso de revisión dependencia con la marca SailPoint - Se requiere soporte del proveedor Heaven a espera de apertura de adenda de servicios - 16 Sept 2026 se realizaron las pruebas en ambiente de test y se desplegaron de forma exitosa. Se solicita a marca SailPoint el despliegue en producción, en espera de respuesta de confirmación | M13: PR.AA-01 | N13: =IFERROR(INDEX(dFrente!$B$2:$B$76,MATCH(C13,dFrente!$A$2:$A$76,0)),"Sin frente") -> SailPoint IGA | O13: =IFERROR(INDEX(dNIST!$B$2:$B$13,MATCH(M13,dNIST!$A$2:$A$13,0)),"") -> PR | P13: =TRIM(IFERROR(LEFT(G13,FIND(CHAR(10),G13)-1),G13)) -> Ana María Vergara | Q13: =LEN(TRIM(G13))-LEN(SUBSTITUTE(TRIM(G13),CHAR(10),""))+1 -> 1 | R13: =IF(E13<>"","Sí","No") -> No | S13: =IF(OR(J13="",H13=""),"",IF(J13<=H13,IF(FechaCorte>=J13,1,0),MAX(0,MIN(1,(FechaCorte-H13)/(J13-H13))))) -> 0.79781421 | T13: =IF(S13="","",K13-S13) -> -0.047814208 | U13: =IF(R13="Sí","Recurrente",IF(K13>=1,"Completado",IF(AND(J13<>"",J13<FechaCorte),"Vencido",IF(AND(K13=0,OR(H13="",H13>FechaCorte)),"Por iniciar",IF(AND(T13<>"",T13<=UmbralRiesgo),"En riesgo","En plazo"))))) -> En plazo | V13: =IF(OR(U13="Vencido",U13="En riesgo",U13="En plazo",U13="Por iniciar"),1,0) -> 1 | W13: =IF(U13="Vencido",FechaCorte-J13,"") | X13: =IF(AND(V13=1,U13<>"Vencido"),J13-FechaCorte,"") -> 37 | Y13: =IF(J13="","",DATE(YEAR(J13),MONTH(J13),1)) -> 46296 | Z13: =IF(AND(U13="Completado",I13<>""),IF(I13<=FechaCorte,DATE(YEAR(I13),MONTH(I13),1),""),"") | AA13: =IF(J13="","",IF(DAY(J13+1)=1,1,0)) -> 1 | AB13: =IF(AND(U13="Completado",I13<>"",I13=J13),1,0) -> 0 | AC13: =IF(AND(K13>=1,I13<>""),IF(I13>FechaCorte,1,0),0) -> 0 | AD13: =IF(AND(I13<>"",H13<>""),IF(I13<H13,1,0),0) -> 0 | AE13: =IF(OR(F13="Riesgos",F13="Obs. Auditoría"),1,0) -> 0 | AF13: =IFERROR(MID(D13,FIND("PMC-",D13),8),"") | AG13: =IF(AND(V13=1,J13<>""),IF(AND(J13>=FechaCorte,J13<=HorizonteExpuestos),1,0),0) -> 0
A14: 13 | B14: 2026 | C14: Gestor de Identidades Sailpoint | Fase 2 | D14: Ajustar configuración para catálogo "Cambio Centro Costos" reducción generación tickets | F14: Mejora | G14: Ana María Vergara | H14: 46143 | I14: 46173 | J14: 46173 | K14: 1 | L14: Se implemento el ajuste en SailPoint para que solo consuma las aplicaciones en las que se debe generar un cambio en el centro de costos | M14: PR.AA-01 | N14: =IFERROR(INDEX(dFrente!$B$2:$B$76,MATCH(C14,dFrente!$A$2:$A$76,0)),"Sin frente") -> SailPoint IGA | O14: =IFERROR(INDEX(dNIST!$B$2:$B$13,MATCH(M14,dNIST!$A$2:$A$13,0)),"") -> PR | P14: =TRIM(IFERROR(LEFT(G14,FIND(CHAR(10),G14)-1),G14)) -> Ana María Vergara | Q14: =LEN(TRIM(G14))-LEN(SUBSTITUTE(TRIM(G14),CHAR(10),""))+1 -> 1 | R14: =IF(E14<>"","Sí","No") -> No | S14: =IF(OR(J14="",H14=""),"",IF(J14<=H14,IF(FechaCorte>=J14,1,0),MAX(0,MIN(1,(FechaCorte-H14)/(J14-H14))))) -> 1 | T14: =IF(S14="","",K14-S14) -> 0 | U14: =IF(R14="Sí","Recurrente",IF(K14>=1,"Completado",IF(AND(J14<>"",J14<FechaCorte),"Vencido",IF(AND(K14=0,OR(H14="",H14>FechaCorte)),"Por iniciar",IF(AND(T14<>"",T14<=UmbralRiesgo),"En riesgo","En plazo"))))) -> Completado | V14: =IF(OR(U14="Vencido",U14="En riesgo",U14="En plazo",U14="Por iniciar"),1,0) -> 0 | W14: =IF(U14="Vencido",FechaCorte-J14,"") | X14: =IF(AND(V14=1,U14<>"Vencido"),J14-FechaCorte,"") | Y14: =IF(J14="","",DATE(YEAR(J14),MONTH(J14),1)) -> 46143 | Z14: =IF(AND(U14="Completado",I14<>""),IF(I14<=FechaCorte,DATE(YEAR(I14),MONTH(I14),1),""),"") -> 46143 | AA14: =IF(J14="","",IF(DAY(J14+1)=1,1,0)) -> 1 | AB14: =IF(AND(U14="Completado",I14<>"",I14=J14),1,0) -> 1 | AC14: =IF(AND(K14>=1,I14<>""),IF(I14>FechaCorte,1,0),0) -> 0 | AD14: =IF(AND(I14<>"",H14<>""),IF(I14<H14,1,0),0) -> 0 | AE14: =IF(OR(F14="Riesgos",F14="Obs. Auditoría"),1,0) -> 0 | AF14: =IFERROR(MID(D14,FIND("PMC-",D14),8),"") | AG14: =IF(AND(V14=1,J14<>""),IF(AND(J14>=FechaCorte,J14<=HorizonteExpuestos),1,0),0) -> 0
A15: 14 | B15: 2026 | C15: Gestor de Identidades Sailpoint | Fase 2 | D15: Cambio de dominio de sailpoint.com a pichincha.com para las notificaciones generadas. | F15: Mejora | G15: Ana María Vergara | H15: 46113 | I15: 46153 | J15: 46153 | K15: 1 | M15: PR.AA-01 | N15: =IFERROR(INDEX(dFrente!$B$2:$B$76,MATCH(C15,dFrente!$A$2:$A$76,0)),"Sin frente") -> SailPoint IGA | O15: =IFERROR(INDEX(dNIST!$B$2:$B$13,MATCH(M15,dNIST!$A$2:$A$13,0)),"") -> PR | P15: =TRIM(IFERROR(LEFT(G15,FIND(CHAR(10),G15)-1),G15)) -> Ana María Vergara | Q15: =LEN(TRIM(G15))-LEN(SUBSTITUTE(TRIM(G15),CHAR(10),""))+1 -> 1 | R15: =IF(E15<>"","Sí","No") -> No | S15: =IF(OR(J15="",H15=""),"",IF(J15<=H15,IF(FechaCorte>=J15,1,0),MAX(0,MIN(1,(FechaCorte-H15)/(J15-H15))))) -> 1 | T15: =IF(S15="","",K15-S15) -> 0 | U15: =IF(R15="Sí","Recurrente",IF(K15>=1,"Completado",IF(AND(J15<>"",J15<FechaCorte),"Vencido",IF(AND(K15=0,OR(H15="",H15>FechaCorte)),"Por iniciar",IF(AND(T15<>"",T15<=UmbralRiesgo),"En riesgo","En plazo"))))) -> Completado | V15: =IF(OR(U15="Vencido",U15="En riesgo",U15="En plazo",U15="Por iniciar"),1,0) -> 0 | W15: =IF(U15="Vencido",FechaCorte-J15,"") | X15: =IF(AND(V15=1,U15<>"Vencido"),J15-FechaCorte,"") | Y15: =IF(J15="","",DATE(YEAR(J15),MONTH(J15),1)) -> 46143 | Z15: =IF(AND(U15="Completado",I15<>""),IF(I15<=FechaCorte,DATE(YEAR(I15),MONTH(I15),1),""),"") -> 46143 | AA15: =IF(J15="","",IF(DAY(J15+1)=1,1,0)) -> 0 | AB15: =IF(AND(U15="Completado",I15<>"",I15=J15),1,0) -> 1 | AC15: =IF(AND(K15>=1,I15<>""),IF(I15>FechaCorte,1,0),0) -> 0 | AD15: =IF(AND(I15<>"",H15<>""),IF(I15<H15,1,0),0) -> 0 | AE15: =IF(OR(F15="Riesgos",F15="Obs. Auditoría"),1,0) -> 0 | AF15: =IFERROR(MID(D15,FIND("PMC-",D15),8),"") | AG15: =IF(AND(V15=1,J15<>""),IF(AND(J15>=FechaCorte,J15<=HorizonteExpuestos),1,0),0) -> 0
A16: 15 | B16: 2026 | C16: Gestor de Identidades Sailpoint | Fase 2 | D16: Sincronización Campo AD Manager | F16: Mejora | G16: Ana María Vergara | H16: 46143 | I16: 46155 | J16: 46155 | K16: 1 | M16: PR.AA-01 | N16: =IFERROR(INDEX(dFrente!$B$2:$B$76,MATCH(C16,dFrente!$A$2:$A$76,0)),"Sin frente") -> SailPoint IGA | O16: =IFERROR(INDEX(dNIST!$B$2:$B$13,MATCH(M16,dNIST!$A$2:$A$13,0)),"") -> PR | P16: =TRIM(IFERROR(LEFT(G16,FIND(CHAR(10),G16)-1),G16)) -> Ana María Vergara | Q16: =LEN(TRIM(G16))-LEN(SUBSTITUTE(TRIM(G16),CHAR(10),""))+1 -> 1 | R16: =IF(E16<>"","Sí","No") -> No | S16: =IF(OR(J16="",H16=""),"",IF(J16<=H16,IF(FechaCorte>=J16,1,0),MAX(0,MIN(1,(FechaCorte-H16)/(J16-H16))))) -> 1 | T16: =IF(S16="","",K16-S16) -> 0 | U16: =IF(R16="Sí","Recurrente",IF(K16>=1,"Completado",IF(AND(J16<>"",J16<FechaCorte),"Vencido",IF(AND(K16=0,OR(H16="",H16>FechaCorte)),"Por iniciar",IF(AND(T16<>"",T16<=UmbralRiesgo),"En riesgo","En plazo"))))) -> Completado | V16: =IF(OR(U16="Vencido",U16="En riesgo",U16="En plazo",U16="Por iniciar"),1,0) -> 0 | W16: =IF(U16="Vencido",FechaCorte-J16,"") | X16: =IF(AND(V16=1,U16<>"Vencido"),J16-FechaCorte,"") | Y16: =IF(J16="","",DATE(YEAR(J16),MONTH(J16),1)) -> 46143 | Z16: =IF(AND(U16="Completado",I16<>""),IF(I16<=FechaCorte,DATE(YEAR(I16),MONTH(I16),1),""),"") -> 46143 | AA16: =IF(J16="","",IF(DAY(J16+1)=1,1,0)) -> 0 | AB16: =IF(AND(U16="Completado",I16<>"",I16=J16),1,0) -> 1 | AC16: =IF(AND(K16>=1,I16<>""),IF(I16>FechaCorte,1,0),0) -> 0 | AD16: =IF(AND(I16<>"",H16<>""),IF(I16<H16,1,0),0) -> 0 | AE16: =IF(OR(F16="Riesgos",F16="Obs. Auditoría"),1,0) -> 0 | AF16: =IFERROR(MID(D16,FIND("PMC-",D16),8),"") | AG16: =IF(AND(V16=1,J16<>""),IF(AND(J16>=FechaCorte,J16<=HorizonteExpuestos),1,0),0) -> 0
A17: 16 | B17: 2026 | C17: Gestor de Identidades Sailpoint | Fase 2 | D17: Depuración usuarios duplicados en AD | Identificación y corrección de inconsistencias asociadas a la causa raíz | F17: Incidencia | G17: Ana María Vergara | H17: 46155 | I17: 46161 | J17: 46161 | K17: 1 | L17: 108 usuarios duplicados. Se incluye en el control mensual de TCS. | M17: PR.AA-01 | N17: =IFERROR(INDEX(dFrente!$B$2:$B$76,MATCH(C17,dFrente!$A$2:$A$76,0)),"Sin frente") -> SailPoint IGA | O17: =IFERROR(INDEX(dNIST!$B$2:$B$13,MATCH(M17,dNIST!$A$2:$A$13,0)),"") -> PR | P17: =TRIM(IFERROR(LEFT(G17,FIND(CHAR(10),G17)-1),G17)) -> Ana María Vergara | Q17: =LEN(TRIM(G17))-LEN(SUBSTITUTE(TRIM(G17),CHAR(10),""))+1 -> 1 | R17: =IF(E17<>"","Sí","No") -> No | S17: =IF(OR(J17="",H17=""),"",IF(J17<=H17,IF(FechaCorte>=J17,1,0),MAX(0,MIN(1,(FechaCorte-H17)/(J17-H17))))) -> 1 | T17: =IF(S17="","",K17-S17) -> 0 | U17: =IF(R17="Sí","Recurrente",IF(K17>=1,"Completado",IF(AND(J17<>"",J17<FechaCorte),"Vencido",IF(AND(K17=0,OR(H17="",H17>FechaCorte)),"Por iniciar",IF(AND(T17<>"",T17<=UmbralRiesgo),"En riesgo","En plazo"))))) -> Completado | V17: =IF(OR(U17="Vencido",U17="En riesgo",U17="En plazo",U17="Por iniciar"),1,0) -> 0 | W17: =IF(U17="Vencido",FechaCorte-J17,"") | X17: =IF(AND(V17=1,U17<>"Vencido"),J17-FechaCorte,"") | Y17: =IF(J17="","",DATE(YEAR(J17),MONTH(J17),1)) -> 46143 | Z17: =IF(AND(U17="Completado",I17<>""),IF(I17<=FechaCorte,DATE(YEAR(I17),MONTH(I17),1),""),"") -> 46143 | AA17: =IF(J17="","",IF(DAY(J17+1)=1,1,0)) -> 0 | AB17: =IF(AND(U17="Completado",I17<>"",I17=J17),1,0) -> 1 | AC17: =IF(AND(K17>=1,I17<>""),IF(I17>FechaCorte,1,0),0) -> 0 | AD17: =IF(AND(I17<>"",H17<>""),IF(I17<H17,1,0),0) -> 0 | AE17: =IF(OR(F17="Riesgos",F17="Obs. Auditoría"),1,0) -> 0 | AF17: =IFERROR(MID(D17,FIND("PMC-",D17),8),"") | AG17: =IF(AND(V17=1,J17<>""),IF(AND(J17>=FechaCorte,J17<=HorizonteExpuestos),1,0),0) -> 0
A18: 17 | B18: 2026 | C18: Gestor de Identidades Sailpoint | Fase 2 | D18: Modificación campo "Last Name" en Externos y revisar novedad en los apellidos que se envia desde ISC hacia el AD. | F18: Iniciativa | G18: Ana María Vergara Jhonny Barreiro | H18: 46155 | I18: 46168 | J18: 46168 | K18: 1 | M18: PR.AA-01 | N18: =IFERROR(INDEX(dFrente!$B$2:$B$76,MATCH(C18,dFrente!$A$2:$A$76,0)),"Sin frente") -> SailPoint IGA | O18: =IFERROR(INDEX(dNIST!$B$2:$B$13,MATCH(M18,dNIST!$A$2:$A$13,0)),"") -> PR | P18: =TRIM(IFERROR(LEFT(G18,FIND(CHAR(10),G18)-1),G18)) -> Ana María Vergara | Q18: =LEN(TRIM(G18))-LEN(SUBSTITUTE(TRIM(G18),CHAR(10),""))+1 -> 2 | R18: =IF(E18<>"","Sí","No") -> No | S18: =IF(OR(J18="",H18=""),"",IF(J18<=H18,IF(FechaCorte>=J18,1,0),MAX(0,MIN(1,(FechaCorte-H18)/(J18-H18))))) -> 1 | T18: =IF(S18="","",K18-S18) -> 0 | U18: =IF(R18="Sí","Recurrente",IF(K18>=1,"Completado",IF(AND(J18<>"",J18<FechaCorte),"Vencido",IF(AND(K18=0,OR(H18="",H18>FechaCorte)),"Por iniciar",IF(AND(T18<>"",T18<=UmbralRiesgo),"En riesgo","En plazo"))))) -> Completado | V18: =IF(OR(U18="Vencido",U18="En riesgo",U18="En plazo",U18="Por iniciar"),1,0) -> 0 | W18: =IF(U18="Vencido",FechaCorte-J18,"") | X18: =IF(AND(V18=1,U18<>"Vencido"),J18-FechaCorte,"") | Y18: =IF(J18="","",DATE(YEAR(J18),MONTH(J18),1)) -> 46143 | Z18: =IF(AND(U18="Completado",I18<>""),IF(I18<=FechaCorte,DATE(YEAR(I18),MONTH(I18),1),""),"") -> 46143 | AA18: =IF(J18="","",IF(DAY(J18+1)=1,1,0)) -> 0 | AB18: =IF(AND(U18="Completado",I18<>"",I18=J18),1,0) -> 1 | AC18: =IF(AND(K18>=1,I18<>""),IF(I18>FechaCorte,1,0),0) -> 0 | AD18: =IF(AND(I18<>"",H18<>""),IF(I18<H18,1,0),0) -> 0 | AE18: =IF(OR(F18="Riesgos",F18="Obs. Auditoría"),1,0) -> 0 | AF18: =IFERROR(MID(D18,FIND("PMC-",D18),8),"") | AG18: =IF(AND(V18=1,J18<>""),IF(AND(J18>=FechaCorte,J18<=HorizonteExpuestos),1,0),0) -> 0
A19: 18 | B19: 2026 | C19: Gestor de Identidades Sailpoint | Fase 2 | D19: Revisión de Fusion: Integración de aplicación - Revisión de lectura y aprovisionamiento automatizado por Sailpoint a Fusion | F19: Iniciativa | G19: Richard Requelme Ana María Vergara | H19: 46213 | J19: 46265 | K19: 0.9 | L19: 15- sep - Se crearon los roles, pendiente análisis de Assertiva para creación de APs 17-Ago - Se ejecutaron las pruebas del conector, fueron exitosas. Pendiente confirmar roles con Agencia y Dueño de app Se encendio el conector en modo lectura, se levantaron con QA los escenarios, se tiene pendiente las pruebas en producción | M19: PR.AA-01 | N19: =IFERROR(INDEX(dFrente!$B$2:$B$76,MATCH(C19,dFrente!$A$2:$A$76,0)),"Sin frente") -> SailPoint IGA | O19: =IFERROR(INDEX(dNIST!$B$2:$B$13,MATCH(M19,dNIST!$A$2:$A$13,0)),"") -> PR | P19: =TRIM(IFERROR(LEFT(G19,FIND(CHAR(10),G19)-1),G19)) -> Richard Requelme | Q19: =LEN(TRIM(G19))-LEN(SUBSTITUTE(TRIM(G19),CHAR(10),""))+1 -> 2 | R19: =IF(E19<>"","Sí","No") -> No | S19: =IF(OR(J19="",H19=""),"",IF(J19<=H19,IF(FechaCorte>=J19,1,0),MAX(0,MIN(1,(FechaCorte-H19)/(J19-H19))))) -> 1 | T19: =IF(S19="","",K19-S19) -> -0.1 | U19: =IF(R19="Sí","Recurrente",IF(K19>=1,"Completado",IF(AND(J19<>"",J19<FechaCorte),"Vencido",IF(AND(K19=0,OR(H19="",H19>FechaCorte)),"Por iniciar",IF(AND(T19<>"",T19<=UmbralRiesgo),"En riesgo","En plazo"))))) -> Vencido | V19: =IF(OR(U19="Vencido",U19="En riesgo",U19="En plazo",U19="Por iniciar"),1,0) -> 1 | W19: =IF(U19="Vencido",FechaCorte-J19,"") -> 24 | X19: =IF(AND(V19=1,U19<>"Vencido"),J19-FechaCorte,"") | Y19: =IF(J19="","",DATE(YEAR(J19),MONTH(J19),1)) -> 46235 | Z19: =IF(AND(U19="Completado",I19<>""),IF(I19<=FechaCorte,DATE(YEAR(I19),MONTH(I19),1),""),"") | AA19: =IF(J19="","",IF(DAY(J19+1)=1,1,0)) -> 1 | AB19: =IF(AND(U19="Completado",I19<>"",I19=J19),1,0) -> 0 | AC19: =IF(AND(K19>=1,I19<>""),IF(I19>FechaCorte,1,0),0) -> 0 | AD19: =IF(AND(I19<>"",H19<>""),IF(I19<H19,1,0),0) -> 0 | AE19: =IF(OR(F19="Riesgos",F19="Obs. Auditoría"),1,0) -> 0 | AF19: =IFERROR(MID(D19,FIND("PMC-",D19),8),"") | AG19: =IF(AND(V19=1,J19<>""),IF(AND(J19>=FechaCorte,J19<=HorizonteExpuestos),1,0),0) -> 0
A20: 19 | B20: 2026 | C20: Gestor de Identidades Sailpoint | Fase 2 | D20: Análisis integración Monitoreo de Fraude | F20: Proyecto | G20: Ana María Vergara Richard Requelme Jhonny Barreiro | H20: 46113 | J20: 46295 | K20: 0.7 | L20: - 17-ago- Se corrigio el esquema y está pendiente del lado del dueño del aplicativo la confirmación de la integración total (auth + autorización) Monitoreo Fraude: Acercamiento con el proyecto en revisión de integración con Entra ID (autenticación) | M20: PR.AA-01 | N20: =IFERROR(INDEX(dFrente!$B$2:$B$76,MATCH(C20,dFrente!$A$2:$A$76,0)),"Sin frente") -> SailPoint IGA | O20: =IFERROR(INDEX(dNIST!$B$2:$B$13,MATCH(M20,dNIST!$A$2:$A$13,0)),"") -> PR | P20: =TRIM(IFERROR(LEFT(G20,FIND(CHAR(10),G20)-1),G20)) -> Ana María Vergara | Q20: =LEN(TRIM(G20))-LEN(SUBSTITUTE(TRIM(G20),CHAR(10),""))+1 -> 3 | R20: =IF(E20<>"","Sí","No") -> No | S20: =IF(OR(J20="",H20=""),"",IF(J20<=H20,IF(FechaCorte>=J20,1,0),MAX(0,MIN(1,(FechaCorte-H20)/(J20-H20))))) -> 0.96703297 | T20: =IF(S20="","",K20-S20) -> -0.26703297 | U20: =IF(R20="Sí","Recurrente",IF(K20>=1,"Completado",IF(AND(J20<>"",J20<FechaCorte),"Vencido",IF(AND(K20=0,OR(H20="",H20>FechaCorte)),"Por iniciar",IF(AND(T20<>"",T20<=UmbralRiesgo),"En riesgo","En plazo"))))) -> En riesgo | V20: =IF(OR(U20="Vencido",U20="En riesgo",U20="En plazo",U20="Por iniciar"),1,0) -> 1 | W20: =IF(U20="Vencido",FechaCorte-J20,"") | X20: =IF(AND(V20=1,U20<>"Vencido"),J20-FechaCorte,"") -> 6 | Y20: =IF(J20="","",DATE(YEAR(J20),MONTH(J20),1)) -> 46266 | Z20: =IF(AND(U20="Completado",I20<>""),IF(I20<=FechaCorte,DATE(YEAR(I20),MONTH(I20),1),""),"") | AA20: =IF(J20="","",IF(DAY(J20+1)=1,1,0)) -> 1 | AB20: =IF(AND(U20="Completado",I20<>"",I20=J20),1,0) -> 0 | AC20: =IF(AND(K20>=1,I20<>""),IF(I20>FechaCorte,1,0),0) -> 0 | AD20: =IF(AND(I20<>"",H20<>""),IF(I20<H20,1,0),0) -> 0 | AE20: =IF(OR(F20="Riesgos",F20="Obs. Auditoría"),1,0) -> 0 | AF20: =IFERROR(MID(D20,FIND("PMC-",D20),8),"") | AG20: =IF(AND(V20=1,J20<>""),IF(AND(J20>=FechaCorte,J20<=HorizonteExpuestos),1,0),0) -> 1
A21: 20 | B21: 2026 | C21: Gestor de Identidades Sailpoint | Fase 2 | D21: Análisis integración AS400 - GAF | F21: Proyecto | G21: Ana María Vergara | H21: 46113 | J21: 46387 | K21: 0.5 | L21: - GAF: Solicitud interdependencia a la célula. En etapa de evaluación - 17/08/2026 Se identificó la necesidad de construir un microservicio para disponibilizar la información que consume SailPoint. El proveedor NTTData compartió una proforma para la construcción, valor que esta fuera del presupuesto | M21: PR.AA-01 | N21: =IFERROR(INDEX(dFrente!$B$2:$B$76,MATCH(C21,dFrente!$A$2:$A$76,0)),"Sin frente") -> SailPoint IGA | O21: =IFERROR(INDEX(dNIST!$B$2:$B$13,MATCH(M21,dNIST!$A$2:$A$13,0)),"") -> PR | P21: =TRIM(IFERROR(LEFT(G21,FIND(CHAR(10),G21)-1),G21)) -> Ana María Vergara | Q21: =LEN(TRIM(G21))-LEN(SUBSTITUTE(TRIM(G21),CHAR(10),""))+1 -> 1 | R21: =IF(E21<>"","Sí","No") -> No | S21: =IF(OR(J21="",H21=""),"",IF(J21<=H21,IF(FechaCorte>=J21,1,0),MAX(0,MIN(1,(FechaCorte-H21)/(J21-H21))))) -> 0.64233577 | T21: =IF(S21="","",K21-S21) -> -0.14233577 | U21: =IF(R21="Sí","Recurrente",IF(K21>=1,"Completado",IF(AND(J21<>"",J21<FechaCorte),"Vencido",IF(AND(K21=0,OR(H21="",H21>FechaCorte)),"Por iniciar",IF(AND(T21<>"",T21<=UmbralRiesgo),"En riesgo","En plazo"))))) -> En plazo | V21: =IF(OR(U21="Vencido",U21="En riesgo",U21="En plazo",U21="Por iniciar"),1,0) -> 1 | W21: =IF(U21="Vencido",FechaCorte-J21,"") | X21: =IF(AND(V21=1,U21<>"Vencido"),J21-FechaCorte,"") -> 98 | Y21: =IF(J21="","",DATE(YEAR(J21),MONTH(J21),1)) -> 46357 | Z21: =IF(AND(U21="Completado",I21<>""),IF(I21<=FechaCorte,DATE(YEAR(I21),MONTH(I21),1),""),"") | AA21: =IF(J21="","",IF(DAY(J21+1)=1,1,0)) -> 1 | AB21: =IF(AND(U21="Completado",I21<>"",I21=J21),1,0) -> 0 | AC21: =IF(AND(K21>=1,I21<>""),IF(I21>FechaCorte,1,0),0) -> 0 | AD21: =IF(AND(I21<>"",H21<>""),IF(I21<H21,1,0),0) -> 0 | AE21: =IF(OR(F21="Riesgos",F21="Obs. Auditoría"),1,0) -> 0 | AF21: =IFERROR(MID(D21,FIND("PMC-",D21),8),"") | AG21: =IF(AND(V21=1,J21<>""),IF(AND(J21>=FechaCorte,J21<=HorizonteExpuestos),1,0),0) -> 0
A22: 21 | B22: 2026 | C22: Gestor de Identidades Sailpoint | Fase 2 | D22: Análisis integración PIVI - CAO (Interdin) | F22: Proyecto | G22: Ana María Vergara | H22: 46113 | J22: 46387 | K22: 0.5 | L22: - PIVI | CAO: Solicitud interdependencia a la célula. En etapa de evaluación - 17/08/2026 La célula de Interdin - William Correa comunica que por temas de capacidad no es viable contar con el análisis técnico de integración por lo que quedaría en backlog | M22: PR.AA-01 | N22: =IFERROR(INDEX(dFrente!$B$2:$B$76,MATCH(C22,dFrente!$A$2:$A$76,0)),"Sin frente") -> SailPoint IGA | O22: =IFERROR(INDEX(dNIST!$B$2:$B$13,MATCH(M22,dNIST!$A$2:$A$13,0)),"") -> PR | P22: =TRIM(IFERROR(LEFT(G22,FIND(CHAR(10),G22)-1),G22)) -> Ana María Vergara | Q22: =LEN(TRIM(G22))-LEN(SUBSTITUTE(TRIM(G22),CHAR(10),""))+1 -> 1 | R22: =IF(E22<>"","Sí","No") -> No | S22: =IF(OR(J22="",H22=""),"",IF(J22<=H22,IF(FechaCorte>=J22,1,0),MAX(0,MIN(1,(FechaCorte-H22)/(J22-H22))))) -> 0.64233577 | T22: =IF(S22="","",K22-S22) -> -0.14233577 | U22: =IF(R22="Sí","Recurrente",IF(K22>=1,"Completado",IF(AND(J22<>"",J22<FechaCorte),"Vencido",IF(AND(K22=0,OR(H22="",H22>FechaCorte)),"Por iniciar",IF(AND(T22<>"",T22<=UmbralRiesgo),"En riesgo","En plazo"))))) -> En plazo | V22: =IF(OR(U22="Vencido",U22="En riesgo",U22="En plazo",U22="Por iniciar"),1,0) -> 1 | W22: =IF(U22="Vencido",FechaCorte-J22,"") | X22: =IF(AND(V22=1,U22<>"Vencido"),J22-FechaCorte,"") -> 98 | Y22: =IF(J22="","",DATE(YEAR(J22),MONTH(J22),1)) -> 46357 | Z22: =IF(AND(U22="Completado",I22<>""),IF(I22<=FechaCorte,DATE(YEAR(I22),MONTH(I22),1),""),"") | AA22: =IF(J22="","",IF(DAY(J22+1)=1,1,0)) -> 1 | AB22: =IF(AND(U22="Completado",I22<>"",I22=J22),1,0) -> 0 | AC22: =IF(AND(K22>=1,I22<>""),IF(I22>FechaCorte,1,0),0) -> 0 | AD22: =IF(AND(I22<>"",H22<>""),IF(I22<H22,1,0),0) -> 0 | AE22: =IF(OR(F22="Riesgos",F22="Obs. Auditoría"),1,0) -> 0 | AF22: =IFERROR(MID(D22,FIND("PMC-",D22),8),"") | AG22: =IF(AND(V22=1,J22<>""),IF(AND(J22>=FechaCorte,J22<=HorizonteExpuestos),1,0),0) -> 0
A23: 22 | B23: 2026 | C23: Gestor de Identidades Sailpoint | Fase 2 | D23: Reemplazo microservicios Bancs, Siglo21, Logiflow | F23: Proyecto | G23: Ana María Vergara | H23: 46113 | J23: 46387 | K23: 0.5 | L23: - Microservicio Bancs: con retraso - Microservicio Siglo21: dependencia de micro de bancs - Microservicio Logiflow: En proceso. Pruebas funcionales 18/08/2026 | M23: PR.AA-01 | N23: =IFERROR(INDEX(dFrente!$B$2:$B$76,MATCH(C23,dFrente!$A$2:$A$76,0)),"Sin frente") -> SailPoint IGA | O23: =IFERROR(INDEX(dNIST!$B$2:$B$13,MATCH(M23,dNIST!$A$2:$A$13,0)),"") -> PR | P23: =TRIM(IFERROR(LEFT(G23,FIND(CHAR(10),G23)-1),G23)) -> Ana María Vergara | Q23: =LEN(TRIM(G23))-LEN(SUBSTITUTE(TRIM(G23),CHAR(10),""))+1 -> 1 | R23: =IF(E23<>"","Sí","No") -> No | S23: =IF(OR(J23="",H23=""),"",IF(J23<=H23,IF(FechaCorte>=J23,1,0),MAX(0,MIN(1,(FechaCorte-H23)/(J23-H23))))) -> 0.64233577 | T23: =IF(S23="","",K23-S23) -> -0.14233577 | U23: =IF(R23="Sí","Recurrente",IF(K23>=1,"Completado",IF(AND(J23<>"",J23<FechaCorte),"Vencido",IF(AND(K23=0,OR(H23="",H23>FechaCorte)),"Por iniciar",IF(AND(T23<>"",T23<=UmbralRiesgo),"En riesgo","En plazo"))))) -> En plazo | V23: =IF(OR(U23="Vencido",U23="En riesgo",U23="En plazo",U23="Por iniciar"),1,0) -> 1 | W23: =IF(U23="Vencido",FechaCorte-J23,"") | X23: =IF(AND(V23=1,U23<>"Vencido"),J23-FechaCorte,"") -> 98 | Y23: =IF(J23="","",DATE(YEAR(J23),MONTH(J23),1)) -> 46357 | Z23: =IF(AND(U23="Completado",I23<>""),IF(I23<=FechaCorte,DATE(YEAR(I23),MONTH(I23),1),""),"") | AA23: =IF(J23="","",IF(DAY(J23+1)=1,1,0)) -> 1 | AB23: =IF(AND(U23="Completado",I23<>"",I23=J23),1,0) -> 0 | AC23: =IF(AND(K23>=1,I23<>""),IF(I23>FechaCorte,1,0),0) -> 0 | AD23: =IF(AND(I23<>"",H23<>""),IF(I23<H23,1,0),0) -> 0 | AE23: =IF(OR(F23="Riesgos",F23="Obs. Auditoría"),1,0) -> 0 | AF23: =IFERROR(MID(D23,FIND("PMC-",D23),8),"") | AG23: =IF(AND(V23=1,J23<>""),IF(AND(J23>=FechaCorte,J23<=HorizonteExpuestos),1,0),0) -> 0
A24: 23 | B24: 2026 | C24: Gestor de Identidades Sailpoint | Fase 2 | D24: Integración automática CRM Salesforce. Análisis construcción roles automáticos | F24: Proyecto | G24: Ana María Vergara Richard Requelme Jhonny Barreiro | H24: 46113 | J24: 46295 | K24: 0.95 | L24: - 15- sept- quitar el CSV -17 ago - Se remite los roles validados (con agencia y con el dueño del app) para creación de roles y proceder con el encendido CRM: Conector implementado, activo modo lectura | M24: PR.AA-05 | N24: =IFERROR(INDEX(dFrente!$B$2:$B$76,MATCH(C24,dFrente!$A$2:$A$76,0)),"Sin frente") -> SailPoint IGA | O24: =IFERROR(INDEX(dNIST!$B$2:$B$13,MATCH(M24,dNIST!$A$2:$A$13,0)),"") -> PR | P24: =TRIM(IFERROR(LEFT(G24,FIND(CHAR(10),G24)-1),G24)) -> Ana María Vergara | Q24: =LEN(TRIM(G24))-LEN(SUBSTITUTE(TRIM(G24),CHAR(10),""))+1 -> 3 | R24: =IF(E24<>"","Sí","No") -> No | S24: =IF(OR(J24="",H24=""),"",IF(J24<=H24,IF(FechaCorte>=J24,1,0),MAX(0,MIN(1,(FechaCorte-H24)/(J24-H24))))) -> 0.96703297 | T24: =IF(S24="","",K24-S24) -> -0.017032967 | U24: =IF(R24="Sí","Recurrente",IF(K24>=1,"Completado",IF(AND(J24<>"",J24<FechaCorte),"Vencido",IF(AND(K24=0,OR(H24="",H24>FechaCorte)),"Por iniciar",IF(AND(T24<>"",T24<=UmbralRiesgo),"En riesgo","En plazo"))))) -> En plazo | V24: =IF(OR(U24="Vencido",U24="En riesgo",U24="En plazo",U24="Por iniciar"),1,0) -> 1 | W24: =IF(U24="Vencido",FechaCorte-J24,"") | X24: =IF(AND(V24=1,U24<>"Vencido"),J24-FechaCorte,"") -> 6 | Y24: =IF(J24="","",DATE(YEAR(J24),MONTH(J24),1)) -> 46266 | Z24: =IF(AND(U24="Completado",I24<>""),IF(I24<=FechaCorte,DATE(YEAR(I24),MONTH(I24),1),""),"") | AA24: =IF(J24="","",IF(DAY(J24+1)=1,1,0)) -> 1 | AB24: =IF(AND(U24="Completado",I24<>"",I24=J24),1,0) -> 0 | AC24: =IF(AND(K24>=1,I24<>""),IF(I24>FechaCorte,1,0),0) -> 0 | AD24: =IF(AND(I24<>"",H24<>""),IF(I24<H24,1,0),0) -> 0 | AE24: =IF(OR(F24="Riesgos",F24="Obs. Auditoría"),1,0) -> 0 | AF24: =IFERROR(MID(D24,FIND("PMC-",D24),8),"") | AG24: =IF(AND(V24=1,J24<>""),IF(AND(J24>=FechaCorte,J24<=HorizonteExpuestos),1,0),0) -> 1
A25: 24 | B25: 2026 | C25: Gestor de Identidades Sailpoint | Fase 2 | D25: Diferencia hora comunicados generados por Sailpoint | F25: Mejora | G25: Ana María Vergara | H25: 46209 | I25: 46233 | J25: 46233 | K25: 1 | L25: Diferencia de 5 horas aprox entre la fecha y hora de la notificación y la fecha y hora reales de envío del correo Ticket de soporte generado para atención de Assertiva #3260 21/07/2026 Comunicado con diferencia de hora corregido | M25: PR.AA-01 | N25: =IFERROR(INDEX(dFrente!$B$2:$B$76,MATCH(C25,dFrente!$A$2:$A$76,0)),"Sin frente") -> SailPoint IGA | O25: =IFERROR(INDEX(dNIST!$B$2:$B$13,MATCH(M25,dNIST!$A$2:$A$13,0)),"") -> PR | P25: =TRIM(IFERROR(LEFT(G25,FIND(CHAR(10),G25)-1),G25)) -> Ana María Vergara | Q25: =LEN(TRIM(G25))-LEN(SUBSTITUTE(TRIM(G25),CHAR(10),""))+1 -> 1 | R25: =IF(E25<>"","Sí","No") -> No | S25: =IF(OR(J25="",H25=""),"",IF(J25<=H25,IF(FechaCorte>=J25,1,0),MAX(0,MIN(1,(FechaCorte-H25)/(J25-H25))))) -> 1 | T25: =IF(S25="","",K25-S25) -> 0 | U25: =IF(R25="Sí","Recurrente",IF(K25>=1,"Completado",IF(AND(J25<>"",J25<FechaCorte),"Vencido",IF(AND(K25=0,OR(H25="",H25>FechaCorte)),"Por iniciar",IF(AND(T25<>"",T25<=UmbralRiesgo),"En riesgo","En plazo"))))) -> Completado | V25: =IF(OR(U25="Vencido",U25="En riesgo",U25="En plazo",U25="Por iniciar"),1,0) -> 0 | W25: =IF(U25="Vencido",FechaCorte-J25,"") | X25: =IF(AND(V25=1,U25<>"Vencido"),J25-FechaCorte,"") | Y25: =IF(J25="","",DATE(YEAR(J25),MONTH(J25),1)) -> 46204 | Z25: =IF(AND(U25="Completado",I25<>""),IF(I25<=FechaCorte,DATE(YEAR(I25),MONTH(I25),1),""),"") -> 46204 | AA25: =IF(J25="","",IF(DAY(J25+1)=1,1,0)) -> 0 | AB25: =IF(AND(U25="Completado",I25<>"",I25=J25),1,0) -> 1 | AC25: =IF(AND(K25>=1,I25<>""),IF(I25>FechaCorte,1,0),0) -> 0 | AD25: =IF(AND(I25<>"",H25<>""),IF(I25<H25,1,0),0) -> 0 | AE25: =IF(OR(F25="Riesgos",F25="Obs. Auditoría"),1,0) -> 0 | AF25: =IFERROR(MID(D25,FIND("PMC-",D25),8),"") | AG25: =IF(AND(V25=1,J25<>""),IF(AND(J25>=FechaCorte,J25<=HorizonteExpuestos),1,0),0) -> 0
A26: 25 | B26: 2026 | C26: Gestor de Identidades Sailpoint | Fase 2 | D26: Soporte Assertiva: Flujo Genéricos ATM´s | #2953 (Eliminación) | F26: Mejora | G26: Richard Requelme Ana María Vergara | H26: 46143 | I26: 46173 | J26: 46173 | K26: 1 | L26: Se configura para que se elimine automáticamente el genérico en AD, BANCS y Siglo una vez ingresado por el flujo de eliminación. | M26: PR.AA-05 | N26: =IFERROR(INDEX(dFrente!$B$2:$B$76,MATCH(C26,dFrente!$A$2:$A$76,0)),"Sin frente") -> SailPoint IGA | O26: =IFERROR(INDEX(dNIST!$B$2:$B$13,MATCH(M26,dNIST!$A$2:$A$13,0)),"") -> PR | P26: =TRIM(IFERROR(LEFT(G26,FIND(CHAR(10),G26)-1),G26)) -> Richard Requelme | Q26: =LEN(TRIM(G26))-LEN(SUBSTITUTE(TRIM(G26),CHAR(10),""))+1 -> 2 | R26: =IF(E26<>"","Sí","No") -> No | S26: =IF(OR(J26="",H26=""),"",IF(J26<=H26,IF(FechaCorte>=J26,1,0),MAX(0,MIN(1,(FechaCorte-H26)/(J26-H26))))) -> 1 | T26: =IF(S26="","",K26-S26) -> 0 | U26: =IF(R26="Sí","Recurrente",IF(K26>=1,"Completado",IF(AND(J26<>"",J26<FechaCorte),"Vencido",IF(AND(K26=0,OR(H26="",H26>FechaCorte)),"Por iniciar",IF(AND(T26<>"",T26<=UmbralRiesgo),"En riesgo","En plazo"))))) -> Completado | V26: =IF(OR(U26="Vencido",U26="En riesgo",U26="En plazo",U26="Por iniciar"),1,0) -> 0 | W26: =IF(U26="Vencido",FechaCorte-J26,"") | X26: =IF(AND(V26=1,U26<>"Vencido"),J26-FechaCorte,"") | Y26: =IF(J26="","",DATE(YEAR(J26),MONTH(J26),1)) -> 46143 | Z26: =IF(AND(U26="Completado",I26<>""),IF(I26<=FechaCorte,DATE(YEAR(I26),MONTH(I26),1),""),"") -> 46143 | AA26: =IF(J26="","",IF(DAY(J26+1)=1,1,0)) -> 1 | AB26: =IF(AND(U26="Completado",I26<>"",I26=J26),1,0) -> 1 | AC26: =IF(AND(K26>=1,I26<>""),IF(I26>FechaCorte,1,0),0) -> 0 | AD26: =IF(AND(I26<>"",H26<>""),IF(I26<H26,1,0),0) -> 0 | AE26: =IF(OR(F26="Riesgos",F26="Obs. Auditoría"),1,0) -> 0 | AF26: =IFERROR(MID(D26,FIND("PMC-",D26),8),"") | AG26: =IF(AND(V26=1,J26<>""),IF(AND(J26>=FechaCorte,J26<=HorizonteExpuestos),1,0),0) -> 0
A27: 26 | B27: 2026 | C27: Gestor de Identidades Sailpoint | Fase 2 | D27: Corrección de roles reportados con inconsistencia | E27: Mensual | F27: Operación | G27: Richard Requelme Ana María Vergara | H27: 46113 | K27: 1 | L27: - Las sesiones de revisión de roles se generan una vez al mes con el equipo de Assertiva, se analiza y se realiza las correcciones reportadas - Actividad ejecutada bajo demanda | M27: PR.AA-05 | N27: =IFERROR(INDEX(dFrente!$B$2:$B$76,MATCH(C27,dFrente!$A$2:$A$76,0)),"Sin frente") -> SailPoint IGA | O27: =IFERROR(INDEX(dNIST!$B$2:$B$13,MATCH(M27,dNIST!$A$2:$A$13,0)),"") -> PR | P27: =TRIM(IFERROR(LEFT(G27,FIND(CHAR(10),G27)-1),G27)) -> Richard Requelme | Q27: =LEN(TRIM(G27))-LEN(SUBSTITUTE(TRIM(G27),CHAR(10),""))+1 -> 2 | R27: =IF(E27<>"","Sí","No") -> Sí | S27: =IF(OR(J27="",H27=""),"",IF(J27<=H27,IF(FechaCorte>=J27,1,0),MAX(0,MIN(1,(FechaCorte-H27)/(J27-H27))))) | T27: =IF(S27="","",K27-S27) | U27: =IF(R27="Sí","Recurrente",IF(K27>=1,"Completado",IF(AND(J27<>"",J27<FechaCorte),"Vencido",IF(AND(K27=0,OR(H27="",H27>FechaCorte)),"Por iniciar",IF(AND(T27<>"",T27<=UmbralRiesgo),"En riesgo","En plazo"))))) -> Recurrente | V27: =IF(OR(U27="Vencido",U27="En riesgo",U27="En plazo",U27="Por iniciar"),1,0) -> 0 | W27: =IF(U27="Vencido",FechaCorte-J27,"") | X27: =IF(AND(V27=1,U27<>"Vencido"),J27-FechaCorte,"") | Y27: =IF(J27="","",DATE(YEAR(J27),MONTH(J27),1)) | Z27: =IF(AND(U27="Completado",I27<>""),IF(I27<=FechaCorte,DATE(YEAR(I27),MONTH(I27),1),""),"") | AA27: =IF(J27="","",IF(DAY(J27+1)=1,1,0)) | AB27: =IF(AND(U27="Completado",I27<>"",I27=J27),1,0) -> 0 | AC27: =IF(AND(K27>=1,I27<>""),IF(I27>FechaCorte,1,0),0) -> 0 | AD27: =IF(AND(I27<>"",H27<>""),IF(I27<H27,1,0),0) -> 0 | AE27: =IF(OR(F27="Riesgos",F27="Obs. Auditoría"),1,0) -> 0 | AF27: =IFERROR(MID(D27,FIND("PMC-",D27),8),"") | AG27: =IF(AND(V27=1,J27<>""),IF(AND(J27>=FechaCorte,J27<=HorizonteExpuestos),1,0),0) -> 0
A28: 27 | B28: 2026 | C28: Gestor de Identidades Sailpoint | Fase 2 | D28: Revisión, Ajustes y Corrección Implementación Rol Ejecutivo Integral 2.0 | F28: Proyecto | G28: Ana María Vergara | H28: 46204 | J28: 46218 | K28: 0.5 | L28: - Revisión integral del proceso del levantamiento de roles para el piloto Ejecutivo Integral 2.0 - Corrección de roles asociados - Sesión y comunicación con los responsables del proyecto piloto - Procesamiento de 130 usuarios bajo este esquema - Comunicación del proceso al equipo interno y externo | M28: PR.AA-05 | N28: =IFERROR(INDEX(dFrente!$B$2:$B$76,MATCH(C28,dFrente!$A$2:$A$76,0)),"Sin frente") -> SailPoint IGA | O28: =IFERROR(INDEX(dNIST!$B$2:$B$13,MATCH(M28,dNIST!$A$2:$A$13,0)),"") -> PR | P28: =TRIM(IFERROR(LEFT(G28,FIND(CHAR(10),G28)-1),G28)) -> Ana María Vergara | Q28: =LEN(TRIM(G28))-LEN(SUBSTITUTE(TRIM(G28),CHAR(10),""))+1 -> 1 | R28: =IF(E28<>"","Sí","No") -> No | S28: =IF(OR(J28="",H28=""),"",IF(J28<=H28,IF(FechaCorte>=J28,1,0),MAX(0,MIN(1,(FechaCorte-H28)/(J28-H28))))) -> 1 | T28: =IF(S28="","",K28-S28) -> -0.5 | U28: =IF(R28="Sí","Recurrente",IF(K28>=1,"Completado",IF(AND(J28<>"",J28<FechaCorte),"Vencido",IF(AND(K28=0,OR(H28="",H28>FechaCorte)),"Por iniciar",IF(AND(T28<>"",T28<=UmbralRiesgo),"En riesgo","En plazo"))))) -> Vencido | V28: =IF(OR(U28="Vencido",U28="En riesgo",U28="En plazo",U28="Por iniciar"),1,0) -> 1 | W28: =IF(U28="Vencido",FechaCorte-J28,"") -> 71 | X28: =IF(AND(V28=1,U28<>"Vencido"),J28-FechaCorte,"") | Y28: =IF(J28="","",DATE(YEAR(J28),MONTH(J28),1)) -> 46204 | Z28: =IF(AND(U28="Completado",I28<>""),IF(I28<=FechaCorte,DATE(YEAR(I28),MONTH(I28),1),""),"") | AA28: =IF(J28="","",IF(DAY(J28+1)=1,1,0)) -> 0 | AB28: =IF(AND(U28="Completado",I28<>"",I28=J28),1,0) -> 0 | AC28: =IF(AND(K28>=1,I28<>""),IF(I28>FechaCorte,1,0),0) -> 0 | AD28: =IF(AND(I28<>"",H28<>""),IF(I28<H28,1,0),0) -> 0 | AE28: =IF(OR(F28="Riesgos",F28="Obs. Auditoría"),1,0) -> 0 | AF28: =IFERROR(MID(D28,FIND("PMC-",D28),8),"") | AG28: =IF(AND(V28=1,J28<>""),IF(AND(J28>=FechaCorte,J28<=HorizonteExpuestos),1,0),0) -> 0
A29: 28 | B29: 2026 | C29: Gestor de Identidades Sailpoint | Fase 2 | D29: Revisión y correlación de cuentas huérfanas en AD | F29: Iniciativa | G29: Ana María Vergara Richard Requelme Bryan Uyana | H29: 46266 | J29: 46356 | K29: 0.5 | L29: Se genero el ticket #3446 para identificar la causa raiz | M29: PR.AA-01 | N29: =IFERROR(INDEX(dFrente!$B$2:$B$76,MATCH(C29,dFrente!$A$2:$A$76,0)),"Sin frente") -> SailPoint IGA | O29: =IFERROR(INDEX(dNIST!$B$2:$B$13,MATCH(M29,dNIST!$A$2:$A$13,0)),"") -> PR | P29: =TRIM(IFERROR(LEFT(G29,FIND(CHAR(10),G29)-1),G29)) -> Ana María Vergara | Q29: =LEN(TRIM(G29))-LEN(SUBSTITUTE(TRIM(G29),CHAR(10),""))+1 -> 3 | R29: =IF(E29<>"","Sí","No") -> No | S29: =IF(OR(J29="",H29=""),"",IF(J29<=H29,IF(FechaCorte>=J29,1,0),MAX(0,MIN(1,(FechaCorte-H29)/(J29-H29))))) -> 0.25555556 | T29: =IF(S29="","",K29-S29) -> 0.24444444 | U29: =IF(R29="Sí","Recurrente",IF(K29>=1,"Completado",IF(AND(J29<>"",J29<FechaCorte),"Vencido",IF(AND(K29=0,OR(H29="",H29>FechaCorte)),"Por iniciar",IF(AND(T29<>"",T29<=UmbralRiesgo),"En riesgo","En plazo"))))) -> En plazo | V29: =IF(OR(U29="Vencido",U29="En riesgo",U29="En plazo",U29="Por iniciar"),1,0) -> 1 | W29: =IF(U29="Vencido",FechaCorte-J29,"") | X29: =IF(AND(V29=1,U29<>"Vencido"),J29-FechaCorte,"") -> 67 | Y29: =IF(J29="","",DATE(YEAR(J29),MONTH(J29),1)) -> 46327 | Z29: =IF(AND(U29="Completado",I29<>""),IF(I29<=FechaCorte,DATE(YEAR(I29),MONTH(I29),1),""),"") | AA29: =IF(J29="","",IF(DAY(J29+1)=1,1,0)) -> 1 | AB29: =IF(AND(U29="Completado",I29<>"",I29=J29),1,0) -> 0 | AC29: =IF(AND(K29>=1,I29<>""),IF(I29>FechaCorte,1,0),0) -> 0 | AD29: =IF(AND(I29<>"",H29<>""),IF(I29<H29,1,0),0) -> 0 | AE29: =IF(OR(F29="Riesgos",F29="Obs. Auditoría"),1,0) -> 0 | AF29: =IFERROR(MID(D29,FIND("PMC-",D29),8),"") | AG29: =IF(AND(V29=1,J29<>""),IF(AND(J29>=FechaCorte,J29<=HorizonteExpuestos),1,0),0) -> 0
A30: 29 | B30: 2026 | C30: Gestor de Identidades Sailpoint | Fase 2 | D30: Cambio en el ciclo de vida de offboarding para usuarios internos y externos en AD. (No se mantendrán por 30 días, se eliminará el mismo día). | F30: Proyecto | G30: Ana María Vergara | H30: 46202 | J30: 46280 | K30: 0.7 | L30: - Solicitud soporte Assertiva ticket #3089 - Análisis de impacto sobre identidades VIP o excepcionadas - Se mantendrá una sesión el viernes 24/06/2026 con el equipo de Assertiva para realizar pruebas sobre el grupo de excepción de AD, para garantizar que la cuenta se mantenga y no sea eliminada - Eliminación lista marcada sobre usuarios excepcionados en NERM, para manejar un proceso transversal para todas las identidades - 17/08/2026 Se crea el grupo de AD: Grupo usuarios VIP, para agregar a los usuarios que requieren excepción en el proceso de offboarding | M30: PR.AA-01 | N30: =IFERROR(INDEX(dFrente!$B$2:$B$76,MATCH(C30,dFrente!$A$2:$A$76,0)),"Sin frente") -> SailPoint IGA | O30: =IFERROR(INDEX(dNIST!$B$2:$B$13,MATCH(M30,dNIST!$A$2:$A$13,0)),"") -> PR | P30: =TRIM(IFERROR(LEFT(G30,FIND(CHAR(10),G30)-1),G30)) -> Ana María Vergara | Q30: =LEN(TRIM(G30))-LEN(SUBSTITUTE(TRIM(G30),CHAR(10),""))+1 -> 1 | R30: =IF(E30<>"","Sí","No") -> No | S30: =IF(OR(J30="",H30=""),"",IF(J30<=H30,IF(FechaCorte>=J30,1,0),MAX(0,MIN(1,(FechaCorte-H30)/(J30-H30))))) -> 1 | T30: =IF(S30="","",K30-S30) -> -0.3 | U30: =IF(R30="Sí","Recurrente",IF(K30>=1,"Completado",IF(AND(J30<>"",J30<FechaCorte),"Vencido",IF(AND(K30=0,OR(H30="",H30>FechaCorte)),"Por iniciar",IF(AND(T30<>"",T30<=UmbralRiesgo),"En riesgo","En plazo"))))) -> Vencido | V30: =IF(OR(U30="Vencido",U30="En riesgo",U30="En plazo",U30="Por iniciar"),1,0) -> 1 | W30: =IF(U30="Vencido",FechaCorte-J30,"") -> 9 | X30: =IF(AND(V30=1,U30<>"Vencido"),J30-FechaCorte,"") | Y30: =IF(J30="","",DATE(YEAR(J30),MONTH(J30),1)) -> 46266 | Z30: =IF(AND(U30="Completado",I30<>""),IF(I30<=FechaCorte,DATE(YEAR(I30),MONTH(I30),1),""),"") | AA30: =IF(J30="","",IF(DAY(J30+1)=1,1,0)) -> 0 | AB30: =IF(AND(U30="Completado",I30<>"",I30=J30),1,0) -> 0 | AC30: =IF(AND(K30>=1,I30<>""),IF(I30>FechaCorte,1,0),0) -> 0 | AD30: =IF(AND(I30<>"",H30<>""),IF(I30<H30,1,0),0) -> 0 | AE30: =IF(OR(F30="Riesgos",F30="Obs. Auditoría"),1,0) -> 0 | AF30: =IFERROR(MID(D30,FIND("PMC-",D30),8),"") | AG30: =IF(AND(V30=1,J30<>""),IF(AND(J30>=FechaCorte,J30<=HorizonteExpuestos),1,0),0) -> 0
A31: 30 | B31: 2026 | C31: Gestor de Identidades Sailpoint | Fase 2 | D31: Deshabilitación automática baja colaborador | F31: Proyecto | G31: Ana María Vergara | H31: 46107 | I31: 46148 | J31: 46148 | K31: 1 | L31: - Solicitud Soporte Assertiva #2762 - Proceso implementado operativo. Depedencia con la carga en SSFF del atributo "end date" | M31: PR.AA-01 | N31: =IFERROR(INDEX(dFrente!$B$2:$B$76,MATCH(C31,dFrente!$A$2:$A$76,0)),"Sin frente") -> SailPoint IGA | O31: =IFERROR(INDEX(dNIST!$B$2:$B$13,MATCH(M31,dNIST!$A$2:$A$13,0)),"") -> PR | P31: =TRIM(IFERROR(LEFT(G31,FIND(CHAR(10),G31)-1),G31)) -> Ana María Vergara | Q31: =LEN(TRIM(G31))-LEN(SUBSTITUTE(TRIM(G31),CHAR(10),""))+1 -> 1 | R31: =IF(E31<>"","Sí","No") -> No | S31: =IF(OR(J31="",H31=""),"",IF(J31<=H31,IF(FechaCorte>=J31,1,0),MAX(0,MIN(1,(FechaCorte-H31)/(J31-H31))))) -> 1 | T31: =IF(S31="","",K31-S31) -> 0 | U31: =IF(R31="Sí","Recurrente",IF(K31>=1,"Completado",IF(AND(J31<>"",J31<FechaCorte),"Vencido",IF(AND(K31=0,OR(H31="",H31>FechaCorte)),"Por iniciar",IF(AND(T31<>"",T31<=UmbralRiesgo),"En riesgo","En plazo"))))) -> Completado | V31: =IF(OR(U31="Vencido",U31="En riesgo",U31="En plazo",U31="Por iniciar"),1,0) -> 0 | W31: =IF(U31="Vencido",FechaCorte-J31,"") | X31: =IF(AND(V31=1,U31<>"Vencido"),J31-FechaCorte,"") | Y31: =IF(J31="","",DATE(YEAR(J31),MONTH(J31),1)) -> 46143 | Z31: =IF(AND(U31="Completado",I31<>""),IF(I31<=FechaCorte,DATE(YEAR(I31),MONTH(I31),1),""),"") -> 46143 | AA31: =IF(J31="","",IF(DAY(J31+1)=1,1,0)) -> 0 | AB31: =IF(AND(U31="Completado",I31<>"",I31=J31),1,0) -> 1 | AC31: =IF(AND(K31>=1,I31<>""),IF(I31>FechaCorte,1,0),0) -> 0 | AD31: =IF(AND(I31<>"",H31<>""),IF(I31<H31,1,0),0) -> 0 | AE31: =IF(OR(F31="Riesgos",F31="Obs. Auditoría"),1,0) -> 0 | AF31: =IFERROR(MID(D31,FIND("PMC-",D31),8),"") | AG31: =IF(AND(V31=1,J31<>""),IF(AND(J31>=FechaCorte,J31<=HorizonteExpuestos),1,0),0) -> 0
A32: 31 | B32: 2026 | C32: Gestor de Identidades Sailpoint | Fase 2 | D32: Flujo de Deshabilitación de Cuentas/permisos - Usuarios Cesantes /Crossboarding- Conector BANCS | F32: Operación | G32: Richard Requelme Bryan Uyana | H32: 46082 | J32: 46265 | K32: 0.5 | L32: Se levanto un workflow ya establecido para cuentas cesantes y que haga el reprocesamiento. Sin embargo toca ajustar la configuración para el crossboarding | M32: PR.AA-01 | N32: =IFERROR(INDEX(dFrente!$B$2:$B$76,MATCH(C32,dFrente!$A$2:$A$76,0)),"Sin frente") -> SailPoint IGA | O32: =IFERROR(INDEX(dNIST!$B$2:$B$13,MATCH(M32,dNIST!$A$2:$A$13,0)),"") -> PR | P32: =TRIM(IFERROR(LEFT(G32,FIND(CHAR(10),G32)-1),G32)) -> Richard Requelme | Q32: =LEN(TRIM(G32))-LEN(SUBSTITUTE(TRIM(G32),CHAR(10),""))+1 -> 2 | R32: =IF(E32<>"","Sí","No") -> No | S32: =IF(OR(J32="",H32=""),"",IF(J32<=H32,IF(FechaCorte>=J32,1,0),MAX(0,MIN(1,(FechaCorte-H32)/(J32-H32))))) -> 1 | T32: =IF(S32="","",K32-S32) -> -0.5 | U32: =IF(R32="Sí","Recurrente",IF(K32>=1,"Completado",IF(AND(J32<>"",J32<FechaCorte),"Vencido",IF(AND(K32=0,OR(H32="",H32>FechaCorte)),"Por iniciar",IF(AND(T32<>"",T32<=UmbralRiesgo),"En riesgo","En plazo"))))) -> Vencido | V32: =IF(OR(U32="Vencido",U32="En riesgo",U32="En plazo",U32="Por iniciar"),1,0) -> 1 | W32: =IF(U32="Vencido",FechaCorte-J32,"") -> 24 | X32: =IF(AND(V32=1,U32<>"Vencido"),J32-FechaCorte,"") | Y32: =IF(J32="","",DATE(YEAR(J32),MONTH(J32),1)) -> 46235 | Z32: =IF(AND(U32="Completado",I32<>""),IF(I32<=FechaCorte,DATE(YEAR(I32),MONTH(I32),1),""),"") | AA32: =IF(J32="","",IF(DAY(J32+1)=1,1,0)) -> 1 | AB32: =IF(AND(U32="Completado",I32<>"",I32=J32),1,0) -> 0 | AC32: =IF(AND(K32>=1,I32<>""),IF(I32>FechaCorte,1,0),0) -> 0 | AD32: =IF(AND(I32<>"",H32<>""),IF(I32<H32,1,0),0) -> 0 | AE32: =IF(OR(F32="Riesgos",F32="Obs. Auditoría"),1,0) -> 0 | AF32: =IFERROR(MID(D32,FIND("PMC-",D32),8),"") | AG32: =IF(AND(V32=1,J32<>""),IF(AND(J32>=FechaCorte,J32<=HorizonteExpuestos),1,0),0) -> 0
A33: 32 | B33: 2026 | C33: Gestor de Identidades Sailpoint | Fase 2 | D33: Revisión y correlación de cuentas huérfanas en Bancs | F33: Operación | G33: Richard Requelme Bryan Uyana | H33: 46082 | J33: 46265 | K33: 0.5 | L33: Se deshabilito cuentas cesantes. Sin embargo, se debe regularizar la información de las cuentas no correlacionadas para el control en vuelo | M33: PR.AA-01 | N33: =IFERROR(INDEX(dFrente!$B$2:$B$76,MATCH(C33,dFrente!$A$2:$A$76,0)),"Sin frente") -> SailPoint IGA | O33: =IFERROR(INDEX(dNIST!$B$2:$B$13,MATCH(M33,dNIST!$A$2:$A$13,0)),"") -> PR | P33: =TRIM(IFERROR(LEFT(G33,FIND(CHAR(10),G33)-1),G33)) -> Richard Requelme | Q33: =LEN(TRIM(G33))-LEN(SUBSTITUTE(TRIM(G33),CHAR(10),""))+1 -> 2 | R33: =IF(E33<>"","Sí","No") -> No | S33: =IF(OR(J33="",H33=""),"",IF(J33<=H33,IF(FechaCorte>=J33,1,0),MAX(0,MIN(1,(FechaCorte-H33)/(J33-H33))))) -> 1 | T33: =IF(S33="","",K33-S33) -> -0.5 | U33: =IF(R33="Sí","Recurrente",IF(K33>=1,"Completado",IF(AND(J33<>"",J33<FechaCorte),"Vencido",IF(AND(K33=0,OR(H33="",H33>FechaCorte)),"Por iniciar",IF(AND(T33<>"",T33<=UmbralRiesgo),"En riesgo","En plazo"))))) -> Vencido | V33: =IF(OR(U33="Vencido",U33="En riesgo",U33="En plazo",U33="Por iniciar"),1,0) -> 1 | W33: =IF(U33="Vencido",FechaCorte-J33,"") -> 24 | X33: =IF(AND(V33=1,U33<>"Vencido"),J33-FechaCorte,"") | Y33: =IF(J33="","",DATE(YEAR(J33),MONTH(J33),1)) -> 46235 | Z33: =IF(AND(U33="Completado",I33<>""),IF(I33<=FechaCorte,DATE(YEAR(I33),MONTH(I33),1),""),"") | AA33: =IF(J33="","",IF(DAY(J33+1)=1,1,0)) -> 1 | AB33: =IF(AND(U33="Completado",I33<>"",I33=J33),1,0) -> 0 | AC33: =IF(AND(K33>=1,I33<>""),IF(I33>FechaCorte,1,0),0) -> 0 | AD33: =IF(AND(I33<>"",H33<>""),IF(I33<H33,1,0),0) -> 0 | AE33: =IF(OR(F33="Riesgos",F33="Obs. Auditoría"),1,0) -> 0 | AF33: =IFERROR(MID(D33,FIND("PMC-",D33),8),"") | AG33: =IF(AND(V33=1,J33<>""),IF(AND(J33>=FechaCorte,J33<=HorizonteExpuestos),1,0),0) -> 0
A34: 33 | B34: 2026 | C34: Gestor de Identidades Sailpoint | Fase 2 | D34: Asociación de cuentas privilegiadas (ENTRAID y AD) -priv.- y no el nominado (sailpoint) Correlacionar las cuentas priv. a la identidad del usuario en Sailpoint | F34: Operación | G34: Richard Requelme Bryan Uyana | H34: 46082 | I34: 46272 | J34: 46272 | K34: 1 | L34: -15 de sept - se enciende el conector nuevo de privc En la reunión de seguimiento con Assertiva se reviso este tema, y se vio dos opciones para trabajar este tema, se genero un ticket a Assertiva para regularizar. Para las privc, se evalua ajustes en el conector. | M34: PR.AA-05 | N34: =IFERROR(INDEX(dFrente!$B$2:$B$76,MATCH(C34,dFrente!$A$2:$A$76,0)),"Sin frente") -> SailPoint IGA | O34: =IFERROR(INDEX(dNIST!$B$2:$B$13,MATCH(M34,dNIST!$A$2:$A$13,0)),"") -> PR | P34: =TRIM(IFERROR(LEFT(G34,FIND(CHAR(10),G34)-1),G34)) -> Richard Requelme | Q34: =LEN(TRIM(G34))-LEN(SUBSTITUTE(TRIM(G34),CHAR(10),""))+1 -> 2 | R34: =IF(E34<>"","Sí","No") -> No | S34: =IF(OR(J34="",H34=""),"",IF(J34<=H34,IF(FechaCorte>=J34,1,0),MAX(0,MIN(1,(FechaCorte-H34)/(J34-H34))))) -> 1 | T34: =IF(S34="","",K34-S34) -> 0 | U34: =IF(R34="Sí","Recurrente",IF(K34>=1,"Completado",IF(AND(J34<>"",J34<FechaCorte),"Vencido",IF(AND(K34=0,OR(H34="",H34>FechaCorte)),"Por iniciar",IF(AND(T34<>"",T34<=UmbralRiesgo),"En riesgo","En plazo"))))) -> Completado | V34: =IF(OR(U34="Vencido",U34="En riesgo",U34="En plazo",U34="Por iniciar"),1,0) -> 0 | W34: =IF(U34="Vencido",FechaCorte-J34,"") | X34: =IF(AND(V34=1,U34<>"Vencido"),J34-FechaCorte,"") | Y34: =IF(J34="","",DATE(YEAR(J34),MONTH(J34),1)) -> 46266 | Z34: =IF(AND(U34="Completado",I34<>""),IF(I34<=FechaCorte,DATE(YEAR(I34),MONTH(I34),1),""),"") -> 46266 | AA34: =IF(J34="","",IF(DAY(J34+1)=1,1,0)) -> 0 | AB34: =IF(AND(U34="Completado",I34<>"",I34=J34),1,0) -> 1 | AC34: =IF(AND(K34>=1,I34<>""),IF(I34>FechaCorte,1,0),0) -> 0 | AD34: =IF(AND(I34<>"",H34<>""),IF(I34<H34,1,0),0) -> 0 | AE34: =IF(OR(F34="Riesgos",F34="Obs. Auditoría"),1,0) -> 0 | AF34: =IFERROR(MID(D34,FIND("PMC-",D34),8),"") | AG34: =IF(AND(V34=1,J34<>""),IF(AND(J34>=FechaCorte,J34<=HorizonteExpuestos),1,0),0) -> 0
A35: 34 | B35: 2026 | C35: Certificación de Accesos: Accesos usuarios | D35: Depuración de cuentas de usuarios priv. y privc. | F35: Operación | G35: Richard Requelme Bryan Uyana | H35: 46235 | I35: 46265 | J35: 46265 | K35: 1 | M35: PR.AA-05 | N35: =IFERROR(INDEX(dFrente!$B$2:$B$76,MATCH(C35,dFrente!$A$2:$A$76,0)),"Sin frente") -> Certificación de accesos | O35: =IFERROR(INDEX(dNIST!$B$2:$B$13,MATCH(M35,dNIST!$A$2:$A$13,0)),"") -> PR | P35: =TRIM(IFERROR(LEFT(G35,FIND(CHAR(10),G35)-1),G35)) -> Richard Requelme | Q35: =LEN(TRIM(G35))-LEN(SUBSTITUTE(TRIM(G35),CHAR(10),""))+1 -> 2 | R35: =IF(E35<>"","Sí","No") -> No | S35: =IF(OR(J35="",H35=""),"",IF(J35<=H35,IF(FechaCorte>=J35,1,0),MAX(0,MIN(1,(FechaCorte-H35)/(J35-H35))))) -> 1 | T35: =IF(S35="","",K35-S35) -> 0 | U35: =IF(R35="Sí","Recurrente",IF(K35>=1,"Completado",IF(AND(J35<>"",J35<FechaCorte),"Vencido",IF(AND(K35=0,OR(H35="",H35>FechaCorte)),"Por iniciar",IF(AND(T35<>"",T35<=UmbralRiesgo),"En riesgo","En plazo"))))) -> Completado | V35: =IF(OR(U35="Vencido",U35="En riesgo",U35="En plazo",U35="Por iniciar"),1,0) -> 0 | W35: =IF(U35="Vencido",FechaCorte-J35,"") | X35: =IF(AND(V35=1,U35<>"Vencido"),J35-FechaCorte,"") | Y35: =IF(J35="","",DATE(YEAR(J35),MONTH(J35),1)) -> 46235 | Z35: =IF(AND(U35="Completado",I35<>""),IF(I35<=FechaCorte,DATE(YEAR(I35),MONTH(I35),1),""),"") -> 46235 | AA35: =IF(J35="","",IF(DAY(J35+1)=1,1,0)) -> 1 | AB35: =IF(AND(U35="Completado",I35<>"",I35=J35),1,0) -> 1 | AC35: =IF(AND(K35>=1,I35<>""),IF(I35>FechaCorte,1,0),0) -> 0 | AD35: =IF(AND(I35<>"",H35<>""),IF(I35<H35,1,0),0) -> 0 | AE35: =IF(OR(F35="Riesgos",F35="Obs. Auditoría"),1,0) -> 0 | AF35: =IFERROR(MID(D35,FIND("PMC-",D35),8),"") | AG35: =IF(AND(V35=1,J35<>""),IF(AND(J35>=FechaCorte,J35<=HorizonteExpuestos),1,0),0) -> 0
A36: 35 | B36: 2026 | C36: Gestor de Identidades Sailpoint | Fase 2 | D36: Flujo de Deshabilitación de Cuentas/permisos - Usuarios Cesantes /Crossboarding- Conector RHDS | F36: Operación | G36: Richard Requelme | H36: 46082 | J36: 46325 | K36: 0.1 | L36: Se tiene el análisis de las cuentas no correlacionadas. Se debe determinar causa raíz y corrección. | M36: PR.AA-01 | N36: =IFERROR(INDEX(dFrente!$B$2:$B$76,MATCH(C36,dFrente!$A$2:$A$76,0)),"Sin frente") -> SailPoint IGA | O36: =IFERROR(INDEX(dNIST!$B$2:$B$13,MATCH(M36,dNIST!$A$2:$A$13,0)),"") -> PR | P36: =TRIM(IFERROR(LEFT(G36,FIND(CHAR(10),G36)-1),G36)) -> Richard Requelme | Q36: =LEN(TRIM(G36))-LEN(SUBSTITUTE(TRIM(G36),CHAR(10),""))+1 -> 1 | R36: =IF(E36<>"","Sí","No") -> No | S36: =IF(OR(J36="",H36=""),"",IF(J36<=H36,IF(FechaCorte>=J36,1,0),MAX(0,MIN(1,(FechaCorte-H36)/(J36-H36))))) -> 0.85185185 | T36: =IF(S36="","",K36-S36) -> -0.75185185 | U36: =IF(R36="Sí","Recurrente",IF(K36>=1,"Completado",IF(AND(J36<>"",J36<FechaCorte),"Vencido",IF(AND(K36=0,OR(H36="",H36>FechaCorte)),"Por iniciar",IF(AND(T36<>"",T36<=UmbralRiesgo),"En riesgo","En plazo"))))) -> En riesgo | V36: =IF(OR(U36="Vencido",U36="En riesgo",U36="En plazo",U36="Por iniciar"),1,0) -> 1 | W36: =IF(U36="Vencido",FechaCorte-J36,"") | X36: =IF(AND(V36=1,U36<>"Vencido"),J36-FechaCorte,"") -> 36 | Y36: =IF(J36="","",DATE(YEAR(J36),MONTH(J36),1)) -> 46296 | Z36: =IF(AND(U36="Completado",I36<>""),IF(I36<=FechaCorte,DATE(YEAR(I36),MONTH(I36),1),""),"") | AA36: =IF(J36="","",IF(DAY(J36+1)=1,1,0)) -> 0 | AB36: =IF(AND(U36="Completado",I36<>"",I36=J36),1,0) -> 0 | AC36: =IF(AND(K36>=1,I36<>""),IF(I36>FechaCorte,1,0),0) -> 0 | AD36: =IF(AND(I36<>"",H36<>""),IF(I36<H36,1,0),0) -> 0 | AE36: =IF(OR(F36="Riesgos",F36="Obs. Auditoría"),1,0) -> 0 | AF36: =IFERROR(MID(D36,FIND("PMC-",D36),8),"") | AG36: =IF(AND(V36=1,J36<>""),IF(AND(J36>=FechaCorte,J36<=HorizonteExpuestos),1,0),0) -> 0
A37: 36 | B37: 2026 | C37: Gestor de Identidades Sailpoint | Fase 2 | D37: Revisión y correlación de cuentas huérfanas RHDS | F37: Operación | G37: Richard Requelme Bryan Uyana | H37: 46082 | J37: 46295 | K37: 0.1 | L37: Se tiene el análisis de las cuentas no correlacionadas. Se debe determinar causa raíz y corrección. | M37: PR.AA-01 | N37: =IFERROR(INDEX(dFrente!$B$2:$B$76,MATCH(C37,dFrente!$A$2:$A$76,0)),"Sin frente") -> SailPoint IGA | O37: =IFERROR(INDEX(dNIST!$B$2:$B$13,MATCH(M37,dNIST!$A$2:$A$13,0)),"") -> PR | P37: =TRIM(IFERROR(LEFT(G37,FIND(CHAR(10),G37)-1),G37)) -> Richard Requelme | Q37: =LEN(TRIM(G37))-LEN(SUBSTITUTE(TRIM(G37),CHAR(10),""))+1 -> 2 | R37: =IF(E37<>"","Sí","No") -> No | S37: =IF(OR(J37="",H37=""),"",IF(J37<=H37,IF(FechaCorte>=J37,1,0),MAX(0,MIN(1,(FechaCorte-H37)/(J37-H37))))) -> 0.97183099 | T37: =IF(S37="","",K37-S37) -> -0.87183099 | U37: =IF(R37="Sí","Recurrente",IF(K37>=1,"Completado",IF(AND(J37<>"",J37<FechaCorte),"Vencido",IF(AND(K37=0,OR(H37="",H37>FechaCorte)),"Por iniciar",IF(AND(T37<>"",T37<=UmbralRiesgo),"En riesgo","En plazo"))))) -> En riesgo | V37: =IF(OR(U37="Vencido",U37="En riesgo",U37="En plazo",U37="Por iniciar"),1,0) -> 1 | W37: =IF(U37="Vencido",FechaCorte-J37,"") | X37: =IF(AND(V37=1,U37<>"Vencido"),J37-FechaCorte,"") -> 6 | Y37: =IF(J37="","",DATE(YEAR(J37),MONTH(J37),1)) -> 46266 | Z37: =IF(AND(U37="Completado",I37<>""),IF(I37<=FechaCorte,DATE(YEAR(I37),MONTH(I37),1),""),"") | AA37: =IF(J37="","",IF(DAY(J37+1)=1,1,0)) -> 1 | AB37: =IF(AND(U37="Completado",I37<>"",I37=J37),1,0) -> 0 | AC37: =IF(AND(K37>=1,I37<>""),IF(I37>FechaCorte,1,0),0) -> 0 | AD37: =IF(AND(I37<>"",H37<>""),IF(I37<H37,1,0),0) -> 0 | AE37: =IF(OR(F37="Riesgos",F37="Obs. Auditoría"),1,0) -> 0 | AF37: =IFERROR(MID(D37,FIND("PMC-",D37),8),"") | AG37: =IF(AND(V37=1,J37<>""),IF(AND(J37>=FechaCorte,J37<=HorizonteExpuestos),1,0),0) -> 1
A38: 37 | B38: 2026 | C38: Regularización de Roles | D38: Regularización de Accesos y Permisos Crowstrike. Desde la aplicación hacia ISC Sailpoint | F38: Operación | G38: Jhonny Barreiro | H38: 46211 | J38: 46233 | K38: 0.5 | L38: Se incia con Valerai Tandazo la depuracion de accesos en Crowstrike, Fase 1 en la aplicación. Fase 2 en ISC actualmente en la aplicación | M38: PR.AA-05 | N38: =IFERROR(INDEX(dFrente!$B$2:$B$76,MATCH(C38,dFrente!$A$2:$A$76,0)),"Sin frente") -> Aplicaciones y roles | O38: =IFERROR(INDEX(dNIST!$B$2:$B$13,MATCH(M38,dNIST!$A$2:$A$13,0)),"") -> PR | P38: =TRIM(IFERROR(LEFT(G38,FIND(CHAR(10),G38)-1),G38)) -> Jhonny Barreiro | Q38: =LEN(TRIM(G38))-LEN(SUBSTITUTE(TRIM(G38),CHAR(10),""))+1 -> 1 | R38: =IF(E38<>"","Sí","No") -> No | S38: =IF(OR(J38="",H38=""),"",IF(J38<=H38,IF(FechaCorte>=J38,1,0),MAX(0,MIN(1,(FechaCorte-H38)/(J38-H38))))) -> 1 | T38: =IF(S38="","",K38-S38) -> -0.5 | U38: =IF(R38="Sí","Recurrente",IF(K38>=1,"Completado",IF(AND(J38<>"",J38<FechaCorte),"Vencido",IF(AND(K38=0,OR(H38="",H38>FechaCorte)),"Por iniciar",IF(AND(T38<>"",T38<=UmbralRiesgo),"En riesgo","En plazo"))))) -> Vencido | V38: =IF(OR(U38="Vencido",U38="En riesgo",U38="En plazo",U38="Por iniciar"),1,0) -> 1 | W38: =IF(U38="Vencido",FechaCorte-J38,"") -> 56 | X38: =IF(AND(V38=1,U38<>"Vencido"),J38-FechaCorte,"") | Y38: =IF(J38="","",DATE(YEAR(J38),MONTH(J38),1)) -> 46204 | Z38: =IF(AND(U38="Completado",I38<>""),IF(I38<=FechaCorte,DATE(YEAR(I38),MONTH(I38),1),""),"") | AA38: =IF(J38="","",IF(DAY(J38+1)=1,1,0)) -> 0 | AB38: =IF(AND(U38="Completado",I38<>"",I38=J38),1,0) -> 0 | AC38: =IF(AND(K38>=1,I38<>""),IF(I38>FechaCorte,1,0),0) -> 0 | AD38: =IF(AND(I38<>"",H38<>""),IF(I38<H38,1,0),0) -> 0 | AE38: =IF(OR(F38="Riesgos",F38="Obs. Auditoría"),1,0) -> 0 | AF38: =IFERROR(MID(D38,FIND("PMC-",D38),8),"") | AG38: =IF(AND(V38=1,J38<>""),IF(AND(J38>=FechaCorte,J38<=HorizonteExpuestos),1,0),0) -> 0
A39: 38 | B39: 2026 | C39: Regularización de Roles | D39: Regularización de Accesos y Permisos Firewall Checkpoint. Desde la aplicación hacia ISC Sailpoint | F39: Operación | G39: Jhonny Barreiro | H39: 46211 | J39: 46233 | K39: 0.75 | L39: Se incia con Maria Peñaherrera la depuracion de accesos en Firewall Checkpoint, Fase 1 en la aplicación. Fase 2 en ISC actualmente en la aplicación | M39: PR.AA-05 | N39: =IFERROR(INDEX(dFrente!$B$2:$B$76,MATCH(C39,dFrente!$A$2:$A$76,0)),"Sin frente") -> Aplicaciones y roles | O39: =IFERROR(INDEX(dNIST!$B$2:$B$13,MATCH(M39,dNIST!$A$2:$A$13,0)),"") -> PR | P39: =TRIM(IFERROR(LEFT(G39,FIND(CHAR(10),G39)-1),G39)) -> Jhonny Barreiro | Q39: =LEN(TRIM(G39))-LEN(SUBSTITUTE(TRIM(G39),CHAR(10),""))+1 -> 1 | R39: =IF(E39<>"","Sí","No") -> No | S39: =IF(OR(J39="",H39=""),"",IF(J39<=H39,IF(FechaCorte>=J39,1,0),MAX(0,MIN(1,(FechaCorte-H39)/(J39-H39))))) -> 1 | T39: =IF(S39="","",K39-S39) -> -0.25 | U39: =IF(R39="Sí","Recurrente",IF(K39>=1,"Completado",IF(AND(J39<>"",J39<FechaCorte),"Vencido",IF(AND(K39=0,OR(H39="",H39>FechaCorte)),"Por iniciar",IF(AND(T39<>"",T39<=UmbralRiesgo),"En riesgo","En plazo"))))) -> Vencido | V39: =IF(OR(U39="Vencido",U39="En riesgo",U39="En plazo",U39="Por iniciar"),1,0) -> 1 | W39: =IF(U39="Vencido",FechaCorte-J39,"") -> 56 | X39: =IF(AND(V39=1,U39<>"Vencido"),J39-FechaCorte,"") | Y39: =IF(J39="","",DATE(YEAR(J39),MONTH(J39),1)) -> 46204 | Z39: =IF(AND(U39="Completado",I39<>""),IF(I39<=FechaCorte,DATE(YEAR(I39),MONTH(I39),1),""),"") | AA39: =IF(J39="","",IF(DAY(J39+1)=1,1,0)) -> 0 | AB39: =IF(AND(U39="Completado",I39<>"",I39=J39),1,0) -> 0 | AC39: =IF(AND(K39>=1,I39<>""),IF(I39>FechaCorte,1,0),0) -> 0 | AD39: =IF(AND(I39<>"",H39<>""),IF(I39<H39,1,0),0) -> 0 | AE39: =IF(OR(F39="Riesgos",F39="Obs. Auditoría"),1,0) -> 0 | AF39: =IFERROR(MID(D39,FIND("PMC-",D39),8),"") | AG39: =IF(AND(V39=1,J39<>""),IF(AND(J39>=FechaCorte,J39<=HorizonteExpuestos),1,0),0) -> 0
A40: 39 | B40: 2026 | C40: Gestión de accesos y permisos | D40: Integración de nuevas fuentes al control - Access Request Center - Fuentes Nube (My Access). | F40: Iniciativa | G40: Richard Requelme Bryan Uyana | H40: 46163 | I40: 46203 | J40: 46203 | K40: 1 | L40: Se levantaron scripts para obtener la información y se creo una pestaña en GEMA para visualizar todos los permisos asignados fuera del rol | M40: PR.AA-05 | N40: =IFERROR(INDEX(dFrente!$B$2:$B$76,MATCH(C40,dFrente!$A$2:$A$76,0)),"Sin frente") -> Aplicaciones y roles | O40: =IFERROR(INDEX(dNIST!$B$2:$B$13,MATCH(M40,dNIST!$A$2:$A$13,0)),"") -> PR | P40: =TRIM(IFERROR(LEFT(G40,FIND(CHAR(10),G40)-1),G40)) -> Richard Requelme | Q40: =LEN(TRIM(G40))-LEN(SUBSTITUTE(TRIM(G40),CHAR(10),""))+1 -> 2 | R40: =IF(E40<>"","Sí","No") -> No | S40: =IF(OR(J40="",H40=""),"",IF(J40<=H40,IF(FechaCorte>=J40,1,0),MAX(0,MIN(1,(FechaCorte-H40)/(J40-H40))))) -> 1 | T40: =IF(S40="","",K40-S40) -> 0 | U40: =IF(R40="Sí","Recurrente",IF(K40>=1,"Completado",IF(AND(J40<>"",J40<FechaCorte),"Vencido",IF(AND(K40=0,OR(H40="",H40>FechaCorte)),"Por iniciar",IF(AND(T40<>"",T40<=UmbralRiesgo),"En riesgo","En plazo"))))) -> Completado | V40: =IF(OR(U40="Vencido",U40="En riesgo",U40="En plazo",U40="Por iniciar"),1,0) -> 0 | W40: =IF(U40="Vencido",FechaCorte-J40,"") | X40: =IF(AND(V40=1,U40<>"Vencido"),J40-FechaCorte,"") | Y40: =IF(J40="","",DATE(YEAR(J40),MONTH(J40),1)) -> 46174 | Z40: =IF(AND(U40="Completado",I40<>""),IF(I40<=FechaCorte,DATE(YEAR(I40),MONTH(I40),1),""),"") -> 46174 | AA40: =IF(J40="","",IF(DAY(J40+1)=1,1,0)) -> 1 | AB40: =IF(AND(U40="Completado",I40<>"",I40=J40),1,0) -> 1 | AC40: =IF(AND(K40>=1,I40<>""),IF(I40>FechaCorte,1,0),0) -> 0 | AD40: =IF(AND(I40<>"",H40<>""),IF(I40<H40,1,0),0) -> 0 | AE40: =IF(OR(F40="Riesgos",F40="Obs. Auditoría"),1,0) -> 0 | AF40: =IFERROR(MID(D40,FIND("PMC-",D40),8),"") | AG40: =IF(AND(V40=1,J40<>""),IF(AND(J40>=FechaCorte,J40<=HorizonteExpuestos),1,0),0) -> 0
A41: 40 | B41: 2026 | C41: Gestión de accesos y permisos | D41: Actualización Flujo de Accesos y Permisos SNOW. (Unificar flujo de perfiles globales y modificación de atributos, para que se coloquen los autorizadores de la CMDB en función de la aplicación a la que estan solicitando acceso el usuario). | F41: Iniciativa | G41: Ana María Vergara Richard Requelme Jhonny Barreiro | H41: 46204 | I41: 46234 | J41: 46234 | K41: 1 | L41: - Se paso a producción y se tiene el comunicado aprobado por Juan. Se revisa con equipo NTT y equipo de SNOW para pasar a producción - Solicitud de comunicado al área de gobierno | M41: PR.AA-05 | N41: =IFERROR(INDEX(dFrente!$B$2:$B$76,MATCH(C41,dFrente!$A$2:$A$76,0)),"Sin frente") -> Aplicaciones y roles | O41: =IFERROR(INDEX(dNIST!$B$2:$B$13,MATCH(M41,dNIST!$A$2:$A$13,0)),"") -> PR | P41: =TRIM(IFERROR(LEFT(G41,FIND(CHAR(10),G41)-1),G41)) -> Ana María Vergara | Q41: =LEN(TRIM(G41))-LEN(SUBSTITUTE(TRIM(G41),CHAR(10),""))+1 -> 3 | R41: =IF(E41<>"","Sí","No") -> No | S41: =IF(OR(J41="",H41=""),"",IF(J41<=H41,IF(FechaCorte>=J41,1,0),MAX(0,MIN(1,(FechaCorte-H41)/(J41-H41))))) -> 1 | T41: =IF(S41="","",K41-S41) -> 0 | U41: =IF(R41="Sí","Recurrente",IF(K41>=1,"Completado",IF(AND(J41<>"",J41<FechaCorte),"Vencido",IF(AND(K41=0,OR(H41="",H41>FechaCorte)),"Por iniciar",IF(AND(T41<>"",T41<=UmbralRiesgo),"En riesgo","En plazo"))))) -> Completado | V41: =IF(OR(U41="Vencido",U41="En riesgo",U41="En plazo",U41="Por iniciar"),1,0) -> 0 | W41: =IF(U41="Vencido",FechaCorte-J41,"") | X41: =IF(AND(V41=1,U41<>"Vencido"),J41-FechaCorte,"") | Y41: =IF(J41="","",DATE(YEAR(J41),MONTH(J41),1)) -> 46204 | Z41: =IF(AND(U41="Completado",I41<>""),IF(I41<=FechaCorte,DATE(YEAR(I41),MONTH(I41),1),""),"") -> 46204 | AA41: =IF(J41="","",IF(DAY(J41+1)=1,1,0)) -> 1 | AB41: =IF(AND(U41="Completado",I41<>"",I41=J41),1,0) -> 1 | AC41: =IF(AND(K41>=1,I41<>""),IF(I41>FechaCorte,1,0),0) -> 0 | AD41: =IF(AND(I41<>"",H41<>""),IF(I41<H41,1,0),0) -> 0 | AE41: =IF(OR(F41="Riesgos",F41="Obs. Auditoría"),1,0) -> 0 | AF41: =IFERROR(MID(D41,FIND("PMC-",D41),8),"") | AG41: =IF(AND(V41=1,J41<>""),IF(AND(J41>=FechaCorte,J41<=HorizonteExpuestos),1,0),0) -> 0
A42: 41 | B42: 2026 | C42: Usuarios y Perfiles Globales | D42: Eliminación de accesos a usuarios de Tecnología, Operaciones y Tribu para que puedan crear usuarios de dominio directamente con perfil. | F42: Iniciativa | G42: Ana María Fierro | H42: 46082 | I42: 46080 | J42: 46080 | K42: 1 | M42: PR.AA-05 | N42: =IFERROR(INDEX(dFrente!$B$2:$B$76,MATCH(C42,dFrente!$A$2:$A$76,0)),"Sin frente") -> Aplicaciones y roles | O42: =IFERROR(INDEX(dNIST!$B$2:$B$13,MATCH(M42,dNIST!$A$2:$A$13,0)),"") -> PR | P42: =TRIM(IFERROR(LEFT(G42,FIND(CHAR(10),G42)-1),G42)) -> Ana María Fierro | Q42: =LEN(TRIM(G42))-LEN(SUBSTITUTE(TRIM(G42),CHAR(10),""))+1 -> 1 | R42: =IF(E42<>"","Sí","No") -> No | S42: =IF(OR(J42="",H42=""),"",IF(J42<=H42,IF(FechaCorte>=J42,1,0),MAX(0,MIN(1,(FechaCorte-H42)/(J42-H42))))) -> 1 | T42: =IF(S42="","",K42-S42) -> 0 | U42: =IF(R42="Sí","Recurrente",IF(K42>=1,"Completado",IF(AND(J42<>"",J42<FechaCorte),"Vencido",IF(AND(K42=0,OR(H42="",H42>FechaCorte)),"Por iniciar",IF(AND(T42<>"",T42<=UmbralRiesgo),"En riesgo","En plazo"))))) -> Completado | V42: =IF(OR(U42="Vencido",U42="En riesgo",U42="En plazo",U42="Por iniciar"),1,0) -> 0 | W42: =IF(U42="Vencido",FechaCorte-J42,"") | X42: =IF(AND(V42=1,U42<>"Vencido"),J42-FechaCorte,"") | Y42: =IF(J42="","",DATE(YEAR(J42),MONTH(J42),1)) -> 46054 | Z42: =IF(AND(U42="Completado",I42<>""),IF(I42<=FechaCorte,DATE(YEAR(I42),MONTH(I42),1),""),"") -> 46054 | AA42: =IF(J42="","",IF(DAY(J42+1)=1,1,0)) -> 0 | AB42: =IF(AND(U42="Completado",I42<>"",I42=J42),1,0) -> 1 | AC42: =IF(AND(K42>=1,I42<>""),IF(I42>FechaCorte,1,0),0) -> 0 | AD42: =IF(AND(I42<>"",H42<>""),IF(I42<H42,1,0),0) -> 1 | AE42: =IF(OR(F42="Riesgos",F42="Obs. Auditoría"),1,0) -> 0 | AF42: =IFERROR(MID(D42,FIND("PMC-",D42),8),"") | AG42: =IF(AND(V42=1,J42<>""),IF(AND(J42>=FechaCorte,J42<=HorizonteExpuestos),1,0),0) -> 0
A43: 42 | B43: 2026 | C43: Automatizaciones | D43: Automatización de la gestión de accesos para las aplicaciones: AS400, GAF, Sistema Monitoreo Fraudes con RPA. | F43: Proyecto | G43: Ana María Fierro | H43: 46098 | J43: 46249 | K43: 0.75 | L43: Pendiente validación API con heaven para luego validación en test y posterior paso a producción. | M43: PR.AA-05 | N43: =IFERROR(INDEX(dFrente!$B$2:$B$76,MATCH(C43,dFrente!$A$2:$A$76,0)),"Sin frente") -> Aplicaciones y roles | O43: =IFERROR(INDEX(dNIST!$B$2:$B$13,MATCH(M43,dNIST!$A$2:$A$13,0)),"") -> PR | P43: =TRIM(IFERROR(LEFT(G43,FIND(CHAR(10),G43)-1),G43)) -> Ana María Fierro | Q43: =LEN(TRIM(G43))-LEN(SUBSTITUTE(TRIM(G43),CHAR(10),""))+1 -> 1 | R43: =IF(E43<>"","Sí","No") -> No | S43: =IF(OR(J43="",H43=""),"",IF(J43<=H43,IF(FechaCorte>=J43,1,0),MAX(0,MIN(1,(FechaCorte-H43)/(J43-H43))))) -> 1 | T43: =IF(S43="","",K43-S43) -> -0.25 | U43: =IF(R43="Sí","Recurrente",IF(K43>=1,"Completado",IF(AND(J43<>"",J43<FechaCorte),"Vencido",IF(AND(K43=0,OR(H43="",H43>FechaCorte)),"Por iniciar",IF(AND(T43<>"",T43<=UmbralRiesgo),"En riesgo","En plazo"))))) -> Vencido | V43: =IF(OR(U43="Vencido",U43="En riesgo",U43="En plazo",U43="Por iniciar"),1,0) -> 1 | W43: =IF(U43="Vencido",FechaCorte-J43,"") -> 40 | X43: =IF(AND(V43=1,U43<>"Vencido"),J43-FechaCorte,"") | Y43: =IF(J43="","",DATE(YEAR(J43),MONTH(J43),1)) -> 46235 | Z43: =IF(AND(U43="Completado",I43<>""),IF(I43<=FechaCorte,DATE(YEAR(I43),MONTH(I43),1),""),"") | AA43: =IF(J43="","",IF(DAY(J43+1)=1,1,0)) -> 0 | AB43: =IF(AND(U43="Completado",I43<>"",I43=J43),1,0) -> 0 | AC43: =IF(AND(K43>=1,I43<>""),IF(I43>FechaCorte,1,0),0) -> 0 | AD43: =IF(AND(I43<>"",H43<>""),IF(I43<H43,1,0),0) -> 0 | AE43: =IF(OR(F43="Riesgos",F43="Obs. Auditoría"),1,0) -> 0 | AF43: =IFERROR(MID(D43,FIND("PMC-",D43),8),"") | AG43: =IF(AND(V43=1,J43<>""),IF(AND(J43>=FechaCorte,J43<=HorizonteExpuestos),1,0),0) -> 0
A44: 43 | B44: 2026 | C44: Migración de módulos de seguridad | D44: Apagado Siglo 21: Sincronización en Test y Producción; Desarrollo Módulo de Seguridad | F44: Proyecto | G44: Ana María Fierro Daniel Lescano | H44: 46156 | I44: 46272 | J44: 46272 | K44: 1 | L44: Se han realizado pruebas, certificación, capacitación; pendiente corregir ciertos hallazgos identificados, validar y pasar el periodo de estabilización (10 días). | M44: PR.PS | N44: =IFERROR(INDEX(dFrente!$B$2:$B$76,MATCH(C44,dFrente!$A$2:$A$76,0)),"Sin frente") -> Aplicaciones y roles | O44: =IFERROR(INDEX(dNIST!$B$2:$B$13,MATCH(M44,dNIST!$A$2:$A$13,0)),"") -> PR | P44: =TRIM(IFERROR(LEFT(G44,FIND(CHAR(10),G44)-1),G44)) -> Ana María Fierro | Q44: =LEN(TRIM(G44))-LEN(SUBSTITUTE(TRIM(G44),CHAR(10),""))+1 -> 2 | R44: =IF(E44<>"","Sí","No") -> No | S44: =IF(OR(J44="",H44=""),"",IF(J44<=H44,IF(FechaCorte>=J44,1,0),MAX(0,MIN(1,(FechaCorte-H44)/(J44-H44))))) -> 1 | T44: =IF(S44="","",K44-S44) -> 0 | U44: =IF(R44="Sí","Recurrente",IF(K44>=1,"Completado",IF(AND(J44<>"",J44<FechaCorte),"Vencido",IF(AND(K44=0,OR(H44="",H44>FechaCorte)),"Por iniciar",IF(AND(T44<>"",T44<=UmbralRiesgo),"En riesgo","En plazo"))))) -> Completado | V44: =IF(OR(U44="Vencido",U44="En riesgo",U44="En plazo",U44="Por iniciar"),1,0) -> 0 | W44: =IF(U44="Vencido",FechaCorte-J44,"") | X44: =IF(AND(V44=1,U44<>"Vencido"),J44-FechaCorte,"") | Y44: =IF(J44="","",DATE(YEAR(J44),MONTH(J44),1)) -> 46266 | Z44: =IF(AND(U44="Completado",I44<>""),IF(I44<=FechaCorte,DATE(YEAR(I44),MONTH(I44),1),""),"") -> 46266 | AA44: =IF(J44="","",IF(DAY(J44+1)=1,1,0)) -> 0 | AB44: =IF(AND(U44="Completado",I44<>"",I44=J44),1,0) -> 1 | AC44: =IF(AND(K44>=1,I44<>""),IF(I44>FechaCorte,1,0),0) -> 0 | AD44: =IF(AND(I44<>"",H44<>""),IF(I44<H44,1,0),0) -> 0 | AE44: =IF(OR(F44="Riesgos",F44="Obs. Auditoría"),1,0) -> 0 | AF44: =IFERROR(MID(D44,FIND("PMC-",D44),8),"") | AG44: =IF(AND(V44=1,J44<>""),IF(AND(J44>=FechaCorte,J44<=HorizonteExpuestos),1,0),0) -> 0
A45: 44 | B45: 2026 | C45: Recepción de Aplicaciones | D45: Transferir aplicaciones al equipo de Gestión de Identidades para su gestión de identidades y accesos. En enero 2026 se tenia 154 aplicaciones administradas, a diciembre se debe llegar a 232 aplicaciones. Llevamos 165 aplicaciones. Pestaña "Recepción de Aplicaciones". | F45: Proyecto | G45: Jhonny Barreiro Yolanda León | H45: 46023 | J45: 46387 | K45: 0.71 | L45: Comprometido en indicador gerencial y fuga de información. Junio.26: Se tienen 169 aplicaciones. Julio.26: Se tienen 176 aplicaciones. | M45: ID.AM | N45: =IFERROR(INDEX(dFrente!$B$2:$B$76,MATCH(C45,dFrente!$A$2:$A$76,0)),"Sin frente") -> Aplicaciones y roles | O45: =IFERROR(INDEX(dNIST!$B$2:$B$13,MATCH(M45,dNIST!$A$2:$A$13,0)),"") -> ID | P45: =TRIM(IFERROR(LEFT(G45,FIND(CHAR(10),G45)-1),G45)) -> Jhonny Barreiro | Q45: =LEN(TRIM(G45))-LEN(SUBSTITUTE(TRIM(G45),CHAR(10),""))+1 -> 2 | R45: =IF(E45<>"","Sí","No") -> No | S45: =IF(OR(J45="",H45=""),"",IF(J45<=H45,IF(FechaCorte>=J45,1,0),MAX(0,MIN(1,(FechaCorte-H45)/(J45-H45))))) -> 0.73076923 | T45: =IF(S45="","",K45-S45) -> -0.020769231 | U45: =IF(R45="Sí","Recurrente",IF(K45>=1,"Completado",IF(AND(J45<>"",J45<FechaCorte),"Vencido",IF(AND(K45=0,OR(H45="",H45>FechaCorte)),"Por iniciar",IF(AND(T45<>"",T45<=UmbralRiesgo),"En riesgo","En plazo"))))) -> En plazo | V45: =IF(OR(U45="Vencido",U45="En riesgo",U45="En plazo",U45="Por iniciar"),1,0) -> 1 | W45: =IF(U45="Vencido",FechaCorte-J45,"") | X45: =IF(AND(V45=1,U45<>"Vencido"),J45-FechaCorte,"") -> 98 | Y45: =IF(J45="","",DATE(YEAR(J45),MONTH(J45),1)) -> 46357 | Z45: =IF(AND(U45="Completado",I45<>""),IF(I45<=FechaCorte,DATE(YEAR(I45),MONTH(I45),1),""),"") | AA45: =IF(J45="","",IF(DAY(J45+1)=1,1,0)) -> 1 | AB45: =IF(AND(U45="Completado",I45<>"",I45=J45),1,0) -> 0 | AC45: =IF(AND(K45>=1,I45<>""),IF(I45>FechaCorte,1,0),0) -> 0 | AD45: =IF(AND(I45<>"",H45<>""),IF(I45<H45,1,0),0) -> 0 | AE45: =IF(OR(F45="Riesgos",F45="Obs. Auditoría"),1,0) -> 0 | AF45: =IFERROR(MID(D45,FIND("PMC-",D45),8),"") | AG45: =IF(AND(V45=1,J45<>""),IF(AND(J45>=FechaCorte,J45<=HorizonteExpuestos),1,0),0) -> 0
A46: 45 | B46: 2026 | C46: Indicador | D46: Indicador IDE 01 Universo de aplicaciones y aplicaicones administradas Monitoreo de Aplicaciones CMDB para validacion de criterios | E46: Mensual | F46: Operación | G46: Jhonny Barreiro | H46: 46113 | K46: 1 | L46: Indicador a Gobierno CS | M46: GV.OV | N46: =IFERROR(INDEX(dFrente!$B$2:$B$76,MATCH(C46,dFrente!$A$2:$A$76,0)),"Sin frente") -> Gobierno y reportería | O46: =IFERROR(INDEX(dNIST!$B$2:$B$13,MATCH(M46,dNIST!$A$2:$A$13,0)),"") -> GV | P46: =TRIM(IFERROR(LEFT(G46,FIND(CHAR(10),G46)-1),G46)) -> Jhonny Barreiro | Q46: =LEN(TRIM(G46))-LEN(SUBSTITUTE(TRIM(G46),CHAR(10),""))+1 -> 1 | R46: =IF(E46<>"","Sí","No") -> Sí | S46: =IF(OR(J46="",H46=""),"",IF(J46<=H46,IF(FechaCorte>=J46,1,0),MAX(0,MIN(1,(FechaCorte-H46)/(J46-H46))))) | T46: =IF(S46="","",K46-S46) | U46: =IF(R46="Sí","Recurrente",IF(K46>=1,"Completado",IF(AND(J46<>"",J46<FechaCorte),"Vencido",IF(AND(K46=0,OR(H46="",H46>FechaCorte)),"Por iniciar",IF(AND(T46<>"",T46<=UmbralRiesgo),"En riesgo","En plazo"))))) -> Recurrente | V46: =IF(OR(U46="Vencido",U46="En riesgo",U46="En plazo",U46="Por iniciar"),1,0) -> 0 | W46: =IF(U46="Vencido",FechaCorte-J46,"") | X46: =IF(AND(V46=1,U46<>"Vencido"),J46-FechaCorte,"") | Y46: =IF(J46="","",DATE(YEAR(J46),MONTH(J46),1)) | Z46: =IF(AND(U46="Completado",I46<>""),IF(I46<=FechaCorte,DATE(YEAR(I46),MONTH(I46),1),""),"") | AA46: =IF(J46="","",IF(DAY(J46+1)=1,1,0)) | AB46: =IF(AND(U46="Completado",I46<>"",I46=J46),1,0) -> 0 | AC46: =IF(AND(K46>=1,I46<>""),IF(I46>FechaCorte,1,0),0) -> 0 | AD46: =IF(AND(I46<>"",H46<>""),IF(I46<H46,1,0),0) -> 0 | AE46: =IF(OR(F46="Riesgos",F46="Obs. Auditoría"),1,0) -> 0 | AF46: =IFERROR(MID(D46,FIND("PMC-",D46),8),"") | AG46: =IF(AND(V46=1,J46<>""),IF(AND(J46>=FechaCorte,J46<=HorizonteExpuestos),1,0),0) -> 0
A47: 46 | B47: 2026 | C47: Recepción de Aplicaciones | D47: Remesas - Cambio de definiciones - Únicamente el equipo GI tenga la facultad de modificar los permisos y roles sobre la aplicación Remesas. - Incorporar en el flujo de aprobación de estos requerimientos de usuarios al equipo de GI. - Documentación para completar el proceso de entrega de gestión de usuarios | F47: Proyecto | G47: Ariel Villacis | H47: 46082 | J47: 46182 | K47: 0.5 | L47: Plan de riesgos | M47: GV.PO | N47: =IFERROR(INDEX(dFrente!$B$2:$B$76,MATCH(C47,dFrente!$A$2:$A$76,0)),"Sin frente") -> Aplicaciones y roles | O47: =IFERROR(INDEX(dNIST!$B$2:$B$13,MATCH(M47,dNIST!$A$2:$A$13,0)),"") -> GV | P47: =TRIM(IFERROR(LEFT(G47,FIND(CHAR(10),G47)-1),G47)) -> Ariel Villacis | Q47: =LEN(TRIM(G47))-LEN(SUBSTITUTE(TRIM(G47),CHAR(10),""))+1 -> 1 | R47: =IF(E47<>"","Sí","No") -> No | S47: =IF(OR(J47="",H47=""),"",IF(J47<=H47,IF(FechaCorte>=J47,1,0),MAX(0,MIN(1,(FechaCorte-H47)/(J47-H47))))) -> 1 | T47: =IF(S47="","",K47-S47) -> -0.5 | U47: =IF(R47="Sí","Recurrente",IF(K47>=1,"Completado",IF(AND(J47<>"",J47<FechaCorte),"Vencido",IF(AND(K47=0,OR(H47="",H47>FechaCorte)),"Por iniciar",IF(AND(T47<>"",T47<=UmbralRiesgo),"En riesgo","En plazo"))))) -> Vencido | V47: =IF(OR(U47="Vencido",U47="En riesgo",U47="En plazo",U47="Por iniciar"),1,0) -> 1 | W47: =IF(U47="Vencido",FechaCorte-J47,"") -> 107 | X47: =IF(AND(V47=1,U47<>"Vencido"),J47-FechaCorte,"") | Y47: =IF(J47="","",DATE(YEAR(J47),MONTH(J47),1)) -> 46174 | Z47: =IF(AND(U47="Completado",I47<>""),IF(I47<=FechaCorte,DATE(YEAR(I47),MONTH(I47),1),""),"") | AA47: =IF(J47="","",IF(DAY(J47+1)=1,1,0)) -> 0 | AB47: =IF(AND(U47="Completado",I47<>"",I47=J47),1,0) -> 0 | AC47: =IF(AND(K47>=1,I47<>""),IF(I47>FechaCorte,1,0),0) -> 0 | AD47: =IF(AND(I47<>"",H47<>""),IF(I47<H47,1,0),0) -> 0 | AE47: =IF(OR(F47="Riesgos",F47="Obs. Auditoría"),1,0) -> 0 | AF47: =IFERROR(MID(D47,FIND("PMC-",D47),8),"") | AG47: =IF(AND(V47=1,J47<>""),IF(AND(J47>=FechaCorte,J47<=HorizonteExpuestos),1,0),0) -> 0
A48: 47 | B48: 2026 | C48: NERM - Externos | D48: Perfilamiento y Gestión de Accesos de Usuarios Externos basado en Estructura Organizacional (Seguimiento a través de la pestaña "Planificación Externos") | F48: Proyecto | G48: Ana María Vergara Jhonny Barreiro Richard Requelme | H48: 46157 | J48: 46310 | K48: 0.05 | L48: Comprometido en indicador gerencial y fuga de información. Desarrollo dashboard. | M48: PR.AA-05 | N48: =IFERROR(INDEX(dFrente!$B$2:$B$76,MATCH(C48,dFrente!$A$2:$A$76,0)),"Sin frente") -> Terceros y genéricos | O48: =IFERROR(INDEX(dNIST!$B$2:$B$13,MATCH(M48,dNIST!$A$2:$A$13,0)),"") -> PR | P48: =TRIM(IFERROR(LEFT(G48,FIND(CHAR(10),G48)-1),G48)) -> Ana María Vergara | Q48: =LEN(TRIM(G48))-LEN(SUBSTITUTE(TRIM(G48),CHAR(10),""))+1 -> 3 | R48: =IF(E48<>"","Sí","No") -> No | S48: =IF(OR(J48="",H48=""),"",IF(J48<=H48,IF(FechaCorte>=J48,1,0),MAX(0,MIN(1,(FechaCorte-H48)/(J48-H48))))) -> 0.8627451 | T48: =IF(S48="","",K48-S48) -> -0.8127451 | U48: =IF(R48="Sí","Recurrente",IF(K48>=1,"Completado",IF(AND(J48<>"",J48<FechaCorte),"Vencido",IF(AND(K48=0,OR(H48="",H48>FechaCorte)),"Por iniciar",IF(AND(T48<>"",T48<=UmbralRiesgo),"En riesgo","En plazo"))))) -> En riesgo | V48: =IF(OR(U48="Vencido",U48="En riesgo",U48="En plazo",U48="Por iniciar"),1,0) -> 1 | W48: =IF(U48="Vencido",FechaCorte-J48,"") | X48: =IF(AND(V48=1,U48<>"Vencido"),J48-FechaCorte,"") -> 21 | Y48: =IF(J48="","",DATE(YEAR(J48),MONTH(J48),1)) -> 46296 | Z48: =IF(AND(U48="Completado",I48<>""),IF(I48<=FechaCorte,DATE(YEAR(I48),MONTH(I48),1),""),"") | AA48: =IF(J48="","",IF(DAY(J48+1)=1,1,0)) -> 0 | AB48: =IF(AND(U48="Completado",I48<>"",I48=J48),1,0) -> 0 | AC48: =IF(AND(K48>=1,I48<>""),IF(I48>FechaCorte,1,0),0) -> 0 | AD48: =IF(AND(I48<>"",H48<>""),IF(I48<H48,1,0),0) -> 0 | AE48: =IF(OR(F48="Riesgos",F48="Obs. Auditoría"),1,0) -> 0 | AF48: =IFERROR(MID(D48,FIND("PMC-",D48),8),"") | AG48: =IF(AND(V48=1,J48<>""),IF(AND(J48>=FechaCorte,J48<=HorizonteExpuestos),1,0),0) -> 1
A49: 48 | B49: 2026 | C49: NERM - Externos | D49: Integrar la aplicación de contratos como fuente autoritativa dentro del sistema de control de accesos de terceros | F49: Iniciativa | G49: Ana María Vergara Jhonny Barreiro Richard Requelme | H49: 46210 | J49: 46387 | K49: 0.25 | L49: 17-ago - El equipo de automatizacion ya se integro con Pegasus (ETL de correo). Pendiente definir campos a consumir en NERM y actualizar el catálogo en SNOW Se revisaron los campos para obtener de Fusion. Se tiene una reunión esta semana con el equipo de automatización para integrar NERM-Pegasus-Fusion | M49: PR.AA-01 | N49: =IFERROR(INDEX(dFrente!$B$2:$B$76,MATCH(C49,dFrente!$A$2:$A$76,0)),"Sin frente") -> Terceros y genéricos | O49: =IFERROR(INDEX(dNIST!$B$2:$B$13,MATCH(M49,dNIST!$A$2:$A$13,0)),"") -> PR | P49: =TRIM(IFERROR(LEFT(G49,FIND(CHAR(10),G49)-1),G49)) -> Ana María Vergara | Q49: =LEN(TRIM(G49))-LEN(SUBSTITUTE(TRIM(G49),CHAR(10),""))+1 -> 3 | R49: =IF(E49<>"","Sí","No") -> No | S49: =IF(OR(J49="",H49=""),"",IF(J49<=H49,IF(FechaCorte>=J49,1,0),MAX(0,MIN(1,(FechaCorte-H49)/(J49-H49))))) -> 0.44632768 | T49: =IF(S49="","",K49-S49) -> -0.19632768 | U49: =IF(R49="Sí","Recurrente",IF(K49>=1,"Completado",IF(AND(J49<>"",J49<FechaCorte),"Vencido",IF(AND(K49=0,OR(H49="",H49>FechaCorte)),"Por iniciar",IF(AND(T49<>"",T49<=UmbralRiesgo),"En riesgo","En plazo"))))) -> En plazo | V49: =IF(OR(U49="Vencido",U49="En riesgo",U49="En plazo",U49="Por iniciar"),1,0) -> 1 | W49: =IF(U49="Vencido",FechaCorte-J49,"") | X49: =IF(AND(V49=1,U49<>"Vencido"),J49-FechaCorte,"") -> 98 | Y49: =IF(J49="","",DATE(YEAR(J49),MONTH(J49),1)) -> 46357 | Z49: =IF(AND(U49="Completado",I49<>""),IF(I49<=FechaCorte,DATE(YEAR(I49),MONTH(I49),1),""),"") | AA49: =IF(J49="","",IF(DAY(J49+1)=1,1,0)) -> 1 | AB49: =IF(AND(U49="Completado",I49<>"",I49=J49),1,0) -> 0 | AC49: =IF(AND(K49>=1,I49<>""),IF(I49>FechaCorte,1,0),0) -> 0 | AD49: =IF(AND(I49<>"",H49<>""),IF(I49<H49,1,0),0) -> 0 | AE49: =IF(OR(F49="Riesgos",F49="Obs. Auditoría"),1,0) -> 0 | AF49: =IFERROR(MID(D49,FIND("PMC-",D49),8),"") | AG49: =IF(AND(V49=1,J49<>""),IF(AND(J49>=FechaCorte,J49<=HorizonteExpuestos),1,0),0) -> 0
A50: 49 | B50: 2026 | C50: NERM - Externos | D50: Modificar el flujo de requerimientos para centralizar y automatizar la gestión de solicitudes ABM de terceros | F50: Iniciativa | G50: Ana María Vergara Jhonny Barreiro Richard Requelme | H50: 46249 | J50: 46356 | K50: 0.1 | M50: PR.AA-01 | N50: =IFERROR(INDEX(dFrente!$B$2:$B$76,MATCH(C50,dFrente!$A$2:$A$76,0)),"Sin frente") -> Terceros y genéricos | O50: =IFERROR(INDEX(dNIST!$B$2:$B$13,MATCH(M50,dNIST!$A$2:$A$13,0)),"") -> PR | P50: =TRIM(IFERROR(LEFT(G50,FIND(CHAR(10),G50)-1),G50)) -> Ana María Vergara | Q50: =LEN(TRIM(G50))-LEN(SUBSTITUTE(TRIM(G50),CHAR(10),""))+1 -> 3 | R50: =IF(E50<>"","Sí","No") -> No | S50: =IF(OR(J50="",H50=""),"",IF(J50<=H50,IF(FechaCorte>=J50,1,0),MAX(0,MIN(1,(FechaCorte-H50)/(J50-H50))))) -> 0.37383178 | T50: =IF(S50="","",K50-S50) -> -0.27383178 | U50: =IF(R50="Sí","Recurrente",IF(K50>=1,"Completado",IF(AND(J50<>"",J50<FechaCorte),"Vencido",IF(AND(K50=0,OR(H50="",H50>FechaCorte)),"Por iniciar",IF(AND(T50<>"",T50<=UmbralRiesgo),"En riesgo","En plazo"))))) -> En riesgo | V50: =IF(OR(U50="Vencido",U50="En riesgo",U50="En plazo",U50="Por iniciar"),1,0) -> 1 | W50: =IF(U50="Vencido",FechaCorte-J50,"") | X50: =IF(AND(V50=1,U50<>"Vencido"),J50-FechaCorte,"") -> 67 | Y50: =IF(J50="","",DATE(YEAR(J50),MONTH(J50),1)) -> 46327 | Z50: =IF(AND(U50="Completado",I50<>""),IF(I50<=FechaCorte,DATE(YEAR(I50),MONTH(I50),1),""),"") | AA50: =IF(J50="","",IF(DAY(J50+1)=1,1,0)) -> 1 | AB50: =IF(AND(U50="Completado",I50<>"",I50=J50),1,0) -> 0 | AC50: =IF(AND(K50>=1,I50<>""),IF(I50>FechaCorte,1,0),0) -> 0 | AD50: =IF(AND(I50<>"",H50<>""),IF(I50<H50,1,0),0) -> 0 | AE50: =IF(OR(F50="Riesgos",F50="Obs. Auditoría"),1,0) -> 0 | AF50: =IFERROR(MID(D50,FIND("PMC-",D50),8),"") | AG50: =IF(AND(V50=1,J50<>""),IF(AND(J50>=FechaCorte,J50<=HorizonteExpuestos),1,0),0) -> 0
A51: 50 | B51: 2026 | C51: NERM - Externos | D51: Usuarios disponibles para ser contraparte de genérico (#2994) | F51: Operación | G51: Richard Requelme | H51: 46188 | I51: 46204 | J51: 46204 | K51: 1 | L51: Se amplia la contraparte para filiales de Pichincha Sistemas Acovi con nivel jerárquico 90 o menos debido a que ellos requieren ser contraparte de sus externos. | M51: PR.AA-01 | N51: =IFERROR(INDEX(dFrente!$B$2:$B$76,MATCH(C51,dFrente!$A$2:$A$76,0)),"Sin frente") -> Terceros y genéricos | O51: =IFERROR(INDEX(dNIST!$B$2:$B$13,MATCH(M51,dNIST!$A$2:$A$13,0)),"") -> PR | P51: =TRIM(IFERROR(LEFT(G51,FIND(CHAR(10),G51)-1),G51)) -> Richard Requelme | Q51: =LEN(TRIM(G51))-LEN(SUBSTITUTE(TRIM(G51),CHAR(10),""))+1 -> 1 | R51: =IF(E51<>"","Sí","No") -> No | S51: =IF(OR(J51="",H51=""),"",IF(J51<=H51,IF(FechaCorte>=J51,1,0),MAX(0,MIN(1,(FechaCorte-H51)/(J51-H51))))) -> 1 | T51: =IF(S51="","",K51-S51) -> 0 | U51: =IF(R51="Sí","Recurrente",IF(K51>=1,"Completado",IF(AND(J51<>"",J51<FechaCorte),"Vencido",IF(AND(K51=0,OR(H51="",H51>FechaCorte)),"Por iniciar",IF(AND(T51<>"",T51<=UmbralRiesgo),"En riesgo","En plazo"))))) -> Completado | V51: =IF(OR(U51="Vencido",U51="En riesgo",U51="En plazo",U51="Por iniciar"),1,0) -> 0 | W51: =IF(U51="Vencido",FechaCorte-J51,"") | X51: =IF(AND(V51=1,U51<>"Vencido"),J51-FechaCorte,"") | Y51: =IF(J51="","",DATE(YEAR(J51),MONTH(J51),1)) -> 46204 | Z51: =IF(AND(U51="Completado",I51<>""),IF(I51<=FechaCorte,DATE(YEAR(I51),MONTH(I51),1),""),"") -> 46204 | AA51: =IF(J51="","",IF(DAY(J51+1)=1,1,0)) -> 0 | AB51: =IF(AND(U51="Completado",I51<>"",I51=J51),1,0) -> 1 | AC51: =IF(AND(K51>=1,I51<>""),IF(I51>FechaCorte,1,0),0) -> 0 | AD51: =IF(AND(I51<>"",H51<>""),IF(I51<H51,1,0),0) -> 0 | AE51: =IF(OR(F51="Riesgos",F51="Obs. Auditoría"),1,0) -> 0 | AF51: =IFERROR(MID(D51,FIND("PMC-",D51),8),"") | AG51: =IF(AND(V51=1,J51<>""),IF(AND(J51>=FechaCorte,J51<=HorizonteExpuestos),1,0),0) -> 0
A52: 51 | B52: 2026 | C52: NERM - Externos | D52: Implementación identificador roles externos | F52: Proyecto | G52: Ana María Vergara Richard Requelme Jhonny Barreiro | H52: 46174 | I52: 46175 | J52: 46175 | K52: 1 | L52: - Solicitud Soporte Assertiva #2914 - Implementación del identificador XXXXXXXXXX en todos los roles de externos con el fin de evitar que queden vacíos y disparen una asignación de accesos incorrecta | M52: PR.AA-05 | N52: =IFERROR(INDEX(dFrente!$B$2:$B$76,MATCH(C52,dFrente!$A$2:$A$76,0)),"Sin frente") -> Terceros y genéricos | O52: =IFERROR(INDEX(dNIST!$B$2:$B$13,MATCH(M52,dNIST!$A$2:$A$13,0)),"") -> PR | P52: =TRIM(IFERROR(LEFT(G52,FIND(CHAR(10),G52)-1),G52)) -> Ana María Vergara | Q52: =LEN(TRIM(G52))-LEN(SUBSTITUTE(TRIM(G52),CHAR(10),""))+1 -> 3 | R52: =IF(E52<>"","Sí","No") -> No | S52: =IF(OR(J52="",H52=""),"",IF(J52<=H52,IF(FechaCorte>=J52,1,0),MAX(0,MIN(1,(FechaCorte-H52)/(J52-H52))))) -> 1 | T52: =IF(S52="","",K52-S52) -> 0 | U52: =IF(R52="Sí","Recurrente",IF(K52>=1,"Completado",IF(AND(J52<>"",J52<FechaCorte),"Vencido",IF(AND(K52=0,OR(H52="",H52>FechaCorte)),"Por iniciar",IF(AND(T52<>"",T52<=UmbralRiesgo),"En riesgo","En plazo"))))) -> Completado | V52: =IF(OR(U52="Vencido",U52="En riesgo",U52="En plazo",U52="Por iniciar"),1,0) -> 0 | W52: =IF(U52="Vencido",FechaCorte-J52,"") | X52: =IF(AND(V52=1,U52<>"Vencido"),J52-FechaCorte,"") | Y52: =IF(J52="","",DATE(YEAR(J52),MONTH(J52),1)) -> 46174 | Z52: =IF(AND(U52="Completado",I52<>""),IF(I52<=FechaCorte,DATE(YEAR(I52),MONTH(I52),1),""),"") -> 46174 | AA52: =IF(J52="","",IF(DAY(J52+1)=1,1,0)) -> 0 | AB52: =IF(AND(U52="Completado",I52<>"",I52=J52),1,0) -> 1 | AC52: =IF(AND(K52>=1,I52<>""),IF(I52>FechaCorte,1,0),0) -> 0 | AD52: =IF(AND(I52<>"",H52<>""),IF(I52<H52,1,0),0) -> 0 | AE52: =IF(OR(F52="Riesgos",F52="Obs. Auditoría"),1,0) -> 0 | AF52: =IFERROR(MID(D52,FIND("PMC-",D52),8),"") | AG52: =IF(AND(V52=1,J52<>""),IF(AND(J52>=FechaCorte,J52<=HorizonteExpuestos),1,0),0) -> 0
A53: 52 | B53: 2026 | C53: NERM - Externos | D53: Definición | Implementación Nomenclatura Código y Nombre de Cargos Externos | F53: Proyecto | G53: Ana María Vergara Jhonny Barreiro | H53: 46134 | I53: 46156 | J53: 46156 | K53: 1 | L53: - Solicitud Soporte Assertiva #2682 | #2767 - Definición e implementación código y nombre de cargo para usuarios externos - Pruebas en aplicaciones evaluar impacto en aprovisionamiento. Prueba Logiflow para que cumpla con la condición de 8 carácteres | M53: GV.PO | N53: =IFERROR(INDEX(dFrente!$B$2:$B$76,MATCH(C53,dFrente!$A$2:$A$76,0)),"Sin frente") -> Terceros y genéricos | O53: =IFERROR(INDEX(dNIST!$B$2:$B$13,MATCH(M53,dNIST!$A$2:$A$13,0)),"") -> GV | P53: =TRIM(IFERROR(LEFT(G53,FIND(CHAR(10),G53)-1),G53)) -> Ana María Vergara | Q53: =LEN(TRIM(G53))-LEN(SUBSTITUTE(TRIM(G53),CHAR(10),""))+1 -> 2 | R53: =IF(E53<>"","Sí","No") -> No | S53: =IF(OR(J53="",H53=""),"",IF(J53<=H53,IF(FechaCorte>=J53,1,0),MAX(0,MIN(1,(FechaCorte-H53)/(J53-H53))))) -> 1 | T53: =IF(S53="","",K53-S53) -> 0 | U53: =IF(R53="Sí","Recurrente",IF(K53>=1,"Completado",IF(AND(J53<>"",J53<FechaCorte),"Vencido",IF(AND(K53=0,OR(H53="",H53>FechaCorte)),"Por iniciar",IF(AND(T53<>"",T53<=UmbralRiesgo),"En riesgo","En plazo"))))) -> Completado | V53: =IF(OR(U53="Vencido",U53="En riesgo",U53="En plazo",U53="Por iniciar"),1,0) -> 0 | W53: =IF(U53="Vencido",FechaCorte-J53,"") | X53: =IF(AND(V53=1,U53<>"Vencido"),J53-FechaCorte,"") | Y53: =IF(J53="","",DATE(YEAR(J53),MONTH(J53),1)) -> 46143 | Z53: =IF(AND(U53="Completado",I53<>""),IF(I53<=FechaCorte,DATE(YEAR(I53),MONTH(I53),1),""),"") -> 46143 | AA53: =IF(J53="","",IF(DAY(J53+1)=1,1,0)) -> 0 | AB53: =IF(AND(U53="Completado",I53<>"",I53=J53),1,0) -> 1 | AC53: =IF(AND(K53>=1,I53<>""),IF(I53>FechaCorte,1,0),0) -> 0 | AD53: =IF(AND(I53<>"",H53<>""),IF(I53<H53,1,0),0) -> 0 | AE53: =IF(OR(F53="Riesgos",F53="Obs. Auditoría"),1,0) -> 0 | AF53: =IFERROR(MID(D53,FIND("PMC-",D53),8),"") | AG53: =IF(AND(V53=1,J53<>""),IF(AND(J53>=FechaCorte,J53<=HorizonteExpuestos),1,0),0) -> 0
A54: 53 | B54: 2026 | C54: NERM - Externos | D54: Ampliación vigencia externos. Encendido sync del atributo | F54: Proyecto | G54: Ana María Vergara | H54: 46185 | I54: 46203 | J54: 46203 | K54: 1 | L54: - Solicitud soporte Assertiva ticket #2986 - Análisis de impacto previo al encendido de atributos - Se corregieron 7 casos con inconsistencia previo al encendido - Se ejecuto el encendido de la sincronización se encuentra funcionando correctamente | M54: PR.AA-01 | N54: =IFERROR(INDEX(dFrente!$B$2:$B$76,MATCH(C54,dFrente!$A$2:$A$76,0)),"Sin frente") -> Terceros y genéricos | O54: =IFERROR(INDEX(dNIST!$B$2:$B$13,MATCH(M54,dNIST!$A$2:$A$13,0)),"") -> PR | P54: =TRIM(IFERROR(LEFT(G54,FIND(CHAR(10),G54)-1),G54)) -> Ana María Vergara | Q54: =LEN(TRIM(G54))-LEN(SUBSTITUTE(TRIM(G54),CHAR(10),""))+1 -> 1 | R54: =IF(E54<>"","Sí","No") -> No | S54: =IF(OR(J54="",H54=""),"",IF(J54<=H54,IF(FechaCorte>=J54,1,0),MAX(0,MIN(1,(FechaCorte-H54)/(J54-H54))))) -> 1 | T54: =IF(S54="","",K54-S54) -> 0 | U54: =IF(R54="Sí","Recurrente",IF(K54>=1,"Completado",IF(AND(J54<>"",J54<FechaCorte),"Vencido",IF(AND(K54=0,OR(H54="",H54>FechaCorte)),"Por iniciar",IF(AND(T54<>"",T54<=UmbralRiesgo),"En riesgo","En plazo"))))) -> Completado | V54: =IF(OR(U54="Vencido",U54="En riesgo",U54="En plazo",U54="Por iniciar"),1,0) -> 0 | W54: =IF(U54="Vencido",FechaCorte-J54,"") | X54: =IF(AND(V54=1,U54<>"Vencido"),J54-FechaCorte,"") | Y54: =IF(J54="","",DATE(YEAR(J54),MONTH(J54),1)) -> 46174 | Z54: =IF(AND(U54="Completado",I54<>""),IF(I54<=FechaCorte,DATE(YEAR(I54),MONTH(I54),1),""),"") -> 46174 | AA54: =IF(J54="","",IF(DAY(J54+1)=1,1,0)) -> 1 | AB54: =IF(AND(U54="Completado",I54<>"",I54=J54),1,0) -> 1 | AC54: =IF(AND(K54>=1,I54<>""),IF(I54>FechaCorte,1,0),0) -> 0 | AD54: =IF(AND(I54<>"",H54<>""),IF(I54<H54,1,0),0) -> 0 | AE54: =IF(OR(F54="Riesgos",F54="Obs. Auditoría"),1,0) -> 0 | AF54: =IFERROR(MID(D54,FIND("PMC-",D54),8),"") | AG54: =IF(AND(V54=1,J54<>""),IF(AND(J54>=FechaCorte,J54<=HorizonteExpuestos),1,0),0) -> 0
A55: 54 | B55: 2026 | C55: NERM - Genéricos | D55: Actualización de contrapartes para usuarios genéricos en AD (#2993) | F55: Operación | G55: Bryan Uyana Richard Requelme | H55: 46163 | I55: 46203 | J55: 46203 | K55: 1 | L55: Sincronización entre actualización de contrapartes genéricas. Una vez ingresado en NERM la actualización, se replica en el campo "Calle" la contraparte al igual que en externos. | M55: PR.AA-01 | N55: =IFERROR(INDEX(dFrente!$B$2:$B$76,MATCH(C55,dFrente!$A$2:$A$76,0)),"Sin frente") -> Terceros y genéricos | O55: =IFERROR(INDEX(dNIST!$B$2:$B$13,MATCH(M55,dNIST!$A$2:$A$13,0)),"") -> PR | P55: =TRIM(IFERROR(LEFT(G55,FIND(CHAR(10),G55)-1),G55)) -> Bryan Uyana | Q55: =LEN(TRIM(G55))-LEN(SUBSTITUTE(TRIM(G55),CHAR(10),""))+1 -> 2 | R55: =IF(E55<>"","Sí","No") -> No | S55: =IF(OR(J55="",H55=""),"",IF(J55<=H55,IF(FechaCorte>=J55,1,0),MAX(0,MIN(1,(FechaCorte-H55)/(J55-H55))))) -> 1 | T55: =IF(S55="","",K55-S55) -> 0 | U55: =IF(R55="Sí","Recurrente",IF(K55>=1,"Completado",IF(AND(J55<>"",J55<FechaCorte),"Vencido",IF(AND(K55=0,OR(H55="",H55>FechaCorte)),"Por iniciar",IF(AND(T55<>"",T55<=UmbralRiesgo),"En riesgo","En plazo"))))) -> Completado | V55: =IF(OR(U55="Vencido",U55="En riesgo",U55="En plazo",U55="Por iniciar"),1,0) -> 0 | W55: =IF(U55="Vencido",FechaCorte-J55,"") | X55: =IF(AND(V55=1,U55<>"Vencido"),J55-FechaCorte,"") | Y55: =IF(J55="","",DATE(YEAR(J55),MONTH(J55),1)) -> 46174 | Z55: =IF(AND(U55="Completado",I55<>""),IF(I55<=FechaCorte,DATE(YEAR(I55),MONTH(I55),1),""),"") -> 46174 | AA55: =IF(J55="","",IF(DAY(J55+1)=1,1,0)) -> 1 | AB55: =IF(AND(U55="Completado",I55<>"",I55=J55),1,0) -> 1 | AC55: =IF(AND(K55>=1,I55<>""),IF(I55>FechaCorte,1,0),0) -> 0 | AD55: =IF(AND(I55<>"",H55<>""),IF(I55<H55,1,0),0) -> 0 | AE55: =IF(OR(F55="Riesgos",F55="Obs. Auditoría"),1,0) -> 0 | AF55: =IFERROR(MID(D55,FIND("PMC-",D55),8),"") | AG55: =IF(AND(V55=1,J55<>""),IF(AND(J55>=FechaCorte,J55<=HorizonteExpuestos),1,0),0) -> 0
A56: 55 | B56: 2026 | C56: NERM - VIP | D56: Registro y administración de usuarios VIP en NERM, garantizando la correcta creación y actualización, ya que actualmente no se registran en el gestor de identidades por tener un contrato como honorarios profesionales registrados en SSFF | F56: Operación | G56: Ana María Vergara | H56: 46249 | J56: 46326 | K56: 0.5 | L56: - Análisis para incluir los casos de usuarios existentes en AD adicionales a usuarios VIP - Coordinación con Andrea Moncayo RRHH a partir de la fecha de inicio del plan para validación e implementación de casos de usuarios VIP de forma controlada - 17/08/2026 Creación de grupo de AD: Grupo Usuarios VIP para colocar a los usuarios con excepción | M56: PR.AA-01 | N56: =IFERROR(INDEX(dFrente!$B$2:$B$76,MATCH(C56,dFrente!$A$2:$A$76,0)),"Sin frente") -> Terceros y genéricos | O56: =IFERROR(INDEX(dNIST!$B$2:$B$13,MATCH(M56,dNIST!$A$2:$A$13,0)),"") -> PR | P56: =TRIM(IFERROR(LEFT(G56,FIND(CHAR(10),G56)-1),G56)) -> Ana María Vergara | Q56: =LEN(TRIM(G56))-LEN(SUBSTITUTE(TRIM(G56),CHAR(10),""))+1 -> 1 | R56: =IF(E56<>"","Sí","No") -> No | S56: =IF(OR(J56="",H56=""),"",IF(J56<=H56,IF(FechaCorte>=J56,1,0),MAX(0,MIN(1,(FechaCorte-H56)/(J56-H56))))) -> 0.51948052 | T56: =IF(S56="","",K56-S56) -> -0.019480519 | U56: =IF(R56="Sí","Recurrente",IF(K56>=1,"Completado",IF(AND(J56<>"",J56<FechaCorte),"Vencido",IF(AND(K56=0,OR(H56="",H56>FechaCorte)),"Por iniciar",IF(AND(T56<>"",T56<=UmbralRiesgo),"En riesgo","En plazo"))))) -> En plazo | V56: =IF(OR(U56="Vencido",U56="En riesgo",U56="En plazo",U56="Por iniciar"),1,0) -> 1 | W56: =IF(U56="Vencido",FechaCorte-J56,"") | X56: =IF(AND(V56=1,U56<>"Vencido"),J56-FechaCorte,"") -> 37 | Y56: =IF(J56="","",DATE(YEAR(J56),MONTH(J56),1)) -> 46296 | Z56: =IF(AND(U56="Completado",I56<>""),IF(I56<=FechaCorte,DATE(YEAR(I56),MONTH(I56),1),""),"") | AA56: =IF(J56="","",IF(DAY(J56+1)=1,1,0)) -> 1 | AB56: =IF(AND(U56="Completado",I56<>"",I56=J56),1,0) -> 0 | AC56: =IF(AND(K56>=1,I56<>""),IF(I56>FechaCorte,1,0),0) -> 0 | AD56: =IF(AND(I56<>"",H56<>""),IF(I56<H56,1,0),0) -> 0 | AE56: =IF(OR(F56="Riesgos",F56="Obs. Auditoría"),1,0) -> 0 | AF56: =IFERROR(MID(D56,FIND("PMC-",D56),8),"") | AG56: =IF(AND(V56=1,J56<>""),IF(AND(J56>=FechaCorte,J56<=HorizonteExpuestos),1,0),0) -> 0
A57: 56 | B57: 2026 | C57: Certificación de Accesos: Nombres de roles | D57: Documentar y describir de manera completa y estandarizada los roles configurados en las herramienta (para iniciar campañas de certificación). | F57: Proyecto | G57: Bryan Uyana Ana María Fierro Daniel Lescano Jhonny Barreiro Ana María Vergara Richard Requelme | H57: 46157 | J57: 46295 | K57: 0.5 | L57: Comprometido para campaña de certificación. | M57: GV.PO | N57: =IFERROR(INDEX(dFrente!$B$2:$B$76,MATCH(C57,dFrente!$A$2:$A$76,0)),"Sin frente") -> Certificación de accesos | O57: =IFERROR(INDEX(dNIST!$B$2:$B$13,MATCH(M57,dNIST!$A$2:$A$13,0)),"") -> GV | P57: =TRIM(IFERROR(LEFT(G57,FIND(CHAR(10),G57)-1),G57)) -> Bryan Uyana | Q57: =LEN(TRIM(G57))-LEN(SUBSTITUTE(TRIM(G57),CHAR(10),""))+1 -> 6 | R57: =IF(E57<>"","Sí","No") -> No | S57: =IF(OR(J57="",H57=""),"",IF(J57<=H57,IF(FechaCorte>=J57,1,0),MAX(0,MIN(1,(FechaCorte-H57)/(J57-H57))))) -> 0.95652174 | T57: =IF(S57="","",K57-S57) -> -0.45652174 | U57: =IF(R57="Sí","Recurrente",IF(K57>=1,"Completado",IF(AND(J57<>"",J57<FechaCorte),"Vencido",IF(AND(K57=0,OR(H57="",H57>FechaCorte)),"Por iniciar",IF(AND(T57<>"",T57<=UmbralRiesgo),"En riesgo","En plazo"))))) -> En riesgo | V57: =IF(OR(U57="Vencido",U57="En riesgo",U57="En plazo",U57="Por iniciar"),1,0) -> 1 | W57: =IF(U57="Vencido",FechaCorte-J57,"") | X57: =IF(AND(V57=1,U57<>"Vencido"),J57-FechaCorte,"") -> 6 | Y57: =IF(J57="","",DATE(YEAR(J57),MONTH(J57),1)) -> 46266 | Z57: =IF(AND(U57="Completado",I57<>""),IF(I57<=FechaCorte,DATE(YEAR(I57),MONTH(I57),1),""),"") | AA57: =IF(J57="","",IF(DAY(J57+1)=1,1,0)) -> 1 | AB57: =IF(AND(U57="Completado",I57<>"",I57=J57),1,0) -> 0 | AC57: =IF(AND(K57>=1,I57<>""),IF(I57>FechaCorte,1,0),0) -> 0 | AD57: =IF(AND(I57<>"",H57<>""),IF(I57<H57,1,0),0) -> 0 | AE57: =IF(OR(F57="Riesgos",F57="Obs. Auditoría"),1,0) -> 0 | AF57: =IFERROR(MID(D57,FIND("PMC-",D57),8),"") | AG57: =IF(AND(V57=1,J57<>""),IF(AND(J57>=FechaCorte,J57<=HorizonteExpuestos),1,0),0) -> 1
A58: 57 | B58: 2026 | C58: Certificación de Accesos: Revisión inconsistencias | D58: Proceso de consistencia aplicaciones vs. gestor Sailpoint | F58: Proyecto | G58: Bryan Uyana Ana María Fierro Daniel Lescano | H58: 46082 | J58: 46325 | K58: 0.2 | M58: PR.AA-05 | N58: =IFERROR(INDEX(dFrente!$B$2:$B$76,MATCH(C58,dFrente!$A$2:$A$76,0)),"Sin frente") -> Certificación de accesos | O58: =IFERROR(INDEX(dNIST!$B$2:$B$13,MATCH(M58,dNIST!$A$2:$A$13,0)),"") -> PR | P58: =TRIM(IFERROR(LEFT(G58,FIND(CHAR(10),G58)-1),G58)) -> Bryan Uyana | Q58: =LEN(TRIM(G58))-LEN(SUBSTITUTE(TRIM(G58),CHAR(10),""))+1 -> 3 | R58: =IF(E58<>"","Sí","No") -> No | S58: =IF(OR(J58="",H58=""),"",IF(J58<=H58,IF(FechaCorte>=J58,1,0),MAX(0,MIN(1,(FechaCorte-H58)/(J58-H58))))) -> 0.85185185 | T58: =IF(S58="","",K58-S58) -> -0.65185185 | U58: =IF(R58="Sí","Recurrente",IF(K58>=1,"Completado",IF(AND(J58<>"",J58<FechaCorte),"Vencido",IF(AND(K58=0,OR(H58="",H58>FechaCorte)),"Por iniciar",IF(AND(T58<>"",T58<=UmbralRiesgo),"En riesgo","En plazo"))))) -> En riesgo | V58: =IF(OR(U58="Vencido",U58="En riesgo",U58="En plazo",U58="Por iniciar"),1,0) -> 1 | W58: =IF(U58="Vencido",FechaCorte-J58,"") | X58: =IF(AND(V58=1,U58<>"Vencido"),J58-FechaCorte,"") -> 36 | Y58: =IF(J58="","",DATE(YEAR(J58),MONTH(J58),1)) -> 46296 | Z58: =IF(AND(U58="Completado",I58<>""),IF(I58<=FechaCorte,DATE(YEAR(I58),MONTH(I58),1),""),"") | AA58: =IF(J58="","",IF(DAY(J58+1)=1,1,0)) -> 0 | AB58: =IF(AND(U58="Completado",I58<>"",I58=J58),1,0) -> 0 | AC58: =IF(AND(K58>=1,I58<>""),IF(I58>FechaCorte,1,0),0) -> 0 | AD58: =IF(AND(I58<>"",H58<>""),IF(I58<H58,1,0),0) -> 0 | AE58: =IF(OR(F58="Riesgos",F58="Obs. Auditoría"),1,0) -> 0 | AF58: =IFERROR(MID(D58,FIND("PMC-",D58),8),"") | AG58: =IF(AND(V58=1,J58<>""),IF(AND(J58>=FechaCorte,J58<=HorizonteExpuestos),1,0),0) -> 0
A59: 58 | B59: 2026 | C59: Certificación de Accesos: Usuarios Internos/Externos | D59: Ejecución de campañas de certificación (Externos 100%, Internos 80%, Filiales 0%). PMC-2943 | F59: Proyecto | G59: Todo el Equipo | H59: 46174 | J59: 46387 | K59: 0.3 | L59: Comprometido con riesgos, fuga de información. | M59: PR.AA-05 | N59: =IFERROR(INDEX(dFrente!$B$2:$B$76,MATCH(C59,dFrente!$A$2:$A$76,0)),"Sin frente") -> Certificación de accesos | O59: =IFERROR(INDEX(dNIST!$B$2:$B$13,MATCH(M59,dNIST!$A$2:$A$13,0)),"") -> PR | P59: =TRIM(IFERROR(LEFT(G59,FIND(CHAR(10),G59)-1),G59)) -> Todo el Equipo | Q59: =LEN(TRIM(G59))-LEN(SUBSTITUTE(TRIM(G59),CHAR(10),""))+1 -> 1 | R59: =IF(E59<>"","Sí","No") -> No | S59: =IF(OR(J59="",H59=""),"",IF(J59<=H59,IF(FechaCorte>=J59,1,0),MAX(0,MIN(1,(FechaCorte-H59)/(J59-H59))))) -> 0.5399061 | T59: =IF(S59="","",K59-S59) -> -0.2399061 | U59: =IF(R59="Sí","Recurrente",IF(K59>=1,"Completado",IF(AND(J59<>"",J59<FechaCorte),"Vencido",IF(AND(K59=0,OR(H59="",H59>FechaCorte)),"Por iniciar",IF(AND(T59<>"",T59<=UmbralRiesgo),"En riesgo","En plazo"))))) -> En plazo | V59: =IF(OR(U59="Vencido",U59="En riesgo",U59="En plazo",U59="Por iniciar"),1,0) -> 1 | W59: =IF(U59="Vencido",FechaCorte-J59,"") | X59: =IF(AND(V59=1,U59<>"Vencido"),J59-FechaCorte,"") -> 98 | Y59: =IF(J59="","",DATE(YEAR(J59),MONTH(J59),1)) -> 46357 | Z59: =IF(AND(U59="Completado",I59<>""),IF(I59<=FechaCorte,DATE(YEAR(I59),MONTH(I59),1),""),"") | AA59: =IF(J59="","",IF(DAY(J59+1)=1,1,0)) -> 1 | AB59: =IF(AND(U59="Completado",I59<>"",I59=J59),1,0) -> 0 | AC59: =IF(AND(K59>=1,I59<>""),IF(I59>FechaCorte,1,0),0) -> 0 | AD59: =IF(AND(I59<>"",H59<>""),IF(I59<H59,1,0),0) -> 0 | AE59: =IF(OR(F59="Riesgos",F59="Obs. Auditoría"),1,0) -> 0 | AF59: =IFERROR(MID(D59,FIND("PMC-",D59),8),"") -> PMC-2943 | AG59: =IF(AND(V59=1,J59<>""),IF(AND(J59>=FechaCorte,J59<=HorizonteExpuestos),1,0),0) -> 0
A60: 59 | B60: 2026 | C60: Usuarios Genéricos | D60: Integración de Registros de Caja Fuerte - NERM | F60: Iniciativa | G60: Richard Requelme | H60: 46174 | J60: 46295 | K60: 0.5 | L60: Se definio el modelo de caja fuerte, ahora se va a migrar todos los campos requeridos en NERM para no tener doble registro | M60: PR.AA-01 | N60: =IFERROR(INDEX(dFrente!$B$2:$B$76,MATCH(C60,dFrente!$A$2:$A$76,0)),"Sin frente") -> Terceros y genéricos | O60: =IFERROR(INDEX(dNIST!$B$2:$B$13,MATCH(M60,dNIST!$A$2:$A$13,0)),"") -> PR | P60: =TRIM(IFERROR(LEFT(G60,FIND(CHAR(10),G60)-1),G60)) -> Richard Requelme | Q60: =LEN(TRIM(G60))-LEN(SUBSTITUTE(TRIM(G60),CHAR(10),""))+1 -> 1 | R60: =IF(E60<>"","Sí","No") -> No | S60: =IF(OR(J60="",H60=""),"",IF(J60<=H60,IF(FechaCorte>=J60,1,0),MAX(0,MIN(1,(FechaCorte-H60)/(J60-H60))))) -> 0.95041322 | T60: =IF(S60="","",K60-S60) -> -0.45041322 | U60: =IF(R60="Sí","Recurrente",IF(K60>=1,"Completado",IF(AND(J60<>"",J60<FechaCorte),"Vencido",IF(AND(K60=0,OR(H60="",H60>FechaCorte)),"Por iniciar",IF(AND(T60<>"",T60<=UmbralRiesgo),"En riesgo","En plazo"))))) -> En riesgo | V60: =IF(OR(U60="Vencido",U60="En riesgo",U60="En plazo",U60="Por iniciar"),1,0) -> 1 | W60: =IF(U60="Vencido",FechaCorte-J60,"") | X60: =IF(AND(V60=1,U60<>"Vencido"),J60-FechaCorte,"") -> 6 | Y60: =IF(J60="","",DATE(YEAR(J60),MONTH(J60),1)) -> 46266 | Z60: =IF(AND(U60="Completado",I60<>""),IF(I60<=FechaCorte,DATE(YEAR(I60),MONTH(I60),1),""),"") | AA60: =IF(J60="","",IF(DAY(J60+1)=1,1,0)) -> 1 | AB60: =IF(AND(U60="Completado",I60<>"",I60=J60),1,0) -> 0 | AC60: =IF(AND(K60>=1,I60<>""),IF(I60>FechaCorte,1,0),0) -> 0 | AD60: =IF(AND(I60<>"",H60<>""),IF(I60<H60,1,0),0) -> 0 | AE60: =IF(OR(F60="Riesgos",F60="Obs. Auditoría"),1,0) -> 0 | AF60: =IFERROR(MID(D60,FIND("PMC-",D60),8),"") | AG60: =IF(AND(V60=1,J60<>""),IF(AND(J60>=FechaCorte,J60<=HorizonteExpuestos),1,0),0) -> 1
A61: 60 | B61: 2026 | C61: Usuarios Genéricos | D61: Registro de Genéricos de Sistema (#3158) | F61: Iniciativa | G61: Richard Requelme | H61: 46204 | J61: 46264 | K61: 0.95 | L61: - 15-sept: Se requiere socializar, ya se completo este flujo. Para el proceso de caja fuerte: se requiere un nuevo flujo de registro de genérico de sistema, únicamente debe vivir en NERM y no en ISC. Es netamente informativo. Es una cuenta que tiene los campos de: usuario, responsable, custodio de contraseña, descripción, ticket asociado y privilegiado (si/no). | M61: PR.AA-01 | N61: =IFERROR(INDEX(dFrente!$B$2:$B$76,MATCH(C61,dFrente!$A$2:$A$76,0)),"Sin frente") -> Terceros y genéricos | O61: =IFERROR(INDEX(dNIST!$B$2:$B$13,MATCH(M61,dNIST!$A$2:$A$13,0)),"") -> PR | P61: =TRIM(IFERROR(LEFT(G61,FIND(CHAR(10),G61)-1),G61)) -> Richard Requelme | Q61: =LEN(TRIM(G61))-LEN(SUBSTITUTE(TRIM(G61),CHAR(10),""))+1 -> 1 | R61: =IF(E61<>"","Sí","No") -> No | S61: =IF(OR(J61="",H61=""),"",IF(J61<=H61,IF(FechaCorte>=J61,1,0),MAX(0,MIN(1,(FechaCorte-H61)/(J61-H61))))) -> 1 | T61: =IF(S61="","",K61-S61) -> -0.05 | U61: =IF(R61="Sí","Recurrente",IF(K61>=1,"Completado",IF(AND(J61<>"",J61<FechaCorte),"Vencido",IF(AND(K61=0,OR(H61="",H61>FechaCorte)),"Por iniciar",IF(AND(T61<>"",T61<=UmbralRiesgo),"En riesgo","En plazo"))))) -> Vencido | V61: =IF(OR(U61="Vencido",U61="En riesgo",U61="En plazo",U61="Por iniciar"),1,0) -> 1 | W61: =IF(U61="Vencido",FechaCorte-J61,"") -> 25 | X61: =IF(AND(V61=1,U61<>"Vencido"),J61-FechaCorte,"") | Y61: =IF(J61="","",DATE(YEAR(J61),MONTH(J61),1)) -> 46235 | Z61: =IF(AND(U61="Completado",I61<>""),IF(I61<=FechaCorte,DATE(YEAR(I61),MONTH(I61),1),""),"") | AA61: =IF(J61="","",IF(DAY(J61+1)=1,1,0)) -> 0 | AB61: =IF(AND(U61="Completado",I61<>"",I61=J61),1,0) -> 0 | AC61: =IF(AND(K61>=1,I61<>""),IF(I61>FechaCorte,1,0),0) -> 0 | AD61: =IF(AND(I61<>"",H61<>""),IF(I61<H61,1,0),0) -> 0 | AE61: =IF(OR(F61="Riesgos",F61="Obs. Auditoría"),1,0) -> 0 | AF61: =IFERROR(MID(D61,FIND("PMC-",D61),8),"") | AG61: =IF(AND(V61=1,J61<>""),IF(AND(J61>=FechaCorte,J61<=HorizonteExpuestos),1,0),0) -> 0
A62: 61 | B62: 2026 | C62: Usuarios Genéricos | D62: Proyecto genéricos (identificación, responsable, funcionalidad, caducidad clave, MFA, bloqueo inicio de sesión, depuración y monitoreo). | F62: Iniciativa | G62: Yolanda León | H62: 46174 | J62: 46356 | K62: 0.05 | M62: PR.AA-01 | N62: =IFERROR(INDEX(dFrente!$B$2:$B$76,MATCH(C62,dFrente!$A$2:$A$76,0)),"Sin frente") -> Terceros y genéricos | O62: =IFERROR(INDEX(dNIST!$B$2:$B$13,MATCH(M62,dNIST!$A$2:$A$13,0)),"") -> PR | P62: =TRIM(IFERROR(LEFT(G62,FIND(CHAR(10),G62)-1),G62)) -> Yolanda León | Q62: =LEN(TRIM(G62))-LEN(SUBSTITUTE(TRIM(G62),CHAR(10),""))+1 -> 1 | R62: =IF(E62<>"","Sí","No") -> No | S62: =IF(OR(J62="",H62=""),"",IF(J62<=H62,IF(FechaCorte>=J62,1,0),MAX(0,MIN(1,(FechaCorte-H62)/(J62-H62))))) -> 0.63186813 | T62: =IF(S62="","",K62-S62) -> -0.58186813 | U62: =IF(R62="Sí","Recurrente",IF(K62>=1,"Completado",IF(AND(J62<>"",J62<FechaCorte),"Vencido",IF(AND(K62=0,OR(H62="",H62>FechaCorte)),"Por iniciar",IF(AND(T62<>"",T62<=UmbralRiesgo),"En riesgo","En plazo"))))) -> En riesgo | V62: =IF(OR(U62="Vencido",U62="En riesgo",U62="En plazo",U62="Por iniciar"),1,0) -> 1 | W62: =IF(U62="Vencido",FechaCorte-J62,"") | X62: =IF(AND(V62=1,U62<>"Vencido"),J62-FechaCorte,"") -> 67 | Y62: =IF(J62="","",DATE(YEAR(J62),MONTH(J62),1)) -> 46327 | Z62: =IF(AND(U62="Completado",I62<>""),IF(I62<=FechaCorte,DATE(YEAR(I62),MONTH(I62),1),""),"") | AA62: =IF(J62="","",IF(DAY(J62+1)=1,1,0)) -> 1 | AB62: =IF(AND(U62="Completado",I62<>"",I62=J62),1,0) -> 0 | AC62: =IF(AND(K62>=1,I62<>""),IF(I62>FechaCorte,1,0),0) -> 0 | AD62: =IF(AND(I62<>"",H62<>""),IF(I62<H62,1,0),0) -> 0 | AE62: =IF(OR(F62="Riesgos",F62="Obs. Auditoría"),1,0) -> 0 | AF62: =IFERROR(MID(D62,FIND("PMC-",D62),8),"") | AG62: =IF(AND(V62=1,J62<>""),IF(AND(J62>=FechaCorte,J62<=HorizonteExpuestos),1,0),0) -> 0
A63: 62 | B63: 2026 | C63: Usuarios Genéricos | D63: Revisión de los roles asignados a los genéricos obsoletos (estos tienen los grupos de AD: GF_BP_UC, GF_FW_FILESERVER, GF_FW_FTP, GSC_CGDA_SalesforceGlobal, GSC_BP-Athento.Office-Prod_UsersBP, GSC_CGDA_MembersGeneral, GSC_CA-Persona-CorpServiceAccounts-Entra) | F63: Iniciativa | G63: Richard Requelme | H63: 46218 | J63: 46264 | K63: 0.8 | L63: -15-sept- se depuro todo el tema de Nube | M63: PR.AA-05 | N63: =IFERROR(INDEX(dFrente!$B$2:$B$76,MATCH(C63,dFrente!$A$2:$A$76,0)),"Sin frente") -> Terceros y genéricos | O63: =IFERROR(INDEX(dNIST!$B$2:$B$13,MATCH(M63,dNIST!$A$2:$A$13,0)),"") -> PR | P63: =TRIM(IFERROR(LEFT(G63,FIND(CHAR(10),G63)-1),G63)) -> Richard Requelme | Q63: =LEN(TRIM(G63))-LEN(SUBSTITUTE(TRIM(G63),CHAR(10),""))+1 -> 1 | R63: =IF(E63<>"","Sí","No") -> No | S63: =IF(OR(J63="",H63=""),"",IF(J63<=H63,IF(FechaCorte>=J63,1,0),MAX(0,MIN(1,(FechaCorte-H63)/(J63-H63))))) -> 1 | T63: =IF(S63="","",K63-S63) -> -0.2 | U63: =IF(R63="Sí","Recurrente",IF(K63>=1,"Completado",IF(AND(J63<>"",J63<FechaCorte),"Vencido",IF(AND(K63=0,OR(H63="",H63>FechaCorte)),"Por iniciar",IF(AND(T63<>"",T63<=UmbralRiesgo),"En riesgo","En plazo"))))) -> Vencido | V63: =IF(OR(U63="Vencido",U63="En riesgo",U63="En plazo",U63="Por iniciar"),1,0) -> 1 | W63: =IF(U63="Vencido",FechaCorte-J63,"") -> 25 | X63: =IF(AND(V63=1,U63<>"Vencido"),J63-FechaCorte,"") | Y63: =IF(J63="","",DATE(YEAR(J63),MONTH(J63),1)) -> 46235 | Z63: =IF(AND(U63="Completado",I63<>""),IF(I63<=FechaCorte,DATE(YEAR(I63),MONTH(I63),1),""),"") | AA63: =IF(J63="","",IF(DAY(J63+1)=1,1,0)) -> 0 | AB63: =IF(AND(U63="Completado",I63<>"",I63=J63),1,0) -> 0 | AC63: =IF(AND(K63>=1,I63<>""),IF(I63>FechaCorte,1,0),0) -> 0 | AD63: =IF(AND(I63<>"",H63<>""),IF(I63<H63,1,0),0) -> 0 | AE63: =IF(OR(F63="Riesgos",F63="Obs. Auditoría"),1,0) -> 0 | AF63: =IFERROR(MID(D63,FIND("PMC-",D63),8),"") | AG63: =IF(AND(V63=1,J63<>""),IF(AND(J63>=FechaCorte,J63<=HorizonteExpuestos),1,0),0) -> 0
A64: 63 | B64: 2026 | C64: Certificación de Accesos: Genéricos | D64: Revisión y eliminación usuarios genéricos duplicados en AD. | F64: Operación | G64: Bryan Uyana | H64: 46082 | I64: 46272 | J64: 46272 | K64: 1 | M64: PR.AA-01 | N64: =IFERROR(INDEX(dFrente!$B$2:$B$76,MATCH(C64,dFrente!$A$2:$A$76,0)),"Sin frente") -> Certificación de accesos | O64: =IFERROR(INDEX(dNIST!$B$2:$B$13,MATCH(M64,dNIST!$A$2:$A$13,0)),"") -> PR | P64: =TRIM(IFERROR(LEFT(G64,FIND(CHAR(10),G64)-1),G64)) -> Bryan Uyana | Q64: =LEN(TRIM(G64))-LEN(SUBSTITUTE(TRIM(G64),CHAR(10),""))+1 -> 1 | R64: =IF(E64<>"","Sí","No") -> No | S64: =IF(OR(J64="",H64=""),"",IF(J64<=H64,IF(FechaCorte>=J64,1,0),MAX(0,MIN(1,(FechaCorte-H64)/(J64-H64))))) -> 1 | T64: =IF(S64="","",K64-S64) -> 0 | U64: =IF(R64="Sí","Recurrente",IF(K64>=1,"Completado",IF(AND(J64<>"",J64<FechaCorte),"Vencido",IF(AND(K64=0,OR(H64="",H64>FechaCorte)),"Por iniciar",IF(AND(T64<>"",T64<=UmbralRiesgo),"En riesgo","En plazo"))))) -> Completado | V64: =IF(OR(U64="Vencido",U64="En riesgo",U64="En plazo",U64="Por iniciar"),1,0) -> 0 | W64: =IF(U64="Vencido",FechaCorte-J64,"") | X64: =IF(AND(V64=1,U64<>"Vencido"),J64-FechaCorte,"") | Y64: =IF(J64="","",DATE(YEAR(J64),MONTH(J64),1)) -> 46266 | Z64: =IF(AND(U64="Completado",I64<>""),IF(I64<=FechaCorte,DATE(YEAR(I64),MONTH(I64),1),""),"") -> 46266 | AA64: =IF(J64="","",IF(DAY(J64+1)=1,1,0)) -> 0 | AB64: =IF(AND(U64="Completado",I64<>"",I64=J64),1,0) -> 1 | AC64: =IF(AND(K64>=1,I64<>""),IF(I64>FechaCorte,1,0),0) -> 0 | AD64: =IF(AND(I64<>"",H64<>""),IF(I64<H64,1,0),0) -> 0 | AE64: =IF(OR(F64="Riesgos",F64="Obs. Auditoría"),1,0) -> 0 | AF64: =IFERROR(MID(D64,FIND("PMC-",D64),8),"") | AG64: =IF(AND(V64=1,J64<>""),IF(AND(J64>=FechaCorte,J64<=HorizonteExpuestos),1,0),0) -> 0
A65: 64 | B65: 2026 | C65: Certificación de Accesos: Genéricos | D65: Identificación de usuarios genéricos de procesos manuales y procesos automáticos (habilitar políticas de seguridad). | F65: Iniciativa | G65: Ana María Fierro Yolanda León Santiago Barahona | H65: 46162 | J65: 46387 | K65: 0.25 | L65: Habilitación de passworless | M65: PR.AA-05 | N65: =IFERROR(INDEX(dFrente!$B$2:$B$76,MATCH(C65,dFrente!$A$2:$A$76,0)),"Sin frente") -> Certificación de accesos | O65: =IFERROR(INDEX(dNIST!$B$2:$B$13,MATCH(M65,dNIST!$A$2:$A$13,0)),"") -> PR | P65: =TRIM(IFERROR(LEFT(G65,FIND(CHAR(10),G65)-1),G65)) -> Ana María Fierro | Q65: =LEN(TRIM(G65))-LEN(SUBSTITUTE(TRIM(G65),CHAR(10),""))+1 -> 3 | R65: =IF(E65<>"","Sí","No") -> No | S65: =IF(OR(J65="",H65=""),"",IF(J65<=H65,IF(FechaCorte>=J65,1,0),MAX(0,MIN(1,(FechaCorte-H65)/(J65-H65))))) -> 0.56444444 | T65: =IF(S65="","",K65-S65) -> -0.31444444 | U65: =IF(R65="Sí","Recurrente",IF(K65>=1,"Completado",IF(AND(J65<>"",J65<FechaCorte),"Vencido",IF(AND(K65=0,OR(H65="",H65>FechaCorte)),"Por iniciar",IF(AND(T65<>"",T65<=UmbralRiesgo),"En riesgo","En plazo"))))) -> En riesgo | V65: =IF(OR(U65="Vencido",U65="En riesgo",U65="En plazo",U65="Por iniciar"),1,0) -> 1 | W65: =IF(U65="Vencido",FechaCorte-J65,"") | X65: =IF(AND(V65=1,U65<>"Vencido"),J65-FechaCorte,"") -> 98 | Y65: =IF(J65="","",DATE(YEAR(J65),MONTH(J65),1)) -> 46357 | Z65: =IF(AND(U65="Completado",I65<>""),IF(I65<=FechaCorte,DATE(YEAR(I65),MONTH(I65),1),""),"") | AA65: =IF(J65="","",IF(DAY(J65+1)=1,1,0)) -> 1 | AB65: =IF(AND(U65="Completado",I65<>"",I65=J65),1,0) -> 0 | AC65: =IF(AND(K65>=1,I65<>""),IF(I65>FechaCorte,1,0),0) -> 0 | AD65: =IF(AND(I65<>"",H65<>""),IF(I65<H65,1,0),0) -> 0 | AE65: =IF(OR(F65="Riesgos",F65="Obs. Auditoría"),1,0) -> 0 | AF65: =IFERROR(MID(D65,FIND("PMC-",D65),8),"") | AG65: =IF(AND(V65=1,J65<>""),IF(AND(J65>=FechaCorte,J65<=HorizonteExpuestos),1,0),0) -> 0
A66: 65 | B66: 2026 | C66: Certificación de Accesos: Genéricos | D66: Identificación de cuentas genéricas que inician sesión en las estaciones de trabajo. Caso de uso con Ciberdefensa | F66: Iniciativa | G66: Bryan Uyana Yolanda León Vinicio Samaniego | H66: 46212 | J66: 46326 | K66: 0.15 | L66: Se inactivó el usuario USRPCCPY (24-07-2026) | M66: DE.CM | N66: =IFERROR(INDEX(dFrente!$B$2:$B$76,MATCH(C66,dFrente!$A$2:$A$76,0)),"Sin frente") -> Certificación de accesos | O66: =IFERROR(INDEX(dNIST!$B$2:$B$13,MATCH(M66,dNIST!$A$2:$A$13,0)),"") -> DE | P66: =TRIM(IFERROR(LEFT(G66,FIND(CHAR(10),G66)-1),G66)) -> Bryan Uyana | Q66: =LEN(TRIM(G66))-LEN(SUBSTITUTE(TRIM(G66),CHAR(10),""))+1 -> 3 | R66: =IF(E66<>"","Sí","No") -> No | S66: =IF(OR(J66="",H66=""),"",IF(J66<=H66,IF(FechaCorte>=J66,1,0),MAX(0,MIN(1,(FechaCorte-H66)/(J66-H66))))) -> 0.6754386 | T66: =IF(S66="","",K66-S66) -> -0.5254386 | U66: =IF(R66="Sí","Recurrente",IF(K66>=1,"Completado",IF(AND(J66<>"",J66<FechaCorte),"Vencido",IF(AND(K66=0,OR(H66="",H66>FechaCorte)),"Por iniciar",IF(AND(T66<>"",T66<=UmbralRiesgo),"En riesgo","En plazo"))))) -> En riesgo | V66: =IF(OR(U66="Vencido",U66="En riesgo",U66="En plazo",U66="Por iniciar"),1,0) -> 1 | W66: =IF(U66="Vencido",FechaCorte-J66,"") | X66: =IF(AND(V66=1,U66<>"Vencido"),J66-FechaCorte,"") -> 37 | Y66: =IF(J66="","",DATE(YEAR(J66),MONTH(J66),1)) -> 46296 | Z66: =IF(AND(U66="Completado",I66<>""),IF(I66<=FechaCorte,DATE(YEAR(I66),MONTH(I66),1),""),"") | AA66: =IF(J66="","",IF(DAY(J66+1)=1,1,0)) -> 1 | AB66: =IF(AND(U66="Completado",I66<>"",I66=J66),1,0) -> 0 | AC66: =IF(AND(K66>=1,I66<>""),IF(I66>FechaCorte,1,0),0) -> 0 | AD66: =IF(AND(I66<>"",H66<>""),IF(I66<H66,1,0),0) -> 0 | AE66: =IF(OR(F66="Riesgos",F66="Obs. Auditoría"),1,0) -> 0 | AF66: =IFERROR(MID(D66,FIND("PMC-",D66),8),"") | AG66: =IF(AND(V66=1,J66<>""),IF(AND(J66>=FechaCorte,J66<=HorizonteExpuestos),1,0),0) -> 0
A67: 66 | B67: 2026 | C67: Certificación de Accesos: Accesos usuarios | D67: Controlar el uso de cuentas de usuarios que no han iniciado sesión en 120 días. (Control con TCS). | E67: Mensual | F67: Operación | G67: Bryan Uyana | H67: 46113 | K67: 1 | L67: Esta actividad es permanente, mensual. | M67: DE.CM | N67: =IFERROR(INDEX(dFrente!$B$2:$B$76,MATCH(C67,dFrente!$A$2:$A$76,0)),"Sin frente") -> Certificación de accesos | O67: =IFERROR(INDEX(dNIST!$B$2:$B$13,MATCH(M67,dNIST!$A$2:$A$13,0)),"") -> DE | P67: =TRIM(IFERROR(LEFT(G67,FIND(CHAR(10),G67)-1),G67)) -> Bryan Uyana | Q67: =LEN(TRIM(G67))-LEN(SUBSTITUTE(TRIM(G67),CHAR(10),""))+1 -> 1 | R67: =IF(E67<>"","Sí","No") -> Sí | S67: =IF(OR(J67="",H67=""),"",IF(J67<=H67,IF(FechaCorte>=J67,1,0),MAX(0,MIN(1,(FechaCorte-H67)/(J67-H67))))) | T67: =IF(S67="","",K67-S67) | U67: =IF(R67="Sí","Recurrente",IF(K67>=1,"Completado",IF(AND(J67<>"",J67<FechaCorte),"Vencido",IF(AND(K67=0,OR(H67="",H67>FechaCorte)),"Por iniciar",IF(AND(T67<>"",T67<=UmbralRiesgo),"En riesgo","En plazo"))))) -> Recurrente | V67: =IF(OR(U67="Vencido",U67="En riesgo",U67="En plazo",U67="Por iniciar"),1,0) -> 0 | W67: =IF(U67="Vencido",FechaCorte-J67,"") | X67: =IF(AND(V67=1,U67<>"Vencido"),J67-FechaCorte,"") | Y67: =IF(J67="","",DATE(YEAR(J67),MONTH(J67),1)) | Z67: =IF(AND(U67="Completado",I67<>""),IF(I67<=FechaCorte,DATE(YEAR(I67),MONTH(I67),1),""),"") | AA67: =IF(J67="","",IF(DAY(J67+1)=1,1,0)) | AB67: =IF(AND(U67="Completado",I67<>"",I67=J67),1,0) -> 0 | AC67: =IF(AND(K67>=1,I67<>""),IF(I67>FechaCorte,1,0),0) -> 0 | AD67: =IF(AND(I67<>"",H67<>""),IF(I67<H67,1,0),0) -> 0 | AE67: =IF(OR(F67="Riesgos",F67="Obs. Auditoría"),1,0) -> 0 | AF67: =IFERROR(MID(D67,FIND("PMC-",D67),8),"") | AG67: =IF(AND(V67=1,J67<>""),IF(AND(J67>=FechaCorte,J67<=HorizonteExpuestos),1,0),0) -> 0
A68: 67 | B68: 2026 | C68: Cesantes | D68: Actualización Automática de Contrapartes Cesantes - Genéricos y Externos (#3159) | F68: Iniciativa | G68: Richard Requelme Bryan Uyana | H68: 46210 | I68: 46248 | J68: 46248 | K68: 1 | L68: -15-sept- Falta únicamente socializarRevisar el proceso cuando un interno sale de la organización, y el mismo tiene asociado usuarios genéricos y externos bajo su cargo. Esto debido a que el proceso actual es manual. La idea es que se actualice automáticamente y se asigne a su línea de supervisión (siempre y cuando tenga un rango jerarquico > 50 y no sea un usuario VIP) hasta que se defina un responsable nuevo. | M68: PR.AA-01 | N68: =IFERROR(INDEX(dFrente!$B$2:$B$76,MATCH(C68,dFrente!$A$2:$A$76,0)),"Sin frente") -> Ciclo de vida JML | O68: =IFERROR(INDEX(dNIST!$B$2:$B$13,MATCH(M68,dNIST!$A$2:$A$13,0)),"") -> PR | P68: =TRIM(IFERROR(LEFT(G68,FIND(CHAR(10),G68)-1),G68)) -> Richard Requelme | Q68: =LEN(TRIM(G68))-LEN(SUBSTITUTE(TRIM(G68),CHAR(10),""))+1 -> 2 | R68: =IF(E68<>"","Sí","No") -> No | S68: =IF(OR(J68="",H68=""),"",IF(J68<=H68,IF(FechaCorte>=J68,1,0),MAX(0,MIN(1,(FechaCorte-H68)/(J68-H68))))) -> 1 | T68: =IF(S68="","",K68-S68) -> 0 | U68: =IF(R68="Sí","Recurrente",IF(K68>=1,"Completado",IF(AND(J68<>"",J68<FechaCorte),"Vencido",IF(AND(K68=0,OR(H68="",H68>FechaCorte)),"Por iniciar",IF(AND(T68<>"",T68<=UmbralRiesgo),"En riesgo","En plazo"))))) -> Completado | V68: =IF(OR(U68="Vencido",U68="En riesgo",U68="En plazo",U68="Por iniciar"),1,0) -> 0 | W68: =IF(U68="Vencido",FechaCorte-J68,"") | X68: =IF(AND(V68=1,U68<>"Vencido"),J68-FechaCorte,"") | Y68: =IF(J68="","",DATE(YEAR(J68),MONTH(J68),1)) -> 46235 | Z68: =IF(AND(U68="Completado",I68<>""),IF(I68<=FechaCorte,DATE(YEAR(I68),MONTH(I68),1),""),"") -> 46235 | AA68: =IF(J68="","",IF(DAY(J68+1)=1,1,0)) -> 0 | AB68: =IF(AND(U68="Completado",I68<>"",I68=J68),1,0) -> 1 | AC68: =IF(AND(K68>=1,I68<>""),IF(I68>FechaCorte,1,0),0) -> 0 | AD68: =IF(AND(I68<>"",H68<>""),IF(I68<H68,1,0),0) -> 0 | AE68: =IF(OR(F68="Riesgos",F68="Obs. Auditoría"),1,0) -> 0 | AF68: =IFERROR(MID(D68,FIND("PMC-",D68),8),"") | AG68: =IF(AND(V68=1,J68<>""),IF(AND(J68>=FechaCorte,J68<=HorizonteExpuestos),1,0),0) -> 0
A69: 68 | B69: 2026 | C69: Onboarding | D69: Revision novedades en onboarding (Cargos nuevos) | E69: Mensual | F69: Mejora | G69: Bryan Uyana Daniel Lescano Ana María Vergara | H69: 46113 | K69: 1 | L69: Esta actividad es permanente. | M69: PR.AA-01 | N69: =IFERROR(INDEX(dFrente!$B$2:$B$76,MATCH(C69,dFrente!$A$2:$A$76,0)),"Sin frente") -> Ciclo de vida JML | O69: =IFERROR(INDEX(dNIST!$B$2:$B$13,MATCH(M69,dNIST!$A$2:$A$13,0)),"") -> PR | P69: =TRIM(IFERROR(LEFT(G69,FIND(CHAR(10),G69)-1),G69)) -> Bryan Uyana | Q69: =LEN(TRIM(G69))-LEN(SUBSTITUTE(TRIM(G69),CHAR(10),""))+1 -> 3 | R69: =IF(E69<>"","Sí","No") -> Sí | S69: =IF(OR(J69="",H69=""),"",IF(J69<=H69,IF(FechaCorte>=J69,1,0),MAX(0,MIN(1,(FechaCorte-H69)/(J69-H69))))) | T69: =IF(S69="","",K69-S69) | U69: =IF(R69="Sí","Recurrente",IF(K69>=1,"Completado",IF(AND(J69<>"",J69<FechaCorte),"Vencido",IF(AND(K69=0,OR(H69="",H69>FechaCorte)),"Por iniciar",IF(AND(T69<>"",T69<=UmbralRiesgo),"En riesgo","En plazo"))))) -> Recurrente | V69: =IF(OR(U69="Vencido",U69="En riesgo",U69="En plazo",U69="Por iniciar"),1,0) -> 0 | W69: =IF(U69="Vencido",FechaCorte-J69,"") | X69: =IF(AND(V69=1,U69<>"Vencido"),J69-FechaCorte,"") | Y69: =IF(J69="","",DATE(YEAR(J69),MONTH(J69),1)) | Z69: =IF(AND(U69="Completado",I69<>""),IF(I69<=FechaCorte,DATE(YEAR(I69),MONTH(I69),1),""),"") | AA69: =IF(J69="","",IF(DAY(J69+1)=1,1,0)) | AB69: =IF(AND(U69="Completado",I69<>"",I69=J69),1,0) -> 0 | AC69: =IF(AND(K69>=1,I69<>""),IF(I69>FechaCorte,1,0),0) -> 0 | AD69: =IF(AND(I69<>"",H69<>""),IF(I69<H69,1,0),0) -> 0 | AE69: =IF(OR(F69="Riesgos",F69="Obs. Auditoría"),1,0) -> 0 | AF69: =IFERROR(MID(D69,FIND("PMC-",D69),8),"") | AG69: =IF(AND(V69=1,J69<>""),IF(AND(J69>=FechaCorte,J69<=HorizonteExpuestos),1,0),0) -> 0
A70: 69 | B70: 2026 | C70: Crossboarding | D70: Creación de Workflows para retiro de accesos referente a (BDD, SFTP, DLP, VPN); Cambios Workflow de Crossboarding (#3036) | F70: Iniciativa | G70: Richard Requelme Ana María Vergara | H70: 46154 | I70: 46169 | J70: 46169 | K70: 1 | L70: Se retira los permisos por fuera de nube (GSC_XXX), grupos de Firewall, y permisos de Fusion cuando se detecta cambios de área + cargo. | M70: PR.AA-05 | N70: =IFERROR(INDEX(dFrente!$B$2:$B$76,MATCH(C70,dFrente!$A$2:$A$76,0)),"Sin frente") -> Ciclo de vida JML | O70: =IFERROR(INDEX(dNIST!$B$2:$B$13,MATCH(M70,dNIST!$A$2:$A$13,0)),"") -> PR | P70: =TRIM(IFERROR(LEFT(G70,FIND(CHAR(10),G70)-1),G70)) -> Richard Requelme | Q70: =LEN(TRIM(G70))-LEN(SUBSTITUTE(TRIM(G70),CHAR(10),""))+1 -> 2 | R70: =IF(E70<>"","Sí","No") -> No | S70: =IF(OR(J70="",H70=""),"",IF(J70<=H70,IF(FechaCorte>=J70,1,0),MAX(0,MIN(1,(FechaCorte-H70)/(J70-H70))))) -> 1 | T70: =IF(S70="","",K70-S70) -> 0 | U70: =IF(R70="Sí","Recurrente",IF(K70>=1,"Completado",IF(AND(J70<>"",J70<FechaCorte),"Vencido",IF(AND(K70=0,OR(H70="",H70>FechaCorte)),"Por iniciar",IF(AND(T70<>"",T70<=UmbralRiesgo),"En riesgo","En plazo"))))) -> Completado | V70: =IF(OR(U70="Vencido",U70="En riesgo",U70="En plazo",U70="Por iniciar"),1,0) -> 0 | W70: =IF(U70="Vencido",FechaCorte-J70,"") | X70: =IF(AND(V70=1,U70<>"Vencido"),J70-FechaCorte,"") | Y70: =IF(J70="","",DATE(YEAR(J70),MONTH(J70),1)) -> 46143 | Z70: =IF(AND(U70="Completado",I70<>""),IF(I70<=FechaCorte,DATE(YEAR(I70),MONTH(I70),1),""),"") -> 46143 | AA70: =IF(J70="","",IF(DAY(J70+1)=1,1,0)) -> 0 | AB70: =IF(AND(U70="Completado",I70<>"",I70=J70),1,0) -> 1 | AC70: =IF(AND(K70>=1,I70<>""),IF(I70>FechaCorte,1,0),0) -> 0 | AD70: =IF(AND(I70<>"",H70<>""),IF(I70<H70,1,0),0) -> 0 | AE70: =IF(OR(F70="Riesgos",F70="Obs. Auditoría"),1,0) -> 0 | AF70: =IFERROR(MID(D70,FIND("PMC-",D70),8),"") | AG70: =IF(AND(V70=1,J70<>""),IF(AND(J70>=FechaCorte,J70<=HorizonteExpuestos),1,0),0) -> 0
A71: 70 | B71: 2026 | C71: Crossboarding | D71: Flujos de Cambios de Cargo Libre (#3022) | F71: Proyecto | G71: Richard Requelme Ana María Vergara | H71: 46190 | I71: 46198 | J71: 46198 | K71: 1 | L71: - Solicitud Soporte Assertiva #3052 - Se genero un nuevo formulario en la sección LauchPad de ISC para procesar los cambios de rol para usuarios nominados que compartan la misma estructura organizacional - Flujo abierto unicamente para Gestión de Identidades banco - Comunicación al equipo interno y externo del proceso Asseritva crea un flujo libre para que el equipo de GI realice cambios fuera de la matriz establecida si corresponde. Esto a raíz de lo identificado en perfilamiento (Anita V). Adicional, se encuentra en depuración los roles solicitables que era el mecanismo usado para tratar estos cambios. | M71: PR.AA-01 | N71: =IFERROR(INDEX(dFrente!$B$2:$B$76,MATCH(C71,dFrente!$A$2:$A$76,0)),"Sin frente") -> Ciclo de vida JML | O71: =IFERROR(INDEX(dNIST!$B$2:$B$13,MATCH(M71,dNIST!$A$2:$A$13,0)),"") -> PR | P71: =TRIM(IFERROR(LEFT(G71,FIND(CHAR(10),G71)-1),G71)) -> Richard Requelme | Q71: =LEN(TRIM(G71))-LEN(SUBSTITUTE(TRIM(G71),CHAR(10),""))+1 -> 2 | R71: =IF(E71<>"","Sí","No") -> No | S71: =IF(OR(J71="",H71=""),"",IF(J71<=H71,IF(FechaCorte>=J71,1,0),MAX(0,MIN(1,(FechaCorte-H71)/(J71-H71))))) -> 1 | T71: =IF(S71="","",K71-S71) -> 0 | U71: =IF(R71="Sí","Recurrente",IF(K71>=1,"Completado",IF(AND(J71<>"",J71<FechaCorte),"Vencido",IF(AND(K71=0,OR(H71="",H71>FechaCorte)),"Por iniciar",IF(AND(T71<>"",T71<=UmbralRiesgo),"En riesgo","En plazo"))))) -> Completado | V71: =IF(OR(U71="Vencido",U71="En riesgo",U71="En plazo",U71="Por iniciar"),1,0) -> 0 | W71: =IF(U71="Vencido",FechaCorte-J71,"") | X71: =IF(AND(V71=1,U71<>"Vencido"),J71-FechaCorte,"") | Y71: =IF(J71="","",DATE(YEAR(J71),MONTH(J71),1)) -> 46174 | Z71: =IF(AND(U71="Completado",I71<>""),IF(I71<=FechaCorte,DATE(YEAR(I71),MONTH(I71),1),""),"") -> 46174 | AA71: =IF(J71="","",IF(DAY(J71+1)=1,1,0)) -> 0 | AB71: =IF(AND(U71="Completado",I71<>"",I71=J71),1,0) -> 1 | AC71: =IF(AND(K71>=1,I71<>""),IF(I71>FechaCorte,1,0),0) -> 0 | AD71: =IF(AND(I71<>"",H71<>""),IF(I71<H71,1,0),0) -> 0 | AE71: =IF(OR(F71="Riesgos",F71="Obs. Auditoría"),1,0) -> 0 | AF71: =IFERROR(MID(D71,FIND("PMC-",D71),8),"") | AG71: =IF(AND(V71=1,J71<>""),IF(AND(J71>=FechaCorte,J71<=HorizonteExpuestos),1,0),0) -> 0
A72: 71 | B72: 2026 | C72: Crossboarding | D72: Workflow de Crossboarding - 2,0 Retiro de permisos cuando detecta cambio de área + cargo | F72: Iniciativa | G72: Richard Requelme | H72: 46184 | I72: 46191 | J72: 46191 | K72: 1 | L72: implementado con ticket (#3036) 1. Cuando existan cambios de estructura sea en el atributo de área y cargo, se retiren automáticamente los accesos dados por fuera del rol de Entra ID con la nomenclatura GSC_XXX, los permisos del origen Oracle Fusion y los grupos de AD de firewall: GF_FW_XXX 2. Notificación de retiro: Agregar una notificación hacia el correo de crossboarding de los permisos fuera del rol que se retiren. En este caso, si se puede acotar únicamente para permisos de VPN sería ideal. | M72: PR.AA-05 | N72: =IFERROR(INDEX(dFrente!$B$2:$B$76,MATCH(C72,dFrente!$A$2:$A$76,0)),"Sin frente") -> Ciclo de vida JML | O72: =IFERROR(INDEX(dNIST!$B$2:$B$13,MATCH(M72,dNIST!$A$2:$A$13,0)),"") -> PR | P72: =TRIM(IFERROR(LEFT(G72,FIND(CHAR(10),G72)-1),G72)) -> Richard Requelme | Q72: =LEN(TRIM(G72))-LEN(SUBSTITUTE(TRIM(G72),CHAR(10),""))+1 -> 1 | R72: =IF(E72<>"","Sí","No") -> No | S72: =IF(OR(J72="",H72=""),"",IF(J72<=H72,IF(FechaCorte>=J72,1,0),MAX(0,MIN(1,(FechaCorte-H72)/(J72-H72))))) -> 1 | T72: =IF(S72="","",K72-S72) -> 0 | U72: =IF(R72="Sí","Recurrente",IF(K72>=1,"Completado",IF(AND(J72<>"",J72<FechaCorte),"Vencido",IF(AND(K72=0,OR(H72="",H72>FechaCorte)),"Por iniciar",IF(AND(T72<>"",T72<=UmbralRiesgo),"En riesgo","En plazo"))))) -> Completado | V72: =IF(OR(U72="Vencido",U72="En riesgo",U72="En plazo",U72="Por iniciar"),1,0) -> 0 | W72: =IF(U72="Vencido",FechaCorte-J72,"") | X72: =IF(AND(V72=1,U72<>"Vencido"),J72-FechaCorte,"") | Y72: =IF(J72="","",DATE(YEAR(J72),MONTH(J72),1)) -> 46174 | Z72: =IF(AND(U72="Completado",I72<>""),IF(I72<=FechaCorte,DATE(YEAR(I72),MONTH(I72),1),""),"") -> 46174 | AA72: =IF(J72="","",IF(DAY(J72+1)=1,1,0)) -> 0 | AB72: =IF(AND(U72="Completado",I72<>"",I72=J72),1,0) -> 1 | AC72: =IF(AND(K72>=1,I72<>""),IF(I72>FechaCorte,1,0),0) -> 0 | AD72: =IF(AND(I72<>"",H72<>""),IF(I72<H72,1,0),0) -> 0 | AE72: =IF(OR(F72="Riesgos",F72="Obs. Auditoría"),1,0) -> 0 | AF72: =IFERROR(MID(D72,FIND("PMC-",D72),8),"") | AG72: =IF(AND(V72=1,J72<>""),IF(AND(J72>=FechaCorte,J72<=HorizonteExpuestos),1,0),0) -> 0
A73: 72 | B73: 2026 | C73: Crossboarding | D73: Workflow de Crossboarding - 3.0 Retiro de permisos cuando detecta cambio únicamente de cargo | F73: Iniciativa | G73: Richard Requelme | H73: 46237 | J73: 46272 | K73: 0.3 | L73: -15 - sept - Se envió a minería de roles Entra ID, se están haciendo ajustes en los roles. Y ya se envió el ticket para crear el flujo. Analizar los resultados del workflow 2,0 y ajustar más permisos, y más restrictivo | M73: PR.AA-05 | N73: =IFERROR(INDEX(dFrente!$B$2:$B$76,MATCH(C73,dFrente!$A$2:$A$76,0)),"Sin frente") -> Ciclo de vida JML | O73: =IFERROR(INDEX(dNIST!$B$2:$B$13,MATCH(M73,dNIST!$A$2:$A$13,0)),"") -> PR | P73: =TRIM(IFERROR(LEFT(G73,FIND(CHAR(10),G73)-1),G73)) -> Richard Requelme | Q73: =LEN(TRIM(G73))-LEN(SUBSTITUTE(TRIM(G73),CHAR(10),""))+1 -> 1 | R73: =IF(E73<>"","Sí","No") -> No | S73: =IF(OR(J73="",H73=""),"",IF(J73<=H73,IF(FechaCorte>=J73,1,0),MAX(0,MIN(1,(FechaCorte-H73)/(J73-H73))))) -> 1 | T73: =IF(S73="","",K73-S73) -> -0.7 | U73: =IF(R73="Sí","Recurrente",IF(K73>=1,"Completado",IF(AND(J73<>"",J73<FechaCorte),"Vencido",IF(AND(K73=0,OR(H73="",H73>FechaCorte)),"Por iniciar",IF(AND(T73<>"",T73<=UmbralRiesgo),"En riesgo","En plazo"))))) -> Vencido | V73: =IF(OR(U73="Vencido",U73="En riesgo",U73="En plazo",U73="Por iniciar"),1,0) -> 1 | W73: =IF(U73="Vencido",FechaCorte-J73,"") -> 17 | X73: =IF(AND(V73=1,U73<>"Vencido"),J73-FechaCorte,"") | Y73: =IF(J73="","",DATE(YEAR(J73),MONTH(J73),1)) -> 46266 | Z73: =IF(AND(U73="Completado",I73<>""),IF(I73<=FechaCorte,DATE(YEAR(I73),MONTH(I73),1),""),"") | AA73: =IF(J73="","",IF(DAY(J73+1)=1,1,0)) -> 0 | AB73: =IF(AND(U73="Completado",I73<>"",I73=J73),1,0) -> 0 | AC73: =IF(AND(K73>=1,I73<>""),IF(I73>FechaCorte,1,0),0) -> 0 | AD73: =IF(AND(I73<>"",H73<>""),IF(I73<H73,1,0),0) -> 0 | AE73: =IF(OR(F73="Riesgos",F73="Obs. Auditoría"),1,0) -> 0 | AF73: =IFERROR(MID(D73,FIND("PMC-",D73),8),"") | AG73: =IF(AND(V73=1,J73<>""),IF(AND(J73>=FechaCorte,J73<=HorizonteExpuestos),1,0),0) -> 0
A74: 73 | B74: 2026 | C74: Offboarding | D74: Flujo de Deshabilitación de Cuentas - Usuarios Cesantes (#3157) - Conector Siglo21 - Proceso de Offboarding | F74: Iniciativa | G74: Richard Requelme | H74: 46223 | I74: 46265 | J74: 46265 | K74: 1 | L74: Implementar un workflow para deshabilitar las cuentas de SIGLO similar al flujo "Reprocesamiento Baja Bancs". Esto debido a que siguen existiendo casos identificados donde los usuarios de baja siguen activos en las aplicaciones. | M74: PR.AA-01 | N74: =IFERROR(INDEX(dFrente!$B$2:$B$76,MATCH(C74,dFrente!$A$2:$A$76,0)),"Sin frente") -> Ciclo de vida JML | O74: =IFERROR(INDEX(dNIST!$B$2:$B$13,MATCH(M74,dNIST!$A$2:$A$13,0)),"") -> PR | P74: =TRIM(IFERROR(LEFT(G74,FIND(CHAR(10),G74)-1),G74)) -> Richard Requelme | Q74: =LEN(TRIM(G74))-LEN(SUBSTITUTE(TRIM(G74),CHAR(10),""))+1 -> 1 | R74: =IF(E74<>"","Sí","No") -> No | S74: =IF(OR(J74="",H74=""),"",IF(J74<=H74,IF(FechaCorte>=J74,1,0),MAX(0,MIN(1,(FechaCorte-H74)/(J74-H74))))) -> 1 | T74: =IF(S74="","",K74-S74) -> 0 | U74: =IF(R74="Sí","Recurrente",IF(K74>=1,"Completado",IF(AND(J74<>"",J74<FechaCorte),"Vencido",IF(AND(K74=0,OR(H74="",H74>FechaCorte)),"Por iniciar",IF(AND(T74<>"",T74<=UmbralRiesgo),"En riesgo","En plazo"))))) -> Completado | V74: =IF(OR(U74="Vencido",U74="En riesgo",U74="En plazo",U74="Por iniciar"),1,0) -> 0 | W74: =IF(U74="Vencido",FechaCorte-J74,"") | X74: =IF(AND(V74=1,U74<>"Vencido"),J74-FechaCorte,"") | Y74: =IF(J74="","",DATE(YEAR(J74),MONTH(J74),1)) -> 46235 | Z74: =IF(AND(U74="Completado",I74<>""),IF(I74<=FechaCorte,DATE(YEAR(I74),MONTH(I74),1),""),"") -> 46235 | AA74: =IF(J74="","",IF(DAY(J74+1)=1,1,0)) -> 1 | AB74: =IF(AND(U74="Completado",I74<>"",I74=J74),1,0) -> 1 | AC74: =IF(AND(K74>=1,I74<>""),IF(I74>FechaCorte,1,0),0) -> 0 | AD74: =IF(AND(I74<>"",H74<>""),IF(I74<H74,1,0),0) -> 0 | AE74: =IF(OR(F74="Riesgos",F74="Obs. Auditoría"),1,0) -> 0 | AF74: =IFERROR(MID(D74,FIND("PMC-",D74),8),"") | AG74: =IF(AND(V74=1,J74<>""),IF(AND(J74>=FechaCorte,J74<=HorizonteExpuestos),1,0),0) -> 0
A75: 74 | B75: 2026 | C75: Reportería | D75: Integración GEMA - Reportes de Negocio y Gobierno CS - Disponibilizar información | F75: Iniciativa | G75: Richard Requelme Bryan Uyana | H75: 46174 | I75: 46203 | J75: 46203 | K75: 1 | L75: Se capacito al equipo y se finalizo la actividad de disponibilizar por GEMA lo requerido | M75: GV.OV | N75: =IFERROR(INDEX(dFrente!$B$2:$B$76,MATCH(C75,dFrente!$A$2:$A$76,0)),"Sin frente") -> Gobierno y reportería | O75: =IFERROR(INDEX(dNIST!$B$2:$B$13,MATCH(M75,dNIST!$A$2:$A$13,0)),"") -> GV | P75: =TRIM(IFERROR(LEFT(G75,FIND(CHAR(10),G75)-1),G75)) -> Richard Requelme | Q75: =LEN(TRIM(G75))-LEN(SUBSTITUTE(TRIM(G75),CHAR(10),""))+1 -> 2 | R75: =IF(E75<>"","Sí","No") -> No | S75: =IF(OR(J75="",H75=""),"",IF(J75<=H75,IF(FechaCorte>=J75,1,0),MAX(0,MIN(1,(FechaCorte-H75)/(J75-H75))))) -> 1 | T75: =IF(S75="","",K75-S75) -> 0 | U75: =IF(R75="Sí","Recurrente",IF(K75>=1,"Completado",IF(AND(J75<>"",J75<FechaCorte),"Vencido",IF(AND(K75=0,OR(H75="",H75>FechaCorte)),"Por iniciar",IF(AND(T75<>"",T75<=UmbralRiesgo),"En riesgo","En plazo"))))) -> Completado | V75: =IF(OR(U75="Vencido",U75="En riesgo",U75="En plazo",U75="Por iniciar"),1,0) -> 0 | W75: =IF(U75="Vencido",FechaCorte-J75,"") | X75: =IF(AND(V75=1,U75<>"Vencido"),J75-FechaCorte,"") | Y75: =IF(J75="","",DATE(YEAR(J75),MONTH(J75),1)) -> 46174 | Z75: =IF(AND(U75="Completado",I75<>""),IF(I75<=FechaCorte,DATE(YEAR(I75),MONTH(I75),1),""),"") -> 46174 | AA75: =IF(J75="","",IF(DAY(J75+1)=1,1,0)) -> 1 | AB75: =IF(AND(U75="Completado",I75<>"",I75=J75),1,0) -> 1 | AC75: =IF(AND(K75>=1,I75<>""),IF(I75>FechaCorte,1,0),0) -> 0 | AD75: =IF(AND(I75<>"",H75<>""),IF(I75<H75,1,0),0) -> 0 | AE75: =IF(OR(F75="Riesgos",F75="Obs. Auditoría"),1,0) -> 0 | AF75: =IFERROR(MID(D75,FIND("PMC-",D75),8),"") | AG75: =IF(AND(V75=1,J75<>""),IF(AND(J75>=FechaCorte,J75<=HorizonteExpuestos),1,0),0) -> 0
A76: 75 | B76: 2026 | C76: Reportería | D76: Vista para control de accesos asignados fuera del rol - revocaciones de permisos por Sailpoint en GEMA | F76: Iniciativa | G76: Richard Requelme | H76: 46217 | I76: 46225 | J76: 46225 | K76: 1 | L76: Se agrega una vista para conocer los tickets con los que se asigna un permiso o se revoca por flujos automáticos de crossboarding. | M76: GV.OV | N76: =IFERROR(INDEX(dFrente!$B$2:$B$76,MATCH(C76,dFrente!$A$2:$A$76,0)),"Sin frente") -> Gobierno y reportería | O76: =IFERROR(INDEX(dNIST!$B$2:$B$13,MATCH(M76,dNIST!$A$2:$A$13,0)),"") -> GV | P76: =TRIM(IFERROR(LEFT(G76,FIND(CHAR(10),G76)-1),G76)) -> Richard Requelme | Q76: =LEN(TRIM(G76))-LEN(SUBSTITUTE(TRIM(G76),CHAR(10),""))+1 -> 1 | R76: =IF(E76<>"","Sí","No") -> No | S76: =IF(OR(J76="",H76=""),"",IF(J76<=H76,IF(FechaCorte>=J76,1,0),MAX(0,MIN(1,(FechaCorte-H76)/(J76-H76))))) -> 1 | T76: =IF(S76="","",K76-S76) -> 0 | U76: =IF(R76="Sí","Recurrente",IF(K76>=1,"Completado",IF(AND(J76<>"",J76<FechaCorte),"Vencido",IF(AND(K76=0,OR(H76="",H76>FechaCorte)),"Por iniciar",IF(AND(T76<>"",T76<=UmbralRiesgo),"En riesgo","En plazo"))))) -> Completado | V76: =IF(OR(U76="Vencido",U76="En riesgo",U76="En plazo",U76="Por iniciar"),1,0) -> 0 | W76: =IF(U76="Vencido",FechaCorte-J76,"") | X76: =IF(AND(V76=1,U76<>"Vencido"),J76-FechaCorte,"") | Y76: =IF(J76="","",DATE(YEAR(J76),MONTH(J76),1)) -> 46204 | Z76: =IF(AND(U76="Completado",I76<>""),IF(I76<=FechaCorte,DATE(YEAR(I76),MONTH(I76),1),""),"") -> 46204 | AA76: =IF(J76="","",IF(DAY(J76+1)=1,1,0)) -> 0 | AB76: =IF(AND(U76="Completado",I76<>"",I76=J76),1,0) -> 1 | AC76: =IF(AND(K76>=1,I76<>""),IF(I76>FechaCorte,1,0),0) -> 0 | AD76: =IF(AND(I76<>"",H76<>""),IF(I76<H76,1,0),0) -> 0 | AE76: =IF(OR(F76="Riesgos",F76="Obs. Auditoría"),1,0) -> 0 | AF76: =IFERROR(MID(D76,FIND("PMC-",D76),8),"") | AG76: =IF(AND(V76=1,J76<>""),IF(AND(J76>=FechaCorte,J76<=HorizonteExpuestos),1,0),0) -> 0
A77: 76 | B77: 2026 | C77: Reportería | D77: Proceso de Reportería para Eventos de Auditoría - Scripts y nuevo formato de reportes | F77: Iniciativa | G77: Richard Requelme | H77: 46210 | I77: 46217 | J77: 46217 | K77: 1 | L77: Se remiten los scripts iniciales para reportería de eventos y tickets generados. | M77: GV.OV | N77: =IFERROR(INDEX(dFrente!$B$2:$B$76,MATCH(C77,dFrente!$A$2:$A$76,0)),"Sin frente") -> Gobierno y reportería | O77: =IFERROR(INDEX(dNIST!$B$2:$B$13,MATCH(M77,dNIST!$A$2:$A$13,0)),"") -> GV | P77: =TRIM(IFERROR(LEFT(G77,FIND(CHAR(10),G77)-1),G77)) -> Richard Requelme | Q77: =LEN(TRIM(G77))-LEN(SUBSTITUTE(TRIM(G77),CHAR(10),""))+1 -> 1 | R77: =IF(E77<>"","Sí","No") -> No | S77: =IF(OR(J77="",H77=""),"",IF(J77<=H77,IF(FechaCorte>=J77,1,0),MAX(0,MIN(1,(FechaCorte-H77)/(J77-H77))))) -> 1 | T77: =IF(S77="","",K77-S77) -> 0 | U77: =IF(R77="Sí","Recurrente",IF(K77>=1,"Completado",IF(AND(J77<>"",J77<FechaCorte),"Vencido",IF(AND(K77=0,OR(H77="",H77>FechaCorte)),"Por iniciar",IF(AND(T77<>"",T77<=UmbralRiesgo),"En riesgo","En plazo"))))) -> Completado | V77: =IF(OR(U77="Vencido",U77="En riesgo",U77="En plazo",U77="Por iniciar"),1,0) -> 0 | W77: =IF(U77="Vencido",FechaCorte-J77,"") | X77: =IF(AND(V77=1,U77<>"Vencido"),J77-FechaCorte,"") | Y77: =IF(J77="","",DATE(YEAR(J77),MONTH(J77),1)) -> 46204 | Z77: =IF(AND(U77="Completado",I77<>""),IF(I77<=FechaCorte,DATE(YEAR(I77),MONTH(I77),1),""),"") -> 46204 | AA77: =IF(J77="","",IF(DAY(J77+1)=1,1,0)) -> 0 | AB77: =IF(AND(U77="Completado",I77<>"",I77=J77),1,0) -> 1 | AC77: =IF(AND(K77>=1,I77<>""),IF(I77>FechaCorte,1,0),0) -> 0 | AD77: =IF(AND(I77<>"",H77<>""),IF(I77<H77,1,0),0) -> 0 | AE77: =IF(OR(F77="Riesgos",F77="Obs. Auditoría"),1,0) -> 0 | AF77: =IFERROR(MID(D77,FIND("PMC-",D77),8),"") | AG77: =IF(AND(V77=1,J77<>""),IF(AND(J77>=FechaCorte,J77<=HorizonteExpuestos),1,0),0) -> 0
A78: 77 | B78: 2026 | C78: Centros de Costos Temporales (No red de agencia). | D78: Colaboradores con centros de costos diferentes en las aplicaciones vs. fuente autoritativa (1187 usuarios). | F78: Incidencia | G78: Daniel Lescano Ana María Fierro | H78: 46192 | I78: 46199 | J78: 46199 | K78: 1 | L78: El equipo de Nómina nos ha enviado el detalle de los usuarios que se debe cambiar el centro de costo y quienes lo deben mantener. 52 colaboradores han sido excepcionados, asignándoles una fecha fin temporal al 31/12/2050, con el objetivo de evitar afectaciones en futuros procesos de depuración. 113 usuarios pendientes (en revisión del área Talento Humano). Se finalizó con las correcciones, autorizados 98 colaboradores. | M78: PR.AA-01 | N78: =IFERROR(INDEX(dFrente!$B$2:$B$76,MATCH(C78,dFrente!$A$2:$A$76,0)),"Sin frente") -> Ciclo de vida JML | O78: =IFERROR(INDEX(dNIST!$B$2:$B$13,MATCH(M78,dNIST!$A$2:$A$13,0)),"") -> PR | P78: =TRIM(IFERROR(LEFT(G78,FIND(CHAR(10),G78)-1),G78)) -> Daniel Lescano | Q78: =LEN(TRIM(G78))-LEN(SUBSTITUTE(TRIM(G78),CHAR(10),""))+1 -> 2 | R78: =IF(E78<>"","Sí","No") -> No | S78: =IF(OR(J78="",H78=""),"",IF(J78<=H78,IF(FechaCorte>=J78,1,0),MAX(0,MIN(1,(FechaCorte-H78)/(J78-H78))))) -> 1 | T78: =IF(S78="","",K78-S78) -> 0 | U78: =IF(R78="Sí","Recurrente",IF(K78>=1,"Completado",IF(AND(J78<>"",J78<FechaCorte),"Vencido",IF(AND(K78=0,OR(H78="",H78>FechaCorte)),"Por iniciar",IF(AND(T78<>"",T78<=UmbralRiesgo),"En riesgo","En plazo"))))) -> Completado | V78: =IF(OR(U78="Vencido",U78="En riesgo",U78="En plazo",U78="Por iniciar"),1,0) -> 0 | W78: =IF(U78="Vencido",FechaCorte-J78,"") | X78: =IF(AND(V78=1,U78<>"Vencido"),J78-FechaCorte,"") | Y78: =IF(J78="","",DATE(YEAR(J78),MONTH(J78),1)) -> 46174 | Z78: =IF(AND(U78="Completado",I78<>""),IF(I78<=FechaCorte,DATE(YEAR(I78),MONTH(I78),1),""),"") -> 46174 | AA78: =IF(J78="","",IF(DAY(J78+1)=1,1,0)) -> 0 | AB78: =IF(AND(U78="Completado",I78<>"",I78=J78),1,0) -> 1 | AC78: =IF(AND(K78>=1,I78<>""),IF(I78>FechaCorte,1,0),0) -> 0 | AD78: =IF(AND(I78<>"",H78<>""),IF(I78<H78,1,0),0) -> 0 | AE78: =IF(OR(F78="Riesgos",F78="Obs. Auditoría"),1,0) -> 0 | AF78: =IFERROR(MID(D78,FIND("PMC-",D78),8),"") | AG78: =IF(AND(V78=1,J78<>""),IF(AND(J78>=FechaCorte,J78<=HorizonteExpuestos),1,0),0) -> 0
A79: 78 | B79: 2026 | C79: Centros de Costos y Cambios Temporales (red de agencia). | D79: Agregar Aprobación en Flujos de Centro de costos y Cambios temporales (#3131) Establecer todos los controles: - Ticket SN - Aprobaciones - Consideración matriz de coreografía - Tiempos de ausencia (temporalidad). | F79: Iniciativa | G79: Richard Requelme Ana María Fierro | H79: 46218 | J79: 46326 | K79: 0.4 | L79: -15-sept - Se poblo el campo de Manager en AD para poblar en Service now y llevar el flujo de agencias a este nuevo formato. *22-jul, se tiene una reunión con Agencias para validar, se requiere foro extendido con Soledad Pazmino, Pilar Vallejo y Tatiana Hoyos -Validar opciones de como colocar aprobaciones adicionales para la liberación del flujo de centro de costos y cambios temporales. La idea es que las agencias hagan uso del flujo y cada cambio tenga su autorización requerido. De igual forma, se notifiquen estos cambios a Gestión de Identidades e involucrados para conocimiento de ejecución. | M79: PR.AA-05 | N79: =IFERROR(INDEX(dFrente!$B$2:$B$76,MATCH(C79,dFrente!$A$2:$A$76,0)),"Sin frente") -> Ciclo de vida JML | O79: =IFERROR(INDEX(dNIST!$B$2:$B$13,MATCH(M79,dNIST!$A$2:$A$13,0)),"") -> PR | P79: =TRIM(IFERROR(LEFT(G79,FIND(CHAR(10),G79)-1),G79)) -> Richard Requelme | Q79: =LEN(TRIM(G79))-LEN(SUBSTITUTE(TRIM(G79),CHAR(10),""))+1 -> 2 | R79: =IF(E79<>"","Sí","No") -> No | S79: =IF(OR(J79="",H79=""),"",IF(J79<=H79,IF(FechaCorte>=J79,1,0),MAX(0,MIN(1,(FechaCorte-H79)/(J79-H79))))) -> 0.65740741 | T79: =IF(S79="","",K79-S79) -> -0.25740741 | U79: =IF(R79="Sí","Recurrente",IF(K79>=1,"Completado",IF(AND(J79<>"",J79<FechaCorte),"Vencido",IF(AND(K79=0,OR(H79="",H79>FechaCorte)),"Por iniciar",IF(AND(T79<>"",T79<=UmbralRiesgo),"En riesgo","En plazo"))))) -> En riesgo | V79: =IF(OR(U79="Vencido",U79="En riesgo",U79="En plazo",U79="Por iniciar"),1,0) -> 1 | W79: =IF(U79="Vencido",FechaCorte-J79,"") | X79: =IF(AND(V79=1,U79<>"Vencido"),J79-FechaCorte,"") -> 37 | Y79: =IF(J79="","",DATE(YEAR(J79),MONTH(J79),1)) -> 46296 | Z79: =IF(AND(U79="Completado",I79<>""),IF(I79<=FechaCorte,DATE(YEAR(I79),MONTH(I79),1),""),"") | AA79: =IF(J79="","",IF(DAY(J79+1)=1,1,0)) -> 1 | AB79: =IF(AND(U79="Completado",I79<>"",I79=J79),1,0) -> 0 | AC79: =IF(AND(K79>=1,I79<>""),IF(I79>FechaCorte,1,0),0) -> 0 | AD79: =IF(AND(I79<>"",H79<>""),IF(I79<H79,1,0),0) -> 0 | AE79: =IF(OR(F79="Riesgos",F79="Obs. Auditoría"),1,0) -> 0 | AF79: =IFERROR(MID(D79,FIND("PMC-",D79),8),"") | AG79: =IF(AND(V79=1,J79<>""),IF(AND(J79>=FechaCorte,J79<=HorizonteExpuestos),1,0),0) -> 0
A80: 79 | B80: 2026 | C80: Centros de Costos | D80: Revisión del error de tickets que el estado no puede ser modificado no cancelado debido a que no se encuentra la información de centro de costos | F80: Operación | G80: Daniel Lescano | H80: 46225 | I80: 46233 | J80: 46233 | K80: 1 | L80: Se levantó el ticket 3263 a Assertiva para solventar el inconveniente sobre el campo Centro de Costos null al momento de la creación de tickets | M80: PR.AA-01 | N80: =IFERROR(INDEX(dFrente!$B$2:$B$76,MATCH(C80,dFrente!$A$2:$A$76,0)),"Sin frente") -> Ciclo de vida JML | O80: =IFERROR(INDEX(dNIST!$B$2:$B$13,MATCH(M80,dNIST!$A$2:$A$13,0)),"") -> PR | P80: =TRIM(IFERROR(LEFT(G80,FIND(CHAR(10),G80)-1),G80)) -> Daniel Lescano | Q80: =LEN(TRIM(G80))-LEN(SUBSTITUTE(TRIM(G80),CHAR(10),""))+1 -> 1 | R80: =IF(E80<>"","Sí","No") -> No | S80: =IF(OR(J80="",H80=""),"",IF(J80<=H80,IF(FechaCorte>=J80,1,0),MAX(0,MIN(1,(FechaCorte-H80)/(J80-H80))))) -> 1 | T80: =IF(S80="","",K80-S80) -> 0 | U80: =IF(R80="Sí","Recurrente",IF(K80>=1,"Completado",IF(AND(J80<>"",J80<FechaCorte),"Vencido",IF(AND(K80=0,OR(H80="",H80>FechaCorte)),"Por iniciar",IF(AND(T80<>"",T80<=UmbralRiesgo),"En riesgo","En plazo"))))) -> Completado | V80: =IF(OR(U80="Vencido",U80="En riesgo",U80="En plazo",U80="Por iniciar"),1,0) -> 0 | W80: =IF(U80="Vencido",FechaCorte-J80,"") | X80: =IF(AND(V80=1,U80<>"Vencido"),J80-FechaCorte,"") | Y80: =IF(J80="","",DATE(YEAR(J80),MONTH(J80),1)) -> 46204 | Z80: =IF(AND(U80="Completado",I80<>""),IF(I80<=FechaCorte,DATE(YEAR(I80),MONTH(I80),1),""),"") -> 46204 | AA80: =IF(J80="","",IF(DAY(J80+1)=1,1,0)) -> 0 | AB80: =IF(AND(U80="Completado",I80<>"",I80=J80),1,0) -> 1 | AC80: =IF(AND(K80>=1,I80<>""),IF(I80>FechaCorte,1,0),0) -> 0 | AD80: =IF(AND(I80<>"",H80<>""),IF(I80<H80,1,0),0) -> 0 | AE80: =IF(OR(F80="Riesgos",F80="Obs. Auditoría"),1,0) -> 0 | AF80: =IFERROR(MID(D80,FIND("PMC-",D80),8),"") | AG80: =IF(AND(V80=1,J80<>""),IF(AND(J80>=FechaCorte,J80<=HorizonteExpuestos),1,0),0) -> 0
A81: 80 | B81: 2026 | C81: Certificación de Accesos: Agencias | D81: Actualización matriz de coreografías y autorizadores - nuevas definiciones. | F81: Proyecto | G81: Ana María Fierro | H81: 46113 | J81: 46265 | K81: 0.05 | L81: Conversar con Diego Piedra / RRHH Estructura / Sole Pazmino | M81: PR.AA-05 | N81: =IFERROR(INDEX(dFrente!$B$2:$B$76,MATCH(C81,dFrente!$A$2:$A$76,0)),"Sin frente") -> Certificación de accesos | O81: =IFERROR(INDEX(dNIST!$B$2:$B$13,MATCH(M81,dNIST!$A$2:$A$13,0)),"") -> PR | P81: =TRIM(IFERROR(LEFT(G81,FIND(CHAR(10),G81)-1),G81)) -> Ana María Fierro | Q81: =LEN(TRIM(G81))-LEN(SUBSTITUTE(TRIM(G81),CHAR(10),""))+1 -> 1 | R81: =IF(E81<>"","Sí","No") -> No | S81: =IF(OR(J81="",H81=""),"",IF(J81<=H81,IF(FechaCorte>=J81,1,0),MAX(0,MIN(1,(FechaCorte-H81)/(J81-H81))))) -> 1 | T81: =IF(S81="","",K81-S81) -> -0.95 | U81: =IF(R81="Sí","Recurrente",IF(K81>=1,"Completado",IF(AND(J81<>"",J81<FechaCorte),"Vencido",IF(AND(K81=0,OR(H81="",H81>FechaCorte)),"Por iniciar",IF(AND(T81<>"",T81<=UmbralRiesgo),"En riesgo","En plazo"))))) -> Vencido | V81: =IF(OR(U81="Vencido",U81="En riesgo",U81="En plazo",U81="Por iniciar"),1,0) -> 1 | W81: =IF(U81="Vencido",FechaCorte-J81,"") -> 24 | X81: =IF(AND(V81=1,U81<>"Vencido"),J81-FechaCorte,"") | Y81: =IF(J81="","",DATE(YEAR(J81),MONTH(J81),1)) -> 46235 | Z81: =IF(AND(U81="Completado",I81<>""),IF(I81<=FechaCorte,DATE(YEAR(I81),MONTH(I81),1),""),"") | AA81: =IF(J81="","",IF(DAY(J81+1)=1,1,0)) -> 1 | AB81: =IF(AND(U81="Completado",I81<>"",I81=J81),1,0) -> 0 | AC81: =IF(AND(K81>=1,I81<>""),IF(I81>FechaCorte,1,0),0) -> 0 | AD81: =IF(AND(I81<>"",H81<>""),IF(I81<H81,1,0),0) -> 0 | AE81: =IF(OR(F81="Riesgos",F81="Obs. Auditoría"),1,0) -> 0 | AF81: =IFERROR(MID(D81,FIND("PMC-",D81),8),"") | AG81: =IF(AND(V81=1,J81<>""),IF(AND(J81>=FechaCorte,J81<=HorizonteExpuestos),1,0),0) -> 0
A82: 81 | B82: 2026 | C82: Certificación de Accesos: Agencias | D82: Homologación de perfiles de agencias para disminuir cambios cuando se requiere cambio de perfil global agencias. | F82: Proyecto | G82: Ana María Fierro | H82: 46023 | J82: 46387 | K82: 0.5 | L82: Pendiente Area Comercial | M82: PR.AA-05 | N82: =IFERROR(INDEX(dFrente!$B$2:$B$76,MATCH(C82,dFrente!$A$2:$A$76,0)),"Sin frente") -> Certificación de accesos | O82: =IFERROR(INDEX(dNIST!$B$2:$B$13,MATCH(M82,dNIST!$A$2:$A$13,0)),"") -> PR | P82: =TRIM(IFERROR(LEFT(G82,FIND(CHAR(10),G82)-1),G82)) -> Ana María Fierro | Q82: =LEN(TRIM(G82))-LEN(SUBSTITUTE(TRIM(G82),CHAR(10),""))+1 -> 1 | R82: =IF(E82<>"","Sí","No") -> No | S82: =IF(OR(J82="",H82=""),"",IF(J82<=H82,IF(FechaCorte>=J82,1,0),MAX(0,MIN(1,(FechaCorte-H82)/(J82-H82))))) -> 0.73076923 | T82: =IF(S82="","",K82-S82) -> -0.23076923 | U82: =IF(R82="Sí","Recurrente",IF(K82>=1,"Completado",IF(AND(J82<>"",J82<FechaCorte),"Vencido",IF(AND(K82=0,OR(H82="",H82>FechaCorte)),"Por iniciar",IF(AND(T82<>"",T82<=UmbralRiesgo),"En riesgo","En plazo"))))) -> En plazo | V82: =IF(OR(U82="Vencido",U82="En riesgo",U82="En plazo",U82="Por iniciar"),1,0) -> 1 | W82: =IF(U82="Vencido",FechaCorte-J82,"") | X82: =IF(AND(V82=1,U82<>"Vencido"),J82-FechaCorte,"") -> 98 | Y82: =IF(J82="","",DATE(YEAR(J82),MONTH(J82),1)) -> 46357 | Z82: =IF(AND(U82="Completado",I82<>""),IF(I82<=FechaCorte,DATE(YEAR(I82),MONTH(I82),1),""),"") | AA82: =IF(J82="","",IF(DAY(J82+1)=1,1,0)) -> 1 | AB82: =IF(AND(U82="Completado",I82<>"",I82=J82),1,0) -> 0 | AC82: =IF(AND(K82>=1,I82<>""),IF(I82>FechaCorte,1,0),0) -> 0 | AD82: =IF(AND(I82<>"",H82<>""),IF(I82<H82,1,0),0) -> 0 | AE82: =IF(OR(F82="Riesgos",F82="Obs. Auditoría"),1,0) -> 0 | AF82: =IFERROR(MID(D82,FIND("PMC-",D82),8),"") | AG82: =IF(AND(V82=1,J82<>""),IF(AND(J82>=FechaCorte,J82<=HorizonteExpuestos),1,0),0) -> 0
A83: 82 | B83: 2026 | C83: Certificación de Accesos: Agencias | D83: Actualización del instructivo - Nuevo proceso para la gestión de cambios de perfil y centro de costos Correo mensual al equipo de Negocio sobre los cambios mensuales en CC y perfil global temporal. | F83: Mejora | G83: Ana María Fierro | H83: 46113 | J83: 46265 | K83: 0.2 | L83: Reforzar con el equipo de Gye (las definiciones). | M83: GV.PO | N83: =IFERROR(INDEX(dFrente!$B$2:$B$76,MATCH(C83,dFrente!$A$2:$A$76,0)),"Sin frente") -> Certificación de accesos | O83: =IFERROR(INDEX(dNIST!$B$2:$B$13,MATCH(M83,dNIST!$A$2:$A$13,0)),"") -> GV | P83: =TRIM(IFERROR(LEFT(G83,FIND(CHAR(10),G83)-1),G83)) -> Ana María Fierro | Q83: =LEN(TRIM(G83))-LEN(SUBSTITUTE(TRIM(G83),CHAR(10),""))+1 -> 1 | R83: =IF(E83<>"","Sí","No") -> No | S83: =IF(OR(J83="",H83=""),"",IF(J83<=H83,IF(FechaCorte>=J83,1,0),MAX(0,MIN(1,(FechaCorte-H83)/(J83-H83))))) -> 1 | T83: =IF(S83="","",K83-S83) -> -0.8 | U83: =IF(R83="Sí","Recurrente",IF(K83>=1,"Completado",IF(AND(J83<>"",J83<FechaCorte),"Vencido",IF(AND(K83=0,OR(H83="",H83>FechaCorte)),"Por iniciar",IF(AND(T83<>"",T83<=UmbralRiesgo),"En riesgo","En plazo"))))) -> Vencido | V83: =IF(OR(U83="Vencido",U83="En riesgo",U83="En plazo",U83="Por iniciar"),1,0) -> 1 | W83: =IF(U83="Vencido",FechaCorte-J83,"") -> 24 | X83: =IF(AND(V83=1,U83<>"Vencido"),J83-FechaCorte,"") | Y83: =IF(J83="","",DATE(YEAR(J83),MONTH(J83),1)) -> 46235 | Z83: =IF(AND(U83="Completado",I83<>""),IF(I83<=FechaCorte,DATE(YEAR(I83),MONTH(I83),1),""),"") | AA83: =IF(J83="","",IF(DAY(J83+1)=1,1,0)) -> 1 | AB83: =IF(AND(U83="Completado",I83<>"",I83=J83),1,0) -> 0 | AC83: =IF(AND(K83>=1,I83<>""),IF(I83>FechaCorte,1,0),0) -> 0 | AD83: =IF(AND(I83<>"",H83<>""),IF(I83<H83,1,0),0) -> 0 | AE83: =IF(OR(F83="Riesgos",F83="Obs. Auditoría"),1,0) -> 0 | AF83: =IFERROR(MID(D83,FIND("PMC-",D83),8),"") | AG83: =IF(AND(V83=1,J83<>""),IF(AND(J83>=FechaCorte,J83<=HorizonteExpuestos),1,0),0) -> 0
A84: 83 | B84: 2026 | C84: Certificación de Accesos: Agencias | D84: Revisión de reseteos/deslogueo de usuarios de siglo 21 a través de VIA (787 colaboradores con este acceso), personal de Banca Relacional, Call Center, Operaciones y Banca Privada Internacional. | F84: Iniciativa | G84: Ana María Fierro | H84: 46023 | J84: 46295 | K84: 0.71 | L84: Se eliminó el acceso a 555 colaboradores, pendiente 214. cargo (Administrador Comercial y Servicios) | M84: PR.AA-05 | N84: =IFERROR(INDEX(dFrente!$B$2:$B$76,MATCH(C84,dFrente!$A$2:$A$76,0)),"Sin frente") -> Certificación de accesos | O84: =IFERROR(INDEX(dNIST!$B$2:$B$13,MATCH(M84,dNIST!$A$2:$A$13,0)),"") -> PR | P84: =TRIM(IFERROR(LEFT(G84,FIND(CHAR(10),G84)-1),G84)) -> Ana María Fierro | Q84: =LEN(TRIM(G84))-LEN(SUBSTITUTE(TRIM(G84),CHAR(10),""))+1 -> 1 | R84: =IF(E84<>"","Sí","No") -> No | S84: =IF(OR(J84="",H84=""),"",IF(J84<=H84,IF(FechaCorte>=J84,1,0),MAX(0,MIN(1,(FechaCorte-H84)/(J84-H84))))) -> 0.97794118 | T84: =IF(S84="","",K84-S84) -> -0.26794118 | U84: =IF(R84="Sí","Recurrente",IF(K84>=1,"Completado",IF(AND(J84<>"",J84<FechaCorte),"Vencido",IF(AND(K84=0,OR(H84="",H84>FechaCorte)),"Por iniciar",IF(AND(T84<>"",T84<=UmbralRiesgo),"En riesgo","En plazo"))))) -> En riesgo | V84: =IF(OR(U84="Vencido",U84="En riesgo",U84="En plazo",U84="Por iniciar"),1,0) -> 1 | W84: =IF(U84="Vencido",FechaCorte-J84,"") | X84: =IF(AND(V84=1,U84<>"Vencido"),J84-FechaCorte,"") -> 6 | Y84: =IF(J84="","",DATE(YEAR(J84),MONTH(J84),1)) -> 46266 | Z84: =IF(AND(U84="Completado",I84<>""),IF(I84<=FechaCorte,DATE(YEAR(I84),MONTH(I84),1),""),"") | AA84: =IF(J84="","",IF(DAY(J84+1)=1,1,0)) -> 1 | AB84: =IF(AND(U84="Completado",I84<>"",I84=J84),1,0) -> 0 | AC84: =IF(AND(K84>=1,I84<>""),IF(I84>FechaCorte,1,0),0) -> 0 | AD84: =IF(AND(I84<>"",H84<>""),IF(I84<H84,1,0),0) -> 0 | AE84: =IF(OR(F84="Riesgos",F84="Obs. Auditoría"),1,0) -> 0 | AF84: =IFERROR(MID(D84,FIND("PMC-",D84),8),"") | AG84: =IF(AND(V84=1,J84<>""),IF(AND(J84>=FechaCorte,J84<=HorizonteExpuestos),1,0),0) -> 1
A85: 84 | B85: 2026 | C85: Certificación de Accesos: Rotativas | D85: Revisión proceso utilización cuentas genéricas rotativas. CAJERO ROTATIVO: 499; JEFE ROTATIVO: 195; SUPERVISOR ROTATIVO: 209 | F85: Proyecto | G85: Ana María Fierro Yolanda León | H85: 46175 | J85: 46234 | K85: 0.75 | L85: Se ha efectuado un proceso de depuración de estas cuentas rotativas. | M85: PR.AA-05 | N85: =IFERROR(INDEX(dFrente!$B$2:$B$76,MATCH(C85,dFrente!$A$2:$A$76,0)),"Sin frente") -> Certificación de accesos | O85: =IFERROR(INDEX(dNIST!$B$2:$B$13,MATCH(M85,dNIST!$A$2:$A$13,0)),"") -> PR | P85: =TRIM(IFERROR(LEFT(G85,FIND(CHAR(10),G85)-1),G85)) -> Ana María Fierro | Q85: =LEN(TRIM(G85))-LEN(SUBSTITUTE(TRIM(G85),CHAR(10),""))+1 -> 2 | R85: =IF(E85<>"","Sí","No") -> No | S85: =IF(OR(J85="",H85=""),"",IF(J85<=H85,IF(FechaCorte>=J85,1,0),MAX(0,MIN(1,(FechaCorte-H85)/(J85-H85))))) -> 1 | T85: =IF(S85="","",K85-S85) -> -0.25 | U85: =IF(R85="Sí","Recurrente",IF(K85>=1,"Completado",IF(AND(J85<>"",J85<FechaCorte),"Vencido",IF(AND(K85=0,OR(H85="",H85>FechaCorte)),"Por iniciar",IF(AND(T85<>"",T85<=UmbralRiesgo),"En riesgo","En plazo"))))) -> Vencido | V85: =IF(OR(U85="Vencido",U85="En riesgo",U85="En plazo",U85="Por iniciar"),1,0) -> 1 | W85: =IF(U85="Vencido",FechaCorte-J85,"") -> 55 | X85: =IF(AND(V85=1,U85<>"Vencido"),J85-FechaCorte,"") | Y85: =IF(J85="","",DATE(YEAR(J85),MONTH(J85),1)) -> 46204 | Z85: =IF(AND(U85="Completado",I85<>""),IF(I85<=FechaCorte,DATE(YEAR(I85),MONTH(I85),1),""),"") | AA85: =IF(J85="","",IF(DAY(J85+1)=1,1,0)) -> 1 | AB85: =IF(AND(U85="Completado",I85<>"",I85=J85),1,0) -> 0 | AC85: =IF(AND(K85>=1,I85<>""),IF(I85>FechaCorte,1,0),0) -> 0 | AD85: =IF(AND(I85<>"",H85<>""),IF(I85<H85,1,0),0) -> 0 | AE85: =IF(OR(F85="Riesgos",F85="Obs. Auditoría"),1,0) -> 0 | AF85: =IFERROR(MID(D85,FIND("PMC-",D85),8),"") | AG85: =IF(AND(V85=1,J85<>""),IF(AND(J85>=FechaCorte,J85<=HorizonteExpuestos),1,0),0) -> 0
A86: 85 | B86: 2026 | C86: Certificación de Accesos: Estaciones Digitales | D86: Estaciones Digitales (Revisión de accesos, procesos y proponer nueva metodología) Informe de ciberdefensa (plan de acción de GI) - nuevo método de autenticación. | F86: Iniciativa | G86: Ana María Fierro Yolanda León | H86: 46023 | J86: 46326 | K86: 0.75 | L86: Se generó un informe y se realizaron correcciones. Pendiente metodología de acceso para estos usuarios. | M86: PR.AA-05 | N86: =IFERROR(INDEX(dFrente!$B$2:$B$76,MATCH(C86,dFrente!$A$2:$A$76,0)),"Sin frente") -> Certificación de accesos | O86: =IFERROR(INDEX(dNIST!$B$2:$B$13,MATCH(M86,dNIST!$A$2:$A$13,0)),"") -> PR | P86: =TRIM(IFERROR(LEFT(G86,FIND(CHAR(10),G86)-1),G86)) -> Ana María Fierro | Q86: =LEN(TRIM(G86))-LEN(SUBSTITUTE(TRIM(G86),CHAR(10),""))+1 -> 2 | R86: =IF(E86<>"","Sí","No") -> No | S86: =IF(OR(J86="",H86=""),"",IF(J86<=H86,IF(FechaCorte>=J86,1,0),MAX(0,MIN(1,(FechaCorte-H86)/(J86-H86))))) -> 0.87788779 | T86: =IF(S86="","",K86-S86) -> -0.12788779 | U86: =IF(R86="Sí","Recurrente",IF(K86>=1,"Completado",IF(AND(J86<>"",J86<FechaCorte),"Vencido",IF(AND(K86=0,OR(H86="",H86>FechaCorte)),"Por iniciar",IF(AND(T86<>"",T86<=UmbralRiesgo),"En riesgo","En plazo"))))) -> En plazo | V86: =IF(OR(U86="Vencido",U86="En riesgo",U86="En plazo",U86="Por iniciar"),1,0) -> 1 | W86: =IF(U86="Vencido",FechaCorte-J86,"") | X86: =IF(AND(V86=1,U86<>"Vencido"),J86-FechaCorte,"") -> 37 | Y86: =IF(J86="","",DATE(YEAR(J86),MONTH(J86),1)) -> 46296 | Z86: =IF(AND(U86="Completado",I86<>""),IF(I86<=FechaCorte,DATE(YEAR(I86),MONTH(I86),1),""),"") | AA86: =IF(J86="","",IF(DAY(J86+1)=1,1,0)) -> 1 | AB86: =IF(AND(U86="Completado",I86<>"",I86=J86),1,0) -> 0 | AC86: =IF(AND(K86>=1,I86<>""),IF(I86>FechaCorte,1,0),0) -> 0 | AD86: =IF(AND(I86<>"",H86<>""),IF(I86<H86,1,0),0) -> 0 | AE86: =IF(OR(F86="Riesgos",F86="Obs. Auditoría"),1,0) -> 0 | AF86: =IFERROR(MID(D86,FIND("PMC-",D86),8),"") | AG86: =IF(AND(V86=1,J86<>""),IF(AND(J86>=FechaCorte,J86<=HorizonteExpuestos),1,0),0) -> 0
A87: 86 | B87: 2026 | C87: Certificación de Accesos: ATM | D87: Depuración usuarios ATM | F87: Operación | G87: Ana María Fierro Yolanda León | H87: 46164 | I87: 46206 | J87: 46206 | K87: 1 | L87: Se ha procedido a eliminar los 175 usuarios genéricos de ATM. Se mantuvo reunión con el equipo de Implementación de Canales Físicos e incluirán al equipo de GI en las notificaciones para un proceso de depuración más oportuno. | M87: PR.AA-05 | N87: =IFERROR(INDEX(dFrente!$B$2:$B$76,MATCH(C87,dFrente!$A$2:$A$76,0)),"Sin frente") -> Certificación de accesos | O87: =IFERROR(INDEX(dNIST!$B$2:$B$13,MATCH(M87,dNIST!$A$2:$A$13,0)),"") -> PR | P87: =TRIM(IFERROR(LEFT(G87,FIND(CHAR(10),G87)-1),G87)) -> Ana María Fierro | Q87: =LEN(TRIM(G87))-LEN(SUBSTITUTE(TRIM(G87),CHAR(10),""))+1 -> 2 | R87: =IF(E87<>"","Sí","No") -> No | S87: =IF(OR(J87="",H87=""),"",IF(J87<=H87,IF(FechaCorte>=J87,1,0),MAX(0,MIN(1,(FechaCorte-H87)/(J87-H87))))) -> 1 | T87: =IF(S87="","",K87-S87) -> 0 | U87: =IF(R87="Sí","Recurrente",IF(K87>=1,"Completado",IF(AND(J87<>"",J87<FechaCorte),"Vencido",IF(AND(K87=0,OR(H87="",H87>FechaCorte)),"Por iniciar",IF(AND(T87<>"",T87<=UmbralRiesgo),"En riesgo","En plazo"))))) -> Completado | V87: =IF(OR(U87="Vencido",U87="En riesgo",U87="En plazo",U87="Por iniciar"),1,0) -> 0 | W87: =IF(U87="Vencido",FechaCorte-J87,"") | X87: =IF(AND(V87=1,U87<>"Vencido"),J87-FechaCorte,"") | Y87: =IF(J87="","",DATE(YEAR(J87),MONTH(J87),1)) -> 46204 | Z87: =IF(AND(U87="Completado",I87<>""),IF(I87<=FechaCorte,DATE(YEAR(I87),MONTH(I87),1),""),"") -> 46204 | AA87: =IF(J87="","",IF(DAY(J87+1)=1,1,0)) -> 0 | AB87: =IF(AND(U87="Completado",I87<>"",I87=J87),1,0) -> 1 | AC87: =IF(AND(K87>=1,I87<>""),IF(I87>FechaCorte,1,0),0) -> 0 | AD87: =IF(AND(I87<>"",H87<>""),IF(I87<H87,1,0),0) -> 0 | AE87: =IF(OR(F87="Riesgos",F87="Obs. Auditoría"),1,0) -> 0 | AF87: =IFERROR(MID(D87,FIND("PMC-",D87),8),"") | AG87: =IF(AND(V87=1,J87<>""),IF(AND(J87>=FechaCorte,J87<=HorizonteExpuestos),1,0),0) -> 0
A88: 87 | B88: 2026 | C88: Certificación de Accesos: Aplicaciones | D88: Depuración opción 677050 (segmentación de clientes), solicitud del Comité de Estrategía. | F88: Mejora | G88: Ana María Fierro | H88: 46113 | I88: 46265 | J88: 46265 | K88: 1 | L88: El 22 de julio se ejecutará la primera fase, pendiente fase 2 y fase 3 Fase 1: 1658 usuarios (usuarios nominados) Fase 2: 51 usuarios (genéricos de procesos que no registran inicios de sesión en más de 1 año) - Ejecutado 13/08/2026 Fase 3: 566 usuarios (genéricos de procesos con inicios de sesión activo) | M88: PR.AA-05 | N88: =IFERROR(INDEX(dFrente!$B$2:$B$76,MATCH(C88,dFrente!$A$2:$A$76,0)),"Sin frente") -> Certificación de accesos | O88: =IFERROR(INDEX(dNIST!$B$2:$B$13,MATCH(M88,dNIST!$A$2:$A$13,0)),"") -> PR | P88: =TRIM(IFERROR(LEFT(G88,FIND(CHAR(10),G88)-1),G88)) -> Ana María Fierro | Q88: =LEN(TRIM(G88))-LEN(SUBSTITUTE(TRIM(G88),CHAR(10),""))+1 -> 1 | R88: =IF(E88<>"","Sí","No") -> No | S88: =IF(OR(J88="",H88=""),"",IF(J88<=H88,IF(FechaCorte>=J88,1,0),MAX(0,MIN(1,(FechaCorte-H88)/(J88-H88))))) -> 1 | T88: =IF(S88="","",K88-S88) -> 0 | U88: =IF(R88="Sí","Recurrente",IF(K88>=1,"Completado",IF(AND(J88<>"",J88<FechaCorte),"Vencido",IF(AND(K88=0,OR(H88="",H88>FechaCorte)),"Por iniciar",IF(AND(T88<>"",T88<=UmbralRiesgo),"En riesgo","En plazo"))))) -> Completado | V88: =IF(OR(U88="Vencido",U88="En riesgo",U88="En plazo",U88="Por iniciar"),1,0) -> 0 | W88: =IF(U88="Vencido",FechaCorte-J88,"") | X88: =IF(AND(V88=1,U88<>"Vencido"),J88-FechaCorte,"") | Y88: =IF(J88="","",DATE(YEAR(J88),MONTH(J88),1)) -> 46235 | Z88: =IF(AND(U88="Completado",I88<>""),IF(I88<=FechaCorte,DATE(YEAR(I88),MONTH(I88),1),""),"") -> 46235 | AA88: =IF(J88="","",IF(DAY(J88+1)=1,1,0)) -> 1 | AB88: =IF(AND(U88="Completado",I88<>"",I88=J88),1,0) -> 1 | AC88: =IF(AND(K88>=1,I88<>""),IF(I88>FechaCorte,1,0),0) -> 0 | AD88: =IF(AND(I88<>"",H88<>""),IF(I88<H88,1,0),0) -> 0 | AE88: =IF(OR(F88="Riesgos",F88="Obs. Auditoría"),1,0) -> 0 | AF88: =IFERROR(MID(D88,FIND("PMC-",D88),8),"") | AG88: =IF(AND(V88=1,J88<>""),IF(AND(J88>=FechaCorte,J88<=HorizonteExpuestos),1,0),0) -> 0
A89: 88 | B89: 2026 | C89: Certificación de Accesos: Aplicaciones | D89: Observación Opciones Sensibles, depuración opción 1045 (validación opciones 21097, 21098, 21051), depuración menus en Bancs. | F89: Obs. Auditoría | G89: Ana María Fierro | H89: 46023 | J89: 46356 | K89: 0.9 | L89: pendiente opción 1045 a cargo de A. Fierro; Octavio Mejia. Se ejecutará un primer CC el 22 de julio. | M89: PR.AA-05 | N89: =IFERROR(INDEX(dFrente!$B$2:$B$76,MATCH(C89,dFrente!$A$2:$A$76,0)),"Sin frente") -> Certificación de accesos | O89: =IFERROR(INDEX(dNIST!$B$2:$B$13,MATCH(M89,dNIST!$A$2:$A$13,0)),"") -> PR | P89: =TRIM(IFERROR(LEFT(G89,FIND(CHAR(10),G89)-1),G89)) -> Ana María Fierro | Q89: =LEN(TRIM(G89))-LEN(SUBSTITUTE(TRIM(G89),CHAR(10),""))+1 -> 1 | R89: =IF(E89<>"","Sí","No") -> No | S89: =IF(OR(J89="",H89=""),"",IF(J89<=H89,IF(FechaCorte>=J89,1,0),MAX(0,MIN(1,(FechaCorte-H89)/(J89-H89))))) -> 0.7987988 | T89: =IF(S89="","",K89-S89) -> 0.1012012 | U89: =IF(R89="Sí","Recurrente",IF(K89>=1,"Completado",IF(AND(J89<>"",J89<FechaCorte),"Vencido",IF(AND(K89=0,OR(H89="",H89>FechaCorte)),"Por iniciar",IF(AND(T89<>"",T89<=UmbralRiesgo),"En riesgo","En plazo"))))) -> En plazo | V89: =IF(OR(U89="Vencido",U89="En riesgo",U89="En plazo",U89="Por iniciar"),1,0) -> 1 | W89: =IF(U89="Vencido",FechaCorte-J89,"") | X89: =IF(AND(V89=1,U89<>"Vencido"),J89-FechaCorte,"") -> 67 | Y89: =IF(J89="","",DATE(YEAR(J89),MONTH(J89),1)) -> 46327 | Z89: =IF(AND(U89="Completado",I89<>""),IF(I89<=FechaCorte,DATE(YEAR(I89),MONTH(I89),1),""),"") | AA89: =IF(J89="","",IF(DAY(J89+1)=1,1,0)) -> 1 | AB89: =IF(AND(U89="Completado",I89<>"",I89=J89),1,0) -> 0 | AC89: =IF(AND(K89>=1,I89<>""),IF(I89>FechaCorte,1,0),0) -> 0 | AD89: =IF(AND(I89<>"",H89<>""),IF(I89<H89,1,0),0) -> 0 | AE89: =IF(OR(F89="Riesgos",F89="Obs. Auditoría"),1,0) -> 1 | AF89: =IFERROR(MID(D89,FIND("PMC-",D89),8),"") | AG89: =IF(AND(V89=1,J89<>""),IF(AND(J89>=FechaCorte,J89<=HorizonteExpuestos),1,0),0) -> 0
A90: 89 | B90: 2026 | C90: Certificación de Accesos: Aplicaciones | D90: Análisis de factibilidad automatización de inconsistencias | F90: Operación | G90: Bryan Uyana Richard Requelme | H90: 46224 | J90: 46325 | K90: 0.2 | L90: Se evaluara con 5 aplicaciones incialmente para automatizar | M90: PR.AA-05 | N90: =IFERROR(INDEX(dFrente!$B$2:$B$76,MATCH(C90,dFrente!$A$2:$A$76,0)),"Sin frente") -> Certificación de accesos | O90: =IFERROR(INDEX(dNIST!$B$2:$B$13,MATCH(M90,dNIST!$A$2:$A$13,0)),"") -> PR | P90: =TRIM(IFERROR(LEFT(G90,FIND(CHAR(10),G90)-1),G90)) -> Bryan Uyana | Q90: =LEN(TRIM(G90))-LEN(SUBSTITUTE(TRIM(G90),CHAR(10),""))+1 -> 2 | R90: =IF(E90<>"","Sí","No") -> No | S90: =IF(OR(J90="",H90=""),"",IF(J90<=H90,IF(FechaCorte>=J90,1,0),MAX(0,MIN(1,(FechaCorte-H90)/(J90-H90))))) -> 0.64356436 | T90: =IF(S90="","",K90-S90) -> -0.44356436 | U90: =IF(R90="Sí","Recurrente",IF(K90>=1,"Completado",IF(AND(J90<>"",J90<FechaCorte),"Vencido",IF(AND(K90=0,OR(H90="",H90>FechaCorte)),"Por iniciar",IF(AND(T90<>"",T90<=UmbralRiesgo),"En riesgo","En plazo"))))) -> En riesgo | V90: =IF(OR(U90="Vencido",U90="En riesgo",U90="En plazo",U90="Por iniciar"),1,0) -> 1 | W90: =IF(U90="Vencido",FechaCorte-J90,"") | X90: =IF(AND(V90=1,U90<>"Vencido"),J90-FechaCorte,"") -> 36 | Y90: =IF(J90="","",DATE(YEAR(J90),MONTH(J90),1)) -> 46296 | Z90: =IF(AND(U90="Completado",I90<>""),IF(I90<=FechaCorte,DATE(YEAR(I90),MONTH(I90),1),""),"") | AA90: =IF(J90="","",IF(DAY(J90+1)=1,1,0)) -> 0 | AB90: =IF(AND(U90="Completado",I90<>"",I90=J90),1,0) -> 0 | AC90: =IF(AND(K90>=1,I90<>""),IF(I90>FechaCorte,1,0),0) -> 0 | AD90: =IF(AND(I90<>"",H90<>""),IF(I90<H90,1,0),0) -> 0 | AE90: =IF(OR(F90="Riesgos",F90="Obs. Auditoría"),1,0) -> 0 | AF90: =IFERROR(MID(D90,FIND("PMC-",D90),8),"") | AG90: =IF(AND(V90=1,J90<>""),IF(AND(J90>=FechaCorte,J90<=HorizonteExpuestos),1,0),0) -> 0
A91: 90 | B91: 2026 | C91: Certificación de Accesos: Aplicaciones | D91: Pipeline para aprobación de modificación de roles en BPOne (control de cambios en roles y creación de nuevos roles en BPOne) | F91: Iniciativa | G91: Ana María Fierro | H91: 46204 | I91: 46235 | J91: 46235 | K91: 1 | L91: En periodo de pruebas. | M91: PR.AA-05 | N91: =IFERROR(INDEX(dFrente!$B$2:$B$76,MATCH(C91,dFrente!$A$2:$A$76,0)),"Sin frente") -> Certificación de accesos | O91: =IFERROR(INDEX(dNIST!$B$2:$B$13,MATCH(M91,dNIST!$A$2:$A$13,0)),"") -> PR | P91: =TRIM(IFERROR(LEFT(G91,FIND(CHAR(10),G91)-1),G91)) -> Ana María Fierro | Q91: =LEN(TRIM(G91))-LEN(SUBSTITUTE(TRIM(G91),CHAR(10),""))+1 -> 1 | R91: =IF(E91<>"","Sí","No") -> No | S91: =IF(OR(J91="",H91=""),"",IF(J91<=H91,IF(FechaCorte>=J91,1,0),MAX(0,MIN(1,(FechaCorte-H91)/(J91-H91))))) -> 1 | T91: =IF(S91="","",K91-S91) -> 0 | U91: =IF(R91="Sí","Recurrente",IF(K91>=1,"Completado",IF(AND(J91<>"",J91<FechaCorte),"Vencido",IF(AND(K91=0,OR(H91="",H91>FechaCorte)),"Por iniciar",IF(AND(T91<>"",T91<=UmbralRiesgo),"En riesgo","En plazo"))))) -> Completado | V91: =IF(OR(U91="Vencido",U91="En riesgo",U91="En plazo",U91="Por iniciar"),1,0) -> 0 | W91: =IF(U91="Vencido",FechaCorte-J91,"") | X91: =IF(AND(V91=1,U91<>"Vencido"),J91-FechaCorte,"") | Y91: =IF(J91="","",DATE(YEAR(J91),MONTH(J91),1)) -> 46235 | Z91: =IF(AND(U91="Completado",I91<>""),IF(I91<=FechaCorte,DATE(YEAR(I91),MONTH(I91),1),""),"") -> 46235 | AA91: =IF(J91="","",IF(DAY(J91+1)=1,1,0)) -> 0 | AB91: =IF(AND(U91="Completado",I91<>"",I91=J91),1,0) -> 1 | AC91: =IF(AND(K91>=1,I91<>""),IF(I91>FechaCorte,1,0),0) -> 0 | AD91: =IF(AND(I91<>"",H91<>""),IF(I91<H91,1,0),0) -> 0 | AE91: =IF(OR(F91="Riesgos",F91="Obs. Auditoría"),1,0) -> 0 | AF91: =IFERROR(MID(D91,FIND("PMC-",D91),8),"") | AG91: =IF(AND(V91=1,J91<>""),IF(AND(J91>=FechaCorte,J91<=HorizonteExpuestos),1,0),0) -> 0
A92: 91 | B92: 2026 | C92: Certificación de Accesos: Aplicaciones | D92: Apagado Portal de Negocios perfilamiento BPOne, CRM y Athento | F92: Operación | G92: Ana María Fierro | H92: 46235 | I92: 46266 | J92: 46266 | K92: 1 | L92: Perfilamiento BPOne y Athento, pendiente CRM. | M92: PR.AA-05 | N92: =IFERROR(INDEX(dFrente!$B$2:$B$76,MATCH(C92,dFrente!$A$2:$A$76,0)),"Sin frente") -> Certificación de accesos | O92: =IFERROR(INDEX(dNIST!$B$2:$B$13,MATCH(M92,dNIST!$A$2:$A$13,0)),"") -> PR | P92: =TRIM(IFERROR(LEFT(G92,FIND(CHAR(10),G92)-1),G92)) -> Ana María Fierro | Q92: =LEN(TRIM(G92))-LEN(SUBSTITUTE(TRIM(G92),CHAR(10),""))+1 -> 1 | R92: =IF(E92<>"","Sí","No") -> No | S92: =IF(OR(J92="",H92=""),"",IF(J92<=H92,IF(FechaCorte>=J92,1,0),MAX(0,MIN(1,(FechaCorte-H92)/(J92-H92))))) -> 1 | T92: =IF(S92="","",K92-S92) -> 0 | U92: =IF(R92="Sí","Recurrente",IF(K92>=1,"Completado",IF(AND(J92<>"",J92<FechaCorte),"Vencido",IF(AND(K92=0,OR(H92="",H92>FechaCorte)),"Por iniciar",IF(AND(T92<>"",T92<=UmbralRiesgo),"En riesgo","En plazo"))))) -> Completado | V92: =IF(OR(U92="Vencido",U92="En riesgo",U92="En plazo",U92="Por iniciar"),1,0) -> 0 | W92: =IF(U92="Vencido",FechaCorte-J92,"") | X92: =IF(AND(V92=1,U92<>"Vencido"),J92-FechaCorte,"") | Y92: =IF(J92="","",DATE(YEAR(J92),MONTH(J92),1)) -> 46266 | Z92: =IF(AND(U92="Completado",I92<>""),IF(I92<=FechaCorte,DATE(YEAR(I92),MONTH(I92),1),""),"") -> 46266 | AA92: =IF(J92="","",IF(DAY(J92+1)=1,1,0)) -> 0 | AB92: =IF(AND(U92="Completado",I92<>"",I92=J92),1,0) -> 1 | AC92: =IF(AND(K92>=1,I92<>""),IF(I92>FechaCorte,1,0),0) -> 0 | AD92: =IF(AND(I92<>"",H92<>""),IF(I92<H92,1,0),0) -> 0 | AE92: =IF(OR(F92="Riesgos",F92="Obs. Auditoría"),1,0) -> 0 | AF92: =IFERROR(MID(D92,FIND("PMC-",D92),8),"") | AG92: =IF(AND(V92=1,J92<>""),IF(AND(J92>=FechaCorte,J92<=HorizonteExpuestos),1,0),0) -> 0
A93: 92 | B93: 2026 | C93: Certificación de Accesos: Aplicaciones | D93: Depuración de accesos a usuarios en aplicativos priorizados. 1) GAF, 2) Cash Management, 3) CREDIFE, 4) BPOne, 5) CRM, 6) Webteller 7) Bancs. | F93: Operación | G93: Ana María Fierro Yolanda León | H93: 46266 | J93: 46356 | K93: 0.14 | L93: Inicio septiembre 2026 | M93: PR.AA-05 | N93: =IFERROR(INDEX(dFrente!$B$2:$B$76,MATCH(C93,dFrente!$A$2:$A$76,0)),"Sin frente") -> Certificación de accesos | O93: =IFERROR(INDEX(dNIST!$B$2:$B$13,MATCH(M93,dNIST!$A$2:$A$13,0)),"") -> PR | P93: =TRIM(IFERROR(LEFT(G93,FIND(CHAR(10),G93)-1),G93)) -> Ana María Fierro | Q93: =LEN(TRIM(G93))-LEN(SUBSTITUTE(TRIM(G93),CHAR(10),""))+1 -> 2 | R93: =IF(E93<>"","Sí","No") -> No | S93: =IF(OR(J93="",H93=""),"",IF(J93<=H93,IF(FechaCorte>=J93,1,0),MAX(0,MIN(1,(FechaCorte-H93)/(J93-H93))))) -> 0.25555556 | T93: =IF(S93="","",K93-S93) -> -0.11555556 | U93: =IF(R93="Sí","Recurrente",IF(K93>=1,"Completado",IF(AND(J93<>"",J93<FechaCorte),"Vencido",IF(AND(K93=0,OR(H93="",H93>FechaCorte)),"Por iniciar",IF(AND(T93<>"",T93<=UmbralRiesgo),"En riesgo","En plazo"))))) -> En plazo | V93: =IF(OR(U93="Vencido",U93="En riesgo",U93="En plazo",U93="Por iniciar"),1,0) -> 1 | W93: =IF(U93="Vencido",FechaCorte-J93,"") | X93: =IF(AND(V93=1,U93<>"Vencido"),J93-FechaCorte,"") -> 67 | Y93: =IF(J93="","",DATE(YEAR(J93),MONTH(J93),1)) -> 46327 | Z93: =IF(AND(U93="Completado",I93<>""),IF(I93<=FechaCorte,DATE(YEAR(I93),MONTH(I93),1),""),"") | AA93: =IF(J93="","",IF(DAY(J93+1)=1,1,0)) -> 1 | AB93: =IF(AND(U93="Completado",I93<>"",I93=J93),1,0) -> 0 | AC93: =IF(AND(K93>=1,I93<>""),IF(I93>FechaCorte,1,0),0) -> 0 | AD93: =IF(AND(I93<>"",H93<>""),IF(I93<H93,1,0),0) -> 0 | AE93: =IF(OR(F93="Riesgos",F93="Obs. Auditoría"),1,0) -> 0 | AF93: =IFERROR(MID(D93,FIND("PMC-",D93),8),"") | AG93: =IF(AND(V93=1,J93<>""),IF(AND(J93>=FechaCorte,J93<=HorizonteExpuestos),1,0),0) -> 0
A94: 93 | B94: 2026 | C94: Base de Datos | D94: Levantamiento nuevo flujo gestion de accesos a BBDD. | F94: Obs. Auditoría | G94: Bryan Uyana Daniel Lescano Richard Requelme | H94: 46113 | J94: 46295 | K94: 0.8 | L94: - 15-sept- se tiene los acuerdos, está en proceso de actualización el anexo del instructivo. Se opera en función a la estrategia | M94: PR.AA-05 | N94: =IFERROR(INDEX(dFrente!$B$2:$B$76,MATCH(C94,dFrente!$A$2:$A$76,0)),"Sin frente") -> Bases de datos y SFTP | O94: =IFERROR(INDEX(dNIST!$B$2:$B$13,MATCH(M94,dNIST!$A$2:$A$13,0)),"") -> PR | P94: =TRIM(IFERROR(LEFT(G94,FIND(CHAR(10),G94)-1),G94)) -> Bryan Uyana | Q94: =LEN(TRIM(G94))-LEN(SUBSTITUTE(TRIM(G94),CHAR(10),""))+1 -> 3 | R94: =IF(E94<>"","Sí","No") -> No | S94: =IF(OR(J94="",H94=""),"",IF(J94<=H94,IF(FechaCorte>=J94,1,0),MAX(0,MIN(1,(FechaCorte-H94)/(J94-H94))))) -> 0.96703297 | T94: =IF(S94="","",K94-S94) -> -0.16703297 | U94: =IF(R94="Sí","Recurrente",IF(K94>=1,"Completado",IF(AND(J94<>"",J94<FechaCorte),"Vencido",IF(AND(K94=0,OR(H94="",H94>FechaCorte)),"Por iniciar",IF(AND(T94<>"",T94<=UmbralRiesgo),"En riesgo","En plazo"))))) -> En plazo | V94: =IF(OR(U94="Vencido",U94="En riesgo",U94="En plazo",U94="Por iniciar"),1,0) -> 1 | W94: =IF(U94="Vencido",FechaCorte-J94,"") | X94: =IF(AND(V94=1,U94<>"Vencido"),J94-FechaCorte,"") -> 6 | Y94: =IF(J94="","",DATE(YEAR(J94),MONTH(J94),1)) -> 46266 | Z94: =IF(AND(U94="Completado",I94<>""),IF(I94<=FechaCorte,DATE(YEAR(I94),MONTH(I94),1),""),"") | AA94: =IF(J94="","",IF(DAY(J94+1)=1,1,0)) -> 1 | AB94: =IF(AND(U94="Completado",I94<>"",I94=J94),1,0) -> 0 | AC94: =IF(AND(K94>=1,I94<>""),IF(I94>FechaCorte,1,0),0) -> 0 | AD94: =IF(AND(I94<>"",H94<>""),IF(I94<H94,1,0),0) -> 0 | AE94: =IF(OR(F94="Riesgos",F94="Obs. Auditoría"),1,0) -> 1 | AF94: =IFERROR(MID(D94,FIND("PMC-",D94),8),"") | AG94: =IF(AND(V94=1,J94<>""),IF(AND(J94>=FechaCorte,J94<=HorizonteExpuestos),1,0),0) -> 1
A95: 94 | B95: 2026 | C95: Base de Datos | D95: Ejecución de controles de depuración BBDD. Control Estandar. | F95: Operación | G95: Rommel Merchan | H95: 46204 | J95: 46387 | K95: 0.05 | M95: PR.AA-05 | N95: =IFERROR(INDEX(dFrente!$B$2:$B$76,MATCH(C95,dFrente!$A$2:$A$76,0)),"Sin frente") -> Bases de datos y SFTP | O95: =IFERROR(INDEX(dNIST!$B$2:$B$13,MATCH(M95,dNIST!$A$2:$A$13,0)),"") -> PR | P95: =TRIM(IFERROR(LEFT(G95,FIND(CHAR(10),G95)-1),G95)) -> Rommel Merchan | Q95: =LEN(TRIM(G95))-LEN(SUBSTITUTE(TRIM(G95),CHAR(10),""))+1 -> 1 | R95: =IF(E95<>"","Sí","No") -> No | S95: =IF(OR(J95="",H95=""),"",IF(J95<=H95,IF(FechaCorte>=J95,1,0),MAX(0,MIN(1,(FechaCorte-H95)/(J95-H95))))) -> 0.46448087 | T95: =IF(S95="","",K95-S95) -> -0.41448087 | U95: =IF(R95="Sí","Recurrente",IF(K95>=1,"Completado",IF(AND(J95<>"",J95<FechaCorte),"Vencido",IF(AND(K95=0,OR(H95="",H95>FechaCorte)),"Por iniciar",IF(AND(T95<>"",T95<=UmbralRiesgo),"En riesgo","En plazo"))))) -> En riesgo | V95: =IF(OR(U95="Vencido",U95="En riesgo",U95="En plazo",U95="Por iniciar"),1,0) -> 1 | W95: =IF(U95="Vencido",FechaCorte-J95,"") | X95: =IF(AND(V95=1,U95<>"Vencido"),J95-FechaCorte,"") -> 98 | Y95: =IF(J95="","",DATE(YEAR(J95),MONTH(J95),1)) -> 46357 | Z95: =IF(AND(U95="Completado",I95<>""),IF(I95<=FechaCorte,DATE(YEAR(I95),MONTH(I95),1),""),"") | AA95: =IF(J95="","",IF(DAY(J95+1)=1,1,0)) -> 1 | AB95: =IF(AND(U95="Completado",I95<>"",I95=J95),1,0) -> 0 | AC95: =IF(AND(K95>=1,I95<>""),IF(I95>FechaCorte,1,0),0) -> 0 | AD95: =IF(AND(I95<>"",H95<>""),IF(I95<H95,1,0),0) -> 0 | AE95: =IF(OR(F95="Riesgos",F95="Obs. Auditoría"),1,0) -> 0 | AF95: =IFERROR(MID(D95,FIND("PMC-",D95),8),"") | AG95: =IF(AND(V95=1,J95<>""),IF(AND(J95>=FechaCorte,J95<=HorizonteExpuestos),1,0),0) -> 0
A96: 95 | B96: 2026 | C96: Base de Datos | D96: Realización de control de cambios estándar para depuración masiva | F96: Iniciativa | G96: Bryan Uyana | H96: 46146 | I96: 46154 | J96: 46154 | K96: 1 | M96: PR.AA-05 | N96: =IFERROR(INDEX(dFrente!$B$2:$B$76,MATCH(C96,dFrente!$A$2:$A$76,0)),"Sin frente") -> Bases de datos y SFTP | O96: =IFERROR(INDEX(dNIST!$B$2:$B$13,MATCH(M96,dNIST!$A$2:$A$13,0)),"") -> PR | P96: =TRIM(IFERROR(LEFT(G96,FIND(CHAR(10),G96)-1),G96)) -> Bryan Uyana | Q96: =LEN(TRIM(G96))-LEN(SUBSTITUTE(TRIM(G96),CHAR(10),""))+1 -> 1 | R96: =IF(E96<>"","Sí","No") -> No | S96: =IF(OR(J96="",H96=""),"",IF(J96<=H96,IF(FechaCorte>=J96,1,0),MAX(0,MIN(1,(FechaCorte-H96)/(J96-H96))))) -> 1 | T96: =IF(S96="","",K96-S96) -> 0 | U96: =IF(R96="Sí","Recurrente",IF(K96>=1,"Completado",IF(AND(J96<>"",J96<FechaCorte),"Vencido",IF(AND(K96=0,OR(H96="",H96>FechaCorte)),"Por iniciar",IF(AND(T96<>"",T96<=UmbralRiesgo),"En riesgo","En plazo"))))) -> Completado | V96: =IF(OR(U96="Vencido",U96="En riesgo",U96="En plazo",U96="Por iniciar"),1,0) -> 0 | W96: =IF(U96="Vencido",FechaCorte-J96,"") | X96: =IF(AND(V96=1,U96<>"Vencido"),J96-FechaCorte,"") | Y96: =IF(J96="","",DATE(YEAR(J96),MONTH(J96),1)) -> 46143 | Z96: =IF(AND(U96="Completado",I96<>""),IF(I96<=FechaCorte,DATE(YEAR(I96),MONTH(I96),1),""),"") -> 46143 | AA96: =IF(J96="","",IF(DAY(J96+1)=1,1,0)) -> 0 | AB96: =IF(AND(U96="Completado",I96<>"",I96=J96),1,0) -> 1 | AC96: =IF(AND(K96>=1,I96<>""),IF(I96>FechaCorte,1,0),0) -> 0 | AD96: =IF(AND(I96<>"",H96<>""),IF(I96<H96,1,0),0) -> 0 | AE96: =IF(OR(F96="Riesgos",F96="Obs. Auditoría"),1,0) -> 0 | AF96: =IFERROR(MID(D96,FIND("PMC-",D96),8),"") | AG96: =IF(AND(V96=1,J96<>""),IF(AND(J96>=FechaCorte,J96<=HorizonteExpuestos),1,0),0) -> 0
A97: 96 | B97: 2026 | C97: Base de Datos | D97: Eliminación de usuarios en BD Bancs P012BAND | F97: Riesgos | G97: Daniel Lescano | H97: 46082 | I97: 46183 | J97: 46183 | K97: 1 | L97: correo enviado el 10.06.2026. 3 usuarios faltantes | M97: PR.AA-05 | N97: =IFERROR(INDEX(dFrente!$B$2:$B$76,MATCH(C97,dFrente!$A$2:$A$76,0)),"Sin frente") -> Bases de datos y SFTP | O97: =IFERROR(INDEX(dNIST!$B$2:$B$13,MATCH(M97,dNIST!$A$2:$A$13,0)),"") -> PR | P97: =TRIM(IFERROR(LEFT(G97,FIND(CHAR(10),G97)-1),G97)) -> Daniel Lescano | Q97: =LEN(TRIM(G97))-LEN(SUBSTITUTE(TRIM(G97),CHAR(10),""))+1 -> 1 | R97: =IF(E97<>"","Sí","No") -> No | S97: =IF(OR(J97="",H97=""),"",IF(J97<=H97,IF(FechaCorte>=J97,1,0),MAX(0,MIN(1,(FechaCorte-H97)/(J97-H97))))) -> 1 | T97: =IF(S97="","",K97-S97) -> 0 | U97: =IF(R97="Sí","Recurrente",IF(K97>=1,"Completado",IF(AND(J97<>"",J97<FechaCorte),"Vencido",IF(AND(K97=0,OR(H97="",H97>FechaCorte)),"Por iniciar",IF(AND(T97<>"",T97<=UmbralRiesgo),"En riesgo","En plazo"))))) -> Completado | V97: =IF(OR(U97="Vencido",U97="En riesgo",U97="En plazo",U97="Por iniciar"),1,0) -> 0 | W97: =IF(U97="Vencido",FechaCorte-J97,"") | X97: =IF(AND(V97=1,U97<>"Vencido"),J97-FechaCorte,"") | Y97: =IF(J97="","",DATE(YEAR(J97),MONTH(J97),1)) -> 46174 | Z97: =IF(AND(U97="Completado",I97<>""),IF(I97<=FechaCorte,DATE(YEAR(I97),MONTH(I97),1),""),"") -> 46174 | AA97: =IF(J97="","",IF(DAY(J97+1)=1,1,0)) -> 0 | AB97: =IF(AND(U97="Completado",I97<>"",I97=J97),1,0) -> 1 | AC97: =IF(AND(K97>=1,I97<>""),IF(I97>FechaCorte,1,0),0) -> 0 | AD97: =IF(AND(I97<>"",H97<>""),IF(I97<H97,1,0),0) -> 0 | AE97: =IF(OR(F97="Riesgos",F97="Obs. Auditoría"),1,0) -> 1 | AF97: =IFERROR(MID(D97,FIND("PMC-",D97),8),"") | AG97: =IF(AND(V97=1,J97<>""),IF(AND(J97>=FechaCorte,J97<=HorizonteExpuestos),1,0),0) -> 0
A98: 97 | B98: 2026 | C98: Base de Datos | D98: Diseño de nueva estrategia para el otorgamiento de accesos a BD, grupos AD, bloqueos fw y construcción roles en SP. | F98: Iniciativa | G98: Daniel Lescano Richard Requelme Bryan Uyana | H98: 46196 | I98: 46224 | J98: 46224 | K98: 1 | L98: Se elaboró presentación con la nueva estrategia y se comunicó al equipo. | M98: PR.AA-05 | N98: =IFERROR(INDEX(dFrente!$B$2:$B$76,MATCH(C98,dFrente!$A$2:$A$76,0)),"Sin frente") -> Bases de datos y SFTP | O98: =IFERROR(INDEX(dNIST!$B$2:$B$13,MATCH(M98,dNIST!$A$2:$A$13,0)),"") -> PR | P98: =TRIM(IFERROR(LEFT(G98,FIND(CHAR(10),G98)-1),G98)) -> Daniel Lescano | Q98: =LEN(TRIM(G98))-LEN(SUBSTITUTE(TRIM(G98),CHAR(10),""))+1 -> 3 | R98: =IF(E98<>"","Sí","No") -> No | S98: =IF(OR(J98="",H98=""),"",IF(J98<=H98,IF(FechaCorte>=J98,1,0),MAX(0,MIN(1,(FechaCorte-H98)/(J98-H98))))) -> 1 | T98: =IF(S98="","",K98-S98) -> 0 | U98: =IF(R98="Sí","Recurrente",IF(K98>=1,"Completado",IF(AND(J98<>"",J98<FechaCorte),"Vencido",IF(AND(K98=0,OR(H98="",H98>FechaCorte)),"Por iniciar",IF(AND(T98<>"",T98<=UmbralRiesgo),"En riesgo","En plazo"))))) -> Completado | V98: =IF(OR(U98="Vencido",U98="En riesgo",U98="En plazo",U98="Por iniciar"),1,0) -> 0 | W98: =IF(U98="Vencido",FechaCorte-J98,"") | X98: =IF(AND(V98=1,U98<>"Vencido"),J98-FechaCorte,"") | Y98: =IF(J98="","",DATE(YEAR(J98),MONTH(J98),1)) -> 46204 | Z98: =IF(AND(U98="Completado",I98<>""),IF(I98<=FechaCorte,DATE(YEAR(I98),MONTH(I98),1),""),"") -> 46204 | AA98: =IF(J98="","",IF(DAY(J98+1)=1,1,0)) -> 0 | AB98: =IF(AND(U98="Completado",I98<>"",I98=J98),1,0) -> 1 | AC98: =IF(AND(K98>=1,I98<>""),IF(I98>FechaCorte,1,0),0) -> 0 | AD98: =IF(AND(I98<>"",H98<>""),IF(I98<H98,1,0),0) -> 0 | AE98: =IF(OR(F98="Riesgos",F98="Obs. Auditoría"),1,0) -> 0 | AF98: =IFERROR(MID(D98,FIND("PMC-",D98),8),"") | AG98: =IF(AND(V98=1,J98<>""),IF(AND(J98>=FechaCorte,J98<=HorizonteExpuestos),1,0),0) -> 0
A99: 98 | B99: 2026 | C99: Base de Datos | D99: Proyecto depuración de accesos a BD en función de la nueva estrategia diseñada. (BD que no tienen acceso info. Sensible -no EPI-) | F99: Iniciativa | G99: Rommel Merchan | H99: 46082 | J99: 46295 | K99: 0.05 | L99: Porcentaje de acuerdo a lo avanzado con Rommel y Jhonna. | M99: PR.AA-05 | N99: =IFERROR(INDEX(dFrente!$B$2:$B$76,MATCH(C99,dFrente!$A$2:$A$76,0)),"Sin frente") -> Bases de datos y SFTP | O99: =IFERROR(INDEX(dNIST!$B$2:$B$13,MATCH(M99,dNIST!$A$2:$A$13,0)),"") -> PR | P99: =TRIM(IFERROR(LEFT(G99,FIND(CHAR(10),G99)-1),G99)) -> Rommel Merchan | Q99: =LEN(TRIM(G99))-LEN(SUBSTITUTE(TRIM(G99),CHAR(10),""))+1 -> 1 | R99: =IF(E99<>"","Sí","No") -> No | S99: =IF(OR(J99="",H99=""),"",IF(J99<=H99,IF(FechaCorte>=J99,1,0),MAX(0,MIN(1,(FechaCorte-H99)/(J99-H99))))) -> 0.97183099 | T99: =IF(S99="","",K99-S99) -> -0.92183099 | U99: =IF(R99="Sí","Recurrente",IF(K99>=1,"Completado",IF(AND(J99<>"",J99<FechaCorte),"Vencido",IF(AND(K99=0,OR(H99="",H99>FechaCorte)),"Por iniciar",IF(AND(T99<>"",T99<=UmbralRiesgo),"En riesgo","En plazo"))))) -> En riesgo | V99: =IF(OR(U99="Vencido",U99="En riesgo",U99="En plazo",U99="Por iniciar"),1,0) -> 1 | W99: =IF(U99="Vencido",FechaCorte-J99,"") | X99: =IF(AND(V99=1,U99<>"Vencido"),J99-FechaCorte,"") -> 6 | Y99: =IF(J99="","",DATE(YEAR(J99),MONTH(J99),1)) -> 46266 | Z99: =IF(AND(U99="Completado",I99<>""),IF(I99<=FechaCorte,DATE(YEAR(I99),MONTH(I99),1),""),"") | AA99: =IF(J99="","",IF(DAY(J99+1)=1,1,0)) -> 1 | AB99: =IF(AND(U99="Completado",I99<>"",I99=J99),1,0) -> 0 | AC99: =IF(AND(K99>=1,I99<>""),IF(I99>FechaCorte,1,0),0) -> 0 | AD99: =IF(AND(I99<>"",H99<>""),IF(I99<H99,1,0),0) -> 0 | AE99: =IF(OR(F99="Riesgos",F99="Obs. Auditoría"),1,0) -> 0 | AF99: =IFERROR(MID(D99,FIND("PMC-",D99),8),"") | AG99: =IF(AND(V99=1,J99<>""),IF(AND(J99>=FechaCorte,J99<=HorizonteExpuestos),1,0),0) -> 1
A100: 99 | B100: 2026 | C100: Base de Datos | D100: Grupos de AD y Firewall (análisis, cambio de funcionalidad, grupos de bloqueo) - Gestión de accesos SQL | F100: Obs. Auditoría | G100: Daniel Lescano Richard Requelme | H100: 46210 | I100: 46239 | J100: 46239 | K100: 1 | L100: Se implementó el control de cambios CHG0775788 para las reglas de bloqueo de los grupos de AD | M100: PR.AA-05 | N100: =IFERROR(INDEX(dFrente!$B$2:$B$76,MATCH(C100,dFrente!$A$2:$A$76,0)),"Sin frente") -> Bases de datos y SFTP | O100: =IFERROR(INDEX(dNIST!$B$2:$B$13,MATCH(M100,dNIST!$A$2:$A$13,0)),"") -> PR | P100: =TRIM(IFERROR(LEFT(G100,FIND(CHAR(10),G100)-1),G100)) -> Daniel Lescano | Q100: =LEN(TRIM(G100))-LEN(SUBSTITUTE(TRIM(G100),CHAR(10),""))+1 -> 2 | R100: =IF(E100<>"","Sí","No") -> No | S100: =IF(OR(J100="",H100=""),"",IF(J100<=H100,IF(FechaCorte>=J100,1,0),MAX(0,MIN(1,(FechaCorte-H100)/(J100-H100))))) -> 1 | T100: =IF(S100="","",K100-S100) -> 0 | U100: =IF(R100="Sí","Recurrente",IF(K100>=1,"Completado",IF(AND(J100<>"",J100<FechaCorte),"Vencido",IF(AND(K100=0,OR(H100="",H100>FechaCorte)),"Por iniciar",IF(AND(T100<>"",T100<=UmbralRiesgo),"En riesgo","En plazo"))))) -> Completado | V100: =IF(OR(U100="Vencido",U100="En riesgo",U100="En plazo",U100="Por iniciar"),1,0) -> 0 | W100: =IF(U100="Vencido",FechaCorte-J100,"") | X100: =IF(AND(V100=1,U100<>"Vencido"),J100-FechaCorte,"") | Y100: =IF(J100="","",DATE(YEAR(J100),MONTH(J100),1)) -> 46235 | Z100: =IF(AND(U100="Completado",I100<>""),IF(I100<=FechaCorte,DATE(YEAR(I100),MONTH(I100),1),""),"") -> 46235 | AA100: =IF(J100="","",IF(DAY(J100+1)=1,1,0)) -> 0 | AB100: =IF(AND(U100="Completado",I100<>"",I100=J100),1,0) -> 1 | AC100: =IF(AND(K100>=1,I100<>""),IF(I100>FechaCorte,1,0),0) -> 0 | AD100: =IF(AND(I100<>"",H100<>""),IF(I100<H100,1,0),0) -> 0 | AE100: =IF(OR(F100="Riesgos",F100="Obs. Auditoría"),1,0) -> 1 | AF100: =IFERROR(MID(D100,FIND("PMC-",D100),8),"") | AG100: =IF(AND(V100=1,J100<>""),IF(AND(J100>=FechaCorte,J100<=HorizonteExpuestos),1,0),0) -> 0
...

Sheet Validacion
A1: Validación: KPIs calculados con fórmulas vs. valor publicado en el PDF
A2: La columna «Valor PDF» es el número impreso en el dashboard con corte 24-sep-2026. Si se cambia la fecha de corte, la diferencia deja de ser 0 y es lo esperado.
A4: Métrica | B4: Valor (fórmula) | C4: Valor PDF | D4: Diferencia | E4: Medida DAX equivalente | F4: Página PDF
A5: Hitos en el plan | B5: =COUNTA(fHitos!$A$2:$A$178) -> 177 | C5: 177 | D5: =IF(ABS(ROUND(B5,4)-C5)<=0.5,"OK",B5-C5) -> OK | E5: [Hitos Total] | F5: 1
A6: Hitos con fecha (no recurrentes) | B6: =COUNTIF(fHitos!$R$2:$R$178,"No") -> 155 | C6: 155 | D6: =IF(ABS(ROUND(B6,4)-C6)<=0.5,"OK",B6-C6) -> OK | E6: [Hitos con Fecha] | F6: 1
A7: Hitos recurrentes | B7: =COUNTIF(fHitos!$R$2:$R$178,"Sí") -> 22 | C7: 22 | D7: =IF(ABS(ROUND(B7,4)-C7)<=0.5,"OK",B7-C7) -> OK | E7: [Hitos Recurrentes] | F7: 1
A8: Completados | B8: =COUNTIF(fHitos!$U$2:$U$178,"Completado") -> 70 | C8: 70 | D8: =IF(ABS(ROUND(B8,4)-C8)<=0.5,"OK",B8-C8) -> OK | E8: [Hitos Completados] | F8: 1
A9: En plazo | B9: =COUNTIF(fHitos!$U$2:$U$178,"En plazo") -> 28 | C9: 28 | D9: =IF(ABS(ROUND(B9,4)-C9)<=0.5,"OK",B9-C9) -> OK | E9: [Hitos En Plazo] | F9: 1
A10: En riesgo | B10: =COUNTIF(fHitos!$U$2:$U$178,"En riesgo") -> 31 | C10: 31 | D10: =IF(ABS(ROUND(B10,4)-C10)<=0.5,"OK",B10-C10) -> OK | E10: [Hitos En Riesgo] | F10: 1
A11: Vencidos | B11: =COUNTIF(fHitos!$U$2:$U$178,"Vencido") -> 25 | C11: 25 | D11: =IF(ABS(ROUND(B11,4)-C11)<=0.5,"OK",B11-C11) -> OK | E11: [Hitos Vencidos] | F11: 1
A12: Por iniciar | B12: =COUNTIF(fHitos!$U$2:$U$178,"Por iniciar") -> 1 | C12: 1 | D12: =IF(ABS(ROUND(B12,4)-C12)<=0.5,"OK",B12-C12) -> OK | E12: [Hitos Por Iniciar] | F12: 1
A13: % completados sobre hitos con fecha | B13: =B8/B6 -> 0.4516129 | C13: 0.45 | D13: =IF(ABS(ROUND(B13,4)-C13)<=0.005,"OK",B13-C13) -> OK | E13: [% Completado] | F13: 1
A14: Avance real promedio | B14: =AVERAGEIF(fHitos!$R$2:$R$178,"No",fHitos!$K$2:$K$178) -> 0.67690323 | C14: 0.68 | D14: =IF(ABS(ROUND(B14,4)-C14)<=0.005,"OK",B14-C14) -> OK | E14: [Avance Real] | F14: 1
A15: Avance esperado promedio | B15: =AVERAGEIF(fHitos!$R$2:$R$178,"No",fHitos!$S$2:$S$178) -> 0.86487489 | C15: 0.86 | D15: =IF(ABS(ROUND(B15,4)-C15)<=0.005,"OK",B15-C15) -> OK | E15: [Avance Esperado] | F15: 1
A16: SPI | B16: =B14/B15 -> 0.78266028 | C16: 0.78 | D16: =IF(ABS(ROUND(B16,4)-C16)<=0.05,"OK",B16-C16) -> OK | E16: [SPI] | F16: 1
A17: Días de atraso promedio (vencidos) | B17: =AVERAGEIF(fHitos!$U$2:$U$178,"Vencido",fHitos!$W$2:$W$178) -> 37.36 | C17: 37 | D17: =IF(ABS(ROUND(B17,4)-C17)<=0.5,"OK",B17-C17) -> OK | E17: [Dias Atraso Promedio] | F17: 1
A18: Hitos abiertos | B18: =SUM(fHitos!$V$2:$V$178) -> 85 | C18: 85 | D18: =IF(ABS(ROUND(B18,4)-C18)<=0.5,"OK",B18-C18) -> OK | E18: [Hitos Abiertos] | F18: 2
A19: Cierres desde InicioRitmo hasta el corte | B19: =COUNTIFS(fHitos!$Z$2:$Z$178,">="&InicioRitmo,fHitos!$Z$2:$Z$178,"<="&FechaCorte) -> 60 | C19: 60 | D19: =IF(ABS(ROUND(B19,4)-C19)<=0.5,"OK",B19-C19) -> OK | E19: — | F19: 2
