Workbook

Sheet Parametros
A1: PARÁMETROS DEL MODELO — POA 2026
A3: Fecha de Corte | B3: 46258
A4: Umbral Verde (Gap ≤) | B4: 5
A5: Umbral Amarillo (Gap ≤) | B5: 20
A6: Umbral % Cierres Q4 (Riesgo) | B6: 55
A7: Umbral Brecha Q4 (Riesgo) | B7: 6
A9: Nota: las celdas amarillas son parámetros editables. Todo el modelo (Datos_POA, Resumen_Gerencias) recalcula automáticamente al cambiarlos.

Sheet Datos_POA
A1: Codigo | B1: Nombre_Iniciativa | C1: Actividad_Detallada | D1: Fecha_Inicio | E1: Fecha_Fin | F1: Avance_Real_Pct | G1: Avance_Esperado_Pct | H1: Gap_pp | I1: Semaforo | J1: Situacion | K1: Estado | L1: Usuario | M1: Gerencia_Responsable | N1: Tipo_Gestion | O1: Es_Q4 | P1: Es_Vencida | Q1: Es_Proxima_30d
A2: AR-01 | B2: IAM - Gestor de identidades interno (Fase 2) | C2: Habilitar el módulo para externos ""NERM"". Despliegue y estabilización en producción. Habilitar roles de Internos basados en el cargo de SSFF. Habilitar roles para Filiales (Acovi, App Deuna, Almesa, Vaserum) Despliegue, estabilización y entrega a operaciones Resolver deuda técnica integraciones" Eliminar dependencias WSO2: Desacoplar aplicaciones que usan la plataforma WSO2 (Servicios Omnicanalidad, login central, motor de transferencias, SGG, Portal 8) Apagado plataforma WSO2 | D2: 45383 | E2: 46689 | F2: 35 | G2: =IF(OR(D2="",E2="",E2<=D2),"",MIN(100,MAX(0,(Parametros!$B$3-D2)/(E2-D2)*100))) -> 66.998469 | H2: =IF(G2="","",G2-F2) -> 31.998469 | I2: =IF(K2="Finalizado","Verde",IF(G2="","Amarillo",IF(H2<=Parametros!$B$4,"Verde",IF(H2<=Parametros!$B$5,"Amarillo","Rojo")))) -> Rojo | J2: =IF(K2="Finalizado","Completado",IF(G2="","Sin fecha válida - revisar plazos",IF(H2<=Parametros!$B$4,"En tiempo, según lo planificado",IF(H2<=Parametros!$B$5,"Atraso leve - seguimiento cercano ("&TEXT(H2,"0.0")&" p.p.)","Atraso crítico - requiere intervención ("&TEXT(H2,"0.0")&" p.p.)")))) -> Atraso crítico - requiere intervención (32.0 p.p.) | K2: En ejecución | L2: VERDEZOTO GARCIA ROCIO PIEDAD;#29 | M2: COE Arquitectura | N2: Proyecto | O2: =IF(AND(E2<>"",YEAR(E2)=YEAR(Parametros!$B$3),MONTH(E2)>=10),1,0) -> 0 | P2: =IF(AND(E2<Parametros!$B$3,K2<>"Finalizado"),1,0) -> 0 | Q2: =IF(AND(E2>=Parametros!$B$3,E2<=Parametros!$B$3+30,K2<>"Finalizado"),1,0) -> 0
A3: AR-02 | B3: Adquisición e implementación herramienta de modelamiento de amenazas | C3: Integrar el modelamiento de amenazas en aplicaciones de Banco en base al número de licencias adquiridas | D3: 45658 | E3: 46387 | F3: 80 | G3: =IF(OR(D3="",E3="",E3<=D3),"",MIN(100,MAX(0,(Parametros!$B$3-D3)/(E3-D3)*100))) -> 82.304527 | H3: =IF(G3="","",G3-F3) -> 2.3045267 | I3: =IF(K3="Finalizado","Verde",IF(G3="","Amarillo",IF(H3<=Parametros!$B$4,"Verde",IF(H3<=Parametros!$B$5,"Amarillo","Rojo")))) -> Verde | J3: =IF(K3="Finalizado","Completado",IF(G3="","Sin fecha válida - revisar plazos",IF(H3<=Parametros!$B$4,"En tiempo, según lo planificado",IF(H3<=Parametros!$B$5,"Atraso leve - seguimiento cercano ("&TEXT(H3,"0.0")&" p.p.)","Atraso crítico - requiere intervención ("&TEXT(H3,"0.0")&" p.p.)")))) -> En tiempo, según lo planificado | K3: En ejecución | L3: BURGOS SHUGULI MARCELO VINICIO;#394 | M3: COE Arquitectura | N3: Proyecto | O3: =IF(AND(E3<>"",YEAR(E3)=YEAR(Parametros!$B$3),MONTH(E3)>=10),1,0) -> 1 | P3: =IF(AND(E3<Parametros!$B$3,K3<>"Finalizado"),1,0) -> 0 | Q3: =IF(AND(E3>=Parametros!$B$3,E3<=Parametros!$B$3+30,K3<>"Finalizado"),1,0) -> 0
A4: AR-03 | B4: Actualización de la plataforma de CyberArk (Fase1-Fase2) | C4: Cambio de versión a 14.x Switch de plataforma de módulos adicionales a la boveda Implementación PSMP en CyberArk v14.6 — Privileged Session Manager for SSH | D4: 45566 | E4: 46111 | F4: 100 | G4: =IF(OR(D4="",E4="",E4<=D4),"",MIN(100,MAX(0,(Parametros!$B$3-D4)/(E4-D4)*100))) -> 100 | H4: =IF(G4="","",G4-F4) -> 0 | I4: =IF(K4="Finalizado","Verde",IF(G4="","Amarillo",IF(H4<=Parametros!$B$4,"Verde",IF(H4<=Parametros!$B$5,"Amarillo","Rojo")))) -> Verde | J4: =IF(K4="Finalizado","Completado",IF(G4="","Sin fecha válida - revisar plazos",IF(H4<=Parametros!$B$4,"En tiempo, según lo planificado",IF(H4<=Parametros!$B$5,"Atraso leve - seguimiento cercano ("&TEXT(H4,"0.0")&" p.p.)","Atraso crítico - requiere intervención ("&TEXT(H4,"0.0")&" p.p.)")))) -> Completado | K4: Finalizado | L4: NOGALES LEON LUIS GUSTAVO;#17;#SOTO CORONEL ROBERT STALIN;#344 | M4: COE Arquitectura | N4: Proyecto | O4: =IF(AND(E4<>"",YEAR(E4)=YEAR(Parametros!$B$3),MONTH(E4)>=10),1,0) -> 0 | P4: =IF(AND(E4<Parametros!$B$3,K4<>"Finalizado"),1,0) -> 0 | Q4: =IF(AND(E4>=Parametros!$B$3,E4<=Parametros!$B$3+30,K4<>"Finalizado"),1,0) -> 0
A5: AR-04 | B5: IAM - Gestor de identidades interno (Fase 1) | C5: "1.1 Integración fuentes autoritativas: SSFF / NERM 1.2 Integración sistemas conectados: Bancs, Siglo21, RHDS, Logiflow 1.3 Integración sistemas no conectados - Service Now 1.4 Construcción Worflows ABM usuarios 1.5 Construcción Roles de Acceso" 1.6. Eliminar dependencias WSO2 - Desacoplar aplicaciones que usan la plataforma WSO2 (Servicios Omnicanalidad, login central, motor de transferencias, SGG, Portal 8) Apagado plataforma WSO2 | D5: 45383 | E5: 46111 | F5: 100 | G5: =IF(OR(D5="",E5="",E5<=D5),"",MIN(100,MAX(0,(Parametros!$B$3-D5)/(E5-D5)*100))) -> 100 | H5: =IF(G5="","",G5-F5) -> 0 | I5: =IF(K5="Finalizado","Verde",IF(G5="","Amarillo",IF(H5<=Parametros!$B$4,"Verde",IF(H5<=Parametros!$B$5,"Amarillo","Rojo")))) -> Verde | J5: =IF(K5="Finalizado","Completado",IF(G5="","Sin fecha válida - revisar plazos",IF(H5<=Parametros!$B$4,"En tiempo, según lo planificado",IF(H5<=Parametros!$B$5,"Atraso leve - seguimiento cercano ("&TEXT(H5,"0.0")&" p.p.)","Atraso crítico - requiere intervención ("&TEXT(H5,"0.0")&" p.p.)")))) -> Completado | K5: Finalizado | L5: RAMIREZ ESPINOSA CARLOS ALBERTO;#16;#VERDEZOTO GARCIA ROCIO PIEDAD;#29 | M5: COE Arquitectura | N5: Proyecto | O5: =IF(AND(E5<>"",YEAR(E5)=YEAR(Parametros!$B$3),MONTH(E5)>=10),1,0) -> 0 | P5: =IF(AND(E5<Parametros!$B$3,K5<>"Finalizado"),1,0) -> 0 | Q5: =IF(AND(E5>=Parametros!$B$3,E5<=Parametros!$B$3+30,K5<>"Finalizado"),1,0) -> 0
A6: AR-05 | B6: Gestión de Incidentes de Seguridad e Inteligencia de Amenazas - Service Now (Fase2) | C6: Ajuste funcionalidad SIR & TIP para el equipo de Respuesta a Incidentes usando la plataforma de Service Now y los módulos Secops | D6: 45383 | E6: 46202 | F6: 89 | G6: =IF(OR(D6="",E6="",E6<=D6),"",MIN(100,MAX(0,(Parametros!$B$3-D6)/(E6-D6)*100))) -> 100 | H6: =IF(G6="","",G6-F6) -> 11 | I6: =IF(K6="Finalizado","Verde",IF(G6="","Amarillo",IF(H6<=Parametros!$B$4,"Verde",IF(H6<=Parametros!$B$5,"Amarillo","Rojo")))) -> Amarillo | J6: =IF(K6="Finalizado","Completado",IF(G6="","Sin fecha válida - revisar plazos",IF(H6<=Parametros!$B$4,"En tiempo, según lo planificado",IF(H6<=Parametros!$B$5,"Atraso leve - seguimiento cercano ("&TEXT(H6,"0.0")&" p.p.)","Atraso crítico - requiere intervención ("&TEXT(H6,"0.0")&" p.p.)")))) -> Atraso leve - seguimiento cercano (11.0 p.p.) | K6: En ejecución | L6: SILVA PROANO SANTIAGO DAVID;#389 | M6: COE Arquitectura | N6: Proyecto | O6: =IF(AND(E6<>"",YEAR(E6)=YEAR(Parametros!$B$3),MONTH(E6)>=10),1,0) -> 0 | P6: =IF(AND(E6<Parametros!$B$3,K6<>"Finalizado"),1,0) -> 1 | Q6: =IF(AND(E6>=Parametros!$B$3,E6<=Parametros!$B$3+30,K6<>"Finalizado"),1,0) -> 0
A7: AR-06 | B7: Optimización procedimiento de evaluación de plantilla Línea Base | C7: Despliegue de los componentes de CIS CAT Pro en Infraestructura On-premise de Banco Pichincha | D7: 46027 | E7: 46295 | F7: 90 | G7: =IF(OR(D7="",E7="",E7<=D7),"",MIN(100,MAX(0,(Parametros!$B$3-D7)/(E7-D7)*100))) -> 86.19403 | H7: =IF(G7="","",G7-F7) -> -3.8059701 | I7: =IF(K7="Finalizado","Verde",IF(G7="","Amarillo",IF(H7<=Parametros!$B$4,"Verde",IF(H7<=Parametros!$B$5,"Amarillo","Rojo")))) -> Verde | J7: =IF(K7="Finalizado","Completado",IF(G7="","Sin fecha válida - revisar plazos",IF(H7<=Parametros!$B$4,"En tiempo, según lo planificado",IF(H7<=Parametros!$B$5,"Atraso leve - seguimiento cercano ("&TEXT(H7,"0.0")&" p.p.)","Atraso crítico - requiere intervención ("&TEXT(H7,"0.0")&" p.p.)")))) -> En tiempo, según lo planificado | K7: En ejecución | L7: SILVA PROANO SANTIAGO DAVID;#389 | M7: COE Arquitectura | N7: POA | O7: =IF(AND(E7<>"",YEAR(E7)=YEAR(Parametros!$B$3),MONTH(E7)>=10),1,0) -> 0 | P7: =IF(AND(E7<Parametros!$B$3,K7<>"Finalizado"),1,0) -> 0 | Q7: =IF(AND(E7>=Parametros!$B$3,E7<=Parametros!$B$3+30,K7<>"Finalizado"),1,0) -> 0
A8: AR-07 | B8: Reestructurar los estandares Windows y Linux para mejorar el proceso de medición de configuraciones de Ciberseguridad | C8: Creación de estándar para Servidores Members Server, AD Servers y Windows 2025 | D8: 46027 | E8: 46234 | F8: 100 | G8: =IF(OR(D8="",E8="",E8<=D8),"",MIN(100,MAX(0,(Parametros!$B$3-D8)/(E8-D8)*100))) -> 100 | H8: =IF(G8="","",G8-F8) -> 0 | I8: =IF(K8="Finalizado","Verde",IF(G8="","Amarillo",IF(H8<=Parametros!$B$4,"Verde",IF(H8<=Parametros!$B$5,"Amarillo","Rojo")))) -> Verde | J8: =IF(K8="Finalizado","Completado",IF(G8="","Sin fecha válida - revisar plazos",IF(H8<=Parametros!$B$4,"En tiempo, según lo planificado",IF(H8<=Parametros!$B$5,"Atraso leve - seguimiento cercano ("&TEXT(H8,"0.0")&" p.p.)","Atraso crítico - requiere intervención ("&TEXT(H8,"0.0")&" p.p.)")))) -> Completado | K8: Finalizado | L8: SILVA PROANO SANTIAGO DAVID;#389 | M8: COE Arquitectura | N8: POA | O8: =IF(AND(E8<>"",YEAR(E8)=YEAR(Parametros!$B$3),MONTH(E8)>=10),1,0) -> 0 | P8: =IF(AND(E8<Parametros!$B$3,K8<>"Finalizado"),1,0) -> 0 | Q8: =IF(AND(E8>=Parametros!$B$3,E8<=Parametros!$B$3+30,K8<>"Finalizado"),1,0) -> 0
A9: AR-08 | B9: Mejora del proceso de Gestión de Software Utilitario - Integración con el proceso de Software Utilitario de TI (Workplace) | C9: Integración con el proceso de TI, para gestión centralizada del Software Utilitario de Usuarios Finales | D9: 46027 | E9: 46234 | F9: 100 | G9: =IF(OR(D9="",E9="",E9<=D9),"",MIN(100,MAX(0,(Parametros!$B$3-D9)/(E9-D9)*100))) -> 100 | H9: =IF(G9="","",G9-F9) -> 0 | I9: =IF(K9="Finalizado","Verde",IF(G9="","Amarillo",IF(H9<=Parametros!$B$4,"Verde",IF(H9<=Parametros!$B$5,"Amarillo","Rojo")))) -> Verde | J9: =IF(K9="Finalizado","Completado",IF(G9="","Sin fecha válida - revisar plazos",IF(H9<=Parametros!$B$4,"En tiempo, según lo planificado",IF(H9<=Parametros!$B$5,"Atraso leve - seguimiento cercano ("&TEXT(H9,"0.0")&" p.p.)","Atraso crítico - requiere intervención ("&TEXT(H9,"0.0")&" p.p.)")))) -> Completado | K9: Finalizado | L9: SILVA PROANO SANTIAGO DAVID;#389 | M9: COE Arquitectura | N9: POA | O9: =IF(AND(E9<>"",YEAR(E9)=YEAR(Parametros!$B$3),MONTH(E9)>=10),1,0) -> 0 | P9: =IF(AND(E9<Parametros!$B$3,K9<>"Finalizado"),1,0) -> 0 | Q9: =IF(AND(E9>=Parametros!$B$3,E9<=Parametros!$B$3+30,K9<>"Finalizado"),1,0) -> 0
A10: AR-09 | B10: Mejora Proceso SSDLC | C10: "Ampliar la cobertura de SAST y DAST Optimizar el control dinamico con DAST Acompañar al equipo de Devops a la plataforma de GitHub" | D10: 45719 | E10: 46568 | F10: 58 | G10: =IF(OR(D10="",E10="",E10<=D10),"",MIN(100,MAX(0,(Parametros!$B$3-D10)/(E10-D10)*100))) -> 63.486455 | H10: =IF(G10="","",G10-F10) -> 5.4864547 | I10: =IF(K10="Finalizado","Verde",IF(G10="","Amarillo",IF(H10<=Parametros!$B$4,"Verde",IF(H10<=Parametros!$B$5,"Amarillo","Rojo")))) -> Amarillo | J10: =IF(K10="Finalizado","Completado",IF(G10="","Sin fecha válida - revisar plazos",IF(H10<=Parametros!$B$4,"En tiempo, según lo planificado",IF(H10<=Parametros!$B$5,"Atraso leve - seguimiento cercano ("&TEXT(H10,"0.0")&" p.p.)","Atraso crítico - requiere intervención ("&TEXT(H10,"0.0")&" p.p.)")))) -> Atraso leve - seguimiento cercano (5.5 p.p.) | K10: En ejecución | L10: GUEVARA LOPEZ SALOMON DARIO;#380 | M10: COE Arquitectura | N10: POA | O10: =IF(AND(E10<>"",YEAR(E10)=YEAR(Parametros!$B$3),MONTH(E10)>=10),1,0) -> 0 | P10: =IF(AND(E10<Parametros!$B$3,K10<>"Finalizado"),1,0) -> 0 | Q10: =IF(AND(E10>=Parametros!$B$3,E10<=Parametros!$B$3+30,K10<>"Finalizado"),1,0) -> 0
A11: AR-10 | B11: HARDWARE IPS & FIREWALL | C11: Despliegue de Infraestructura Palo Alto en los siguientes entornos: EnP, Terceros y Filiales | D11: 45366 | E11: 46965 | F11: 60 | G11: =IF(OR(D11="",E11="",E11<=D11),"",MIN(100,MAX(0,(Parametros!$B$3-D11)/(E11-D11)*100))) -> 55.784866 | H11: =IF(G11="","",G11-F11) -> -4.2151345 | I11: =IF(K11="Finalizado","Verde",IF(G11="","Amarillo",IF(H11<=Parametros!$B$4,"Verde",IF(H11<=Parametros!$B$5,"Amarillo","Rojo")))) -> Verde | J11: =IF(K11="Finalizado","Completado",IF(G11="","Sin fecha válida - revisar plazos",IF(H11<=Parametros!$B$4,"En tiempo, según lo planificado",IF(H11<=Parametros!$B$5,"Atraso leve - seguimiento cercano ("&TEXT(H11,"0.0")&" p.p.)","Atraso crítico - requiere intervención ("&TEXT(H11,"0.0")&" p.p.)")))) -> En tiempo, según lo planificado | K11: En ejecución | L11: PUNINA CORDOVA CARINA PRISCILA;#393 | M11: COE Arquitectura | N11: Proyecto | O11: =IF(AND(E11<>"",YEAR(E11)=YEAR(Parametros!$B$3),MONTH(E11)>=10),1,0) -> 0 | P11: =IF(AND(E11<Parametros!$B$3,K11<>"Finalizado"),1,0) -> 0 | Q11: =IF(AND(E11>=Parametros!$B$3,E11<=Parametros!$B$3+30,K11<>"Finalizado"),1,0) -> 0
A12: AR-12 | B12: Extender los controles de seguridad Cloud - Firewall Palo Alto Azure (Fase 1 - Azure Inicio Fase 2) | C12: Despliegue en Nube Azure de EnP y Productivo | D12: 46037 | E12: 46387 | F12: 100 | G12: =IF(OR(D12="",E12="",E12<=D12),"",MIN(100,MAX(0,(Parametros!$B$3-D12)/(E12-D12)*100))) -> 63.142857 | H12: =IF(G12="","",G12-F12) -> -36.857143 | I12: =IF(K12="Finalizado","Verde",IF(G12="","Amarillo",IF(H12<=Parametros!$B$4,"Verde",IF(H12<=Parametros!$B$5,"Amarillo","Rojo")))) -> Verde | J12: =IF(K12="Finalizado","Completado",IF(G12="","Sin fecha válida - revisar plazos",IF(H12<=Parametros!$B$4,"En tiempo, según lo planificado",IF(H12<=Parametros!$B$5,"Atraso leve - seguimiento cercano ("&TEXT(H12,"0.0")&" p.p.)","Atraso crítico - requiere intervención ("&TEXT(H12,"0.0")&" p.p.)")))) -> Completado | K12: Finalizado | L12: NOGALES LEON LUIS GUSTAVO;#17 | M12: COE Arquitectura | N12: Proyecto | O12: =IF(AND(E12<>"",YEAR(E12)=YEAR(Parametros!$B$3),MONTH(E12)>=10),1,0) -> 1 | P12: =IF(AND(E12<Parametros!$B$3,K12<>"Finalizado"),1,0) -> 0 | Q12: =IF(AND(E12>=Parametros!$B$3,E12<=Parametros!$B$3+30,K12<>"Finalizado"),1,0) -> 0
A13: AR-13 | B13: Gestor de Vulnerabilidades | C13: Repotenciar el gestor de vulnerabilidades | D13: 46037 | E13: 46387 | F13: 10 | G13: =IF(OR(D13="",E13="",E13<=D13),"",MIN(100,MAX(0,(Parametros!$B$3-D13)/(E13-D13)*100))) -> 63.142857 | H13: =IF(G13="","",G13-F13) -> 53.142857 | I13: =IF(K13="Finalizado","Verde",IF(G13="","Amarillo",IF(H13<=Parametros!$B$4,"Verde",IF(H13<=Parametros!$B$5,"Amarillo","Rojo")))) -> Rojo | J13: =IF(K13="Finalizado","Completado",IF(G13="","Sin fecha válida - revisar plazos",IF(H13<=Parametros!$B$4,"En tiempo, según lo planificado",IF(H13<=Parametros!$B$5,"Atraso leve - seguimiento cercano ("&TEXT(H13,"0.0")&" p.p.)","Atraso crítico - requiere intervención ("&TEXT(H13,"0.0")&" p.p.)")))) -> Atraso crítico - requiere intervención (53.1 p.p.) | K13: Iniciado | L13: NOGALES LEON LUIS GUSTAVO;#17 | M13: COE Arquitectura | N13: Proyecto | O13: =IF(AND(E13<>"",YEAR(E13)=YEAR(Parametros!$B$3),MONTH(E13)>=10),1,0) -> 1 | P13: =IF(AND(E13<Parametros!$B$3,K13<>"Finalizado"),1,0) -> 0 | Q13: =IF(AND(E13>=Parametros!$B$3,E13<=Parametros!$B$3+30,K13<>"Finalizado"),1,0) -> 0
A14: AR-14 | B14: Control de Acceso a Información IRM | C14: Configuración y publicación de etiquetado de información de Office 365 en formatos de archivos soportados por la herramienta. Despliegue de agentes Purview en los equipos Windows de maqueta de Banco. | D14: 45658 | E14: 46111 | F14: 98 | G14: =IF(OR(D14="",E14="",E14<=D14),"",MIN(100,MAX(0,(Parametros!$B$3-D14)/(E14-D14)*100))) -> 100 | H14: =IF(G14="","",G14-F14) -> 2 | I14: =IF(K14="Finalizado","Verde",IF(G14="","Amarillo",IF(H14<=Parametros!$B$4,"Verde",IF(H14<=Parametros!$B$5,"Amarillo","Rojo")))) -> Verde | J14: =IF(K14="Finalizado","Completado",IF(G14="","Sin fecha válida - revisar plazos",IF(H14<=Parametros!$B$4,"En tiempo, según lo planificado",IF(H14<=Parametros!$B$5,"Atraso leve - seguimiento cercano ("&TEXT(H14,"0.0")&" p.p.)","Atraso crítico - requiere intervención ("&TEXT(H14,"0.0")&" p.p.)")))) -> En tiempo, según lo planificado | K14: En ejecución | L14: EXTERNO RODRIGUEZ VARILLAS ABRAHAM JESUS;#390;#EXTERNO RIERA CHAVEZ MARIO ALBERTO;#466 | M14: COE Arquitectura | N14: POA | O14: =IF(AND(E14<>"",YEAR(E14)=YEAR(Parametros!$B$3),MONTH(E14)>=10),1,0) -> 0 | P14: =IF(AND(E14<Parametros!$B$3,K14<>"Finalizado"),1,0) -> 1 | Q14: =IF(AND(E14>=Parametros!$B$3,E14<=Parametros!$B$3+30,K14<>"Finalizado"),1,0) -> 0
A15: CD-01 | B15: Despliegue MISP Banco Pichincha en la nube empresarial | C15: 1. Despliegue de MISP en ambiente TEST. | D15: 46023 | E15: 46173 | F15: 100 | G15: =IF(OR(D15="",E15="",E15<=D15),"",MIN(100,MAX(0,(Parametros!$B$3-D15)/(E15-D15)*100))) -> 100 | H15: =IF(G15="","",G15-F15) -> 0 | I15: =IF(K15="Finalizado","Verde",IF(G15="","Amarillo",IF(H15<=Parametros!$B$4,"Verde",IF(H15<=Parametros!$B$5,"Amarillo","Rojo")))) -> Verde | J15: =IF(K15="Finalizado","Completado",IF(G15="","Sin fecha válida - revisar plazos",IF(H15<=Parametros!$B$4,"En tiempo, según lo planificado",IF(H15<=Parametros!$B$5,"Atraso leve - seguimiento cercano ("&TEXT(H15,"0.0")&" p.p.)","Atraso crítico - requiere intervención ("&TEXT(H15,"0.0")&" p.p.)")))) -> Completado | K15: Finalizado | M15: Ciberdefensa | N15: POA | O15: =IF(AND(E15<>"",YEAR(E15)=YEAR(Parametros!$B$3),MONTH(E15)>=10),1,0) -> 0 | P15: =IF(AND(E15<Parametros!$B$3,K15<>"Finalizado"),1,0) -> 0 | Q15: =IF(AND(E15>=Parametros!$B$3,E15<=Parametros!$B$3+30,K15<>"Finalizado"),1,0) -> 0
A16: CD-01 | B16: Despliegue MISP Banco Pichincha en la nube empresarial | C16: 2. Despliegue de MISP en ambiente PRODUCCIÓN. | D16: 46174 | E16: 46387 | F16: 50 | G16: =IF(OR(D16="",E16="",E16<=D16),"",MIN(100,MAX(0,(Parametros!$B$3-D16)/(E16-D16)*100))) -> 39.43662 | H16: =IF(G16="","",G16-F16) -> -10.56338 | I16: =IF(K16="Finalizado","Verde",IF(G16="","Amarillo",IF(H16<=Parametros!$B$4,"Verde",IF(H16<=Parametros!$B$5,"Amarillo","Rojo")))) -> Verde | J16: =IF(K16="Finalizado","Completado",IF(G16="","Sin fecha válida - revisar plazos",IF(H16<=Parametros!$B$4,"En tiempo, según lo planificado",IF(H16<=Parametros!$B$5,"Atraso leve - seguimiento cercano ("&TEXT(H16,"0.0")&" p.p.)","Atraso crítico - requiere intervención ("&TEXT(H16,"0.0")&" p.p.)")))) -> En tiempo, según lo planificado | K16: En ejecución | M16: Ciberdefensa | N16: POA | O16: =IF(AND(E16<>"",YEAR(E16)=YEAR(Parametros!$B$3),MONTH(E16)>=10),1,0) -> 1 | P16: =IF(AND(E16<Parametros!$B$3,K16<>"Finalizado"),1,0) -> 0 | Q16: =IF(AND(E16>=Parametros!$B$3,E16<=Parametros!$B$3+30,K16<>"Finalizado"),1,0) -> 0
A17: CD-02 | B17: Integración de Ciberinteligencia y Monitoreo Marca Corporativa | C17: 1. Actualización del instructivo de gestión de ciberinteligencia. | D17: 46023 | E17: 46142 | F17: 100 | G17: =IF(OR(D17="",E17="",E17<=D17),"",MIN(100,MAX(0,(Parametros!$B$3-D17)/(E17-D17)*100))) -> 100 | H17: =IF(G17="","",G17-F17) -> 0 | I17: =IF(K17="Finalizado","Verde",IF(G17="","Amarillo",IF(H17<=Parametros!$B$4,"Verde",IF(H17<=Parametros!$B$5,"Amarillo","Rojo")))) -> Verde | J17: =IF(K17="Finalizado","Completado",IF(G17="","Sin fecha válida - revisar plazos",IF(H17<=Parametros!$B$4,"En tiempo, según lo planificado",IF(H17<=Parametros!$B$5,"Atraso leve - seguimiento cercano ("&TEXT(H17,"0.0")&" p.p.)","Atraso crítico - requiere intervención ("&TEXT(H17,"0.0")&" p.p.)")))) -> Completado | K17: Finalizado | M17: Ciberdefensa | N17: POA | O17: =IF(AND(E17<>"",YEAR(E17)=YEAR(Parametros!$B$3),MONTH(E17)>=10),1,0) -> 0 | P17: =IF(AND(E17<Parametros!$B$3,K17<>"Finalizado"),1,0) -> 0 | Q17: =IF(AND(E17>=Parametros!$B$3,E17<=Parametros!$B$3+30,K17<>"Finalizado"),1,0) -> 0
A18: CD-02 | B18: Integración de Ciberinteligencia y Monitoreo Marca Corporativa | C18: 2. Ejecución de la producción de informes de ciberinteligencia para el área de marca corporativa. | D18: 46143 | E18: 46387 | F18: 25 | G18: =IF(OR(D18="",E18="",E18<=D18),"",MIN(100,MAX(0,(Parametros!$B$3-D18)/(E18-D18)*100))) -> 47.131148 | H18: =IF(G18="","",G18-F18) -> 22.131148 | I18: =IF(K18="Finalizado","Verde",IF(G18="","Amarillo",IF(H18<=Parametros!$B$4,"Verde",IF(H18<=Parametros!$B$5,"Amarillo","Rojo")))) -> Rojo | J18: =IF(K18="Finalizado","Completado",IF(G18="","Sin fecha válida - revisar plazos",IF(H18<=Parametros!$B$4,"En tiempo, según lo planificado",IF(H18<=Parametros!$B$5,"Atraso leve - seguimiento cercano ("&TEXT(H18,"0.0")&" p.p.)","Atraso crítico - requiere intervención ("&TEXT(H18,"0.0")&" p.p.)")))) -> Atraso crítico - requiere intervención (22.1 p.p.) | K18: En ejecución | M18: Ciberdefensa | N18: POA | O18: =IF(AND(E18<>"",YEAR(E18)=YEAR(Parametros!$B$3),MONTH(E18)>=10),1,0) -> 1 | P18: =IF(AND(E18<Parametros!$B$3,K18<>"Finalizado"),1,0) -> 0 | Q18: =IF(AND(E18>=Parametros!$B$3,E18<=Parametros!$B$3+30,K18<>"Finalizado"),1,0) -> 0
A19: CD-02 | B19: Integración de Ciberinteligencia y Monitoreo Marca Corporativa | C19: Conectar los procesos de Ciberinteligencia con el manejo de marca corporativa conceptualizando la relación como área consumidora de los productos de inteligencia relacionadas al monitoreo de marca. | D19: 46023 | E19: 46387 | F19: 62.5 | G19: =IF(OR(D19="",E19="",E19<=D19),"",MIN(100,MAX(0,(Parametros!$B$3-D19)/(E19-D19)*100))) -> 64.56044 | H19: =IF(G19="","",G19-F19) -> 2.0604396 | I19: =IF(K19="Finalizado","Verde",IF(G19="","Amarillo",IF(H19<=Parametros!$B$4,"Verde",IF(H19<=Parametros!$B$5,"Amarillo","Rojo")))) -> Verde | J19: =IF(K19="Finalizado","Completado",IF(G19="","Sin fecha válida - revisar plazos",IF(H19<=Parametros!$B$4,"En tiempo, según lo planificado",IF(H19<=Parametros!$B$5,"Atraso leve - seguimiento cercano ("&TEXT(H19,"0.0")&" p.p.)","Atraso crítico - requiere intervención ("&TEXT(H19,"0.0")&" p.p.)")))) -> En tiempo, según lo planificado | K19: En ejecución | L19: ZULES ACOSTA FABRICIO ANDRES;#349 | M19: Ciberdefensa | N19: POA | O19: =IF(AND(E19<>"",YEAR(E19)=YEAR(Parametros!$B$3),MONTH(E19)>=10),1,0) -> 1 | P19: =IF(AND(E19<Parametros!$B$3,K19<>"Finalizado"),1,0) -> 0 | Q19: =IF(AND(E19>=Parametros!$B$3,E19<=Parametros!$B$3+30,K19<>"Finalizado"),1,0) -> 0
A20: CD-03 | B20: Automatización de actividades en cacería de amenazas | C20: 1. Definición, diseño y despliegue de la automatización de la fase de ejecución de cacería de amenazas para al menos 20 ejercicios con información de 1 plataforma de ciberseguridad (EDR). | D20: 46023 | E20: 46203 | F20: 100 | G20: =IF(OR(D20="",E20="",E20<=D20),"",MIN(100,MAX(0,(Parametros!$B$3-D20)/(E20-D20)*100))) -> 100 | H20: =IF(G20="","",G20-F20) -> 0 | I20: =IF(K20="Finalizado","Verde",IF(G20="","Amarillo",IF(H20<=Parametros!$B$4,"Verde",IF(H20<=Parametros!$B$5,"Amarillo","Rojo")))) -> Verde | J20: =IF(K20="Finalizado","Completado",IF(G20="","Sin fecha válida - revisar plazos",IF(H20<=Parametros!$B$4,"En tiempo, según lo planificado",IF(H20<=Parametros!$B$5,"Atraso leve - seguimiento cercano ("&TEXT(H20,"0.0")&" p.p.)","Atraso crítico - requiere intervención ("&TEXT(H20,"0.0")&" p.p.)")))) -> Completado | K20: Finalizado | M20: Ciberdefensa | N20: POA | O20: =IF(AND(E20<>"",YEAR(E20)=YEAR(Parametros!$B$3),MONTH(E20)>=10),1,0) -> 0 | P20: =IF(AND(E20<Parametros!$B$3,K20<>"Finalizado"),1,0) -> 0 | Q20: =IF(AND(E20>=Parametros!$B$3,E20<=Parametros!$B$3+30,K20<>"Finalizado"),1,0) -> 0
A21: CD-03 | B21: Automatización de actividades en cacería de amenazas | C21: 2. Validación, optimización y medición de la automatización de la fase de ejecución de cacería de amenazas para al menos 20 ejercicios con información de 1 plataforma de ciberseguridad (EDR). | D21: 46204 | E21: 46387 | F21: 15 | G21: =IF(OR(D21="",E21="",E21<=D21),"",MIN(100,MAX(0,(Parametros!$B$3-D21)/(E21-D21)*100))) -> 29.508197 | H21: =IF(G21="","",G21-F21) -> 14.508197 | I21: =IF(K21="Finalizado","Verde",IF(G21="","Amarillo",IF(H21<=Parametros!$B$4,"Verde",IF(H21<=Parametros!$B$5,"Amarillo","Rojo")))) -> Amarillo | J21: =IF(K21="Finalizado","Completado",IF(G21="","Sin fecha válida - revisar plazos",IF(H21<=Parametros!$B$4,"En tiempo, según lo planificado",IF(H21<=Parametros!$B$5,"Atraso leve - seguimiento cercano ("&TEXT(H21,"0.0")&" p.p.)","Atraso crítico - requiere intervención ("&TEXT(H21,"0.0")&" p.p.)")))) -> Atraso leve - seguimiento cercano (14.5 p.p.) | K21: En ejecución | M21: Ciberdefensa | N21: POA | O21: =IF(AND(E21<>"",YEAR(E21)=YEAR(Parametros!$B$3),MONTH(E21)>=10),1,0) -> 1 | P21: =IF(AND(E21<Parametros!$B$3,K21<>"Finalizado"),1,0) -> 0 | Q21: =IF(AND(E21>=Parametros!$B$3,E21<=Parametros!$B$3+30,K21<>"Finalizado"),1,0) -> 0
A22: CD-03 | B22: Automatización de actividades en cacería de amenazas | C22: Automatizar la fase de ejecución de cacería de amenazas para al menos 20 ejercicios con información de 1 plataforma de ciberseguridad (EDR). | D22: 46023 | E22: 46387 | F22: 57.5 | G22: =IF(OR(D22="",E22="",E22<=D22),"",MIN(100,MAX(0,(Parametros!$B$3-D22)/(E22-D22)*100))) -> 64.56044 | H22: =IF(G22="","",G22-F22) -> 7.0604396 | I22: =IF(K22="Finalizado","Verde",IF(G22="","Amarillo",IF(H22<=Parametros!$B$4,"Verde",IF(H22<=Parametros!$B$5,"Amarillo","Rojo")))) -> Amarillo | J22: =IF(K22="Finalizado","Completado",IF(G22="","Sin fecha válida - revisar plazos",IF(H22<=Parametros!$B$4,"En tiempo, según lo planificado",IF(H22<=Parametros!$B$5,"Atraso leve - seguimiento cercano ("&TEXT(H22,"0.0")&" p.p.)","Atraso crítico - requiere intervención ("&TEXT(H22,"0.0")&" p.p.)")))) -> Atraso leve - seguimiento cercano (7.1 p.p.) | K22: En ejecución | L22: ZULES ACOSTA FABRICIO ANDRES;#349 | M22: Ciberdefensa | N22: POA | O22: =IF(AND(E22<>"",YEAR(E22)=YEAR(Parametros!$B$3),MONTH(E22)>=10),1,0) -> 1 | P22: =IF(AND(E22<Parametros!$B$3,K22<>"Finalizado"),1,0) -> 0 | Q22: =IF(AND(E22>=Parametros!$B$3,E22<=Parametros!$B$3+30,K22<>"Finalizado"),1,0) -> 0
A23: CD-04 | B23: Implementación del Dashboard - Normalidad, Alerta y Crisis | C23: Arquitectura y ambiente Splunk | D23: 46078 | E23: 46087 | F23: 100 | G23: =IF(OR(D23="",E23="",E23<=D23),"",MIN(100,MAX(0,(Parametros!$B$3-D23)/(E23-D23)*100))) -> 100 | H23: =IF(G23="","",G23-F23) -> 0 | I23: =IF(K23="Finalizado","Verde",IF(G23="","Amarillo",IF(H23<=Parametros!$B$4,"Verde",IF(H23<=Parametros!$B$5,"Amarillo","Rojo")))) -> Verde | J23: =IF(K23="Finalizado","Completado",IF(G23="","Sin fecha válida - revisar plazos",IF(H23<=Parametros!$B$4,"En tiempo, según lo planificado",IF(H23<=Parametros!$B$5,"Atraso leve - seguimiento cercano ("&TEXT(H23,"0.0")&" p.p.)","Atraso crítico - requiere intervención ("&TEXT(H23,"0.0")&" p.p.)")))) -> Completado | K23: Finalizado | M23: Ciberdefensa | N23: POA | O23: =IF(AND(E23<>"",YEAR(E23)=YEAR(Parametros!$B$3),MONTH(E23)>=10),1,0) -> 0 | P23: =IF(AND(E23<Parametros!$B$3,K23<>"Finalizado"),1,0) -> 0 | Q23: =IF(AND(E23>=Parametros!$B$3,E23<=Parametros!$B$3+30,K23<>"Finalizado"),1,0) -> 0
A24: CD-04 | B24: Implementación del Dashboard - Normalidad, Alerta y Crisis | C24: Automatización y alertamiento | D24: 46222 | E24: 46276 | F24: 25 | G24: =IF(OR(D24="",E24="",E24<=D24),"",MIN(100,MAX(0,(Parametros!$B$3-D24)/(E24-D24)*100))) -> 66.666667 | H24: =IF(G24="","",G24-F24) -> 41.666667 | I24: =IF(K24="Finalizado","Verde",IF(G24="","Amarillo",IF(H24<=Parametros!$B$4,"Verde",IF(H24<=Parametros!$B$5,"Amarillo","Rojo")))) -> Rojo | J24: =IF(K24="Finalizado","Completado",IF(G24="","Sin fecha válida - revisar plazos",IF(H24<=Parametros!$B$4,"En tiempo, según lo planificado",IF(H24<=Parametros!$B$5,"Atraso leve - seguimiento cercano ("&TEXT(H24,"0.0")&" p.p.)","Atraso crítico - requiere intervención ("&TEXT(H24,"0.0")&" p.p.)")))) -> Atraso crítico - requiere intervención (41.7 p.p.) | K24: En ejecución | M24: Ciberdefensa | N24: POA | O24: =IF(AND(E24<>"",YEAR(E24)=YEAR(Parametros!$B$3),MONTH(E24)>=10),1,0) -> 0 | P24: =IF(AND(E24<Parametros!$B$3,K24<>"Finalizado"),1,0) -> 0 | Q24: =IF(AND(E24>=Parametros!$B$3,E24<=Parametros!$B$3+30,K24<>"Finalizado"),1,0) -> 1
A25: CD-04 | B25: Implementación del Dashboard - Normalidad, Alerta y Crisis | C25: Capacitación y adopción | D25: 46155 | E25: 46164 | F25: 100 | G25: =IF(OR(D25="",E25="",E25<=D25),"",MIN(100,MAX(0,(Parametros!$B$3-D25)/(E25-D25)*100))) -> 100 | H25: =IF(G25="","",G25-F25) -> 0 | I25: =IF(K25="Finalizado","Verde",IF(G25="","Amarillo",IF(H25<=Parametros!$B$4,"Verde",IF(H25<=Parametros!$B$5,"Amarillo","Rojo")))) -> Verde | J25: =IF(K25="Finalizado","Completado",IF(G25="","Sin fecha válida - revisar plazos",IF(H25<=Parametros!$B$4,"En tiempo, según lo planificado",IF(H25<=Parametros!$B$5,"Atraso leve - seguimiento cercano ("&TEXT(H25,"0.0")&" p.p.)","Atraso crítico - requiere intervención ("&TEXT(H25,"0.0")&" p.p.)")))) -> Completado | K25: Finalizado | M25: Ciberdefensa | N25: POA | O25: =IF(AND(E25<>"",YEAR(E25)=YEAR(Parametros!$B$3),MONTH(E25)>=10),1,0) -> 0 | P25: =IF(AND(E25<Parametros!$B$3,K25<>"Finalizado"),1,0) -> 0 | Q25: =IF(AND(E25>=Parametros!$B$3,E25<=Parametros!$B$3+30,K25<>"Finalizado"),1,0) -> 0
A26: CD-04 | B26: Implementación del Dashboard - Normalidad, Alerta y Crisis | C26: Cierre del proyecto | D26: 46266 | E26: 46295 | F26: 0 | G26: =IF(OR(D26="",E26="",E26<=D26),"",MIN(100,MAX(0,(Parametros!$B$3-D26)/(E26-D26)*100))) -> 0 | H26: =IF(G26="","",G26-F26) -> 0 | I26: =IF(K26="Finalizado","Verde",IF(G26="","Amarillo",IF(H26<=Parametros!$B$4,"Verde",IF(H26<=Parametros!$B$5,"Amarillo","Rojo")))) -> Verde | J26: =IF(K26="Finalizado","Completado",IF(G26="","Sin fecha válida - revisar plazos",IF(H26<=Parametros!$B$4,"En tiempo, según lo planificado",IF(H26<=Parametros!$B$5,"Atraso leve - seguimiento cercano ("&TEXT(H26,"0.0")&" p.p.)","Atraso crítico - requiere intervención ("&TEXT(H26,"0.0")&" p.p.)")))) -> En tiempo, según lo planificado | K26: No iniciado | M26: Ciberdefensa | N26: POA | O26: =IF(AND(E26<>"",YEAR(E26)=YEAR(Parametros!$B$3),MONTH(E26)>=10),1,0) -> 0 | P26: =IF(AND(E26<Parametros!$B$3,K26<>"Finalizado"),1,0) -> 0 | Q26: =IF(AND(E26>=Parametros!$B$3,E26<=Parametros!$B$3+30,K26<>"Finalizado"),1,0) -> 0
A27: CD-04 | B27: Implementación del Dashboard - Normalidad, Alerta y Crisis | C27: Construcción del Dashboard | D27: 46084 | E27: 46115 | F27: 100 | G27: =IF(OR(D27="",E27="",E27<=D27),"",MIN(100,MAX(0,(Parametros!$B$3-D27)/(E27-D27)*100))) -> 100 | H27: =IF(G27="","",G27-F27) -> 0 | I27: =IF(K27="Finalizado","Verde",IF(G27="","Amarillo",IF(H27<=Parametros!$B$4,"Verde",IF(H27<=Parametros!$B$5,"Amarillo","Rojo")))) -> Verde | J27: =IF(K27="Finalizado","Completado",IF(G27="","Sin fecha válida - revisar plazos",IF(H27<=Parametros!$B$4,"En tiempo, según lo planificado",IF(H27<=Parametros!$B$5,"Atraso leve - seguimiento cercano ("&TEXT(H27,"0.0")&" p.p.)","Atraso crítico - requiere intervención ("&TEXT(H27,"0.0")&" p.p.)")))) -> Completado | K27: Finalizado | M27: Ciberdefensa | N27: POA | O27: =IF(AND(E27<>"",YEAR(E27)=YEAR(Parametros!$B$3),MONTH(E27)>=10),1,0) -> 0 | P27: =IF(AND(E27<Parametros!$B$3,K27<>"Finalizado"),1,0) -> 0 | Q27: =IF(AND(E27>=Parametros!$B$3,E27<=Parametros!$B$3+30,K27<>"Finalizado"),1,0) -> 0
A28: CD-04 | B28: Implementación del Dashboard - Normalidad, Alerta y Crisis | C28: Definición de umbrales y estados | D28: 46118 | E28: 46157 | F28: 100 | G28: =IF(OR(D28="",E28="",E28<=D28),"",MIN(100,MAX(0,(Parametros!$B$3-D28)/(E28-D28)*100))) -> 100 | H28: =IF(G28="","",G28-F28) -> 0 | I28: =IF(K28="Finalizado","Verde",IF(G28="","Amarillo",IF(H28<=Parametros!$B$4,"Verde",IF(H28<=Parametros!$B$5,"Amarillo","Rojo")))) -> Verde | J28: =IF(K28="Finalizado","Completado",IF(G28="","Sin fecha válida - revisar plazos",IF(H28<=Parametros!$B$4,"En tiempo, según lo planificado",IF(H28<=Parametros!$B$5,"Atraso leve - seguimiento cercano ("&TEXT(H28,"0.0")&" p.p.)","Atraso crítico - requiere intervención ("&TEXT(H28,"0.0")&" p.p.)")))) -> Completado | K28: Finalizado | M28: Ciberdefensa | N28: POA | O28: =IF(AND(E28<>"",YEAR(E28)=YEAR(Parametros!$B$3),MONTH(E28)>=10),1,0) -> 0 | P28: =IF(AND(E28<Parametros!$B$3,K28<>"Finalizado"),1,0) -> 0 | Q28: =IF(AND(E28>=Parametros!$B$3,E28<=Parametros!$B$3+30,K28<>"Finalizado"),1,0) -> 0
A29: CD-04 | B29: Implementación del Dashboard - Normalidad, Alerta y Crisis | C29: Diseño conceptual del Dashboard | D29: 46078 | E29: 46094 | F29: 100 | G29: =IF(OR(D29="",E29="",E29<=D29),"",MIN(100,MAX(0,(Parametros!$B$3-D29)/(E29-D29)*100))) -> 100 | H29: =IF(G29="","",G29-F29) -> 0 | I29: =IF(K29="Finalizado","Verde",IF(G29="","Amarillo",IF(H29<=Parametros!$B$4,"Verde",IF(H29<=Parametros!$B$5,"Amarillo","Rojo")))) -> Verde | J29: =IF(K29="Finalizado","Completado",IF(G29="","Sin fecha válida - revisar plazos",IF(H29<=Parametros!$B$4,"En tiempo, según lo planificado",IF(H29<=Parametros!$B$5,"Atraso leve - seguimiento cercano ("&TEXT(H29,"0.0")&" p.p.)","Atraso crítico - requiere intervención ("&TEXT(H29,"0.0")&" p.p.)")))) -> Completado | K29: Finalizado | M29: Ciberdefensa | N29: POA | O29: =IF(AND(E29<>"",YEAR(E29)=YEAR(Parametros!$B$3),MONTH(E29)>=10),1,0) -> 0 | P29: =IF(AND(E29<Parametros!$B$3,K29<>"Finalizado"),1,0) -> 0 | Q29: =IF(AND(E29>=Parametros!$B$3,E29<=Parametros!$B$3+30,K29<>"Finalizado"),1,0) -> 0
A30: CD-04 | B30: Implementación del Dashboard - Normalidad, Alerta y Crisis | C30: Gobierno y flujo operativo.. | D30: 46258 | E30: 46276 | F30: 0 | G30: =IF(OR(D30="",E30="",E30<=D30),"",MIN(100,MAX(0,(Parametros!$B$3-D30)/(E30-D30)*100))) -> 0 | H30: =IF(G30="","",G30-F30) -> 0 | I30: =IF(K30="Finalizado","Verde",IF(G30="","Amarillo",IF(H30<=Parametros!$B$4,"Verde",IF(H30<=Parametros!$B$5,"Amarillo","Rojo")))) -> Verde | J30: =IF(K30="Finalizado","Completado",IF(G30="","Sin fecha válida - revisar plazos",IF(H30<=Parametros!$B$4,"En tiempo, según lo planificado",IF(H30<=Parametros!$B$5,"Atraso leve - seguimiento cercano ("&TEXT(H30,"0.0")&" p.p.)","Atraso crítico - requiere intervención ("&TEXT(H30,"0.0")&" p.p.)")))) -> En tiempo, según lo planificado | K30: No iniciado | M30: Ciberdefensa | N30: POA | O30: =IF(AND(E30<>"",YEAR(E30)=YEAR(Parametros!$B$3),MONTH(E30)>=10),1,0) -> 0 | P30: =IF(AND(E30<Parametros!$B$3,K30<>"Finalizado"),1,0) -> 0 | Q30: =IF(AND(E30>=Parametros!$B$3,E30<=Parametros!$B$3+30,K30<>"Finalizado"),1,0) -> 1
A31: CD-04 | B31: Implementación del Dashboard - Normalidad, Alerta y Crisis | C31: Mejoras y ampliaciones | D31: 46160 | E31: 46272 | F31: 68 | G31: =IF(OR(D31="",E31="",E31<=D31),"",MIN(100,MAX(0,(Parametros!$B$3-D31)/(E31-D31)*100))) -> 87.5 | H31: =IF(G31="","",G31-F31) -> 19.5 | I31: =IF(K31="Finalizado","Verde",IF(G31="","Amarillo",IF(H31<=Parametros!$B$4,"Verde",IF(H31<=Parametros!$B$5,"Amarillo","Rojo")))) -> Amarillo | J31: =IF(K31="Finalizado","Completado",IF(G31="","Sin fecha válida - revisar plazos",IF(H31<=Parametros!$B$4,"En tiempo, según lo planificado",IF(H31<=Parametros!$B$5,"Atraso leve - seguimiento cercano ("&TEXT(H31,"0.0")&" p.p.)","Atraso crítico - requiere intervención ("&TEXT(H31,"0.0")&" p.p.)")))) -> Atraso leve - seguimiento cercano (19.5 p.p.) | K31: En ejecución | M31: Ciberdefensa | N31: POA | O31: =IF(AND(E31<>"",YEAR(E31)=YEAR(Parametros!$B$3),MONTH(E31)>=10),1,0) -> 0 | P31: =IF(AND(E31<Parametros!$B$3,K31<>"Finalizado"),1,0) -> 0 | Q31: =IF(AND(E31>=Parametros!$B$3,E31<=Parametros!$B$3+30,K31<>"Finalizado"),1,0) -> 1
A32: CD-04 | B32: Implementación del Dashboard - Normalidad, Alerta y Crisis | C32: Organización y definición de iniciativa | D32: 46063 | E32: 46078 | F32: 100 | G32: =IF(OR(D32="",E32="",E32<=D32),"",MIN(100,MAX(0,(Parametros!$B$3-D32)/(E32-D32)*100))) -> 100 | H32: =IF(G32="","",G32-F32) -> 0 | I32: =IF(K32="Finalizado","Verde",IF(G32="","Amarillo",IF(H32<=Parametros!$B$4,"Verde",IF(H32<=Parametros!$B$5,"Amarillo","Rojo")))) -> Verde | J32: =IF(K32="Finalizado","Completado",IF(G32="","Sin fecha válida - revisar plazos",IF(H32<=Parametros!$B$4,"En tiempo, según lo planificado",IF(H32<=Parametros!$B$5,"Atraso leve - seguimiento cercano ("&TEXT(H32,"0.0")&" p.p.)","Atraso crítico - requiere intervención ("&TEXT(H32,"0.0")&" p.p.)")))) -> Completado | K32: Finalizado | L32: GOMEZ PRADO SANDRA PATRICIA;#144 | M32: Ciberdefensa | N32: POA | O32: =IF(AND(E32<>"",YEAR(E32)=YEAR(Parametros!$B$3),MONTH(E32)>=10),1,0) -> 0 | P32: =IF(AND(E32<Parametros!$B$3,K32<>"Finalizado"),1,0) -> 0 | Q32: =IF(AND(E32>=Parametros!$B$3,E32<=Parametros!$B$3+30,K32<>"Finalizado"),1,0) -> 0
A33: CD-05 | B33: Automatización de actividades de Respuesta a incidentes | C33: Despliegue en ambiente final- Cierre del proyecto | D33: 46329 | E33: 46349 | F33: 0 | G33: =IF(OR(D33="",E33="",E33<=D33),"",MIN(100,MAX(0,(Parametros!$B$3-D33)/(E33-D33)*100))) -> 0 | H33: =IF(G33="","",G33-F33) -> 0 | I33: =IF(K33="Finalizado","Verde",IF(G33="","Amarillo",IF(H33<=Parametros!$B$4,"Verde",IF(H33<=Parametros!$B$5,"Amarillo","Rojo")))) -> Verde | J33: =IF(K33="Finalizado","Completado",IF(G33="","Sin fecha válida - revisar plazos",IF(H33<=Parametros!$B$4,"En tiempo, según lo planificado",IF(H33<=Parametros!$B$5,"Atraso leve - seguimiento cercano ("&TEXT(H33,"0.0")&" p.p.)","Atraso crítico - requiere intervención ("&TEXT(H33,"0.0")&" p.p.)")))) -> En tiempo, según lo planificado | K33: No iniciado | M33: Ciberdefensa | N33: POA | O33: =IF(AND(E33<>"",YEAR(E33)=YEAR(Parametros!$B$3),MONTH(E33)>=10),1,0) -> 1 | P33: =IF(AND(E33<Parametros!$B$3,K33<>"Finalizado"),1,0) -> 0 | Q33: =IF(AND(E33>=Parametros!$B$3,E33<=Parametros!$B$3+30,K33<>"Finalizado"),1,0) -> 0
A34: CD-05 | B34: Automatización de actividades de Respuesta a incidentes | C34: Diseño teorico de playbooks | D34: 46149 | E34: 46209 | F34: 100 | G34: =IF(OR(D34="",E34="",E34<=D34),"",MIN(100,MAX(0,(Parametros!$B$3-D34)/(E34-D34)*100))) -> 100 | H34: =IF(G34="","",G34-F34) -> 0 | I34: =IF(K34="Finalizado","Verde",IF(G34="","Amarillo",IF(H34<=Parametros!$B$4,"Verde",IF(H34<=Parametros!$B$5,"Amarillo","Rojo")))) -> Verde | J34: =IF(K34="Finalizado","Completado",IF(G34="","Sin fecha válida - revisar plazos",IF(H34<=Parametros!$B$4,"En tiempo, según lo planificado",IF(H34<=Parametros!$B$5,"Atraso leve - seguimiento cercano ("&TEXT(H34,"0.0")&" p.p.)","Atraso crítico - requiere intervención ("&TEXT(H34,"0.0")&" p.p.)")))) -> Completado | K34: Finalizado | M34: Ciberdefensa | N34: POA | O34: =IF(AND(E34<>"",YEAR(E34)=YEAR(Parametros!$B$3),MONTH(E34)>=10),1,0) -> 0 | P34: =IF(AND(E34<Parametros!$B$3,K34<>"Finalizado"),1,0) -> 0 | Q34: =IF(AND(E34>=Parametros!$B$3,E34<=Parametros!$B$3+30,K34<>"Finalizado"),1,0) -> 0
A35: CD-05 | B35: Automatización de actividades de Respuesta a incidentes | C35: Estabilización y afinamientos de playbooks en Test | D35: 46269 | E35: 46329 | F35: 0 | G35: =IF(OR(D35="",E35="",E35<=D35),"",MIN(100,MAX(0,(Parametros!$B$3-D35)/(E35-D35)*100))) -> 0 | H35: =IF(G35="","",G35-F35) -> 0 | I35: =IF(K35="Finalizado","Verde",IF(G35="","Amarillo",IF(H35<=Parametros!$B$4,"Verde",IF(H35<=Parametros!$B$5,"Amarillo","Rojo")))) -> Verde | J35: =IF(K35="Finalizado","Completado",IF(G35="","Sin fecha válida - revisar plazos",IF(H35<=Parametros!$B$4,"En tiempo, según lo planificado",IF(H35<=Parametros!$B$5,"Atraso leve - seguimiento cercano ("&TEXT(H35,"0.0")&" p.p.)","Atraso crítico - requiere intervención ("&TEXT(H35,"0.0")&" p.p.)")))) -> En tiempo, según lo planificado | K35: No iniciado | M35: Ciberdefensa | N35: POA | O35: =IF(AND(E35<>"",YEAR(E35)=YEAR(Parametros!$B$3),MONTH(E35)>=10),1,0) -> 1 | P35: =IF(AND(E35<Parametros!$B$3,K35<>"Finalizado"),1,0) -> 0 | Q35: =IF(AND(E35>=Parametros!$B$3,E35<=Parametros!$B$3+30,K35<>"Finalizado"),1,0) -> 0
A36: CD-05 | B36: Automatización de actividades de Respuesta a incidentes | C36: Implementación y pruebas de playbooks en Test | D36: 46209 | E36: 46269 | F36: 44 | G36: =IF(OR(D36="",E36="",E36<=D36),"",MIN(100,MAX(0,(Parametros!$B$3-D36)/(E36-D36)*100))) -> 81.666667 | H36: =IF(G36="","",G36-F36) -> 37.666667 | I36: =IF(K36="Finalizado","Verde",IF(G36="","Amarillo",IF(H36<=Parametros!$B$4,"Verde",IF(H36<=Parametros!$B$5,"Amarillo","Rojo")))) -> Rojo | J36: =IF(K36="Finalizado","Completado",IF(G36="","Sin fecha válida - revisar plazos",IF(H36<=Parametros!$B$4,"En tiempo, según lo planificado",IF(H36<=Parametros!$B$5,"Atraso leve - seguimiento cercano ("&TEXT(H36,"0.0")&" p.p.)","Atraso crítico - requiere intervención ("&TEXT(H36,"0.0")&" p.p.)")))) -> Atraso crítico - requiere intervención (37.7 p.p.) | K36: En ejecución | M36: Ciberdefensa | N36: POA | O36: =IF(AND(E36<>"",YEAR(E36)=YEAR(Parametros!$B$3),MONTH(E36)>=10),1,0) -> 0 | P36: =IF(AND(E36<Parametros!$B$3,K36<>"Finalizado"),1,0) -> 0 | Q36: =IF(AND(E36>=Parametros!$B$3,E36<=Parametros!$B$3+30,K36<>"Finalizado"),1,0) -> 1
A37: CD-05 | B37: Automatización de actividades de Respuesta a incidentes | C37: Integración de plataformas a XSOAR | D37: 46147 | E37: 46192 | F37: 100 | G37: =IF(OR(D37="",E37="",E37<=D37),"",MIN(100,MAX(0,(Parametros!$B$3-D37)/(E37-D37)*100))) -> 100 | H37: =IF(G37="","",G37-F37) -> 0 | I37: =IF(K37="Finalizado","Verde",IF(G37="","Amarillo",IF(H37<=Parametros!$B$4,"Verde",IF(H37<=Parametros!$B$5,"Amarillo","Rojo")))) -> Verde | J37: =IF(K37="Finalizado","Completado",IF(G37="","Sin fecha válida - revisar plazos",IF(H37<=Parametros!$B$4,"En tiempo, según lo planificado",IF(H37<=Parametros!$B$5,"Atraso leve - seguimiento cercano ("&TEXT(H37,"0.0")&" p.p.)","Atraso crítico - requiere intervención ("&TEXT(H37,"0.0")&" p.p.)")))) -> Completado | K37: Finalizado | M37: Ciberdefensa | N37: POA | O37: =IF(AND(E37<>"",YEAR(E37)=YEAR(Parametros!$B$3),MONTH(E37)>=10),1,0) -> 0 | P37: =IF(AND(E37<Parametros!$B$3,K37<>"Finalizado"),1,0) -> 0 | Q37: =IF(AND(E37>=Parametros!$B$3,E37<=Parametros!$B$3+30,K37<>"Finalizado"),1,0) -> 0
A38: CD-05 | B38: Automatización de actividades de Respuesta a incidentes | C38: Integración de plataformas a XSOAR Test | D38: 46147 | E38: 46162 | F38: 100 | G38: =IF(OR(D38="",E38="",E38<=D38),"",MIN(100,MAX(0,(Parametros!$B$3-D38)/(E38-D38)*100))) -> 100 | H38: =IF(G38="","",G38-F38) -> 0 | I38: =IF(K38="Finalizado","Verde",IF(G38="","Amarillo",IF(H38<=Parametros!$B$4,"Verde",IF(H38<=Parametros!$B$5,"Amarillo","Rojo")))) -> Verde | J38: =IF(K38="Finalizado","Completado",IF(G38="","Sin fecha válida - revisar plazos",IF(H38<=Parametros!$B$4,"En tiempo, según lo planificado",IF(H38<=Parametros!$B$5,"Atraso leve - seguimiento cercano ("&TEXT(H38,"0.0")&" p.p.)","Atraso crítico - requiere intervención ("&TEXT(H38,"0.0")&" p.p.)")))) -> Completado | K38: Finalizado | M38: Ciberdefensa | N38: POA | O38: =IF(AND(E38<>"",YEAR(E38)=YEAR(Parametros!$B$3),MONTH(E38)>=10),1,0) -> 0 | P38: =IF(AND(E38<Parametros!$B$3,K38<>"Finalizado"),1,0) -> 0 | Q38: =IF(AND(E38>=Parametros!$B$3,E38<=Parametros!$B$3+30,K38<>"Finalizado"),1,0) -> 0
A39: CD-05 | B39: Automatización de actividades de Respuesta a incidentes | C39: Organización y definición de iniciativa | D39: 46083 | E39: 46121 | F39: 100 | G39: =IF(OR(D39="",E39="",E39<=D39),"",MIN(100,MAX(0,(Parametros!$B$3-D39)/(E39-D39)*100))) -> 100 | H39: =IF(G39="","",G39-F39) -> 0 | I39: =IF(K39="Finalizado","Verde",IF(G39="","Amarillo",IF(H39<=Parametros!$B$4,"Verde",IF(H39<=Parametros!$B$5,"Amarillo","Rojo")))) -> Verde | J39: =IF(K39="Finalizado","Completado",IF(G39="","Sin fecha válida - revisar plazos",IF(H39<=Parametros!$B$4,"En tiempo, según lo planificado",IF(H39<=Parametros!$B$5,"Atraso leve - seguimiento cercano ("&TEXT(H39,"0.0")&" p.p.)","Atraso crítico - requiere intervención ("&TEXT(H39,"0.0")&" p.p.)")))) -> Completado | K39: Finalizado | L39: GOMEZ PRADO SANDRA PATRICIA;#144 | M39: Ciberdefensa | N39: POA | O39: =IF(AND(E39<>"",YEAR(E39)=YEAR(Parametros!$B$3),MONTH(E39)>=10),1,0) -> 0 | P39: =IF(AND(E39<Parametros!$B$3,K39<>"Finalizado"),1,0) -> 0 | Q39: =IF(AND(E39>=Parametros!$B$3,E39<=Parametros!$B$3+30,K39<>"Finalizado"),1,0) -> 0
A40: CD-06 | B40: Preparacion y resiliencia operacional ante incidentes críticos | C40: 1er ejercicio preparación | D40: 46202 | E40: 46262 | F40: 83 | G40: =IF(OR(D40="",E40="",E40<=D40),"",MIN(100,MAX(0,(Parametros!$B$3-D40)/(E40-D40)*100))) -> 93.333333 | H40: =IF(G40="","",G40-F40) -> 10.333333 | I40: =IF(K40="Finalizado","Verde",IF(G40="","Amarillo",IF(H40<=Parametros!$B$4,"Verde",IF(H40<=Parametros!$B$5,"Amarillo","Rojo")))) -> Amarillo | J40: =IF(K40="Finalizado","Completado",IF(G40="","Sin fecha válida - revisar plazos",IF(H40<=Parametros!$B$4,"En tiempo, según lo planificado",IF(H40<=Parametros!$B$5,"Atraso leve - seguimiento cercano ("&TEXT(H40,"0.0")&" p.p.)","Atraso crítico - requiere intervención ("&TEXT(H40,"0.0")&" p.p.)")))) -> Atraso leve - seguimiento cercano (10.3 p.p.) | K40: En ejecución | M40: Ciberdefensa | N40: POA | O40: =IF(AND(E40<>"",YEAR(E40)=YEAR(Parametros!$B$3),MONTH(E40)>=10),1,0) -> 0 | P40: =IF(AND(E40<Parametros!$B$3,K40<>"Finalizado"),1,0) -> 0 | Q40: =IF(AND(E40>=Parametros!$B$3,E40<=Parametros!$B$3+30,K40<>"Finalizado"),1,0) -> 1
A41: CD-06 | B41: Preparacion y resiliencia operacional ante incidentes críticos | C41: 2do ejercicio preparación | D41: 46301 | E41: 46353 | F41: 0 | G41: =IF(OR(D41="",E41="",E41<=D41),"",MIN(100,MAX(0,(Parametros!$B$3-D41)/(E41-D41)*100))) -> 0 | H41: =IF(G41="","",G41-F41) -> 0 | I41: =IF(K41="Finalizado","Verde",IF(G41="","Amarillo",IF(H41<=Parametros!$B$4,"Verde",IF(H41<=Parametros!$B$5,"Amarillo","Rojo")))) -> Verde | J41: =IF(K41="Finalizado","Completado",IF(G41="","Sin fecha válida - revisar plazos",IF(H41<=Parametros!$B$4,"En tiempo, según lo planificado",IF(H41<=Parametros!$B$5,"Atraso leve - seguimiento cercano ("&TEXT(H41,"0.0")&" p.p.)","Atraso crítico - requiere intervención ("&TEXT(H41,"0.0")&" p.p.)")))) -> En tiempo, según lo planificado | K41: No iniciado | M41: Ciberdefensa | N41: POA | O41: =IF(AND(E41<>"",YEAR(E41)=YEAR(Parametros!$B$3),MONTH(E41)>=10),1,0) -> 1 | P41: =IF(AND(E41<Parametros!$B$3,K41<>"Finalizado"),1,0) -> 0 | Q41: =IF(AND(E41>=Parametros!$B$3,E41<=Parametros!$B$3+30,K41<>"Finalizado"),1,0) -> 0
A42: CD-06 | B42: Preparacion y resiliencia operacional ante incidentes críticos | C42: Capacidad de reestablecer operaciones con el mínimo impacto (Backups) | D42: 46174 | E42: 46265 | F42: 67 | G42: =IF(OR(D42="",E42="",E42<=D42),"",MIN(100,MAX(0,(Parametros!$B$3-D42)/(E42-D42)*100))) -> 92.307692 | H42: =IF(G42="","",G42-F42) -> 25.307692 | I42: =IF(K42="Finalizado","Verde",IF(G42="","Amarillo",IF(H42<=Parametros!$B$4,"Verde",IF(H42<=Parametros!$B$5,"Amarillo","Rojo")))) -> Rojo | J42: =IF(K42="Finalizado","Completado",IF(G42="","Sin fecha válida - revisar plazos",IF(H42<=Parametros!$B$4,"En tiempo, según lo planificado",IF(H42<=Parametros!$B$5,"Atraso leve - seguimiento cercano ("&TEXT(H42,"0.0")&" p.p.)","Atraso crítico - requiere intervención ("&TEXT(H42,"0.0")&" p.p.)")))) -> Atraso crítico - requiere intervención (25.3 p.p.) | K42: En ejecución | M42: Ciberdefensa | N42: POA | O42: =IF(AND(E42<>"",YEAR(E42)=YEAR(Parametros!$B$3),MONTH(E42)>=10),1,0) -> 0 | P42: =IF(AND(E42<Parametros!$B$3,K42<>"Finalizado"),1,0) -> 0 | Q42: =IF(AND(E42>=Parametros!$B$3,E42<=Parametros!$B$3+30,K42<>"Finalizado"),1,0) -> 1
A43: CD-06 | B43: Preparacion y resiliencia operacional ante incidentes críticos | C43: Cierre de iniciativa | D43: 46370 | E43: 46386 | F43: 0 | G43: =IF(OR(D43="",E43="",E43<=D43),"",MIN(100,MAX(0,(Parametros!$B$3-D43)/(E43-D43)*100))) -> 0 | H43: =IF(G43="","",G43-F43) -> 0 | I43: =IF(K43="Finalizado","Verde",IF(G43="","Amarillo",IF(H43<=Parametros!$B$4,"Verde",IF(H43<=Parametros!$B$5,"Amarillo","Rojo")))) -> Verde | J43: =IF(K43="Finalizado","Completado",IF(G43="","Sin fecha válida - revisar plazos",IF(H43<=Parametros!$B$4,"En tiempo, según lo planificado",IF(H43<=Parametros!$B$5,"Atraso leve - seguimiento cercano ("&TEXT(H43,"0.0")&" p.p.)","Atraso crítico - requiere intervención ("&TEXT(H43,"0.0")&" p.p.)")))) -> En tiempo, según lo planificado | K43: No iniciado | M43: Ciberdefensa | N43: POA | O43: =IF(AND(E43<>"",YEAR(E43)=YEAR(Parametros!$B$3),MONTH(E43)>=10),1,0) -> 1 | P43: =IF(AND(E43<Parametros!$B$3,K43<>"Finalizado"),1,0) -> 0 | Q43: =IF(AND(E43>=Parametros!$B$3,E43<=Parametros!$B$3+30,K43<>"Finalizado"),1,0) -> 0
A44: CD-06 | B44: Preparacion y resiliencia operacional ante incidentes críticos | C44: Gobierno (Actualización de instructivos IRT, D&C, CTI) | D44: 46181 | E44: 46195 | F44: 100 | G44: =IF(OR(D44="",E44="",E44<=D44),"",MIN(100,MAX(0,(Parametros!$B$3-D44)/(E44-D44)*100))) -> 100 | H44: =IF(G44="","",G44-F44) -> 0 | I44: =IF(K44="Finalizado","Verde",IF(G44="","Amarillo",IF(H44<=Parametros!$B$4,"Verde",IF(H44<=Parametros!$B$5,"Amarillo","Rojo")))) -> Verde | J44: =IF(K44="Finalizado","Completado",IF(G44="","Sin fecha válida - revisar plazos",IF(H44<=Parametros!$B$4,"En tiempo, según lo planificado",IF(H44<=Parametros!$B$5,"Atraso leve - seguimiento cercano ("&TEXT(H44,"0.0")&" p.p.)","Atraso crítico - requiere intervención ("&TEXT(H44,"0.0")&" p.p.)")))) -> En tiempo, según lo planificado | K44: En ejecución | M44: Ciberdefensa | N44: POA | O44: =IF(AND(E44<>"",YEAR(E44)=YEAR(Parametros!$B$3),MONTH(E44)>=10),1,0) -> 0 | P44: =IF(AND(E44<Parametros!$B$3,K44<>"Finalizado"),1,0) -> 1 | Q44: =IF(AND(E44>=Parametros!$B$3,E44<=Parametros!$B$3+30,K44<>"Finalizado"),1,0) -> 0
A45: CD-06 | B45: Preparacion y resiliencia operacional ante incidentes críticos | C45: Organización y definición de iniciativa | D45: 46124 | E45: 46203 | F45: 100 | G45: =IF(OR(D45="",E45="",E45<=D45),"",MIN(100,MAX(0,(Parametros!$B$3-D45)/(E45-D45)*100))) -> 100 | H45: =IF(G45="","",G45-F45) -> 0 | I45: =IF(K45="Finalizado","Verde",IF(G45="","Amarillo",IF(H45<=Parametros!$B$4,"Verde",IF(H45<=Parametros!$B$5,"Amarillo","Rojo")))) -> Verde | J45: =IF(K45="Finalizado","Completado",IF(G45="","Sin fecha válida - revisar plazos",IF(H45<=Parametros!$B$4,"En tiempo, según lo planificado",IF(H45<=Parametros!$B$5,"Atraso leve - seguimiento cercano ("&TEXT(H45,"0.0")&" p.p.)","Atraso crítico - requiere intervención ("&TEXT(H45,"0.0")&" p.p.)")))) -> Completado | K45: Finalizado | L45: GOMEZ PRADO SANDRA PATRICIA;#144 | M45: Ciberdefensa | N45: POA | O45: =IF(AND(E45<>"",YEAR(E45)=YEAR(Parametros!$B$3),MONTH(E45)>=10),1,0) -> 0 | P45: =IF(AND(E45<Parametros!$B$3,K45<>"Finalizado"),1,0) -> 0 | Q45: =IF(AND(E45>=Parametros!$B$3,E45<=Parametros!$B$3+30,K45<>"Finalizado"),1,0) -> 0
A46: CD-06 | B46: Preparacion y resiliencia operacional ante incidentes críticos | C46: Preparacion y comunicación | D46: 46153 | E46: 46233 | F46: 100 | G46: =IF(OR(D46="",E46="",E46<=D46),"",MIN(100,MAX(0,(Parametros!$B$3-D46)/(E46-D46)*100))) -> 100 | H46: =IF(G46="","",G46-F46) -> 0 | I46: =IF(K46="Finalizado","Verde",IF(G46="","Amarillo",IF(H46<=Parametros!$B$4,"Verde",IF(H46<=Parametros!$B$5,"Amarillo","Rojo")))) -> Verde | J46: =IF(K46="Finalizado","Completado",IF(G46="","Sin fecha válida - revisar plazos",IF(H46<=Parametros!$B$4,"En tiempo, según lo planificado",IF(H46<=Parametros!$B$5,"Atraso leve - seguimiento cercano ("&TEXT(H46,"0.0")&" p.p.)","Atraso crítico - requiere intervención ("&TEXT(H46,"0.0")&" p.p.)")))) -> Completado | K46: Finalizado | M46: Ciberdefensa | N46: POA | O46: =IF(AND(E46<>"",YEAR(E46)=YEAR(Parametros!$B$3),MONTH(E46)>=10),1,0) -> 0 | P46: =IF(AND(E46<Parametros!$B$3,K46<>"Finalizado"),1,0) -> 0 | Q46: =IF(AND(E46>=Parametros!$B$3,E46<=Parametros!$B$3+30,K46<>"Finalizado"),1,0) -> 0
A47: CD-07 | B47: Automatización del análisis de monitoreo de plataformas Windows | C47: 1.- Definición de arquitectura de automatización | D47: 46055 | E47: 46118 | F47: 100 | G47: =IF(OR(D47="",E47="",E47<=D47),"",MIN(100,MAX(0,(Parametros!$B$3-D47)/(E47-D47)*100))) -> 100 | H47: =IF(G47="","",G47-F47) -> 0 | I47: =IF(K47="Finalizado","Verde",IF(G47="","Amarillo",IF(H47<=Parametros!$B$4,"Verde",IF(H47<=Parametros!$B$5,"Amarillo","Rojo")))) -> Verde | J47: =IF(K47="Finalizado","Completado",IF(G47="","Sin fecha válida - revisar plazos",IF(H47<=Parametros!$B$4,"En tiempo, según lo planificado",IF(H47<=Parametros!$B$5,"Atraso leve - seguimiento cercano ("&TEXT(H47,"0.0")&" p.p.)","Atraso crítico - requiere intervención ("&TEXT(H47,"0.0")&" p.p.)")))) -> Completado | K47: Finalizado | M47: Ciberdefensa | N47: POA | O47: =IF(AND(E47<>"",YEAR(E47)=YEAR(Parametros!$B$3),MONTH(E47)>=10),1,0) -> 0 | P47: =IF(AND(E47<Parametros!$B$3,K47<>"Finalizado"),1,0) -> 0 | Q47: =IF(AND(E47>=Parametros!$B$3,E47<=Parametros!$B$3+30,K47<>"Finalizado"),1,0) -> 0
A48: CD-07 | B48: Automatización del análisis de monitoreo de plataformas Windows | C48: 2.- Consolidación y normalización de inventario (fuente única) | D48: 46119 | E48: 46178 | F48: 100 | G48: =IF(OR(D48="",E48="",E48<=D48),"",MIN(100,MAX(0,(Parametros!$B$3-D48)/(E48-D48)*100))) -> 100 | H48: =IF(G48="","",G48-F48) -> 0 | I48: =IF(K48="Finalizado","Verde",IF(G48="","Amarillo",IF(H48<=Parametros!$B$4,"Verde",IF(H48<=Parametros!$B$5,"Amarillo","Rojo")))) -> Verde | J48: =IF(K48="Finalizado","Completado",IF(G48="","Sin fecha válida - revisar plazos",IF(H48<=Parametros!$B$4,"En tiempo, según lo planificado",IF(H48<=Parametros!$B$5,"Atraso leve - seguimiento cercano ("&TEXT(H48,"0.0")&" p.p.)","Atraso crítico - requiere intervención ("&TEXT(H48,"0.0")&" p.p.)")))) -> Completado | K48: Finalizado | M48: Ciberdefensa | N48: POA | O48: =IF(AND(E48<>"",YEAR(E48)=YEAR(Parametros!$B$3),MONTH(E48)>=10),1,0) -> 0 | P48: =IF(AND(E48<Parametros!$B$3,K48<>"Finalizado"),1,0) -> 0 | Q48: =IF(AND(E48>=Parametros!$B$3,E48<=Parametros!$B$3+30,K48<>"Finalizado"),1,0) -> 0
A49: CD-07 | B49: Automatización del análisis de monitoreo de plataformas Windows | C49: 3.- Desarrollo de conectores para extracción automatizada | D49: 46181 | E49: 46213 | F49: 100 | G49: =IF(OR(D49="",E49="",E49<=D49),"",MIN(100,MAX(0,(Parametros!$B$3-D49)/(E49-D49)*100))) -> 100 | H49: =IF(G49="","",G49-F49) -> 0 | I49: =IF(K49="Finalizado","Verde",IF(G49="","Amarillo",IF(H49<=Parametros!$B$4,"Verde",IF(H49<=Parametros!$B$5,"Amarillo","Rojo")))) -> Verde | J49: =IF(K49="Finalizado","Completado",IF(G49="","Sin fecha válida - revisar plazos",IF(H49<=Parametros!$B$4,"En tiempo, según lo planificado",IF(H49<=Parametros!$B$5,"Atraso leve - seguimiento cercano ("&TEXT(H49,"0.0")&" p.p.)","Atraso crítico - requiere intervención ("&TEXT(H49,"0.0")&" p.p.)")))) -> Completado | K49: Finalizado | M49: Ciberdefensa | N49: POA | O49: =IF(AND(E49<>"",YEAR(E49)=YEAR(Parametros!$B$3),MONTH(E49)>=10),1,0) -> 0 | P49: =IF(AND(E49<Parametros!$B$3,K49<>"Finalizado"),1,0) -> 0 | Q49: =IF(AND(E49>=Parametros!$B$3,E49<=Parametros!$B$3+30,K49<>"Finalizado"),1,0) -> 0
A50: CD-07 | B50: Automatización del análisis de monitoreo de plataformas Windows | C50: 4.- Motor de correlación y análisis de cumplimiento | D50: 46216 | E50: 46248 | F50: 80 | G50: =IF(OR(D50="",E50="",E50<=D50),"",MIN(100,MAX(0,(Parametros!$B$3-D50)/(E50-D50)*100))) -> 100 | H50: =IF(G50="","",G50-F50) -> 20 | I50: =IF(K50="Finalizado","Verde",IF(G50="","Amarillo",IF(H50<=Parametros!$B$4,"Verde",IF(H50<=Parametros!$B$5,"Amarillo","Rojo")))) -> Amarillo | J50: =IF(K50="Finalizado","Completado",IF(G50="","Sin fecha válida - revisar plazos",IF(H50<=Parametros!$B$4,"En tiempo, según lo planificado",IF(H50<=Parametros!$B$5,"Atraso leve - seguimiento cercano ("&TEXT(H50,"0.0")&" p.p.)","Atraso crítico - requiere intervención ("&TEXT(H50,"0.0")&" p.p.)")))) -> Atraso leve - seguimiento cercano (20.0 p.p.) | K50: En ejecución | M50: Ciberdefensa | N50: POA | O50: =IF(AND(E50<>"",YEAR(E50)=YEAR(Parametros!$B$3),MONTH(E50)>=10),1,0) -> 0 | P50: =IF(AND(E50<Parametros!$B$3,K50<>"Finalizado"),1,0) -> 1 | Q50: =IF(AND(E50>=Parametros!$B$3,E50<=Parametros!$B$3+30,K50<>"Finalizado"),1,0) -> 0
A51: CD-07 | B51: Automatización del análisis de monitoreo de plataformas Windows | C51: 6.- Construcción de indicadores (KPI / KRI ) | D51: 46251 | E51: 46265 | F51: 0 | G51: =IF(OR(D51="",E51="",E51<=D51),"",MIN(100,MAX(0,(Parametros!$B$3-D51)/(E51-D51)*100))) -> 50 | H51: =IF(G51="","",G51-F51) -> 50 | I51: =IF(K51="Finalizado","Verde",IF(G51="","Amarillo",IF(H51<=Parametros!$B$4,"Verde",IF(H51<=Parametros!$B$5,"Amarillo","Rojo")))) -> Rojo | J51: =IF(K51="Finalizado","Completado",IF(G51="","Sin fecha válida - revisar plazos",IF(H51<=Parametros!$B$4,"En tiempo, según lo planificado",IF(H51<=Parametros!$B$5,"Atraso leve - seguimiento cercano ("&TEXT(H51,"0.0")&" p.p.)","Atraso crítico - requiere intervención ("&TEXT(H51,"0.0")&" p.p.)")))) -> Atraso crítico - requiere intervención (50.0 p.p.) | K51: No iniciado | M51: Ciberdefensa | N51: POA | O51: =IF(AND(E51<>"",YEAR(E51)=YEAR(Parametros!$B$3),MONTH(E51)>=10),1,0) -> 0 | P51: =IF(AND(E51<Parametros!$B$3,K51<>"Finalizado"),1,0) -> 0 | Q51: =IF(AND(E51>=Parametros!$B$3,E51<=Parametros!$B$3+30,K51<>"Finalizado"),1,0) -> 1
A52: CD-07 | B52: Automatización del análisis de monitoreo de plataformas Windows | C52: 7.- Automatización de alertas y notificaciones | D52: 46266 | E52: 46283 | F52: 0 | G52: =IF(OR(D52="",E52="",E52<=D52),"",MIN(100,MAX(0,(Parametros!$B$3-D52)/(E52-D52)*100))) -> 0 | H52: =IF(G52="","",G52-F52) -> 0 | I52: =IF(K52="Finalizado","Verde",IF(G52="","Amarillo",IF(H52<=Parametros!$B$4,"Verde",IF(H52<=Parametros!$B$5,"Amarillo","Rojo")))) -> Verde | J52: =IF(K52="Finalizado","Completado",IF(G52="","Sin fecha válida - revisar plazos",IF(H52<=Parametros!$B$4,"En tiempo, según lo planificado",IF(H52<=Parametros!$B$5,"Atraso leve - seguimiento cercano ("&TEXT(H52,"0.0")&" p.p.)","Atraso crítico - requiere intervención ("&TEXT(H52,"0.0")&" p.p.)")))) -> En tiempo, según lo planificado | K52: No iniciado | M52: Ciberdefensa | N52: POA | O52: =IF(AND(E52<>"",YEAR(E52)=YEAR(Parametros!$B$3),MONTH(E52)>=10),1,0) -> 0 | P52: =IF(AND(E52<Parametros!$B$3,K52<>"Finalizado"),1,0) -> 0 | Q52: =IF(AND(E52>=Parametros!$B$3,E52<=Parametros!$B$3+30,K52<>"Finalizado"),1,0) -> 1
A53: CD-07 | B53: Automatización del análisis de monitoreo de plataformas Windows | C53: 8.- Pruebas piloto y validación de resultados | D53: 46286 | E53: 46325 | F53: 0 | G53: =IF(OR(D53="",E53="",E53<=D53),"",MIN(100,MAX(0,(Parametros!$B$3-D53)/(E53-D53)*100))) -> 0 | H53: =IF(G53="","",G53-F53) -> 0 | I53: =IF(K53="Finalizado","Verde",IF(G53="","Amarillo",IF(H53<=Parametros!$B$4,"Verde",IF(H53<=Parametros!$B$5,"Amarillo","Rojo")))) -> Verde | J53: =IF(K53="Finalizado","Completado",IF(G53="","Sin fecha válida - revisar plazos",IF(H53<=Parametros!$B$4,"En tiempo, según lo planificado",IF(H53<=Parametros!$B$5,"Atraso leve - seguimiento cercano ("&TEXT(H53,"0.0")&" p.p.)","Atraso crítico - requiere intervención ("&TEXT(H53,"0.0")&" p.p.)")))) -> En tiempo, según lo planificado | K53: No iniciado | M53: Ciberdefensa | N53: POA | O53: =IF(AND(E53<>"",YEAR(E53)=YEAR(Parametros!$B$3),MONTH(E53)>=10),1,0) -> 1 | P53: =IF(AND(E53<Parametros!$B$3,K53<>"Finalizado"),1,0) -> 0 | Q53: =IF(AND(E53>=Parametros!$B$3,E53<=Parametros!$B$3+30,K53<>"Finalizado"),1,0) -> 0
A54: CD-07 | B54: Automatización del análisis de monitoreo de plataformas Windows | C54: 9.- Despliegue y estabilización del modelo | D54: 46328 | E54: 46367 | F54: 0 | G54: =IF(OR(D54="",E54="",E54<=D54),"",MIN(100,MAX(0,(Parametros!$B$3-D54)/(E54-D54)*100))) -> 0 | H54: =IF(G54="","",G54-F54) -> 0 | I54: =IF(K54="Finalizado","Verde",IF(G54="","Amarillo",IF(H54<=Parametros!$B$4,"Verde",IF(H54<=Parametros!$B$5,"Amarillo","Rojo")))) -> Verde | J54: =IF(K54="Finalizado","Completado",IF(G54="","Sin fecha válida - revisar plazos",IF(H54<=Parametros!$B$4,"En tiempo, según lo planificado",IF(H54<=Parametros!$B$5,"Atraso leve - seguimiento cercano ("&TEXT(H54,"0.0")&" p.p.)","Atraso crítico - requiere intervención ("&TEXT(H54,"0.0")&" p.p.)")))) -> En tiempo, según lo planificado | K54: No iniciado | M54: Ciberdefensa | N54: POA | O54: =IF(AND(E54<>"",YEAR(E54)=YEAR(Parametros!$B$3),MONTH(E54)>=10),1,0) -> 1 | P54: =IF(AND(E54<Parametros!$B$3,K54<>"Finalizado"),1,0) -> 0 | Q54: =IF(AND(E54>=Parametros!$B$3,E54<=Parametros!$B$3+30,K54<>"Finalizado"),1,0) -> 0
A55: CD-07 | B55: Automatización del análisis de monitoreo de plataformas Windows | C55: Estaciones de trabajo y servidores Windows, detectados por la plataforma EDR. | D55: 46055 | E55: 46387 | F55: 60 | G55: =IF(OR(D55="",E55="",E55<=D55),"",MIN(100,MAX(0,(Parametros!$B$3-D55)/(E55-D55)*100))) -> 61.144578 | H55: =IF(G55="","",G55-F55) -> 1.1445783 | I55: =IF(K55="Finalizado","Verde",IF(G55="","Amarillo",IF(H55<=Parametros!$B$4,"Verde",IF(H55<=Parametros!$B$5,"Amarillo","Rojo")))) -> Verde | J55: =IF(K55="Finalizado","Completado",IF(G55="","Sin fecha válida - revisar plazos",IF(H55<=Parametros!$B$4,"En tiempo, según lo planificado",IF(H55<=Parametros!$B$5,"Atraso leve - seguimiento cercano ("&TEXT(H55,"0.0")&" p.p.)","Atraso crítico - requiere intervención ("&TEXT(H55,"0.0")&" p.p.)")))) -> En tiempo, según lo planificado | K55: En ejecución | L55: YEPEZ CROW HUGO SANTIAGO;#409 | M55: Ciberdefensa | N55: POA | O55: =IF(AND(E55<>"",YEAR(E55)=YEAR(Parametros!$B$3),MONTH(E55)>=10),1,0) -> 1 | P55: =IF(AND(E55<Parametros!$B$3,K55<>"Finalizado"),1,0) -> 0 | Q55: =IF(AND(E55>=Parametros!$B$3,E55<=Parametros!$B$3+30,K55<>"Finalizado"),1,0) -> 0
A56: CD-08 | B56: Estrategia de Automatización e implementación Ola 1 | C56: Automatizaciones 2025, Contención Radware, Akamai, Checkpoint | D56: 45778 | E56: 46081 | F56: 100 | G56: =IF(OR(D56="",E56="",E56<=D56),"",MIN(100,MAX(0,(Parametros!$B$3-D56)/(E56-D56)*100))) -> 100 | H56: =IF(G56="","",G56-F56) -> 0 | I56: =IF(K56="Finalizado","Verde",IF(G56="","Amarillo",IF(H56<=Parametros!$B$4,"Verde",IF(H56<=Parametros!$B$5,"Amarillo","Rojo")))) -> Verde | J56: =IF(K56="Finalizado","Completado",IF(G56="","Sin fecha válida - revisar plazos",IF(H56<=Parametros!$B$4,"En tiempo, según lo planificado",IF(H56<=Parametros!$B$5,"Atraso leve - seguimiento cercano ("&TEXT(H56,"0.0")&" p.p.)","Atraso crítico - requiere intervención ("&TEXT(H56,"0.0")&" p.p.)")))) -> Completado | K56: Finalizado | L56: BASTIDAS FLORES DANNY ALEXANDER;#288 | M56: Ciberdefensa | N56: POA | O56: =IF(AND(E56<>"",YEAR(E56)=YEAR(Parametros!$B$3),MONTH(E56)>=10),1,0) -> 0 | P56: =IF(AND(E56<Parametros!$B$3,K56<>"Finalizado"),1,0) -> 0 | Q56: =IF(AND(E56>=Parametros!$B$3,E56<=Parametros!$B$3+30,K56<>"Finalizado"),1,0) -> 0
A57: CD-09 | B57: Automatizaciones en triage/respuesta de alertas | C57: Definición de arquitectura, criterios y priorización de reglas para automatización | D57: 46090 | E57: 46216 | F57: 90 | G57: =IF(OR(D57="",E57="",E57<=D57),"",MIN(100,MAX(0,(Parametros!$B$3-D57)/(E57-D57)*100))) -> 100 | H57: =IF(G57="","",G57-F57) -> 10 | I57: =IF(K57="Finalizado","Verde",IF(G57="","Amarillo",IF(H57<=Parametros!$B$4,"Verde",IF(H57<=Parametros!$B$5,"Amarillo","Rojo")))) -> Amarillo | J57: =IF(K57="Finalizado","Completado",IF(G57="","Sin fecha válida - revisar plazos",IF(H57<=Parametros!$B$4,"En tiempo, según lo planificado",IF(H57<=Parametros!$B$5,"Atraso leve - seguimiento cercano ("&TEXT(H57,"0.0")&" p.p.)","Atraso crítico - requiere intervención ("&TEXT(H57,"0.0")&" p.p.)")))) -> Atraso leve - seguimiento cercano (10.0 p.p.) | K57: En ejecución | M57: Ciberdefensa | N57: POA | O57: =IF(AND(E57<>"",YEAR(E57)=YEAR(Parametros!$B$3),MONTH(E57)>=10),1,0) -> 0 | P57: =IF(AND(E57<Parametros!$B$3,K57<>"Finalizado"),1,0) -> 1 | Q57: =IF(AND(E57>=Parametros!$B$3,E57<=Parametros!$B$3+30,K57<>"Finalizado"),1,0) -> 0
A58: CD-09 | B58: Automatizaciones en triage/respuesta de alertas | C58: Implementación de automatizaciones - Playbook 1 | D58: 46104 | E58: 46142 | F58: 100 | G58: =IF(OR(D58="",E58="",E58<=D58),"",MIN(100,MAX(0,(Parametros!$B$3-D58)/(E58-D58)*100))) -> 100 | H58: =IF(G58="","",G58-F58) -> 0 | I58: =IF(K58="Finalizado","Verde",IF(G58="","Amarillo",IF(H58<=Parametros!$B$4,"Verde",IF(H58<=Parametros!$B$5,"Amarillo","Rojo")))) -> Verde | J58: =IF(K58="Finalizado","Completado",IF(G58="","Sin fecha válida - revisar plazos",IF(H58<=Parametros!$B$4,"En tiempo, según lo planificado",IF(H58<=Parametros!$B$5,"Atraso leve - seguimiento cercano ("&TEXT(H58,"0.0")&" p.p.)","Atraso crítico - requiere intervención ("&TEXT(H58,"0.0")&" p.p.)")))) -> Completado | K58: Finalizado | M58: Ciberdefensa | N58: POA | O58: =IF(AND(E58<>"",YEAR(E58)=YEAR(Parametros!$B$3),MONTH(E58)>=10),1,0) -> 0 | P58: =IF(AND(E58<Parametros!$B$3,K58<>"Finalizado"),1,0) -> 0 | Q58: =IF(AND(E58>=Parametros!$B$3,E58<=Parametros!$B$3+30,K58<>"Finalizado"),1,0) -> 0
A59: CD-09 | B59: Automatizaciones en triage/respuesta de alertas | C59: Implementación de automatizaciones - Playbook 2 | D59: 46237 | E59: 46295 | F59: 90 | G59: =IF(OR(D59="",E59="",E59<=D59),"",MIN(100,MAX(0,(Parametros!$B$3-D59)/(E59-D59)*100))) -> 36.206897 | H59: =IF(G59="","",G59-F59) -> -53.793103 | I59: =IF(K59="Finalizado","Verde",IF(G59="","Amarillo",IF(H59<=Parametros!$B$4,"Verde",IF(H59<=Parametros!$B$5,"Amarillo","Rojo")))) -> Verde | J59: =IF(K59="Finalizado","Completado",IF(G59="","Sin fecha válida - revisar plazos",IF(H59<=Parametros!$B$4,"En tiempo, según lo planificado",IF(H59<=Parametros!$B$5,"Atraso leve - seguimiento cercano ("&TEXT(H59,"0.0")&" p.p.)","Atraso crítico - requiere intervención ("&TEXT(H59,"0.0")&" p.p.)")))) -> En tiempo, según lo planificado | K59: En ejecución | M59: Ciberdefensa | N59: POA | O59: =IF(AND(E59<>"",YEAR(E59)=YEAR(Parametros!$B$3),MONTH(E59)>=10),1,0) -> 0 | P59: =IF(AND(E59<Parametros!$B$3,K59<>"Finalizado"),1,0) -> 0 | Q59: =IF(AND(E59>=Parametros!$B$3,E59<=Parametros!$B$3+30,K59<>"Finalizado"),1,0) -> 0
A60: CD-09 | B60: Automatizaciones en triage/respuesta de alertas | C60: Implementación de automatizaciones - Playbook 3 | D60: 46300 | E60: 46356 | F60: 0 | G60: =IF(OR(D60="",E60="",E60<=D60),"",MIN(100,MAX(0,(Parametros!$B$3-D60)/(E60-D60)*100))) -> 0 | H60: =IF(G60="","",G60-F60) -> 0 | I60: =IF(K60="Finalizado","Verde",IF(G60="","Amarillo",IF(H60<=Parametros!$B$4,"Verde",IF(H60<=Parametros!$B$5,"Amarillo","Rojo")))) -> Verde | J60: =IF(K60="Finalizado","Completado",IF(G60="","Sin fecha válida - revisar plazos",IF(H60<=Parametros!$B$4,"En tiempo, según lo planificado",IF(H60<=Parametros!$B$5,"Atraso leve - seguimiento cercano ("&TEXT(H60,"0.0")&" p.p.)","Atraso crítico - requiere intervención ("&TEXT(H60,"0.0")&" p.p.)")))) -> En tiempo, según lo planificado | K60: No iniciado | M60: Ciberdefensa | N60: POA | O60: =IF(AND(E60<>"",YEAR(E60)=YEAR(Parametros!$B$3),MONTH(E60)>=10),1,0) -> 1 | P60: =IF(AND(E60<Parametros!$B$3,K60<>"Finalizado"),1,0) -> 0 | Q60: =IF(AND(E60>=Parametros!$B$3,E60<=Parametros!$B$3+30,K60<>"Finalizado"),1,0) -> 0
A61: CD-09 | B61: Automatizaciones en triage/respuesta de alertas | C61: Validacion de herramientas para automatización | D61: 46034 | E61: 46081 | F61: 100 | G61: =IF(OR(D61="",E61="",E61<=D61),"",MIN(100,MAX(0,(Parametros!$B$3-D61)/(E61-D61)*100))) -> 100 | H61: =IF(G61="","",G61-F61) -> 0 | I61: =IF(K61="Finalizado","Verde",IF(G61="","Amarillo",IF(H61<=Parametros!$B$4,"Verde",IF(H61<=Parametros!$B$5,"Amarillo","Rojo")))) -> Verde | J61: =IF(K61="Finalizado","Completado",IF(G61="","Sin fecha válida - revisar plazos",IF(H61<=Parametros!$B$4,"En tiempo, según lo planificado",IF(H61<=Parametros!$B$5,"Atraso leve - seguimiento cercano ("&TEXT(H61,"0.0")&" p.p.)","Atraso crítico - requiere intervención ("&TEXT(H61,"0.0")&" p.p.)")))) -> Completado | K61: Finalizado | M61: Ciberdefensa | N61: POA | O61: =IF(AND(E61<>"",YEAR(E61)=YEAR(Parametros!$B$3),MONTH(E61)>=10),1,0) -> 0 | P61: =IF(AND(E61<Parametros!$B$3,K61<>"Finalizado"),1,0) -> 0 | Q61: =IF(AND(E61>=Parametros!$B$3,E61<=Parametros!$B$3+30,K61<>"Finalizado"),1,0) -> 0
A62: CD-09 | B62: Automatizaciones en triage/respuesta de alertas | C62: XSOAR pruebas en entorno de TEST | D62: 46146 | E62: 46233 | F62: 75 | G62: =IF(OR(D62="",E62="",E62<=D62),"",MIN(100,MAX(0,(Parametros!$B$3-D62)/(E62-D62)*100))) -> 100 | H62: =IF(G62="","",G62-F62) -> 25 | I62: =IF(K62="Finalizado","Verde",IF(G62="","Amarillo",IF(H62<=Parametros!$B$4,"Verde",IF(H62<=Parametros!$B$5,"Amarillo","Rojo")))) -> Rojo | J62: =IF(K62="Finalizado","Completado",IF(G62="","Sin fecha válida - revisar plazos",IF(H62<=Parametros!$B$4,"En tiempo, según lo planificado",IF(H62<=Parametros!$B$5,"Atraso leve - seguimiento cercano ("&TEXT(H62,"0.0")&" p.p.)","Atraso crítico - requiere intervención ("&TEXT(H62,"0.0")&" p.p.)")))) -> Atraso crítico - requiere intervención (25.0 p.p.) | K62: En ejecución | M62: Ciberdefensa | N62: POA | O62: =IF(AND(E62<>"",YEAR(E62)=YEAR(Parametros!$B$3),MONTH(E62)>=10),1,0) -> 0 | P62: =IF(AND(E62<Parametros!$B$3,K62<>"Finalizado"),1,0) -> 1 | Q62: =IF(AND(E62>=Parametros!$B$3,E62<=Parametros!$B$3+30,K62<>"Finalizado"),1,0) -> 0
A63: CD-10 | B63: Definición de proceso de Gestión de vulnerabilidades emergentes | C63: Definir proceso de gestión de vulnerabilidades emergentes. | D63: 45809 | E63: 46081 | F63: 100 | G63: =IF(OR(D63="",E63="",E63<=D63),"",MIN(100,MAX(0,(Parametros!$B$3-D63)/(E63-D63)*100))) -> 100 | H63: =IF(G63="","",G63-F63) -> 0 | I63: =IF(K63="Finalizado","Verde",IF(G63="","Amarillo",IF(H63<=Parametros!$B$4,"Verde",IF(H63<=Parametros!$B$5,"Amarillo","Rojo")))) -> Verde | J63: =IF(K63="Finalizado","Completado",IF(G63="","Sin fecha válida - revisar plazos",IF(H63<=Parametros!$B$4,"En tiempo, según lo planificado",IF(H63<=Parametros!$B$5,"Atraso leve - seguimiento cercano ("&TEXT(H63,"0.0")&" p.p.)","Atraso crítico - requiere intervención ("&TEXT(H63,"0.0")&" p.p.)")))) -> Completado | K63: Finalizado | L63: ORTIZ GUTIERREZ VICTOR ULISES;#387 | M63: Ciberdefensa | N63: POA | O63: =IF(AND(E63<>"",YEAR(E63)=YEAR(Parametros!$B$3),MONTH(E63)>=10),1,0) -> 0 | P63: =IF(AND(E63<Parametros!$B$3,K63<>"Finalizado"),1,0) -> 0 | Q63: =IF(AND(E63>=Parametros!$B$3,E63<=Parametros!$B$3+30,K63<>"Finalizado"),1,0) -> 0
A64: CD-11 | B64: Afinamiento y convergencia de Procesos SOC | C64: 1. Levantamiento de información | D64: 46027 | E64: 46090 | F64: 100 | G64: =IF(OR(D64="",E64="",E64<=D64),"",MIN(100,MAX(0,(Parametros!$B$3-D64)/(E64-D64)*100))) -> 100 | H64: =IF(G64="","",G64-F64) -> 0 | I64: =IF(K64="Finalizado","Verde",IF(G64="","Amarillo",IF(H64<=Parametros!$B$4,"Verde",IF(H64<=Parametros!$B$5,"Amarillo","Rojo")))) -> Verde | J64: =IF(K64="Finalizado","Completado",IF(G64="","Sin fecha válida - revisar plazos",IF(H64<=Parametros!$B$4,"En tiempo, según lo planificado",IF(H64<=Parametros!$B$5,"Atraso leve - seguimiento cercano ("&TEXT(H64,"0.0")&" p.p.)","Atraso crítico - requiere intervención ("&TEXT(H64,"0.0")&" p.p.)")))) -> Completado | K64: Finalizado | L64: AYALA NAREA GABRIEL SEBASTIAN;#496 | M64: Ciberdefensa | N64: POA | O64: =IF(AND(E64<>"",YEAR(E64)=YEAR(Parametros!$B$3),MONTH(E64)>=10),1,0) -> 0 | P64: =IF(AND(E64<Parametros!$B$3,K64<>"Finalizado"),1,0) -> 0 | Q64: =IF(AND(E64>=Parametros!$B$3,E64<=Parametros!$B$3+30,K64<>"Finalizado"),1,0) -> 0
A65: CD-11 | B65: Afinamiento y convergencia de Procesos SOC | C65: 2. Accionable 1: Panel de seguimiento. | D65: 46091 | E65: 46114 | F65: 100 | G65: =IF(OR(D65="",E65="",E65<=D65),"",MIN(100,MAX(0,(Parametros!$B$3-D65)/(E65-D65)*100))) -> 100 | H65: =IF(G65="","",G65-F65) -> 0 | I65: =IF(K65="Finalizado","Verde",IF(G65="","Amarillo",IF(H65<=Parametros!$B$4,"Verde",IF(H65<=Parametros!$B$5,"Amarillo","Rojo")))) -> Verde | J65: =IF(K65="Finalizado","Completado",IF(G65="","Sin fecha válida - revisar plazos",IF(H65<=Parametros!$B$4,"En tiempo, según lo planificado",IF(H65<=Parametros!$B$5,"Atraso leve - seguimiento cercano ("&TEXT(H65,"0.0")&" p.p.)","Atraso crítico - requiere intervención ("&TEXT(H65,"0.0")&" p.p.)")))) -> Completado | K65: Finalizado | M65: Ciberdefensa | N65: POA | O65: =IF(AND(E65<>"",YEAR(E65)=YEAR(Parametros!$B$3),MONTH(E65)>=10),1,0) -> 0 | P65: =IF(AND(E65<Parametros!$B$3,K65<>"Finalizado"),1,0) -> 0 | Q65: =IF(AND(E65>=Parametros!$B$3,E65<=Parametros!$B$3+30,K65<>"Finalizado"),1,0) -> 0
A66: CD-11 | B66: Afinamiento y convergencia de Procesos SOC | C66: 3. Accionable 2: Activación del proceso de análisis de efectividad de casos de uso | D66: 46204 | E66: 46264 | F66: 90 | G66: =IF(OR(D66="",E66="",E66<=D66),"",MIN(100,MAX(0,(Parametros!$B$3-D66)/(E66-D66)*100))) -> 90 | H66: =IF(G66="","",G66-F66) -> 0 | I66: =IF(K66="Finalizado","Verde",IF(G66="","Amarillo",IF(H66<=Parametros!$B$4,"Verde",IF(H66<=Parametros!$B$5,"Amarillo","Rojo")))) -> Verde | J66: =IF(K66="Finalizado","Completado",IF(G66="","Sin fecha válida - revisar plazos",IF(H66<=Parametros!$B$4,"En tiempo, según lo planificado",IF(H66<=Parametros!$B$5,"Atraso leve - seguimiento cercano ("&TEXT(H66,"0.0")&" p.p.)","Atraso crítico - requiere intervención ("&TEXT(H66,"0.0")&" p.p.)")))) -> En tiempo, según lo planificado | K66: En ejecución | M66: Ciberdefensa | N66: POA | O66: =IF(AND(E66<>"",YEAR(E66)=YEAR(Parametros!$B$3),MONTH(E66)>=10),1,0) -> 0 | P66: =IF(AND(E66<Parametros!$B$3,K66<>"Finalizado"),1,0) -> 0 | Q66: =IF(AND(E66>=Parametros!$B$3,E66<=Parametros!$B$3+30,K66<>"Finalizado"),1,0) -> 1
A67: CD-11 | B67: Afinamiento y convergencia de Procesos SOC | C67: 4. Accionable 3: División de instructivo de Alertas e Incidentes | D67: 46147 | E67: 46198 | F67: 100 | G67: =IF(OR(D67="",E67="",E67<=D67),"",MIN(100,MAX(0,(Parametros!$B$3-D67)/(E67-D67)*100))) -> 100 | H67: =IF(G67="","",G67-F67) -> 0 | I67: =IF(K67="Finalizado","Verde",IF(G67="","Amarillo",IF(H67<=Parametros!$B$4,"Verde",IF(H67<=Parametros!$B$5,"Amarillo","Rojo")))) -> Verde | J67: =IF(K67="Finalizado","Completado",IF(G67="","Sin fecha válida - revisar plazos",IF(H67<=Parametros!$B$4,"En tiempo, según lo planificado",IF(H67<=Parametros!$B$5,"Atraso leve - seguimiento cercano ("&TEXT(H67,"0.0")&" p.p.)","Atraso crítico - requiere intervención ("&TEXT(H67,"0.0")&" p.p.)")))) -> Completado | K67: Finalizado | M67: Ciberdefensa | N67: POA | O67: =IF(AND(E67<>"",YEAR(E67)=YEAR(Parametros!$B$3),MONTH(E67)>=10),1,0) -> 0 | P67: =IF(AND(E67<Parametros!$B$3,K67<>"Finalizado"),1,0) -> 0 | Q67: =IF(AND(E67>=Parametros!$B$3,E67<=Parametros!$B$3+30,K67<>"Finalizado"),1,0) -> 0
A68: CD-11 | B68: Afinamiento y convergencia de Procesos SOC | C68: 6. Accionable 5: Agregación de monitoreos de la plataforma | D68: 46266 | E68: 46295 | F68: 67 | G68: =IF(OR(D68="",E68="",E68<=D68),"",MIN(100,MAX(0,(Parametros!$B$3-D68)/(E68-D68)*100))) -> 0 | H68: =IF(G68="","",G68-F68) -> -67 | I68: =IF(K68="Finalizado","Verde",IF(G68="","Amarillo",IF(H68<=Parametros!$B$4,"Verde",IF(H68<=Parametros!$B$5,"Amarillo","Rojo")))) -> Verde | J68: =IF(K68="Finalizado","Completado",IF(G68="","Sin fecha válida - revisar plazos",IF(H68<=Parametros!$B$4,"En tiempo, según lo planificado",IF(H68<=Parametros!$B$5,"Atraso leve - seguimiento cercano ("&TEXT(H68,"0.0")&" p.p.)","Atraso crítico - requiere intervención ("&TEXT(H68,"0.0")&" p.p.)")))) -> En tiempo, según lo planificado | K68: En ejecución | M68: Ciberdefensa | N68: POA | O68: =IF(AND(E68<>"",YEAR(E68)=YEAR(Parametros!$B$3),MONTH(E68)>=10),1,0) -> 0 | P68: =IF(AND(E68<Parametros!$B$3,K68<>"Finalizado"),1,0) -> 0 | Q68: =IF(AND(E68>=Parametros!$B$3,E68<=Parametros!$B$3+30,K68<>"Finalizado"),1,0) -> 0
A69: CD-11 | B69: Afinamiento y convergencia de Procesos SOC | C69: 7. Accionable 6: Comienzo de utilización por los analistas de la guía de troubleshooting de fuentes | D69: 46235 | E69: 46265 | F69: 100 | G69: =IF(OR(D69="",E69="",E69<=D69),"",MIN(100,MAX(0,(Parametros!$B$3-D69)/(E69-D69)*100))) -> 76.666667 | H69: =IF(G69="","",G69-F69) -> -23.333333 | I69: =IF(K69="Finalizado","Verde",IF(G69="","Amarillo",IF(H69<=Parametros!$B$4,"Verde",IF(H69<=Parametros!$B$5,"Amarillo","Rojo")))) -> Verde | J69: =IF(K69="Finalizado","Completado",IF(G69="","Sin fecha válida - revisar plazos",IF(H69<=Parametros!$B$4,"En tiempo, según lo planificado",IF(H69<=Parametros!$B$5,"Atraso leve - seguimiento cercano ("&TEXT(H69,"0.0")&" p.p.)","Atraso crítico - requiere intervención ("&TEXT(H69,"0.0")&" p.p.)")))) -> Completado | K69: Finalizado | M69: Ciberdefensa | N69: POA | O69: =IF(AND(E69<>"",YEAR(E69)=YEAR(Parametros!$B$3),MONTH(E69)>=10),1,0) -> 0 | P69: =IF(AND(E69<Parametros!$B$3,K69<>"Finalizado"),1,0) -> 0 | Q69: =IF(AND(E69>=Parametros!$B$3,E69<=Parametros!$B$3+30,K69<>"Finalizado"),1,0) -> 0
A70: CD-12 | B70: Optimización del esquema de priorización de alertas de SOC | C70: Accionable 1: Preparación - Preparación de Base de datos con los campos y tablas separadas | D70: 46034 | E70: 46059 | F70: 100 | G70: =IF(OR(D70="",E70="",E70<=D70),"",MIN(100,MAX(0,(Parametros!$B$3-D70)/(E70-D70)*100))) -> 100 | H70: =IF(G70="","",G70-F70) -> 0 | I70: =IF(K70="Finalizado","Verde",IF(G70="","Amarillo",IF(H70<=Parametros!$B$4,"Verde",IF(H70<=Parametros!$B$5,"Amarillo","Rojo")))) -> Verde | J70: =IF(K70="Finalizado","Completado",IF(G70="","Sin fecha válida - revisar plazos",IF(H70<=Parametros!$B$4,"En tiempo, según lo planificado",IF(H70<=Parametros!$B$5,"Atraso leve - seguimiento cercano ("&TEXT(H70,"0.0")&" p.p.)","Atraso crítico - requiere intervención ("&TEXT(H70,"0.0")&" p.p.)")))) -> Completado | K70: Finalizado | M70: Ciberdefensa | N70: POA | O70: =IF(AND(E70<>"",YEAR(E70)=YEAR(Parametros!$B$3),MONTH(E70)>=10),1,0) -> 0 | P70: =IF(AND(E70<Parametros!$B$3,K70<>"Finalizado"),1,0) -> 0 | Q70: =IF(AND(E70>=Parametros!$B$3,E70<=Parametros!$B$3+30,K70<>"Finalizado"),1,0) -> 0
A71: CD-12 | B71: Optimización del esquema de priorización de alertas de SOC | C71: Accionable 2: Diagnostico - Baseline de efectividad (volumen, FP, incidentes, tiempo investigación) 7 meses | D71: 46062 | E71: 46129 | F71: 100 | G71: =IF(OR(D71="",E71="",E71<=D71),"",MIN(100,MAX(0,(Parametros!$B$3-D71)/(E71-D71)*100))) -> 100 | H71: =IF(G71="","",G71-F71) -> 0 | I71: =IF(K71="Finalizado","Verde",IF(G71="","Amarillo",IF(H71<=Parametros!$B$4,"Verde",IF(H71<=Parametros!$B$5,"Amarillo","Rojo")))) -> Verde | J71: =IF(K71="Finalizado","Completado",IF(G71="","Sin fecha válida - revisar plazos",IF(H71<=Parametros!$B$4,"En tiempo, según lo planificado",IF(H71<=Parametros!$B$5,"Atraso leve - seguimiento cercano ("&TEXT(H71,"0.0")&" p.p.)","Atraso crítico - requiere intervención ("&TEXT(H71,"0.0")&" p.p.)")))) -> Completado | K71: Finalizado | M71: Ciberdefensa | N71: POA | O71: =IF(AND(E71<>"",YEAR(E71)=YEAR(Parametros!$B$3),MONTH(E71)>=10),1,0) -> 0 | P71: =IF(AND(E71<Parametros!$B$3,K71<>"Finalizado"),1,0) -> 0 | Q71: =IF(AND(E71>=Parametros!$B$3,E71<=Parametros!$B$3+30,K71<>"Finalizado"),1,0) -> 0
A72: CD-12 | B72: Optimización del esquema de priorización de alertas de SOC | C72: Accionable 3: Modelo de severidad - Definir matriz de scoring (Impacto, Probabilidad, Fidelidad, Explotabilidad) + pesos | D72: 46132 | E72: 46233 | F72: 100 | G72: =IF(OR(D72="",E72="",E72<=D72),"",MIN(100,MAX(0,(Parametros!$B$3-D72)/(E72-D72)*100))) -> 100 | H72: =IF(G72="","",G72-F72) -> 0 | I72: =IF(K72="Finalizado","Verde",IF(G72="","Amarillo",IF(H72<=Parametros!$B$4,"Verde",IF(H72<=Parametros!$B$5,"Amarillo","Rojo")))) -> Verde | J72: =IF(K72="Finalizado","Completado",IF(G72="","Sin fecha válida - revisar plazos",IF(H72<=Parametros!$B$4,"En tiempo, según lo planificado",IF(H72<=Parametros!$B$5,"Atraso leve - seguimiento cercano ("&TEXT(H72,"0.0")&" p.p.)","Atraso crítico - requiere intervención ("&TEXT(H72,"0.0")&" p.p.)")))) -> Completado | K72: Finalizado | M72: Ciberdefensa | N72: POA | O72: =IF(AND(E72<>"",YEAR(E72)=YEAR(Parametros!$B$3),MONTH(E72)>=10),1,0) -> 0 | P72: =IF(AND(E72<Parametros!$B$3,K72<>"Finalizado"),1,0) -> 0 | Q72: =IF(AND(E72>=Parametros!$B$3,E72<=Parametros!$B$3+30,K72<>"Finalizado"),1,0) -> 0
A73: CD-12 | B73: Optimización del esquema de priorización de alertas de SOC | C73: Accionable 4: Recategorización - Revisión Bloque 1: reglas Críticas (recategorizar / justificar / correlacionar) - Revisión Bloque 2: reglas Altas (downgrade a Media si aplica + tuning) | D73: 46181 | E73: 46295 | F73: 0 | G73: =IF(OR(D73="",E73="",E73<=D73),"",MIN(100,MAX(0,(Parametros!$B$3-D73)/(E73-D73)*100))) -> 67.54386 | H73: =IF(G73="","",G73-F73) -> 67.54386 | I73: =IF(K73="Finalizado","Verde",IF(G73="","Amarillo",IF(H73<=Parametros!$B$4,"Verde",IF(H73<=Parametros!$B$5,"Amarillo","Rojo")))) -> Rojo | J73: =IF(K73="Finalizado","Completado",IF(G73="","Sin fecha válida - revisar plazos",IF(H73<=Parametros!$B$4,"En tiempo, según lo planificado",IF(H73<=Parametros!$B$5,"Atraso leve - seguimiento cercano ("&TEXT(H73,"0.0")&" p.p.)","Atraso crítico - requiere intervención ("&TEXT(H73,"0.0")&" p.p.)")))) -> Atraso crítico - requiere intervención (67.5 p.p.) | K73: Iniciado | M73: Ciberdefensa | N73: POA | O73: =IF(AND(E73<>"",YEAR(E73)=YEAR(Parametros!$B$3),MONTH(E73)>=10),1,0) -> 0 | P73: =IF(AND(E73<Parametros!$B$3,K73<>"Finalizado"),1,0) -> 0 | Q73: =IF(AND(E73>=Parametros!$B$3,E73<=Parametros!$B$3+30,K73<>"Finalizado"),1,0) -> 0
A74: CD-12 | B74: Optimización del esquema de priorización de alertas de SOC | C74: Accionable 5: Documentación y Difusión - Documentación de cambios realizados en producción (cambios severidad + reglas nuevas) + rollback plan | D74: 46296 | E74: 46346 | F74: 0 | G74: =IF(OR(D74="",E74="",E74<=D74),"",MIN(100,MAX(0,(Parametros!$B$3-D74)/(E74-D74)*100))) -> 0 | H74: =IF(G74="","",G74-F74) -> 0 | I74: =IF(K74="Finalizado","Verde",IF(G74="","Amarillo",IF(H74<=Parametros!$B$4,"Verde",IF(H74<=Parametros!$B$5,"Amarillo","Rojo")))) -> Verde | J74: =IF(K74="Finalizado","Completado",IF(G74="","Sin fecha válida - revisar plazos",IF(H74<=Parametros!$B$4,"En tiempo, según lo planificado",IF(H74<=Parametros!$B$5,"Atraso leve - seguimiento cercano ("&TEXT(H74,"0.0")&" p.p.)","Atraso crítico - requiere intervención ("&TEXT(H74,"0.0")&" p.p.)")))) -> En tiempo, según lo planificado | K74: No iniciado | M74: Ciberdefensa | N74: POA | O74: =IF(AND(E74<>"",YEAR(E74)=YEAR(Parametros!$B$3),MONTH(E74)>=10),1,0) -> 1 | P74: =IF(AND(E74<Parametros!$B$3,K74<>"Finalizado"),1,0) -> 0 | Q74: =IF(AND(E74>=Parametros!$B$3,E74<=Parametros!$B$3+30,K74<>"Finalizado"),1,0) -> 0
A75: CD-13 | B75: Automatización de ingesta y cierre de vulnerabilidades en la plataforma SAVI + | C75: 1.1 Integración con Snyk Open Source (SCA) -- Diseño de requerimiento funcional | D75: 46027 | E75: 46031 | F75: 100 | G75: =IF(OR(D75="",E75="",E75<=D75),"",MIN(100,MAX(0,(Parametros!$B$3-D75)/(E75-D75)*100))) -> 100 | H75: =IF(G75="","",G75-F75) -> 0 | I75: =IF(K75="Finalizado","Verde",IF(G75="","Amarillo",IF(H75<=Parametros!$B$4,"Verde",IF(H75<=Parametros!$B$5,"Amarillo","Rojo")))) -> Verde | J75: =IF(K75="Finalizado","Completado",IF(G75="","Sin fecha válida - revisar plazos",IF(H75<=Parametros!$B$4,"En tiempo, según lo planificado",IF(H75<=Parametros!$B$5,"Atraso leve - seguimiento cercano ("&TEXT(H75,"0.0")&" p.p.)","Atraso crítico - requiere intervención ("&TEXT(H75,"0.0")&" p.p.)")))) -> Completado | K75: Finalizado | L75: SANDOVAL HINOJOSA SANTIAGO ALEJANDRO;#410 | M75: Ciberdefensa | N75: POA | O75: =IF(AND(E75<>"",YEAR(E75)=YEAR(Parametros!$B$3),MONTH(E75)>=10),1,0) -> 0 | P75: =IF(AND(E75<Parametros!$B$3,K75<>"Finalizado"),1,0) -> 0 | Q75: =IF(AND(E75>=Parametros!$B$3,E75<=Parametros!$B$3+30,K75<>"Finalizado"),1,0) -> 0
A76: CD-13 | B76: Automatización de ingesta y cierre de vulnerabilidades en la plataforma SAVI + | C76: 1.2 Integración con Snyk Open Source (SCA) -- Integración del API de Snyk con SAVI | D76: 46034 | E76: 46052 | F76: 100 | G76: =IF(OR(D76="",E76="",E76<=D76),"",MIN(100,MAX(0,(Parametros!$B$3-D76)/(E76-D76)*100))) -> 100 | H76: =IF(G76="","",G76-F76) -> 0 | I76: =IF(K76="Finalizado","Verde",IF(G76="","Amarillo",IF(H76<=Parametros!$B$4,"Verde",IF(H76<=Parametros!$B$5,"Amarillo","Rojo")))) -> Verde | J76: =IF(K76="Finalizado","Completado",IF(G76="","Sin fecha válida - revisar plazos",IF(H76<=Parametros!$B$4,"En tiempo, según lo planificado",IF(H76<=Parametros!$B$5,"Atraso leve - seguimiento cercano ("&TEXT(H76,"0.0")&" p.p.)","Atraso crítico - requiere intervención ("&TEXT(H76,"0.0")&" p.p.)")))) -> Completado | K76: Finalizado | M76: Ciberdefensa | N76: POA | O76: =IF(AND(E76<>"",YEAR(E76)=YEAR(Parametros!$B$3),MONTH(E76)>=10),1,0) -> 0 | P76: =IF(AND(E76<Parametros!$B$3,K76<>"Finalizado"),1,0) -> 0 | Q76: =IF(AND(E76>=Parametros!$B$3,E76<=Parametros!$B$3+30,K76<>"Finalizado"),1,0) -> 0
A77: CD-13 | B77: Automatización de ingesta y cierre de vulnerabilidades en la plataforma SAVI + | C77: 1.3 Integración con Snyk Open Source (SCA) -- Pruebas funcionales | D77: 46052 | E77: 46056 | F77: 100 | G77: =IF(OR(D77="",E77="",E77<=D77),"",MIN(100,MAX(0,(Parametros!$B$3-D77)/(E77-D77)*100))) -> 100 | H77: =IF(G77="","",G77-F77) -> 0 | I77: =IF(K77="Finalizado","Verde",IF(G77="","Amarillo",IF(H77<=Parametros!$B$4,"Verde",IF(H77<=Parametros!$B$5,"Amarillo","Rojo")))) -> Verde | J77: =IF(K77="Finalizado","Completado",IF(G77="","Sin fecha válida - revisar plazos",IF(H77<=Parametros!$B$4,"En tiempo, según lo planificado",IF(H77<=Parametros!$B$5,"Atraso leve - seguimiento cercano ("&TEXT(H77,"0.0")&" p.p.)","Atraso crítico - requiere intervención ("&TEXT(H77,"0.0")&" p.p.)")))) -> Completado | K77: Finalizado | M77: Ciberdefensa | N77: POA | O77: =IF(AND(E77<>"",YEAR(E77)=YEAR(Parametros!$B$3),MONTH(E77)>=10),1,0) -> 0 | P77: =IF(AND(E77<Parametros!$B$3,K77<>"Finalizado"),1,0) -> 0 | Q77: =IF(AND(E77>=Parametros!$B$3,E77<=Parametros!$B$3+30,K77<>"Finalizado"),1,0) -> 0
A78: CD-13 | B78: Automatización de ingesta y cierre de vulnerabilidades en la plataforma SAVI + | C78: 1.4 Integración con Snyk Open Source (SCA) -- Paso a producción | D78: 46056 | E78: 46056 | F78: 100 | G78: =IF(OR(D78="",E78="",E78<=D78),"",MIN(100,MAX(0,(Parametros!$B$3-D78)/(E78-D78)*100))) | H78: =IF(G78="","",G78-F78) | I78: =IF(K78="Finalizado","Verde",IF(G78="","Amarillo",IF(H78<=Parametros!$B$4,"Verde",IF(H78<=Parametros!$B$5,"Amarillo","Rojo")))) -> Verde | J78: =IF(K78="Finalizado","Completado",IF(G78="","Sin fecha válida - revisar plazos",IF(H78<=Parametros!$B$4,"En tiempo, según lo planificado",IF(H78<=Parametros!$B$5,"Atraso leve - seguimiento cercano ("&TEXT(H78,"0.0")&" p.p.)","Atraso crítico - requiere intervención ("&TEXT(H78,"0.0")&" p.p.)")))) -> Completado | K78: Finalizado | M78: Ciberdefensa | N78: POA | O78: =IF(AND(E78<>"",YEAR(E78)=YEAR(Parametros!$B$3),MONTH(E78)>=10),1,0) -> 0 | P78: =IF(AND(E78<Parametros!$B$3,K78<>"Finalizado"),1,0) -> 0 | Q78: =IF(AND(E78>=Parametros!$B$3,E78<=Parametros!$B$3+30,K78<>"Finalizado"),1,0) -> 0
A79: CD-13 | B79: Automatización de ingesta y cierre de vulnerabilidades en la plataforma SAVI + | C79: 2.1 Integración con Prisma Cloud -- Diseño de requerimiento funcional | D79: 46062 | E79: 46064 | F79: 100 | G79: =IF(OR(D79="",E79="",E79<=D79),"",MIN(100,MAX(0,(Parametros!$B$3-D79)/(E79-D79)*100))) -> 100 | H79: =IF(G79="","",G79-F79) -> 0 | I79: =IF(K79="Finalizado","Verde",IF(G79="","Amarillo",IF(H79<=Parametros!$B$4,"Verde",IF(H79<=Parametros!$B$5,"Amarillo","Rojo")))) -> Verde | J79: =IF(K79="Finalizado","Completado",IF(G79="","Sin fecha válida - revisar plazos",IF(H79<=Parametros!$B$4,"En tiempo, según lo planificado",IF(H79<=Parametros!$B$5,"Atraso leve - seguimiento cercano ("&TEXT(H79,"0.0")&" p.p.)","Atraso crítico - requiere intervención ("&TEXT(H79,"0.0")&" p.p.)")))) -> Completado | K79: Finalizado | M79: Ciberdefensa | N79: POA | O79: =IF(AND(E79<>"",YEAR(E79)=YEAR(Parametros!$B$3),MONTH(E79)>=10),1,0) -> 0 | P79: =IF(AND(E79<Parametros!$B$3,K79<>"Finalizado"),1,0) -> 0 | Q79: =IF(AND(E79>=Parametros!$B$3,E79<=Parametros!$B$3+30,K79<>"Finalizado"),1,0) -> 0
A80: CD-13 | B80: Automatización de ingesta y cierre de vulnerabilidades en la plataforma SAVI + | C80: 2.2 Integración con Prisma Cloud -- Integración Prisma Cloud con SAVI, se obtiene información de Images, Hosts y Serverless. | D80: 46064 | E80: 46087 | F80: 100 | G80: =IF(OR(D80="",E80="",E80<=D80),"",MIN(100,MAX(0,(Parametros!$B$3-D80)/(E80-D80)*100))) -> 100 | H80: =IF(G80="","",G80-F80) -> 0 | I80: =IF(K80="Finalizado","Verde",IF(G80="","Amarillo",IF(H80<=Parametros!$B$4,"Verde",IF(H80<=Parametros!$B$5,"Amarillo","Rojo")))) -> Verde | J80: =IF(K80="Finalizado","Completado",IF(G80="","Sin fecha válida - revisar plazos",IF(H80<=Parametros!$B$4,"En tiempo, según lo planificado",IF(H80<=Parametros!$B$5,"Atraso leve - seguimiento cercano ("&TEXT(H80,"0.0")&" p.p.)","Atraso crítico - requiere intervención ("&TEXT(H80,"0.0")&" p.p.)")))) -> Completado | K80: Finalizado | M80: Ciberdefensa | N80: POA | O80: =IF(AND(E80<>"",YEAR(E80)=YEAR(Parametros!$B$3),MONTH(E80)>=10),1,0) -> 0 | P80: =IF(AND(E80<Parametros!$B$3,K80<>"Finalizado"),1,0) -> 0 | Q80: =IF(AND(E80>=Parametros!$B$3,E80<=Parametros!$B$3+30,K80<>"Finalizado"),1,0) -> 0
A81: CD-13 | B81: Automatización de ingesta y cierre de vulnerabilidades en la plataforma SAVI + | C81: 2.3 Integración con Prisma Cloud -- Diseño de los reportes y Dashboards | D81: 46090 | E81: 46101 | F81: 100 | G81: =IF(OR(D81="",E81="",E81<=D81),"",MIN(100,MAX(0,(Parametros!$B$3-D81)/(E81-D81)*100))) -> 100 | H81: =IF(G81="","",G81-F81) -> 0 | I81: =IF(K81="Finalizado","Verde",IF(G81="","Amarillo",IF(H81<=Parametros!$B$4,"Verde",IF(H81<=Parametros!$B$5,"Amarillo","Rojo")))) -> Verde | J81: =IF(K81="Finalizado","Completado",IF(G81="","Sin fecha válida - revisar plazos",IF(H81<=Parametros!$B$4,"En tiempo, según lo planificado",IF(H81<=Parametros!$B$5,"Atraso leve - seguimiento cercano ("&TEXT(H81,"0.0")&" p.p.)","Atraso crítico - requiere intervención ("&TEXT(H81,"0.0")&" p.p.)")))) -> Completado | K81: Finalizado | M81: Ciberdefensa | N81: POA | O81: =IF(AND(E81<>"",YEAR(E81)=YEAR(Parametros!$B$3),MONTH(E81)>=10),1,0) -> 0 | P81: =IF(AND(E81<Parametros!$B$3,K81<>"Finalizado"),1,0) -> 0 | Q81: =IF(AND(E81>=Parametros!$B$3,E81<=Parametros!$B$3+30,K81<>"Finalizado"),1,0) -> 0
A82: CD-13 | B82: Automatización de ingesta y cierre de vulnerabilidades en la plataforma SAVI + | C82: 2.4 Integración con Prisma Cloud -- Pruebas funcionales | D82: 46104 | E82: 46105 | F82: 100 | G82: =IF(OR(D82="",E82="",E82<=D82),"",MIN(100,MAX(0,(Parametros!$B$3-D82)/(E82-D82)*100))) -> 100 | H82: =IF(G82="","",G82-F82) -> 0 | I82: =IF(K82="Finalizado","Verde",IF(G82="","Amarillo",IF(H82<=Parametros!$B$4,"Verde",IF(H82<=Parametros!$B$5,"Amarillo","Rojo")))) -> Verde | J82: =IF(K82="Finalizado","Completado",IF(G82="","Sin fecha válida - revisar plazos",IF(H82<=Parametros!$B$4,"En tiempo, según lo planificado",IF(H82<=Parametros!$B$5,"Atraso leve - seguimiento cercano ("&TEXT(H82,"0.0")&" p.p.)","Atraso crítico - requiere intervención ("&TEXT(H82,"0.0")&" p.p.)")))) -> Completado | K82: Finalizado | M82: Ciberdefensa | N82: POA | O82: =IF(AND(E82<>"",YEAR(E82)=YEAR(Parametros!$B$3),MONTH(E82)>=10),1,0) -> 0 | P82: =IF(AND(E82<Parametros!$B$3,K82<>"Finalizado"),1,0) -> 0 | Q82: =IF(AND(E82>=Parametros!$B$3,E82<=Parametros!$B$3+30,K82<>"Finalizado"),1,0) -> 0
A83: CD-13 | B83: Automatización de ingesta y cierre de vulnerabilidades en la plataforma SAVI + | C83: 2.5 Integración con Prisma Cloud -- Paso a producción | D83: 46105 | E83: 46107 | F83: 100 | G83: =IF(OR(D83="",E83="",E83<=D83),"",MIN(100,MAX(0,(Parametros!$B$3-D83)/(E83-D83)*100))) -> 100 | H83: =IF(G83="","",G83-F83) -> 0 | I83: =IF(K83="Finalizado","Verde",IF(G83="","Amarillo",IF(H83<=Parametros!$B$4,"Verde",IF(H83<=Parametros!$B$5,"Amarillo","Rojo")))) -> Verde | J83: =IF(K83="Finalizado","Completado",IF(G83="","Sin fecha válida - revisar plazos",IF(H83<=Parametros!$B$4,"En tiempo, según lo planificado",IF(H83<=Parametros!$B$5,"Atraso leve - seguimiento cercano ("&TEXT(H83,"0.0")&" p.p.)","Atraso crítico - requiere intervención ("&TEXT(H83,"0.0")&" p.p.)")))) -> Completado | K83: Finalizado | M83: Ciberdefensa | N83: POA | O83: =IF(AND(E83<>"",YEAR(E83)=YEAR(Parametros!$B$3),MONTH(E83)>=10),1,0) -> 0 | P83: =IF(AND(E83<Parametros!$B$3,K83<>"Finalizado"),1,0) -> 0 | Q83: =IF(AND(E83>=Parametros!$B$3,E83<=Parametros!$B$3+30,K83<>"Finalizado"),1,0) -> 0
A84: CD-13 | B84: Automatización de ingesta y cierre de vulnerabilidades en la plataforma SAVI + | C84: 3.1 Integración con Snyk Code (SAST) -- Diseño de requerimiento funcional | D84: 46069 | E84: 46073 | F84: 100 | G84: =IF(OR(D84="",E84="",E84<=D84),"",MIN(100,MAX(0,(Parametros!$B$3-D84)/(E84-D84)*100))) -> 100 | H84: =IF(G84="","",G84-F84) -> 0 | I84: =IF(K84="Finalizado","Verde",IF(G84="","Amarillo",IF(H84<=Parametros!$B$4,"Verde",IF(H84<=Parametros!$B$5,"Amarillo","Rojo")))) -> Verde | J84: =IF(K84="Finalizado","Completado",IF(G84="","Sin fecha válida - revisar plazos",IF(H84<=Parametros!$B$4,"En tiempo, según lo planificado",IF(H84<=Parametros!$B$5,"Atraso leve - seguimiento cercano ("&TEXT(H84,"0.0")&" p.p.)","Atraso crítico - requiere intervención ("&TEXT(H84,"0.0")&" p.p.)")))) -> Completado | K84: Finalizado | M84: Ciberdefensa | N84: POA | O84: =IF(AND(E84<>"",YEAR(E84)=YEAR(Parametros!$B$3),MONTH(E84)>=10),1,0) -> 0 | P84: =IF(AND(E84<Parametros!$B$3,K84<>"Finalizado"),1,0) -> 0 | Q84: =IF(AND(E84>=Parametros!$B$3,E84<=Parametros!$B$3+30,K84<>"Finalizado"),1,0) -> 0
A85: CD-13 | B85: Automatización de ingesta y cierre de vulnerabilidades en la plataforma SAVI + | C85: 3.2 Integración con Snyk Code (SAST) -- Integración del API de Snyk con SAVI | D85: 46076 | E85: 46087 | F85: 100 | G85: =IF(OR(D85="",E85="",E85<=D85),"",MIN(100,MAX(0,(Parametros!$B$3-D85)/(E85-D85)*100))) -> 100 | H85: =IF(G85="","",G85-F85) -> 0 | I85: =IF(K85="Finalizado","Verde",IF(G85="","Amarillo",IF(H85<=Parametros!$B$4,"Verde",IF(H85<=Parametros!$B$5,"Amarillo","Rojo")))) -> Verde | J85: =IF(K85="Finalizado","Completado",IF(G85="","Sin fecha válida - revisar plazos",IF(H85<=Parametros!$B$4,"En tiempo, según lo planificado",IF(H85<=Parametros!$B$5,"Atraso leve - seguimiento cercano ("&TEXT(H85,"0.0")&" p.p.)","Atraso crítico - requiere intervención ("&TEXT(H85,"0.0")&" p.p.)")))) -> Completado | K85: Finalizado | M85: Ciberdefensa | N85: POA | O85: =IF(AND(E85<>"",YEAR(E85)=YEAR(Parametros!$B$3),MONTH(E85)>=10),1,0) -> 0 | P85: =IF(AND(E85<Parametros!$B$3,K85<>"Finalizado"),1,0) -> 0 | Q85: =IF(AND(E85>=Parametros!$B$3,E85<=Parametros!$B$3+30,K85<>"Finalizado"),1,0) -> 0
A86: CD-13 | B86: Automatización de ingesta y cierre de vulnerabilidades en la plataforma SAVI + | C86: 3.3 Integración con Snyk Code (SAST) -- Pruebas funcionales | D86: 46090 | E86: 46091 | F86: 100 | G86: =IF(OR(D86="",E86="",E86<=D86),"",MIN(100,MAX(0,(Parametros!$B$3-D86)/(E86-D86)*100))) -> 100 | H86: =IF(G86="","",G86-F86) -> 0 | I86: =IF(K86="Finalizado","Verde",IF(G86="","Amarillo",IF(H86<=Parametros!$B$4,"Verde",IF(H86<=Parametros!$B$5,"Amarillo","Rojo")))) -> Verde | J86: =IF(K86="Finalizado","Completado",IF(G86="","Sin fecha válida - revisar plazos",IF(H86<=Parametros!$B$4,"En tiempo, según lo planificado",IF(H86<=Parametros!$B$5,"Atraso leve - seguimiento cercano ("&TEXT(H86,"0.0")&" p.p.)","Atraso crítico - requiere intervención ("&TEXT(H86,"0.0")&" p.p.)")))) -> Completado | K86: Finalizado | M86: Ciberdefensa | N86: POA | O86: =IF(AND(E86<>"",YEAR(E86)=YEAR(Parametros!$B$3),MONTH(E86)>=10),1,0) -> 0 | P86: =IF(AND(E86<Parametros!$B$3,K86<>"Finalizado"),1,0) -> 0 | Q86: =IF(AND(E86>=Parametros!$B$3,E86<=Parametros!$B$3+30,K86<>"Finalizado"),1,0) -> 0
A87: CD-13 | B87: Automatización de ingesta y cierre de vulnerabilidades en la plataforma SAVI + | C87: 3.4 Integración con Snyk Code (SAST) -- Paso a producción | D87: 46092 | E87: 46092 | F87: 100 | G87: =IF(OR(D87="",E87="",E87<=D87),"",MIN(100,MAX(0,(Parametros!$B$3-D87)/(E87-D87)*100))) | H87: =IF(G87="","",G87-F87) | I87: =IF(K87="Finalizado","Verde",IF(G87="","Amarillo",IF(H87<=Parametros!$B$4,"Verde",IF(H87<=Parametros!$B$5,"Amarillo","Rojo")))) -> Verde | J87: =IF(K87="Finalizado","Completado",IF(G87="","Sin fecha válida - revisar plazos",IF(H87<=Parametros!$B$4,"En tiempo, según lo planificado",IF(H87<=Parametros!$B$5,"Atraso leve - seguimiento cercano ("&TEXT(H87,"0.0")&" p.p.)","Atraso crítico - requiere intervención ("&TEXT(H87,"0.0")&" p.p.)")))) -> Completado | K87: Finalizado | M87: Ciberdefensa | N87: POA | O87: =IF(AND(E87<>"",YEAR(E87)=YEAR(Parametros!$B$3),MONTH(E87)>=10),1,0) -> 0 | P87: =IF(AND(E87<Parametros!$B$3,K87<>"Finalizado"),1,0) -> 0 | Q87: =IF(AND(E87>=Parametros!$B$3,E87<=Parametros!$B$3+30,K87<>"Finalizado"),1,0) -> 0
... A103: CD-13 | B103: Automatización de ingesta y cierre de vulnerabilidades en la plataforma SAVI + | C103: 7.4 Integración con Tenable -- Paso a producción | D103: 46356 | E103: 46387 | F103: 0 | G103: =IF(OR(D103="",E103="",E103<=D103),"",MIN(100,MAX(0,(Parametros!$B$3-D103)/(E103-D103)*100))) -> 0 | H103: =IF(G103="","",G103-F103) -> 0 | I103: =IF(K103="Finalizado","Verde",IF(G103="","Amarillo",IF(H103<=Parametros!$B$4,"Verde",IF(H103<=Parametros!$B$5,"Amarillo","Rojo")))) -> Verde | J103: =IF(K103="Finalizado","Completado",IF(G103="","Sin fecha válida - revisar plazos",IF(H103<=Parametros!$B$4,"En tiempo, según lo planificado",IF(H103<=Parametros!$B$5,"Atraso leve - seguimiento cercano ("&TEXT(H103,"0.0")&" p.p.)","Atraso crítico - requiere intervención ("&TEXT(H103,"0.0")&" p.p.)")))) -> En tiempo, según lo planificado | K103: No iniciado | M103: Ciberdefensa | N103: POA | O103: =IF(AND(E103<>"",YEAR(E103)=YEAR(Parametros!$B$3),MONTH(E103)>=10),1,0) -> 1 | P103: =IF(AND(E103<Parametros!$B$3,K103<>"Finalizado"),1,0) -> 0 | Q103: =IF(AND(E103>=Parametros!$B$3,E103<=Parametros!$B$3+30,K103<>"Finalizado"),1,0) -> 0
A104: CD-14 | B104: Definición de lineamientos para la identificación, remediación y verificación de vulnerabilidades en servicios PaaS. | C104: Definición del modelo de gestión de vulnerabilidades en servicios PaaS | D104: 46082 | E104: 46387 | F104: 40 | G104: =IF(OR(D104="",E104="",E104<=D104),"",MIN(100,MAX(0,(Parametros!$B$3-D104)/(E104-D104)*100))) -> 57.704918 | H104: =IF(G104="","",G104-F104) -> 17.704918 | I104: =IF(K104="Finalizado","Verde",IF(G104="","Amarillo",IF(H104<=Parametros!$B$4,"Verde",IF(H104<=Parametros!$B$5,"Amarillo","Rojo")))) -> Amarillo | J104: =IF(K104="Finalizado","Completado",IF(G104="","Sin fecha válida - revisar plazos",IF(H104<=Parametros!$B$4,"En tiempo, según lo planificado",IF(H104<=Parametros!$B$5,"Atraso leve - seguimiento cercano ("&TEXT(H104,"0.0")&" p.p.)","Atraso crítico - requiere intervención ("&TEXT(H104,"0.0")&" p.p.)")))) -> Atraso leve - seguimiento cercano (17.7 p.p.) | K104: En ejecución | L104: ORTIZ GUTIERREZ VICTOR ULISES;#387 | M104: Ciberdefensa | N104: POA | O104: =IF(AND(E104<>"",YEAR(E104)=YEAR(Parametros!$B$3),MONTH(E104)>=10),1,0) -> 1 | P104: =IF(AND(E104<Parametros!$B$3,K104<>"Finalizado"),1,0) -> 0 | Q104: =IF(AND(E104>=Parametros!$B$3,E104<=Parametros!$B$3+30,K104<>"Finalizado"),1,0) -> 0
A105: CD-15 | B105: Automatización del Proceso de Monitoreo y Generación de Reportes de Cumplimiento de Hardening para Iniciativas / Proyectos | C105: Carga y normalización de inventarios para servidores Cloud y Onpremise | D105: 46174 | E105: 46234 | F105: 100 | G105: =IF(OR(D105="",E105="",E105<=D105),"",MIN(100,MAX(0,(Parametros!$B$3-D105)/(E105-D105)*100))) -> 100 | H105: =IF(G105="","",G105-F105) -> 0 | I105: =IF(K105="Finalizado","Verde",IF(G105="","Amarillo",IF(H105<=Parametros!$B$4,"Verde",IF(H105<=Parametros!$B$5,"Amarillo","Rojo")))) -> Verde | J105: =IF(K105="Finalizado","Completado",IF(G105="","Sin fecha válida - revisar plazos",IF(H105<=Parametros!$B$4,"En tiempo, según lo planificado",IF(H105<=Parametros!$B$5,"Atraso leve - seguimiento cercano ("&TEXT(H105,"0.0")&" p.p.)","Atraso crítico - requiere intervención ("&TEXT(H105,"0.0")&" p.p.)")))) -> Completado | K105: Finalizado | M105: Ciberdefensa | N105: POA | O105: =IF(AND(E105<>"",YEAR(E105)=YEAR(Parametros!$B$3),MONTH(E105)>=10),1,0) -> 0 | P105: =IF(AND(E105<Parametros!$B$3,K105<>"Finalizado"),1,0) -> 0 | Q105: =IF(AND(E105>=Parametros!$B$3,E105<=Parametros!$B$3+30,K105<>"Finalizado"),1,0) -> 0
A106: CD-15 | B106: Automatización del Proceso de Monitoreo y Generación de Reportes de Cumplimiento de Hardening para Iniciativas / Proyectos | C106: Definición del alcance funcional y técnico de la automatización Servidores Windows y Unix Cloud y Onpremise | D106: 46143 | E106: 46223 | F106: 100 | G106: =IF(OR(D106="",E106="",E106<=D106),"",MIN(100,MAX(0,(Parametros!$B$3-D106)/(E106-D106)*100))) -> 100 | H106: =IF(G106="","",G106-F106) -> 0 | I106: =IF(K106="Finalizado","Verde",IF(G106="","Amarillo",IF(H106<=Parametros!$B$4,"Verde",IF(H106<=Parametros!$B$5,"Amarillo","Rojo")))) -> Verde | J106: =IF(K106="Finalizado","Completado",IF(G106="","Sin fecha válida - revisar plazos",IF(H106<=Parametros!$B$4,"En tiempo, según lo planificado",IF(H106<=Parametros!$B$5,"Atraso leve - seguimiento cercano ("&TEXT(H106,"0.0")&" p.p.)","Atraso crítico - requiere intervención ("&TEXT(H106,"0.0")&" p.p.)")))) -> Completado | K106: Finalizado | L106: ONATE ORTEGA NATHALY CAROLINA;#386 | M106: Ciberdefensa | N106: POA | O106: =IF(AND(E106<>"",YEAR(E106)=YEAR(Parametros!$B$3),MONTH(E106)>=10),1,0) -> 0 | P106: =IF(AND(E106<Parametros!$B$3,K106<>"Finalizado"),1,0) -> 0 | Q106: =IF(AND(E106>=Parametros!$B$3,E106<=Parametros!$B$3+30,K106<>"Finalizado"),1,0) -> 0
A107: CD-15 | B107: Automatización del Proceso de Monitoreo y Generación de Reportes de Cumplimiento de Hardening para Iniciativas / Proyectos | C107: Documentación, cierre y entrega operativa del proceso automatizado | D107: 46357 | E107: 46387 | F107: 0 | G107: =IF(OR(D107="",E107="",E107<=D107),"",MIN(100,MAX(0,(Parametros!$B$3-D107)/(E107-D107)*100))) -> 0 | H107: =IF(G107="","",G107-F107) -> 0 | I107: =IF(K107="Finalizado","Verde",IF(G107="","Amarillo",IF(H107<=Parametros!$B$4,"Verde",IF(H107<=Parametros!$B$5,"Amarillo","Rojo")))) -> Verde | J107: =IF(K107="Finalizado","Completado",IF(G107="","Sin fecha válida - revisar plazos",IF(H107<=Parametros!$B$4,"En tiempo, según lo planificado",IF(H107<=Parametros!$B$5,"Atraso leve - seguimiento cercano ("&TEXT(H107,"0.0")&" p.p.)","Atraso crítico - requiere intervención ("&TEXT(H107,"0.0")&" p.p.)")))) -> En tiempo, según lo planificado | K107: No iniciado | M107: Ciberdefensa | N107: POA | O107: =IF(AND(E107<>"",YEAR(E107)=YEAR(Parametros!$B$3),MONTH(E107)>=10),1,0) -> 1 | P107: =IF(AND(E107<Parametros!$B$3,K107<>"Finalizado"),1,0) -> 0 | Q107: =IF(AND(E107>=Parametros!$B$3,E107<=Parametros!$B$3+30,K107<>"Finalizado"),1,0) -> 0
A108: CD-15 | B108: Automatización del Proceso de Monitoreo y Generación de Reportes de Cumplimiento de Hardening para Iniciativas / Proyectos | C108: Generación de dashboards de cumplimiento para servidores Cloud | D108: 46266 | E108: 46326 | F108: 0 | G108: =IF(OR(D108="",E108="",E108<=D108),"",MIN(100,MAX(0,(Parametros!$B$3-D108)/(E108-D108)*100))) -> 0 | H108: =IF(G108="","",G108-F108) -> 0 | I108: =IF(K108="Finalizado","Verde",IF(G108="","Amarillo",IF(H108<=Parametros!$B$4,"Verde",IF(H108<=Parametros!$B$5,"Amarillo","Rojo")))) -> Verde | J108: =IF(K108="Finalizado","Completado",IF(G108="","Sin fecha válida - revisar plazos",IF(H108<=Parametros!$B$4,"En tiempo, según lo planificado",IF(H108<=Parametros!$B$5,"Atraso leve - seguimiento cercano ("&TEXT(H108,"0.0")&" p.p.)","Atraso crítico - requiere intervención ("&TEXT(H108,"0.0")&" p.p.)")))) -> En tiempo, según lo planificado | K108: No iniciado | M108: Ciberdefensa | N108: POA | O108: =IF(AND(E108<>"",YEAR(E108)=YEAR(Parametros!$B$3),MONTH(E108)>=10),1,0) -> 1 | P108: =IF(AND(E108<Parametros!$B$3,K108<>"Finalizado"),1,0) -> 0 | Q108: =IF(AND(E108>=Parametros!$B$3,E108<=Parametros!$B$3+30,K108<>"Finalizado"),1,0) -> 0
A109: CD-15 | B109: Automatización del Proceso de Monitoreo y Generación de Reportes de Cumplimiento de Hardening para Iniciativas / Proyectos | C109: Generación de dashboards de cumplimiento para servidores Onpremise | D109: 46296 | E109: 46356 | F109: 0 | G109: =IF(OR(D109="",E109="",E109<=D109),"",MIN(100,MAX(0,(Parametros!$B$3-D109)/(E109-D109)*100))) -> 0 | H109: =IF(G109="","",G109-F109) -> 0 | I109: =IF(K109="Finalizado","Verde",IF(G109="","Amarillo",IF(H109<=Parametros!$B$4,"Verde",IF(H109<=Parametros!$B$5,"Amarillo","Rojo")))) -> Verde | J109: =IF(K109="Finalizado","Completado",IF(G109="","Sin fecha válida - revisar plazos",IF(H109<=Parametros!$B$4,"En tiempo, según lo planificado",IF(H109<=Parametros!$B$5,"Atraso leve - seguimiento cercano ("&TEXT(H109,"0.0")&" p.p.)","Atraso crítico - requiere intervención ("&TEXT(H109,"0.0")&" p.p.)")))) -> En tiempo, según lo planificado | K109: No iniciado | M109: Ciberdefensa | N109: POA | O109: =IF(AND(E109<>"",YEAR(E109)=YEAR(Parametros!$B$3),MONTH(E109)>=10),1,0) -> 1 | P109: =IF(AND(E109<Parametros!$B$3,K109<>"Finalizado"),1,0) -> 0 | Q109: =IF(AND(E109>=Parametros!$B$3,E109<=Parametros!$B$3+30,K109<>"Finalizado"),1,0) -> 0
A110: CD-15 | B110: Automatización del Proceso de Monitoreo y Generación de Reportes de Cumplimiento de Hardening para Iniciativas / Proyectos | C110: Procesamiento y validación de resultados de Línea Base para servidores Cloud | D110: 46235 | E110: 46295 | F110: 0 | G110: =IF(OR(D110="",E110="",E110<=D110),"",MIN(100,MAX(0,(Parametros!$B$3-D110)/(E110-D110)*100))) -> 38.333333 | H110: =IF(G110="","",G110-F110) -> 38.333333 | I110: =IF(K110="Finalizado","Verde",IF(G110="","Amarillo",IF(H110<=Parametros!$B$4,"Verde",IF(H110<=Parametros!$B$5,"Amarillo","Rojo")))) -> Rojo | J110: =IF(K110="Finalizado","Completado",IF(G110="","Sin fecha válida - revisar plazos",IF(H110<=Parametros!$B$4,"En tiempo, según lo planificado",IF(H110<=Parametros!$B$5,"Atraso leve - seguimiento cercano ("&TEXT(H110,"0.0")&" p.p.)","Atraso crítico - requiere intervención ("&TEXT(H110,"0.0")&" p.p.)")))) -> Atraso crítico - requiere intervención (38.3 p.p.) | K110: No iniciado | M110: Ciberdefensa | N110: POA | O110: =IF(AND(E110<>"",YEAR(E110)=YEAR(Parametros!$B$3),MONTH(E110)>=10),1,0) -> 0 | P110: =IF(AND(E110<Parametros!$B$3,K110<>"Finalizado"),1,0) -> 0 | Q110: =IF(AND(E110>=Parametros!$B$3,E110<=Parametros!$B$3+30,K110<>"Finalizado"),1,0) -> 0
A111: CD-15 | B111: Automatización del Proceso de Monitoreo y Generación de Reportes de Cumplimiento de Hardening para Iniciativas / Proyectos | C111: Procesamiento y validación de resultados de Línea Base para servidores Onpremise | D111: 46266 | E111: 46326 | F111: 0 | G111: =IF(OR(D111="",E111="",E111<=D111),"",MIN(100,MAX(0,(Parametros!$B$3-D111)/(E111-D111)*100))) -> 0 | H111: =IF(G111="","",G111-F111) -> 0 | I111: =IF(K111="Finalizado","Verde",IF(G111="","Amarillo",IF(H111<=Parametros!$B$4,"Verde",IF(H111<=Parametros!$B$5,"Amarillo","Rojo")))) -> Verde | J111: =IF(K111="Finalizado","Completado",IF(G111="","Sin fecha válida - revisar plazos",IF(H111<=Parametros!$B$4,"En tiempo, según lo planificado",IF(H111<=Parametros!$B$5,"Atraso leve - seguimiento cercano ("&TEXT(H111,"0.0")&" p.p.)","Atraso crítico - requiere intervención ("&TEXT(H111,"0.0")&" p.p.)")))) -> En tiempo, según lo planificado | K111: No iniciado | M111: Ciberdefensa | N111: POA | O111: =IF(AND(E111<>"",YEAR(E111)=YEAR(Parametros!$B$3),MONTH(E111)>=10),1,0) -> 1 | P111: =IF(AND(E111<Parametros!$B$3,K111<>"Finalizado"),1,0) -> 0 | Q111: =IF(AND(E111>=Parametros!$B$3,E111<=Parametros!$B$3+30,K111<>"Finalizado"),1,0) -> 0
A112: CD-15 | B112: Automatización del Proceso de Monitoreo y Generación de Reportes de Cumplimiento de Hardening para Iniciativas / Proyectos | C112: Programación de la lógica de escaneos para servidores Cloud | D112: 46224 | E112: 46265 | F112: 80 | G112: =IF(OR(D112="",E112="",E112<=D112),"",MIN(100,MAX(0,(Parametros!$B$3-D112)/(E112-D112)*100))) -> 82.926829 | H112: =IF(G112="","",G112-F112) -> 2.9268293 | I112: =IF(K112="Finalizado","Verde",IF(G112="","Amarillo",IF(H112<=Parametros!$B$4,"Verde",IF(H112<=Parametros!$B$5,"Amarillo","Rojo")))) -> Verde | J112: =IF(K112="Finalizado","Completado",IF(G112="","Sin fecha válida - revisar plazos",IF(H112<=Parametros!$B$4,"En tiempo, según lo planificado",IF(H112<=Parametros!$B$5,"Atraso leve - seguimiento cercano ("&TEXT(H112,"0.0")&" p.p.)","Atraso crítico - requiere intervención ("&TEXT(H112,"0.0")&" p.p.)")))) -> En tiempo, según lo planificado | K112: Iniciado | M112: Ciberdefensa | N112: POA | O112: =IF(AND(E112<>"",YEAR(E112)=YEAR(Parametros!$B$3),MONTH(E112)>=10),1,0) -> 0 | P112: =IF(AND(E112<Parametros!$B$3,K112<>"Finalizado"),1,0) -> 0 | Q112: =IF(AND(E112>=Parametros!$B$3,E112<=Parametros!$B$3+30,K112<>"Finalizado"),1,0) -> 1
A113: CD-15 | B113: Automatización del Proceso de Monitoreo y Generación de Reportes de Cumplimiento de Hardening para Iniciativas / Proyectos | C113: Programación de la lógica de escaneos para servidores Onpremise | D113: 46266 | E113: 46326 | F113: 0 | G113: =IF(OR(D113="",E113="",E113<=D113),"",MIN(100,MAX(0,(Parametros!$B$3-D113)/(E113-D113)*100))) -> 0 | H113: =IF(G113="","",G113-F113) -> 0 | I113: =IF(K113="Finalizado","Verde",IF(G113="","Amarillo",IF(H113<=Parametros!$B$4,"Verde",IF(H113<=Parametros!$B$5,"Amarillo","Rojo")))) -> Verde | J113: =IF(K113="Finalizado","Completado",IF(G113="","Sin fecha válida - revisar plazos",IF(H113<=Parametros!$B$4,"En tiempo, según lo planificado",IF(H113<=Parametros!$B$5,"Atraso leve - seguimiento cercano ("&TEXT(H113,"0.0")&" p.p.)","Atraso crítico - requiere intervención ("&TEXT(H113,"0.0")&" p.p.)")))) -> En tiempo, según lo planificado | K113: No iniciado | M113: Ciberdefensa | N113: POA | O113: =IF(AND(E113<>"",YEAR(E113)=YEAR(Parametros!$B$3),MONTH(E113)>=10),1,0) -> 1 | P113: =IF(AND(E113<Parametros!$B$3,K113<>"Finalizado"),1,0) -> 0 | Q113: =IF(AND(E113>=Parametros!$B$3,E113<=Parametros!$B$3+30,K113<>"Finalizado"),1,0) -> 0
A114: CD-15 | B114: Automatización del Proceso de Monitoreo y Generación de Reportes de Cumplimiento de Hardening para Iniciativas / Proyectos | C114: Pruebas integrales, ajustes y validación del proceso automatizado | D114: 46327 | E114: 46387 | F114: 0 | G114: =IF(OR(D114="",E114="",E114<=D114),"",MIN(100,MAX(0,(Parametros!$B$3-D114)/(E114-D114)*100))) -> 0 | H114: =IF(G114="","",G114-F114) -> 0 | I114: =IF(K114="Finalizado","Verde",IF(G114="","Amarillo",IF(H114<=Parametros!$B$4,"Verde",IF(H114<=Parametros!$B$5,"Amarillo","Rojo")))) -> Verde | J114: =IF(K114="Finalizado","Completado",IF(G114="","Sin fecha válida - revisar plazos",IF(H114<=Parametros!$B$4,"En tiempo, según lo planificado",IF(H114<=Parametros!$B$5,"Atraso leve - seguimiento cercano ("&TEXT(H114,"0.0")&" p.p.)","Atraso crítico - requiere intervención ("&TEXT(H114,"0.0")&" p.p.)")))) -> En tiempo, según lo planificado | K114: No iniciado | M114: Ciberdefensa | N114: POA | O114: =IF(AND(E114<>"",YEAR(E114)=YEAR(Parametros!$B$3),MONTH(E114)>=10),1,0) -> 1 | P114: =IF(AND(E114<Parametros!$B$3,K114<>"Finalizado"),1,0) -> 0 | Q114: =IF(AND(E114>=Parametros!$B$3,E114<=Parametros!$B$3+30,K114<>"Finalizado"),1,0) -> 0
A115: ES-01 | B115: Integración de seguimiento de observaciones de Auditoría del SGSI en herramienta de seguimiento de hallazgos | C115: Actualización del instructivo de gestión de evaluaciones de Seguridad de la Información y Ciberseguridad | D115: 46023 | E115: 46234 | F115: 40 | G115: =IF(OR(D115="",E115="",E115<=D115),"",MIN(100,MAX(0,(Parametros!$B$3-D115)/(E115-D115)*100))) -> 100 | H115: =IF(G115="","",G115-F115) -> 60 | I115: =IF(K115="Finalizado","Verde",IF(G115="","Amarillo",IF(H115<=Parametros!$B$4,"Verde",IF(H115<=Parametros!$B$5,"Amarillo","Rojo")))) -> Rojo | J115: =IF(K115="Finalizado","Completado",IF(G115="","Sin fecha válida - revisar plazos",IF(H115<=Parametros!$B$4,"En tiempo, según lo planificado",IF(H115<=Parametros!$B$5,"Atraso leve - seguimiento cercano ("&TEXT(H115,"0.0")&" p.p.)","Atraso crítico - requiere intervención ("&TEXT(H115,"0.0")&" p.p.)")))) -> Atraso crítico - requiere intervención (60.0 p.p.) | K115: En ejecución | L115: RAMIREZ TENECELA VERONICA ALEXANDRA;#375 | M115: Estrategia y Gobierno | N115: POA | O115: =IF(AND(E115<>"",YEAR(E115)=YEAR(Parametros!$B$3),MONTH(E115)>=10),1,0) -> 0 | P115: =IF(AND(E115<Parametros!$B$3,K115<>"Finalizado"),1,0) -> 1 | Q115: =IF(AND(E115>=Parametros!$B$3,E115<=Parametros!$B$3+30,K115<>"Finalizado"),1,0) -> 0
...

Sheet Resumen_Gerencias
A1: Gerencia | B1: Total_Registros | C1: Finalizados | D1: Tasa_Cumplimiento_Pct | E1: Avance_Real_Prom | F1: Avance_Esperado_Prom | G1: Gap_prom_pp | H1: Pct_Cierres_Q4 | I1: No_Iniciado_Q4 | J1: Vencidas | K1: Veredicto_Ritmo
A2: COE Arquitectura | B2: =COUNTIF(Datos_POA!$M$2:$M$295,A2) -> 13 | C2: =COUNTIFS(Datos_POA!$M$2:$M$295,A2,Datos_POA!$K$2:$K$295,"Finalizado") -> 5 | D2: =IFERROR(C2/B2*100,0) -> 38.461538 | E2: =AVERAGEIFS(Datos_POA!$F$2:$F$295,Datos_POA!$M$2:$M$295,A2) -> 78.461538 | F2: =AVERAGEIFS(Datos_POA!$G$2:$G$295,Datos_POA!$M$2:$M$295,A2) -> 83.158005 | G2: =F2-E2 -> 4.6964661 | H2: =IFERROR(SUMIFS(Datos_POA!$O$2:$O$295,Datos_POA!$M$2:$M$295,A2)/COUNTIFS(Datos_POA!$M$2:$M$295,A2)*100,0) -> 23.076923 | I2: =SUMIFS(Datos_POA!$O$2:$O$295,Datos_POA!$M$2:$M$295,A2,Datos_POA!$K$2:$K$295,"No iniciado") -> 0 | J2: =SUMIFS(Datos_POA!$P$2:$P$295,Datos_POA!$M$2:$M$295,A2) -> 2 | K2: =IF(AND(G2<=3,H2<=45),"Ejecución constante",IF(OR(H2>Parametros!$B$6,G2>Parametros!$B$7),"Carga concentrada al cierre","Ritmo moderado")) -> Ritmo moderado
A3: Ciberdefensa | B3: =COUNTIF(Datos_POA!$M$2:$M$295,A3) -> 100 | C3: =COUNTIFS(Datos_POA!$M$2:$M$295,A3,Datos_POA!$K$2:$K$295,"Finalizado") -> 49 | D3: =IFERROR(C3/B3*100,0) -> 49 | E3: =AVERAGEIFS(Datos_POA!$F$2:$F$295,Datos_POA!$M$2:$M$295,A3) -> 61.69 | F3: =AVERAGEIFS(Datos_POA!$G$2:$G$295,Datos_POA!$M$2:$M$295,A3) -> 63.989268 | G3: =F3-E3 -> 2.2992682 | H3: =IFERROR(SUMIFS(Datos_POA!$O$2:$O$295,Datos_POA!$M$2:$M$295,A3)/COUNTIFS(Datos_POA!$M$2:$M$295,A3)*100,0) -> 29 | I3: =SUMIFS(Datos_POA!$O$2:$O$295,Datos_POA!$M$2:$M$295,A3,Datos_POA!$K$2:$K$295,"No iniciado") -> 22 | J3: =SUMIFS(Datos_POA!$P$2:$P$295,Datos_POA!$M$2:$M$295,A3) -> 4 | K3: =IF(AND(G3<=3,H3<=45),"Ejecución constante",IF(OR(H3>Parametros!$B$6,G3>Parametros!$B$7),"Carga concentrada al cierre","Ritmo moderado")) -> Ejecución constante
A4: Estrategia y Gobierno | B4: =COUNTIF(Datos_POA!$M$2:$M$295,A4) -> 55 | C4: =COUNTIFS(Datos_POA!$M$2:$M$295,A4,Datos_POA!$K$2:$K$295,"Finalizado") -> 12 | D4: =IFERROR(C4/B4*100,0) -> 21.818182 | E4: =AVERAGEIFS(Datos_POA!$F$2:$F$295,Datos_POA!$M$2:$M$295,A4) -> 47.321091 | F4: =AVERAGEIFS(Datos_POA!$G$2:$G$295,Datos_POA!$M$2:$M$295,A4) -> 54.958455 | G4: =F4-E4 -> 7.6373636 | H4: =IFERROR(SUMIFS(Datos_POA!$O$2:$O$295,Datos_POA!$M$2:$M$295,A4)/COUNTIFS(Datos_POA!$M$2:$M$295,A4)*100,0) -> 67.272727 | I4: =SUMIFS(Datos_POA!$O$2:$O$295,Datos_POA!$M$2:$M$295,A4,Datos_POA!$K$2:$K$295,"No iniciado") -> 11 | J4: =SUMIFS(Datos_POA!$P$2:$P$295,Datos_POA!$M$2:$M$295,A4) -> 1 | K4: =IF(AND(G4<=3,H4<=45),"Ejecución constante",IF(OR(H4>Parametros!$B$6,G4>Parametros!$B$7),"Carga concentrada al cierre","Ritmo moderado")) -> Carga concentrada al cierre
A5: Fraude | B5: =COUNTIF(Datos_POA!$M$2:$M$295,A5) -> 23 | C5: =COUNTIFS(Datos_POA!$M$2:$M$295,A5,Datos_POA!$K$2:$K$295,"Finalizado") -> 12 | D5: =IFERROR(C5/B5*100,0) -> 52.173913 | E5: =AVERAGEIFS(Datos_POA!$F$2:$F$295,Datos_POA!$M$2:$M$295,A5) -> 73.913043 | F5: =AVERAGEIFS(Datos_POA!$G$2:$G$295,Datos_POA!$M$2:$M$295,A5) -> 72.589984 | G5: =F5-E5 -> -1.3230595 | H5: =IFERROR(SUMIFS(Datos_POA!$O$2:$O$295,Datos_POA!$M$2:$M$295,A5)/COUNTIFS(Datos_POA!$M$2:$M$295,A5)*100,0) -> 34.782609 | I5: =SUMIFS(Datos_POA!$O$2:$O$295,Datos_POA!$M$2:$M$295,A5,Datos_POA!$K$2:$K$295,"No iniciado") -> 3 | J5: =SUMIFS(Datos_POA!$P$2:$P$295,Datos_POA!$M$2:$M$295,A5) -> 0 | K5: =IF(AND(G5<=3,H5<=45),"Ejecución constante",IF(OR(H5>Parametros!$B$6,G5>Parametros!$B$7),"Carga concentrada al cierre","Ritmo moderado")) -> Ejecución constante
A6: Operaciones | B6: =COUNTIF(Datos_POA!$M$2:$M$295,A6) -> 61 | C6: =COUNTIFS(Datos_POA!$M$2:$M$295,A6,Datos_POA!$K$2:$K$295,"Finalizado") -> 28 | D6: =IFERROR(C6/B6*100,0) -> 45.901639 | E6: =AVERAGEIFS(Datos_POA!$F$2:$F$295,Datos_POA!$M$2:$M$295,A6) -> 67.868852 | F6: =AVERAGEIFS(Datos_POA!$G$2:$G$295,Datos_POA!$M$2:$M$295,A6) -> 69.256594 | G6: =F6-E6 -> 1.387742 | H6: =IFERROR(SUMIFS(Datos_POA!$O$2:$O$295,Datos_POA!$M$2:$M$295,A6)/COUNTIFS(Datos_POA!$M$2:$M$295,A6)*100,0) -> 47.540984 | I6: =SUMIFS(Datos_POA!$O$2:$O$295,Datos_POA!$M$2:$M$295,A6,Datos_POA!$K$2:$K$295,"No iniciado") -> 9 | J6: =SUMIFS(Datos_POA!$P$2:$P$295,Datos_POA!$M$2:$M$295,A6) -> 1 | K6: =IF(AND(G6<=3,H6<=45),"Ejecución constante",IF(OR(H6>Parametros!$B$6,G6>Parametros!$B$7),"Carga concentrada al cierre","Ritmo moderado")) -> Ritmo moderado
A7: Seguridad física | B7: =COUNTIF(Datos_POA!$M$2:$M$295,A7) -> 39 | C7: =COUNTIFS(Datos_POA!$M$2:$M$295,A7,Datos_POA!$K$2:$K$295,"Finalizado") -> 9 | D7: =IFERROR(C7/B7*100,0) -> 23.076923 | E7: =AVERAGEIFS(Datos_POA!$F$2:$F$295,Datos_POA!$M$2:$M$295,A7) -> 44.789744 | F7: =AVERAGEIFS(Datos_POA!$G$2:$G$295,Datos_POA!$M$2:$M$295,A7) -> 49.765676 | G7: =F7-E7 -> 4.9759329 | H7: =IFERROR(SUMIFS(Datos_POA!$O$2:$O$295,Datos_POA!$M$2:$M$295,A7)/COUNTIFS(Datos_POA!$M$2:$M$295,A7)*100,0) -> 43.589744 | I7: =SUMIFS(Datos_POA!$O$2:$O$295,Datos_POA!$M$2:$M$295,A7,Datos_POA!$K$2:$K$295,"No iniciado") -> 9 | J7: =SUMIFS(Datos_POA!$P$2:$P$295,Datos_POA!$M$2:$M$295,A7) -> 1 | K7: =IF(AND(G7<=3,H7<=45),"Ejecución constante",IF(OR(H7>Parametros!$B$6,G7>Parametros!$B$7),"Carga concentrada al cierre","Ritmo moderado")) -> Ritmo moderado
A8: Tribu Ciberseguridad | B8: =COUNTIF(Datos_POA!$M$2:$M$295,A8) -> 3 | C8: =COUNTIFS(Datos_POA!$M$2:$M$295,A8,Datos_POA!$K$2:$K$295,"Finalizado") -> 1 | D8: =IFERROR(C8/B8*100,0) -> 33.333333 | E8: =AVERAGEIFS(Datos_POA!$F$2:$F$295,Datos_POA!$M$2:$M$295,A8) -> 36.666667 | F8: =AVERAGEIFS(Datos_POA!$G$2:$G$295,Datos_POA!$M$2:$M$295,A8) -> 43.169399 | G8: =F8-E8 -> 6.5027322 | H8: =IFERROR(SUMIFS(Datos_POA!$O$2:$O$295,Datos_POA!$M$2:$M$295,A8)/COUNTIFS(Datos_POA!$M$2:$M$295,A8)*100,0) -> 66.666667 | I8: =SUMIFS(Datos_POA!$O$2:$O$295,Datos_POA!$M$2:$M$295,A8,Datos_POA!$K$2:$K$295,"No iniciado") -> 1 | J8: =SUMIFS(Datos_POA!$P$2:$P$295,Datos_POA!$M$2:$M$295,A8) -> 0 | K8: =IF(AND(G8<=3,H8<=45),"Ejecución constante",IF(OR(H8>Parametros!$B$6,G8>Parametros!$B$7),"Carga concentrada al cierre","Ritmo moderado")) -> Carga concentrada al cierre

Sheet DAX_Medidas
A1: MEDIDAS DAX — MODELO POA 2026 (copiar/pegar en Power BI Desktop)
A3: Medida | B3: Fórmula DAX | C3: Descripción
A4: Total Registros | B4: Total Registros = COUNTROWS(Datos_POA) | C4: Total de hitos/registros del POA
A5: Total Iniciativas | B5: Total Iniciativas = DISTINCTCOUNT(Datos_POA[Codigo]) | C5: Iniciativas o mejoras únicas (los registros son hitos de estas)
A6: Promedio Hitos x Iniciativa | B6: Promedio Hitos x Iniciativa = DIVIDE([Total Registros],[Total Iniciativas]) | C6: Cuántos hitos agrupa en promedio cada iniciativa
A7: Avance Promedio Real | B7: Avance Promedio Real = AVERAGE(Datos_POA[Avance_Real_Pct]) | C7: % de avance real promedio
A8: Avance Promedio Esperado | B8: Avance Promedio Esperado = AVERAGE(Datos_POA[Avance_Esperado_Pct]) | C8: % de avance que debería existir a la fecha de corte según cronograma
A9: Brecha vs Plan | B9: Brecha vs Plan = [Avance Promedio Esperado] - [Avance Promedio Real] | C9: Puntos porcentuales de atraso frente al plan
A10: Finalizadas | B10: Finalizadas = CALCULATE(COUNTROWS(Datos_POA), Datos_POA[Estado] = "Finalizado") | C10: Actividades cerradas
A11: En Curso | B11: En Curso = CALCULATE(COUNTROWS(Datos_POA), Datos_POA[Estado] IN {"En ejecución","Iniciado"}) | C11: Actividades en ejecución o iniciadas
A12: Sin Iniciar | B12: Sin Iniciar = CALCULATE(COUNTROWS(Datos_POA), Datos_POA[Estado] = "No iniciado") | C12: Actividades que no han arrancado
A13: Tasa de Cumplimiento | B13: Tasa de Cumplimiento = DIVIDE([Finalizadas], [Total Registros]) | C13: % finalizado sobre el total (formatear como %)
A14: Verde | B14: Verde = CALCULATE(COUNTROWS(Datos_POA), Datos_POA[Semaforo] = "Verde") | C14: Actividades en semáforo verde
... A28: Iniciativas con Multiples Hitos | B28: Iniciativas Multi-Hito = VAR T = SUMMARIZE(Datos_POA, Datos_POA[Codigo], "NHitos", COUNTROWS(Datos_POA)) RETURN COUNTROWS(FILTER(T,[NHitos]>1)) | C28: Cuántas iniciativas están desagregadas en más de un hito (48 en el corte actual)

Sheet Instrucciones_PowerBI
A1: CÓMO USAR ESTE ARCHIVO EN POWER BI DESKTOP
A3: 1. Importar datos | B3: Abrir Power BI Desktop → Obtener datos → Excel → seleccionar este archivo → cargar las hojas 'Datos_POA' y 'Parametros' (Resumen_Gerencias es opcional, ya que las medidas DAX lo recalculan).
A5: 2. Crear relaciones | B5: No se requieren relaciones adicionales: todo el análisis parte de una única tabla 'Datos_POA'. Si se agrega una tabla de fechas, relacionarla por 'Fecha_Fin'.
A7: 3. Crear medidas | B7: Abrir la hoja 'DAX_Medidas' de este archivo y copiar cada fórmula en Modelado → Nueva medida (o Nueva columna, según corresponda) dentro de la tabla Datos_POA.
A9: 4. Construir visuales | B9: Reproducir los bloques de la lámina PNG: tarjetas KPI (medidas), gráfico de dispersión (Gerencia_Responsable, Pct Cierres Q4, Brecha vs Plan, tamaño=Total Registros), tabla matricial (Gerencia_Responsable en filas), gráfico de barras (Sin Iniciar y Vencidas por gerencia), anillo (Semaforo).
A11: 5. Formato | B11: Aplicar la paleta corporativa: azul marino #0A185B, amarillo #FCEC7C, verde #3FA772, ámbar #F2A93B, rojo #D6553F, fondo #F4F6F9.
A13: 6. Incrustar el HTML | B13: Agregar el visual 'HTML Content' (AppSource, gratuito) o 'Web content' nativo de Power BI y pegar/enlazar el archivo Dashboard_POA2026_PowerBI.html incluido en esta entrega para mostrar el resumen ejecutivo dentro del mismo reporte.
A15: 7. Guardar como .pbix | B15: Guardar el reporte desde Power BI Desktop; se generará el archivo .pbix nativo. Este formato solo puede crearse dentro de Power BI Desktop, por lo que no se entrega prearmado — este Excel + las medidas DAX permiten reconstruirlo en menos de 15 minutos.
