Workbook

Sheet Leeme
B2: Modelo Power BI · Recepción de aplicaciones 2026
B3: Especificación para replicar en Power BI el dashboard PDF de 4 páginas. Hito liderado por Jhonny Barreiro. Fuentes: Matriz de Aplicaciones GI (agosto 2026) e informe de conciliación CMDB (DatosSN, 11-ago-2026).
B5: Hojas
B6: Parametros | C6: Fecha de corte, meta, alcance, cifra del informe y responsable del hito. Celdas amarillas con texto azul: se editan.
B7: fAplicaciones | C7: Tabla de hechos: una fila por registro de la matriz. Columnas A–N son copia de la matriz; O en adelante son columnas calculadas (fórmula Excel; su DAX está en «Columnas_DAX»).
B8: Dimensiones | C8: dEtapa (etapa de recepción, orden y color), dCriticidad (A–E, orden, color, si es crítica), dConciliacion (cascada CMDB → universo, datos del informe), dAlcance (criterios que ampliaron el alcance), dDuplicadosGI (posibles duplicados ID GI vs. CMDB, editable), dCalendario.
B9: Validacion | C9: KPIs del dashboard calculados con fórmulas y el valor publicado en el PDF. Todo debe decir «OK».
B10: Medidas_DAX | C10: Medidas base (conteos, avance, ritmo, conciliación, criticidad).
B11: Textos_DAX | C11: Medidas de texto dinámico: subtítulos, etiquetas y notas, con el resultado esperado al corte.
B12: HTML_Content | C12: Medidas que devuelven HTML/SVG para el visual HTML Content: encabezados, KPIs, gráficos SVG (barra del universo, curva acumulada, cascada, barras apiladas) y tablas.
B13: Visuales | C13: Qué medida va en cada visual de cada página, con tamaño sugerido.
B14: PowerQuery_M | C14: Script para cargar la matriz original en Power BI.
B15: Tema_PowerBI | C15: JSON con la paleta Banco Pichincha.
B16: Archivo .txt | C16: Recepcion_Aplicaciones_DAX.txt trae todas las medidas listas para copiar (copiar desde celdas de Excel con saltos de línea agrega comillas).
B18: Modelo
B19: Relaciones | C19: dEtapa[Etapa] 1 → * fAplicaciones[Etapa] dCriticidad[Letra] 1 → * fAplicaciones[CritLetra] dCalendario[Fecha] 1 → * fAplicaciones[Fecha Recepcion] Parametros, dConciliacion, dAlcance y dDuplicadosGI: tablas desconectadas.
B20: Orden de creación | C20: 1) Tablas y relaciones · 2) Columnas calculadas (Columnas_DAX, en orden) · 3) Medidas_DAX · 4) Textos_DAX · 5) HTML_Content.
B21: Parámetros en DAX | C21: La tabla Parametros tiene columnas Valor (números y fechas, tipo Decimal) y Texto. Las medidas convierten las fechas con DATE(YEAR(),MONTH(),DAY()).
B22: Configuración regional | C22: Idioma del modelo Español (Ecuador) para que FORMAT use coma decimal. Los nombres de mes vienen de dCalendario[MesCorto]/[MesLargo].
B24: Reglas de negocio
B25: Aplicación única | C25: Se cuenta una vez cada combinación Nombre + Bp Id (columna Cuenta). La matriz tiene 3 filas repetidas exactas.
B26: Gobernada | C26: «Entregada Identidades» = Si (equivale a Priorización «N/A ENTREGADA»).
B27: Etapa | C27: Gobernada, Criterio 1, Criterio 2, Criterio 3 o Planificada 2027, según la columna Priorización.
B28: Universo | C28: CMDB + ajustes de conciliación (tabla dConciliacion): 331 + 35 + 16 + 23 + 12 = 417.
B29: Ritmo | C29: Recepciones del año de corte / meses transcurridos (días / 30,4). Ritmo requerido = brecha a la meta / meses restantes hasta FinAnio.
B30: Crítica | C30: Criticidad A, B o C (Prioridad de la matriz).
B31: ID propio GI | C31: Bp Id que empieza con GI0 o GA0: aplicación registrada por Identidades porque no existe en la CMDB.
B32: Posible duplicado GI | C32: Aplicación pendiente cuyo nombre normalizado coincide con una gobernada con ID GI (tabla dDuplicadosGI, validar caso a caso).
B33: Gobernadas sin fecha | C33: Hay 2 gobernadas sin Fecha Recepcion: se cuentan en el acumulado desde el inicio.

Sheet fAplicaciones
A1: ID | B1: Nombre | C1: Bp Id | D1: Descripcion | E1: Prioridad | F1: Ubicacion | G1: Equipo Administrado Por | H1: Dueno Aplicacion | I1: Dueno Negocio | J1: Administrado Por | K1: Categoria Identidades | L1: Entregada Identidades | M1: Fecha Recepcion | N1: Priorización | O1: Cuenta | P1: Etapa | Q1: Gobernada | R1: Priorizada2026 | S1: CritLetra | T1: EsCritica | U1: IDPropioGI | V1: Equipo | W1: UbicacionN | X1: AnioRecepcion | Y1: MesRecepcion | Z1: PosibleDuplicadoGI | AA1: Pendiente
A2: 1 | B2: IBM WebSphere Portal | C2: CHL0017 | D2: IBM Websphere Portal, es el portal web empresarial que ofrece experiencias sociales altamente personalizadas a los usuarios. Brinda a los usuarios un único punto de acceso a las aplicaciones, servicios, información y conexiones sociales que necesiten. El usuario puede acceder de manera directa a aplicaciones como: BancsLink, Administrador de Remesas, Asesores, Balcones, Cardholder, CreditosCom, Riesgo Global, Reclamos y Requerimientos, BPM, Informes Legales. | E2: A - Apetito de Riesgo Disponibilidad | F2: On Premise | G2: TRIBU_CANALES | H2: MIGUEL ALEXANDER MEJIA BRONCANO | I2: JORGE HUMBERTO BRAVO YUNDA | J2: Luis Remigio Bayas Rea | K2: Aplicación del negocio | L2: Si | N2: N/A ENTREGADA | O2: =IF(COUNTIFS($B$2:B2,B2,$C$2:C2,C2)=1,1,0) -> 1 | P2: =IFERROR(INDEX(dEtapa!$A$2:$A$6,MATCH(N2,dEtapa!$B$2:$B$6,0)),"Sin etapa") -> Gobernada | Q2: =IF(L2="Si",1,0) -> 1 | R2: =IF(ISNUMBER(SEARCH("CRITERIO",N2)),1,0) -> 0 | S2: =IF(E2="","Sin dato",LEFT(E2,1)) -> A | T2: =IFERROR(INDEX(dCriticidad!$G$2:$G$7,MATCH(S2,dCriticidad!$A$2:$A$7,0)),0) -> 1 | U2: =IF(OR(LEFT(C2,3)="GI0",LEFT(C2,3)="GA0"),1,0) -> 0 | V2: =IF(G2="","Sin dato (ID GI)",TRIM(G2)) -> TRIBU_CANALES | W2: =IF(F2="","Sin dato",F2) -> On Premise | X2: =IF(M2="","",YEAR(M2)) | Y2: =IF(M2="","",DATE(YEAR(M2),MONTH(M2),1)) | Z2: =IF(AND(Q2=0,COUNTIF(dDuplicadosGI!$A$2:$A$60,C2)>0),1,0) -> 0 | AA2: =IF(Q2=0,1,0) -> 0
A3: 2 | B3: ICEPanel | C3: ITM0068 | D3: Modelado de Arquitectura de Soluciones | E3: D - BIA No Crítica | F3: Nube | G3: COE ARQUITECTURA | H3: MAURICIO BLADIMIR AUQUI MIRANDA | I3: LUIS MIGUEL ULLOA MOREIRA | J3: LUIS MIGUEL ULLOA MOREIRA | K3: Aplicación complementaria | L3: No | N3: PRIORIZACIÓN CRITERIO 1 | O3: =IF(COUNTIFS($B$2:B3,B3,$C$2:C3,C3)=1,1,0) -> 1 | P3: =IFERROR(INDEX(dEtapa!$A$2:$A$6,MATCH(N3,dEtapa!$B$2:$B$6,0)),"Sin etapa") -> Criterio 1 | Q3: =IF(L3="Si",1,0) -> 0 | R3: =IF(ISNUMBER(SEARCH("CRITERIO",N3)),1,0) -> 1 | S3: =IF(E3="","Sin dato",LEFT(E3,1)) -> D | T3: =IFERROR(INDEX(dCriticidad!$G$2:$G$7,MATCH(S3,dCriticidad!$A$2:$A$7,0)),0) -> 0 | U3: =IF(OR(LEFT(C3,3)="GI0",LEFT(C3,3)="GA0"),1,0) -> 0 | V3: =IF(G3="","Sin dato (ID GI)",TRIM(G3)) -> COE ARQUITECTURA | W3: =IF(F3="","Sin dato",F3) -> Nube | X3: =IF(M3="","",YEAR(M3)) | Y3: =IF(M3="","",DATE(YEAR(M3),MONTH(M3),1)) | Z3: =IF(AND(Q3=0,COUNTIF(dDuplicadosGI!$A$2:$A$60,C3)>0),1,0) -> 0 | AA3: =IF(Q3=0,1,0) -> 1
A4: 3 | B4: Idera | C4: ITM0035 | D4: Es una aplicación para administrar motores SQL, donde se visualiza eventos que ocurran en las bases de datos como en el servidor | E4: D - BIA No Crítica | F4: On Premise | G4: INFRAESTRUCTURA | H4: BYRON ORLANDO MELENDREZ CABRERA | I4: NELSON ANDRES POZO YEPEZ | J4: FELIX ALEXANDER MANJARRES QUEZADA | K4: Consolas de Administración TI | L4: No | N4: PLANIFICADA 2027 | O4: =IF(COUNTIFS($B$2:B4,B4,$C$2:C4,C4)=1,1,0) -> 1 | P4: =IFERROR(INDEX(dEtapa!$A$2:$A$6,MATCH(N4,dEtapa!$B$2:$B$6,0)),"Sin etapa") -> Planificada 2027 | Q4: =IF(L4="Si",1,0) -> 0 | R4: =IF(ISNUMBER(SEARCH("CRITERIO",N4)),1,0) -> 0 | S4: =IF(E4="","Sin dato",LEFT(E4,1)) -> D | T4: =IFERROR(INDEX(dCriticidad!$G$2:$G$7,MATCH(S4,dCriticidad!$A$2:$A$7,0)),0) -> 0 | U4: =IF(OR(LEFT(C4,3)="GI0",LEFT(C4,3)="GA0"),1,0) -> 0 | V4: =IF(G4="","Sin dato (ID GI)",TRIM(G4)) -> INFRAESTRUCTURA | W4: =IF(F4="","Sin dato",F4) -> On Premise | X4: =IF(M4="","",YEAR(M4)) | Y4: =IF(M4="","",DATE(YEAR(M4),MONTH(M4),1)) | Z4: =IF(AND(Q4=0,COUNTIF(dDuplicadosGI!$A$2:$A$60,C4)>0),1,0) -> 0 | AA4: =IF(Q4=0,1,0) -> 1
A5: 4 | B5: IGNITION | C5: ITM0069 | D5: Monitoreo de las facilidades de los centros de datos, Sistemas Electricos, Enfriamiento, Electrogenos | E5: C - BIA Crítica | F5: On Premise | G5: INFRAESTRUCTURA | H5: BYRON ORLANDO MELENDREZ CABRERA | I5: DIEGO JAVIER SALAZAR MOLINA | J5: DIEGO PAUL BETANCOURT REYES | K5: Aplicación complementaria | L5: No | N5: PLANIFICADA 2027 | O5: =IF(COUNTIFS($B$2:B5,B5,$C$2:C5,C5)=1,1,0) -> 1 | P5: =IFERROR(INDEX(dEtapa!$A$2:$A$6,MATCH(N5,dEtapa!$B$2:$B$6,0)),"Sin etapa") -> Planificada 2027 | Q5: =IF(L5="Si",1,0) -> 0 | R5: =IF(ISNUMBER(SEARCH("CRITERIO",N5)),1,0) -> 0 | S5: =IF(E5="","Sin dato",LEFT(E5,1)) -> C | T5: =IFERROR(INDEX(dCriticidad!$G$2:$G$7,MATCH(S5,dCriticidad!$A$2:$A$7,0)),0) -> 1 | U5: =IF(OR(LEFT(C5,3)="GI0",LEFT(C5,3)="GA0"),1,0) -> 0 | V5: =IF(G5="","Sin dato (ID GI)",TRIM(G5)) -> INFRAESTRUCTURA | W5: =IF(F5="","Sin dato",F5) -> On Premise | X5: =IF(M5="","",YEAR(M5)) | Y5: =IF(M5="","",DATE(YEAR(M5),MONTH(M5),1)) | Z5: =IF(AND(Q5=0,COUNTIF(dDuplicadosGI!$A$2:$A$60,C5)>0),1,0) -> 0 | AA5: =IF(Q5=0,1,0) -> 1
A6: 5 | B6: ILMT | C6: ITM0036 | D6: Monitoreo de Software IBM instalado en servidores licenciamiento | E6: E - No Crítica | F6: On Premise | G6: INFRAESTRUCTURA | H6: BYRON ORLANDO MELENDREZ CABRERA | I6: HORACIO LEONEL HOLGUIN ALCIVAR | J6: FREDDY VINICIO ESTRELLA HIDALGO | K6: Consolas de Administración TI | L6: No | N6: PLANIFICADA 2027 | O6: =IF(COUNTIFS($B$2:B6,B6,$C$2:C6,C6)=1,1,0) -> 1 | P6: =IFERROR(INDEX(dEtapa!$A$2:$A$6,MATCH(N6,dEtapa!$B$2:$B$6,0)),"Sin etapa") -> Planificada 2027 | Q6: =IF(L6="Si",1,0) -> 0 | R6: =IF(ISNUMBER(SEARCH("CRITERIO",N6)),1,0) -> 0 | S6: =IF(E6="","Sin dato",LEFT(E6,1)) -> E | T6: =IFERROR(INDEX(dCriticidad!$G$2:$G$7,MATCH(S6,dCriticidad!$A$2:$A$7,0)),0) -> 0 | U6: =IF(OR(LEFT(C6,3)="GI0",LEFT(C6,3)="GA0"),1,0) -> 0 | V6: =IF(G6="","Sin dato (ID GI)",TRIM(G6)) -> INFRAESTRUCTURA | W6: =IF(F6="","Sin dato",F6) -> On Premise | X6: =IF(M6="","",YEAR(M6)) | Y6: =IF(M6="","",DATE(YEAR(M6),MONTH(M6),1)) | Z6: =IF(AND(Q6=0,COUNTIF(dDuplicadosGI!$A$2:$A$60,C6)>0),1,0) -> 0 | AA6: =IF(Q6=0,1,0) -> 1
A7: 6 | B7: Impacto 360 | C7: DAT0015 | D7: la iniciativa es una plataforma de inteligencia empresarial y análisis de mercado con un enfoque específico en los clientes que utilizan medios de pago del Banco Pichincha (tarjetas de crédito, tarjetas de débito y transferencias digitales). Esta plataforma brinda a los empresarios la capacidad de acceder y visualizar información histórica y resumida de estos clientes, permitiéndoles obtener una visión más detallada y específica de su base de clientes y sus comportamientos de pago. | E7: E - No Crítica | F7: Nube | G7: Negocios y Monetización | H7: ANTONIO ALEJANDRO CANAVERAL GIL | I7: SEBASTIAN MUNOZ ANDERSEN | J7: HEVER GONZALEZ GARCIA | K7: Aplicación del negocio | L7: No | N7: PLANIFICADA 2027 | O7: =IF(COUNTIFS($B$2:B7,B7,$C$2:C7,C7)=1,1,0) -> 1 | P7: =IFERROR(INDEX(dEtapa!$A$2:$A$6,MATCH(N7,dEtapa!$B$2:$B$6,0)),"Sin etapa") -> Planificada 2027 | Q7: =IF(L7="Si",1,0) -> 0 | R7: =IF(ISNUMBER(SEARCH("CRITERIO",N7)),1,0) -> 0 | S7: =IF(E7="","Sin dato",LEFT(E7,1)) -> E | T7: =IFERROR(INDEX(dCriticidad!$G$2:$G$7,MATCH(S7,dCriticidad!$A$2:$A$7,0)),0) -> 0 | U7: =IF(OR(LEFT(C7,3)="GI0",LEFT(C7,3)="GA0"),1,0) -> 0 | V7: =IF(G7="","Sin dato (ID GI)",TRIM(G7)) -> Negocios y Monetización | W7: =IF(F7="","Sin dato",F7) -> Nube | X7: =IF(M7="","",YEAR(M7)) | Y7: =IF(M7="","",DATE(YEAR(M7),MONTH(M7),1)) | Z7: =IF(AND(Q7=0,COUNTIF(dDuplicadosGI!$A$2:$A$60,C7)>0),1,0) -> 0 | AA7: =IF(Q7=0,1,0) -> 1
A8: 7 | B8: Impresion Documentos | C8: TIE0018 | D8: Aplicación que permite levantar documentos de word ejecutando macros. Genera documentos entregados a los clientes, principalmente de solicitudes de crédito. | E8: E - No Crítica | F8: On Premise | G8: ACTIVOS | H8: LAURA ELIZABETH CARRASCO UQUILLAS | I8: ANDREA FERNANDA ORTIZ CISNEROS | J8: ERISLAN MARTINEZ JERA | K8: Aplicación del negocio | L8: Si | M8: 45199 | N8: N/A ENTREGADA | O8: =IF(COUNTIFS($B$2:B8,B8,$C$2:C8,C8)=1,1,0) -> 1 | P8: =IFERROR(INDEX(dEtapa!$A$2:$A$6,MATCH(N8,dEtapa!$B$2:$B$6,0)),"Sin etapa") -> Gobernada | Q8: =IF(L8="Si",1,0) -> 1 | R8: =IF(ISNUMBER(SEARCH("CRITERIO",N8)),1,0) -> 0 | S8: =IF(E8="","Sin dato",LEFT(E8,1)) -> E | T8: =IFERROR(INDEX(dCriticidad!$G$2:$G$7,MATCH(S8,dCriticidad!$A$2:$A$7,0)),0) -> 0 | U8: =IF(OR(LEFT(C8,3)="GI0",LEFT(C8,3)="GA0"),1,0) -> 0 | V8: =IF(G8="","Sin dato (ID GI)",TRIM(G8)) -> ACTIVOS | W8: =IF(F8="","Sin dato",F8) -> On Premise | X8: =IF(M8="","",YEAR(M8)) -> 2023 | Y8: =IF(M8="","",DATE(YEAR(M8),MONTH(M8),1)) -> 45170 | Z8: =IF(AND(Q8=0,COUNTIF(dDuplicadosGI!$A$2:$A$60,C8)>0),1,0) -> 0 | AA8: =IF(Q8=0,1,0) -> 0
A9: 8 | B9: informesCredito | C9: PRD0021 | D9: Aplicación utilizada por las empresas que contratan el servicio para ver referencias bancarias de los clientes del Banco del Pichincha, pueden ver la cantidad de cifras, altas o bajas de sus cuentas, clientes como Dinners, Artefacta, Movistar lo utilizan. Cada consulta de los clientes tiene un costo. | E9: E - No Crítica | F9: Nube | G9: Frente de Soluciones Empresariales | H9: LUIS MIGUEL ULLOA MOREIRA | I9: FABRICIO ANTONIO PEREIRA GARCIA | J9: WILLIAM PATRICIO PANCHI SHUGULI | K9: Aplicación del negocio | L9: Si | M9: 45199 | N9: N/A ENTREGADA | O9: =IF(COUNTIFS($B$2:B9,B9,$C$2:C9,C9)=1,1,0) -> 1 | P9: =IFERROR(INDEX(dEtapa!$A$2:$A$6,MATCH(N9,dEtapa!$B$2:$B$6,0)),"Sin etapa") -> Gobernada | Q9: =IF(L9="Si",1,0) -> 1 | R9: =IF(ISNUMBER(SEARCH("CRITERIO",N9)),1,0) -> 0 | S9: =IF(E9="","Sin dato",LEFT(E9,1)) -> E | T9: =IFERROR(INDEX(dCriticidad!$G$2:$G$7,MATCH(S9,dCriticidad!$A$2:$A$7,0)),0) -> 0 | U9: =IF(OR(LEFT(C9,3)="GI0",LEFT(C9,3)="GA0"),1,0) -> 0 | V9: =IF(G9="","Sin dato (ID GI)",TRIM(G9)) -> Frente de Soluciones Empresariales | W9: =IF(F9="","Sin dato",F9) -> Nube | X9: =IF(M9="","",YEAR(M9)) -> 2023 | Y9: =IF(M9="","",DATE(YEAR(M9),MONTH(M9),1)) -> 45170 | Z9: =IF(AND(Q9=0,COUNTIF(dDuplicadosGI!$A$2:$A$60,C9)>0),1,0) -> 0 | AA9: =IF(Q9=0,1,0) -> 0
A10: 9 | B10: Integration Bus Soporte | C10: INT0009 | D10: Integration Bus permite administrar y monitorear los flujos de integración que conectan múltiples canales digitales y sistemas backend. Facilita la gestión de servicios, procesamiento de mensajes y orquestación de transacciones entre aplicaciones. Es un componente clave para asegurar la operación continua y la integración eficiente en arquitecturas omnicanal. | E10: B - Ecosistema Apetito de Riesgo | F10: On Premise | G10: Tribu_Integraciones_Apis | H10: DAVID RODRIGO REVELO RIVERA | I10: DIEGO VLADIMIR JAYA GUAMANZARA | J10: DIEGO VLADIMIR JAYA GUAMANZARA | K10: Consolas de Administración TI | L10: Si | M10: 46197 | N10: N/A ENTREGADA | O10: =IF(COUNTIFS($B$2:B10,B10,$C$2:C10,C10)=1,1,0) -> 1 | P10: =IFERROR(INDEX(dEtapa!$A$2:$A$6,MATCH(N10,dEtapa!$B$2:$B$6,0)),"Sin etapa") -> Gobernada | Q10: =IF(L10="Si",1,0) -> 1 | R10: =IF(ISNUMBER(SEARCH("CRITERIO",N10)),1,0) -> 0 | S10: =IF(E10="","Sin dato",LEFT(E10,1)) -> B | T10: =IFERROR(INDEX(dCriticidad!$G$2:$G$7,MATCH(S10,dCriticidad!$A$2:$A$7,0)),0) -> 1 | U10: =IF(OR(LEFT(C10,3)="GI0",LEFT(C10,3)="GA0"),1,0) -> 0 | V10: =IF(G10="","Sin dato (ID GI)",TRIM(G10)) -> Tribu_Integraciones_Apis | W10: =IF(F10="","Sin dato",F10) -> On Premise | X10: =IF(M10="","",YEAR(M10)) -> 2026 | Y10: =IF(M10="","",DATE(YEAR(M10),MONTH(M10),1)) -> 46174 | Z10: =IF(AND(Q10=0,COUNTIF(dDuplicadosGI!$A$2:$A$60,C10)>0),1,0) -> 0 | AA10: =IF(Q10=0,1,0) -> 0
A11: 10 | B11: Interdin AS 400/ CAO | C11: PAY0010 | D11: No existe descripción | E11: C - BIA Crítica | F11: Terceros | G11: MEDIOS_DE_PAGO | H11: EDWIN GEOVANNY FLORES CASTRO | I11: KATHERINE FATIMA CJURO VERA | J11: JEAN ANEL PROANO FALCONES | K11: Aplicación del negocio | L11: Si | M11: 45199 | N11: N/A ENTREGADA | O11: =IF(COUNTIFS($B$2:B11,B11,$C$2:C11,C11)=1,1,0) -> 1 | P11: =IFERROR(INDEX(dEtapa!$A$2:$A$6,MATCH(N11,dEtapa!$B$2:$B$6,0)),"Sin etapa") -> Gobernada | Q11: =IF(L11="Si",1,0) -> 1 | R11: =IF(ISNUMBER(SEARCH("CRITERIO",N11)),1,0) -> 0 | S11: =IF(E11="","Sin dato",LEFT(E11,1)) -> C | T11: =IFERROR(INDEX(dCriticidad!$G$2:$G$7,MATCH(S11,dCriticidad!$A$2:$A$7,0)),0) -> 1 | U11: =IF(OR(LEFT(C11,3)="GI0",LEFT(C11,3)="GA0"),1,0) -> 0 | V11: =IF(G11="","Sin dato (ID GI)",TRIM(G11)) -> MEDIOS_DE_PAGO | W11: =IF(F11="","Sin dato",F11) -> Terceros | X11: =IF(M11="","",YEAR(M11)) -> 2023 | Y11: =IF(M11="","",DATE(YEAR(M11),MONTH(M11),1)) -> 45170 | Z11: =IF(AND(Q11=0,COUNTIF(dDuplicadosGI!$A$2:$A$60,C11)>0),1,0) -> 0 | AA11: =IF(Q11=0,1,0) -> 0
A12: 11 | B12: Inversiones | C12: PRD0060 | D12: Aplicacion para venta y postventa de Inversiones. | E12: E - No Crítica | F12: Nube | G12: PASIVOS Y SEGUROS | H12: LAURA ELIZABETH CARRASCO UQUILLAS | I12: JONATHAN HERNAN ARIAS HERNANDEZ | J12: MANUEL ABELARDO HARO MONTERO | K12: Aplicación del negocio | L12: No | N12: PLANIFICADA 2027 | O12: =IF(COUNTIFS($B$2:B12,B12,$C$2:C12,C12)=1,1,0) -> 1 | P12: =IFERROR(INDEX(dEtapa!$A$2:$A$6,MATCH(N12,dEtapa!$B$2:$B$6,0)),"Sin etapa") -> Planificada 2027 | Q12: =IF(L12="Si",1,0) -> 0 | R12: =IF(ISNUMBER(SEARCH("CRITERIO",N12)),1,0) -> 0 | S12: =IF(E12="","Sin dato",LEFT(E12,1)) -> E | T12: =IFERROR(INDEX(dCriticidad!$G$2:$G$7,MATCH(S12,dCriticidad!$A$2:$A$7,0)),0) -> 0 | U12: =IF(OR(LEFT(C12,3)="GI0",LEFT(C12,3)="GA0"),1,0) -> 0 | V12: =IF(G12="","Sin dato (ID GI)",TRIM(G12)) -> PASIVOS Y SEGUROS | W12: =IF(F12="","Sin dato",F12) -> Nube | X12: =IF(M12="","",YEAR(M12)) | Y12: =IF(M12="","",DATE(YEAR(M12),MONTH(M12),1)) | Z12: =IF(AND(Q12=0,COUNTIF(dDuplicadosGI!$A$2:$A$60,C12)>0),1,0) -> 0 | AA12: =IF(Q12=0,1,0) -> 1
A13: 12 | B13: IPS Intrusion Prevention System | C13: SEC0025 | D13: Cisco Firepower Management Center 4600 | E13: C - BIA Crítica | F13: On Premise | G13: Ciberseguridad | H13: ERICK DAMIAN RISUENO BENITEZ | I13: MARCO FABRICIO FALCONI NORIEGA | J13: JORGE XAVIER LUCERO GALLEGOS | K13: Consolas de Administración Seguridad | L13: Si | M13: 45929 | N13: N/A ENTREGADA | O13: =IF(COUNTIFS($B$2:B13,B13,$C$2:C13,C13)=1,1,0) -> 1 | P13: =IFERROR(INDEX(dEtapa!$A$2:$A$6,MATCH(N13,dEtapa!$B$2:$B$6,0)),"Sin etapa") -> Gobernada | Q13: =IF(L13="Si",1,0) -> 1 | R13: =IF(ISNUMBER(SEARCH("CRITERIO",N13)),1,0) -> 0 | S13: =IF(E13="","Sin dato",LEFT(E13,1)) -> C | T13: =IFERROR(INDEX(dCriticidad!$G$2:$G$7,MATCH(S13,dCriticidad!$A$2:$A$7,0)),0) -> 1 | U13: =IF(OR(LEFT(C13,3)="GI0",LEFT(C13,3)="GA0"),1,0) -> 0 | V13: =IF(G13="","Sin dato (ID GI)",TRIM(G13)) -> Ciberseguridad | W13: =IF(F13="","Sin dato",F13) -> On Premise | X13: =IF(M13="","",YEAR(M13)) -> 2025 | Y13: =IF(M13="","",DATE(YEAR(M13),MONTH(M13),1)) -> 45901 | Z13: =IF(AND(Q13=0,COUNTIF(dDuplicadosGI!$A$2:$A$60,C13)>0),1,0) -> 0 | AA13: =IF(Q13=0,1,0) -> 0
A14: 13 | B14: ISE | C14: SEC0026 | D14: CONTROL DE ACCESO A LA RED | E14: C - BIA Crítica | F14: On Premise | G14: Ciberseguridad | H14: JORGE XAVIER LUCERO GALLEGOS | I14: MARCO FABRICIO FALCONI NORIEGA | J14: ROBERT STALIN SOTO CORONEL | K14: Consolas de Administración Seguridad | L14: Si | M14: 45772 | N14: N/A ENTREGADA | O14: =IF(COUNTIFS($B$2:B14,B14,$C$2:C14,C14)=1,1,0) -> 1 | P14: =IFERROR(INDEX(dEtapa!$A$2:$A$6,MATCH(N14,dEtapa!$B$2:$B$6,0)),"Sin etapa") -> Gobernada | Q14: =IF(L14="Si",1,0) -> 1 | R14: =IF(ISNUMBER(SEARCH("CRITERIO",N14)),1,0) -> 0 | S14: =IF(E14="","Sin dato",LEFT(E14,1)) -> C | T14: =IFERROR(INDEX(dCriticidad!$G$2:$G$7,MATCH(S14,dCriticidad!$A$2:$A$7,0)),0) -> 1 | U14: =IF(OR(LEFT(C14,3)="GI0",LEFT(C14,3)="GA0"),1,0) -> 0 | V14: =IF(G14="","Sin dato (ID GI)",TRIM(G14)) -> Ciberseguridad | W14: =IF(F14="","Sin dato",F14) -> On Premise | X14: =IF(M14="","",YEAR(M14)) -> 2025 | Y14: =IF(M14="","",DATE(YEAR(M14),MONTH(M14),1)) -> 45748 | Z14: =IF(AND(Q14=0,COUNTIF(dDuplicadosGI!$A$2:$A$60,C14)>0),1,0) -> 0 | AA14: =IF(Q14=0,1,0) -> 0
A15: 14 | B15: Kafka | C15: OMN0004 | D15: Basado en una transmisión de evetos,captura datos en tiempo real desde varias fuentes, enruta los flujos de datos a diferentes tecnologías de destino según sea necesario. | E15: B - Ecosistema Apetito de Riesgo | F15: On Premise | G15: Tribu_Integraciones_Apis | H15: DAVID RODRIGO REVELO RIVERA | I15: DIEGO VLADIMIR JAYA GUAMANZARA | J15: DIEGO VLADIMIR JAYA GUAMANZARA | K15: Consolas de Administración TI | L15: No | N15: PRIORIZACIÓN CRITERIO 2 | O15: =IF(COUNTIFS($B$2:B15,B15,$C$2:C15,C15)=1,1,0) -> 1 | P15: =IFERROR(INDEX(dEtapa!$A$2:$A$6,MATCH(N15,dEtapa!$B$2:$B$6,0)),"Sin etapa") -> Criterio 2 | Q15: =IF(L15="Si",1,0) -> 0 | R15: =IF(ISNUMBER(SEARCH("CRITERIO",N15)),1,0) -> 1 | S15: =IF(E15="","Sin dato",LEFT(E15,1)) -> B | T15: =IFERROR(INDEX(dCriticidad!$G$2:$G$7,MATCH(S15,dCriticidad!$A$2:$A$7,0)),0) -> 1 | U15: =IF(OR(LEFT(C15,3)="GI0",LEFT(C15,3)="GA0"),1,0) -> 0 | V15: =IF(G15="","Sin dato (ID GI)",TRIM(G15)) -> Tribu_Integraciones_Apis | W15: =IF(F15="","Sin dato",F15) -> On Premise | X15: =IF(M15="","",YEAR(M15)) | Y15: =IF(M15="","",DATE(YEAR(M15),MONTH(M15),1)) | Z15: =IF(AND(Q15=0,COUNTIF(dDuplicadosGI!$A$2:$A$60,C15)>0),1,0) -> 0 | AA15: =IF(Q15=0,1,0) -> 1
A16: 15 | B16: Keeper Security | C16: SEC0053 | D16: Solución para la gestión de contraseñas de los usuarios | E16: E - No Crítica | F16: Nube | G16: Ciberseguridad | H16: lvtandaz@pichincha.com TANDAZO GALLEGOS | I16: MARCO FABRICIO FALCONI NORIEGA | J16: ISRAEL SEBASTIAN DE LA TORRE TRUJILLO | K16: Consolas de Administración Seguridad | L16: No | N16: PRIORIZACIÓN CRITERIO 1 | O16: =IF(COUNTIFS($B$2:B16,B16,$C$2:C16,C16)=1,1,0) -> 1 | P16: =IFERROR(INDEX(dEtapa!$A$2:$A$6,MATCH(N16,dEtapa!$B$2:$B$6,0)),"Sin etapa") -> Criterio 1 | Q16: =IF(L16="Si",1,0) -> 0 | R16: =IF(ISNUMBER(SEARCH("CRITERIO",N16)),1,0) -> 1 | S16: =IF(E16="","Sin dato",LEFT(E16,1)) -> E | T16: =IFERROR(INDEX(dCriticidad!$G$2:$G$7,MATCH(S16,dCriticidad!$A$2:$A$7,0)),0) -> 0 | U16: =IF(OR(LEFT(C16,3)="GI0",LEFT(C16,3)="GA0"),1,0) -> 0 | V16: =IF(G16="","Sin dato (ID GI)",TRIM(G16)) -> Ciberseguridad | W16: =IF(F16="","Sin dato",F16) -> Nube | X16: =IF(M16="","",YEAR(M16)) | Y16: =IF(M16="","",DATE(YEAR(M16),MONTH(M16),1)) | Z16: =IF(AND(Q16=0,COUNTIF(dDuplicadosGI!$A$2:$A$60,C16)>0),1,0) -> 0 | AA16: =IF(Q16=0,1,0) -> 1
A17: 16 | B17: Kriptos | C17: SEC0055 | D17: Solución basada en clasificación artificial que tiene la capacidad de identificar y clasificar los datos de la empresa. | E17: E - No Crítica | F17: Nube | G17: Ciberseguridad | H17: FERNANDO JAVIER PALADINES BUSTAMANTE | I17: MARCO FABRICIO FALCONI NORIEGA | J17: MARIA DEL CARMEN PENAHERRERA PLUA | K17: Consolas de Administración Seguridad | L17: No | N17: PRIORIZACIÓN CRITERIO 3 | O17: =IF(COUNTIFS($B$2:B17,B17,$C$2:C17,C17)=1,1,0) -> 1 | P17: =IFERROR(INDEX(dEtapa!$A$2:$A$6,MATCH(N17,dEtapa!$B$2:$B$6,0)),"Sin etapa") -> Criterio 3 | Q17: =IF(L17="Si",1,0) -> 0 | R17: =IF(ISNUMBER(SEARCH("CRITERIO",N17)),1,0) -> 1 | S17: =IF(E17="","Sin dato",LEFT(E17,1)) -> E | T17: =IFERROR(INDEX(dCriticidad!$G$2:$G$7,MATCH(S17,dCriticidad!$A$2:$A$7,0)),0) -> 0 | U17: =IF(OR(LEFT(C17,3)="GI0",LEFT(C17,3)="GA0"),1,0) -> 0 | V17: =IF(G17="","Sin dato (ID GI)",TRIM(G17)) -> Ciberseguridad | W17: =IF(F17="","Sin dato",F17) -> Nube | X17: =IF(M17="","",YEAR(M17)) | Y17: =IF(M17="","",DATE(YEAR(M17),MONTH(M17),1)) | Z17: =IF(AND(Q17=0,COUNTIF(dDuplicadosGI!$A$2:$A$60,C17)>0),1,0) -> 0 | AA17: =IF(Q17=0,1,0) -> 1
A18: 17 | B18: Fielweb | C18: SUP0011 | D18: No existe descripción | E18: E - No Crítica | F18: Terceros | G18: AREAS_DE_APOYO | H18: FABIAN GEOVANNI PAZMINO UBIDIA | I18: JOSE LUIS ZAPATA ROSERO | J18: FERNANDO JOSE ROLDAN CORREA | K18: Aplicación complementaria | L18: No | N18: PLANIFICADA 2027 | O18: =IF(COUNTIFS($B$2:B18,B18,$C$2:C18,C18)=1,1,0) -> 1 | P18: =IFERROR(INDEX(dEtapa!$A$2:$A$6,MATCH(N18,dEtapa!$B$2:$B$6,0)),"Sin etapa") -> Planificada 2027 | Q18: =IF(L18="Si",1,0) -> 0 | R18: =IF(ISNUMBER(SEARCH("CRITERIO",N18)),1,0) -> 0 | S18: =IF(E18="","Sin dato",LEFT(E18,1)) -> E | T18: =IFERROR(INDEX(dCriticidad!$G$2:$G$7,MATCH(S18,dCriticidad!$A$2:$A$7,0)),0) -> 0 | U18: =IF(OR(LEFT(C18,3)="GI0",LEFT(C18,3)="GA0"),1,0) -> 0 | V18: =IF(G18="","Sin dato (ID GI)",TRIM(G18)) -> AREAS_DE_APOYO | W18: =IF(F18="","Sin dato",F18) -> Terceros | X18: =IF(M18="","",YEAR(M18)) | Y18: =IF(M18="","",DATE(YEAR(M18),MONTH(M18),1)) | Z18: =IF(AND(Q18=0,COUNTIF(dDuplicadosGI!$A$2:$A$60,C18)>0),1,0) -> 0 | AA18: =IF(Q18=0,1,0) -> 1
A19: 18 | B19: LEXMARK CLOUD PRINT MANAGEMENT (CPM) | C19: ITM0038 | D19: Administración Multifunción Lexmark para Integración multifuncionales con Talla Impresión | E19: E - No Crítica | F19: Nube | G19: Gerencia Arquitectura Usuario Final | H19: AMPARO MARIANA CARDENAS HUILCA | I19: ABNER ANDY AREVALO BRACAMONTE | J19: ABNER ANDY AREVALO BRACAMONTE | K19: Aplicación complementaria | L19: No | N19: PLANIFICADA 2027 | O19: =IF(COUNTIFS($B$2:B19,B19,$C$2:C19,C19)=1,1,0) -> 1 | P19: =IFERROR(INDEX(dEtapa!$A$2:$A$6,MATCH(N19,dEtapa!$B$2:$B$6,0)),"Sin etapa") -> Planificada 2027 | Q19: =IF(L19="Si",1,0) -> 0 | R19: =IF(ISNUMBER(SEARCH("CRITERIO",N19)),1,0) -> 0 | S19: =IF(E19="","Sin dato",LEFT(E19,1)) -> E | T19: =IFERROR(INDEX(dCriticidad!$G$2:$G$7,MATCH(S19,dCriticidad!$A$2:$A$7,0)),0) -> 0 | U19: =IF(OR(LEFT(C19,3)="GI0",LEFT(C19,3)="GA0"),1,0) -> 0 | V19: =IF(G19="","Sin dato (ID GI)",TRIM(G19)) -> Gerencia Arquitectura Usuario Final | W19: =IF(F19="","Sin dato",F19) -> Nube | X19: =IF(M19="","",YEAR(M19)) | Y19: =IF(M19="","",DATE(YEAR(M19),MONTH(M19),1)) | Z19: =IF(AND(Q19=0,COUNTIF(dDuplicadosGI!$A$2:$A$60,C19)>0),1,0) -> 0 | AA19: =IF(Q19=0,1,0) -> 1
A20: 19 | B20: ListaObservados | C20: GOB0013 | D20: Es una aplicación que permite la validación de clientes en listas de validación utilizando componentes de terceros (Bridger). | E20: B - Ecosistema Apetito de Riesgo | F20: Nube | G20: AREAS_DE_APOYO | H20: FABIAN GEOVANNI PAZMINO UBIDIA | I20: JOSE LUIS ZAPATA ROSERO | J20: FERNANDO JOSE ROLDAN CORREA | K20: Aplicación del negocio | L20: No | N20: PRIORIZACIÓN CRITERIO 2 | O20: =IF(COUNTIFS($B$2:B20,B20,$C$2:C20,C20)=1,1,0) -> 1 | P20: =IFERROR(INDEX(dEtapa!$A$2:$A$6,MATCH(N20,dEtapa!$B$2:$B$6,0)),"Sin etapa") -> Criterio 2 | Q20: =IF(L20="Si",1,0) -> 0 | R20: =IF(ISNUMBER(SEARCH("CRITERIO",N20)),1,0) -> 1 | S20: =IF(E20="","Sin dato",LEFT(E20,1)) -> B | T20: =IFERROR(INDEX(dCriticidad!$G$2:$G$7,MATCH(S20,dCriticidad!$A$2:$A$7,0)),0) -> 1 | U20: =IF(OR(LEFT(C20,3)="GI0",LEFT(C20,3)="GA0"),1,0) -> 0 | V20: =IF(G20="","Sin dato (ID GI)",TRIM(G20)) -> AREAS_DE_APOYO | W20: =IF(F20="","Sin dato",F20) -> Nube | X20: =IF(M20="","",YEAR(M20)) | Y20: =IF(M20="","",DATE(YEAR(M20),MONTH(M20),1)) | Z20: =IF(AND(Q20=0,COUNTIF(dDuplicadosGI!$A$2:$A$60,C20)>0),1,0) -> 1 | AA20: =IF(Q20=0,1,0) -> 1
A21: 20 | B21: LogiFlow | C21: TIE0019 | D21: Portal de aplicaciones para la gestión y administracion de procesos del Banco. | E21: C - BIA Crítica | F21: On Premise | G21: ACTIVOS | H21: LAURA ELIZABETH CARRASCO UQUILLAS | I21: ANDREA FERNANDA ORTIZ CISNEROS | J21: ERISLAN MARTINEZ JERA | K21: Aplicación del negocio | L21: Si | M21: 45200 | N21: N/A ENTREGADA | O21: =IF(COUNTIFS($B$2:B21,B21,$C$2:C21,C21)=1,1,0) -> 1 | P21: =IFERROR(INDEX(dEtapa!$A$2:$A$6,MATCH(N21,dEtapa!$B$2:$B$6,0)),"Sin etapa") -> Gobernada | Q21: =IF(L21="Si",1,0) -> 1 | R21: =IF(ISNUMBER(SEARCH("CRITERIO",N21)),1,0) -> 0 | S21: =IF(E21="","Sin dato",LEFT(E21,1)) -> C | T21: =IFERROR(INDEX(dCriticidad!$G$2:$G$7,MATCH(S21,dCriticidad!$A$2:$A$7,0)),0) -> 1 | U21: =IF(OR(LEFT(C21,3)="GI0",LEFT(C21,3)="GA0"),1,0) -> 0 | V21: =IF(G21="","Sin dato (ID GI)",TRIM(G21)) -> ACTIVOS | W21: =IF(F21="","Sin dato",F21) -> On Premise | X21: =IF(M21="","",YEAR(M21)) -> 2023 | Y21: =IF(M21="","",DATE(YEAR(M21),MONTH(M21),1)) -> 45200 | Z21: =IF(AND(Q21=0,COUNTIF(dDuplicadosGI!$A$2:$A$60,C21)>0),1,0) -> 0 | AA21: =IF(Q21=0,1,0) -> 0
A22: 21 | B22: LoginCentral | C22: SEC0028 | D22: Aplicación que reemplaza al Portal Empresarial respecto al tema de ingreso a las aplicaciones portalizadas, por esta aplicación permite el logueo a todas las aplicaciones portalizadas que dispone BP, el Login Central consume el serbvicio de WsConexioLdap, pose conexión con una BD de datos BD_TALOS y consume servicios del Process Server. | E22: B - Ecosistema Apetito de Riesgo | F22: On Premise | G22: Tribu Ciberseguridad | H22: JUAN FELIPE GALLEGO COSSIO | I22: FRANCISCO DAVID CEVALLOS GRANJA | J22: ROBERTO CARLOS PINO CEDENO | K22: Aplicación del negocio | L22: Si | M22: 45200 | N22: N/A ENTREGADA | O22: =IF(COUNTIFS($B$2:B22,B22,$C$2:C22,C22)=1,1,0) -> 1 | P22: =IFERROR(INDEX(dEtapa!$A$2:$A$6,MATCH(N22,dEtapa!$B$2:$B$6,0)),"Sin etapa") -> Gobernada | Q22: =IF(L22="Si",1,0) -> 1 | R22: =IF(ISNUMBER(SEARCH("CRITERIO",N22)),1,0) -> 0 | S22: =IF(E22="","Sin dato",LEFT(E22,1)) -> B | T22: =IFERROR(INDEX(dCriticidad!$G$2:$G$7,MATCH(S22,dCriticidad!$A$2:$A$7,0)),0) -> 1 | U22: =IF(OR(LEFT(C22,3)="GI0",LEFT(C22,3)="GA0"),1,0) -> 0 | V22: =IF(G22="","Sin dato (ID GI)",TRIM(G22)) -> Tribu Ciberseguridad | W22: =IF(F22="","Sin dato",F22) -> On Premise | X22: =IF(M22="","",YEAR(M22)) -> 2023 | Y22: =IF(M22="","",DATE(YEAR(M22),MONTH(M22),1)) -> 45200 | Z22: =IF(AND(Q22=0,COUNTIF(dDuplicadosGI!$A$2:$A$60,C22)>0),1,0) -> 0 | AA22: =IF(Q22=0,1,0) -> 0
A23: 22 | B23: Logística de Efectivo | C23: CHL0001 | D23: Aplicación que permite controlar el pedido de remesas de efectivo desde las agencias a los centros de acopio. Permite administrar en forma adecuada el proceso de Gestión de Logística de Efectivo y Valorados, desde el registro de la recepción de la solicitud, procesamiento, envío y contabilización de remesas en los centros de acopio, ATM¿s, agencias o sucursales y Banco Central. | E23: C - BIA Crítica | F23: On Premise | G23: AREAS_DE_APOYO | H23: FABIAN GEOVANNI PAZMINO UBIDIA | I23: PRISCILA ALEXANDRA PARRA LEON | J23: PRISCILA ALEXANDRA PARRA LEON | K23: Aplicación del negocio | L23: Si | M23: 45199 | N23: N/A ENTREGADA | O23: =IF(COUNTIFS($B$2:B23,B23,$C$2:C23,C23)=1,1,0) -> 1 | P23: =IFERROR(INDEX(dEtapa!$A$2:$A$6,MATCH(N23,dEtapa!$B$2:$B$6,0)),"Sin etapa") -> Gobernada | Q23: =IF(L23="Si",1,0) -> 1 | R23: =IF(ISNUMBER(SEARCH("CRITERIO",N23)),1,0) -> 0 | S23: =IF(E23="","Sin dato",LEFT(E23,1)) -> C | T23: =IFERROR(INDEX(dCriticidad!$G$2:$G$7,MATCH(S23,dCriticidad!$A$2:$A$7,0)),0) -> 1 | U23: =IF(OR(LEFT(C23,3)="GI0",LEFT(C23,3)="GA0"),1,0) -> 0 | V23: =IF(G23="","Sin dato (ID GI)",TRIM(G23)) -> AREAS_DE_APOYO | W23: =IF(F23="","Sin dato",F23) -> On Premise | X23: =IF(M23="","",YEAR(M23)) -> 2023 | Y23: =IF(M23="","",DATE(YEAR(M23),MONTH(M23),1)) -> 45170 | Z23: =IF(AND(Q23=0,COUNTIF(dDuplicadosGI!$A$2:$A$60,C23)>0),1,0) -> 0 | AA23: =IF(Q23=0,1,0) -> 0
A24: 23 | B24: Mail Control System | C24: SUP0012 | D24: Aplicación utilizada por el área Administrativa para gestionar el proceso de entrega y recepción de correspondencia interna. | E24: E - No Crítica | F24: Nube | G24: AREAS_DE_APOYO | H24: FABIAN GEOVANNI PAZMINO UBIDIA | I24: LIZETH AURORA ENCALADA RAMON | J24: ABRAHAM JOSUE MOGOLLON VASQUEZ | K24: Aplicación del negocio | L24: No | N24: PRIORIZACIÓN CRITERIO 1 | O24: =IF(COUNTIFS($B$2:B24,B24,$C$2:C24,C24)=1,1,0) -> 1 | P24: =IFERROR(INDEX(dEtapa!$A$2:$A$6,MATCH(N24,dEtapa!$B$2:$B$6,0)),"Sin etapa") -> Criterio 1 | Q24: =IF(L24="Si",1,0) -> 0 | R24: =IF(ISNUMBER(SEARCH("CRITERIO",N24)),1,0) -> 1 | S24: =IF(E24="","Sin dato",LEFT(E24,1)) -> E | T24: =IFERROR(INDEX(dCriticidad!$G$2:$G$7,MATCH(S24,dCriticidad!$A$2:$A$7,0)),0) -> 0 | U24: =IF(OR(LEFT(C24,3)="GI0",LEFT(C24,3)="GA0"),1,0) -> 0 | V24: =IF(G24="","Sin dato (ID GI)",TRIM(G24)) -> AREAS_DE_APOYO | W24: =IF(F24="","Sin dato",F24) -> Nube | X24: =IF(M24="","",YEAR(M24)) | Y24: =IF(M24="","",DATE(YEAR(M24),MONTH(M24),1)) | Z24: =IF(AND(Q24=0,COUNTIF(dDuplicadosGI!$A$2:$A$60,C24)>0),1,0) -> 1 | AA24: =IF(Q24=0,1,0) -> 1
A25: 24 | B25: MatiBOT | C25: ITM0075 | D25: Brindar a los usuarios la capacidad de realizar solicitudes a través de una interfaz de chat en diversos canales conversacionales, como Microsoft Teams, Web Chat o WhatsApp. | E25: E - No Crítica | F25: Nube | G25: Gerencia Arquitectura Usuario Final | H25: FAYOL SMITH MONTANO MELENDEZ | I25: ABNER ANDY AREVALO BRACAMONTE | J25: CARMEN ROCIO AGUILAR MAYANQUER | K25: Aplicación complementaria | L25: No | N25: PLANIFICADA 2027 | O25: =IF(COUNTIFS($B$2:B25,B25,$C$2:C25,C25)=1,1,0) -> 1 | P25: =IFERROR(INDEX(dEtapa!$A$2:$A$6,MATCH(N25,dEtapa!$B$2:$B$6,0)),"Sin etapa") -> Planificada 2027 | Q25: =IF(L25="Si",1,0) -> 0 | R25: =IF(ISNUMBER(SEARCH("CRITERIO",N25)),1,0) -> 0 | S25: =IF(E25="","Sin dato",LEFT(E25,1)) -> E | T25: =IFERROR(INDEX(dCriticidad!$G$2:$G$7,MATCH(S25,dCriticidad!$A$2:$A$7,0)),0) -> 0 | U25: =IF(OR(LEFT(C25,3)="GI0",LEFT(C25,3)="GA0"),1,0) -> 0 | V25: =IF(G25="","Sin dato (ID GI)",TRIM(G25)) -> Gerencia Arquitectura Usuario Final | W25: =IF(F25="","Sin dato",F25) -> Nube | X25: =IF(M25="","",YEAR(M25)) | Y25: =IF(M25="","",DATE(YEAR(M25),MONTH(M25),1)) | Z25: =IF(AND(Q25=0,COUNTIF(dDuplicadosGI!$A$2:$A$60,C25)>0),1,0) -> 0 | AA25: =IF(Q25=0,1,0) -> 1
A26: 25 | B26: Maze | C26: EDC0006 | D26: Herramienta de pruebas con usuarios de prototipos y encuestas masivas moderadas y no moderadas. | E26: E - No Crítica | F26: Nube | G26: COE Experiencia | H26: ANTONIO ALEJANDRO CANAVERAL GIL | I26: GABRIEL ANDRES PACHECO TELLO | J26: GABRIEL ANDRES PACHECO TELLO | K26: Utilitario | L26: No | N26: PLANIFICADA 2027 | O26: =IF(COUNTIFS($B$2:B26,B26,$C$2:C26,C26)=1,1,0) -> 1 | P26: =IFERROR(INDEX(dEtapa!$A$2:$A$6,MATCH(N26,dEtapa!$B$2:$B$6,0)),"Sin etapa") -> Planificada 2027 | Q26: =IF(L26="Si",1,0) -> 0 | R26: =IF(ISNUMBER(SEARCH("CRITERIO",N26)),1,0) -> 0 | S26: =IF(E26="","Sin dato",LEFT(E26,1)) -> E | T26: =IFERROR(INDEX(dCriticidad!$G$2:$G$7,MATCH(S26,dCriticidad!$A$2:$A$7,0)),0) -> 0 | U26: =IF(OR(LEFT(C26,3)="GI0",LEFT(C26,3)="GA0"),1,0) -> 0 | V26: =IF(G26="","Sin dato (ID GI)",TRIM(G26)) -> COE Experiencia | W26: =IF(F26="","Sin dato",F26) -> Nube | X26: =IF(M26="","",YEAR(M26)) | Y26: =IF(M26="","",DATE(YEAR(M26),MONTH(M26),1)) | Z26: =IF(AND(Q26=0,COUNTIF(dDuplicadosGI!$A$2:$A$60,C26)>0),1,0) -> 0 | AA26: =IF(Q26=0,1,0) -> 1
A27: 26 | B27: Mi Portal (4u) | C27: SUP0013 | D27: Es una aplicación web desarrollada en Angular y Node JS con base de datos postgres y se encuentra alojada en la nube de Google Cloud. En esta aplicación se disponibiliza para la autogestión del colaborador en temas internos | E27: D - BIA No Crítica | F27: Nube | G27: AREAS_DE_APOYO | H27: FABIAN GEOVANNI PAZMINO UBIDIA | I27: ANDREA PAULINA PARDO ULLAGUARI | J27: FRANKLIN STALIN GARZON ANDRADE | K27: Aplicación complementaria | L27: No | N27: PLANIFICADA 2027 | O27: =IF(COUNTIFS($B$2:B27,B27,$C$2:C27,C27)=1,1,0) -> 1 | P27: =IFERROR(INDEX(dEtapa!$A$2:$A$6,MATCH(N27,dEtapa!$B$2:$B$6,0)),"Sin etapa") -> Planificada 2027 | Q27: =IF(L27="Si",1,0) -> 0 | R27: =IF(ISNUMBER(SEARCH("CRITERIO",N27)),1,0) -> 0 | S27: =IF(E27="","Sin dato",LEFT(E27,1)) -> D | T27: =IFERROR(INDEX(dCriticidad!$G$2:$G$7,MATCH(S27,dCriticidad!$A$2:$A$7,0)),0) -> 0 | U27: =IF(OR(LEFT(C27,3)="GI0",LEFT(C27,3)="GA0"),1,0) -> 0 | V27: =IF(G27="","Sin dato (ID GI)",TRIM(G27)) -> AREAS_DE_APOYO | W27: =IF(F27="","Sin dato",F27) -> Nube | X27: =IF(M27="","",YEAR(M27)) | Y27: =IF(M27="","",DATE(YEAR(M27),MONTH(M27),1)) | Z27: =IF(AND(Q27=0,COUNTIF(dDuplicadosGI!$A$2:$A$60,C27)>0),1,0) -> 0 | AA27: =IF(Q27=0,1,0) -> 1
A28: 27 | B28: Microcrédito Digital | C28: PRD0053 | D28: Aplicativo para Microcredito en Linea de Microfinanzas | E28: E - No Crítica | F28: Nube | G28: MICROFINANZAS | H28: EUDOCIA BEATRIZ VASQUEZ CASTILLO | I28: LAURA ELIZABETH CARRASCO UQUILLAS | J28: ERISLAN MARTINEZ JERA | K28: Aplicación del negocio | L28: No | N28: PLANIFICADA 2027 | O28: =IF(COUNTIFS($B$2:B28,B28,$C$2:C28,C28)=1,1,0) -> 1 | P28: =IFERROR(INDEX(dEtapa!$A$2:$A$6,MATCH(N28,dEtapa!$B$2:$B$6,0)),"Sin etapa") -> Planificada 2027 | Q28: =IF(L28="Si",1,0) -> 0 | R28: =IF(ISNUMBER(SEARCH("CRITERIO",N28)),1,0) -> 0 | S28: =IF(E28="","Sin dato",LEFT(E28,1)) -> E | T28: =IFERROR(INDEX(dCriticidad!$G$2:$G$7,MATCH(S28,dCriticidad!$A$2:$A$7,0)),0) -> 0 | U28: =IF(OR(LEFT(C28,3)="GI0",LEFT(C28,3)="GA0"),1,0) -> 0 | V28: =IF(G28="","Sin dato (ID GI)",TRIM(G28)) -> MICROFINANZAS | W28: =IF(F28="","Sin dato",F28) -> Nube | X28: =IF(M28="","",YEAR(M28)) | Y28: =IF(M28="","",DATE(YEAR(M28),MONTH(M28),1)) | Z28: =IF(AND(Q28=0,COUNTIF(dDuplicadosGI!$A$2:$A$60,C28)>0),1,0) -> 0 | AA28: =IF(Q28=0,1,0) -> 1
A29: 28 | B29: Microfinance Portal | C29: PRD0063 | D29: Aplicativo para la aprobación, instrumentación y desembolso de créditos de la metodología Microfinanzas Individual y Grupal | E29: E - No Crítica | F29: Nube | G29: MICROFINANZAS | H29: LAURA ELIZABETH CARRASCO UQUILLAS | I29: FREDDY NEY BASTIDAS CALERO | J29: Willam Marcel Ontaneda Yaguana | K29: Aplicación del negocio | L29: No | N29: PRIORIZACIÓN CRITERIO 1 | O29: =IF(COUNTIFS($B$2:B29,B29,$C$2:C29,C29)=1,1,0) -> 1 | P29: =IFERROR(INDEX(dEtapa!$A$2:$A$6,MATCH(N29,dEtapa!$B$2:$B$6,0)),"Sin etapa") -> Criterio 1 | Q29: =IF(L29="Si",1,0) -> 0 | R29: =IF(ISNUMBER(SEARCH("CRITERIO",N29)),1,0) -> 1 | S29: =IF(E29="","Sin dato",LEFT(E29,1)) -> E | T29: =IFERROR(INDEX(dCriticidad!$G$2:$G$7,MATCH(S29,dCriticidad!$A$2:$A$7,0)),0) -> 0 | U29: =IF(OR(LEFT(C29,3)="GI0",LEFT(C29,3)="GA0"),1,0) -> 0 | V29: =IF(G29="","Sin dato (ID GI)",TRIM(G29)) -> MICROFINANZAS | W29: =IF(F29="","Sin dato",F29) -> Nube | X29: =IF(M29="","",YEAR(M29)) | Y29: =IF(M29="","",DATE(YEAR(M29),MONTH(M29),1)) | Z29: =IF(AND(Q29=0,COUNTIF(dDuplicadosGI!$A$2:$A$60,C29)>0),1,0) -> 0 | AA29: =IF(Q29=0,1,0) -> 1
A30: 29 | B30: Mis Riesgos | C30: RIS0008 | D30: Agrupación lógica de las aplicaciones internas desarrolladas por Banco, que no cuentan con un ambiente controlado, Banco realiza cambios directos y sus actualizaciones no sigue el proceso de control de cambios. | E30: E - No Crítica | F30: On Premise | G30: Tribu Administración de Créditos | H30: JORGE MARIO PULGARIN MAZO | I30: JOHANNA NATALIA RODRIGUEZ SANCHEZ | J30: CHRISTIAN PAUL ENRIQUEZ LOPEZ | K30: Aplicación del negocio | L30: No | N30: PRIORIZACIÓN CRITERIO 1 | O30: =IF(COUNTIFS($B$2:B30,B30,$C$2:C30,C30)=1,1,0) -> 1 | P30: =IFERROR(INDEX(dEtapa!$A$2:$A$6,MATCH(N30,dEtapa!$B$2:$B$6,0)),"Sin etapa") -> Criterio 1 | Q30: =IF(L30="Si",1,0) -> 0 | R30: =IF(ISNUMBER(SEARCH("CRITERIO",N30)),1,0) -> 1 | S30: =IF(E30="","Sin dato",LEFT(E30,1)) -> E | T30: =IFERROR(INDEX(dCriticidad!$G$2:$G$7,MATCH(S30,dCriticidad!$A$2:$A$7,0)),0) -> 0 | U30: =IF(OR(LEFT(C30,3)="GI0",LEFT(C30,3)="GA0"),1,0) -> 0 | V30: =IF(G30="","Sin dato (ID GI)",TRIM(G30)) -> Tribu Administración de Créditos | W30: =IF(F30="","Sin dato",F30) -> On Premise | X30: =IF(M30="","",YEAR(M30)) | Y30: =IF(M30="","",DATE(YEAR(M30),MONTH(M30),1)) | Z30: =IF(AND(Q30=0,COUNTIF(dDuplicadosGI!$A$2:$A$60,C30)>0),1,0) -> 0 | AA30: =IF(Q30=0,1,0) -> 1
A31: 30 | B31: MODELO PREDICTIVO CIIU | C31: DAT0006 | D31: Modelo de Sector y Actividad Económica | E31: E - No Crítica | F31: On Premise | G31: COE DATOS&ANALITICA | H31: ARNALDO UTRIA AZAN | I31: ARNALDO UTRIA AZAN | J31: ARNALDO UTRIA AZAN | K31: Aplicación complementaria | L31: No | N31: PLANIFICADA 2027 | O31: =IF(COUNTIFS($B$2:B31,B31,$C$2:C31,C31)=1,1,0) -> 1 | P31: =IFERROR(INDEX(dEtapa!$A$2:$A$6,MATCH(N31,dEtapa!$B$2:$B$6,0)),"Sin etapa") -> Planificada 2027 | Q31: =IF(L31="Si",1,0) -> 0 | R31: =IF(ISNUMBER(SEARCH("CRITERIO",N31)),1,0) -> 0 | S31: =IF(E31="","Sin dato",LEFT(E31,1)) -> E | T31: =IFERROR(INDEX(dCriticidad!$G$2:$G$7,MATCH(S31,dCriticidad!$A$2:$A$7,0)),0) -> 0 | U31: =IF(OR(LEFT(C31,3)="GI0",LEFT(C31,3)="GA0"),1,0) -> 0 | V31: =IF(G31="","Sin dato (ID GI)",TRIM(G31)) -> COE DATOS&ANALITICA | W31: =IF(F31="","Sin dato",F31) -> On Premise | X31: =IF(M31="","",YEAR(M31)) | Y31: =IF(M31="","",DATE(YEAR(M31),MONTH(M31),1)) | Z31: =IF(AND(Q31=0,COUNTIF(dDuplicadosGI!$A$2:$A$60,C31)>0),1,0) -> 0 | AA31: =IF(Q31=0,1,0) -> 1
A32: 31 | B32: Moengage | C32: OMN0001 | D32: Es una plataforma de compromiso del cliente y automatización de marketing que ayuda a las empresas a interactuar con sus usuarios a través de canales como notificaciones push, mensajes dentro de la aplicación, correos electrónicos, mensajes de texto (SMS) y más | E32: B - Ecosistema Apetito de Riesgo | F32: Nube | G32: INFRAESTRUCTURA | H32: BYRON ORLANDO MELENDREZ CABRERA | I32: CESAR ALEJANDRO VELASCO TORO | J32: HORACIO LEONEL HOLGUIN ALCIVAR | K32: Aplicación complementaria | L32: No | N32: PRIORIZACIÓN CRITERIO 1 | O32: =IF(COUNTIFS($B$2:B32,B32,$C$2:C32,C32)=1,1,0) -> 1 | P32: =IFERROR(INDEX(dEtapa!$A$2:$A$6,MATCH(N32,dEtapa!$B$2:$B$6,0)),"Sin etapa") -> Criterio 1 | Q32: =IF(L32="Si",1,0) -> 0 | R32: =IF(ISNUMBER(SEARCH("CRITERIO",N32)),1,0) -> 1 | S32: =IF(E32="","Sin dato",LEFT(E32,1)) -> B | T32: =IFERROR(INDEX(dCriticidad!$G$2:$G$7,MATCH(S32,dCriticidad!$A$2:$A$7,0)),0) -> 1 | U32: =IF(OR(LEFT(C32,3)="GI0",LEFT(C32,3)="GA0"),1,0) -> 0 | V32: =IF(G32="","Sin dato (ID GI)",TRIM(G32)) -> INFRAESTRUCTURA | W32: =IF(F32="","Sin dato",F32) -> Nube | X32: =IF(M32="","",YEAR(M32)) | Y32: =IF(M32="","",DATE(YEAR(M32),MONTH(M32),1)) | Z32: =IF(AND(Q32=0,COUNTIF(dDuplicadosGI!$A$2:$A$60,C32)>0),1,0) -> 0 | AA32: =IF(Q32=0,1,0) -> 1
A33: 32 | B33: Monitor Plus | C33: GOB0005 | D33: Aplicación que permite realizar el monitoreo de las transacciones de clientes para identificación de lavado de dinero y fraude, es de tercero (nombre proveedor plus Holding) implementado en datacenter de Banco. | E33: E - No Crítica | F33: Híbrida | G33: AREAS_DE_APOYO | H33: FABIAN GEOVANNI PAZMINO UBIDIA | I33: JOSE LUIS ZAPATA ROSERO | J33: FERNANDO JOSE ROLDAN CORREA | K33: Aplicación complementaria | L33: No | N33: PRIORIZACIÓN CRITERIO 1 | O33: =IF(COUNTIFS($B$2:B33,B33,$C$2:C33,C33)=1,1,0) -> 1 | P33: =IFERROR(INDEX(dEtapa!$A$2:$A$6,MATCH(N33,dEtapa!$B$2:$B$6,0)),"Sin etapa") -> Criterio 1 | Q33: =IF(L33="Si",1,0) -> 0 | R33: =IF(ISNUMBER(SEARCH("CRITERIO",N33)),1,0) -> 1 | S33: =IF(E33="","Sin dato",LEFT(E33,1)) -> E | T33: =IFERROR(INDEX(dCriticidad!$G$2:$G$7,MATCH(S33,dCriticidad!$A$2:$A$7,0)),0) -> 0 | U33: =IF(OR(LEFT(C33,3)="GI0",LEFT(C33,3)="GA0"),1,0) -> 0 | V33: =IF(G33="","Sin dato (ID GI)",TRIM(G33)) -> AREAS_DE_APOYO | W33: =IF(F33="","Sin dato",F33) -> Híbrida | X33: =IF(M33="","",YEAR(M33)) | Y33: =IF(M33="","",DATE(YEAR(M33),MONTH(M33),1)) | Z33: =IF(AND(Q33=0,COUNTIF(dDuplicadosGI!$A$2:$A$60,C33)>0),1,0) -> 0 | AA33: =IF(Q33=0,1,0) -> 1
A34: 33 | B34: CreditoDistribuidor | C34: PRD0014 | D34: Aplicación web en la Intranet que genera créditos a pequeñas y medianas empresas que se encuentran afiliadas a Banco Pichincha. Se manejan créditos a proveedores y distribuidores basados en una empresa mayorista o ancla, en el caso de créditos a proveedores se deposita en la cuenta de la empresa directamente afiliada a BP y en el caso de créditos a proveedores en la cuenta del proveedor de la empresa afiliada a Banco Pichincha. | E34: D - BIA No Crítica | F34: On Premise | G34: Frente de Soluciones Empresariales | H34: LUIS MIGUEL ULLOA MOREIRA | I34: FABRICIO ANTONIO PEREIRA GARCIA | J34: WILLIAM PATRICIO PANCHI SHUGULI | K34: Aplicación del negocio | L34: Si | M34: 45199 | N34: N/A ENTREGADA | O34: =IF(COUNTIFS($B$2:B34,B34,$C$2:C34,C34)=1,1,0) -> 1 | P34: =IFERROR(INDEX(dEtapa!$A$2:$A$6,MATCH(N34,dEtapa!$B$2:$B$6,0)),"Sin etapa") -> Gobernada | Q34: =IF(L34="Si",1,0) -> 1 | R34: =IF(ISNUMBER(SEARCH("CRITERIO",N34)),1,0) -> 0 | S34: =IF(E34="","Sin dato",LEFT(E34,1)) -> D | T34: =IFERROR(INDEX(dCriticidad!$G$2:$G$7,MATCH(S34,dCriticidad!$A$2:$A$7,0)),0) -> 0 | U34: =IF(OR(LEFT(C34,3)="GI0",LEFT(C34,3)="GA0"),1,0) -> 0 | V34: =IF(G34="","Sin dato (ID GI)",TRIM(G34)) -> Frente de Soluciones Empresariales | W34: =IF(F34="","Sin dato",F34) -> On Premise | X34: =IF(M34="","",YEAR(M34)) -> 2023 | Y34: =IF(M34="","",DATE(YEAR(M34),MONTH(M34),1)) -> 45170 | Z34: =IF(AND(Q34=0,COUNTIF(dDuplicadosGI!$A$2:$A$60,C34)>0),1,0) -> 0 | AA34: =IF(Q34=0,1,0) -> 0
A35: 34 | B35: CreditosCOM | C35: PRD0015 | D35: Aplicación que maneja el flujo de créditos para Crédito Distribuidor. | E35: D - BIA No Crítica | F35: On Premise | G35: ACTIVOS | H35: LAURA ELIZABETH CARRASCO UQUILLAS | I35: ANDREA FERNANDA ORTIZ CISNEROS | J35: ERISLAN MARTINEZ JERA | K35: Aplicación del negocio | L35: Si | M35: 45199 | N35: N/A ENTREGADA | O35: =IF(COUNTIFS($B$2:B35,B35,$C$2:C35,C35)=1,1,0) -> 1 | P35: =IFERROR(INDEX(dEtapa!$A$2:$A$6,MATCH(N35,dEtapa!$B$2:$B$6,0)),"Sin etapa") -> Gobernada | Q35: =IF(L35="Si",1,0) -> 1 | R35: =IF(ISNUMBER(SEARCH("CRITERIO",N35)),1,0) -> 0 | S35: =IF(E35="","Sin dato",LEFT(E35,1)) -> D | T35: =IFERROR(INDEX(dCriticidad!$G$2:$G$7,MATCH(S35,dCriticidad!$A$2:$A$7,0)),0) -> 0 | U35: =IF(OR(LEFT(C35,3)="GI0",LEFT(C35,3)="GA0"),1,0) -> 0 | V35: =IF(G35="","Sin dato (ID GI)",TRIM(G35)) -> ACTIVOS | W35: =IF(F35="","Sin dato",F35) -> On Premise | X35: =IF(M35="","",YEAR(M35)) -> 2023 | Y35: =IF(M35="","",DATE(YEAR(M35),MONTH(M35),1)) -> 45170 | Z35: =IF(AND(Q35=0,COUNTIF(dDuplicadosGI!$A$2:$A$60,C35)>0),1,0) -> 0 | AA35: =IF(Q35=0,1,0) -> 0
A36: 35 | B36: CRM (salesforce - Financial services) | C36: CUS0007 | D36: No existe descripción | E36: C - BIA Crítica | F36: Nube | G36: Negocios y Monetización | H36: ANTONIO ALEJANDRO CANAVERAL GIL | I36: JULIEN LOUIS ADRIEN LEREBOULLET | J36: HECTOR EDUARDO JARAMILLO RUALES | K36: Aplicación del negocio | L36: Si | M36: 45200 | N36: N/A ENTREGADA | O36: =IF(COUNTIFS($B$2:B36,B36,$C$2:C36,C36)=1,1,0) -> 1 | P36: =IFERROR(INDEX(dEtapa!$A$2:$A$6,MATCH(N36,dEtapa!$B$2:$B$6,0)),"Sin etapa") -> Gobernada | Q36: =IF(L36="Si",1,0) -> 1 | R36: =IF(ISNUMBER(SEARCH("CRITERIO",N36)),1,0) -> 0 | S36: =IF(E36="","Sin dato",LEFT(E36,1)) -> C | T36: =IFERROR(INDEX(dCriticidad!$G$2:$G$7,MATCH(S36,dCriticidad!$A$2:$A$7,0)),0) -> 1 | U36: =IF(OR(LEFT(C36,3)="GI0",LEFT(C36,3)="GA0"),1,0) -> 0 | V36: =IF(G36="","Sin dato (ID GI)",TRIM(G36)) -> Negocios y Monetización | W36: =IF(F36="","Sin dato",F36) -> Nube | X36: =IF(M36="","",YEAR(M36)) -> 2023 | Y36: =IF(M36="","",DATE(YEAR(M36),MONTH(M36),1)) -> 45200 | Z36: =IF(AND(Q36=0,COUNTIF(dDuplicadosGI!$A$2:$A$60,C36)>0),1,0) -> 0 | AA36: =IF(Q36=0,1,0) -> 0
A37: 36 | B37: CRM (salesforce - Marketing Cloud) | C37: CUS0008 | D37: Es una plataforma de automatización de marketing digital en la nube, parte del ecosistema CRM de Salesforce, diseñada para gestionar campañas multicanal (email, móvil, redes sociales, web). | E37: E - No Crítica | F37: Nube | G37: Negocios y Monetización | H37: ANTONIO ALEJANDRO CANAVERAL GIL | I37: SEBASTIAN MUNOZ ANDERSEN | J37: HECTOR EDUARDO JARAMILLO RUALES | K37: Aplicación del negocio | L37: Si | M37: 46052 | N37: N/A ENTREGADA | O37: =IF(COUNTIFS($B$2:B37,B37,$C$2:C37,C37)=1,1,0) -> 1 | P37: =IFERROR(INDEX(dEtapa!$A$2:$A$6,MATCH(N37,dEtapa!$B$2:$B$6,0)),"Sin etapa") -> Gobernada | Q37: =IF(L37="Si",1,0) -> 1 | R37: =IF(ISNUMBER(SEARCH("CRITERIO",N37)),1,0) -> 0 | S37: =IF(E37="","Sin dato",LEFT(E37,1)) -> E | T37: =IFERROR(INDEX(dCriticidad!$G$2:$G$7,MATCH(S37,dCriticidad!$A$2:$A$7,0)),0) -> 0 | U37: =IF(OR(LEFT(C37,3)="GI0",LEFT(C37,3)="GA0"),1,0) -> 0 | V37: =IF(G37="","Sin dato (ID GI)",TRIM(G37)) -> Negocios y Monetización | W37: =IF(F37="","Sin dato",F37) -> Nube | X37: =IF(M37="","",YEAR(M37)) -> 2026 | Y37: =IF(M37="","",DATE(YEAR(M37),MONTH(M37),1)) -> 46023 | Z37: =IF(AND(Q37=0,COUNTIF(dDuplicadosGI!$A$2:$A$60,C37)>0),1,0) -> 0 | AA37: =IF(Q37=0,1,0) -> 0
A38: 37 | B38: Crowdstrike | C38: SEC0009 | D38: Ofrece una prevención de amenazas óptima, mediante el uso de inteligencia artificial (AI) y aprendizaje automático (ML) con detección y respuesta avanzada e información sobre amenazas, integrada a través de una consola de gestión altamente intuitiva. | E38: C - BIA Crítica | F38: Nube | G38: Ciberseguridad | H38: ERICK DAMIAN RISUENO BENITEZ | I38: MARCO FABRICIO FALCONI NORIEGA | J38: lvtandaz@pichincha.com TANDAZO GALLEGOS | K38: Consolas de Administración Seguridad | L38: Si | M38: 45715 | N38: N/A ENTREGADA | O38: =IF(COUNTIFS($B$2:B38,B38,$C$2:C38,C38)=1,1,0) -> 1 | P38: =IFERROR(INDEX(dEtapa!$A$2:$A$6,MATCH(N38,dEtapa!$B$2:$B$6,0)),"Sin etapa") -> Gobernada | Q38: =IF(L38="Si",1,0) -> 1 | R38: =IF(ISNUMBER(SEARCH("CRITERIO",N38)),1,0) -> 0 | S38: =IF(E38="","Sin dato",LEFT(E38,1)) -> C | T38: =IFERROR(INDEX(dCriticidad!$G$2:$G$7,MATCH(S38,dCriticidad!$A$2:$A$7,0)),0) -> 1 | U38: =IF(OR(LEFT(C38,3)="GI0",LEFT(C38,3)="GA0"),1,0) -> 0 | V38: =IF(G38="","Sin dato (ID GI)",TRIM(G38)) -> Ciberseguridad | W38: =IF(F38="","Sin dato",F38) -> Nube | X38: =IF(M38="","",YEAR(M38)) -> 2025 | Y38: =IF(M38="","",DATE(YEAR(M38),MONTH(M38),1)) -> 45689 | Z38: =IF(AND(Q38=0,COUNTIF(dDuplicadosGI!$A$2:$A$60,C38)>0),1,0) -> 0 | AA38: =IF(Q38=0,1,0) -> 0
A39: 38 | B39: Cuadre Atms | C39: SUP0021 | D39: Aplicación que dispone de procesos para cuadre de cajeros automáticos (cuadre físico vs reporte del Switch de Servicios ATMs) y conciliación de transacciones en ATMs propios (clientes BP y clientes de otras redes). | E39: C - BIA Crítica | F39: On Premise | G39: TRIBU_CANALES | H39: MIGUEL ALEXANDER MEJIA BRONCANO | I39: MILTON PATRICIO MANTILLA CAYO | J39: JUAN FRANCISCO PROCEL MICHILENA | K39: Aplicación del negocio | L39: Si | M39: 45199 | N39: N/A ENTREGADA | O39: =IF(COUNTIFS($B$2:B39,B39,$C$2:C39,C39)=1,1,0) -> 1 | P39: =IFERROR(INDEX(dEtapa!$A$2:$A$6,MATCH(N39,dEtapa!$B$2:$B$6,0)),"Sin etapa") -> Gobernada | Q39: =IF(L39="Si",1,0) -> 1 | R39: =IF(ISNUMBER(SEARCH("CRITERIO",N39)),1,0) -> 0 | S39: =IF(E39="","Sin dato",LEFT(E39,1)) -> C | T39: =IFERROR(INDEX(dCriticidad!$G$2:$G$7,MATCH(S39,dCriticidad!$A$2:$A$7,0)),0) -> 1 | U39: =IF(OR(LEFT(C39,3)="GI0",LEFT(C39,3)="GA0"),1,0) -> 0 | V39: =IF(G39="","Sin dato (ID GI)",TRIM(G39)) -> TRIBU_CANALES | W39: =IF(F39="","Sin dato",F39) -> On Premise | X39: =IF(M39="","",YEAR(M39)) -> 2023 | Y39: =IF(M39="","",DATE(YEAR(M39),MONTH(M39),1)) -> 45170 | Z39: =IF(AND(Q39=0,COUNTIF(dDuplicadosGI!$A$2:$A$60,C39)>0),1,0) -> 0 | AA39: =IF(Q39=0,1,0) -> 0
A40: 39 | B40: Cuenta Digital Personas | C40: CHL0037 | D40: APP ONBOARDING, aplicación movil de Banco Pichincha, en la que podrá crear clientes, activar cuentas, crear chequeras. | E40: C - BIA Crítica | F40: Nube | G40: PASIVOS Y SEGUROS | H40: LAURA ELIZABETH CARRASCO UQUILLAS | I40: JONATHAN HERNAN ARIAS HERNANDEZ | J40: MANUEL ABELARDO HARO MONTERO | K40: Aplicación complementaria | L40: No | N40: PLANIFICADA 2027 | O40: =IF(COUNTIFS($B$2:B40,B40,$C$2:C40,C40)=1,1,0) -> 1 | P40: =IFERROR(INDEX(dEtapa!$A$2:$A$6,MATCH(N40,dEtapa!$B$2:$B$6,0)),"Sin etapa") -> Planificada 2027 | Q40: =IF(L40="Si",1,0) -> 0 | R40: =IF(ISNUMBER(SEARCH("CRITERIO",N40)),1,0) -> 0 | S40: =IF(E40="","Sin dato",LEFT(E40,1)) -> C | T40: =IFERROR(INDEX(dCriticidad!$G$2:$G$7,MATCH(S40,dCriticidad!$A$2:$A$7,0)),0) -> 1 | U40: =IF(OR(LEFT(C40,3)="GI0",LEFT(C40,3)="GA0"),1,0) -> 0 | V40: =IF(G40="","Sin dato (ID GI)",TRIM(G40)) -> PASIVOS Y SEGUROS | W40: =IF(F40="","Sin dato",F40) -> Nube | X40: =IF(M40="","",YEAR(M40)) | Y40: =IF(M40="","",DATE(YEAR(M40),MONTH(M40),1)) | Z40: =IF(AND(Q40=0,COUNTIF(dDuplicadosGI!$A$2:$A$60,C40)>0),1,0) -> 0 | AA40: =IF(Q40=0,1,0) -> 1
A41: 40 | B41: Cuentas por pagar | C41: SUP0031 | D41: Es un por portal donde se visualiza los diferentes documentos de proveedores de banco (facturas, retenciones). Está en un aks de azure | E41: E - No Crítica | F41: Nube | G41: AREAS_DE_APOYO | H41: FABIAN GEOVANNI PAZMINO UBIDIA | I41: LIZETH AURORA ENCALADA RAMON | J41: ABRAHAM JOSUE MOGOLLON VASQUEZ | K41: Aplicación complementaria | L41: No | N41: PLANIFICADA 2027 | O41: =IF(COUNTIFS($B$2:B41,B41,$C$2:C41,C41)=1,1,0) -> 1 | P41: =IFERROR(INDEX(dEtapa!$A$2:$A$6,MATCH(N41,dEtapa!$B$2:$B$6,0)),"Sin etapa") -> Planificada 2027 | Q41: =IF(L41="Si",1,0) -> 0 | R41: =IF(ISNUMBER(SEARCH("CRITERIO",N41)),1,0) -> 0 | S41: =IF(E41="","Sin dato",LEFT(E41,1)) -> E | T41: =IFERROR(INDEX(dCriticidad!$G$2:$G$7,MATCH(S41,dCriticidad!$A$2:$A$7,0)),0) -> 0 | U41: =IF(OR(LEFT(C41,3)="GI0",LEFT(C41,3)="GA0"),1,0) -> 0 | V41: =IF(G41="","Sin dato (ID GI)",TRIM(G41)) -> AREAS_DE_APOYO | W41: =IF(F41="","Sin dato",F41) -> Nube | X41: =IF(M41="","",YEAR(M41)) | Y41: =IF(M41="","",DATE(YEAR(M41),MONTH(M41),1)) | Z41: =IF(AND(Q41=0,COUNTIF(dDuplicadosGI!$A$2:$A$60,C41)>0),1,0) -> 0 | AA41: =IF(Q41=0,1,0) -> 1
A42: 41 | B42: CXP (Banca Web) | C42: CHL0014 | D42: Nueva banca electrónica con cambios en su tecnología para soportar el crecimiento de Banco Pichincha, así como también para apalancar los objetivos de banco para lograr una aplicación Omnicanal. Permite realizar transacciones y trámites bancarios a través de Internet. Una solucion virtual, digital y electrónica. | E42: A - Apetito de Riesgo Disponibilidad | F42: Nube | G42: TRIBU_CANALES | H42: MIGUEL ALEXANDER MEJIA BRONCANO | I42: DIANA PATRICIA CAICEDO RODRIGUEZ | J42: MIGUEL ALEXANDER MEJIA BRONCANO | K42: Aplicación del negocio | L42: No | N42: PLANIFICADA 2027 | O42: =IF(COUNTIFS($B$2:B42,B42,$C$2:C42,C42)=1,1,0) -> 1 | P42: =IFERROR(INDEX(dEtapa!$A$2:$A$6,MATCH(N42,dEtapa!$B$2:$B$6,0)),"Sin etapa") -> Planificada 2027 | Q42: =IF(L42="Si",1,0) -> 0 | R42: =IF(ISNUMBER(SEARCH("CRITERIO",N42)),1,0) -> 0 | S42: =IF(E42="","Sin dato",LEFT(E42,1)) -> A | T42: =IFERROR(INDEX(dCriticidad!$G$2:$G$7,MATCH(S42,dCriticidad!$A$2:$A$7,0)),0) -> 1 | U42: =IF(OR(LEFT(C42,3)="GI0",LEFT(C42,3)="GA0"),1,0) -> 0 | V42: =IF(G42="","Sin dato (ID GI)",TRIM(G42)) -> TRIBU_CANALES | W42: =IF(F42="","Sin dato",F42) -> Nube | X42: =IF(M42="","",YEAR(M42)) | Y42: =IF(M42="","",DATE(YEAR(M42),MONTH(M42),1)) | Z42: =IF(AND(Q42=0,COUNTIF(dDuplicadosGI!$A$2:$A$60,C42)>0),1,0) -> 0 | AA42: =IF(Q42=0,1,0) -> 1
A43: 42 | B43: CyberArk | C43: SEC0010 | D43: Aplicación que permite el manejo de cuentas de usuarios privilegiados | E43: C - BIA Crítica | F43: On Premise | G43: Ciberseguridad | H43: ROBERT STALIN SOTO CORONEL | I43: MARCO FABRICIO FALCONI NORIEGA | J43: ERICK DAMIAN RISUENO BENITEZ | K43: Consolas de Administración Seguridad | L43: Si | M43: 46262 | N43: N/A ENTREGADA | O43: =IF(COUNTIFS($B$2:B43,B43,$C$2:C43,C43)=1,1,0) -> 1 | P43: =IFERROR(INDEX(dEtapa!$A$2:$A$6,MATCH(N43,dEtapa!$B$2:$B$6,0)),"Sin etapa") -> Gobernada | Q43: =IF(L43="Si",1,0) -> 1 | R43: =IF(ISNUMBER(SEARCH("CRITERIO",N43)),1,0) -> 0 | S43: =IF(E43="","Sin dato",LEFT(E43,1)) -> C | T43: =IFERROR(INDEX(dCriticidad!$G$2:$G$7,MATCH(S43,dCriticidad!$A$2:$A$7,0)),0) -> 1 | U43: =IF(OR(LEFT(C43,3)="GI0",LEFT(C43,3)="GA0"),1,0) -> 0 | V43: =IF(G43="","Sin dato (ID GI)",TRIM(G43)) -> Ciberseguridad | W43: =IF(F43="","Sin dato",F43) -> On Premise | X43: =IF(M43="","",YEAR(M43)) -> 2026 | Y43: =IF(M43="","",DATE(YEAR(M43),MONTH(M43),1)) -> 46235 | Z43: =IF(AND(Q43=0,COUNTIF(dDuplicadosGI!$A$2:$A$60,C43)>0),1,0) -> 0 | AA43: =IF(Q43=0,1,0) -> 0
A44: 43 | B44: DarkTrace | C44: SEC0011 | D44: Inspección de tráfico de Red para determinar amenazas de seguridad. Tecnología de inteligencia artificial cibernética de autoaprendizaje que detecta nuevos ataques y amenazas internas en una etapa temprana | E44: E - No Crítica | F44: On Premise | G44: Ciberseguridad | H44: MARIA DEL CARMEN PENAHERRERA PLUA | I44: MARCO FABRICIO FALCONI NORIEGA | J44: JORGE XAVIER LUCERO GALLEGOS | K44: Consolas de Administración Seguridad | L44: No | N44: PRIORIZACIÓN CRITERIO 3 | O44: =IF(COUNTIFS($B$2:B44,B44,$C$2:C44,C44)=1,1,0) -> 1 | P44: =IFERROR(INDEX(dEtapa!$A$2:$A$6,MATCH(N44,dEtapa!$B$2:$B$6,0)),"Sin etapa") -> Criterio 3 | Q44: =IF(L44="Si",1,0) -> 0 | R44: =IF(ISNUMBER(SEARCH("CRITERIO",N44)),1,0) -> 1 | S44: =IF(E44="","Sin dato",LEFT(E44,1)) -> E | T44: =IFERROR(INDEX(dCriticidad!$G$2:$G$7,MATCH(S44,dCriticidad!$A$2:$A$7,0)),0) -> 0 | U44: =IF(OR(LEFT(C44,3)="GI0",LEFT(C44,3)="GA0"),1,0) -> 0 | V44: =IF(G44="","Sin dato (ID GI)",TRIM(G44)) -> Ciberseguridad | W44: =IF(F44="","Sin dato",F44) -> On Premise | X44: =IF(M44="","",YEAR(M44)) | Y44: =IF(M44="","",DATE(YEAR(M44),MONTH(M44),1)) | Z44: =IF(AND(Q44=0,COUNTIF(dDuplicadosGI!$A$2:$A$60,C44)>0),1,0) -> 0 | AA44: =IF(Q44=0,1,0) -> 1
A45: 44 | B45: DataPower Externo | C45: INT0005 | D45: IBM DataPower es una consola/plataforma de seguridad e integración usada para administrar, proteger y publicar servicios como APIs, SOAP y REST. Permite aplicar políticas de autenticación, autorización, cifrado, firma y validación de mensajes. También se usa como gateway para enrutar, transformar y monitorear tráfico entre aplicaciones y sistemas | E45: B - Ecosistema Apetito de Riesgo | F45: On Premise | G45: Tribu_Integraciones_Apis | H45: DAVID RODRIGO REVELO RIVERA | I45: DIEGO VLADIMIR JAYA GUAMANZARA | J45: CHRISTIAN DARIO PASQUEL PARRA | K45: Consolas de Administración TI | L45: Si | M45: 46197 | N45: N/A ENTREGADA | O45: =IF(COUNTIFS($B$2:B45,B45,$C$2:C45,C45)=1,1,0) -> 1 | P45: =IFERROR(INDEX(dEtapa!$A$2:$A$6,MATCH(N45,dEtapa!$B$2:$B$6,0)),"Sin etapa") -> Gobernada | Q45: =IF(L45="Si",1,0) -> 1 | R45: =IF(ISNUMBER(SEARCH("CRITERIO",N45)),1,0) -> 0 | S45: =IF(E45="","Sin dato",LEFT(E45,1)) -> B | T45: =IFERROR(INDEX(dCriticidad!$G$2:$G$7,MATCH(S45,dCriticidad!$A$2:$A$7,0)),0) -> 1 | U45: =IF(OR(LEFT(C45,3)="GI0",LEFT(C45,3)="GA0"),1,0) -> 0 | V45: =IF(G45="","Sin dato (ID GI)",TRIM(G45)) -> Tribu_Integraciones_Apis | W45: =IF(F45="","Sin dato",F45) -> On Premise | X45: =IF(M45="","",YEAR(M45)) -> 2026 | Y45: =IF(M45="","",DATE(YEAR(M45),MONTH(M45),1)) -> 46174 | Z45: =IF(AND(Q45=0,COUNTIF(dDuplicadosGI!$A$2:$A$60,C45)>0),1,0) -> 0 | AA45: =IF(Q45=0,1,0) -> 0
A46: 45 | B46: Decisión Cloud | C46: ITM0001 | D46: No existe descripción | E46: E - No Crítica | F46: Nube | G46: Ciberseguridad | H46: ANDY JOSE ANDRADE BRAVO | I46: MARCO FABRICIO FALCONI NORIEGA | J46: CARLOS ANDRES MORALES MALDONADO | K46: Consolas de Administración Seguridad | L46: Si | M46: 46035 | N46: N/A ENTREGADA | O46: =IF(COUNTIFS($B$2:B46,B46,$C$2:C46,C46)=1,1,0) -> 1 | P46: =IFERROR(INDEX(dEtapa!$A$2:$A$6,MATCH(N46,dEtapa!$B$2:$B$6,0)),"Sin etapa") -> Gobernada | Q46: =IF(L46="Si",1,0) -> 1 | R46: =IF(ISNUMBER(SEARCH("CRITERIO",N46)),1,0) -> 0 | S46: =IF(E46="","Sin dato",LEFT(E46,1)) -> E | T46: =IFERROR(INDEX(dCriticidad!$G$2:$G$7,MATCH(S46,dCriticidad!$A$2:$A$7,0)),0) -> 0 | U46: =IF(OR(LEFT(C46,3)="GI0",LEFT(C46,3)="GA0"),1,0) -> 0 | V46: =IF(G46="","Sin dato (ID GI)",TRIM(G46)) -> Ciberseguridad | W46: =IF(F46="","Sin dato",F46) -> Nube | X46: =IF(M46="","",YEAR(M46)) -> 2026 | Y46: =IF(M46="","",DATE(YEAR(M46),MONTH(M46),1)) -> 46023 | Z46: =IF(AND(Q46=0,COUNTIF(dDuplicadosGI!$A$2:$A$60,C46)>0),1,0) -> 0 | AA46: =IF(Q46=0,1,0) -> 0
A47: 46 | B47: Deep Security | C47: SEC0014 | D47: Proporciona una protección completa, adaptable y extremadamente eficiente, con antimalware, detección y prevención de intrusiones, firewall, protección de aplicaciones Web, supervisión de la integridad e inspección de registros | E47: E - No Crítica | F47: On Premise | G47: Ciberseguridad | H47: ERICK DAMIAN RISUENO BENITEZ | I47: MARCO FABRICIO FALCONI NORIEGA | J47: ROBERT STALIN SOTO CORONEL | K47: Consolas de Administración Seguridad | L47: Si | M47: 45736 | N47: N/A ENTREGADA | O47: =IF(COUNTIFS($B$2:B47,B47,$C$2:C47,C47)=1,1,0) -> 1 | P47: =IFERROR(INDEX(dEtapa!$A$2:$A$6,MATCH(N47,dEtapa!$B$2:$B$6,0)),"Sin etapa") -> Gobernada | Q47: =IF(L47="Si",1,0) -> 1 | R47: =IF(ISNUMBER(SEARCH("CRITERIO",N47)),1,0) -> 0 | S47: =IF(E47="","Sin dato",LEFT(E47,1)) -> E | T47: =IFERROR(INDEX(dCriticidad!$G$2:$G$7,MATCH(S47,dCriticidad!$A$2:$A$7,0)),0) -> 0 | U47: =IF(OR(LEFT(C47,3)="GI0",LEFT(C47,3)="GA0"),1,0) -> 0 | V47: =IF(G47="","Sin dato (ID GI)",TRIM(G47)) -> Ciberseguridad | W47: =IF(F47="","Sin dato",F47) -> On Premise | X47: =IF(M47="","",YEAR(M47)) -> 2025 | Y47: =IF(M47="","",DATE(YEAR(M47),MONTH(M47),1)) -> 45717 | Z47: =IF(AND(Q47=0,COUNTIF(dDuplicadosGI!$A$2:$A$60,C47)>0),1,0) -> 0 | AA47: =IF(Q47=0,1,0) -> 0
A48: 47 | B48: DESIGNSYSTEM | C48: CHL0044 | D48: Sin descripción | E48: E - No Crítica | F48: Nube | G48: TRIBU_CANALES | H48: JUAN FELIPE DIAZ RESTREPO | I48: JORGE ALBERTO VILLAFUERTE GORDILLO | J48: PRICILA VANESSA QUICHIMBO ARMIJOS | K48: Aplicación complementaria | L48: No | N48: PLANIFICADA 2027 | O48: =IF(COUNTIFS($B$2:B48,B48,$C$2:C48,C48)=1,1,0) -> 1 | P48: =IFERROR(INDEX(dEtapa!$A$2:$A$6,MATCH(N48,dEtapa!$B$2:$B$6,0)),"Sin etapa") -> Planificada 2027 | Q48: =IF(L48="Si",1,0) -> 0 | R48: =IF(ISNUMBER(SEARCH("CRITERIO",N48)),1,0) -> 0 | S48: =IF(E48="","Sin dato",LEFT(E48,1)) -> E | T48: =IFERROR(INDEX(dCriticidad!$G$2:$G$7,MATCH(S48,dCriticidad!$A$2:$A$7,0)),0) -> 0 | U48: =IF(OR(LEFT(C48,3)="GI0",LEFT(C48,3)="GA0"),1,0) -> 0 | V48: =IF(G48="","Sin dato (ID GI)",TRIM(G48)) -> TRIBU_CANALES | W48: =IF(F48="","Sin dato",F48) -> Nube | X48: =IF(M48="","",YEAR(M48)) | Y48: =IF(M48="","",DATE(YEAR(M48),MONTH(M48),1)) | Z48: =IF(AND(Q48=0,COUNTIF(dDuplicadosGI!$A$2:$A$60,C48)>0),1,0) -> 0 | AA48: =IF(Q48=0,1,0) -> 1
A49: 48 | B49: Detect ID | C49: SEC0015 | D49: Aplicación para generación de softoken en lugar de OTP enviada por SMS. | E49: B - Ecosistema Apetito de Riesgo | F49: On Premise | G49: Tribu Ciberseguridad | H49: ISRAEL SEBASTIAN DE LA TORRE TRUJILLO | I49: Vladimir Stalin Lamina Sanchez | J49: ROBERTO CARLOS PINO CEDENO | K49: Aplicación del negocio | L49: Si | M49: 45200 | N49: N/A ENTREGADA | O49: =IF(COUNTIFS($B$2:B49,B49,$C$2:C49,C49)=1,1,0) -> 1 | P49: =IFERROR(INDEX(dEtapa!$A$2:$A$6,MATCH(N49,dEtapa!$B$2:$B$6,0)),"Sin etapa") -> Gobernada | Q49: =IF(L49="Si",1,0) -> 1 | R49: =IF(ISNUMBER(SEARCH("CRITERIO",N49)),1,0) -> 0 | S49: =IF(E49="","Sin dato",LEFT(E49,1)) -> B | T49: =IFERROR(INDEX(dCriticidad!$G$2:$G$7,MATCH(S49,dCriticidad!$A$2:$A$7,0)),0) -> 1 | U49: =IF(OR(LEFT(C49,3)="GI0",LEFT(C49,3)="GA0"),1,0) -> 0 | V49: =IF(G49="","Sin dato (ID GI)",TRIM(G49)) -> Tribu Ciberseguridad | W49: =IF(F49="","Sin dato",F49) -> On Premise | X49: =IF(M49="","",YEAR(M49)) -> 2023 | Y49: =IF(M49="","",DATE(YEAR(M49),MONTH(M49),1)) -> 45200 | Z49: =IF(AND(Q49=0,COUNTIF(dDuplicadosGI!$A$2:$A$60,C49)>0),1,0) -> 0 | AA49: =IF(Q49=0,1,0) -> 0
A50: 49 | B50: Deuna Microcomercios | C50: CHL0041 | D50: Aplicacion para administracion de microcomercios | E50: E - No Crítica | F50: Nube | G50: TRIBU_DE_UNA | H50: LUIS JAVIER MARIDUENA NOVILLO | I50: DIEGO ALBERTO ORDONEZ BARRIOS | J50: LUIS JAVIER MARIDUENA NOVILLO | K50: Consolas de Administración TI | L50: No | N50: PLANIFICADA 2027 | O50: =IF(COUNTIFS($B$2:B50,B50,$C$2:C50,C50)=1,1,0) -> 1 | P50: =IFERROR(INDEX(dEtapa!$A$2:$A$6,MATCH(N50,dEtapa!$B$2:$B$6,0)),"Sin etapa") -> Planificada 2027 | Q50: =IF(L50="Si",1,0) -> 0 | R50: =IF(ISNUMBER(SEARCH("CRITERIO",N50)),1,0) -> 0 | S50: =IF(E50="","Sin dato",LEFT(E50,1)) -> E | T50: =IFERROR(INDEX(dCriticidad!$G$2:$G$7,MATCH(S50,dCriticidad!$A$2:$A$7,0)),0) -> 0 | U50: =IF(OR(LEFT(C50,3)="GI0",LEFT(C50,3)="GA0"),1,0) -> 0 | V50: =IF(G50="","Sin dato (ID GI)",TRIM(G50)) -> TRIBU_DE_UNA | W50: =IF(F50="","Sin dato",F50) -> Nube | X50: =IF(M50="","",YEAR(M50)) | Y50: =IF(M50="","",DATE(YEAR(M50),MONTH(M50),1)) | Z50: =IF(AND(Q50=0,COUNTIF(dDuplicadosGI!$A$2:$A$60,C50)>0),1,0) -> 0 | AA50: =IF(Q50=0,1,0) -> 1
A51: 50 | B51: Ansible | C51: TIE0024 | D51: Ansible Automation platform para automatizar la configuracion de la infrastructura | E51: E - No Crítica | F51: On Premise | G51: Gerencia SRE | H51: GONZALO TRANCILLO | I51: GONZALO TRANCILLO | J51: DIANA CRISTINA AVEIGA LOVATO | K51: Consolas de Administración TI | L51: No | N51: PLANIFICADA 2027 | O51: =IF(COUNTIFS($B$2:B51,B51,$C$2:C51,C51)=1,1,0) -> 1 | P51: =IFERROR(INDEX(dEtapa!$A$2:$A$6,MATCH(N51,dEtapa!$B$2:$B$6,0)),"Sin etapa") -> Planificada 2027 | Q51: =IF(L51="Si",1,0) -> 0 | R51: =IF(ISNUMBER(SEARCH("CRITERIO",N51)),1,0) -> 0 | S51: =IF(E51="","Sin dato",LEFT(E51,1)) -> E | T51: =IFERROR(INDEX(dCriticidad!$G$2:$G$7,MATCH(S51,dCriticidad!$A$2:$A$7,0)),0) -> 0 | U51: =IF(OR(LEFT(C51,3)="GI0",LEFT(C51,3)="GA0"),1,0) -> 0 | V51: =IF(G51="","Sin dato (ID GI)",TRIM(G51)) -> Gerencia SRE | W51: =IF(F51="","Sin dato",F51) -> On Premise | X51: =IF(M51="","",YEAR(M51)) | Y51: =IF(M51="","",DATE(YEAR(M51),MONTH(M51),1)) | Z51: =IF(AND(Q51=0,COUNTIF(dDuplicadosGI!$A$2:$A$60,C51)>0),1,0) -> 0 | AA51: =IF(Q51=0,1,0) -> 1
A52: 51 | B52: AntiDDoS Radware | C52: SEC0052 | D52: Es un servicio que bloquea ataques volumétricos de las 3 redes públicas / 24 que el banco tiene adquirido | E52: B - Ecosistema Apetito de Riesgo | F52: Nube | G52: Ciberseguridad | H52: ROBERT STALIN SOTO CORONEL | I52: MARCO FABRICIO FALCONI NORIEGA | J52: JORGE XAVIER LUCERO GALLEGOS | K52: Consolas de Administración Seguridad | L52: Si | M52: 46140 | N52: N/A ENTREGADA | O52: =IF(COUNTIFS($B$2:B52,B52,$C$2:C52,C52)=1,1,0) -> 1 | P52: =IFERROR(INDEX(dEtapa!$A$2:$A$6,MATCH(N52,dEtapa!$B$2:$B$6,0)),"Sin etapa") -> Gobernada | Q52: =IF(L52="Si",1,0) -> 1 | R52: =IF(ISNUMBER(SEARCH("CRITERIO",N52)),1,0) -> 0 | S52: =IF(E52="","Sin dato",LEFT(E52,1)) -> B | T52: =IFERROR(INDEX(dCriticidad!$G$2:$G$7,MATCH(S52,dCriticidad!$A$2:$A$7,0)),0) -> 1 | U52: =IF(OR(LEFT(C52,3)="GI0",LEFT(C52,3)="GA0"),1,0) -> 0 | V52: =IF(G52="","Sin dato (ID GI)",TRIM(G52)) -> Ciberseguridad | W52: =IF(F52="","Sin dato",F52) -> Nube | X52: =IF(M52="","",YEAR(M52)) -> 2026 | Y52: =IF(M52="","",DATE(YEAR(M52),MONTH(M52),1)) -> 46113 | Z52: =IF(AND(Q52=0,COUNTIF(dDuplicadosGI!$A$2:$A$60,C52)>0),1,0) -> 0 | AA52: =IF(Q52=0,1,0) -> 0
A53: 52 | B53: APEX | C53: SEC0064 | D53: Sistema de gestión de eventos de ciberdefensa | E53: B - Ecosistema Apetito de Riesgo | F53: Nube | G53: Tribu Ciberseguridad | H53: JUAN FELIPE GALLEGO COSSIO | I53: FRANCISCO DAVID CEVALLOS GRANJA | J53: ROBERTO CARLOS PINO CEDENO | K53: Consolas de Administración Seguridad | L53: No | N53: PRIORIZACIÓN CRITERIO 2 | O53: =IF(COUNTIFS($B$2:B53,B53,$C$2:C53,C53)=1,1,0) -> 1 | P53: =IFERROR(INDEX(dEtapa!$A$2:$A$6,MATCH(N53,dEtapa!$B$2:$B$6,0)),"Sin etapa") -> Criterio 2 | Q53: =IF(L53="Si",1,0) -> 0 | R53: =IF(ISNUMBER(SEARCH("CRITERIO",N53)),1,0) -> 1 | S53: =IF(E53="","Sin dato",LEFT(E53,1)) -> B | T53: =IFERROR(INDEX(dCriticidad!$G$2:$G$7,MATCH(S53,dCriticidad!$A$2:$A$7,0)),0) -> 1 | U53: =IF(OR(LEFT(C53,3)="GI0",LEFT(C53,3)="GA0"),1,0) -> 0 | V53: =IF(G53="","Sin dato (ID GI)",TRIM(G53)) -> Tribu Ciberseguridad | W53: =IF(F53="","Sin dato",F53) -> Nube | X53: =IF(M53="","",YEAR(M53)) | Y53: =IF(M53="","",DATE(YEAR(M53),MONTH(M53),1)) | Z53: =IF(AND(Q53=0,COUNTIF(dDuplicadosGI!$A$2:$A$60,C53)>0),1,0) -> 0 | AA53: =IF(Q53=0,1,0) -> 1
A54: 53 | B54: Apigee | C54: INT0004 | D54: No existe dentro del portafolio | E54: B - Ecosistema Apetito de Riesgo | F54: Nube | G54: Tribu_Integraciones_Apis | H54: MARICELA NATALY ACUNA GUANOLUISA | I54: PABLO SANTIAGO DELGADO MONCAYO | J54: ANDREA ESTEFANIA CHAVEZ ORDONEZ | K54: Consolas de Administración TI | L54: Si | M54: 46007 | N54: N/A ENTREGADA | O54: =IF(COUNTIFS($B$2:B54,B54,$C$2:C54,C54)=1,1,0) -> 1 | P54: =IFERROR(INDEX(dEtapa!$A$2:$A$6,MATCH(N54,dEtapa!$B$2:$B$6,0)),"Sin etapa") -> Gobernada | Q54: =IF(L54="Si",1,0) -> 1 | R54: =IF(ISNUMBER(SEARCH("CRITERIO",N54)),1,0) -> 0 | S54: =IF(E54="","Sin dato",LEFT(E54,1)) -> B | T54: =IFERROR(INDEX(dCriticidad!$G$2:$G$7,MATCH(S54,dCriticidad!$A$2:$A$7,0)),0) -> 1 | U54: =IF(OR(LEFT(C54,3)="GI0",LEFT(C54,3)="GA0"),1,0) -> 0 | V54: =IF(G54="","Sin dato (ID GI)",TRIM(G54)) -> Tribu_Integraciones_Apis | W54: =IF(F54="","Sin dato",F54) -> Nube | X54: =IF(M54="","",YEAR(M54)) -> 2025 | Y54: =IF(M54="","",DATE(YEAR(M54),MONTH(M54),1)) -> 45992 | Z54: =IF(AND(Q54=0,COUNTIF(dDuplicadosGI!$A$2:$A$60,C54)>0),1,0) -> 0 | AA54: =IF(Q54=0,1,0) -> 0
A55: 54 | B55: APIM | C55: INT0016 | D55: Servicio de Microsoft Azure API Management. Mantiene la gestión de las APIs, autorización de consumo y analítica de los componentes. | E55: B - Ecosistema Apetito de Riesgo | F55: Nube | G55: Tribu_Integraciones_Apis | H55: DAVID RODRIGO REVELO RIVERA | I55: PABLO SANTIAGO DELGADO MONCAYO | J55: JUAN CARLOS CONTRERAS PAREDES | K55: Consolas de Administración TI | L55: Si | M55: 46028 | N55: N/A ENTREGADA | O55: =IF(COUNTIFS($B$2:B55,B55,$C$2:C55,C55)=1,1,0) -> 1 | P55: =IFERROR(INDEX(dEtapa!$A$2:$A$6,MATCH(N55,dEtapa!$B$2:$B$6,0)),"Sin etapa") -> Gobernada | Q55: =IF(L55="Si",1,0) -> 1 | R55: =IF(ISNUMBER(SEARCH("CRITERIO",N55)),1,0) -> 0 | S55: =IF(E55="","Sin dato",LEFT(E55,1)) -> B | T55: =IFERROR(INDEX(dCriticidad!$G$2:$G$7,MATCH(S55,dCriticidad!$A$2:$A$7,0)),0) -> 1 | U55: =IF(OR(LEFT(C55,3)="GI0",LEFT(C55,3)="GA0"),1,0) -> 0 | V55: =IF(G55="","Sin dato (ID GI)",TRIM(G55)) -> Tribu_Integraciones_Apis | W55: =IF(F55="","Sin dato",F55) -> Nube | X55: =IF(M55="","",YEAR(M55)) -> 2026 | Y55: =IF(M55="","",DATE(YEAR(M55),MONTH(M55),1)) -> 46023 | Z55: =IF(AND(Q55=0,COUNTIF(dDuplicadosGI!$A$2:$A$60,C55)>0),1,0) -> 0 | AA55: =IF(Q55=0,1,0) -> 0
A56: 55 | B56: Atalla | C56: SEC0004 | D56: Herramienta de generación de llaves de cifrado para la encripción del tráfico usado por varios aplicativos | E56: B - Ecosistema Apetito de Riesgo | F56: On Premise | G56: Ciberseguridad | H56: ERICK DAMIAN RISUENO BENITEZ | I56: MARCO FABRICIO FALCONI NORIEGA | J56: ROBERT STALIN SOTO CORONEL | K56: Consolas de Administración Seguridad | L56: No | N56: PRIORIZACIÓN CRITERIO 2 | O56: =IF(COUNTIFS($B$2:B56,B56,$C$2:C56,C56)=1,1,0) -> 1 | P56: =IFERROR(INDEX(dEtapa!$A$2:$A$6,MATCH(N56,dEtapa!$B$2:$B$6,0)),"Sin etapa") -> Criterio 2 | Q56: =IF(L56="Si",1,0) -> 0 | R56: =IF(ISNUMBER(SEARCH("CRITERIO",N56)),1,0) -> 1 | S56: =IF(E56="","Sin dato",LEFT(E56,1)) -> B | T56: =IFERROR(INDEX(dCriticidad!$G$2:$G$7,MATCH(S56,dCriticidad!$A$2:$A$7,0)),0) -> 1 | U56: =IF(OR(LEFT(C56,3)="GI0",LEFT(C56,3)="GA0"),1,0) -> 0 | V56: =IF(G56="","Sin dato (ID GI)",TRIM(G56)) -> Ciberseguridad | W56: =IF(F56="","Sin dato",F56) -> On Premise | X56: =IF(M56="","",YEAR(M56)) | Y56: =IF(M56="","",DATE(YEAR(M56),MONTH(M56),1)) | Z56: =IF(AND(Q56=0,COUNTIF(dDuplicadosGI!$A$2:$A$60,C56)>0),1,0) -> 0 | AA56: =IF(Q56=0,1,0) -> 1
A57: 56 | B57: Athento | C57: TIE0025 | D57: ECM Athento, es una herramienta de gestión de contenido transversal a institución, que cuenta con capacidades de ocr,ia, clasificación entre otras con la finalidad de dar gestión y almacenamiento a documentos | E57: E - No Crítica | F57: Terceros | G57: COE_TRANSFORMACION_PROCESOS | H57: JAVIER ENRIQUE RIOS CASTILLO | I57: FREDI ALEXANDER ELIZALDE RODRIGUEZ | J57: SANTIAGO POSADA ZULUAGA | K57: Aplicación del negocio | L57: Si | M57: 46107 | N57: N/A ENTREGADA | O57: =IF(COUNTIFS($B$2:B57,B57,$C$2:C57,C57)=1,1,0) -> 1 | P57: =IFERROR(INDEX(dEtapa!$A$2:$A$6,MATCH(N57,dEtapa!$B$2:$B$6,0)),"Sin etapa") -> Gobernada | Q57: =IF(L57="Si",1,0) -> 1 | R57: =IF(ISNUMBER(SEARCH("CRITERIO",N57)),1,0) -> 0 | S57: =IF(E57="","Sin dato",LEFT(E57,1)) -> E | T57: =IFERROR(INDEX(dCriticidad!$G$2:$G$7,MATCH(S57,dCriticidad!$A$2:$A$7,0)),0) -> 0 | U57: =IF(OR(LEFT(C57,3)="GI0",LEFT(C57,3)="GA0"),1,0) -> 0 | V57: =IF(G57="","Sin dato (ID GI)",TRIM(G57)) -> COE_TRANSFORMACION_PROCESOS | W57: =IF(F57="","Sin dato",F57) -> Terceros | X57: =IF(M57="","",YEAR(M57)) -> 2026 | Y57: =IF(M57="","",DATE(YEAR(M57),MONTH(M57),1)) -> 46082 | Z57: =IF(AND(Q57=0,COUNTIF(dDuplicadosGI!$A$2:$A$60,C57)>0),1,0) -> 0 | AA57: =IF(Q57=0,1,0) -> 0
A58: 57 | B58: AURO SUITE | C58: COR0003 | D58: Sistema que permite gestionar los depósitos a plazo generados en Banco Pichincha por los segmentos de bancas privada, empresarial y preferencial | E58: C - BIA Crítica | F58: On Premise | G58: Tribu_Cores_Transacciones | H58: DAVID RODRIGO REVELO RIVERA | I58: EDITH SUSANA ACUNA GARCIA | J58: DAVID RODRIGO REVELO RIVERA | K58: Aplicación del negocio | L58: Si | M58: 45200 | N58: N/A ENTREGADA | O58: =IF(COUNTIFS($B$2:B58,B58,$C$2:C58,C58)=1,1,0) -> 1 | P58: =IFERROR(INDEX(dEtapa!$A$2:$A$6,MATCH(N58,dEtapa!$B$2:$B$6,0)),"Sin etapa") -> Gobernada | Q58: =IF(L58="Si",1,0) -> 1 | R58: =IF(ISNUMBER(SEARCH("CRITERIO",N58)),1,0) -> 0 | S58: =IF(E58="","Sin dato",LEFT(E58,1)) -> C | T58: =IFERROR(INDEX(dCriticidad!$G$2:$G$7,MATCH(S58,dCriticidad!$A$2:$A$7,0)),0) -> 1 | U58: =IF(OR(LEFT(C58,3)="GI0",LEFT(C58,3)="GA0"),1,0) -> 0 | V58: =IF(G58="","Sin dato (ID GI)",TRIM(G58)) -> Tribu_Cores_Transacciones | W58: =IF(F58="","Sin dato",F58) -> On Premise | X58: =IF(M58="","",YEAR(M58)) -> 2023 | Y58: =IF(M58="","",DATE(YEAR(M58),MONTH(M58),1)) -> 45200 | Z58: =IF(AND(Q58=0,COUNTIF(dDuplicadosGI!$A$2:$A$60,C58)>0),1,0) -> 0 | AA58: =IF(Q58=0,1,0) -> 0
A59: 58 | B59: Auth0 | C59: SEC0051 | D59: Auth0, es la nueva aplicación de autenticación para los clientes de canales digitales | E59: B - Ecosistema Apetito de Riesgo | F59: Nube | G59: Tribu Ciberseguridad | H59: JUAN FELIPE GALLEGO COSSIO | I59: Vladimir Stalin Lamina Sanchez | J59: ROBERTO CARLOS PINO CEDENO | K59: Consolas de Administración Seguridad | L59: No | N59: PLANIFICADA 2027 | O59: =IF(COUNTIFS($B$2:B59,B59,$C$2:C59,C59)=1,1,0) -> 1 | P59: =IFERROR(INDEX(dEtapa!$A$2:$A$6,MATCH(N59,dEtapa!$B$2:$B$6,0)),"Sin etapa") -> Planificada 2027 | Q59: =IF(L59="Si",1,0) -> 0 | R59: =IF(ISNUMBER(SEARCH("CRITERIO",N59)),1,0) -> 0 | S59: =IF(E59="","Sin dato",LEFT(E59,1)) -> B | T59: =IFERROR(INDEX(dCriticidad!$G$2:$G$7,MATCH(S59,dCriticidad!$A$2:$A$7,0)),0) -> 1 | U59: =IF(OR(LEFT(C59,3)="GI0",LEFT(C59,3)="GA0"),1,0) -> 0 | V59: =IF(G59="","Sin dato (ID GI)",TRIM(G59)) -> Tribu Ciberseguridad | W59: =IF(F59="","Sin dato",F59) -> Nube | X59: =IF(M59="","",YEAR(M59)) | Y59: =IF(M59="","",DATE(YEAR(M59),MONTH(M59),1)) | Z59: =IF(AND(Q59=0,COUNTIF(dDuplicadosGI!$A$2:$A$60,C59)>0),1,0) -> 0 | AA59: =IF(Q59=0,1,0) -> 1
A60: 59 | B60: AutorizadorPichincha | C60: SEC0005 | D60: Aplicación para generar una OTP para que el asesor ejecute la transacción financiera solicitada. | E60: E - No Crítica | F60: On Premise | G60: Tribu Ciberseguridad | H60: JUAN FELIPE GALLEGO COSSIO | I60: FRANCISCO DAVID CEVALLOS GRANJA | J60: ROBERTO CARLOS PINO CEDENO | K60: Aplicación complementaria | L60: No | N60: PRIORIZACIÓN CRITERIO 3 | O60: =IF(COUNTIFS($B$2:B60,B60,$C$2:C60,C60)=1,1,0) -> 1 | P60: =IFERROR(INDEX(dEtapa!$A$2:$A$6,MATCH(N60,dEtapa!$B$2:$B$6,0)),"Sin etapa") -> Criterio 3 | Q60: =IF(L60="Si",1,0) -> 0 | R60: =IF(ISNUMBER(SEARCH("CRITERIO",N60)),1,0) -> 1 | S60: =IF(E60="","Sin dato",LEFT(E60,1)) -> E | T60: =IFERROR(INDEX(dCriticidad!$G$2:$G$7,MATCH(S60,dCriticidad!$A$2:$A$7,0)),0) -> 0 | U60: =IF(OR(LEFT(C60,3)="GI0",LEFT(C60,3)="GA0"),1,0) -> 0 | V60: =IF(G60="","Sin dato (ID GI)",TRIM(G60)) -> Tribu Ciberseguridad | W60: =IF(F60="","Sin dato",F60) -> On Premise | X60: =IF(M60="","",YEAR(M60)) | Y60: =IF(M60="","",DATE(YEAR(M60),MONTH(M60),1)) | Z60: =IF(AND(Q60=0,COUNTIF(dDuplicadosGI!$A$2:$A$60,C60)>0),1,0) -> 0 | AA60: =IF(Q60=0,1,0) -> 1
A61: 60 | B61: Azure AD | C61: SEC0048 | D61: Sincronización Usuarios Office 365 | E61: B - Ecosistema Apetito de Riesgo | F61: Nube | G61: INFRAESTRUCTURA | H61: BYRON ORLANDO MELENDREZ CABRERA | I61: MARIO ALBERTO TOSCANO GUANIN | J61: RICHARD FABRICIO BRIONES LAICA | K61: Consolas de Administración Seguridad | L61: No | N61: PRIORIZACIÓN CRITERIO 1 | O61: =IF(COUNTIFS($B$2:B61,B61,$C$2:C61,C61)=1,1,0) -> 1 | P61: =IFERROR(INDEX(dEtapa!$A$2:$A$6,MATCH(N61,dEtapa!$B$2:$B$6,0)),"Sin etapa") -> Criterio 1 | Q61: =IF(L61="Si",1,0) -> 0 | R61: =IF(ISNUMBER(SEARCH("CRITERIO",N61)),1,0) -> 1 | S61: =IF(E61="","Sin dato",LEFT(E61,1)) -> B | T61: =IFERROR(INDEX(dCriticidad!$G$2:$G$7,MATCH(S61,dCriticidad!$A$2:$A$7,0)),0) -> 1 | U61: =IF(OR(LEFT(C61,3)="GI0",LEFT(C61,3)="GA0"),1,0) -> 0 | V61: =IF(G61="","Sin dato (ID GI)",TRIM(G61)) -> INFRAESTRUCTURA | W61: =IF(F61="","Sin dato",F61) -> Nube | X61: =IF(M61="","",YEAR(M61)) | Y61: =IF(M61="","",DATE(YEAR(M61),MONTH(M61),1)) | Z61: =IF(AND(Q61=0,COUNTIF(dDuplicadosGI!$A$2:$A$60,C61)>0),1,0) -> 0 | AA61: =IF(Q61=0,1,0) -> 1
A62: 61 | B62: Cheque Image Server (CIS Totem) | C62: CHL0010 | D62: Componente que permite el envío de imágenes de cheques desde cada ATM de Depositario hacia la solución de Canje Digital (CheqScan). | E62: B - Ecosistema Apetito de Riesgo | F62: On Premise | G62: TRIBU_CANALES | H62: MIGUEL ALEXANDER MEJIA BRONCANO | I62: MILTON PATRICIO MANTILLA CAYO | J62: JUAN FRANCISCO PROCEL MICHILENA | K62: Aplicación complementaria | L62: No | N62: PRIORIZACIÓN CRITERIO 2 | O62: =IF(COUNTIFS($B$2:B62,B62,$C$2:C62,C62)=1,1,0) -> 1 | P62: =IFERROR(INDEX(dEtapa!$A$2:$A$6,MATCH(N62,dEtapa!$B$2:$B$6,0)),"Sin etapa") -> Criterio 2 | Q62: =IF(L62="Si",1,0) -> 0 | R62: =IF(ISNUMBER(SEARCH("CRITERIO",N62)),1,0) -> 1 | S62: =IF(E62="","Sin dato",LEFT(E62,1)) -> B | T62: =IFERROR(INDEX(dCriticidad!$G$2:$G$7,MATCH(S62,dCriticidad!$A$2:$A$7,0)),0) -> 1 | U62: =IF(OR(LEFT(C62,3)="GI0",LEFT(C62,3)="GA0"),1,0) -> 0 | V62: =IF(G62="","Sin dato (ID GI)",TRIM(G62)) -> TRIBU_CANALES | W62: =IF(F62="","Sin dato",F62) -> On Premise | X62: =IF(M62="","",YEAR(M62)) | Y62: =IF(M62="","",DATE(YEAR(M62),MONTH(M62),1)) | Z62: =IF(AND(Q62=0,COUNTIF(dDuplicadosGI!$A$2:$A$60,C62)>0),1,0) -> 0 | AA62: =IF(Q62=0,1,0) -> 1
A63: 62 | B63: Cisco Collector | C63: ITM0004 | D63: Herramienta de monitoreo, El Cisco Collector es una herramienta que permite levar el inventario de los equipos Cisco vía SNMP, esta información posteriormente se sincroniza al portal de Cisco NCST donde se puede ver la información de los contratos de soporte por cada equipo, fechas de fin de soporte ETC | E63: E - No Crítica | F63: On Premise | G63: INFRAESTRUCTURA | H63: BYRON ORLANDO MELENDREZ CABRERA | I63: MAURICIO FERNANDO NAVAS GALLARDO | J63: HECTOR DAVID CANTOS CEDENO | K63: Consolas de Administración TI | L63: No | N63: PLANIFICADA 2027 | O63: =IF(COUNTIFS($B$2:B63,B63,$C$2:C63,C63)=1,1,0) -> 1 | P63: =IFERROR(INDEX(dEtapa!$A$2:$A$6,MATCH(N63,dEtapa!$B$2:$B$6,0)),"Sin etapa") -> Planificada 2027 | Q63: =IF(L63="Si",1,0) -> 0 | R63: =IF(ISNUMBER(SEARCH("CRITERIO",N63)),1,0) -> 0 | S63: =IF(E63="","Sin dato",LEFT(E63,1)) -> E | T63: =IFERROR(INDEX(dCriticidad!$G$2:$G$7,MATCH(S63,dCriticidad!$A$2:$A$7,0)),0) -> 0 | U63: =IF(OR(LEFT(C63,3)="GI0",LEFT(C63,3)="GA0"),1,0) -> 0 | V63: =IF(G63="","Sin dato (ID GI)",TRIM(G63)) -> INFRAESTRUCTURA | W63: =IF(F63="","Sin dato",F63) -> On Premise | X63: =IF(M63="","",YEAR(M63)) | Y63: =IF(M63="","",DATE(YEAR(M63),MONTH(M63),1)) | Z63: =IF(AND(Q63=0,COUNTIF(dDuplicadosGI!$A$2:$A$60,C63)>0),1,0) -> 0 | AA63: =IF(Q63=0,1,0) -> 1
A64: 63 | B64: COBIS BANCA COMUNAL | C64: PRD0052 | D64: Gestión de préstamos colectivos. | E64: C - BIA Crítica | F64: On Premise | G64: MICROFINANZAS | H64: LAURA ELIZABETH CARRASCO UQUILLAS | I64: MYRIAM ADRIANA YANGUICELA TIPAN | J64: Willam Marcel Ontaneda Yaguana | K64: Aplicación del negocio | L64: Si | M64: 45200 | N64: N/A ENTREGADA | O64: =IF(COUNTIFS($B$2:B64,B64,$C$2:C64,C64)=1,1,0) -> 1 | P64: =IFERROR(INDEX(dEtapa!$A$2:$A$6,MATCH(N64,dEtapa!$B$2:$B$6,0)),"Sin etapa") -> Gobernada | Q64: =IF(L64="Si",1,0) -> 1 | R64: =IF(ISNUMBER(SEARCH("CRITERIO",N64)),1,0) -> 0 | S64: =IF(E64="","Sin dato",LEFT(E64,1)) -> C | T64: =IFERROR(INDEX(dCriticidad!$G$2:$G$7,MATCH(S64,dCriticidad!$A$2:$A$7,0)),0) -> 1 | U64: =IF(OR(LEFT(C64,3)="GI0",LEFT(C64,3)="GA0"),1,0) -> 0 | V64: =IF(G64="","Sin dato (ID GI)",TRIM(G64)) -> MICROFINANZAS | W64: =IF(F64="","Sin dato",F64) -> On Premise | X64: =IF(M64="","",YEAR(M64)) -> 2023 | Y64: =IF(M64="","",DATE(YEAR(M64),MONTH(M64),1)) -> 45200 | Z64: =IF(AND(Q64=0,COUNTIF(dDuplicadosGI!$A$2:$A$60,C64)>0),1,0) -> 0 | AA64: =IF(Q64=0,1,0) -> 0
A65: 64 | B65: Compass | C65: SEC0076 | D65: Sistema de alarmas | E65: C - BIA Crítica | F65: On Premise | G65: Ciberseguridad | H65: ANDY JOSE ANDRADE BRAVO | I65: MARCO FABRICIO FALCONI NORIEGA | J65: LUIS ENRIQUE ALVAREZ GARCIA | K65: Consolas de Administración Seguridad | L65: Si | M65: 46104 | N65: N/A ENTREGADA | O65: =IF(COUNTIFS($B$2:B65,B65,$C$2:C65,C65)=1,1,0) -> 1 | P65: =IFERROR(INDEX(dEtapa!$A$2:$A$6,MATCH(N65,dEtapa!$B$2:$B$6,0)),"Sin etapa") -> Gobernada | Q65: =IF(L65="Si",1,0) -> 1 | R65: =IF(ISNUMBER(SEARCH("CRITERIO",N65)),1,0) -> 0 | S65: =IF(E65="","Sin dato",LEFT(E65,1)) -> C | T65: =IFERROR(INDEX(dCriticidad!$G$2:$G$7,MATCH(S65,dCriticidad!$A$2:$A$7,0)),0) -> 1 | U65: =IF(OR(LEFT(C65,3)="GI0",LEFT(C65,3)="GA0"),1,0) -> 0 | V65: =IF(G65="","Sin dato (ID GI)",TRIM(G65)) -> Ciberseguridad | W65: =IF(F65="","Sin dato",F65) -> On Premise | X65: =IF(M65="","",YEAR(M65)) -> 2026 | Y65: =IF(M65="","",DATE(YEAR(M65),MONTH(M65),1)) -> 46082 | Z65: =IF(AND(Q65=0,COUNTIF(dDuplicadosGI!$A$2:$A$60,C65)>0),1,0) -> 0 | AA65: =IF(Q65=0,1,0) -> 0
A66: 65 | B66: Compensacion | C66: SUP0025 | D66: Aplicativo encargado de la generación de los archivos para la compensación de empresas de recaudación en CNB's. Frontea la gestión integral y parametrización relacionada con el servicio de compensación general de Banco Pichincha. | E66: D - BIA No Crítica | F66: On Premise | G66: EMPRESAS | H66: MIRTHA CATHERINE ARCELA ESPINOZA | I66: GONZALO MARCELO NAZATI GONZALEZ | J66: FRANKLIN HAYBECK SERRANO GOMEZ | K66: Aplicación complementaria | L66: Si | M66: 45199 | N66: N/A ENTREGADA | O66: =IF(COUNTIFS($B$2:B66,B66,$C$2:C66,C66)=1,1,0) -> 1 | P66: =IFERROR(INDEX(dEtapa!$A$2:$A$6,MATCH(N66,dEtapa!$B$2:$B$6,0)),"Sin etapa") -> Gobernada | Q66: =IF(L66="Si",1,0) -> 1 | R66: =IF(ISNUMBER(SEARCH("CRITERIO",N66)),1,0) -> 0 | S66: =IF(E66="","Sin dato",LEFT(E66,1)) -> D | T66: =IFERROR(INDEX(dCriticidad!$G$2:$G$7,MATCH(S66,dCriticidad!$A$2:$A$7,0)),0) -> 0 | U66: =IF(OR(LEFT(C66,3)="GI0",LEFT(C66,3)="GA0"),1,0) -> 0 | V66: =IF(G66="","Sin dato (ID GI)",TRIM(G66)) -> EMPRESAS | W66: =IF(F66="","Sin dato",F66) -> On Premise | X66: =IF(M66="","",YEAR(M66)) -> 2023 | Y66: =IF(M66="","",DATE(YEAR(M66),MONTH(M66),1)) -> 45170 | Z66: =IF(AND(Q66=0,COUNTIF(dDuplicadosGI!$A$2:$A$60,C66)>0),1,0) -> 0 | AA66: =IF(Q66=0,1,0) -> 0
A67: 66 | B67: Compra de Cartera | C67: PRD0013 | D67: Aplicación que permite realizar la pre-validación de las tramas de información de clientes, operaciones y pagos remitidas por las diversas instituciones que le venden cartera a BP, mismas que una vez se encuentren correctas pasaran a ser procesadas en ambiente de producción; y proporcionar los diferentes reportes definidos y necesarios para el seguimiento y gestión de la Cartera, dentro de BP como desde las Casas Comerciales e Instituciones Financieras y no Financieras. | E67: E - No Crítica | F67: On Premise | G67: ACTIVOS | H67: LAURA ELIZABETH CARRASCO UQUILLAS | I67: FABRICIO ANTONIO PEREIRA GARCIA | J67: Carlos Ernesto Bolanos Abad | K67: Aplicación complementaria | L67: Si | M67: 46282 | N67: N/A ENTREGADA | O67: =IF(COUNTIFS($B$2:B67,B67,$C$2:C67,C67)=1,1,0) -> 1 | P67: =IFERROR(INDEX(dEtapa!$A$2:$A$6,MATCH(N67,dEtapa!$B$2:$B$6,0)),"Sin etapa") -> Gobernada | Q67: =IF(L67="Si",1,0) -> 1 | R67: =IF(ISNUMBER(SEARCH("CRITERIO",N67)),1,0) -> 0 | S67: =IF(E67="","Sin dato",LEFT(E67,1)) -> E | T67: =IFERROR(INDEX(dCriticidad!$G$2:$G$7,MATCH(S67,dCriticidad!$A$2:$A$7,0)),0) -> 0 | U67: =IF(OR(LEFT(C67,3)="GI0",LEFT(C67,3)="GA0"),1,0) -> 0 | V67: =IF(G67="","Sin dato (ID GI)",TRIM(G67)) -> ACTIVOS | W67: =IF(F67="","Sin dato",F67) -> On Premise | X67: =IF(M67="","",YEAR(M67)) -> 2026 | Y67: =IF(M67="","",DATE(YEAR(M67),MONTH(M67),1)) -> 46266 | Z67: =IF(AND(Q67=0,COUNTIF(dDuplicadosGI!$A$2:$A$60,C67)>0),1,0) -> 0 | AA67: =IF(Q67=0,1,0) -> 0
A68: 67 | B68: Conexión Empresas Online | C68: PAY0005 | D68: Front del Sitio Web que permite administrar tarjetas prepago. | E68: D - BIA No Crítica | F68: Terceros | G68: MEDIOS_DE_PAGO | H68: EDWIN GEOVANNY FLORES CASTRO | I68: DAVID ALEJANDRO CHAVEZ PENAHERRERA | J68: HENRRY DANIEL MORETA IZA | K68: Aplicación del negocio | L68: No | N68: PLANIFICADA 2027 | O68: =IF(COUNTIFS($B$2:B68,B68,$C$2:C68,C68)=1,1,0) -> 1 | P68: =IFERROR(INDEX(dEtapa!$A$2:$A$6,MATCH(N68,dEtapa!$B$2:$B$6,0)),"Sin etapa") -> Planificada 2027 | Q68: =IF(L68="Si",1,0) -> 0 | R68: =IF(ISNUMBER(SEARCH("CRITERIO",N68)),1,0) -> 0 | S68: =IF(E68="","Sin dato",LEFT(E68,1)) -> D | T68: =IFERROR(INDEX(dCriticidad!$G$2:$G$7,MATCH(S68,dCriticidad!$A$2:$A$7,0)),0) -> 0 | U68: =IF(OR(LEFT(C68,3)="GI0",LEFT(C68,3)="GA0"),1,0) -> 0 | V68: =IF(G68="","Sin dato (ID GI)",TRIM(G68)) -> MEDIOS_DE_PAGO | W68: =IF(F68="","Sin dato",F68) -> Terceros | X68: =IF(M68="","",YEAR(M68)) | Y68: =IF(M68="","",DATE(YEAR(M68),MONTH(M68),1)) | Z68: =IF(AND(Q68=0,COUNTIF(dDuplicadosGI!$A$2:$A$60,C68)>0),1,0) -> 0 | AA68: =IF(Q68=0,1,0) -> 1
A69: 68 | B69: Conexión Personas Online | C69: PAY0006 | D69: Front del Sitio Web que permite administrar tarjetas prepago. | E69: D - BIA No Crítica | F69: Terceros | G69: MEDIOS_DE_PAGO | H69: EDWIN GEOVANNY FLORES CASTRO | I69: DAVID ALEJANDRO CHAVEZ PENAHERRERA | J69: HENRRY DANIEL MORETA IZA | K69: Aplicación del negocio | L69: No | N69: PLANIFICADA 2027 | O69: =IF(COUNTIFS($B$2:B69,B69,$C$2:C69,C69)=1,1,0) -> 1 | P69: =IFERROR(INDEX(dEtapa!$A$2:$A$6,MATCH(N69,dEtapa!$B$2:$B$6,0)),"Sin etapa") -> Planificada 2027 | Q69: =IF(L69="Si",1,0) -> 0 | R69: =IF(ISNUMBER(SEARCH("CRITERIO",N69)),1,0) -> 0 | S69: =IF(E69="","Sin dato",LEFT(E69,1)) -> D | T69: =IFERROR(INDEX(dCriticidad!$G$2:$G$7,MATCH(S69,dCriticidad!$A$2:$A$7,0)),0) -> 0 | U69: =IF(OR(LEFT(C69,3)="GI0",LEFT(C69,3)="GA0"),1,0) -> 0 | V69: =IF(G69="","Sin dato (ID GI)",TRIM(G69)) -> MEDIOS_DE_PAGO | W69: =IF(F69="","Sin dato",F69) -> Terceros | X69: =IF(M69="","",YEAR(M69)) | Y69: =IF(M69="","",DATE(YEAR(M69),MONTH(M69),1)) | Z69: =IF(AND(Q69=0,COUNTIF(dDuplicadosGI!$A$2:$A$60,C69)>0),1,0) -> 0 | AA69: =IF(Q69=0,1,0) -> 1
A70: 69 | B70: Configuración Centralizada | C70: SEC0008 | D70: Aplicativo que permite la administración de las configuraciones de comunicación de las distintas aplicaciones: servidores, usuarios, cadenas de conexión, bases de datos, servicios. | E70: B - Ecosistema Apetito de Riesgo | F70: On Premise | G70: Tribu Ciberseguridad | H70: RODNEY XAVIER JACOME TERAN | I70: FRANCISCO DAVID CEVALLOS GRANJA | J70: ROBERTO CARLOS PINO CEDENO | K70: Consolas de Administración Seguridad | L70: Si | M70: 45200 | N70: N/A ENTREGADA | O70: =IF(COUNTIFS($B$2:B70,B70,$C$2:C70,C70)=1,1,0) -> 1 | P70: =IFERROR(INDEX(dEtapa!$A$2:$A$6,MATCH(N70,dEtapa!$B$2:$B$6,0)),"Sin etapa") -> Gobernada | Q70: =IF(L70="Si",1,0) -> 1 | R70: =IF(ISNUMBER(SEARCH("CRITERIO",N70)),1,0) -> 0 | S70: =IF(E70="","Sin dato",LEFT(E70,1)) -> B | T70: =IFERROR(INDEX(dCriticidad!$G$2:$G$7,MATCH(S70,dCriticidad!$A$2:$A$7,0)),0) -> 1 | U70: =IF(OR(LEFT(C70,3)="GI0",LEFT(C70,3)="GA0"),1,0) -> 0 | V70: =IF(G70="","Sin dato (ID GI)",TRIM(G70)) -> Tribu Ciberseguridad | W70: =IF(F70="","Sin dato",F70) -> On Premise | X70: =IF(M70="","",YEAR(M70)) -> 2023 | Y70: =IF(M70="","",DATE(YEAR(M70),MONTH(M70),1)) -> 45200 | Z70: =IF(AND(Q70=0,COUNTIF(dDuplicadosGI!$A$2:$A$60,C70)>0),1,0) -> 0 | AA70: =IF(Q70=0,1,0) -> 0
A71: 70 | B71: Confluent | C71: OMN0002 | D71: No existe descripción | E71: E - No Crítica | F71: Nube | G71: Tribu_Integraciones_Apis | H71: DIEGO VLADIMIR JAYA GUAMANZARA | I71: JOHANNA ELIZABETH CARANGUI VIVAR | J71: DIEGO VLADIMIR JAYA GUAMANZARA | K71: Aplicación complementaria | L71: No | N71: PRIORIZACIÓN CRITERIO 1 | O71: =IF(COUNTIFS($B$2:B71,B71,$C$2:C71,C71)=1,1,0) -> 1 | P71: =IFERROR(INDEX(dEtapa!$A$2:$A$6,MATCH(N71,dEtapa!$B$2:$B$6,0)),"Sin etapa") -> Criterio 1 | Q71: =IF(L71="Si",1,0) -> 0 | R71: =IF(ISNUMBER(SEARCH("CRITERIO",N71)),1,0) -> 1 | S71: =IF(E71="","Sin dato",LEFT(E71,1)) -> E | T71: =IFERROR(INDEX(dCriticidad!$G$2:$G$7,MATCH(S71,dCriticidad!$A$2:$A$7,0)),0) -> 0 | U71: =IF(OR(LEFT(C71,3)="GI0",LEFT(C71,3)="GA0"),1,0) -> 0 | V71: =IF(G71="","Sin dato (ID GI)",TRIM(G71)) -> Tribu_Integraciones_Apis | W71: =IF(F71="","Sin dato",F71) -> Nube | X71: =IF(M71="","",YEAR(M71)) | Y71: =IF(M71="","",DATE(YEAR(M71),MONTH(M71),1)) | Z71: =IF(AND(Q71=0,COUNTIF(dDuplicadosGI!$A$2:$A$60,C71)>0),1,0) -> 0 | AA71: =IF(Q71=0,1,0) -> 1
A72: 71 | B72: Control-M | C72: ITM0008 | D72: Herramienta Schedule (Calendarización y ejecución de Procesos Batch) | E72: C - BIA Crítica | F72: Híbrida | G72: Gerencia Servicios Producción Tecnológica | H72: MARIO SIXTO ZEGARRA OREZZOLI | I72: XAVIER ALEJANDRO JARAMILLO CEVALLOS | J72: HEVER GONZALEZ GARCIA | K72: Consolas de Administración TI | L72: No | N72: PRIORIZACIÓN CRITERIO 2 | O72: =IF(COUNTIFS($B$2:B72,B72,$C$2:C72,C72)=1,1,0) -> 1 | P72: =IFERROR(INDEX(dEtapa!$A$2:$A$6,MATCH(N72,dEtapa!$B$2:$B$6,0)),"Sin etapa") -> Criterio 2 | Q72: =IF(L72="Si",1,0) -> 0 | R72: =IF(ISNUMBER(SEARCH("CRITERIO",N72)),1,0) -> 1 | S72: =IF(E72="","Sin dato",LEFT(E72,1)) -> C | T72: =IFERROR(INDEX(dCriticidad!$G$2:$G$7,MATCH(S72,dCriticidad!$A$2:$A$7,0)),0) -> 1 | U72: =IF(OR(LEFT(C72,3)="GI0",LEFT(C72,3)="GA0"),1,0) -> 0 | V72: =IF(G72="","Sin dato (ID GI)",TRIM(G72)) -> Gerencia Servicios Producción Tecnológica | W72: =IF(F72="","Sin dato",F72) -> Híbrida | X72: =IF(M72="","",YEAR(M72)) | Y72: =IF(M72="","",DATE(YEAR(M72),MONTH(M72),1)) | Z72: =IF(AND(Q72=0,COUNTIF(dDuplicadosGI!$A$2:$A$60,C72)>0),1,0) -> 0 | AA72: =IF(Q72=0,1,0) -> 1
A73: 72 | B73: Copy Services Manager | C73: ITM0009 | D73: Software Administración de Replicas del Storage | E73: C - BIA Crítica | F73: On Premise | G73: INFRAESTRUCTURA | H73: BYRON ORLANDO MELENDREZ CABRERA | I73: NELSON ANDRES POZO YEPEZ | J73: PABLO RAUL CAICEDO ARELLANO | K73: Consolas de Administración TI | L73: No | N73: PLANIFICADA 2027 | O73: =IF(COUNTIFS($B$2:B73,B73,$C$2:C73,C73)=1,1,0) -> 1 | P73: =IFERROR(INDEX(dEtapa!$A$2:$A$6,MATCH(N73,dEtapa!$B$2:$B$6,0)),"Sin etapa") -> Planificada 2027 | Q73: =IF(L73="Si",1,0) -> 0 | R73: =IF(ISNUMBER(SEARCH("CRITERIO",N73)),1,0) -> 0 | S73: =IF(E73="","Sin dato",LEFT(E73,1)) -> C | T73: =IFERROR(INDEX(dCriticidad!$G$2:$G$7,MATCH(S73,dCriticidad!$A$2:$A$7,0)),0) -> 1 | U73: =IF(OR(LEFT(C73,3)="GI0",LEFT(C73,3)="GA0"),1,0) -> 0 | V73: =IF(G73="","Sin dato (ID GI)",TRIM(G73)) -> INFRAESTRUCTURA | W73: =IF(F73="","Sin dato",F73) -> On Premise | X73: =IF(M73="","",YEAR(M73)) | Y73: =IF(M73="","",DATE(YEAR(M73),MONTH(M73),1)) | Z73: =IF(AND(Q73=0,COUNTIF(dDuplicadosGI!$A$2:$A$60,C73)>0),1,0) -> 0 | AA73: =IF(Q73=0,1,0) -> 1
A74: 73 | B74: Coren WEB | C74: SEC0071 | D74: Cerraduras electrónicas | E74: C - BIA Crítica | F74: On Premise | G74: Ciberseguridad | H74: CARLOS ANDRES MORALES MALDONADO | I74: MARCO FABRICIO FALCONI NORIEGA | J74: ANDY JOSE ANDRADE BRAVO | K74: Consolas de Administración Seguridad | L74: Si | M74: 45911 | N74: N/A ENTREGADA | O74: =IF(COUNTIFS($B$2:B74,B74,$C$2:C74,C74)=1,1,0) -> 1 | P74: =IFERROR(INDEX(dEtapa!$A$2:$A$6,MATCH(N74,dEtapa!$B$2:$B$6,0)),"Sin etapa") -> Gobernada | Q74: =IF(L74="Si",1,0) -> 1 | R74: =IF(ISNUMBER(SEARCH("CRITERIO",N74)),1,0) -> 0 | S74: =IF(E74="","Sin dato",LEFT(E74,1)) -> C | T74: =IFERROR(INDEX(dCriticidad!$G$2:$G$7,MATCH(S74,dCriticidad!$A$2:$A$7,0)),0) -> 1 | U74: =IF(OR(LEFT(C74,3)="GI0",LEFT(C74,3)="GA0"),1,0) -> 0 | V74: =IF(G74="","Sin dato (ID GI)",TRIM(G74)) -> Ciberseguridad | W74: =IF(F74="","Sin dato",F74) -> On Premise | X74: =IF(M74="","",YEAR(M74)) -> 2025 | Y74: =IF(M74="","",DATE(YEAR(M74),MONTH(M74),1)) -> 45901 | Z74: =IF(AND(Q74=0,COUNTIF(dDuplicadosGI!$A$2:$A$60,C74)>0),1,0) -> 0 | AA74: =IF(Q74=0,1,0) -> 0
A75: 74 | B75: CreditLens | C75: RIS0004 | D75: Motor de cálculo de banca para proyecciones, balances, representa el 1/3 de las funciones del Banco. para pymes y empresas | E75: E - No Crítica | F75: Nube | G75: Tribu Administración de Créditos | H75: JORGE MARIO PULGARIN MAZO | I75: JOHANNA NATALIA RODRIGUEZ SANCHEZ | J75: EDISON JAVIER RODRIGUEZ SIMBANA | K75: Aplicación del negocio | L75: Si | M75: 45200 | N75: N/A ENTREGADA | O75: =IF(COUNTIFS($B$2:B75,B75,$C$2:C75,C75)=1,1,0) -> 1 | P75: =IFERROR(INDEX(dEtapa!$A$2:$A$6,MATCH(N75,dEtapa!$B$2:$B$6,0)),"Sin etapa") -> Gobernada | Q75: =IF(L75="Si",1,0) -> 1 | R75: =IF(ISNUMBER(SEARCH("CRITERIO",N75)),1,0) -> 0 | S75: =IF(E75="","Sin dato",LEFT(E75,1)) -> E | T75: =IFERROR(INDEX(dCriticidad!$G$2:$G$7,MATCH(S75,dCriticidad!$A$2:$A$7,0)),0) -> 0 | U75: =IF(OR(LEFT(C75,3)="GI0",LEFT(C75,3)="GA0"),1,0) -> 0 | V75: =IF(G75="","Sin dato (ID GI)",TRIM(G75)) -> Tribu Administración de Créditos | W75: =IF(F75="","Sin dato",F75) -> Nube | X75: =IF(M75="","",YEAR(M75)) -> 2023 | Y75: =IF(M75="","",DATE(YEAR(M75),MONTH(M75),1)) -> 45200 | Z75: =IF(AND(Q75=0,COUNTIF(dDuplicadosGI!$A$2:$A$60,C75)>0),1,0) -> 0 | AA75: =IF(Q75=0,1,0) -> 0
A76: 75 | B76: CREDITO EN LINEA | C76: PRD0046 | D76: Aplicación para la generación, simulación y desembolso de créditos preciso preaprobados. | E76: D - BIA No Crítica | F76: Nube | G76: ACTIVOS | H76: LAURA ELIZABETH CARRASCO UQUILLAS | I76: TATIANA ISABEL ZAMORA VILLAVICENCIO | J76: ERISLAN MARTINEZ JERA | K76: Aplicación del negocio | L76: No | N76: PLANIFICADA 2027 | O76: =IF(COUNTIFS($B$2:B76,B76,$C$2:C76,C76)=1,1,0) -> 1 | P76: =IFERROR(INDEX(dEtapa!$A$2:$A$6,MATCH(N76,dEtapa!$B$2:$B$6,0)),"Sin etapa") -> Planificada 2027 | Q76: =IF(L76="Si",1,0) -> 0 | R76: =IF(ISNUMBER(SEARCH("CRITERIO",N76)),1,0) -> 0 | S76: =IF(E76="","Sin dato",LEFT(E76,1)) -> D | T76: =IFERROR(INDEX(dCriticidad!$G$2:$G$7,MATCH(S76,dCriticidad!$A$2:$A$7,0)),0) -> 0 | U76: =IF(OR(LEFT(C76,3)="GI0",LEFT(C76,3)="GA0"),1,0) -> 0 | V76: =IF(G76="","Sin dato (ID GI)",TRIM(G76)) -> ACTIVOS | W76: =IF(F76="","Sin dato",F76) -> Nube | X76: =IF(M76="","",YEAR(M76)) | Y76: =IF(M76="","",DATE(YEAR(M76),MONTH(M76),1)) | Z76: =IF(AND(Q76=0,COUNTIF(dDuplicadosGI!$A$2:$A$60,C76)>0),1,0) -> 0 | AA76: =IF(Q76=0,1,0) -> 1
A77: 76 | B77: Crédito Hipotecario | C77: PRD0047 | D77: Portal para Autogestion de creditos hipotecarios | E77: E - No Crítica | F77: Nube | G77: ACTIVOS | H77: LAURA ELIZABETH CARRASCO UQUILLAS | I77: SAMIRA ISABEL RABIE CABEZAS | J77: ERISLAN MARTINEZ JERA | K77: Aplicación del negocio | L77: No | N77: PLANIFICADA 2027 | O77: =IF(COUNTIFS($B$2:B77,B77,$C$2:C77,C77)=1,1,0) -> 1 | P77: =IFERROR(INDEX(dEtapa!$A$2:$A$6,MATCH(N77,dEtapa!$B$2:$B$6,0)),"Sin etapa") -> Planificada 2027 | Q77: =IF(L77="Si",1,0) -> 0 | R77: =IF(ISNUMBER(SEARCH("CRITERIO",N77)),1,0) -> 0 | S77: =IF(E77="","Sin dato",LEFT(E77,1)) -> E | T77: =IFERROR(INDEX(dCriticidad!$G$2:$G$7,MATCH(S77,dCriticidad!$A$2:$A$7,0)),0) -> 0 | U77: =IF(OR(LEFT(C77,3)="GI0",LEFT(C77,3)="GA0"),1,0) -> 0 | V77: =IF(G77="","Sin dato (ID GI)",TRIM(G77)) -> ACTIVOS | W77: =IF(F77="","Sin dato",F77) -> Nube | X77: =IF(M77="","",YEAR(M77)) | Y77: =IF(M77="","",DATE(YEAR(M77),MONTH(M77),1)) | Z77: =IF(AND(Q77=0,COUNTIF(dDuplicadosGI!$A$2:$A$60,C77)>0),1,0) -> 0 | AA77: =IF(Q77=0,1,0) -> 1
A78: 77 | B78: Azure Devops | C78: ITM0072 | D78: Servicio CI/CD | E78: E - No Crítica | F78: Nube | G78: COE de Ingeniería | H78: GERMAN MARTIN GUTIERREZ | I78: GERMAN MARTIN GUTIERREZ | J78: GERMAN MARTIN GUTIERREZ | K78: Consolas de Administración TI | L78: No | N78: PRIORIZACIÓN CRITERIO 1 | O78: =IF(COUNTIFS($B$2:B78,B78,$C$2:C78,C78)=1,1,0) -> 1 | P78: =IFERROR(INDEX(dEtapa!$A$2:$A$6,MATCH(N78,dEtapa!$B$2:$B$6,0)),"Sin etapa") -> Criterio 1 | Q78: =IF(L78="Si",1,0) -> 0 | R78: =IF(ISNUMBER(SEARCH("CRITERIO",N78)),1,0) -> 1 | S78: =IF(E78="","Sin dato",LEFT(E78,1)) -> E | T78: =IFERROR(INDEX(dCriticidad!$G$2:$G$7,MATCH(S78,dCriticidad!$A$2:$A$7,0)),0) -> 0 | U78: =IF(OR(LEFT(C78,3)="GI0",LEFT(C78,3)="GA0"),1,0) -> 0 | V78: =IF(G78="","Sin dato (ID GI)",TRIM(G78)) -> COE de Ingeniería | W78: =IF(F78="","Sin dato",F78) -> Nube | X78: =IF(M78="","",YEAR(M78)) | Y78: =IF(M78="","",DATE(YEAR(M78),MONTH(M78),1)) | Z78: =IF(AND(Q78=0,COUNTIF(dDuplicadosGI!$A$2:$A$60,C78)>0),1,0) -> 0 | AA78: =IF(Q78=0,1,0) -> 1
A79: 78 | B79: Deuna Backoffice | C79: SUP0030 | D79: Aplicacion micro Front end que permite autogestión del comercio para la configuración del negocio, consilización y ajustes contables | E79: D - BIA No Crítica | F79: Nube | G79: TRIBU_DE_UNA | H79: LUIS JAVIER MARIDUENA NOVILLO | I79: DIEGO ALBERTO ORDONEZ BARRIOS | J79: LUIS JAVIER MARIDUENA NOVILLO | K79: Aplicación del negocio | L79: No | N79: PLANIFICADA 2027 | O79: =IF(COUNTIFS($B$2:B79,B79,$C$2:C79,C79)=1,1,0) -> 1 | P79: =IFERROR(INDEX(dEtapa!$A$2:$A$6,MATCH(N79,dEtapa!$B$2:$B$6,0)),"Sin etapa") -> Planificada 2027 | Q79: =IF(L79="Si",1,0) -> 0 | R79: =IF(ISNUMBER(SEARCH("CRITERIO",N79)),1,0) -> 0 | S79: =IF(E79="","Sin dato",LEFT(E79,1)) -> D | T79: =IFERROR(INDEX(dCriticidad!$G$2:$G$7,MATCH(S79,dCriticidad!$A$2:$A$7,0)),0) -> 0 | U79: =IF(OR(LEFT(C79,3)="GI0",LEFT(C79,3)="GA0"),1,0) -> 0 | V79: =IF(G79="","Sin dato (ID GI)",TRIM(G79)) -> TRIBU_DE_UNA | W79: =IF(F79="","Sin dato",F79) -> Nube | X79: =IF(M79="","",YEAR(M79)) | Y79: =IF(M79="","",DATE(YEAR(M79),MONTH(M79),1)) | Z79: =IF(AND(Q79=0,COUNTIF(dDuplicadosGI!$A$2:$A$60,C79)>0),1,0) -> 0 | AA79: =IF(Q79=0,1,0) -> 1
A80: 79 | B80: Bactrader | C80: SUP0004 | D80: Aplicación que permite el manejo de inversiones a nivel de clientes corporativos y Banca Privada (Clientes Naturales). | E80: E - No Crítica | F80: Híbrida | G80: AREAS_DE_APOYO | H80: FABIAN GEOVANNI PAZMINO UBIDIA | I80: MARIA ISABEL AYALA HIDALGO | J80: FRANKLIN STALIN GARZON ANDRADE | K80: Aplicación del negocio | L80: No | N80: PLANIFICADA 2027 | O80: =IF(COUNTIFS($B$2:B80,B80,$C$2:C80,C80)=1,1,0) -> 1 | P80: =IFERROR(INDEX(dEtapa!$A$2:$A$6,MATCH(N80,dEtapa!$B$2:$B$6,0)),"Sin etapa") -> Planificada 2027 | Q80: =IF(L80="Si",1,0) -> 0 | R80: =IF(ISNUMBER(SEARCH("CRITERIO",N80)),1,0) -> 0 | S80: =IF(E80="","Sin dato",LEFT(E80,1)) -> E | T80: =IFERROR(INDEX(dCriticidad!$G$2:$G$7,MATCH(S80,dCriticidad!$A$2:$A$7,0)),0) -> 0 | U80: =IF(OR(LEFT(C80,3)="GI0",LEFT(C80,3)="GA0"),1,0) -> 0 | V80: =IF(G80="","Sin dato (ID GI)",TRIM(G80)) -> AREAS_DE_APOYO | W80: =IF(F80="","Sin dato",F80) -> Híbrida | X80: =IF(M80="","",YEAR(M80)) | Y80: =IF(M80="","",DATE(YEAR(M80),MONTH(M80),1)) | Z80: =IF(AND(Q80=0,COUNTIF(dDuplicadosGI!$A$2:$A$60,C80)>0),1,0) -> 0 | AA80: =IF(Q80=0,1,0) -> 1
A81: 80 | B81: Bancs | C81: COR0004 | D81: Core bancario del Banco Pichincha. Permite el manejo de funciones como: banca universal, banca central, pagos, administración de patrimonio, mercados de divisas y dinero, cumplimiento, seguros, procesamiento de valores, custodia, inclusión financiera. Contiene los módulos de Activos, Pasivos, Clientes, Parámetros. | E81: B - Ecosistema Apetito de Riesgo | F81: On Premise | G81: Tribu_Cores_Transacciones | H81: DAVID RODRIGO REVELO RIVERA | I81: CHRISTIAN DARIO PASQUEL PARRA | J81: DAVID RODRIGO REVELO RIVERA | K81: Switch Transaccional | L81: No | N81: PLANIFICADA 2027 | O81: =IF(COUNTIFS($B$2:B81,B81,$C$2:C81,C81)=1,1,0) -> 1 | P81: =IFERROR(INDEX(dEtapa!$A$2:$A$6,MATCH(N81,dEtapa!$B$2:$B$6,0)),"Sin etapa") -> Planificada 2027 | Q81: =IF(L81="Si",1,0) -> 0 | R81: =IF(ISNUMBER(SEARCH("CRITERIO",N81)),1,0) -> 0 | S81: =IF(E81="","Sin dato",LEFT(E81,1)) -> B | T81: =IFERROR(INDEX(dCriticidad!$G$2:$G$7,MATCH(S81,dCriticidad!$A$2:$A$7,0)),0) -> 1 | U81: =IF(OR(LEFT(C81,3)="GI0",LEFT(C81,3)="GA0"),1,0) -> 0 | V81: =IF(G81="","Sin dato (ID GI)",TRIM(G81)) -> Tribu_Cores_Transacciones | W81: =IF(F81="","Sin dato",F81) -> On Premise | X81: =IF(M81="","",YEAR(M81)) | Y81: =IF(M81="","",DATE(YEAR(M81),MONTH(M81),1)) | Z81: =IF(AND(Q81=0,COUNTIF(dDuplicadosGI!$A$2:$A$60,C81)>0),1,0) -> 0 | AA81: =IF(Q81=0,1,0) -> 1
A82: 81 | B82: BancsLink | C82: COR0005 | D82: Front del Core Bancario Bancs encargado de presentar una interfaz de usuario para la ejecucion de diversas transacciones financieras y no financieras. | E82: B - Ecosistema Apetito de Riesgo | F82: On Premise | G82: Tribu_Cores_Transacciones | H82: DAVID RODRIGO REVELO RIVERA | I82: CHRISTIAN DARIO PASQUEL PARRA | J82: DAVID RODRIGO REVELO RIVERA | K82: Aplicación del negocio | L82: Si | M82: 45200 | N82: N/A ENTREGADA | O82: =IF(COUNTIFS($B$2:B82,B82,$C$2:C82,C82)=1,1,0) -> 1 | P82: =IFERROR(INDEX(dEtapa!$A$2:$A$6,MATCH(N82,dEtapa!$B$2:$B$6,0)),"Sin etapa") -> Gobernada | Q82: =IF(L82="Si",1,0) -> 1 | R82: =IF(ISNUMBER(SEARCH("CRITERIO",N82)),1,0) -> 0 | S82: =IF(E82="","Sin dato",LEFT(E82,1)) -> B | T82: =IFERROR(INDEX(dCriticidad!$G$2:$G$7,MATCH(S82,dCriticidad!$A$2:$A$7,0)),0) -> 1 | U82: =IF(OR(LEFT(C82,3)="GI0",LEFT(C82,3)="GA0"),1,0) -> 0 | V82: =IF(G82="","Sin dato (ID GI)",TRIM(G82)) -> Tribu_Cores_Transacciones | W82: =IF(F82="","Sin dato",F82) -> On Premise | X82: =IF(M82="","",YEAR(M82)) -> 2023 | Y82: =IF(M82="","",DATE(YEAR(M82),MONTH(M82),1)) -> 45200 | Z82: =IF(AND(Q82=0,COUNTIF(dDuplicadosGI!$A$2:$A$60,C82)>0),1,0) -> 0 | AA82: =IF(Q82=0,1,0) -> 0
A83: 82 | B83: Banner Campañas | C83: CUS0018 | D83: Banner para campañas de marketing | E83: E - No Crítica | F83: Nube | G83: Negocios y Monetización | H83: ANTONIO ALEJANDRO CANAVERAL GIL | I83: ESTEFANY CAROLINA GONGORA PAREDES | J83: ANTONIO ALEJANDRO CANAVERAL GIL | K83: Componente | L83: No | N83: PLANIFICADA 2027 | O83: =IF(COUNTIFS($B$2:B83,B83,$C$2:C83,C83)=1,1,0) -> 1 | P83: =IFERROR(INDEX(dEtapa!$A$2:$A$6,MATCH(N83,dEtapa!$B$2:$B$6,0)),"Sin etapa") -> Planificada 2027 | Q83: =IF(L83="Si",1,0) -> 0 | R83: =IF(ISNUMBER(SEARCH("CRITERIO",N83)),1,0) -> 0 | S83: =IF(E83="","Sin dato",LEFT(E83,1)) -> E | T83: =IFERROR(INDEX(dCriticidad!$G$2:$G$7,MATCH(S83,dCriticidad!$A$2:$A$7,0)),0) -> 0 | U83: =IF(OR(LEFT(C83,3)="GI0",LEFT(C83,3)="GA0"),1,0) -> 0 | V83: =IF(G83="","Sin dato (ID GI)",TRIM(G83)) -> Negocios y Monetización | W83: =IF(F83="","Sin dato",F83) -> Nube | X83: =IF(M83="","",YEAR(M83)) | Y83: =IF(M83="","",DATE(YEAR(M83),MONTH(M83),1)) | Z83: =IF(AND(Q83=0,COUNTIF(dDuplicadosGI!$A$2:$A$60,C83)>0),1,0) -> 0 | AA83: =IF(Q83=0,1,0) -> 1
A84: 83 | B84: Banred ON2 (Pago directo) | C84: PRD0037 | D84: No existe dentro del portafolio | E84: E - No Crítica | F84: Terceros | G84: Tribu_Integraciones_Apis | H84: DAVID RODRIGO REVELO RIVERA | I84: WILLIAM RENATO CALDERON ROSERO | J84: JULIO CESAR VEGA GUZMAN | K84: Aplicación del negocio | L84: No | N84: PLANIFICADA 2027 | O84: =IF(COUNTIFS($B$2:B84,B84,$C$2:C84,C84)=1,1,0) -> 1 | P84: =IFERROR(INDEX(dEtapa!$A$2:$A$6,MATCH(N84,dEtapa!$B$2:$B$6,0)),"Sin etapa") -> Planificada 2027 | Q84: =IF(L84="Si",1,0) -> 0 | R84: =IF(ISNUMBER(SEARCH("CRITERIO",N84)),1,0) -> 0 | S84: =IF(E84="","Sin dato",LEFT(E84,1)) -> E | T84: =IFERROR(INDEX(dCriticidad!$G$2:$G$7,MATCH(S84,dCriticidad!$A$2:$A$7,0)),0) -> 0 | U84: =IF(OR(LEFT(C84,3)="GI0",LEFT(C84,3)="GA0"),1,0) -> 0 | V84: =IF(G84="","Sin dato (ID GI)",TRIM(G84)) -> Tribu_Integraciones_Apis | W84: =IF(F84="","Sin dato",F84) -> Terceros | X84: =IF(M84="","",YEAR(M84)) | Y84: =IF(M84="","",DATE(YEAR(M84),MONTH(M84),1)) | Z84: =IF(AND(Q84=0,COUNTIF(dDuplicadosGI!$A$2:$A$60,C84)>0),1,0) -> 0 | AA84: =IF(Q84=0,1,0) -> 1
A85: 84 | B85: Procesamiento Datos Onpremise | C85: DAT0002 | D85: Bodega de datos centralizada para fines analíticos. Información de clientes, activos, pasivos, tarjeta de crédito, tesorería, recursos humanos, CNB's, ventanillas, Banca Digital, Banca Móvil, ATM's, sistema integrado de información - rentabilidad, costos -. | E85: D - BIA No Crítica | F85: On Premise | G85: COE DATOS&ANALITICA | H85: CARLOS ALBERTO DURAN LOPEZ | I85: CARLOS ALBERTO DURAN LOPEZ | J85: CARLOS ALBERTO DURAN LOPEZ | K85: Datos | L85: No | N85: PLANIFICADA 2027 | O85: =IF(COUNTIFS($B$2:B85,B85,$C$2:C85,C85)=1,1,0) -> 1 | P85: =IFERROR(INDEX(dEtapa!$A$2:$A$6,MATCH(N85,dEtapa!$B$2:$B$6,0)),"Sin etapa") -> Planificada 2027 | Q85: =IF(L85="Si",1,0) -> 0 | R85: =IF(ISNUMBER(SEARCH("CRITERIO",N85)),1,0) -> 0 | S85: =IF(E85="","Sin dato",LEFT(E85,1)) -> D | T85: =IFERROR(INDEX(dCriticidad!$G$2:$G$7,MATCH(S85,dCriticidad!$A$2:$A$7,0)),0) -> 0 | U85: =IF(OR(LEFT(C85,3)="GI0",LEFT(C85,3)="GA0"),1,0) -> 0 | V85: =IF(G85="","Sin dato (ID GI)",TRIM(G85)) -> COE DATOS&ANALITICA | W85: =IF(F85="","Sin dato",F85) -> On Premise | X85: =IF(M85="","",YEAR(M85)) | Y85: =IF(M85="","",DATE(YEAR(M85),MONTH(M85),1)) | Z85: =IF(AND(Q85=0,COUNTIF(dDuplicadosGI!$A$2:$A$60,C85)>0),1,0) -> 0 | AA85: =IF(Q85=0,1,0) -> 1
A86: 85 | B86: BECLEVER | C86: RIS0003 | D86: Motor de Decisión que realiza la calificación de créditos de un cliente. | E86: C - BIA Crítica | F86: Nube | G86: Tribu Administración de Créditos | H86: JORGE MARIO PULGARIN MAZO | I86: JOHANNA NATALIA RODRIGUEZ SANCHEZ | J86: EDISON JAVIER RODRIGUEZ SIMBANA | K86: Aplicación complementaria | L86: No | N86: PLANIFICADA 2027 | O86: =IF(COUNTIFS($B$2:B86,B86,$C$2:C86,C86)=1,1,0) -> 1 | P86: =IFERROR(INDEX(dEtapa!$A$2:$A$6,MATCH(N86,dEtapa!$B$2:$B$6,0)),"Sin etapa") -> Planificada 2027 | Q86: =IF(L86="Si",1,0) -> 0 | R86: =IF(ISNUMBER(SEARCH("CRITERIO",N86)),1,0) -> 0 | S86: =IF(E86="","Sin dato",LEFT(E86,1)) -> C | T86: =IFERROR(INDEX(dCriticidad!$G$2:$G$7,MATCH(S86,dCriticidad!$A$2:$A$7,0)),0) -> 1 | U86: =IF(OR(LEFT(C86,3)="GI0",LEFT(C86,3)="GA0"),1,0) -> 0 | V86: =IF(G86="","Sin dato (ID GI)",TRIM(G86)) -> Tribu Administración de Créditos | W86: =IF(F86="","Sin dato",F86) -> Nube | X86: =IF(M86="","",YEAR(M86)) | Y86: =IF(M86="","",DATE(YEAR(M86),MONTH(M86),1)) | Z86: =IF(AND(Q86=0,COUNTIF(dDuplicadosGI!$A$2:$A$60,C86)>0),1,0) -> 0 | AA86: =IF(Q86=0,1,0) -> 1
A87: 86 | B87: Billetera Pichincha | C87: CHL0033 | D87: Aplicación móvil para realizar pagos entre personas y comercios. | E87: E - No Crítica | F87: Nube | G87: TRIBU_DE_UNA | H87: LUIS JAVIER MARIDUENA NOVILLO | I87: DIEGO ALBERTO ORDONEZ BARRIOS | J87: LUIS JAVIER MARIDUENA NOVILLO | K87: Aplicación del negocio | L87: No | N87: PLANIFICADA 2027 | O87: =IF(COUNTIFS($B$2:B87,B87,$C$2:C87,C87)=1,1,0) -> 1 | P87: =IFERROR(INDEX(dEtapa!$A$2:$A$6,MATCH(N87,dEtapa!$B$2:$B$6,0)),"Sin etapa") -> Planificada 2027 | Q87: =IF(L87="Si",1,0) -> 0 | R87: =IF(ISNUMBER(SEARCH("CRITERIO",N87)),1,0) -> 0 | S87: =IF(E87="","Sin dato",LEFT(E87,1)) -> E | T87: =IFERROR(INDEX(dCriticidad!$G$2:$G$7,MATCH(S87,dCriticidad!$A$2:$A$7,0)),0) -> 0 | U87: =IF(OR(LEFT(C87,3)="GI0",LEFT(C87,3)="GA0"),1,0) -> 0 | V87: =IF(G87="","Sin dato (ID GI)",TRIM(G87)) -> TRIBU_DE_UNA | W87: =IF(F87="","Sin dato",F87) -> Nube | X87: =IF(M87="","",YEAR(M87)) | Y87: =IF(M87="","",DATE(YEAR(M87),MONTH(M87),1)) | Z87: =IF(AND(Q87=0,COUNTIF(dDuplicadosGI!$A$2:$A$60,C87)>0),1,0) -> 0 | AA87: =IF(Q87=0,1,0) -> 1
A88: 87 | B88: Biocatch | C88: SEC0006 | D88: Solución de biometría comportamental que analiza patrones y aprende el comportamiento de los usuarios al interactuar con aplicaciones web y móviles. Está basada en inteligencia artificial y machine learning para detectar comportamientos inusuales y prevenir fraudes en los canales digitales. | E88: C - BIA Crítica | F88: Nube | G88: Tribu Ciberseguridad | H88: ISRAEL SEBASTIAN DE LA TORRE TRUJILLO | I88: DAVID OCTAVIO CORDOVA COLLAHUAZO | J88: DAVID OCTAVIO CORDOVA COLLAHUAZO | K88: Consolas de Administración Seguridad | L88: Si | M88: 45448 | N88: N/A ENTREGADA | O88: =IF(COUNTIFS($B$2:B88,B88,$C$2:C88,C88)=1,1,0) -> 1 | P88: =IFERROR(INDEX(dEtapa!$A$2:$A$6,MATCH(N88,dEtapa!$B$2:$B$6,0)),"Sin etapa") -> Gobernada | Q88: =IF(L88="Si",1,0) -> 1 | R88: =IF(ISNUMBER(SEARCH("CRITERIO",N88)),1,0) -> 0 | S88: =IF(E88="","Sin dato",LEFT(E88,1)) -> C | T88: =IFERROR(INDEX(dCriticidad!$G$2:$G$7,MATCH(S88,dCriticidad!$A$2:$A$7,0)),0) -> 1 | U88: =IF(OR(LEFT(C88,3)="GI0",LEFT(C88,3)="GA0"),1,0) -> 0 | V88: =IF(G88="","Sin dato (ID GI)",TRIM(G88)) -> Tribu Ciberseguridad | W88: =IF(F88="","Sin dato",F88) -> Nube | X88: =IF(M88="","",YEAR(M88)) -> 2024 | Y88: =IF(M88="","",DATE(YEAR(M88),MONTH(M88),1)) -> 45444 | Z88: =IF(AND(Q88=0,COUNTIF(dDuplicadosGI!$A$2:$A$60,C88)>0),1,0) -> 0 | AA88: =IF(Q88=0,1,0) -> 0
A89: 88 | B89: BMC TSSA | C89: ITM0076 | D89: Agente para el control de Automatización | E89: E - No Crítica | F89: On Premise | G89: Gerencia Ingeniería de Seguridad Tecnológica | H89: GONZALO TRANCILLO | I89: PABLO ALEJANDRO VERDESOTO AVILES | J89: MAURICIO JAVIER BALDEON GARZON | K89: Consolas de Administración TI | L89: No | N89: PLANIFICADA 2027 | O89: =IF(COUNTIFS($B$2:B89,B89,$C$2:C89,C89)=1,1,0) -> 1 | P89: =IFERROR(INDEX(dEtapa!$A$2:$A$6,MATCH(N89,dEtapa!$B$2:$B$6,0)),"Sin etapa") -> Planificada 2027 | Q89: =IF(L89="Si",1,0) -> 0 | R89: =IF(ISNUMBER(SEARCH("CRITERIO",N89)),1,0) -> 0 | S89: =IF(E89="","Sin dato",LEFT(E89,1)) -> E | T89: =IFERROR(INDEX(dCriticidad!$G$2:$G$7,MATCH(S89,dCriticidad!$A$2:$A$7,0)),0) -> 0 | U89: =IF(OR(LEFT(C89,3)="GI0",LEFT(C89,3)="GA0"),1,0) -> 0 | V89: =IF(G89="","Sin dato (ID GI)",TRIM(G89)) -> Gerencia Ingeniería de Seguridad Tecnológica | W89: =IF(F89="","Sin dato",F89) -> On Premise | X89: =IF(M89="","",YEAR(M89)) | Y89: =IF(M89="","",DATE(YEAR(M89),MONTH(M89),1)) | Z89: =IF(AND(Q89=0,COUNTIF(dDuplicadosGI!$A$2:$A$60,C89)>0),1,0) -> 0 | AA89: =IF(Q89=0,1,0) -> 1
A90: 89 | B90: BP-MOVIL | C90: CHL0007 | D90: APP BP-MOVIL, aplicación móvil Banco Pichincha, en la que podrá consultar posicion consolidada, consultar últimos movimientos, realizar transferencias. | E90: A - Apetito de Riesgo Disponibilidad | F90: Nube | G90: TRIBU_CANALES | H90: MIGUEL ALEXANDER MEJIA BRONCANO | I90: DIANA PATRICIA CAICEDO RODRIGUEZ | J90: MIGUEL ALEXANDER MEJIA BRONCANO | K90: Aplicación del negocio | L90: No | N90: PLANIFICADA 2027 | O90: =IF(COUNTIFS($B$2:B90,B90,$C$2:C90,C90)=1,1,0) -> 1 | P90: =IFERROR(INDEX(dEtapa!$A$2:$A$6,MATCH(N90,dEtapa!$B$2:$B$6,0)),"Sin etapa") -> Planificada 2027 | Q90: =IF(L90="Si",1,0) -> 0 | R90: =IF(ISNUMBER(SEARCH("CRITERIO",N90)),1,0) -> 0 | S90: =IF(E90="","Sin dato",LEFT(E90,1)) -> A | T90: =IFERROR(INDEX(dCriticidad!$G$2:$G$7,MATCH(S90,dCriticidad!$A$2:$A$7,0)),0) -> 1 | U90: =IF(OR(LEFT(C90,3)="GI0",LEFT(C90,3)="GA0"),1,0) -> 0 | V90: =IF(G90="","Sin dato (ID GI)",TRIM(G90)) -> TRIBU_CANALES | W90: =IF(F90="","Sin dato",F90) -> Nube | X90: =IF(M90="","",YEAR(M90)) | Y90: =IF(M90="","",DATE(YEAR(M90),MONTH(M90),1)) | Z90: =IF(AND(Q90=0,COUNTIF(dDuplicadosGI!$A$2:$A$60,C90)>0),1,0) -> 0 | AA90: =IF(Q90=0,1,0) -> 1
A91: 90 | B91: BPOne | C91: CHL0045 | D91: BPOne es el portal único para la atención de los clientes en los canales físicos (Agencias y Call Center). | E91: B - Ecosistema Apetito de Riesgo | F91: Nube | G91: TRIBU_CANALES | H91: MIGUEL ALEXANDER MEJIA BRONCANO | I91: DIEGO ROBERTO GORDON UCHUARI | J91: LUIS FERNANDO CORDOVAS RODAS | K91: Aplicación del negocio | L91: No | N91: PRIORIZACIÓN CRITERIO 1 | O91: =IF(COUNTIFS($B$2:B91,B91,$C$2:C91,C91)=1,1,0) -> 1 | P91: =IFERROR(INDEX(dEtapa!$A$2:$A$6,MATCH(N91,dEtapa!$B$2:$B$6,0)),"Sin etapa") -> Criterio 1 | Q91: =IF(L91="Si",1,0) -> 0 | R91: =IF(ISNUMBER(SEARCH("CRITERIO",N91)),1,0) -> 1 | S91: =IF(E91="","Sin dato",LEFT(E91,1)) -> B | T91: =IFERROR(INDEX(dCriticidad!$G$2:$G$7,MATCH(S91,dCriticidad!$A$2:$A$7,0)),0) -> 1 | U91: =IF(OR(LEFT(C91,3)="GI0",LEFT(C91,3)="GA0"),1,0) -> 0 | V91: =IF(G91="","Sin dato (ID GI)",TRIM(G91)) -> TRIBU_CANALES | W91: =IF(F91="","Sin dato",F91) -> Nube | X91: =IF(M91="","",YEAR(M91)) | Y91: =IF(M91="","",DATE(YEAR(M91),MONTH(M91),1)) | Z91: =IF(AND(Q91=0,COUNTIF(dDuplicadosGI!$A$2:$A$60,C91)>0),1,0) -> 0 | AA91: =IF(Q91=0,1,0) -> 1
A92: 91 | B92: Bridger Insight XG Enterprise | C92: GOB0011 | D92: Aplicación que administra la gestión de Lista de Observados, permite realizar las búsquedas de un cliente determinado en las listas que se configuren. | E92: B - Ecosistema Apetito de Riesgo | F92: Nube | G92: AREAS_DE_APOYO | H92: FABIAN GEOVANNI PAZMINO UBIDIA | I92: CRISTIAN IVAN SOLORZANO MAYA | J92: FERNANDO JOSE ROLDAN CORREA | K92: Aplicación del negocio | L92: Si | M92: 45834 | N92: N/A ENTREGADA | O92: =IF(COUNTIFS($B$2:B92,B92,$C$2:C92,C92)=1,1,0) -> 1 | P92: =IFERROR(INDEX(dEtapa!$A$2:$A$6,MATCH(N92,dEtapa!$B$2:$B$6,0)),"Sin etapa") -> Gobernada | Q92: =IF(L92="Si",1,0) -> 1 | R92: =IF(ISNUMBER(SEARCH("CRITERIO",N92)),1,0) -> 0 | S92: =IF(E92="","Sin dato",LEFT(E92,1)) -> B | T92: =IFERROR(INDEX(dCriticidad!$G$2:$G$7,MATCH(S92,dCriticidad!$A$2:$A$7,0)),0) -> 1 | U92: =IF(OR(LEFT(C92,3)="GI0",LEFT(C92,3)="GA0"),1,0) -> 0 | V92: =IF(G92="","Sin dato (ID GI)",TRIM(G92)) -> AREAS_DE_APOYO | W92: =IF(F92="","Sin dato",F92) -> Nube | X92: =IF(M92="","",YEAR(M92)) -> 2025 | Y92: =IF(M92="","",DATE(YEAR(M92),MONTH(M92),1)) -> 45809 | Z92: =IF(AND(Q92=0,COUNTIF(dDuplicadosGI!$A$2:$A$60,C92)>0),1,0) -> 0 | AA92: =IF(Q92=0,1,0) -> 0
A93: 92 | B93: Cadenas de Valor | C93: PRD0062 | D93: Cadenas de Valor es un paraguas de productos orientados hacia el financiamiento de capital de trabajo. Estos procesos financieros involucran a tres partes principales: el proveedor, el cliente y una entidad financiera. Dependiendo del producto las partes podrían cambiar de nombre a ser emisor, receptor y la entidad financiera.Cadenas de Valor es un paraguas de productos orientados hacia el financiamiento de capital de trabajo. Estos procesos financieros involucran a tres partes principales: el proveedor, el cliente y una entidad financiera. Dependiendo del producto las partes podrían cambiar de nombre a ser emisor, receptor y la entidad financiera. | E93: E - No Crítica | F93: Nube | G93: Frente de Soluciones Empresariales | H93: LUIS MIGUEL ULLOA MOREIRA | I93: FABRICIO ANTONIO PEREIRA GARCIA | J93: WILLIAM PATRICIO PANCHI SHUGULI | K93: Aplicación del negocio | L93: No | N93: PLANIFICADA 2027 | O93: =IF(COUNTIFS($B$2:B93,B93,$C$2:C93,C93)=1,1,0) -> 1 | P93: =IFERROR(INDEX(dEtapa!$A$2:$A$6,MATCH(N93,dEtapa!$B$2:$B$6,0)),"Sin etapa") -> Planificada 2027 | Q93: =IF(L93="Si",1,0) -> 0 | R93: =IF(ISNUMBER(SEARCH("CRITERIO",N93)),1,0) -> 0 | S93: =IF(E93="","Sin dato",LEFT(E93,1)) -> E | T93: =IFERROR(INDEX(dCriticidad!$G$2:$G$7,MATCH(S93,dCriticidad!$A$2:$A$7,0)),0) -> 0 | U93: =IF(OR(LEFT(C93,3)="GI0",LEFT(C93,3)="GA0"),1,0) -> 0 | V93: =IF(G93="","Sin dato (ID GI)",TRIM(G93)) -> Frente de Soluciones Empresariales | W93: =IF(F93="","Sin dato",F93) -> Nube | X93: =IF(M93="","",YEAR(M93)) | Y93: =IF(M93="","",DATE(YEAR(M93),MONTH(M93),1)) | Z93: =IF(AND(Q93=0,COUNTIF(dDuplicadosGI!$A$2:$A$60,C93)>0),1,0) -> 0 | AA93: =IF(Q93=0,1,0) -> 1
A94: 93 | B94: CAFServer (TOTEM) | C94: PAY0003 | D94: Aplicación que permite gestionar la seguridad, la validación, sincronización, consulta de datos de tarjetas de débito. Apalanca el funcionamiento del StandIn en Banred. | E94: B - Ecosistema Apetito de Riesgo | F94: On Premise | G94: MEDIOS_DE_PAGO | H94: EDWIN GEOVANNY FLORES CASTRO | I94: DAVID ALEJANDRO CHAVEZ PENAHERRERA | J94: HENRRY DANIEL MORETA IZA | K94: Aplicación del negocio | L94: No | N94: PRIORIZACIÓN CRITERIO 2 | O94: =IF(COUNTIFS($B$2:B94,B94,$C$2:C94,C94)=1,1,0) -> 1 | P94: =IFERROR(INDEX(dEtapa!$A$2:$A$6,MATCH(N94,dEtapa!$B$2:$B$6,0)),"Sin etapa") -> Criterio 2 | Q94: =IF(L94="Si",1,0) -> 0 | R94: =IF(ISNUMBER(SEARCH("CRITERIO",N94)),1,0) -> 1 | S94: =IF(E94="","Sin dato",LEFT(E94,1)) -> B | T94: =IFERROR(INDEX(dCriticidad!$G$2:$G$7,MATCH(S94,dCriticidad!$A$2:$A$7,0)),0) -> 1 | U94: =IF(OR(LEFT(C94,3)="GI0",LEFT(C94,3)="GA0"),1,0) -> 0 | V94: =IF(G94="","Sin dato (ID GI)",TRIM(G94)) -> MEDIOS_DE_PAGO | W94: =IF(F94="","Sin dato",F94) -> On Premise | X94: =IF(M94="","",YEAR(M94)) | Y94: =IF(M94="","",DATE(YEAR(M94),MONTH(M94),1)) | Z94: =IF(AND(Q94=0,COUNTIF(dDuplicadosGI!$A$2:$A$60,C94)>0),1,0) -> 0 | AA94: =IF(Q94=0,1,0) -> 1
A95: 94 | B95: Calificación Crediticia | C95: RIS0018 | D95: La calificación crediticia es una funcionalidad que nos permite comunicar a nuestros clientes la importancia de tener una buena salud financiera, entendiendo los diferentes factores clave y productos que mantiene con nosotros. | E95: E - No Crítica | F95: Nube | G95: Tribu Administración de Créditos | H95: JORGE MARIO PULGARIN MAZO | I95: MAURICIO JAVIER BALDEON GARZON | J95: CHRISTIAN PAUL ENRIQUEZ LOPEZ | K95: Aplicación complementaria | L95: No | N95: PLANIFICADA 2027 | O95: =IF(COUNTIFS($B$2:B95,B95,$C$2:C95,C95)=1,1,0) -> 1 | P95: =IFERROR(INDEX(dEtapa!$A$2:$A$6,MATCH(N95,dEtapa!$B$2:$B$6,0)),"Sin etapa") -> Planificada 2027 | Q95: =IF(L95="Si",1,0) -> 0 | R95: =IF(ISNUMBER(SEARCH("CRITERIO",N95)),1,0) -> 0 | S95: =IF(E95="","Sin dato",LEFT(E95,1)) -> E | T95: =IFERROR(INDEX(dCriticidad!$G$2:$G$7,MATCH(S95,dCriticidad!$A$2:$A$7,0)),0) -> 0 | U95: =IF(OR(LEFT(C95,3)="GI0",LEFT(C95,3)="GA0"),1,0) -> 0 | V95: =IF(G95="","Sin dato (ID GI)",TRIM(G95)) -> Tribu Administración de Créditos | W95: =IF(F95="","Sin dato",F95) -> Nube | X95: =IF(M95="","",YEAR(M95)) | Y95: =IF(M95="","",DATE(YEAR(M95),MONTH(M95),1)) | Z95: =IF(AND(Q95=0,COUNTIF(dDuplicadosGI!$A$2:$A$60,C95)>0),1,0) -> 0 | AA95: =IF(Q95=0,1,0) -> 1
A96: 95 | B96: CapturadeFirmas | C96: TIE0004 | D96: Aplicación que permite digitalizar las imágenes de las firmas, sellos y sellos secos capturadas en las transacciones del Banco que requieren este tipo de autenticación. Es utilizado por el Front operativo de Banco y Operaciones TCS | E96: C - BIA Crítica | F96: Nube | G96: COE_TRANSFORMACION_PROCESOS | H96: JAVIER ENRIQUE RIOS CASTILLO | I96: FREDI ALEXANDER ELIZALDE RODRIGUEZ | J96: SANTIAGO POSADA ZULUAGA | K96: Aplicación del negocio | L96: No | N96: PRIORIZACIÓN CRITERIO 2 | O96: =IF(COUNTIFS($B$2:B96,B96,$C$2:C96,C96)=1,1,0) -> 1 | P96: =IFERROR(INDEX(dEtapa!$A$2:$A$6,MATCH(N96,dEtapa!$B$2:$B$6,0)),"Sin etapa") -> Criterio 2 | Q96: =IF(L96="Si",1,0) -> 0 | R96: =IF(ISNUMBER(SEARCH("CRITERIO",N96)),1,0) -> 1 | S96: =IF(E96="","Sin dato",LEFT(E96,1)) -> C | T96: =IFERROR(INDEX(dCriticidad!$G$2:$G$7,MATCH(S96,dCriticidad!$A$2:$A$7,0)),0) -> 1 | U96: =IF(OR(LEFT(C96,3)="GI0",LEFT(C96,3)="GA0"),1,0) -> 0 | V96: =IF(G96="","Sin dato (ID GI)",TRIM(G96)) -> COE_TRANSFORMACION_PROCESOS | W96: =IF(F96="","Sin dato",F96) -> Nube | X96: =IF(M96="","",YEAR(M96)) | Y96: =IF(M96="","",DATE(YEAR(M96),MONTH(M96),1)) | Z96: =IF(AND(Q96=0,COUNTIF(dDuplicadosGI!$A$2:$A$60,C96)>0),1,0) -> 1 | AA96: =IF(Q96=0,1,0) -> 1
A97: 96 | B97: CAR Sectorial Digital | C97: PRD0010 | D97: Aplicación usada por oficiales de Crédito para realizar el análisis de los clientes | E97: E - No Crítica | F97: Nube | G97: Tribu Administración de Créditos | H97: JORGE MARIO PULGARIN MAZO | I97: JOHANNA NATALIA RODRIGUEZ SANCHEZ | J97: CHRISTIAN PAUL ENRIQUEZ LOPEZ | K97: Aplicación complementaria | L97: No | N97: PLANIFICADA 2027 | O97: =IF(COUNTIFS($B$2:B97,B97,$C$2:C97,C97)=1,1,0) -> 1 | P97: =IFERROR(INDEX(dEtapa!$A$2:$A$6,MATCH(N97,dEtapa!$B$2:$B$6,0)),"Sin etapa") -> Planificada 2027 | Q97: =IF(L97="Si",1,0) -> 0 | R97: =IF(ISNUMBER(SEARCH("CRITERIO",N97)),1,0) -> 0 | S97: =IF(E97="","Sin dato",LEFT(E97,1)) -> E | T97: =IFERROR(INDEX(dCriticidad!$G$2:$G$7,MATCH(S97,dCriticidad!$A$2:$A$7,0)),0) -> 0 | U97: =IF(OR(LEFT(C97,3)="GI0",LEFT(C97,3)="GA0"),1,0) -> 0 | V97: =IF(G97="","Sin dato (ID GI)",TRIM(G97)) -> Tribu Administración de Créditos | W97: =IF(F97="","Sin dato",F97) -> Nube | X97: =IF(M97="","",YEAR(M97)) | Y97: =IF(M97="","",DATE(YEAR(M97),MONTH(M97),1)) | Z97: =IF(AND(Q97=0,COUNTIF(dDuplicadosGI!$A$2:$A$60,C97)>0),1,0) -> 0 | AA97: =IF(Q97=0,1,0) -> 1
A98: 97 | B98: CardHolder | C98: PAY0004 | D98: Aplicación utilizada por el Balcón de Servicios para ejecutar los procesos de registro, solicitud, emisión, entrega, activación, modificación, reposición y cancelación de tarjetas débito | E98: C - BIA Crítica | F98: On Premise | G98: MEDIOS_DE_PAGO | H98: EDWIN GEOVANNY FLORES CASTRO | I98: DAVID ALEJANDRO CHAVEZ PENAHERRERA | J98: HENRRY DANIEL MORETA IZA | K98: Aplicación del negocio | L98: Si | M98: 45199 | N98: N/A ENTREGADA | O98: =IF(COUNTIFS($B$2:B98,B98,$C$2:C98,C98)=1,1,0) -> 1 | P98: =IFERROR(INDEX(dEtapa!$A$2:$A$6,MATCH(N98,dEtapa!$B$2:$B$6,0)),"Sin etapa") -> Gobernada | Q98: =IF(L98="Si",1,0) -> 1 | R98: =IF(ISNUMBER(SEARCH("CRITERIO",N98)),1,0) -> 0 | S98: =IF(E98="","Sin dato",LEFT(E98,1)) -> C | T98: =IFERROR(INDEX(dCriticidad!$G$2:$G$7,MATCH(S98,dCriticidad!$A$2:$A$7,0)),0) -> 1 | U98: =IF(OR(LEFT(C98,3)="GI0",LEFT(C98,3)="GA0"),1,0) -> 0 | V98: =IF(G98="","Sin dato (ID GI)",TRIM(G98)) -> MEDIOS_DE_PAGO | W98: =IF(F98="","Sin dato",F98) -> On Premise | X98: =IF(M98="","",YEAR(M98)) -> 2023 | Y98: =IF(M98="","",DATE(YEAR(M98),MONTH(M98),1)) -> 45170 | Z98: =IF(AND(Q98=0,COUNTIF(dDuplicadosGI!$A$2:$A$60,C98)>0),1,0) -> 0 | AA98: =IF(Q98=0,1,0) -> 0
A99: 98 | B99: CARTERA_CASTIGADA | C99: RIS0020 | D99: Sin descripción | E99: E - No Crítica | F99: On Premise | G99: Tribu Administración de Créditos | H99: JORGE MARIO PULGARIN MAZO | I99: JOHANNA NATALIA RODRIGUEZ SANCHEZ | J99: CHRISTIAN PAUL ENRIQUEZ LOPEZ | K99: Aplicación del negocio | L99: No | N99: PRIORIZACIÓN CRITERIO 1 | O99: =IF(COUNTIFS($B$2:B99,B99,$C$2:C99,C99)=1,1,0) -> 1 | P99: =IFERROR(INDEX(dEtapa!$A$2:$A$6,MATCH(N99,dEtapa!$B$2:$B$6,0)),"Sin etapa") -> Criterio 1 | Q99: =IF(L99="Si",1,0) -> 0 | R99: =IF(ISNUMBER(SEARCH("CRITERIO",N99)),1,0) -> 1 | S99: =IF(E99="","Sin dato",LEFT(E99,1)) -> E | T99: =IFERROR(INDEX(dCriticidad!$G$2:$G$7,MATCH(S99,dCriticidad!$A$2:$A$7,0)),0) -> 0 | U99: =IF(OR(LEFT(C99,3)="GI0",LEFT(C99,3)="GA0"),1,0) -> 0 | V99: =IF(G99="","Sin dato (ID GI)",TRIM(G99)) -> Tribu Administración de Créditos | W99: =IF(F99="","Sin dato",F99) -> On Premise | X99: =IF(M99="","",YEAR(M99)) | Y99: =IF(M99="","",DATE(YEAR(M99),MONTH(M99),1)) | Z99: =IF(AND(Q99=0,COUNTIF(dDuplicadosGI!$A$2:$A$60,C99)>0),1,0) -> 0 | AA99: =IF(Q99=0,1,0) -> 1
A100: 99 | B100: CashManagement | C100: PRD0012 | D100: Componente front que expone la funcionalidad de CashManagement. | E100: A - Apetito de Riesgo Disponibilidad | F100: On Premise | G100: Frente de Soluciones Empresariales | H100: LUIS MIGUEL ULLOA MOREIRA | I100: MARIA GABRIELA GAVILANES BARRERA | J100: LUIS MIGUEL ULLOA MOREIRA | K100: Aplicación del negocio | L100: Si | M100: 45200 | N100: N/A ENTREGADA | O100: =IF(COUNTIFS($B$2:B100,B100,$C$2:C100,C100)=1,1,0) -> 1 | P100: =IFERROR(INDEX(dEtapa!$A$2:$A$6,MATCH(N100,dEtapa!$B$2:$B$6,0)),"Sin etapa") -> Gobernada | Q100: =IF(L100="Si",1,0) -> 1 | R100: =IF(ISNUMBER(SEARCH("CRITERIO",N100)),1,0) -> 0 | S100: =IF(E100="","Sin dato",LEFT(E100,1)) -> A | T100: =IFERROR(INDEX(dCriticidad!$G$2:$G$7,MATCH(S100,dCriticidad!$A$2:$A$7,0)),0) -> 1 | U100: =IF(OR(LEFT(C100,3)="GI0",LEFT(C100,3)="GA0"),1,0) -> 0 | V100: =IF(G100="","Sin dato (ID GI)",TRIM(G100)) -> Frente de Soluciones Empresariales | W100: =IF(F100="","Sin dato",F100) -> On Premise | X100: =IF(M100="","",YEAR(M100)) -> 2023 | Y100: =IF(M100="","",DATE(YEAR(M100),MONTH(M100),1)) -> 45200 | Z100: =IF(AND(Q100=0,COUNTIF(dDuplicadosGI!$A$2:$A$60,C100)>0),1,0) -> 0 | AA100: =IF(Q100=0,1,0) -> 0
...

Sheet Validacion
A1: Validación: KPIs con fórmulas vs. valor publicado en el PDF (corte 17-sep-2026)
A2: Si cambia la matriz o los parámetros, la diferencia deja de ser 0 y es lo esperado.
A4: Métrica | B4: Valor (fórmula) | C4: Valor PDF | D4: Control | E4: Medida DAX | F4: Página
A5: Universo (CMDB + ajustes) | B5: =SUM(dConciliacion!$C$2:$C$6) -> 417 | C5: 417 | D5: =IF(ABS(B5-C5)<=0.5,"OK",B5-C5) -> OK | E5: [Universo] | F5: 1
A6: CMDB | B6: =SUMIFS(dConciliacion!$C$2:$C$7,dConciliacion!$D$2:$D$7,"Base") -> 331 | C6: 331 | D6: =IF(ABS(B6-C6)<=0.5,"OK",B6-C6) -> OK | E6: [CMDB] | F6: 2
A7: Filas en la matriz | B7: =COUNTA(fAplicaciones!$A$2:$A$414) -> 413 | C7: 413 | D7: =IF(ABS(B7-C7)<=0.5,"OK",B7-C7) -> OK | E7: [Filas Matriz] | F7: 2
A8: Aplicaciones únicas | B8: =SUM(fAplicaciones!$O$2:$O$414) -> 410 | C8: 410 | D8: =IF(ABS(B8-C8)<=0.5,"OK",B8-C8) -> OK | E8: [Aplicaciones Unicas] | F8: 2
A9: Sin fila en la matriz | B9: =B5-B8 -> 7 | C9: 7 | D9: =IF(ABS(B9-C9)<=0.5,"OK",B9-C9) -> OK | E9: [Sin Fila en Matriz] | F9: 2
A10: Gobernadas | B10: =SUMIFS(fAplicaciones!$O$2:$O$414,fAplicaciones!$Q$2:$Q$414,1) -> 188 | C10: 188 | D10: =IF(ABS(B10-C10)<=0.5,"OK",B10-C10) -> OK | E10: [Gobernadas] | F10: 1
A11: % gobernadas sobre universo | B11: =B10/B5 -> 0.45083933 | C11: 0.45 | D11: =IF(ABS(B11-C11)<=0.005,"OK",B11-C11) -> OK | E11: [% Gobernadas Universo] | F11: 1
A12: Brecha a la meta | B12: =MAX(0,Meta-B10) -> 44 | C12: 44 | D12: =IF(ABS(B12-C12)<=0.5,"OK",B12-C12) -> OK | E12: [Brecha Meta] | F12: 1
A13: Criterio 1 | B13: =COUNTIFS(fAplicaciones!$P$2:$P$414,"Criterio 1",fAplicaciones!$O$2:$O$414,1) -> 22 | C13: 22 | D13: =IF(ABS(B13-C13)<=0.5,"OK",B13-C13) -> OK | E13: [Criterio 1] | F13: 1
A14: Criterio 2 | B14: =COUNTIFS(fAplicaciones!$P$2:$P$414,"Criterio 2",fAplicaciones!$O$2:$O$414,1) -> 27 | C14: 27 | D14: =IF(ABS(B14-C14)<=0.5,"OK",B14-C14) -> OK | E14: [Criterio 2] | F14: 1
A15: Criterio 3 | B15: =COUNTIFS(fAplicaciones!$P$2:$P$414,"Criterio 3",fAplicaciones!$O$2:$O$414,1) -> 14 | C15: 14 | D15: =IF(ABS(B15-C15)<=0.5,"OK",B15-C15) -> OK | E15: [Criterio 3] | F15: 1
A16: Planificadas 2027 | B16: =COUNTIFS(fAplicaciones!$P$2:$P$414,"Planificada 2027",fAplicaciones!$O$2:$O$414,1) -> 159 | C16: 159 | D16: =IF(ABS(B16-C16)<=0.5,"OK",B16-C16) -> OK | E16: [Planificadas 2027] | F16: 1
A17: Recibidas en el año de corte | B17: =COUNTIFS(fAplicaciones!$Q$2:$Q$414,1,fAplicaciones!$O$2:$O$414,1,fAplicaciones!$M$2:$M$414,">="&DATE(YEAR(FechaCorte),1,1),fAplicaciones!$M$2:$M$414,"<="&FechaCorte) -> 42 | C17: 42 | D17: =IF(ABS(B17-C17)<=0.5,"OK",B17-C17) -> OK | E17: [Recibidas Anio] | F17: 1
A18: Ritmo mensual | B18: =B17/((FechaCorte-DATE(YEAR(FechaCorte),1,1))/DiasMes) -> 4.9297297 | C18: 4.9 | D18: =IF(ABS(B18-C18)<=0.05,"OK",B18-C18) -> OK | E18: [Ritmo Mensual] | F18: 1
A19: Meses restantes | B19: =(FinAnio-FechaCorte)/DiasMes -> 3.4539474 | C19: 3.5 | D19: =IF(ABS(B19-C19)<=0.05,"OK",B19-C19) -> OK | E19: [Meses Restantes] | F19: 1
A20: Ritmo requerido | B20: =B12/B19 -> 12.739048 | C20: 12.7 | D20: =IF(ABS(B20-C20)<=0.05,"OK",B20-C20) -> OK | E20: [Ritmo Requerido] | F20: 1
A21: Multiplicador de ritmo | B21: =B20/B18 -> 2.584127 | C21: 2.6 | D21: =IF(ABS(B21-C21)<=0.05,"OK",B21-C21) -> OK | E21: [Multiplicador Ritmo] | F21: 1
A22: Proyección a fin de año | B22: =B10+B18*B19 -> 205.02703 | C22: 205 | D22: =IF(ABS(B22-C22)<=0.5,"OK",B22-C22) -> OK | E22: [Proyeccion Fin Anio] | F22: 1
A23: % gobernadas sobre CMDB | B23: =B10/B6 -> 0.56797583 | C23: 0.57 | D23: =IF(ABS(B23-C23)<=0.005,"OK",B23-C23) -> OK | E23: [% Gobernadas sobre CMDB] | F23: 2
A24: % informe sobre CMDB | B24: =GobernadasInforme/B6 -> 0.53172205 | C24: 0.53 | D24: =IF(ABS(B24-C24)<=0.005,"OK",B24-C24) -> OK | E24: [% Informe sobre CMDB] | F24: 2
A25: % informe sobre universo | B25: =GobernadasInforme/B5 -> 0.42206235 | C25: 0.42 | D25: =IF(ABS(B25-C25)<=0.005,"OK",B25-C25) -> OK | E25: [% Informe sobre Universo] | F25: 2
A26: Gobernadas con ID GI | B26: =COUNTIFS(fAplicaciones!$Q$2:$Q$414,1,fAplicaciones!$O$2:$O$414,1,fAplicaciones!$U$2:$U$414,1) -> 41 | C26: 41 | D26: =IF(ABS(B26-C26)<=0.5,"OK",B26-C26) -> OK | E26: [Gobernadas ID GI] | F26: 2
A27: Críticas (A, B, C) | B27: =COUNTIFS(fAplicaciones!$T$2:$T$414,1,fAplicaciones!$O$2:$O$414,1) -> 136 | C27: 136 | D27: =IF(ABS(B27-C27)<=0.5,"OK",B27-C27) -> OK | E27: [Criticas] | F27: 3
A28: Críticas gobernadas | B28: =COUNTIFS(fAplicaciones!$T$2:$T$414,1,fAplicaciones!$O$2:$O$414,1,fAplicaciones!$Q$2:$Q$414,1) -> 83 | C28: 83 | D28: =IF(ABS(B28-C28)<=0.5,"OK",B28-C28) -> OK | E28: [Criticas Gobernadas] | F28: 3
A29: Críticas planificadas 2027 | B29: =COUNTIFS(fAplicaciones!$T$2:$T$414,1,fAplicaciones!$O$2:$O$414,1,fAplicaciones!$P$2:$P$414,"Planificada 2027") -> 21 | C29: 21 | D29: =IF(ABS(B29-C29)<=0.5,"OK",B29-C29) -> OK | E29: [Criticas 2027] | F29: 3
A30: Criterio 1 de baja criticidad (D, E) | B30: =COUNTIFS(fAplicaciones!$P$2:$P$414,"Criterio 1",fAplicaciones!$O$2:$O$414,1,fAplicaciones!$S$2:$S$414,"D")+COUNTIFS(fAplicaciones!$P$2:$P$414,"Criterio 1",fAplicaciones!$O$2:$O$414,1,fAplicaciones!$S$2:$S$414,"E") -> 15 | C30: 15 | D30: =IF(ABS(B30-C30)<=0.5,"OK",B30-C30) -> OK | E30: [Criterio 1 Baja Criticidad] | F30: 3
A31: Criterio 2 críticas | B31: =COUNTIFS(fAplicaciones!$P$2:$P$414,"Criterio 2",fAplicaciones!$O$2:$O$414,1,fAplicaciones!$T$2:$T$414,1) -> 25 | C31: 25 | D31: =IF(ABS(B31-C31)<=0.5,"OK",B31-C31) -> OK | E31: [Criterio 2 Criticas] | F31: 3
A32: Posibles duplicados GI | B32: =SUMIFS(fAplicaciones!$Z$2:$Z$414,fAplicaciones!$O$2:$O$414,1) -> 4 | C32: 4 | D32: =IF(ABS(B32-C32)<=0.5,"OK",B32-C32) -> OK | E32: [Posibles Duplicados GI] | F32: 4
A35: Etapa por criticidad (página 3)
A36: Criticidad | B36: Gobernada | C36: Criterio 1 | D36: Criterio 2 | E36: Criterio 3 | F36: Planificada 2027 | G36: Total | H36: % gobernadas
A37: A | B37: =COUNTIFS(fAplicaciones!$S$2:$S$414,$A37,fAplicaciones!$P$2:$P$414,"Gobernada",fAplicaciones!$O$2:$O$414,1) -> 10 | C37: =COUNTIFS(fAplicaciones!$S$2:$S$414,$A37,fAplicaciones!$P$2:$P$414,"Criterio 1",fAplicaciones!$O$2:$O$414,1) -> 0 | D37: =COUNTIFS(fAplicaciones!$S$2:$S$414,$A37,fAplicaciones!$P$2:$P$414,"Criterio 2",fAplicaciones!$O$2:$O$414,1) -> 1 | E37: =COUNTIFS(fAplicaciones!$S$2:$S$414,$A37,fAplicaciones!$P$2:$P$414,"Criterio 3",fAplicaciones!$O$2:$O$414,1) -> 0 | F37: =COUNTIFS(fAplicaciones!$S$2:$S$414,$A37,fAplicaciones!$P$2:$P$414,"Planificada 2027",fAplicaciones!$O$2:$O$414,1) -> 7 | G37: =SUM(B37:F37) -> 18 | H37: =IFERROR(B37/G37,0) -> 0.55555556
A38: B | B38: =COUNTIFS(fAplicaciones!$S$2:$S$414,$A38,fAplicaciones!$P$2:$P$414,"Gobernada",fAplicaciones!$O$2:$O$414,1) -> 28 | C38: =COUNTIFS(fAplicaciones!$S$2:$S$414,$A38,fAplicaciones!$P$2:$P$414,"Criterio 1",fAplicaciones!$O$2:$O$414,1) -> 5 | D38: =COUNTIFS(fAplicaciones!$S$2:$S$414,$A38,fAplicaciones!$P$2:$P$414,"Criterio 2",fAplicaciones!$O$2:$O$414,1) -> 15 | E38: =COUNTIFS(fAplicaciones!$S$2:$S$414,$A38,fAplicaciones!$P$2:$P$414,"Criterio 3",fAplicaciones!$O$2:$O$414,1) -> 0 | F38: =COUNTIFS(fAplicaciones!$S$2:$S$414,$A38,fAplicaciones!$P$2:$P$414,"Planificada 2027",fAplicaciones!$O$2:$O$414,1) -> 6 | G38: =SUM(B38:F38) -> 54 | H38: =IFERROR(B38/G38,0) -> 0.51851852
A39: C | B39: =COUNTIFS(fAplicaciones!$S$2:$S$414,$A39,fAplicaciones!$P$2:$P$414,"Gobernada",fAplicaciones!$O$2:$O$414,1) -> 45 | C39: =COUNTIFS(fAplicaciones!$S$2:$S$414,$A39,fAplicaciones!$P$2:$P$414,"Criterio 1",fAplicaciones!$O$2:$O$414,1) -> 2 | D39: =COUNTIFS(fAplicaciones!$S$2:$S$414,$A39,fAplicaciones!$P$2:$P$414,"Criterio 2",fAplicaciones!$O$2:$O$414,1) -> 9 | E39: =COUNTIFS(fAplicaciones!$S$2:$S$414,$A39,fAplicaciones!$P$2:$P$414,"Criterio 3",fAplicaciones!$O$2:$O$414,1) -> 0 | F39: =COUNTIFS(fAplicaciones!$S$2:$S$414,$A39,fAplicaciones!$P$2:$P$414,"Planificada 2027",fAplicaciones!$O$2:$O$414,1) -> 8 | G39: =SUM(B39:F39) -> 64 | H39: =IFERROR(B39/G39,0) -> 0.703125
A40: D | B40: =COUNTIFS(fAplicaciones!$S$2:$S$414,$A40,fAplicaciones!$P$2:$P$414,"Gobernada",fAplicaciones!$O$2:$O$414,1) -> 7 | C40: =COUNTIFS(fAplicaciones!$S$2:$S$414,$A40,fAplicaciones!$P$2:$P$414,"Criterio 1",fAplicaciones!$O$2:$O$414,1) -> 1 | D40: =COUNTIFS(fAplicaciones!$S$2:$S$414,$A40,fAplicaciones!$P$2:$P$414,"Criterio 2",fAplicaciones!$O$2:$O$414,1) -> 0 | E40: =COUNTIFS(fAplicaciones!$S$2:$S$414,$A40,fAplicaciones!$P$2:$P$414,"Criterio 3",fAplicaciones!$O$2:$O$414,1) -> 0 | F40: =COUNTIFS(fAplicaciones!$S$2:$S$414,$A40,fAplicaciones!$P$2:$P$414,"Planificada 2027",fAplicaciones!$O$2:$O$414,1) -> 16 | G40: =SUM(B40:F40) -> 24 | H40: =IFERROR(B40/G40,0) -> 0.29166667
A41: E | B41: =COUNTIFS(fAplicaciones!$S$2:$S$414,$A41,fAplicaciones!$P$2:$P$414,"Gobernada",fAplicaciones!$O$2:$O$414,1) -> 63 | C41: =COUNTIFS(fAplicaciones!$S$2:$S$414,$A41,fAplicaciones!$P$2:$P$414,"Criterio 1",fAplicaciones!$O$2:$O$414,1) -> 14 | D41: =COUNTIFS(fAplicaciones!$S$2:$S$414,$A41,fAplicaciones!$P$2:$P$414,"Criterio 2",fAplicaciones!$O$2:$O$414,1) -> 2 | E41: =COUNTIFS(fAplicaciones!$S$2:$S$414,$A41,fAplicaciones!$P$2:$P$414,"Criterio 3",fAplicaciones!$O$2:$O$414,1) -> 14 | F41: =COUNTIFS(fAplicaciones!$S$2:$S$414,$A41,fAplicaciones!$P$2:$P$414,"Planificada 2027",fAplicaciones!$O$2:$O$414,1) -> 122 | G41: =SUM(B41:F41) -> 215 | H41: =IFERROR(B41/G41,0) -> 0.29302326
A42: Sin dato | B42: =COUNTIFS(fAplicaciones!$S$2:$S$414,$A42,fAplicaciones!$P$2:$P$414,"Gobernada",fAplicaciones!$O$2:$O$414,1) -> 35 | C42: =COUNTIFS(fAplicaciones!$S$2:$S$414,$A42,fAplicaciones!$P$2:$P$414,"Criterio 1",fAplicaciones!$O$2:$O$414,1) -> 0 | D42: =COUNTIFS(fAplicaciones!$S$2:$S$414,$A42,fAplicaciones!$P$2:$P$414,"Criterio 2",fAplicaciones!$O$2:$O$414,1) -> 0 | E42: =COUNTIFS(fAplicaciones!$S$2:$S$414,$A42,fAplicaciones!$P$2:$P$414,"Criterio 3",fAplicaciones!$O$2:$O$414,1) -> 0 | F42: =COUNTIFS(fAplicaciones!$S$2:$S$414,$A42,fAplicaciones!$P$2:$P$414,"Planificada 2027",fAplicaciones!$O$2:$O$414,1) -> 0 | G42: =SUM(B42:F42) -> 35 | H42: =IFERROR(B42/G42,0) -> 1

Sheet Medidas_DAX
A1: Medidas base · crear primero (carpetas sugeridas en la columna A)
A3: Carpeta | B3: Medida | C3: Expresión DAX | D3: Formato | E3: Descripción | F3: Valor esperado al corte
A4: 0 Parámetros | B4: Fecha Corte | C4: VAR x0 = CALCULATE ( MAX ( Parametros[Valor] ), Parametros[Parámetro] = "FechaCorte" ) VAR x = DATE ( YEAR ( x0 ), MONTH ( x0 ), DAY ( x0 ) ) RETURN x | D4: dd/mm/yyyy | E4: Fecha de corte de la matriz. | F4: 17/09/2026
A5: 0 Parámetros | B5: Fecha Fin Anio | C5: VAR x0 = CALCULATE ( MAX ( Parametros[Valor] ), Parametros[Parámetro] = "FinAnio" ) VAR x = DATE ( YEAR ( x0 ), MONTH ( x0 ), DAY ( x0 ) ) RETURN x | D5: dd/mm/yyyy | E5: Fecha objetivo de la meta. | F5: 31/12/2026
A6: 0 Parámetros | B6: Fecha Informe | C6: VAR x0 = CALCULATE ( MAX ( Parametros[Valor] ), Parametros[Parámetro] = "FechaInforme" ) VAR x = DATE ( YEAR ( x0 ), MONTH ( x0 ), DAY ( x0 ) ) RETURN x | D6: dd/mm/yyyy | E6: Fecha del informe de conciliación (Word). | F6: 11/08/2026
A7: 0 Parámetros | B7: Meta | C7: CALCULATE ( MAX ( Parametros[Valor] ), Parametros[Parámetro] = "Meta" ) | D7: 0 | E7: Aplicaciones gobernadas objetivo a fin de año. | F7: 232
A8: 0 Parámetros | B8: Alcance Inicial | C8: CALCULATE ( MAX ( Parametros[Valor] ), Parametros[Parámetro] = "AlcanceInicial" ) | D8: 0 | E8: Alcance de recepción antes de ampliar criterios. | F8: 232
A9: 0 Parámetros | B9: Alcance Actual | C9: CALCULATE ( MAX ( Parametros[Valor] ), Parametros[Parámetro] = "AlcanceActual" ) | D9: 0 | E9: Alcance de recepción con los nuevos criterios. | F9: 395
A10: 0 Parámetros | B10: Gobernadas Informe | C10: CALCULATE ( MAX ( Parametros[Valor] ), Parametros[Parámetro] = "GobernadasInforme" ) | D10: 0 | E10: Gobernadas según el informe de conciliación. | F10: 176
A11: 0 Parámetros | B11: Dias Mes | C11: CALCULATE ( MAX ( Parametros[Valor] ), Parametros[Parámetro] = "DiasMes" ) | D11: 0.0 | E11: Días promedio por mes. | F11: 30,4
A12: 1 Universo | B12: CMDB | C12: CALCULATE ( SUM ( dConciliacion[Valor] ), dConciliacion[Tipo] = "Base" ) | D12: 0 | E12: Aplicaciones registradas en la CMDB. | F12: 331
A13: 1 Universo | B13: Ajustes CMDB | C13: CALCULATE ( SUM ( dConciliacion[Valor] ), dConciliacion[Tipo] = "Ajuste" ) | D13: 0 | E13: Suma de ajustes de conciliación. | F13: 86
A14: 1 Universo | B14: Universo | C14: [CMDB] + [Ajustes CMDB] | D14: 0 | E14: Universo conciliado de aplicaciones. | F14: 417
... A21: 2 Avance | B21: % Gobernadas Universo | C21: DIVIDE ( CALCULATE ( [Gobernadas], REMOVEFILTERS ( dEtapa ) ), [Universo] ) | D21: 0% | E21: Avance sobre el universo conciliado. | F21: 45%
A22: 2 Avance | B22: % Gobernadas Segmento | C22: DIVIDE ( [Gobernadas], [Aplicaciones Unicas] ) | D22: 0% | E22: Cobertura dentro de un segmento (criticidad, equipo, ubicación).
A23: 2 Avance | B23: % Meta Universo | C23: DIVIDE ( [Meta], [Universo] ) | D23: 0% | F23: 56%
A24: 2 Avance | B24: % Meta Cumplida | C24: DIVIDE ( [Gobernadas], [Meta] ) | D24: 0% | F24: 81%
A25: 2 Avance | B25: Brecha Meta | C25: MAX ( 0, [Meta] - [Gobernadas] ) | D25: 0 | E25: Recepciones que faltan para la meta. | F25: 44
A26: 2 Avance | B26: Criterio 1 | C26: CALCULATE ( [Aplicaciones Unicas], fAplicaciones[Etapa] = "Criterio 1" ) | D26: 0 | F26: 22
A27: 2 Avance | B27: Criterio 2 | C27: CALCULATE ( [Aplicaciones Unicas], fAplicaciones[Etapa] = "Criterio 2" ) | D27: 0 | F27: 27
A28: 2 Avance | B28: Criterio 3 | C28: CALCULATE ( [Aplicaciones Unicas], fAplicaciones[Etapa] = "Criterio 3" ) | D28: 0 | F28: 14
A29: 2 Avance | B29: Planificadas 2027 | C29: CALCULATE ( [Aplicaciones Unicas], fAplicaciones[Etapa] = "Planificada 2027" ) | D29: 0 | F29: 159
A30: 2 Avance | B30: Priorizadas 2026 | C30: [Criterio 1] + [Criterio 2] + [Criterio 3] | D30: 0 | E30: Cartera priorizada para el año. | F30: 63
A31: 2 Avance | B31: Con Criterio 1 | C31: [Gobernadas] + [Criterio 1] | D31: 0 | E31: Gobernadas si se recibe todo el criterio 1. | F31: 210
A32: 2 Avance | B32: Necesarias Criterio 2 | C32: MAX ( 0, [Meta] - [Gobernadas] - [Criterio 1] ) | D32: 0 | E32: Del criterio 2 necesarias para la meta. | F32: 22
A33: 3 Ritmo | B33: Recibidas Anio | C33: VAR c = [Fecha Corte] RETURN CALCULATE ( [Gobernadas], REMOVEFILTERS ( dCalendario ), fAplicaciones[Fecha Recepcion] >= DATE ( YEAR ( c ), 1, 1 ), fAplicaciones[Fecha Recepcion] <= c ) | D33: 0 | E33: Recepciones del año de corte. | F33: 42
A34: 3 Ritmo | B34: Meses Transcurridos | C34: VAR c = [Fecha Corte] RETURN DIVIDE ( c - DATE ( YEAR ( c ), 1, 1 ), [Dias Mes] ) | D34: 0.0 | F34: 8,5
A35: 3 Ritmo | B35: Ritmo Mensual | C35: DIVIDE ( [Recibidas Anio], [Meses Transcurridos] ) | D35: 0.0 | E35: Recepciones por mes en el año. | F35: 4,9
A36: 3 Ritmo | B36: Meses Restantes | C36: DIVIDE ( [Fecha Fin Anio] - [Fecha Corte], [Dias Mes] ) | D36: 0.0 | F36: 3,5
A37: 3 Ritmo | B37: Ritmo Requerido | C37: DIVIDE ( [Brecha Meta], [Meses Restantes] ) | D37: 0.0 | E37: Recepciones por mes necesarias. | F37: 12,7
A38: 3 Ritmo | B38: Multiplicador Ritmo | C38: DIVIDE ( [Ritmo Requerido], [Ritmo Mensual] ) | D38: 0.0 | F38: 2,6
A39: 3 Ritmo | B39: Proyeccion Fin Anio | C39: [Gobernadas] + [Ritmo Mensual] * [Meses Restantes] | D39: 0 | E39: Gobernadas a fin de año al ritmo actual. | F39: 205
A40: 3 Ritmo | B40: % Proyeccion Universo | C40: DIVIDE ( [Proyeccion Fin Anio], [Universo] ) | D40: 0% | F40: 49%
A41: 3 Ritmo | B41: Gobernadas Acumuladas | C41: VAR c = [Fecha Corte] VAR f = MAX ( dCalendario[Fecha] ) VAR lim = MIN ( f, c ) RETURN IF ( MIN ( dCalendario[Fecha] ) > c, BLANK (), CALCULATE ( [Gobernadas], REMOVEFILTERS ( dCalendario ), FILTER ( ALL ( fAplicaciones[Fecha Recepcion] ), fAplicaciones[Fecha Recepcion] <= lim || ISBLANK ( fAplicaciones[Fecha Recepcion] ) ) ) ) | D41: 0 | E41: Acumulado al final de cada periodo (para un gráfico de líneas con dCalendario[InicioMes]). Incluye las gobernadas sin fecha.
A42: 4 Conciliación | B42: % Informe sobre CMDB | C42: DIVIDE ( [Gobernadas Informe], [CMDB] ) | D42: 0% | F42: 53%
A43: 4 Conciliación | B43: % Informe sobre Universo | C43: DIVIDE ( [Gobernadas Informe], [Universo] ) | D43: 0% | F43: 42%
A44: 4 Conciliación | B44: % Gobernadas sobre CMDB | C44: DIVIDE ( CALCULATE ( [Gobernadas], REMOVEFILTERS ( dEtapa ) ), [CMDB] ) | D44: 0% | F44: 57%
A45: 4 Conciliación | B45: Sobrestimacion Puntos | C45: ( [% Gobernadas sobre CMDB] - [% Gobernadas Universo] ) * 100 | D45: 0 | E45: Puntos de más al reportar sobre la CMDB. | F45: 12
A46: 4 Conciliación | B46: Gobernadas ID GI | C46: CALCULATE ( [Gobernadas], fAplicaciones[IDPropioGI] = 1 ) | D46: 0 | E46: Gobernadas con ID propio de Identidades (sin ficha CMDB). | F46: 41
A47: 4 Conciliación | B47: % Gobernadas ID GI | C47: DIVIDE ( [Gobernadas ID GI], [Gobernadas] ) | D47: 0% | F47: 22%
A48: 4 Conciliación | B48: Posibles Duplicados GI | C48: CALCULATE ( [Aplicaciones Unicas], fAplicaciones[PosibleDuplicadoGI] = 1 ) | D48: 0 | E48: Pendientes que ya figuran gobernadas con ID GI. | F48: 4
A49: 5 Criticidad | B49: Criticas | C49: CALCULATE ( [Aplicaciones Unicas], dCriticidad[EsCritica] = 1 ) | D49: 0 | E49: Criticidad A, B o C. | F49: 136
A50: 5 Criticidad | B50: Criticas Gobernadas | C50: CALCULATE ( [Gobernadas], dCriticidad[EsCritica] = 1 ) | D50: 0 | F50: 83
A51: 5 Criticidad | B51: % Criticas Gobernadas | C51: DIVIDE ( [Criticas Gobernadas], [Criticas] ) | D51: 0% | F51: 61%
A52: 5 Criticidad | B52: Criticas 2027 | C52: CALCULATE ( [Criticas], fAplicaciones[Etapa] = "Planificada 2027" ) | D52: 0 | E52: Críticas diferidas al año siguiente. | F52: 21
A53: 5 Criticidad | B53: Criticas A 2027 | C53: CALCULATE ( [Aplicaciones Unicas], dCriticidad[Letra] = "A", fAplicaciones[Etapa] = "Planificada 2027" ) | D53: 0 | F53: 7
A54: 5 Criticidad | B54: Criterio 1 Baja Criticidad | C54: CALCULATE ( [Criterio 1], dCriticidad[Letra] IN { "D", "E" } ) | D54: 0 | F54: 15
A55: 5 Criticidad | B55: Criterio 2 Criticas | C55: CALCULATE ( [Criterio 2], dCriticidad[EsCritica] = 1 ) | D55: 0 | F55: 25

Sheet Textos_DAX
A1: Textos dinámicos · carpeta sugerida «7 Textos»
A3: Página | B3: Dónde aparece | C3: Medida | D3: Expresión DAX | E3: Resultado esperado al corte
A4: Todas | B4: Recuadro de corte | C4: Texto Corte | D4: VAR c = [Fecha Corte] RETURN DAY ( c ) & " " & LOOKUPVALUE ( dCalendario[MesCorto], dCalendario[Fecha], c ) & " " & YEAR ( c ) | E4: 17 sep 2026
A5: Todas | B5: Pie de página | C5: Texto Fuente | D5: VAR c = [Fecha Corte] VAR i = [Fecha Informe] RETURN "Fuentes: Matriz de Aplicaciones GI (última recepción registrada " & DAY ( c ) & " " & LOOKUPVALUE ( dCalendario[MesCorto], dCalendario[Fecha], c ) & " " & YEAR ( c ) & ") y revisión CMDB vs. Gestión de Identidades al " & DAY ( i ) & " de " & LOOKUPVALUE ( dCalendario[MesLargo], dCalendario[Fecha], i ) & "." | E5: Fuentes: Matriz de Aplicaciones GI (última recepción registrada 17 sep 2026) y revisión CMDB vs. Gestión de Identidades al 11 de agosto.
A6: 1 | B6: KPI Universo · subtítulo | C6: Sub KPI Universo | D6: "CMDB " & [CMDB] & " + " & [Ajustes CMDB] & " ajustes" | E6: CMDB 331 + 86 ajustes
A7: 1 | B7: KPI Gobernadas · subtítulo | C7: Sub KPI Gobernadas | D7: FORMAT ( [% Gobernadas Universo], "0%" ) & " del universo" | E7: 45% del universo
A8: 1 | B8: KPI Gobernadas · chip | C8: Chip KPI Gobernadas | D8: "+" & [Recibidas Anio] & " en " & YEAR ( [Fecha Corte] ) | E8: +42 en 2026
A9: 1 | B9: KPI Meta · etiqueta | C9: Label KPI Meta | D9: "Meta a diciembre " & YEAR ( [Fecha Fin Anio] ) | E9: Meta a diciembre 2026
A10: 1 | B10: KPI Meta · subtítulo | C10: Sub KPI Meta | D10: FORMAT ( [% Meta Universo], "0%" ) & " del universo" | E10: 56% del universo
A11: 1 | B11: KPI Brecha · subtítulo | C11: Sub KPI Brecha | D11: IF ( [Brecha Meta] = 0, "Meta alcanzada", FORMAT ( [% Meta Cumplida], "0%" ) & " de la meta cumplida" ) | E11: 81% de la meta cumplida
A12: 1 | B12: KPI Ritmo · subtítulo | C12: Sub KPI Ritmo | D12: "Ritmo " & YEAR ( [Fecha Corte] ) & ": " & FORMAT ( [Ritmo Mensual], "0.0" ) & "/mes (" & FORMAT ( [Multiplicador Ritmo], "0.0" ) & "× más)" | E12: Ritmo 2026: 4,9/mes (2,6× más)
A13: 1 | B13: Barra del universo · subtítulo | C13: Sub Barra Universo | D13: "Las " & [Universo] & " aplicaciones del universo según su etapa en la matriz de Gestión de Identidades." | E13: Las 417 aplicaciones del universo según su etapa en la matriz de Gestión de Identidades.
A14: 1 | B14: Barra del universo · marca meta | C14: Etiqueta Meta Barra | D14: VAR f = [Fecha Fin Anio] RETURN "Meta " & LOOKUPVALUE ( dCalendario[MesCorto], dCalendario[Fecha], f ) & "-" & YEAR ( f ) & ": " & [Meta] & " (" & FORMAT ( [% Meta Universo], "0%" ) & " del universo)" | E14: Meta dic-2026: 232 (56% del universo)
... A39: 4 | B39: Nota posibles duplicados | C39: Nota Duplicados | D39: VAR t = CALCULATETABLE ( fAplicaciones, fAplicaciones[PosibleDuplicadoGI] = 1, fAplicaciones[Cuenta] = 1 ) VAR n = COUNTROWS ( t ) VAR lista = CONCATENATEX ( t, fAplicaciones[Nombre] & " (" & LOWER ( fAplicaciones[Etapa] ) & ")", ", ", LOOKUPVALUE ( dEtapa[Orden], dEtapa[Etapa], fAplicaciones[Etapa] ), ASC, fAplicaciones[Nombre], ASC ) RETURN IF ( n = 0, "No se detectan aplicaciones pendientes que ya figuren gobernadas con ID de Identidades.", n & IF ( n = 1, " posible duplicado. ", " posibles duplicados. " ) & lista & IF ( n = 1, " ya figura", " ya figuran" ) & " como gobernadas con un ID de Identidades. Si son la misma aplicación, basta con conciliar el ID para darlas por recibidas, y la cartera real es menor." ) | E39: 4 posibles duplicados. Mail Control System (criterio 1), CapturadeFirmas (criterio 2), ListaObservados (criterio 2), Remesas (criterio 2) ya figuran como gobernadas con un ID de Identidades. Si son la misma aplicación, basta con conciliar el ID para darlas por recibidas, y la cartera real es menor.

Sheet HTML_Content
A1: Medidas para el visual HTML Content (AppSource) · carpeta sugerida «8 HTML» · Values = medida, Granularity vacío, sin título/fondo/borde del visual
A3: Página | B3: Visual del dashboard | C3: Medida | D3: Tamaño sugerido | E3: Expresión DAX
A4: 1 | B4: Encabezado de página | C4: HTML Apps Encabezado P1 | D4: 1600 × 92 px | E4: "<div style='font-family:Poppins,Segoe UI,Arial,sans-serif;position:relative;display:flex;align-items:center;height:92px;background:#FFFFFF;border-bottom:1px solid #E2E6EF;padding:0 30px 0 70px;box-sizing:border-box'>" & "<div style='position:absolute;left:0;top:0;width:0;height:0;border-top:46px solid transparent;border-bottom:46px solid transparent;border-left:40px solid #FFDD00'></div>" & "<div><div style='font-size:30px;font-weight:700;color:#0F265C;line-height:1.15'>" & "Recepción de aplicaciones " & YEAR ( [Fecha Corte] ) & "</div>" & "<div style='font-size:14px;color:#6B7390;margin-top:4px'>" & "Cuántas aplicaciones del universo ya gobierna Gestión de Identidades y qué falta para llegar a la meta de fin de año." & "</div></div>" & "<div style='margin-left:auto;display:flex;align-items:center;gap:20px'>" & "<div style='text-align:right;font-size:12px;color:#6B7390;line-height:1.45'><b style='display:block;color:#0F265C;font-size:16px'>Banco Pichincha</b>Gestión de Identidades · Hito liderado por " & CALCULATE ( MAX ( Parametros[Texto] ), Parametros[Parámetro] = "ResponsableHito" ) & "</div>" & "<div style='background:#0F265C;color:#FFFFFF;border-radius:12px;padding:9px 16px;font-size:11.5px;line-height:1.35'>Corte matriz<br><b style='font-size:15px;color:#FFDD00'>" & [Texto Corte] & "</b></div>" & "</div></div>"
A5: 2 | B5: Encabezado de página | C5: HTML Apps Encabezado P2 | D5: 1600 × 92 px | E5: "<div style='font-family:Poppins,Segoe UI,Arial,sans-serif;position:relative;display:flex;align-items:center;height:92px;background:#FFFFFF;border-bottom:1px solid #E2E6EF;padding:0 30px 0 70px;box-sizing:border-box'>" & "<div style='position:absolute;left:0;top:0;width:0;height:0;border-top:46px solid transparent;border-bottom:46px solid transparent;border-left:40px solid #FFDD00'></div>" & "<div><div style='font-size:30px;font-weight:700;color:#0F265C;line-height:1.15'>" & "Conciliación del universo de aplicaciones" & "</div>" & "<div style='font-size:14px;color:#6B7390;margin-top:4px'>" & [Sub Encabezado P2] & "</div></div>" & "<div style='margin-left:auto;display:flex;align-items:center;gap:20px'>" & "<div style='text-align:right;font-size:12px;color:#6B7390;line-height:1.45'><b style='display:block;color:#0F265C;font-size:16px'>Banco Pichincha</b>Gestión de Identidades · Hito liderado por " & CALCULATE ( MAX ( Parametros[Texto] ), Parametros[Parámetro] = "ResponsableHito" ) & "</div>" & "<div style='background:#0F265C;color:#FFFFFF;border-radius:12px;padding:9px 16px;font-size:11.5px;line-height:1.35'>Corte matriz<br><b style='font-size:15px;color:#FFDD00'>" & [Texto Corte] & "</b></div>" & "</div></div>"
A6: 3 | B6: Encabezado de página | C6: HTML Apps Encabezado P3 | D6: 1600 × 92 px | E6: "<div style='font-family:Poppins,Segoe UI,Arial,sans-serif;position:relative;display:flex;align-items:center;height:92px;background:#FFFFFF;border-bottom:1px solid #E2E6EF;padding:0 30px 0 70px;box-sizing:border-box'>" & "<div style='position:absolute;left:0;top:0;width:0;height:0;border-top:46px solid transparent;border-bottom:46px solid transparent;border-left:40px solid #FFDD00'></div>" & "<div><div style='font-size:30px;font-weight:700;color:#0F265C;line-height:1.15'>" & "Cobertura por criticidad y por equipo" & "</div>" & "<div style='font-size:14px;color:#6B7390;margin-top:4px'>" & "Qué tan gobernadas están las aplicaciones más críticas y dónde se concentra lo pendiente." & "</div></div>" & "<div style='margin-left:auto;display:flex;align-items:center;gap:20px'>" & "<div style='text-align:right;font-size:12px;color:#6B7390;line-height:1.45'><b style='display:block;color:#0F265C;font-size:16px'>Banco Pichincha</b>Gestión de Identidades · Hito liderado por " & CALCULATE ( MAX ( Parametros[Texto] ), Parametros[Parámetro] = "ResponsableHito" ) & "</div>" & "<div style='background:#0F265C;color:#FFFFFF;border-radius:12px;padding:9px 16px;font-size:11.5px;line-height:1.35'>Corte matriz<br><b style='font-size:15px;color:#FFDD00'>" & [Texto Corte] & "</b></div>" & "</div></div>"
A7: 4 | B7: Encabezado de página | C7: HTML Apps Encabezado P4 | D7: 1600 × 92 px | E7: "<div style='font-family:Poppins,Segoe UI,Arial,sans-serif;position:relative;display:flex;align-items:center;height:92px;background:#FFFFFF;border-bottom:1px solid #E2E6EF;padding:0 30px 0 70px;box-sizing:border-box'>" & "<div style='position:absolute;left:0;top:0;width:0;height:0;border-top:46px solid transparent;border-bottom:46px solid transparent;border-left:40px solid #FFDD00'></div>" & "<div><div style='font-size:30px;font-weight:700;color:#0F265C;line-height:1.15'>" & "Cartera priorizada para cerrar la brecha" & "</div>" & "<div style='font-size:14px;color:#6B7390;margin-top:4px'>" & [Sub Encabezado P4] & "</div></div>" & "<div style='margin-left:auto;display:flex;align-items:center;gap:20px'>" & "<div style='text-align:right;font-size:12px;color:#6B7390;line-height:1.45'><b style='display:block;color:#0F265C;font-size:16px'>Banco Pichincha</b>Gestión de Identidades · Hito liderado por " & CALCULATE ( MAX ( Parametros[Texto] ), Parametros[Parámetro] = "ResponsableHito" ) & "</div>" & "<div style='background:#0F265C;color:#FFFFFF;border-radius:12px;padding:9px 16px;font-size:11.5px;line-height:1.35'>Corte matriz<br><b style='font-size:15px;color:#FFDD00'>" & [Texto Corte] & "</b></div>" & "</div></div>"
A8: Todas | B8: Pie de página | C8: HTML Apps Pie | D8: 1520 × 30 px | E8: "<div style='font-family:Poppins,Segoe UI,Arial,sans-serif;font-size:10.5px;color:#6B7390'>" & [Texto Fuente] & "</div>"
A9: 1 | B9: Tarjeta KPI | C9: HTML Apps KPI Universo | D9: 290 × 100 px | E9: "<div style='font-family:Poppins,Segoe UI,Arial,sans-serif;background:#FFFFFF;border:1px solid #E2E6EF;border-left:4px solid #0F265C;border-radius:14px;padding:12px 18px;box-sizing:border-box;height:100%'>" & "<div style='font-size:30px;font-weight:700;color:#0F265C;line-height:1.1'>" & [Universo] & "</div>" & "<div style='font-size:14px;font-weight:500;color:#1B2340;margin-top:3px'>" & "Universo de aplicaciones" & "</div>" & "<div style='font-size:12px;color:#6B7390;margin-top:2px'>" & [Sub KPI Universo] & "</div></div>"
A10: 1 | B10: Tarjeta KPI | C10: HTML Apps KPI Gobernadas | D10: 290 × 100 px | E10: "<div style='font-family:Poppins,Segoe UI,Arial,sans-serif;background:#FFFFFF;border:1px solid #E2E6EF;border-left:4px solid #0F265C;border-radius:14px;padding:12px 18px;box-sizing:border-box;height:100%'>" & "<div style='font-size:30px;font-weight:700;color:#0F265C;line-height:1.1'>" & [Gobernadas] & " <span style='font-size:11.5px;font-weight:600;padding:3px 9px;border-radius:99px;background:#E4EAF7;color:#0F265C;vertical-align:middle'>" & [Chip KPI Gobernadas] & "</span>" & "</div>" & "<div style='font-size:14px;font-weight:500;color:#1B2340;margin-top:3px'>" & "Aplicaciones gobernadas" & "</div>" & "<div style='font-size:12px;color:#6B7390;margin-top:2px'>" & [Sub KPI Gobernadas] & "</div></div>"
A11: 1 | B11: Tarjeta KPI | C11: HTML Apps KPI Meta | D11: 290 × 100 px | E11: "<div style='font-family:Poppins,Segoe UI,Arial,sans-serif;background:#FFFFFF;border:1px solid #E2E6EF;border-left:4px solid #0F265C;border-radius:14px;padding:12px 18px;box-sizing:border-box;height:100%'>" & "<div style='font-size:30px;font-weight:700;color:#0F265C;line-height:1.1'>" & [Meta] & "</div>" & "<div style='font-size:14px;font-weight:500;color:#1B2340;margin-top:3px'>" & [Label KPI Meta] & "</div>" & "<div style='font-size:12px;color:#6B7390;margin-top:2px'>" & [Sub KPI Meta] & "</div></div>"
A12: 1 | B12: Tarjeta KPI | C12: HTML Apps KPI Brecha | D12: 290 × 100 px | E12: "<div style='font-family:Poppins,Segoe UI,Arial,sans-serif;background:#FFFFFF;border:1px solid #E2E6EF;border-left:4px solid #F5B800;border-radius:14px;padding:12px 18px;box-sizing:border-box;height:100%'>" & "<div style='font-size:30px;font-weight:700;color:#0F265C;line-height:1.1'>" & [Brecha Meta] & "</div>" & "<div style='font-size:14px;font-weight:500;color:#1B2340;margin-top:3px'>" & "Faltan para la meta" & "</div>" & "<div style='font-size:12px;color:#6B7390;margin-top:2px'>" & [Sub KPI Brecha] & "</div></div>"
A13: 1 | B13: Tarjeta KPI | C13: HTML Apps KPI Ritmo | D13: 290 × 100 px | E13: "<div style='font-family:Poppins,Segoe UI,Arial,sans-serif;background:#FFFFFF;border:1px solid #E2E6EF;border-left:4px solid #D64545;border-radius:14px;padding:12px 18px;box-sizing:border-box;height:100%'>" & "<div style='font-size:30px;font-weight:700;color:#0F265C;line-height:1.1'>" & FORMAT ( [Ritmo Requerido], "0.0" ) & "</div>" & "<div style='font-size:14px;font-weight:500;color:#1B2340;margin-top:3px'>" & "Recepciones por mes necesarias" & "</div>" & "<div style='font-size:12px;color:#6B7390;margin-top:2px'>" & [Sub KPI Ritmo] & "</div></div>"
A14: 3 | B14: Tarjeta KPI | C14: HTML Apps KPI Criticas | D14: 290 × 100 px | E14: "<div style='font-family:Poppins,Segoe UI,Arial,sans-serif;background:#FFFFFF;border:1px solid #E2E6EF;border-left:4px solid #0F265C;border-radius:14px;padding:12px 18px;box-sizing:border-box;height:100%'>" & "<div style='font-size:30px;font-weight:700;color:#0F265C;line-height:1.1'>" & FORMAT ( [% Criticas Gobernadas], "0%" ) & "</div>" & "<div style='font-size:14px;font-weight:500;color:#1B2340;margin-top:3px'>" & "Críticas gobernadas (A, B y C)" & "</div>" & "<div style='font-size:12px;color:#6B7390;margin-top:2px'>" & [Sub KPI Criticas] & "</div></div>"
... A32: 4 | B32: Leyenda de criticidad | C32: HTML Apps Leyenda Criticidad | D32: 330 × 170 px | E32: "<div style='font-family:Poppins,Segoe UI,Arial,sans-serif;font-size:11.5px;color:#6B7390;background:#FFFFFF;border:1px solid #E2E6EF;border-radius:14px;padding:12px 14px'><b style='color:#0F265C;display:block;margin-bottom:6px'>Criticidad</b>" & CONCATENATEX ( FILTER ( ALL ( dCriticidad ), dCriticidad[Letra] <> "Sin dato" ), "<div style='padding:2px 0'><span style='display:inline-block;width:20px;height:20px;line-height:20px;text-align:center;border-radius:6px;font-size:11px;font-weight:700;margin-right:8px;background:" & dCriticidad[ColorHex] & ";color:" & dCriticidad[TextoColor] & "'>" & dCriticidad[Letra] & "</span>" & dCriticidad[Nombre] & "</div>", "", dCriticidad[Orden], ASC ) & "</div>"

Sheet Columnas_DAX
A1: Columnas calculadas · crear en este orden
A3: Tabla | B3: Columna | C3: Expresión DAX | D3: Tipo | E3: Columna Excel equivalente
A4: fAplicaciones | B4: ID | C4: Se crea en Power Query (columna de índice desde 1). | D4: Entero | E4: A
A5: fAplicaciones | B5: Cuenta | C5: VAR n = fAplicaciones[Nombre] VAR b = fAplicaciones[Bp Id] VAR i = fAplicaciones[ID] RETURN IF ( COUNTROWS ( FILTER ( fAplicaciones, fAplicaciones[Nombre] = n && fAplicaciones[Bp Id] = b && fAplicaciones[ID] < i ) ) = 0, 1, 0 ) | D5: Entero | E5: O
A6: fAplicaciones | B6: Etapa | C6: LOOKUPVALUE ( dEtapa[Etapa], dEtapa[ValorMatriz], fAplicaciones[Priorización], "Sin etapa" ) | D6: Texto | E6: P
A7: fAplicaciones | B7: Gobernada | C7: IF ( fAplicaciones[Entregada Identidades] = "Si", 1, 0 ) | D7: Entero | E7: Q
A8: fAplicaciones | B8: Priorizada2026 | C8: IF ( CONTAINSSTRING ( fAplicaciones[Priorización], "CRITERIO" ), 1, 0 ) | D8: Entero | E8: R
A9: fAplicaciones | B9: CritLetra | C9: IF ( ISBLANK ( fAplicaciones[Prioridad] ) || fAplicaciones[Prioridad] = "", "Sin dato", LEFT ( fAplicaciones[Prioridad], 1 ) ) | D9: Texto | E9: S
A10: fAplicaciones | B10: EsCritica | C10: RELATED ( dCriticidad[EsCritica] ) | D10: Entero | E10: T
A11: fAplicaciones | B11: IDPropioGI | C11: IF ( LEFT ( fAplicaciones[Bp Id], 3 ) IN { "GI0", "GA0" }, 1, 0 ) | D11: Entero | E11: U
A12: fAplicaciones | B12: Equipo | C12: IF ( ISBLANK ( fAplicaciones[Equipo Administrado Por] ) || fAplicaciones[Equipo Administrado Por] = "", "Sin dato (ID GI)", TRIM ( fAplicaciones[Equipo Administrado Por] ) ) | D12: Texto | E12: V
A13: fAplicaciones | B13: UbicacionN | C13: IF ( ISBLANK ( fAplicaciones[Ubicacion] ) || fAplicaciones[Ubicacion] = "", "Sin dato", fAplicaciones[Ubicacion] ) | D13: Texto | E13: W
A14: fAplicaciones | B14: AnioRecepcion | C14: IF ( NOT ISBLANK ( fAplicaciones[Fecha Recepcion] ), YEAR ( fAplicaciones[Fecha Recepcion] ) ) | D14: Entero | E14: X
... A18: dCalendario | B18: Tabla (alternativa DAX) | C18: dCalendario = ADDCOLUMNS ( CALENDAR ( DATE ( 2023, 1, 1 ), DATE ( 2026, 12, 31 ) ), "Anio", YEAR ( [Date] ), "Mes", MONTH ( [Date] ), "InicioMes", DATE ( YEAR ( [Date] ), MONTH ( [Date] ), 1 ), "MesCorto", SWITCH ( MONTH ( [Date] ), 1, "ene", 2, "feb", 3, "mar", 4, "abr", 5, "may", 6, "jun", 7, "jul", 8, "ago", 9, "sep", 10, "oct", 11, "nov", 12, "dic" ), "MesLargo", SWITCH ( MONTH ( [Date] ), 1, "enero", 2, "febrero", 3, "marzo", 4, "abril", 5, "mayo", 6, "junio", 7, "julio", 8, "agosto", 9, "septiembre", 10, "octubre", 11, "noviembre", 12, "diciembre" ) ) -- renombrar [Date] a [Fecha] y marcar como tabla de fechas | D18: Tabla | E18: dCalendario

Sheet Visuales
A1: Página | B1: Visual | C1: Medida(s) | D1: Tamaño sugerido (px)
A2: Todas | B2: Encabezado | C2: HTML Apps Encabezado P1…P4 | D2: 1600 × 92
A3: Todas | B3: Pie de página | C3: HTML Apps Pie | D3: 1520 × 30
A4: 1 | B4: 5 tarjetas KPI | C4: HTML Apps KPI Universo / Gobernadas / Meta / Brecha / Ritmo | D4: 290 × 100 c/u
A5: 1 | B5: Del universo a la meta | C5: HTML Apps Barra Universo | D5: 1520 × 270
A6: 1 | B6: Curva acumulada | C6: HTML Apps Curva Acumulada (alternativa nativa: gráfico de líneas con dCalendario[InicioMes] y [Gobernadas Acumuladas] + línea constante [Meta]) | D6: 960 × 340
A7: 1 | B7: Ruta a la meta | C7: HTML Apps Ruta Meta | D7: 520 × 340
A8: 2 | B8: Cascada CMDB → universo | C8: HTML Apps Cascada (alternativa nativa: gráfico de cascada con dConciliacion[Paso] y SUM(dConciliacion[Valor]) filtrando Tipo ≠ Total) | D8: 940 × 610
A9: 2 | B9: El mismo avance se lee distinto | C9: HTML Apps Doble Base | D9: 560 × 300
A10: 2 | B10: La matriz frente al universo | C10: HTML Apps Matriz Universo | D10: 560 × 290
A11: 2 | B11: Por qué creció el alcance | C11: HTML Apps Alcance | D11: 1520 × 124
A12: 3 | B12: 5 tarjetas KPI | C12: HTML Apps KPI Criticas / Criticas 2027 / C1 Baja / C2 Criticas / Cobertura | D12: 290 × 100 c/u
... A17: 4 | B17: Notas y leyenda | C17: HTML Apps Nota Criterio 3 · HTML Apps Nota Duplicados · HTML Apps Leyenda Criticidad | D17: 330 de ancho
A19: Fondo de página #F3F5FA. Lienzo 1600 × 900. Visual HTML Content: desactivar título, fondo, borde y sombra.

Sheet PowerQuery_M
A1: Consulta fAplicaciones (Editor avanzado)
A3: let
A4: Origen = Excel.Workbook(File.Contents("C:\Ruta\Matriz_de_Aplicaciones_GI_-_Agosto_2026.xlsx"), null, true),
A5: Hoja = Origen{[Item = "Hoja1", Kind = "Sheet"]}[Data],
A6: Encabezados = Table.PromoteHeaders(Hoja, [PromoteAllScalars = true]),
A7: Nombres = Table.TransformColumnNames(Encabezados, Text.Trim),
A8: SinVacias = Table.SelectRows(Nombres, each [Nombre] <> null and [Nombre] <> ""),
A9: ConID = Table.AddIndexColumn(SinVacias, "ID", 1, 1, Int64.Type),
A10: Tipos = Table.TransformColumnTypes(ConID, {
A11: {"Nombre", type text}, {"Bp Id", type text}, {"Descripcion", type text}, {"Prioridad", type text},
A12: {"Ubicacion", type text}, {"Equipo Administrado Por", type text}, {"Dueno Aplicacion", type text},
A13: {"Dueno Negocio", type text}, {"Administrado Por", type text}, {"Categoria Identidades", type text},
... A22: 3. Marcar dCalendario como tabla de fechas.

Sheet Tema_PowerBI
A1: Guardar como tema_pichincha.json e importar en Vista > Temas > Examinar temas.
A3: {
A4: "name": "Banco Pichincha · Recepción de aplicaciones",
A5: "dataColors": [
A6: "#0F265C",
A7: "#3A5BA9",
A8: "#7C97D6",
A9: "#C9D5EE",
A10: "#FFDD00",
A11: "#F5B800",
A12: "#D64545",
A13: "#B4BBCB"
... A54: }

Sheet Parametros
A2: Parámetro | B2: Valor | C2: Texto | D2: Descripción
A3: FechaCorte | B3: 46282 | D3: Fecha de corte: última recepción registrada en la matriz.
A4: FinAnio | B4: 46387 | D4: Fecha objetivo de la meta.
A5: FechaInforme | B5: 46245 | D5: Fecha del informe de conciliación CMDB (DatosSN).
A6: Meta | B6: 232 | D6: Aplicaciones gobernadas objetivo a fin de año.
A7: AlcanceInicial | B7: 232 | D7: Alcance de recepción con el criterio original (solo apps con módulo de seguridad).
A8: AlcanceActual | B8: 395 | D8: Alcance de recepción con los criterios ampliados.
A9: GobernadasInforme | B9: 176 | D9: Gobernadas reportadas en el informe de conciliación.
A10: DiasMes | B10: 30.4 | D10: Días promedio por mes.
A11: ResponsableHito | C11: Jhonny Barreiro | D11: Responsable del hito (texto del encabezado).
A13: Fuente: informe DatosSN (11-ago-2026) para FechaInforme, Meta, Alcance y GobernadasInforme; matriz para FechaCorte.

Sheet dEtapa
A1: Etapa | B1: ValorMatriz | C1: Orden | D1: ColorHex | E1: TextoColor | F1: EsPendiente | G1: EsPriorizada2026 | H1: Leyenda
A2: Gobernada | B2: N/A ENTREGADA | C2: 1 | D2: #0F265C | E2: #FFFFFF | F2: 0 | G2: 0 | H2: Gobernadas
A3: Criterio 1 | B3: PRIORIZACIÓN CRITERIO 1 | C3: 2 | D3: #3A5BA9 | E3: #FFFFFF | F3: 1 | G3: 1 | H3: Priorizadas criterio 1
A4: Criterio 2 | B4: PRIORIZACIÓN CRITERIO 2 | C4: 3 | D4: #7C97D6 | E4: #1B2340 | F4: 1 | G4: 1 | H4: Priorizadas criterio 2
A5: Criterio 3 | B5: PRIORIZACIÓN CRITERIO 3 | C5: 4 | D5: #C9D5EE | E5: #1B2340 | F5: 1 | G5: 1 | H5: Priorizadas criterio 3
A6: Planificada 2027 | B6: PLANIFICADA 2027 | C6: 5 | D6: #DDE2EC | E6: #1B2340 | F6: 1 | G6: 0 | H6: Planificadas 2027

Sheet dCriticidad
A1: Letra | B1: Prioridad | C1: Nombre | D1: Orden | E1: ColorHex | F1: TextoColor | G1: EsCritica
A2: A | B2: A - Apetito de Riesgo Disponibilidad | C2: Apetito de riesgo disponibilidad | D2: 1 | E2: #D64545 | F2: #FFFFFF | G2: 1
A3: B | B3: B - Ecosistema Apetito de Riesgo | C3: Ecosistema apetito de riesgo | D3: 2 | E3: #F5B800 | F3: #1B2340 | G3: 1
A4: C | B4: C - BIA Crítica | C4: BIA crítica | D4: 3 | E4: #7C97D6 | F4: #1B2340 | G4: 1
A5: D | B5: D - BIA No Crítica | C5: BIA no crítica | D5: 4 | E5: #C9D5EE | F5: #1B2340 | G5: 0
A6: E | B6: E - No Crítica | C6: No crítica | D6: 5 | E6: #DDE2EC | F6: #1B2340 | G6: 0
A7: Sin dato | B7: Sin dato | C7: Sin dato | D7: 6 | E7: #F3F5FA | F7: #1B2340 | G7: 0

Sheet dConciliacion
A1: Orden | B1: Paso | C1: Valor | D1: Tipo | E1: EtiquetaL1 | F1: EtiquetaL2 | G1: Descripcion
A2: 1 | B2: CMDB (ServiceNow) | C2: 331 | D2: Base | E2: CMDB | F2: (ServiceNow) | G2: Total registrado en la CMDB de ServiceNow.
A3: 2 | B3: Servicios externos | C3: 35 | D3: Ajuste | E3: Servicios | F3: externos | G3: Excluidos por un filtro de tipo de aplicación en el dashboard de ServiceNow, aunque Identidades también los administra.
A4: 3 | B4: Sin registro en CMDB | C4: 16 | D4: Ajuste | E4: Sin registro | F4: en CMDB | G4: Bajo gestión de Identidades y con procesos activos de accesos, pero sin ficha en la CMDB.
A5: 4 | B5: Infraestructura Siglo XXI | C5: 23 | D5: Ajuste | E5: Infraestructura | F5: Siglo XXI | G5: Tienen roles de acceso asignados, pero al no estar en la CMDB no se pueden someter a depuración de accesos.
A6: 5 | B6: Decomisadas pero activas | C6: 12 | D6: Ajuste | E6: Decomisadas | F6: pero activas | G6: Figuran como decomisadas en la CMDB; Identidades confirma que siguen operativas y con gestión de accesos.
A7: 6 | B7: Universo GI | C7: 417 | D7: Total | E7: Universo | F7: GI | G7: Universo conciliado que administra Gestión de Identidades.

Sheet dAlcance
A1: Orden | B1: Titulo | C1: Texto
A2: 1 | B2: Aplicaciones estratégicas sin módulo de seguridad. | C2: Casos como BPOne o Remesas entran con controles compensatorios: autenticación obligatoria con Microsoft Entra ID integrado al gestor de identidades, y cambios de roles solo por pipeline con aprobación de Identidades.
A3: 2 | B3: Aplicaciones de Ciberseguridad. | C3: Se incorporaron también las de Ciberseguridad sin módulo de seguridad, que no estaban en el esquema inicial.

Sheet dDuplicadosGI
A1: BpIdPendiente | B1: NombrePendiente | C1: Etapa | D1: BpIdGI | E1: NombreGI
A2: GOB0013 | B2: ListaObservados | C2: Criterio 2 | D2: GI0033 | E2: Lista Observados
A3: SUP0012 | B3: Mail Control System | C3: Criterio 1 | D3: GI0034 | E3: Mail Control System
A4: TIE0004 | B4: CapturadeFirmas | C4: Criterio 2 | D4: GI0023 | E4: Aplicativo Captura de Firmas
A5: PAY0023 | B5: Remesas | C5: Criterio 2 | D5: GI0024 | E5: Aplicativo de Remesas
A7: Detectados por coincidencia de nombre normalizado. Agregar o quitar filas tras validar con el equipo; fAplicaciones[PosibleDuplicadoGI] se recalcula.

Sheet dCalendario
A1: Fecha | B1: Anio | C1: Mes | D1: InicioMes | E1: MesCorto | F1: MesLargo | G1: MesAnio
A2: 44927 | B2: =YEAR(A2) -> 2023 | C2: =MONTH(A2) -> 1 | D2: =DATE(B2,C2,1) -> 44927 | E2: =CHOOSE(C2,"ene","feb","mar","abr","may","jun","jul","ago","sep","oct","nov","dic") -> ene | F2: =CHOOSE(C2,"enero","febrero","marzo","abril","mayo","junio","julio","agosto","septiembre","octubre","noviembre","diciembre") -> enero | G2: =E2&"-"&RIGHT(B2,2) -> ene-23
A3: =A2+1 -> 44928 | B3: =YEAR(A3) -> 2023 | C3: =MONTH(A3) -> 1 | D3: =DATE(B3,C3,1) -> 44927 | E3: =CHOOSE(C3,"ene","feb","mar","abr","may","jun","jul","ago","sep","oct","nov","dic") -> ene | F3: =CHOOSE(C3,"enero","febrero","marzo","abril","mayo","junio","julio","agosto","septiembre","octubre","noviembre","diciembre") -> enero | G3: =E3&"-"&RIGHT(B3,2) -> ene-23
A4: =A3+1 -> 44929 | B4: =YEAR(A4) -> 2023 | C4: =MONTH(A4) -> 1 | D4: =DATE(B4,C4,1) -> 44927 | E4: =CHOOSE(C4,"ene","feb","mar","abr","may","jun","jul","ago","sep","oct","nov","dic") -> ene | F4: =CHOOSE(C4,"enero","febrero","marzo","abril","mayo","junio","julio","agosto","septiembre","octubre","noviembre","diciembre") -> enero | G4: =E4&"-"&RIGHT(B4,2) -> ene-23
A5: =A4+1 -> 44930 | B5: =YEAR(A5) -> 2023 | C5: =MONTH(A5) -> 1 | D5: =DATE(B5,C5,1) -> 44927 | E5: =CHOOSE(C5,"ene","feb","mar","abr","may","jun","jul","ago","sep","oct","nov","dic") -> ene | F5: =CHOOSE(C5,"enero","febrero","marzo","abril","mayo","junio","julio","agosto","septiembre","octubre","noviembre","diciembre") -> enero | G5: =E5&"-"&RIGHT(B5,2) -> ene-23
A6: =A5+1 -> 44931 | B6: =YEAR(A6) -> 2023 | C6: =MONTH(A6) -> 1 | D6: =DATE(B6,C6,1) -> 44927 | E6: =CHOOSE(C6,"ene","feb","mar","abr","may","jun","jul","ago","sep","oct","nov","dic") -> ene | F6: =CHOOSE(C6,"enero","febrero","marzo","abril","mayo","junio","julio","agosto","septiembre","octubre","noviembre","diciembre") -> enero | G6: =E6&"-"&RIGHT(B6,2) -> ene-23
A7: =A6+1 -> 44932 | B7: =YEAR(A7) -> 2023 | C7: =MONTH(A7) -> 1 | D7: =DATE(B7,C7,1) -> 44927 | E7: =CHOOSE(C7,"ene","feb","mar","abr","may","jun","jul","ago","sep","oct","nov","dic") -> ene | F7: =CHOOSE(C7,"enero","febrero","marzo","abril","mayo","junio","julio","agosto","septiembre","octubre","noviembre","diciembre") -> enero | G7: =E7&"-"&RIGHT(B7,2) -> ene-23
A8: =A7+1 -> 44933 | B8: =YEAR(A8) -> 2023 | C8: =MONTH(A8) -> 1 | D8: =DATE(B8,C8,1) -> 44927 | E8: =CHOOSE(C8,"ene","feb","mar","abr","may","jun","jul","ago","sep","oct","nov","dic") -> ene | F8: =CHOOSE(C8,"enero","febrero","marzo","abril","mayo","junio","julio","agosto","septiembre","octubre","noviembre","diciembre") -> enero | G8: =E8&"-"&RIGHT(B8,2) -> ene-23
A9: =A8+1 -> 44934 | B9: =YEAR(A9) -> 2023 | C9: =MONTH(A9) -> 1 | D9: =DATE(B9,C9,1) -> 44927 | E9: =CHOOSE(C9,"ene","feb","mar","abr","may","jun","jul","ago","sep","oct","nov","dic") -> ene | F9: =CHOOSE(C9,"enero","febrero","marzo","abril","mayo","junio","julio","agosto","septiembre","octubre","noviembre","diciembre") -> enero | G9: =E9&"-"&RIGHT(B9,2) -> ene-23
A10: =A9+1 -> 44935 | B10: =YEAR(A10) -> 2023 | C10: =MONTH(A10) -> 1 | D10: =DATE(B10,C10,1) -> 44927 | E10: =CHOOSE(C10,"ene","feb","mar","abr","may","jun","jul","ago","sep","oct","nov","dic") -> ene | F10: =CHOOSE(C10,"enero","febrero","marzo","abril","mayo","junio","julio","agosto","septiembre","octubre","noviembre","diciembre") -> enero | G10: =E10&"-"&RIGHT(B10,2) -> ene-23
A11: =A10+1 -> 44936 | B11: =YEAR(A11) -> 2023 | C11: =MONTH(A11) -> 1 | D11: =DATE(B11,C11,1) -> 44927 | E11: =CHOOSE(C11,"ene","feb","mar","abr","may","jun","jul","ago","sep","oct","nov","dic") -> ene | F11: =CHOOSE(C11,"enero","febrero","marzo","abril","mayo","junio","julio","agosto","septiembre","octubre","noviembre","diciembre") -> enero | G11: =E11&"-"&RIGHT(B11,2) -> ene-23
A12: =A11+1 -> 44937 | B12: =YEAR(A12) -> 2023 | C12: =MONTH(A12) -> 1 | D12: =DATE(B12,C12,1) -> 44927 | E12: =CHOOSE(C12,"ene","feb","mar","abr","may","jun","jul","ago","sep","oct","nov","dic") -> ene | F12: =CHOOSE(C12,"enero","febrero","marzo","abril","mayo","junio","julio","agosto","septiembre","octubre","noviembre","diciembre") -> enero | G12: =E12&"-"&RIGHT(B12,2) -> ene-23
A13: =A12+1 -> 44938 | B13: =YEAR(A13) -> 2023 | C13: =MONTH(A13) -> 1 | D13: =DATE(B13,C13,1) -> 44927 | E13: =CHOOSE(C13,"ene","feb","mar","abr","may","jun","jul","ago","sep","oct","nov","dic") -> ene | F13: =CHOOSE(C13,"enero","febrero","marzo","abril","mayo","junio","julio","agosto","septiembre","octubre","noviembre","diciembre") -> enero | G13: =E13&"-"&RIGHT(B13,2) -> ene-23
A14: =A13+1 -> 44939 | B14: =YEAR(A14) -> 2023 | C14: =MONTH(A14) -> 1 | D14: =DATE(B14,C14,1) -> 44927 | E14: =CHOOSE(C14,"ene","feb","mar","abr","may","jun","jul","ago","sep","oct","nov","dic") -> ene | F14: =CHOOSE(C14,"enero","febrero","marzo","abril","mayo","junio","julio","agosto","septiembre","octubre","noviembre","diciembre") -> enero | G14: =E14&"-"&RIGHT(B14,2) -> ene-23
... A1462: =A1461+1 -> 46387 | B1462: =YEAR(A1462) -> 2026 | C1462: =MONTH(A1462) -> 12 | D1462: =DATE(B1462,C1462,1) -> 46357 | E1462: =CHOOSE(C1462,"ene","feb","mar","abr","may","jun","jul","ago","sep","oct","nov","dic") -> dic | F1462: =CHOOSE(C1462,"enero","febrero","marzo","abril","mayo","junio","julio","agosto","septiembre","octubre","noviembre","diciembre") -> diciembre | G1462: =E1462&"-"&RIGHT(B1462,2) -> dic-26
